[
    {
        "title": "Ing\u00e9nieur Process Battery",
        "description_html": null,
        "description_text": "General information\nJob Title\nIng\u00e9nieur Process Battery\nRef #\n20001497\nEmployment Type\nPermanent\nDepartment\nEngineering\nPosition level\nEngineer\nDate\nWednesday, January 28, 2026\nAESC Office Location\nDouai, Hauts-de-France, France\nDescription & Requirements\nJob Description\nL'ing\u00e9nieur process Senior est en charge de mettre en \u0153uvre et d'optimiser l'implantation des \u00e9quipements, des processus majeurs en zones d\u00e9di\u00e9es. Il agit selon les orientations et l'adaptation des moyens allou\u00e9s avec validation par les r\u00e9sultats.\nRequirements / Required skills\nManufacturing Engineering\nMechanical Engineering\nQualifications\nAnalyser et formaliser les besoins techniques et op\u00e9rationnels de l\u2019entreprise en mati\u00e8re d\u2019\u00e9quipements industriels, en int\u00e9grant les contraintes de production, de qualit\u00e9, de s\u00e9curit\u00e9 et de performance.\nConcevoir et planifier l\u2019implantation des \u00e9quipements industriels en optimisant l\u2019ergonomie, les flux, la capacit\u00e9 et l\u2019int\u00e9gration dans l\u2019environnement industriel existant.\nPiloter les \u00e9changes techniques avec les fournisseurs et partenaires industriels afin de garantir la conformit\u00e9 des \u00e9quipements aux exigences normatives (qualit\u00e9, s\u00e9curit\u00e9, r\u00e9glementaire), aux performances attendues et aux d\u00e9lais contractuels.\nAssurer le pilotage global des projets d\u2019implantation d\u2019\u00e9quipements industriels, dans le respect des budgets, des plannings et des objectifs d\u00e9finis, en coordonnant les \u00e9quipes internes et les intervenants externes.\nSuperviser les phases d\u2019installation, de mise en service et de qualification des \u00e9quipements, en veillant \u00e0 la conformit\u00e9 aux sp\u00e9cifications techniques et aux standards HSE.\nOrganiser et dispenser la formation des op\u00e9rateurs et des \u00e9quipes de maintenance afin de garantir une prise en main optimale, s\u00e9curis\u00e9e et durable des nouveaux \u00e9quipements.\nTravailler en \u00e9troite collaboration avec les \u00e9quipes op\u00e9rationnelles pour identifier, analyser et d\u00e9ployer des actions d\u2019am\u00e9lioration continue visant \u00e0 optimiser la performance des \u00e9quipements, la productivit\u00e9 et l\u2019efficacit\u00e9 globale des processus industriels.\nExigences du poste:\n- Niveau ing\u00e9nieur \u00e0 dominante industrielle avec \u00a0exp\u00e9riences dans l'installation d'\u00e9quipements complexes\n- Anglais professionnel obligatoire\nLe poste est en forfait jour, avec des astreintes certain weekend et certain samedi travaill\u00e9s ( 1/3 mois environ)\nPostulez, notre \u00e9quipe prendra le soin de vous recontacter pour vous pr\u00e9senter le poste et r\u00e9pondre \u00e0 vos questions.\n#LI-EO1\nGo back\nApply\nShare this job\nEmail\nFacebook\nX\nWeChat\nWhatsApp\nLinkedIn",
        "application_url": "https://jobs.aesc-group.com/en_US/careers/Login?jobId=990&recommendation=&source=&tags=&user=&formValues=",
        "": {},
        "metadata": {
            "Job Title": "Ing\u00e9nieur Process Battery",
            "Ref #": "20001497",
            "Employment Type": "Permanent",
            "Department": "Engineering",
            "Position level": "Engineer",
            "Date": "Wednesday, January 28, 2026",
            "AESC Office Location": "Douai, Hauts-de-France, France"
        },
        "link": "https://jobs.aesc-group.com/en_US/careers/JobDetail/LAMBRES-LEZ-DOUAI-France-Ing-nieur-Process-Battery/990"
    },
    {
        "title": "Regional Finance Analyst",
        "description_html": null,
        "description_text": "General information\nJob Title\nRegional Finance Analyst\nRef #\n20001496\nEmployment Type\nPermanent\nDepartment\nFinance\nPosition level\nAnalyst\nDate\nTuesday, January 20, 2026\nAESC Office Location\nSmyrna, Tennessee USA\nDescription & Requirements\nJob Description\nAESC US, LLC\nRegional Finance Analyst (Job Code: 20001496)\nResponsible for coordinating corporate financial operations and analysis within the manufacturing department; play a critical role in driving financial performance, cost efficiency, and operational excellence within the manufacturing processes by utilizing a deep understanding of both financial principles and manufacturing operations, as well as strong analytical and leadership skills; provide monthly financial support to the management team, ensuring successful understanding and execution of financial objectives; execute informed business decisions by analyzing financial information to forecast business, industry, and economic conditions; conduct regular financial analysis to monitor manufacturing costs, expenses, and variances against budgets and forecasts; identify opportunities for cost optimization, process improvements, and efficiency enhancement; prepare financial reports, performance metrics, and presentations for management and stakeholders; collaborate with corporate finance and accounting teams to ensure accurate and timely financial reporting for manufacturing activities; employ financial models to develop optimal solutions to financial problems, and assess the financial and capital impact of transactions; collaborate with manufacturing teams to develop annual budgets and periodic forecasts; track and analyze actual performance against budgeted targets, providing insights and recommendations for corrective actions; provide variance analysis and recommendations to management; present oral and written reports on economic trends, corporations, and industries; analyze financial and operational performance to identify and recommend remedies and cost saving opportunities; monitor fundamental economic, industrial, and corporate developments by analyzing information from financial publications and services, investment banking firms, government agencies, trade publications, and company sources; utilize and apply knowledge of project management processes, ERP, SAP systems, financial planning/analysis techniques, manufacturing environment business planning procedures, dynamic financial model development, financial audits, financial system evaluations, financial performance reviews, financial forecasts, Anaplan financial applications, system implementations, IFRS and GAAP, process improvements, Cycle Review reporting, Power BI and Microsoft Query to perform duties; coordinate cost accounting processes, ensuring accurate allocation of costs to products and production lines and standardize costing globally; develop and implement cost accounting policies and procedures to maintain consistency and compliance with accounting standards; monitor inventory levels and implement strategies to optimize inventory turnover and minimize carrying costs; develop and report on a weekly, monthly, and quarterly basis projections and actuals on production, plant performance, inventory, spending on direct labor, direct burden, fixed burden and associated variances; and conduct financial analyses related to investments in green construction or green retrofitting projects.\nLocation: Smyrna, Tennessee, and multiple undetermined worksites throughout the US;\nSalary: $175,000 per year\nEducation: Bachelors \u2013 Finance, Accounting, Business Administration, or in a related field of study (will accept equivalent foreign degree);\nTraining: None;\nExperience: Seven (7) years in the position above, as a Corporate Finance Manager, as a Corporate Financial Planning and Analysis Team Leader, as a Senior Finance Analyst, as a Senior Associate, as an Analyst, as an Associate, or in a related occupation;\nOther Requirements: Experience must include all the following:\n\u2022\nOne (1) year experience with Power BI, Microsoft Query, SAP systems, and financial audits.\n\u2022\nFour (4) years experience with project management processes, ERP, financial planning/analysis techniques, manufacturing environment business planning procedures, dynamic financial model development, financial system evaluations, financial performance reviews, financial forecasts, Anaplan financial applications, system implementations, IFRS and GAAP, process improvements, and Cycle Review reporting.\nWill also accept any suitable combination of education, training and/or experience.\nAESC US, LLC\n2350 Mission College Blvd, Suite 1400\nSanta Clara, California 95054\n(Reference Code: 20001496)\nApply for position on AESC website at\nhttps://us.aesc-group.com/\nby searching above Reference code and applying.\n#LI-DNI\nQualifications\nEducation: Bachelors \u2013 Finance, Accounting, Business Administration, or in a related field of study (will accept equivalent foreign degree);\nTraining: None;\nExperience: Seven (7) years in the position above, as a Corporate Finance Manager, as a Corporate Financial Planning and Analysis Team Leader, as a Senior Finance Analyst, as a Senior Associate, as an Analyst, as an Associate, or in a related occupation;\nOther Requirements: Experience must include all the following:\nOne (1) year experience with Power BI, Microsoft Query, SAP systems, and financial audits.\nFour (4) years experience with project management processes, ERP, financial planning/analysis techniques, manufacturing environment business planning procedures, dynamic financial model development, financial system evaluations, financial performance reviews, financial forecasts, Anaplan financial applications, system implementations, IFRS and GAAP, process improvements, and Cycle Review reporting.\nWill also accept any suitable combination of education, training and/or experience.\nAESC US, LLC\n2350 Mission College Blvd, Suite 1400\nSanta Clara, California 95054\n(Reference Code: 20001496)\nApply for position on AESC website at\nhttps://us.aesc-group.com/\nby searching above Reference code and applying.\n#LI-DNI\nGo back\nApply\nShare this job\nEmail\nFacebook\nX\nWeChat\nWhatsApp\nLinkedIn",
        "application_url": "https://jobs.aesc-group.com/en_US/careers/Login?jobId=981&recommendation=&source=&tags=&user=&formValues=",
        "": {},
        "metadata": {
            "Job Title": "Regional Finance Analyst",
            "Ref #": "20001496",
            "Employment Type": "Permanent",
            "Department": "Finance",
            "Position level": "Analyst",
            "Date": "Tuesday, January 20, 2026",
            "AESC Office Location": "Smyrna, Tennessee USA"
        },
        "link": "https://jobs.aesc-group.com/en_US/careers/JobDetail/Smyrna-Tennessee-Tennessee-United-States-Regional-Finance-Analyst/981"
    },
    {
        "title": "HR - R\u00e9f\u00e9rent Int\u00e9rim Usine",
        "description_html": null,
        "description_text": "General information\nJob Title\nHR - R\u00e9f\u00e9rent Int\u00e9rim Usine\nRef #\n20001495\nEmployment Type\nTemporary\nDepartment\nHuman Resources\nPosition level\nAnalyst\nDate\nTuesday, January 13, 2026\nAESC Office Location\nDouai, Hauts-de-France, France\nDescription & Requirements\nJob Description\nPiloter l\u2019ensemble du processus de gestion du personnel int\u00e9rimaire au sein d\u2019une gigafactory ou d\u2019une usine de batteries automobiles, en garantissant la conformit\u00e9 r\u00e9glementaire, la disponibilit\u00e9 des ressources, la s\u00e9curit\u00e9 des personnes et la qualit\u00e9 des partenariats avec les agences d\u2019int\u00e9rim.\n\ud83d\udee0\ufe0f\nResponsabilit\u00e9s et activit\u00e9s cl\u00e9s\n1. Gestion op\u00e9rationnelle de l\u2019int\u00e9rim\nRecueillir les besoins en renforts aupr\u00e8s des diff\u00e9rents managers\nAnticiper les variations de charge li\u00e9es aux ramp-up, aux arr\u00eats techniques ou aux pics de production.\nR\u00e9diger les demandes de personnel et coordonner les propositions avec les agences partenaires.\nOrganiser les entretiens ou tests pratiques si requis (manipulation chimique, pr\u00e9cision gestuelle, travail en salle s\u00e8che\u2026).\nSuivre les affectations, renouvellements, fins de mission et remplacements.\n2. Administration du personnel int\u00e9rimaire\nV\u00e9rifier les contrats, habilitations et documents obligatoires (CACES, habilitations \u00e9lectriques, ATEX, EPI sp\u00e9cifiques\u2026).\nG\u00e9rer les acc\u00e8s aux zones sensibles (salle s\u00e8che, zones chimiques, zones automatis\u00e9es).\nSuivre les heures, absences, accidents, incidents qualit\u00e9 ou s\u00e9curit\u00e9.\nContr\u00f4ler les factures et r\u00e9soudre les \u00e9carts avec les agences.\n3. Int\u00e9gration et s\u00e9curit\u00e9\nOrganiser les parcours d\u2019int\u00e9gration sp\u00e9cifiques au secteur batterie :\nformation s\u00e9curit\u00e9 renforc\u00e9e,\nrisques chimiques (solvants, poudres actives),\nproc\u00e9dures en salle s\u00e8che,\nmanipulation de cellules lithium-ion.\nS\u2019assurer que chaque int\u00e9rimaire dispose des EPI adapt\u00e9s (gants sp\u00e9cifiques, lunettes, tenues salle s\u00e8che\u2026).\nSuivre l\u2019adaptation au poste et remonter les difficult\u00e9s aux managers.\n4. Relation avec les agences d\u2019int\u00e9rim\n\u00catre l\u2019interlocuteur privil\u00e9gi\u00e9 pour les besoins du site.\nSuivre les KPI : taux de couverture, turnover, qualit\u00e9 des profils, taux de pr\u00e9sence, conformit\u00e9 s\u00e9curit\u00e9.\nParticiper aux comit\u00e9s de pilotage et proposer des actions d\u2019am\u00e9lioration.\nGarantir le respect des engagements contractuels et des r\u00e8gles l\u00e9gales.\n5. Reporting et am\u00e9lioration continue\nProduire les tableaux de bord hebdomadaires et mensuels (effectifs, co\u00fbts, heures, taux de renouvellement).\nAnalyser les tendances (absent\u00e9isme, accidents, qualit\u00e9 des recrutements).\nParticiper aux projets RH du site : digitalisation, standardisation des processus, am\u00e9lioration de l\u2019accueil s\u00e9curit\u00e9, optimisation des flux int\u00e9rim.\n?\nComp\u00e9tences requises\nComp\u00e9tences techniques\nConnaissance du droit du travail et du travail temporaire.\nMa\u00eetrise des outils RH et des syst\u00e8mes de badgeage/planification.\nCompr\u00e9hension des environnements industriels automatis\u00e9s et des contraintes sp\u00e9cifiques aux gigafactories (salle s\u00e8che, chimie, haute cadence).\nSensibilit\u00e9 forte aux enjeux s\u00e9curit\u00e9 et qualit\u00e9.\nComp\u00e9tences comportementales\nRigueur, organisation, gestion des priorit\u00e9s.\nAisance relationnelle avec les \u00e9quipes terrain et les partenaires externes.\nR\u00e9activit\u00e9, autonomie, sens du service.\nCapacit\u00e9 \u00e0 travailler dans un environnement en forte croissance et en \u00e9volution rapide.\nQualifications\nBac+2/Bac+3 en RH, gestion ou \u00e9quivalent.\nExp\u00e9rience en gestion de l\u2019int\u00e9rim en milieu industriel, id\u00e9alement dans l\u2019automobile, la chimie, l\u2019\u00e9lectronique ou une gigafactory.\nConnaissance des enjeux s\u00e9curit\u00e9 li\u00e9s aux batteries lithium-ion appr\u00e9ci\u00e9e.\nGo back\nApply\nShare this job\nEmail\nFacebook\nX\nWeChat\nWhatsApp\nLinkedIn",
        "application_url": "https://jobs.aesc-group.com/en_US/careers/Login?jobId=979&recommendation=&source=&tags=&user=&formValues=",
        "": {},
        "metadata": {
            "Job Title": "HR - R\u00e9f\u00e9rent Int\u00e9rim Usine",
            "Ref #": "20001495",
            "Employment Type": "Temporary",
            "Department": "Human Resources",
            "Position level": "Analyst",
            "Date": "Tuesday, January 13, 2026",
            "AESC Office Location": "Douai, Hauts-de-France, France"
        },
        "link": "https://jobs.aesc-group.com/en_US/careers/JobDetail/LAMBRES-LEZ-DOUAI-France-HR-R-f-rent-Int-rim-Usine/979"
    },
    {
        "title": "Project Management Coordinator",
        "description_html": null,
        "description_text": "General information\nJob Title\nProject Management Coordinator\nRef #\nP1008594\nEmployment Type\nPermanent\nDepartment\nSales\nPosition level\nCoordinator\nDate\nTuesday, January 6, 2026\nAESC Office Location\nRemote worker USA\nDescription & Requirements\nJob Description\nAESC is looking to add a Project Management Coordinator to our team.\nFull-Time\nRemote\nAbout AESC US LLC\nAESC is an exciting, newly created global organization committed to solving the challenges of a sustainable future and becoming the leading supplier of full-value-chain battery solutions. Our lithium-ion batteries can be found in nearly one million electric vehicles worldwide and have a stellar safety record of zero-critical issues. AESC US is leading the way in battery technology. We design and manufacture EV battery technology for various electric vehicles and equipment. We are working hard towards unlocking the full potential of sustainable energy and climate change mitigation. We will continue to build upon our successes and expand into new markets and industries, producing innovative and competitive products and technologies that advance the goal of a zero-carbon emission future. AESC is headquartered in Japan and has battery manufacturing locations in Japan, UK, China, and the U.S.\nAESC Mission\nOur mission is to solve the challenges for a sustainable future. Together, we can make a meaningful impact.\nAbout the Role\nWe are seeking a detail-oriented and highly organized Project Management Coordinator to support the execution of utility-scale energy storage and infrastructure projects. This role will focus on project administration, scheduling, documentation, and internal cross-team coordination to ensure smooth delivery of complex projects. The Project Management Coordinator will work closely with sales managers, engineering teams, and external stakeholders to maintain project momentum from initiation through completion.\nWhat You Will Do\nServe as the central point of contact for project documentation, scheduling, and reporting.\nSupport sales managers and project managers in tracking milestones, deliverables, and dependencies.\nCoordinate internal resources and external partners to ensure timely execution of project tasks.\nMaintain accurate project records, including meeting minutes, action items, and progress reports.\nAssist with preparation of project proposals, RFP/RFQ responses, and client-facing documentation.\nMonitor project timelines and budgets, escalating risks or delays to senior management.\nFacilitate communication between cross-functional teams (engineering, procurement, sales, and services).\nSupport compliance with organizational standards, safety requirements, and quality assurance processes.\nQualifications\nWhat You Need\nBachelor\u2019s degree in Business, Engineering, Project Management, or related field (or equivalent experience).\n2\u20134 years of project coordination, project support, or operations experience; exposure to utility-scale energy, infrastructure, or construction projects preferred.\nFamiliarity with project management methodologies (Agile, Waterfall, Hybrid).\nStrong organizational skills with the ability to manage multiple projects simultaneously.\nProficiency with project management tools (MS Project, Smartsheet, Asana, Jira) and Microsoft Office.\nExcellent communication skills with the ability to convey technical and commercial information clearly.\nSelf-driven, detail-oriented, and comfortable working in a fast-paced environment.\nWhat is \u201cNice to Have\u201d?\nKnowledge of energy storage systems, renewable energy, or large-scale infrastructure projects.\nUnderstanding of permitting, interconnection, and regulatory processes.\nExperience supporting EPCs, utilities, IPPs, or project developers.\nFamiliarity with CRM platforms and project tracking systems.\nWhat We Offer\nWelcome to AESC, supporting our state-of-the-art Gigafactories, where you'll have the opportunity to tackle the world's most fascinating challenges alongside exceptionally talented individuals who are driven to make a difference. At AESC, we offer a comprehensive compensation package. In addition, we provide a range of valuable benefits, such as 401K,\nand health insurance. We strive to ensure that our employees are well taken care of, enabling them to focus on their work and contribute to our collective mission of changing the world.\nAn inclusive and diverse work environment that fosters and encourages professional and personal development.\nHighly automated, clean, safe, and temperature-controlled production environment\nMedical, Dental and Vision Insurance\nHSA and Flexible Spending Accounts\n401K with company match\nLife Insurance (Company paid and additional voluntary life available)\nPaid Vacation and 14 Paid Holidays\nShort term and long-term disability coverage (Company Paid)\nTuition reimbursement\nCompetitive base salary with performance-based incentives.\nOpportunity to contribute to large-scale energy transition projects impacting grid reliability and decarbonization.\nHands-on exposure to complex, high-value infrastructure projects.\nComprehensive training in project management methodologies and energy storage technologies.\nCareer growth opportunities within project management, operations, or commercial functions.\nComprehensive benefits package including [health insurance, retirement plan, PTO, etc.].\nApplication Process\nEven if you don't meet every requirement listed, if you believe this role suits you well, we encourage you to apply. Your application gives us the opportunity to learn more about you and explore potential fits within our team.\nFollowing the submission of your application, we are committed to providing timely responses to all applicants, though response times may vary depending on the volume of submissions. If you do not receive an immediate response, please rest assured that this in no way reflects on the quality of your candidacy. Your application will be retained in our files, and we may reach out to you for future roles that align with your skills and interests. As our organization experiences rapid growth, we appreciate your patience in this process. We are actively working each day to enhance our application procedures to ensure a smoother and more efficient experience for all applicants. Thank you for your understanding and enthusiasm for joining our dynamic team.\nEqual Employment Opportunity\nAt AESC, we are committed to providing Equal Employment Opportunity (EEO) to all individuals. We participate in E-Verify and will provide the federal government with your Form I-9 information to confirm that you are authorized to work in the U.S Join us in our passion to design, manufacture, and sell high-performance products, contributing to a sustainable and zero-carbon emission future.\nPhysical Requirements\nThe physical demands described here are representative of those that must be met by an employee to successfully perform the essential functions of this job. Reasonable accommodation may be made to enable otherwise qualified individuals with disabilities to perform the essential job functions.\nAbility to sit for extended periods of time.\nAbility to read, write, speak, hear; stand; walk; use hands to finger, handle, or feel; reach and lift with hands and arms frequently throughout the day.\nRequired to occasionally lift, push, pull and/or move up to 10 pounds and occasionally required to lift, push, pull and/or move up to 35 pounds.\nWork Environment\nThe work environment is primarily an automated manufacturing plant with a concrete floor and is characterized by some temperature extremes, moderate noise, and forklift traffic. The individual must be able to perform all essential functions as appropriate on the plant floor, in meetings, and with employees, management, customers and suppliers.\nCandidate must perform the essential duties and responsibilities with or without reasonable accommodation efficiently and accurately, and without causing significant safety threat to self or others. The statements made herein are intended to describe the general nature and level of work being performed by employees assigned to this job classification. They are not intended to be construed as an exhaustive and inclusive list of all responsibilities, duties, and/or skills required of personnel so classified.\nGo back\nApply\nShare this job\nEmail\nFacebook\nX\nWeChat\nWhatsApp\nLinkedIn",
        "application_url": "https://jobs.aesc-group.com/en_US/careers/Login?jobId=977&recommendation=&source=&tags=&user=&formValues=",
        "": {},
        "metadata": {
            "Job Title": "Project Management Coordinator",
            "Ref #": "P1008594",
            "Employment Type": "Permanent",
            "Department": "Sales",
            "Position level": "Coordinator",
            "Date": "Tuesday, January 6, 2026",
            "AESC Office Location": "Remote worker USA"
        },
        "link": "https://jobs.aesc-group.com/en_US/careers/JobDetail/Santa-Clara-California-United-States-Project-Management-Coordinator/977"
    },
    {
        "title": "Senior Project Manager",
        "description_html": null,
        "description_text": "General information\nJob Title\nSenior Project Manager\nRef #\nP1008597\nEmployment Type\nPermanent\nDepartment\nSales\nPosition level\nManager\nDate\nTuesday, January 6, 2026\nAESC Office Location\nRemote worker USA\nDescription & Requirements\nJob Description\nAESC is looking to add a Senior Project Manager to our team.\nFull-Time\nRemote/Hybrid/On-site\nAbout AESC US LLC\nAESC is an exciting, newly created global organization committed to solving the challenges of a sustainable future and becoming the leading supplier of full-value-chain battery solutions. Our lithium-ion batteries can be found in nearly one million electric vehicles worldwide and have a stellar safety record of zero-critical issues. AESC US is leading the way in battery technology. We design and manufacture EV battery technology for various electric vehicles and equipment. We are working hard towards unlocking the full potential of sustainable energy and climate change mitigation. We will continue to build upon our successes and expand into new markets and industries, producing innovative and competitive products and technologies that advance the goal of a zero-carbon emission future. AESC is headquartered in Japan and has battery manufacturing locations in Japan, UK, China, and the U.S.\nAESC Mission\nOur mission is to solve the challenges for a sustainable future. Together, we can make a meaningful impact.\nAbout the Role\nWe are seeking an experienced and strategic Senior Project Manager to lead the execution of complex, utility-scale energy storage and infrastructure projects. This role will oversee project planning, delivery, and stakeholder management, ensuring projects are completed on time, within scope, and within budget. The Senior Project Manager will act as a trusted advisor to leadership, mentor junior staff, and drive continuous improvement across the project management function.\nWhat You Will Do\nLead end-to-end project management for large-scale energy storage and infrastructure initiatives.\nDefine project scope, objectives, and success metrics in alignment with organizational strategy.\nDevelop and manage detailed project plans, schedules, budgets, and resource allocations.\nIdentify risks, issues, and dependencies; implement mitigation strategies proactively.\nServe as the primary point of contact for clients, partners, and internal stakeholders.\nFacilitate communication and decision-making across cross-functional teams (engineering, procurement, sales, and services).\nEnsure compliance with organizational standards, safety requirements, and quality assurance processes.\nMentor and supervise project coordinators and junior project managers, fostering professional growth.\nDrive adoption of project management best practices and continuous improvement initiatives.\nQualifications\nWhat You Need\nBachelor\u2019s degree in Business, Engineering, Project Management, or related field (Master\u2019s preferred).\n7+ years of project management experience, with at least 3 years in a senior or lead role.\nProven track record of managing large-scale, complex projects in energy, infrastructure, or construction.\nStrong knowledge of project management methodologies (Agile, Waterfall, Hybrid).\nPMP, PRINCE2, or Agile certification strongly preferred.\nProficiency with project management tools (MS Project, Smartsheet, Asana, Jira) and Microsoft Office.\nExceptional communication, negotiation, and leadership skills.\nWhat is \u201cNice to Have\u201d?\nKnowledge of utility-scale energy storage systems, renewable energy, or large infrastructure projects.\nUnderstanding of permitting, interconnection, and regulatory processes.\nExperience working with EPCs, utilities, IPPs, or project developers.\nStrong financial acumen and budget management skills.\nWhat We Offer\nWelcome to AESC, supporting our state-of-the-art Gigafactories, where you'll have the opportunity to tackle the world's most fascinating challenges alongside exceptionally talented individuals who are driven to make a difference. At AESC, we offer a comprehensive compensation package. In addition, we provide a range of valuable benefits, such as 401K,\nand health insurance. We strive to ensure that our employees are well taken care of, enabling them to focus on their work and contribute to our collective mission of changing the world.\nAn inclusive and diverse work environment that fosters and encourages professional and personal development.\nHighly automated, clean, safe, and temperature-controlled production environment\nMedical, Dental and Vision Insurance\nHSA and Flexible Spending Accounts\n401K with company match\nLife Insurance (Company paid and additional voluntary life available)\nPaid Vacation and 14 Paid Holidays\nShort term and long-term disability coverage (Company Paid)\nTuition reimbursement\nCompetitive base salary with performance-based incentives.\nOpportunity to lead high-impact energy transition projects that enhance grid reliability and decarbonization.\nHands-on exposure to complex, high-value infrastructure initiatives.\nComprehensive training in advanced project management methodologies and energy storage technologies.\nCareer growth opportunities into leadership roles within project management or services.\nComprehensive benefits package including [health insurance, retirement plan, PTO, etc.].\nApplication Process\nEven if you don't meet every requirement listed, if you believe this role suits you well, we encourage you to apply. Your application gives us the opportunity to learn more about you and explore potential fits within our team.\nFollowing the submission of your application, we are committed to providing timely responses to all applicants, though response times may vary depending on the volume of submissions. If you do not receive an immediate response, please rest assured that this in no way reflects on the quality of your candidacy. Your application will be retained in our files, and we may reach out to you for future roles that align with your skills and interests. As our organization experiences rapid growth, we appreciate your patience in this process. We are actively working each day to enhance our application procedures to ensure a smoother and more efficient experience for all applicants. Thank you for your understanding and enthusiasm for joining our dynamic team.\nEqual Employment Opportunity\nAt AESC, we are committed to providing Equal Employment Opportunity (EEO) to all individuals. We participate in E-Verify and will provide the federal government with your Form I-9 information to confirm that you are authorized to work in the U.S Join us in our passion to design, manufacture, and sell high-performance products, contributing to a sustainable and zero-carbon emission future.\nPhysical Requirements\nThe physical demands described here are representative of those that must be met by an employee to successfully perform the essential functions of this job. Reasonable accommodation may be made to enable otherwise qualified individuals with disabilities to perform the essential job functions.\nAbility to sit for extended periods of time.\nAbility to read, write, speak, hear; stand; walk; use hands to finger, handle, or feel; reach and lift with hands and arms frequently throughout the day.\nRequired to occasionally lift, push, pull and/or move up to 10 pounds and occasionally required to lift, push, pull and/or move up to 35 pounds.\nWork Environment\nThe work environment is primarily an automated manufacturing plant with a concrete floor and is characterized by some temperature extremes, moderate noise, and forklift traffic. The individual must be able to perform all essential functions as appropriate on the plant floor, in meetings, and with employees, management, customers and suppliers.\nCandidate must perform the essential duties and responsibilities with or without reasonable accommodation efficiently and accurately, and without causing significant safety threat to self or others. The statements made herein are intended to describe the general nature and level of work being performed by employees assigned to this job classification. They are not intended to be construed as an exhaustive and inclusive list of all responsibilities, duties, and/or skills required of personnel so classified.\nGo back\nApply\nShare this job\nEmail\nFacebook\nX\nWeChat\nWhatsApp\nLinkedIn",
        "application_url": "https://jobs.aesc-group.com/en_US/careers/Login?jobId=978&recommendation=&source=&tags=&user=&formValues=",
        "": {},
        "metadata": {
            "Job Title": "Senior Project Manager",
            "Ref #": "P1008597",
            "Employment Type": "Permanent",
            "Department": "Sales",
            "Position level": "Manager",
            "Date": "Tuesday, January 6, 2026",
            "AESC Office Location": "Remote worker USA"
        },
        "link": "https://jobs.aesc-group.com/en_US/careers/JobDetail/Santa-Clara-California-United-States-Senior-Project-Manager/978"
    },
    {
        "title": "Manufacturing Technician",
        "description_html": null,
        "description_text": "General information\nJob Title\nManufacturing Technician\nRef #\n158\nEmployment Type\nPermanent\nDepartment\nManufacturing\nPosition level\nTechnician\nDate\nMonday, January 5, 2026\nAESC Office Location\nSmyrna, Tennessee USA\nDescription & Requirements\nJob Description\nAbout AESC US LLC\nAESC is an exciting, newly created global organization committed to solving the challenges of a sustainable future and becoming the leading supplier of full-value-chain battery solutions. Our lithium-ion batteries can be found in nearly one million electric vehicles worldwide and have a stellar safety record of zero-critical issues. AESC US is leading the way in battery technology. We design and manufacture EV battery technology for various electric vehicles and equipment. We are working hard towards unlocking the full potential of sustainable energy and climate change mitigation. We will continue to build upon our successes and expand into new markets and industries, producing innovative and competitive products and technologies that advance the goal of a zero-carbon emission future. AESC is headquartered in Japan and has battery manufacturing locations in Japan, UK, China, and the U.S.\nAESC Mission\nOur mission is to solve the challenges for a sustainable future. Together, we can make a meaningful impact.\nAbout the Role\nJoin our dynamic team in Smyrna, TN, and contribute to the production of cutting-edge electric vehicle batteries at our state-of-the-art factory. Collaborate with cross-functional teams, uphold our commitment to sustainability, and be part of the journey towards a zero-carbon emission future.\nKey Responsibilities:\nContribute to the production of lithium-ion batteries for electric vehicles.\nCollaborate with cross-functional teams to ensure efficient and high-quality production processes.\nUphold our commitment to environmental sustainability and innovation.\nEmbrace a culture of continuous improvement and adaptability.\nWhat You'll Bring:\nHigh school diploma or GED required\nPrevious experience in manufacturing or related fields preferred.\nStrong work ethic and commitment to excellence.\nAbility to thrive in a dynamic and collaborative team environment.\nPassion for innovation and making a positive impact on the automotive industry.\nWhat You'll Gain at AESC:\nHighly automated, clean, safe, and temperature-controlled production environment.\nBe part of an organization committed to solving challenges for a sustainable future.\nEnjoy competitive compensation and benefits supporting your physical, mental, and financial well-being.\nCareer growth opportunities.\nQualifications\nWhat You'll Bring:\nHigh school diploma or GED required\nPrevious experience in manufacturing or related fields preferred.\nStrong work ethic and commitment to excellence.\nAbility to thrive in a dynamic and collaborative team environment.\nPassion for innovation and making a positive impact on the automotive industry.\nGo back\nApply\nShare this job\nEmail\nFacebook\nX\nWeChat\nWhatsApp\nLinkedIn",
        "application_url": "https://jobs.aesc-group.com/en_US/careers/Login?jobId=164&recommendation=&source=&tags=&user=&formValues=",
        "": {},
        "metadata": {
            "Job Title": "Manufacturing Technician",
            "Ref #": "158",
            "Employment Type": "Permanent",
            "Department": "Manufacturing",
            "Position level": "Technician",
            "Date": "Monday, January 5, 2026",
            "AESC Office Location": "Smyrna, Tennessee USA"
        },
        "link": "https://jobs.aesc-group.com/en_US/careers/JobDetail/Smyrna-Tennessee-United-States-Manufacturing-Technician/164"
    },
    {
        "title": "Infirmier(\u00e8re)",
        "description_html": null,
        "description_text": "General information\nJob Title\nInfirmier(\u00e8re)\nRef #\n20001494\nEmployment Type\nPermanent\nDepartment\nEnvironmental Health and Safety\nPosition level\nTechnician\nDate\nMonday, December 22, 2025\nAESC Office Location\nDouai, Hauts-de-France, France\nDescription & Requirements\nJob Description\n\ud83c\udf0d\u267b\ufe0f\nPr\u00eat(e) \u00e0 contribuer \u00e0 la sant\u00e9 et au bien-\u00eatre des salari\u00e9s dans un environnement industriel exigeant ?\n\u267b\ufe0f\ud83c\udf0d\nRejoignez AESC\net participez activement \u00e0 la pr\u00e9vention des risques professionnels et \u00e0 la promotion de la sant\u00e9 au travail !\nInfirmier(\u00e8re) (H/F)\n\ud83c\udfaf Vos missions principales\nAu sein de l\u2019\u00e9quipe HSE et rattach\u00e9(e) au Manager HSE, vous jouez un r\u00f4le cl\u00e9 dans la surveillance de la sant\u00e9 des salari\u00e9s et la pr\u00e9vention des risques professionnels.\nR\u00e9aliser des consultations infirmi\u00e8res en sant\u00e9 au travail (suivi, conseils, visites)\nParticiper \u00e0 l\u2019\u00e9valuation des risques professionnels avec l\u2019\u00e9quipe pluridisciplinaire (m\u00e9decin du travail, ergonomes, etc.)\nConseiller les salari\u00e9s et l\u2019employeur sur les bonnes pratiques en mati\u00e8re de sant\u00e9, d\u2019hygi\u00e8ne et de s\u00e9curit\u00e9\nMettre en \u0153uvre des actions de pr\u00e9vention, d\u2019\u00e9ducation \u00e0 la sant\u00e9 et de d\u00e9pistage\nAssurer le suivi des dossiers m\u00e9dicaux et des vaccinations\nCollaborer avec les acteurs internes et externes (CSSCT, m\u00e9decine du travail, CARSAT, inspection du travail\u2026)\nParticiper \u00e0 la veille r\u00e9glementaire et au respect des normes en sant\u00e9 au travail\nR\u00e9diger les rapports et bilans d\u2019activit\u00e9\n\ud83d\udcbc Savoir-faire requis\nBonne connaissance de la r\u00e9glementation en sant\u00e9 et s\u00e9curit\u00e9 au travail\nMa\u00eetrise des outils informatiques (bureautique, logiciels de gestion m\u00e9dicale)\nExp\u00e9rience en milieu industriel appr\u00e9ci\u00e9e\n? Savoir-\u00eatre requis\nExcellent sens du relationnel et de l\u2019\u00e9coute\nAutonomie, rigueur et esprit d\u2019\u00e9quipe\nDiscr\u00e9tion absolue et respect de la confidentialit\u00e9\n\u2705 Exigences du poste\nDipl\u00f4me d\u2019\u00c9tat d\u2019Infirmier(\u00e8re)\nobligatoire\nFormation compl\u00e9mentaire en sant\u00e9 au travail\nobligatoire\n#LI-EO1\nQualifications\n\ud83c\udf0d\u267b\ufe0f\nPr\u00eat(e) \u00e0 contribuer \u00e0 la sant\u00e9 et au bien-\u00eatre des salari\u00e9s dans un environnement industriel exigeant ?\n\u267b\ufe0f\ud83c\udf0d\nRejoignez AESC\net participez activement \u00e0 la pr\u00e9vention des risques professionnels et \u00e0 la promotion de la sant\u00e9 au travail !\nInfirmier(\u00e8re) (H/F)\n\ud83c\udfaf Vos missions principales\nAu sein de l\u2019\u00e9quipe HSE et rattach\u00e9(e) au Manager HSE, vous jouez un r\u00f4le cl\u00e9 dans la surveillance de la sant\u00e9 des salari\u00e9s et la pr\u00e9vention des risques professionnels.\nR\u00e9aliser des consultations infirmi\u00e8res en sant\u00e9 au travail (suivi, conseils, visites)\nParticiper \u00e0 l\u2019\u00e9valuation des risques professionnels avec l\u2019\u00e9quipe pluridisciplinaire (m\u00e9decin du travail, ergonomes, etc.)\nConseiller les salari\u00e9s et l\u2019employeur sur les bonnes pratiques en mati\u00e8re de sant\u00e9, d\u2019hygi\u00e8ne et de s\u00e9curit\u00e9\nMettre en \u0153uvre des actions de pr\u00e9vention, d\u2019\u00e9ducation \u00e0 la sant\u00e9 et de d\u00e9pistage\nAssurer le suivi des dossiers m\u00e9dicaux et des vaccinations\nCollaborer avec les acteurs internes et externes (CSSCT, m\u00e9decine du travail, CARSAT, inspection du travail\u2026)\nParticiper \u00e0 la veille r\u00e9glementaire et au respect des normes en sant\u00e9 au travail\nR\u00e9diger les rapports et bilans d\u2019activit\u00e9\n\ud83d\udcbc Savoir-faire requis\nBonne connaissance de la r\u00e9glementation en sant\u00e9 et s\u00e9curit\u00e9 au travail\nMa\u00eetrise des outils informatiques (bureautique, logiciels de gestion m\u00e9dicale)\nExp\u00e9rience en milieu industriel appr\u00e9ci\u00e9e\n? Savoir-\u00eatre requis\nExcellent sens du relationnel et de l\u2019\u00e9coute\nAutonomie, rigueur et esprit d\u2019\u00e9quipe\nDiscr\u00e9tion absolue et respect de la confidentialit\u00e9\n\u2705 Exigences du poste\nDipl\u00f4me d\u2019\u00c9tat d\u2019Infirmier(\u00e8re)\nobligatoire\nFormation compl\u00e9mentaire en sant\u00e9 au travail\nobligatoire\n#LI-EO1\nGo back\nApply\nShare this job\nEmail\nFacebook\nX\nWeChat\nWhatsApp\nLinkedIn",
        "application_url": "https://jobs.aesc-group.com/en_US/careers/Login?jobId=972&recommendation=&source=&tags=&user=&formValues=",
        "": {},
        "metadata": {
            "Job Title": "Infirmier(\u00e8re)",
            "Ref #": "20001494",
            "Employment Type": "Permanent",
            "Department": "Environmental Health and Safety",
            "Position level": "Technician",
            "Date": "Monday, December 22, 2025",
            "AESC Office Location": "Douai, Hauts-de-France, France"
        },
        "link": "https://jobs.aesc-group.com/en_US/careers/JobDetail/LAMBRES-LEZ-DOUAI-Nord-France-Infirmier-re/972"
    },
    {
        "title": "Service Operations Manager",
        "description_html": null,
        "description_text": "General information\nJob Title\nService Operations Manager\nRef #\nP1008523\nEmployment Type\nPermanent\nDepartment\nSales\nPosition level\nManager\nDate\nMonday, December 22, 2025\nAESC Office Location\nSanta Clara, California USA\nDescription & Requirements\nJob Description\nAESC is looking to add a Service Operations Manager to our team remotely.\nFull-Time\nRemote\nAbout AESC US LLC\nAESC is an exciting, newly created global organization committed to solving the challenges of a sustainable future and becoming the leading supplier of full-value-chain battery solutions. Our lithium-ion batteries can be found in nearly one million electric vehicles worldwide and have a stellar safety record of zero-critical issues. AESC US is leading the way in battery technology. We design and manufacture EV battery technology for various electric vehicles and equipment. We are working hard towards unlocking the full potential of sustainable energy and climate change mitigation. We will continue to build upon our successes and expand into new markets and industries, producing innovative and competitive products and technologies that advance the goal of a zero-carbon emission future. AESC is headquartered in Japan and has battery manufacturing locations in Japan, UK, China, and the U.S.\nAESC Mission\nOur mission is to solve the challenges for a sustainable future. Together, we can make a meaningful impact.\nAbout the Role\nWe are seeking an experienced Service Operations Manager to oversee all aspects of service operations for utility-scale energy storage systems. This role is responsible for managing spare parts inventory, warranty requirements, long-term service agreement (LTSA) obligations, and warehouse operations. The Service Operations Manager will ensure efficient processes, compliance with contractual commitments, and timely delivery of parts and services to support customer satisfaction and operational excellence.\nWhat You Will Do\nManage spare parts inventory, procurement, and distribution to support service and maintenance activities.\nOversee warranty administration, including claim processing, documentation, and compliance with manufacturer and customer requirements.\nEnsure fulfillment of LTSA obligations, including scheduled maintenance, parts availability, and performance guarantees.\nCoordinate warehouse operations with our internal logistics team, including receiving, storage, and shipping of parts and equipment.\nDevelop and maintain accurate records for inventory, warranty claims, and LTSA performance metrics.\nCollaborate with service teams, engineering, and procurement to forecast parts demand and optimize inventory levels.\nImplement process improvements to enhance efficiency, reduce costs, and improve service delivery.\nEnsure compliance with safety standards, quality requirements, and regulatory guidelines in all operations.\nPrepare regular reports on inventory status, warranty performance, and LTSA compliance for senior management.\nQualifications\nWhat You Need\nBachelor\u2019s degree in Supply Chain Management, Business Administration, Engineering, or related field (or equivalent experience).\n5+ years of experience in service operations, inventory management, or supply chain roles; experience in energy or industrial sectors preferred.\nStrong understanding of warranty processes, contractual obligations, and service agreements.\nProficiency with inventory management systems, ERP platforms, and Microsoft Office applications.\nExcellent organizational and analytical skills with attention to detail.\nStrong communication and collaboration skills for working with cross-functional teams and external partners.\nWhat is \u201cNice to Have\u201d?\nExperience managing LTSA programs and spare parts logistics for complex systems.\nKnowledge of energy storage systems, renewable energy technologies, or large-scale industrial equipment.\nFamiliarity with warehouse safety standards and best practices.\nUnderstanding of cost optimization strategies in service operations.\nWhat We Offer\nWelcome to AESC, supporting our state-of-the-art Gigafactories, where you'll have the opportunity to tackle the world's most fascinating challenges alongside exceptionally talented individuals who are driven to make a difference. At AESC, we offer a comprehensive compensation package. In addition, we provide a range of valuable benefits, such as 401K,\nand health insurance. We strive to ensure that our employees are well taken care of, enabling them to focus on their work and contribute to our collective mission of changing the world.\nAn inclusive and diverse work environment that fosters and encourages professional and personal development.\nHighly automated, clean, safe, and temperature-controlled production environment\nMedical, Dental and Vision Insurance\nHSA and Flexible Spending Accounts\n401K with company match\nLife Insurance (Company paid and additional voluntary life available)\nPaid Vacation and 14 Paid Holidays\nShort term and long-term disability coverage (Company Paid)\nTuition reimbursement\nCompetitive base salary with performance-based incentives. Salary range: $105,000-$132,000/annual.\nOpportunity to lead service operations for cutting-edge energy storage projects.\nComprehensive training and career development opportunities.\nFull benefits package including [health insurance, retirement plan, PTO, etc.].\nApplication Process\nEven if you don't meet every requirement listed, if you believe this role suits you well, we encourage you to apply. Your application gives us the opportunity to learn more about you and explore potential fits within our team.\nFollowing the submission of your application, we are committed to providing timely responses to all applicants, though response times may vary depending on the volume of submissions. If you do not receive an immediate response, please rest assured that this in no way reflects on the quality of your candidacy. Your application will be retained in our files, and we may reach out to you for future roles that align with your skills and interests. As our organization experiences rapid growth, we appreciate your patience in this process. We are actively working each day to enhance our application procedures to ensure a smoother and more efficient experience for all applicants. Thank you for your understanding and enthusiasm for joining our dynamic team.\nEqual Employment Opportunity\nAt AESC, we are committed to providing Equal Employment Opportunity (EEO) to all individuals. We participate in E-Verify and will provide the federal government with your Form I-9 information to confirm that you are authorized to work in the U.S Join us in our passion to design, manufacture, and sell high-performance products, contributing to a sustainable and zero-carbon emission future.\nPhysical Requirements\nThe physical demands described here are representative of those that must be met by an employee to successfully perform the essential functions of this job. Reasonable accommodation may be made to enable otherwise qualified individuals with disabilities to perform the essential job functions.\nAbility to sit for extended periods of time.\nAbility to read, write, speak, hear; stand; walk; use hands to finger, handle, or feel; reach and lift with hands and arms frequently throughout the day.\nRequired to occasionally lift, push, pull and/or move up to 10 pounds and occasionally required to lift, push, pull and/or move up to 35 pounds.\nAbility to work in warehouse environments and occasionally lift light to moderate objects.\nComfortable conducting inventory checks and inspections in varying conditions.\nStrict adherence to OSHA requirements and company safety protocols.\nUse of appropriate PPE when in warehouse or operational areas.\nWork Environment\nThe work environment is primarily an automated manufacturing plant with a concrete floor and is characterized by some temperature extremes, moderate noise, and forklift traffic. The individual must be able to perform all essential functions as appropriate on the plant floor, in meetings, and with employees, management, customers and suppliers.\nCandidate must perform the essential duties and responsibilities with or without reasonable accommodation efficiently and accurately, and without causing significant safety threat to self or others. The statements made herein are intended to describe the general nature and level of work being performed by employees assigned to this job classification. They are not intended to be construed as an exhaustive and inclusive list of all responsibilities, duties, and/or skills required of personnel so classified.\nGo back\nApply\nShare this job\nEmail\nFacebook\nX\nWeChat\nWhatsApp\nLinkedIn",
        "application_url": "https://jobs.aesc-group.com/en_US/careers/Login?jobId=973&recommendation=&source=&tags=&user=&formValues=",
        "": {},
        "metadata": {
            "Job Title": "Service Operations Manager",
            "Ref #": "P1008523",
            "Employment Type": "Permanent",
            "Department": "Sales",
            "Position level": "Manager",
            "Date": "Monday, December 22, 2025",
            "AESC Office Location": "Santa Clara, California USA"
        },
        "link": "https://jobs.aesc-group.com/en_US/careers/JobDetail/Santa-Clara-California-United-States-Service-Operations-Manager/973"
    },
    {
        "title": "Field Service Technician",
        "description_html": null,
        "description_text": "General information\nJob Title\nField Service Technician\nRef #\nP1008519\nEmployment Type\nPermanent\nDepartment\nSales\nPosition level\nTechnician\nDate\nMonday, December 22, 2025\nAESC Office Location\nSanta Clara, California USA\nDescription & Requirements\nJob Description\nAESC is looking to add a Field Service Technician to our team in remotely.\nFull-Time\nRemote\nAbout AESC US LLC\nAESC is an exciting, newly created global organization committed to solving the challenges of a sustainable future and becoming the leading supplier of full-value-chain battery solutions. Our lithium-ion batteries can be found in nearly one million electric vehicles worldwide and have a stellar safety record of zero-critical issues. AESC US is leading the way in battery technology. We design and manufacture EV battery technology for various electric vehicles and equipment. We are working hard towards unlocking the full potential of sustainable energy and climate change mitigation. We will continue to build upon our successes and expand into new markets and industries, producing innovative and competitive products and technologies that advance the goal of a zero-carbon emission future. AESC is headquartered in Japan and has battery manufacturing locations in Japan, UK, China, and the U.S.\nAESC Mission\nOur mission is to solve the challenges for a sustainable future. Together, we can make a meaningful impact.\nAbout the Role\nWe are seeking a skilled and hands-on Field Service Technician to support the installation and commissioning of utility-scale energy storage systems. This role will oversee on-site activities, including installation verification checks and coordination of commissioning processes, ensuring compliance with safety and quality standards. The ideal candidate will have strong technical aptitude, attention to detail, and the ability to work effectively in dynamic field environments.\nWhat You Will Do\nServe as the on-site representative during equipment installation and commissioning.\nPerform installation verification checks to ensure compliance with design specifications and safety standards.\nCoordinate and execute site commissioning activities for energy storage systems, including functional testing and troubleshooting.\nInterface with project managers, engineering teams, and customer representatives to resolve technical issues promptly.\nDocument installation and commissioning activities, including test results and punch lists.\nEnsure adherence to safety protocols and regulatory requirements during all field operations.\nProvide feedback to engineering and product teams on field performance and installation best practices.\nSupport training for customer personnel on system operation and maintenance.\nQualifications\nWhat You Need\nAssociate degree or technical certification in Electrical Engineering, Mechanical Engineering, or related field (or equivalent experience).\n2\u20135 years of experience in field service, commissioning, or installation of electrical or energy systems; experience with energy storage systems preferred.\nStrong understanding of electrical systems, power electronics, and industrial safety standards.\nAbility to read and interpret technical drawings, schematics, and installation manuals.\nProficiency with diagnostic tools and commissioning software.\nExcellent problem-solving skills and ability to work independently in fast-paced environments.\nWillingness to travel extensively and work on-site at customer locations.\nWhat is \u201cNice to Have\u201d?\nFamiliarity with battery energy storage systems (BESS) and renewable energy technologies.\nExperience with SCADA systems, PLCs, and communication protocols.\nKnowledge of commissioning procedures for large-scale electrical equipment.\nWhat We Offer\nWelcome to AESC, supporting our state-of-the-art Gigafactories, where you'll have the opportunity to tackle the world's most fascinating challenges alongside exceptionally talented individuals who are driven to make a difference. At AESC, we offer a comprehensive compensation package. In addition, we provide a range of valuable benefits, such as 401K,\nand health insurance. We strive to ensure that our employees are well taken care of, enabling them to focus on their work and contribute to our collective mission of changing the world.\nAn inclusive and diverse work environment that fosters and encourages professional and personal development.\nHighly automated, clean, safe, and temperature-controlled production environment\nMedical, Dental and Vision Insurance\nHSA and Flexible Spending Accounts\n401K with company match\nLife Insurance (Company paid and additional voluntary life available)\nPaid Vacation and 14 Paid Holidays\nShort term and long-term disability coverage (Company Paid)\nTuition reimbursement\nCompetitive base salary with performance-based incentives. Salary range: $86,000-$108,000/annual.\nOpportunity to work on cutting-edge energy storage projects contributing to grid reliability and decarbonization.\nHands-on exposure to advanced technologies in real-world applications.\nComprehensive training and career development opportunities.\nComprehensive benefits package including [health insurance, retirement plan, PTO, etc.].\nApplication Process\nEven if you don't meet every requirement listed, if you believe this role suits you well, we encourage you to apply. Your application gives us the opportunity to learn more about you and explore potential fits within our team.\nFollowing the submission of your application, we are committed to providing timely responses to all applicants, though response times may vary depending on the volume of submissions. If you do not receive an immediate response, please rest assured that this in no way reflects on the quality of your candidacy. Your application will be retained in our files, and we may reach out to you for future roles that align with your skills and interests. As our organization experiences rapid growth, we appreciate your patience in this process. We are actively working each day to enhance our application procedures to ensure a smoother and more efficient experience for all applicants. Thank you for your understanding and enthusiasm for joining our dynamic team.\nEqual Employment Opportunity\nAt AESC, we are committed to providing Equal Employment Opportunity (EEO) to all individuals. We participate in E-Verify and will provide the federal government with your Form I-9 information to confirm that you are authorized to work in the U.S Join us in our passion to design, manufacture, and sell high-performance products, contributing to a sustainable and zero-carbon emission future.\nPhysical Requirements\nThe physical demands described here are representative of those that must be met by an employee to successfully perform the essential functions of this job. Reasonable accommodation may be made to enable otherwise qualified individuals with disabilities to perform the essential job functions.\nAbility to sit for extended periods of time.\nAbility to read, write, speak, hear; stand; walk; use hands to finger, handle, or feel; reach and lift with hands and arms frequently throughout the day.\nRequired to occasionally lift, push, pull and/or move up to 10 pounds and occasionally required to lift, push, pull and/or move up to 35 pounds.\nAbility to lift light objects and use basic hand tools.\nCapability to stand and walk for extended periods during site activities.\nComfort working in outdoor conditions, including heat, cold, and varying weather.\nStrict adherence to OSHA requirements and site-specific safety protocols.\nUse of appropriate PPE (Personal Protective Equipment) at all times on site.\nWork Environment\nThe work environment is primarily an automated manufacturing plant with a concrete floor and is characterized by some temperature extremes, moderate noise, and forklift traffic. The individual must be able to perform all essential functions as appropriate on the plant floor, in meetings, and with employees, management, customers and suppliers.\nCandidate must perform the essential duties and responsibilities with or without reasonable accommodation efficiently and accurately, and without causing significant safety threat to self or others. The statements made herein are intended to describe the general nature and level of work being performed by employees assigned to this job classification. They are not intended to be construed as an exhaustive and inclusive list of all responsibilities, duties, and/or skills required of personnel so classified.\nGo back\nApply\nShare this job\nEmail\nFacebook\nX\nWeChat\nWhatsApp\nLinkedIn",
        "application_url": "https://jobs.aesc-group.com/en_US/careers/Login?jobId=974&recommendation=&source=&tags=&user=&formValues=",
        "": {},
        "metadata": {
            "Job Title": "Field Service Technician",
            "Ref #": "P1008519",
            "Employment Type": "Permanent",
            "Department": "Sales",
            "Position level": "Technician",
            "Date": "Monday, December 22, 2025",
            "AESC Office Location": "Santa Clara, California USA"
        },
        "link": "https://jobs.aesc-group.com/en_US/careers/JobDetail/Santa-Clara-California-United-States-Field-Service-Technician/974"
    },
    {
        "title": "Technical Services Engineer",
        "description_html": null,
        "description_text": "General information\nJob Title\nTechnical Services Engineer\nRef #\nP1008521\nEmployment Type\nPermanent\nDepartment\nSales\nPosition level\nEngineer\nDate\nMonday, December 22, 2025\nAESC Office Location\nRemote worker USA\nDescription & Requirements\nJob Description\nAESC is looking to add a Technician Services Engineer to our team remotely.\nFull-Time\nRemote\nAbout AESC US LLC\nAESC is an exciting, newly created global organization committed to solving the challenges of a sustainable future and becoming the leading supplier of full-value-chain battery solutions. Our lithium-ion batteries can be found in nearly one million electric vehicles worldwide and have a stellar safety record of zero-critical issues. AESC US is leading the way in battery technology. We design and manufacture EV battery technology for various electric vehicles and equipment. We are working hard towards unlocking the full potential of sustainable energy and climate change mitigation. We will continue to build upon our successes and expand into new markets and industries, producing innovative and competitive products and technologies that advance the goal of a zero-carbon emission future. AESC is headquartered in Japan and has battery manufacturing locations in Japan, UK, China, and the U.S.\nAESC Mission\nOur mission is to solve the challenges for a sustainable future. Together, we can make a meaningful impact.\nAbout the Role\nWe are seeking a highly skilled Technical Services Engineer to lead commissioning activities and manage technical service work for utility-scale energy storage systems. This role operates remotely and serves as the technical expert during commissioning and service operations, ensuring successful system start-up, troubleshooting, and compliance with all technical standards. The Technical Services Engineer will support the commissioning team and handle technical service activities, including diagnostics, repairs, and remote support. The ideal candidate will have deep technical knowledge, leadership ability, and a commitment to quality and safety.\nWhat You Will Do\nLead remote commissioning activities for energy storage systems, including system configuration, functional testing, and performance validation.\nAct as the technical authority during commissioning, guiding and directing the commissioning team to ensure successful project execution.\nPerform and oversee technical service work, including troubleshooting, diagnostics, and repairs for energy storage systems.\nProvide advanced technical support for service issues and collaborate with engineering teams to resolve complex challenges.\nPrepare and maintain detailed commissioning and service documentation, including test reports and maintenance records.\nEnsure compliance with safety standards, quality requirements, and regulatory guidelines during all commissioning and service activities.\nOffer technical training and mentorship to commissioning and service team members.\nSupport post-commissioning activities such as performance monitoring and issue resolution as needed.\nQualifications\nWhat You Need\nBachelor\u2019s degree in Electrical Engineering, Mechanical Engineering, or related technical field (or equivalent experience).\n3\u20136 years of experience in commissioning and service engineering for electrical or energy systems; experience with energy storage systems strongly preferred.\nExpertise in commissioning processes, system integration, troubleshooting, and repair of complex technical systems.\nProficiency with remote diagnostic tools, SCADA systems, and commissioning software.\nStrong analytical and problem-solving skills with the ability to lead technical activities independently.\nExcellent communication skills for guiding teams and interacting with customers remotely.\nWhat is \u201cNice to Have\u201d?\nExpert knowledge of battery energy storage systems (BESS) and renewable energy technologies.\nFamiliarity with PLC programming, communication protocols, and control systems.\nExperience with cybersecurity best practices for remote system access.\nWhat We Offer\nWelcome to AESC, supporting our state-of-the-art Gigafactories, where you'll have the opportunity to tackle the world's most fascinating challenges alongside exceptionally talented individuals who are driven to make a difference. At AESC, we offer a comprehensive compensation package. In addition, we provide a range of valuable benefits, such as 401K,\nand health insurance. We strive to ensure that our employees are well taken care of, enabling them to focus on their work and contribute to our collective mission of changing the world.\nAn inclusive and diverse work environment that fosters and encourages professional and personal development.\nHighly automated, clean, safe, and temperature-controlled production environment\nMedical, Dental and Vision Insurance\nHSA and Flexible Spending Accounts\n401K with company match\nLife Insurance (Company paid and additional voluntary life available)\nPaid Vacation and 14 Paid Holidays\nShort term and long-term disability coverage (Company Paid)\nTuition reimbursement\nCompetitive base salary with performance-based incentives. Salary range: $105,000-$132,000/annual.\nOpportunity to lead technical commissioning and service work for cutting-edge energy storage projects.\nRemote work flexibility with occasional site visits for critical activities.\nComprehensive training and career development opportunities.\nFull benefits package including [health insurance, retirement plan, PTO, etc.].\nApplication Process\nEven if you don't meet every requirement listed, if you believe this role suits you well, we encourage you to apply. Your application gives us the opportunity to learn more about you and explore potential fits within our team.\nFollowing the submission of your application, we are committed to providing timely responses to all applicants, though response times may vary depending on the volume of submissions. If you do not receive an immediate response, please rest assured that this in no way reflects on the quality of your candidacy. Your application will be retained in our files, and we may reach out to you for future roles that align with your skills and interests. As our organization experiences rapid growth, we appreciate your patience in this process. We are actively working each day to enhance our application procedures to ensure a smoother and more efficient experience for all applicants. Thank you for your understanding and enthusiasm for joining our dynamic team.\nEqual Employment Opportunity\nAt AESC, we are committed to providing Equal Employment Opportunity (EEO) to all individuals. We participate in E-Verify and will provide the federal government with your Form I-9 information to confirm that you are authorized to work in the U.S Join us in our passion to design, manufacture, and sell high-performance products, contributing to a sustainable and zero-carbon emission future.\nPhysical Requirements\nThe physical demands described here are representative of those that must be met by an employee to successfully perform the essential functions of this job. Reasonable accommodation may be made to enable otherwise qualified individuals with disabilities to perform the essential job functions.\nAbility to sit for extended periods of time.\nAbility to read, write, speak, hear; stand; walk; use hands to finger, handle, or feel; reach and lift with hands and arms frequently throughout the day.\nRequired to occasionally lift, push, pull and/or move up to 10 pounds and occasionally required to lift, push, pull and/or move up to 35 pounds.\nAbility to work extended hours during critical commissioning and service phases.\nComfortable working remotely while coordinating with on-site teams.\nStrict adherence to OSHA requirements and company safety protocols during all activities.\nUse of appropriate PPE when visiting sites for audits or troubleshooting.\nWork Environment\nThe work environment is primarily an automated manufacturing plant with a concrete floor and is characterized by some temperature extremes, moderate noise, and forklift traffic. The individual must be able to perform all essential functions as appropriate on the plant floor, in meetings, and with employees, management, customers and suppliers.\nCandidate must perform the essential duties and responsibilities with or without reasonable accommodation efficiently and accurately, and without causing significant safety threat to self or others. The statements made herein are intended to describe the general nature and level of work being performed by employees assigned to this job classification. They are not intended to be construed as an exhaustive and inclusive list of all responsibilities, duties, and/or skills required of personnel so classified.\nGo back\nApply\nShare this job\nEmail\nFacebook\nX\nWeChat\nWhatsApp\nLinkedIn",
        "application_url": "https://jobs.aesc-group.com/en_US/careers/Login?jobId=975&recommendation=&source=&tags=&user=&formValues=",
        "": {},
        "metadata": {
            "Job Title": "Technical Services Engineer",
            "Ref #": "P1008521",
            "Employment Type": "Permanent",
            "Department": "Sales",
            "Position level": "Engineer",
            "Date": "Monday, December 22, 2025",
            "AESC Office Location": "Remote worker USA"
        },
        "link": "https://jobs.aesc-group.com/en_US/careers/JobDetail/Santa-Clara-California-United-States-Technical-Services-Engineer/975"
    },
    {
        "title": "Manager, Inside Sales",
        "description_html": null,
        "description_text": "General information\nJob Title\nManager, Inside Sales\nRef #\nP1008515\nEmployment Type\nPermanent\nDepartment\nSales\nPosition level\nAnalyst\nDate\nFriday, December 19, 2025\nAESC Office Location\nRemote worker USA\nDescription & Requirements\nJob Description\nAESC is looking to add an Inside Sales Manager to our team remotely.\nFull-Time\nRemote/Hybrid/On-site\nAbout AESC US LLC\nAESC is an exciting, newly created global organization committed to solving the challenges of a sustainable future and becoming the leading supplier of full-value-chain battery solutions. Our lithium-ion batteries can be found in nearly one million electric vehicles worldwide and have a stellar safety record of zero-critical issues. AESC US is leading the way in battery technology. We design and manufacture EV battery technology for various electric vehicles and equipment. We are working hard towards unlocking the full potential of sustainable energy and climate change mitigation. We will continue to build upon our successes and expand into new markets and industries, producing innovative and competitive products and technologies that advance the goal of a zero-carbon emission future. AESC is headquartered in Japan and has battery manufacturing locations in Japan, UK, China, and the U.S.\nAESC Mission\nOur mission is to solve the challenges for a sustainable future. Together, we can make a meaningful impact.\nAbout the Role\nWe are seeking a highly organized and technically curious\nInside Sales\nManager\nto support our\nutility-scale energy storage (BESS)\nbusiness. This role will focus on lead qualification, sales support, and opportunity management for large-scale battery storage projects serving utilities, independent power producers (IPPs), developers, and EPCs. The Inside Sales Representative will work closely with account managers, engineering, and project teams to help drive project development from early-stage inquiry through contract award.\nWhat You Will Do\nServe as the primary point of contact for inbound inquiries related to utility-scale BESS projects (typically 10 MW to 500+ MW).\nSupport Account Managers to qualify leads by gathering project details such as project size, location, interconnection status, application (capacity, ancillary services, renewable integration, etc.), and project timeline.\nSupport the sales team by coordinating resources within the company to prepare proposal packages\nWork within the sales org and marketing department to assist in scheduling and planning related to both internal and external activities and industry trade shows\nMaintain accurate opportunity tracking, forecasts, and customer communications within the CRM system.\nAssist with RFP and RFQ responses, including data collection, document organization, and submission support.\nFollow up with customers on proposals, technical clarifications, and commercial discussions.\nMonitor utility-scale market activity, policy drivers, and competitive landscape.\nSupport channel partners, EPCs, and developers throughout early project development phases.\nQualifications\nWhat You Need\nBachelor\u2019s degree in Business, Engineering, Energy Systems, or a related field (or equivalent experience).\n2\u20134 years of inside sales, sales operations, or commercial support experience; exposure to utility-scale renewable energy, energy storage, power generation, or transmission & distribution preferred.\nFamiliarity with large infrastructure or capital equipment sales cycles.\nStrong understanding of sales funnel management and CRM tools.\nAbility to communicate complex technical and commercial concepts clearly and professionally.\nExcellent organizational skills with the ability to manage multiple large-scale opportunities simultaneously.\nSelf-driven, detail-oriented, and comfortable working in a fast-paced project environment.\nWhat is \u201cNice to Have\u201d?\nKnowledge of utility-scale BESS components (battery containers, PCS, EMS, transformers, SCADA).\nUnderstanding of grid-connected applications such as frequency regulation, capacity, energy arbitrage, and renewable integration.\nExperience supporting EPCs, utilities, IPPs, or project developers.\nFamiliarity with interconnection processes, permitting, and project development phases for Utility scale ESS projects.\nProficiency with CRM platforms (Salesforce, HubSpot) and Microsoft Office or Google Workspace.\nBilingual of English and Mandarin is preferred\nWhat We Offer\nWelcome to AESC, supporting our state-of-the-art Gigafactories, where you'll have the opportunity to tackle the world's most fascinating challenges alongside exceptionally talented individuals who are driven to make a difference. At AESC, we offer a comprehensive compensation package. In addition, we provide a range of valuable benefits, such as 401K,\nand health insurance. We strive to ensure that our employees are well taken care of, enabling them to focus on their work and contribute to our collective mission of changing the world.\nAn inclusive and diverse work environment that fosters and encourages professional and personal development.\nHighly automated, clean, safe, and temperature-controlled production environment\nMedical, Dental and Vision Insurance\nHSA and Flexible Spending Accounts\n401K with company match\nLife Insurance (Company paid and additional voluntary life available)\nPaid Vacation and 14 Paid Holidays\nShort term and long-term disability coverage (Company Paid)\nTuition reimbursement\nHands-on exposure to complex, high-value utility-scale infrastructure projects.\nOpportunity to work on large-scale energy transition projects impacting grid reliability and decarbonization.\nCompetitive base salary with performance-based incentives.\nComprehensive training in energy storage technologies and market dynamics.\nCareer growth opportunities within utility-scale sales, project development, or commercial operations.\nComprehensive benefits package including [health insurance, retirement plan, PTO, etc.].\nApplication Process\nEven if you don't meet every requirement listed, if you believe this role suits you well, we encourage you to apply. Your application gives us the opportunity to learn more about you and explore potential fits within our team.\nFollowing the submission of your application, we are committed to providing timely responses to all applicants, though response times may vary depending on the volume of submissions. If you do not receive an immediate response, please rest assured that this in no way reflects on the quality of your candidacy. Your application will be retained in our files, and we may reach out to you for future roles that align with your skills and interests. As our organization experiences rapid growth, we appreciate your patience in this process. We are actively working each day to enhance our application procedures to ensure a smoother and more efficient experience for all applicants. Thank you for your understanding and enthusiasm for joining our dynamic team.\nEqual Employment Opportunity\nAt AESC, we are committed to providing Equal Employment Opportunity (EEO) to all individuals. We participate in E-Verify and will provide the federal government with your Form I-9 information to confirm that you are authorized to work in the U.S Join us in our passion to design, manufacture, and sell high-performance products, contributing to a sustainable and zero-carbon emission future.\nPhysical Requirements\nThe physical demands described here are representative of those that must be met by an employee to successfully perform the essential functions of this job. Reasonable accommodation may be made to enable otherwise qualified individuals with disabilities to perform the essential job functions.\nAbility to sit for extended periods of time.\nAbility to read, write, speak, hear; stand; walk; use hands to finger, handle, or feel; reach and lift with hands and arms frequently throughout the day.\nRequired to occasionally lift, push, pull and/or move up to 10 pounds and occasionally required to lift, push, pull and/or move up to 35 pounds.\nWork Environment\nThe work environment is primarily an automated manufacturing plant with a concrete floor and is characterized by some temperature extremes, moderate noise, and forklift traffic. The individual must be able to perform all essential functions as appropriate on the plant floor, in meetings, and with employees, management, customers and suppliers.\nCandidate must perform the essential duties and responsibilities with or without reasonable accommodation efficiently and accurately, and without causing significant safety threat to self or others. The statements made herein are intended to describe the general nature and level of work being performed by employees assigned to this job classification. They are not intended to be construed as an exhaustive and inclusive list of all responsibilities, duties, and/or skills required of personnel so classified.\nGo back\nApply\nShare this job\nEmail\nFacebook\nX\nWeChat\nWhatsApp\nLinkedIn",
        "application_url": "https://jobs.aesc-group.com/en_US/careers/Login?jobId=969&recommendation=&source=&tags=&user=&formValues=",
        "": {},
        "metadata": {
            "Job Title": "Manager, Inside Sales",
            "Ref #": "P1008515",
            "Employment Type": "Permanent",
            "Department": "Sales",
            "Position level": "Analyst",
            "Date": "Friday, December 19, 2025",
            "AESC Office Location": "Remote worker USA"
        },
        "link": "https://jobs.aesc-group.com/en_US/careers/JobDetail/Santa-Clara-California-United-States-Manager-Inside-Sales/969"
    },
    {
        "title": "Manager, Commercial Contract",
        "description_html": null,
        "description_text": "General information\nJob Title\nManager, Commercial Contract\nRef #\nP1008517\nEmployment Type\nPermanent\nDepartment\nSales\nPosition level\nAnalyst\nDate\nFriday, December 19, 2025\nAESC Office Location\nSanta Clara, California USA\nDescription & Requirements\nJob Description\nAESC is looking to add a Commercial Contract Manager to our team remotely.\nFull-Time\nRemote\nAbout AESC US LLC\nAESC is an exciting, newly created global organization committed to solving the challenges of a sustainable future and becoming the leading supplier of full-value-chain battery solutions. Our lithium-ion batteries can be found in nearly one million electric vehicles worldwide and have a stellar safety record of zero-critical issues. AESC US is leading the way in battery technology. We design and manufacture EV battery technology for various electric vehicles and equipment. We are working hard towards unlocking the full potential of sustainable energy and climate change mitigation. We will continue to build upon our successes and expand into new markets and industries, producing innovative and competitive products and technologies that advance the goal of a zero-carbon emission future. AESC is headquartered in Japan and has battery manufacturing locations in Japan, UK, China, and the U.S.\nAESC Mission\nOur mission is to solve the challenges for a sustainable future. Together, we can make a meaningful impact.\nAbout the Role\nThe\nCommercial Contract Manager\nwill be responsible for managing the commercial and contractual aspects of utility-scale energy storage projects, from bid stage through contract execution and project delivery. This role serves as a key interface between sales, legal, engineering, supply chain, and project execution teams to ensure contracts are commercially sound, risk-balanced, and aligned with company strategy. The ideal candidate has experience with large-scale energy or infrastructure contracts and a strong understanding of project risk, pricing, and commercial terms.\nWhat You Will Do\nContract Development & Negotiation\nLead the review, drafting, and negotiation of commercial contracts for utility-scale BESS projects, including supply agreements, EPC contracts, LTSA/O&M agreements, and framework agreements.\nSupport sales and business development teams during RFP, RFQ, and bid phases by reviewing commercial terms and conditions.\nNegotiate key commercial terms including pricing structures, payment milestones, liquidated damages, performance guarantees, warranties, limitations of liability, and change management provisions.\nIdentify, assess, and mitigate commercial and contractual risks associated with utility-scale projects.\nCross-Functional Collaboration\nWork closely with legal counsel to ensure contracts comply with applicable laws, regulations, and company policies.\nCollaborate with engineering, project management, compliance team, and supply chain teams to align contract terms with technical scope, delivery schedules, and manufacturing constraints.\nSupport project execution teams by interpreting contract terms, managing contractual correspondence, and resolving commercial disputes.\nContract Administration & Governance\nMaintain ownership of contracts throughout the project lifecycle, from contract signature through final acceptance and closeout.\nManage change orders, claims, variations, and amendments in coordination with project management teams.\nEnsure compliance with contractual obligations, including milestone deliverables, documentation, and notice requirements.\nMaintain accurate contract records, risk registers, and commercial trackers.\nCommercial Strategy & Risk Management\nSupport the development of standard contract templates, commercial playbooks, and negotiation guidelines.\nMonitor market trends, customer contracting practices, and risk profiles in utility-scale energy storage and power infrastructure markets.\nProvide input on commercial structures, contract exhibits, and risk allocation\nQualifications\nWhat You Need\nBachelor\u2019s degree in Business, Law, Engineering, Finance, or a related field; advanced degree or legal background preferred.\n5+ years of experience in commercial contract management, contract negotiation, or commercial operations within energy, power generation, renewables, or large infrastructure projects.\nProven experience managing high-value, long-duration contracts (multi-million-dollar projects).\nStrong understanding of project-based contracting, including EPC and equipment supply agreements.\nAbility to identify and balance commercial risk while supporting business objectives.\nExcellent negotiation, communication, and stakeholder management skills.\nWhat is \u201cNice to Have\u201d?\nPreferred Skills & Knowledge\nExperience with utility-scale BESS projects, renewable energy, power electronics, or grid infrastructure.\nFamiliarity with performance guarantees, availability metrics, degradation warranties, and long-term service agreements for energy storage.\nUnderstanding of utility and IPP contracting practices.\nExperience working across international projects and multi-jurisdictional contracts.\nProficiency with contract management systems and Microsoft Office or Google\nWhat We Offer\nWelcome to AESC, supporting our state-of-the-art Gigafactories, where you'll have the opportunity to tackle the world's most fascinating challenges alongside exceptionally talented individuals who are driven to make a difference. At AESC, we offer a comprehensive compensation package. In addition, we provide a range of valuable benefits, such as 401K,\nand health insurance. We strive to ensure that our employees are well taken care of, enabling them to focus on their work and contribute to our collective mission of changing the world.\nAn inclusive and diverse work environment that fosters and encourages professional and personal development.\nHighly automated, clean, safe, and temperature-controlled production environment\nMedical, Dental and Vision Insurance\nHSA and Flexible Spending Accounts\n401K with company match\nLife Insurance (Company paid and additional voluntary life available)\nPaid Vacation and 14 Paid Holidays\nShort term and long-term disability coverage (Company Paid)\nTuition reimbursement\nCompetitive compensation package, including performance-based incentives.\nOpportunity to play a critical role in delivering large-scale energy storage projects supporting grid reliability and decarbonization.\nExposure to complex, high-impact infrastructure contracts.\nCollaborative, cross-functional working environment.\nCareer growth opportunities within commercial leadership, project management, or executive roles.\nComprehensive benefits package including [health insurance, retirement plan, PTO, etc.].\nApplication Process\nEven if you don't meet every requirement listed, if you believe this role suits you well, we encourage you to apply. Your application gives us the opportunity to learn more about you and explore potential fits within our team.\nFollowing the submission of your application, we are committed to providing timely responses to all applicants, though response times may vary depending on the volume of submissions. If you do not receive an immediate response, please rest assured that this in no way reflects on the quality of your candidacy. Your application will be retained in our files, and we may reach out to you for future roles that align with your skills and interests. As our organization experiences rapid growth, we appreciate your patience in this process. We are actively working each day to enhance our application procedures to ensure a smoother and more efficient experience for all applicants. Thank you for your understanding and enthusiasm for joining our dynamic team.\nEqual Employment Opportunity\nAt AESC, we are committed to providing Equal Employment Opportunity (EEO) to all individuals. We participate in E-Verify and will provide the federal government with your Form I-9 information to confirm that you are authorized to work in the U.S Join us in our passion to design, manufacture, and sell high-performance products, contributing to a sustainable and zero-carbon emission future.\nPhysical Requirements\nThe physical demands described here are representative of those that must be met by an employee to successfully perform the essential functions of this job. Reasonable accommodation may be made to enable otherwise qualified individuals with disabilities to perform the essential job functions.\nAbility to sit for extended periods of time.\nAbility to read, write, speak, hear; stand; walk; use hands to finger, handle, or feel; reach and lift with hands and arms frequently throughout the day.\nRequired to occasionally lift, push, pull and/or move up to 10 pounds and occasionally required to lift, push, pull and/or move up to 35 pounds.\nWork Environment\nThe work environment is primarily an automated manufacturing plant with a concrete floor and is characterized by some temperature extremes, moderate noise, and forklift traffic. The individual must be able to perform all essential functions as appropriate on the plant floor, in meetings, and with employees, management, customers and suppliers.\nCandidate must perform the essential duties and responsibilities with or without reasonable accommodation efficiently and accurately, and without causing significant safety threat to self or others. The statements made herein are intended to describe the general nature and level of work being performed by employees assigned to this job classification. They are not intended to be construed as an exhaustive and inclusive list of all responsibilities, duties, and/or skills required of personnel so classified.\nGo back\nApply\nShare this job\nEmail\nFacebook\nX\nWeChat\nWhatsApp\nLinkedIn",
        "application_url": "https://jobs.aesc-group.com/en_US/careers/Login?jobId=970&recommendation=&source=&tags=&user=&formValues=",
        "": {},
        "metadata": {
            "Job Title": "Manager, Commercial Contract",
            "Ref #": "P1008517",
            "Employment Type": "Permanent",
            "Department": "Sales",
            "Position level": "Analyst",
            "Date": "Friday, December 19, 2025",
            "AESC Office Location": "Santa Clara, California USA"
        },
        "link": "https://jobs.aesc-group.com/en_US/careers/JobDetail/Santa-Clara-California-United-States-Manager-Commercial-Contract/970"
    },
    {
        "title": "Environmental Health & Safety Engineer",
        "description_html": null,
        "description_text": "General information\nJob Title\nEnvironmental Health & Safety Engineer\nRef #\nP1008419\nEmployment Type\nPermanent\nDepartment\nEnvironmental Health and Safety\nPosition level\nEngineer\nDate\nMonday, November 24, 2025\nAESC Office Location\nFlorence, South Carolina USA\nDescription & Requirements\nJob Description\nAESC is looking to add a Engineer 3 Environmental, Health and Safety to our team in Florence, SC, supporting Columbia, SC 50/50 split.\nFull-Time\nOn-site\nAbout AESC US LLC\nAESC is a global leader in the development and manufacturing of high-performance batteries for zero-emission electric vehicles and energy storage systems. Founded in Japan in 2007 and headquartered in Yokohama, AESC has been building manufacturing capabilities around the world in the U.S., U.K., Europe, Japan and China to serve key markets and leading customers locally for over 14 years. Today, AESC has become the partner of choice for the world\u2019s leading OEMs and energy storage providers in North America, Europe, and Asia. Its advanced technology powers over one million electric vehicles and provides more than 15GWh of installed capacity for battery energy systems in over 60 countries.\nAESC is expanding its footprint in the United States with gigafactories in Kentucky, South Carolina, and Tennessee to meet the growing demand for EV and BESS batteries and strengthen its presence in the North American market. AESC's Tennessee gigafactory in Smyrna, which has been operational since 2012, produces batteries for Nissan. The Kentucky gigafactory in Bowling Green will supply Mercedes-Benz with high-performance battery cell modules. The South Carolina gigafactory in Florence will supply technology-leading battery cells for new electric models produced in BMW Group's Spartanburg plant. AESC is committed to our local communities where it is making its investments, creating jobs, and supporting local charities.\nAbout the Role\nAs a key member of AESC US LLC, the EHS Engineer (Level 3) will play a crucial role in advancing our mission to lead in full-value-chain battery solutions for a sustainable future. Reporting to the EHS Manager, you will be responsible for developing and implementing procedures, guidelines and recommending equipment to promote and ensure industrial safety and health.\nYour work within the EHS team will directly impact our strategic goals and contribute to our position as a global leader in battery technology.\nWhat You Will Do\nSupport the Development, Implementation, and Execution of MDS safety policies, requirements, and programs\nMaintain Safety Records\nReview documents tverify compliance with Safety Policies and requirements\nMaintain Hazard Tracking System data\nSupport System Safety Risk Identification and Management Processes\nEvaluate Safety documentation, system design, and baseline changes\nReview Program-level system safety assessment reports for completeness, technical accuracy and assessment of safety risk\nReview verification evidence and provide an assessment of whether safety specifications, hazard mitigations, and requirements are met\nConduct Program Reviews and Meetings\nAttend and support system-level design reviews and assessing changes throughout the life cycle of the Programs/Project\nSupport design and test reviews, change and failure review boards, and technical interchange meetings to identify and characterize risks\nSupport milestone reviews including Preliminary Design Reviews (PDR), Critical Design Reviews (CDR), Test Readiness Reviews (TRR)\nAssist in the tracking and closure of safety-related action items assigned during program reviews/meetings\nConduct Safety Audits and report deficiencies identified in the audits related to the implementation of and compliance with safety policies\nPerform safety audit follow-ups, track findings, and verify closure within the guidelines identified\nParticipate in the development and review of safety risk assessments and other safety analysis and assist in obtaining approval from the appropriate authority\nDevelop work instructions related tEHS\nSupport Safe Conduct System Demonstration Activities\nEvaluate mission-specific safety risks, particularly for the interaction of the test event with other systems\nAssess test architecture for safety concerns and review test plans and procedures for safety concerns\nSupport the development of Final Hazard Classification (FHC) detailed plans\nParticipate in pre-test reviews, such as Test Planning Reviews (TPRs)\nParticipate in daily status briefings\nParticipate in Failure Reviews and Mishap Investigations\nDevelop and publish Hazard Classification Documentation\nComplete Department of Transportation documentation in accordance with Federal Regulations\nComplete other duties as assigned\nQualifications\nWhat You Need\nBachelor\u2019s degree in safety engineering, industrial technology, or a related field\n5 years of related experience at a professional level is required\nWorking knowledge of Statistics and related Improvement Processes\nAbility to identify unsafe situations or potentially unsafe safety laws\nStrong knowledge of applicable Occupational Safety and Health Administration (OSHA) standards\nKnowledge of PSM (Process Safety) and RMP (Risk Management) processes\nEffective Problem-Solving/Root Cause Analysis\nAbility to work cross-functionally with staff in all departments\nExperience working and leading a team across cultural and discipline boundaries\nExperience or willingness to work in a global context, with an understanding of the challenges and opportunities associated with operating in diverse international markets\nProven ability to thrive in a fast-paced and evolving environment, demonstrating flexibility and adaptability to meet changing business needs and priorities\nProficient skills in Microsoft Office applications and conferencing systems\nUnderstands and follows all standards of IATF16949 and VDA 6.3 quality standards. (training and awareness will be provided for those who are not familiar with these standards)\nUnderstands and follows all standards of ISO14001 environmental standards. (training and awareness will be provided for those who are not familiar with these standards)\nUnderstands and follows all standards of IATF16949 and VDA 6.3 quality standards. (training and awareness will be provided for those who are not familiar with these standards)\nUnderstands and follows all standards of ISO14001 environmental standards. (training and awareness will be provided for those who are not familiar with these standards)\nWhat is \u201cNice to Have\u201d?\nCertified Safety Professional status\nKnowledge of battery manufacturing, EV manufacturing, or refinery operations\nAutomotive OEM or Tier 1 supplier experience\nNew model experience and equipment design, installation, and commissioning\nPrevious EHS experience in a battery manufacturing facility is highly preferred\nHigh-volume manufacturing environment experience\nStart-up experience\nTravel\nOccasional domestic and international travel required.\nWhat We Offer\nWelcome to AESC, where you'll have the opportunity to tackle the world's most fascinating challenges alongside exceptionally talented individuals who are driven to make a difference. We strive to ensure that our employees are well taken care of, enabling them to focus on their work and contribute to our collective mission.\nWe offer:\n\u2022\nComprehensive compensation packages including a competitive salary and a rewarding bonus program.\n\u2022\nAn inclusive and diverse work environment that fosters and encourages professional and personal development.\n\u2022\nHighly automated, clean, safe, and temperature-controlled production environment\n\u2022\nMedical, Dental and Vision Insurance\n\u2022\nHSA and Flexible Spending Accounts\n\u2022\n401K with company match\n\u2022\nLife Insurance (Company paid and additional voluntary life available)\n\u2022\nPaid Vacation and 14 Paid Holidays\n\u2022\nShort term and long-term disability coverage (Company Paid)\n\u2022\nTuition reimbursement\nApplication Process\nEven if you don't meet every requirement, we encourage you to apply. Your application allows us to learn more about you and find potential fits within our team. We strive to respond to all applicants promptly, though times may vary with submission volume. If you don't receive an immediate response, it doesn't reflect on your candidacy; we'll keep your application for future opportunities. Thank you for your patience and enthusiasm as we improve our application process.\nEqual Employment Opportunity\nAt AESC, we are committed to providing Equal Employment Opportunity (EEO) to all individuals. We participate in E-Verify and will provide the federal government with your Form I-9 information to confirm that you are authorized to work in the U.S Join us in our passion to design, manufacture, and sell high-performance products, contributing to a sustainable and zero-carbon emission future.\nPhysical Requirements\nThe physical demands described here are representative of those that must be met by an employee to successfully perform the essential functions of this job. Reasonable accommodation may be made to enable otherwise qualified individuals with disabilities to perform the essential job functions.\n\u2022\nAbility to sit for extended periods of time.\n\u2022\nAbility to read, write, speak, hear; stand; walk; use hands to finger, handle, or feel; reach and lift with hands and arms frequently throughout the day.\n\u2022\nRequired to occasionally lift, push, pull and/or move up to 10 pounds and occasionally required to lift, push, pull and/or move up to 35 pounds.\nWork Environment\nThe work environment is primarily an automated manufacturing plant with a concrete floor and is characterized by some temperature extremes, moderate noise, and forklift traffic. The individual must be able to perform all essential functions as appropriate on the plant floor, in meetings, and with employees, management, customers and suppliers.\nCandidate must perform the essential duties and responsibilities with or without reasonable accommodation efficiently and accurately, and without causing significant safety threat to self or others. The statements made herein are intended to describe the general nature and level of work being performed by employees assigned to this job classification. They are not intended to be construed as an exhaustive and inclusive list of all responsibilities, duties, and/or skills required of personnel so classified.\nHiring is contingent upon successful completion of drug screen and background check. AESC US LLC is a drug-free workplace.\nGo back\nApply\nShare this job\nEmail\nFacebook\nX\nWeChat\nWhatsApp\nLinkedIn",
        "application_url": "https://jobs.aesc-group.com/en_US/careers/Login?jobId=959&recommendation=&source=&tags=&user=&formValues=",
        "": {},
        "metadata": {
            "Job Title": "Environmental Health & Safety Engineer",
            "Ref #": "P1008419",
            "Employment Type": "Permanent",
            "Department": "Environmental Health and Safety",
            "Position level": "Engineer",
            "Date": "Monday, November 24, 2025",
            "AESC Office Location": "Florence, South Carolina USA"
        },
        "link": "https://jobs.aesc-group.com/en_US/careers/JobDetail/Florence-South-Carolina-United-States-Environmental-Health-Safety-Engineer/959"
    },
    {
        "title": "Superviseur Maintenance (H/F)",
        "description_html": null,
        "description_text": "General information\nJob Title\nSuperviseur Maintenance (H/F)\nRef #\n20001481\nEmployment Type\nPermanent\nDepartment\nHuman Resources\nPosition level\nManager\nDate\nMonday, November 3, 2025\nAESC Office Location\nDouai, Hauts-de-France, France\nDescription & Requirements\nJob Description\nRejoignez AESC et prenez part \u00e0 la r\u00e9volution de la mobilit\u00e9 \u00e9lectrique !\nEn tant que\nSuperviseur Maintenance\n, vous \u00eates le v\u00e9ritable chef d\u2019orchestre des op\u00e9rations d\u2019entretien et de fiabilisation des \u00e9quipements de votre secteur. Garant de la performance, de la s\u00e9curit\u00e9 et de la disponibilit\u00e9 des lignes, vous veillez \u00e0 ce que chaque intervention contribue \u00e0 la fiabilit\u00e9 et \u00e0 l\u2019excellence industrielle d\u2019AESC. Vous managez une \u00e9quipe d'une 40 aine de salari\u00e9s en horaires post\u00e9s 4*12.\nVos missions principales\n\ud83d\udca1 Piloter et animer vos \u00e9quipes\nManager et planifier les activit\u00e9s de maintenance (pr\u00e9ventive, curative, am\u00e9liorative).\nAccompagner techniquement les techniciens dans la remise en service des \u00e9quipements.\nSuivre et d\u00e9velopper les comp\u00e9tences de vos \u00e9quipes (formation, entretiens annuels et disciplinaires).\n\ud83d\udcca Garantir la performance et la fiabilit\u00e9 des installations\nSuivre et analyser les indicateurs cl\u00e9s (OEE, MTBF, MTTR, taux de r\u00e9alisation des pr\u00e9ventifs).\nAssurer la qualit\u00e9 et la pertinence des proc\u00e9dures et standards du d\u00e9partement.\nContribuer activement aux d\u00e9marches d\u2019am\u00e9lioration continue et \u00e0 la r\u00e9solution de probl\u00e8mes.\n\ud83d\udd27 Assurer la disponibilit\u00e9 et la conformit\u00e9 des \u00e9quipements\nSuperviser les op\u00e9rations d\u2019inspection, de maintenance pr\u00e9ventive et curative, dans le strict respect des r\u00e8gles de s\u00e9curit\u00e9 et environnementales.\nCollecter, analyser et partager les informations li\u00e9es aux pannes et incidents.\nPromouvoir la bonne utilisation de la GMAO/EAM.\n? \u00catre un acteur cl\u00e9 de la culture AESC\nPromouvoir une culture s\u00e9curit\u00e9 forte \u2014 la s\u00e9curit\u00e9 est notre priorit\u00e9 num\u00e9ro une.\nParticiper aux QRQC (Qualit\u00e9 avec R\u00e9ponse Rapide) et piloter les plans d\u2019actions correctifs.\nAnimer la d\u00e9marche 5S et garantir un environnement de travail propre, organis\u00e9 et efficace.\nAppliquer et faire respecter les politiques et proc\u00e9dures de l\u2019entreprise.\nCe que nous recherchons\nUne exp\u00e9rience confirm\u00e9e en management d\u2019\u00e9quipes de maintenance dans un environnement industriel exigeant (id\u00e9alement automatis\u00e9 ou \u00e9lectrom\u00e9canique).\nUne forte culture s\u00e9curit\u00e9, qualit\u00e9 et performance.\nUn leadership naturel, orient\u00e9 terrain et d\u00e9veloppement des collaborateurs.\nUne r\u00e9elle app\u00e9tence pour l\u2019am\u00e9lioration continue et les environnements technologiques de pointe.\nPourquoi rejoindre AESC ?\nParticiper \u00e0 un projet industriel d\u2019envergure mondiale au c\u0153ur de la transition \u00e9nerg\u00e9tique.\n\u00c9voluer dans un environnement high-tech, stimulant et en pleine croissance.\nB\u00e9n\u00e9ficier d\u2019un parcours d\u2019int\u00e9gration et de d\u00e9veloppement valorisant vos comp\u00e9tences.\nRejoindre une entreprise o\u00f9 la s\u00e9curit\u00e9, l\u2019innovation et la collaboration sont des valeurs fortes.\nMutuelle 100% prise en charge par l'entreprise pour le salari\u00e9\nhoraires actuels 4*12 contrat 40h cadre\nRequirements / Required skills\nElectrical Maintenance\nQualifications\nComp\u00e9tences techniques requises:\n- Pneumatique/Hydraulique/M\u00e9canique : Capacit\u00e9 \u00e0 lire des sch\u00e9mas/plans, \u00e0 comprendre les concepts de puissance des fluides/ la logique d\u2019assemblage.\n\u00b7 Maintenance \u00e9lectrique : capacit\u00e9 \u00e0 lire des plans et \u00e0 comprendre les installations\n\u00b7 Automates programmables (PLC) : notions d\u2019automatismes\n\u00b7 Robotique : Compr\u00e9hension du fonctionnement et des processus\n\u00b7 Connaissance du process g\u00e9n\u00e9ral d\u2019une gigafactory\n\u00b7 Connaissance avanc\u00e9e de l'outil GMAO/EAM\n\u00b7 Planification d\u2019activit\u00e9s et des arr\u00eats techniques en accord avec la production\n\u00b7 Ma\u00eetrise de la suite Office et des logiciels de bureautique de base\n\u00b7 Capacit\u00e9 \u00e0 utiliser efficacement les logiciels \u00e0 disposition pour saisir des donn\u00e9es et r\u00e9f\u00e9rencer des pi\u00e8ces\n\u00b7 Maitrise des outils de r\u00e9solution de probl\u00e8me\n\u00b7 Capacit\u00e9 \u00e0 remplacer son manager de fa\u00e7on ponctuelle, \u00e0 la demande de celui-ci\nLes savoir \u00eatre:\n\u00b7 Vigilance et attention particuli\u00e8re lors des activit\u00e9s r\u00e9alis\u00e9es avec pour priorit\u00e9 d\u2019\u00e9viter de se blesser et/ou de blesser les autres\n\u00b7 Capacit\u00e9 \u00e0 manager des \u00e9quipes\n\u00b7 Autonome, rigoureux et bienveillant\n\u00b7 Capacit\u00e9 de communication \u00e9crite et verbale\n\u00b7 Capacit\u00e9 de r\u00e9solution de probl\u00e8mes au travers d\u2019outils m\u00e9thodologiques\n\u00b7 Capacit\u00e9 \u00e0 travailler sous pression et \u00e0 respecter les d\u00e9lais\n\u00b7 Capacit\u00e9 \u00e0 travailler en \u00e9quipe\n\u00b7 Capacit\u00e9 de p\u00e9dagogie\nEXIGENCES DU POSTE\n\u00b7 Dipl\u00f4me de BTS ou DUT \u00e0 dominante technique ou \u00e9quivalent avec exp\u00e9rience \u00e9prouv\u00e9e\n\u00b7 Master \u00e0 dominante technique ou \u00e9quivalent avec exp\u00e9rience \u00e9prouv\u00e9e\n\u00b7 Mobilit\u00e9 nationale et/ou internationale ponctuelle\n\u00b7 Respect des r\u00e8gles de confidentialit\u00e9\n\u00b7 Anglais avanc\u00e9 (niveau B2 \u00e9crit et oral souhait\u00e9)\n#LI-EO1\nGo back\nApply\nShare this job\nEmail\nFacebook\nX\nWeChat\nWhatsApp\nLinkedIn",
        "application_url": "https://jobs.aesc-group.com/en_US/careers/Login?jobId=939&recommendation=&source=&tags=&user=&formValues=",
        "": {},
        "metadata": {
            "Job Title": "Superviseur Maintenance (H/F)",
            "Ref #": "20001481",
            "Employment Type": "Permanent",
            "Department": "Human Resources",
            "Position level": "Manager",
            "Date": "Monday, November 3, 2025",
            "AESC Office Location": "Douai, Hauts-de-France, France"
        },
        "link": "https://jobs.aesc-group.com/en_US/careers/JobDetail/LAMBRES-LEZ-DOUAI-France-Superviseur-Maintenance-H-F/939"
    },
    {
        "title": "Associate General Counsel",
        "description_html": null,
        "description_text": "General information\nJob Title\nAssociate General Counsel\nRef #\n20000757\nEmployment Type\nPermanent\nDepartment\nLegal\nPosition level\nSpecialist\nDate\nSaturday, November 1, 2025\nAESC Office Location\nMurfreesboro, Tennessee USA\nDescription & Requirements\nJob Description\nAESC is looking to add a Associate General Counsel to our team in Murfreesboro, TN.\n\u2022\nFull-Time\n\u2022\nHybrid/On-site\nAbout AESC US LLC\nAESC is a global leader in the development and manufacturing of high-performance batteries for zero-emission electric vehicles and energy storage systems. Founded in Japan in 2007 and headquartered in Yokohama, AESC has been building manufacturing capabilities around the world in the U.S., U.K., Europe, Japan and China to serve key markets and leading customers locally for over 14 years. Today, AESC has become the partner of choice for the world\u2019s leading OEMs and energy storage providers in North America, Europe, and Asia. Its advanced technology powers over one million electric vehicles and provides more than 15GWh of installed capacity for battery energy systems in over 60 countries.\nAESC is expanding its footprint in the United States with gigafactories in Kentucky, South Carolina, and Tennessee to meet the growing demand for EV and BESS batteries and strengthen its presence in the North American market. AESC's Tennessee gigafactory in Smyrna, which has been operational and supplying electric vehicle batteries for the Nissan LEAF since 2012, was retooled in 2025 and now produces batteries for Energy Storage Systems. The South Carolina gigafactory in Florence will supply next generation cells for BMW starting in 2026. The Kentucky gigafactory in Bowling Green will supply high-performance batteries and components for other OEMs.\u00a0AESC is committed to our local communities where it is making its investments, creating jobs, and supporting local charities.\nAbout the Role\nAs the Associate General Counsel at AESC, you will play a key role in shaping the legal structure and supporting the company\u2019s growth and compliance. You will work closely with the General Counsel Americas and other legal leaders to develop legal strategies, manage large-scale legal projects, and oversee the drafting, negotiation, and review of key contracts and agreements. This position requires a deep understanding of legal risk management, commercial law, and regulatory compliance while fostering scalable legal processes within a fast-paced, dynamic environment.\nWhat You Will Do\nLegal Strategy and Structure:\nCollaborate with the General Counsel and other legal leaders to develop the foundational structures for a robust legal function.\nEstablish processes and procedures for managing legal projects and daily operations to ensure efficiency and compliance.\nContract Drafting and Negotiation:\nServe as a primary legal advisor to review, draft, and negotiate key commercial agreements, including master services agreements, EPC contracts, vendor agreements, and other contractual documents.\nEnsure all contracts comply with relevant laws, regulations, and internal policies, and analyze legal terms to mitigate risks.\nCompliance and Risk Management:\nProvide counsel on legal and regulatory compliance issues and work to ensure adherence to internal policies and external legal requirements.\nIdentify and creatively solve legal and contractual risks while advising internal teams on various legal questions and long-term projects.\nProject Management and Leadership:\nLead and manage large-scale legal projects on critical issues facing the organization.\nSupervise and mentor junior legal professionals, helping them develop professionally and ensuring their work aligns with company goals.\nProcess Improvement:\nImplement scalable contracting processes to streamline the legal function and improve operational efficiency.\nCollaborate with internal teams across sales, compliance, finance, and operations to provide legal guidance on projects and daily operations.\nComplete other duties as assigned\nWhat You Need\nEducational Background:\n\u00b7\nJ.D. from an ABA-accredited law school is required.\n\u00b7\nMust be a member in good standing of a state bar, enabling independent legal practice.\nExperience:\n\u00b7\nAt least 5 years of legal experience in a law firm, in-house legal department, or equivalent setting.\n\u00b7\nExtensive experience in reviewing, drafting, and negotiating commercial agreements and contracts.\nSkills:\n\u00b7\nStrong organizational, analytical, and drafting skills with great attention to detail.\n\u00b7\nAbility to work independently with sound problem-solving skills and a proactive approach.\n\u00b7\nExceptional communication skills, both written and oral, with the ability to collaborate effectively with cross-functional teams.\n\u00b7\nAbility to manage and prioritize multiple tasks in a fast-paced environment.\no\nUnderstands and follows all standards of IATF16949 and VDA 6.3 quality standards. (training and awareness will be provided for those who are not familiar with these standards)\no\nUnderstands and follows all standards of ISO14001 environmental standards. (training and awareness will be provided for those who are not familiar with these standards)\n\u00b7\nUnderstands and follows all standards of IATF16949 and VDA 6.3 quality standards. (training and awareness will be provided for those who are not familiar with these standards)\n\u00b7\nUnderstands and follows all standards of ISO14001 environmental standards. (training and awareness will be provided for those who are not familiar with these standards)\nWhat is \u201cNice to Have\u201d?\nLeadership Experience:\n\u00b7\nPrior experience managing junior legal professionals or teams in a legal setting.\nIndustry Knowledge:\n\u00b7\nExperience working in the energy, manufacturing, or technology sectors, with a focus on commercial and regulatory issues.\nProject Management:\n\u00b7\nDemonstrated success in managing large-scale legal projects and cross-functional initiatives.\nProcess Improvement:\n\u00b7\nFamiliarity with legal process automation and the implementation of scalable legal workflows.\nIndustry Knowledge:\n\u00b7\nExperience in a high-volume manufacturing environment, particularly in automotive or battery production, is advantageous.\nStartup Experience:\n\u00b7\nExperience in a startup or rapidly growing environment, demonstrating adaptability to change and the ability to work in a dynamic setting.\nTravel\nOccasional domestic and international travel required.\nWhat We Offer\nWelcome to AESC, where you'll have the opportunity to tackle the world's most fascinating challenges alongside exceptionally talented individuals who are driven to make a difference. We strive to ensure that our employees are well taken care of, enabling them to focus on their work and contribute to our collective mission.\nWe offer:\n\u2022\nComprehensive compensation packages including a competitive salary and a rewarding bonus program.\n\u2022\nAn inclusive and diverse work environment that fosters and encourages professional and personal development.\n\u2022\nHighly automated, clean, safe, and temperature-controlled production environment\n\u2022\nMedical, Dental and Vision Insurance\n\u2022\nHSA and Flexible Spending Accounts\n\u2022\n401K with company match\n\u2022\nLife Insurance (Company paid and additional voluntary life available)\n\u2022\nPaid Vacation and 14 Paid Holidays\n\u2022\nShort term and long-term disability coverage (Company Paid)\n\u2022\nTuition reimbursement\nApplication Process\nEven if you don't meet every requirement, we encourage you to apply. Your application allows us to learn more about you and find potential fits within our team. We strive to respond to all applicants promptly, though times may vary with submission volume. If you don't receive an immediate response, it doesn't reflect on your candidacy; we'll keep your application for future opportunities. Thank you for your patience and enthusiasm as we improve our application process.\nEqual Employment Opportunity\nAt AESC, we are committed to providing Equal Employment Opportunity (EEO) to all individuals. We participate in E-Verify and will provide the federal government with your Form I-9 information to confirm that you are authorized to work in the U.S Join us in our passion to design, manufacture, and sell high-performance products, contributing to a sustainable and zero-carbon emission future.\nPhysical Requirements\nThe physical demands described here are representative of those that must be met by an employee to successfully perform the essential functions of this job. Reasonable accommodation may be made to enable otherwise qualified individuals with disabilities to perform the essential job functions.\n\u2022\nAbility to sit for extended periods of time.\n\u2022\nAbility to read, write, speak, hear; stand; walk; use hands to finger, handle, or feel; reach and lift with hands and arms frequently throughout the day.\n\u2022\nRequired to occasionally lift, push, pull and/or move up to 10 pounds and occasionally required to lift, push, pull and/or move up to 35 pounds.\nWork Environment\nThe work environment is primarily an automated manufacturing plant with a concrete floor and is characterized by some temperature extremes, moderate noise, and forklift traffic. The individual must be able to perform all essential functions as appropriate on the plant floor, in meetings, and with employees, management, customers and suppliers.\nCandidate must perform the essential duties and responsibilities with or without reasonable accommodation efficiently and accurately, and without causing significant safety threat to self or others. The statements made herein are intended to describe the general nature and level of work being performed by employees assigned to this job classification. They are not intended to be construed as an exhaustive and inclusive list of all responsibilities, duties, and/or skills required of personnel so classified.\nHiring is contingent upon successful completion of drug screen and background check. AESC US LLC is a drug-free workplace.\nQualifications\nWhat You Need\nEducational Background:\n\u00b7\nJ.D. from an ABA-accredited law school is required.\n\u00b7\nMust be a member in good standing of a state bar, enabling independent legal practice.\nExperience:\n\u00b7\nAt least 5 years of legal experience in a law firm, in-house legal department, or equivalent setting.\n\u00b7\nExtensive experience in reviewing, drafting, and negotiating commercial agreements and contracts.\nSkills:\n\u00b7\nStrong organizational, analytical, and drafting skills with great attention to detail.\n\u00b7\nAbility to work independently with sound problem-solving skills and a proactive approach.\n\u00b7\nExceptional communication skills, both written and oral, with the ability to collaborate effectively with cross-functional teams.\n\u00b7\nAbility to manage and prioritize multiple tasks in a fast-paced environment.\no\nUnderstands and follows all standards of IATF16949 and VDA 6.3 quality standards. (training and awareness will be provided for those who are not familiar with these standards)\no\nUnderstands and follows all standards of ISO14001 environmental standards. (training and awareness will be provided for those who are not familiar with these standards)\n\u00b7\nUnderstands and follows all standards of IATF16949 and VDA 6.3 quality standards. (training and awareness will be provided for those who are not familiar with these standards)\n\u00b7\nUnderstands and follows all standards of ISO14001 environmental standards. (training and awareness will be provided for those who are not familiar with these standards)\nWhat is \u201cNice to Have\u201d?\nLeadership Experience:\n\u00b7\nPrior experience managing junior legal professionals or teams in a legal setting.\nIndustry Knowledge:\n\u00b7\nExperience working in the energy, manufacturing, or technology sectors, with a focus on commercial and regulatory issues.\nProject Management:\n\u00b7\nDemonstrated success in managing large-scale legal projects and cross-functional initiatives.\nProcess Improvement:\n\u00b7\nFamiliarity with legal process automation and the implementation of scalable legal workflows.\nIndustry Knowledge:\n\u00b7\nExperience in a high-volume manufacturing environment, particularly in automotive or battery production, is advantageous.\nStartup Experience:\n\u00b7\nExperience in a startup or rapidly growing environment, demonstrating adaptability to change and the ability to work in a dynamic setting.\nTravel\nOccasional domestic and international travel required.\nWhat We Offer\nWelcome to AESC, where you'll have the opportunity to tackle the world's most fascinating challenges alongside exceptionally talented individuals who are driven to make a difference. We strive to ensure that our employees are well taken care of, enabling them to focus on their work and contribute to our collective mission.\nWe offer:\n\u2022\nComprehensive compensation packages including a competitive salary and a rewarding bonus program.\n\u2022\nAn inclusive and diverse work environment that fosters and encourages professional and personal development.\n\u2022\nHighly automated, clean, safe, and temperature-controlled production environment\n\u2022\nMedical, Dental and Vision Insurance\n\u2022\nHSA and Flexible Spending Accounts\n\u2022\n401K with company match\n\u2022\nLife Insurance (Company paid and additional voluntary life available)\n\u2022\nPaid Vacation and 14 Paid Holidays\n\u2022\nShort term and long-term disability coverage (Company Paid)\n\u2022\nTuition reimbursement\nApplication Process\nEven if you don't meet every requirement, we encourage you to apply. Your application allows us to learn more about you and find potential fits within our team. We strive to respond to all applicants promptly, though times may vary with submission volume. If you don't receive an immediate response, it doesn't reflect on your candidacy; we'll keep your application for future opportunities. Thank you for your patience and enthusiasm as we improve our application process.\nEqual Employment Opportunity\nAt AESC, we are committed to providing Equal Employment Opportunity (EEO) to all individuals. We participate in E-Verify and will provide the federal government with your Form I-9 information to confirm that you are authorized to work in the U.S Join us in our passion to design, manufacture, and sell high-performance products, contributing to a sustainable and zero-carbon emission future.\nPhysical Requirements\nThe physical demands described here are representative of those that must be met by an employee to successfully perform the essential functions of this job. Reasonable accommodation may be made to enable otherwise qualified individuals with disabilities to perform the essential job functions.\n\u2022\nAbility to sit for extended periods of time.\n\u2022\nAbility to read, write, speak, hear; stand; walk; use hands to finger, handle, or feel; reach and lift with hands and arms frequently throughout the day.\n\u2022\nRequired to occasionally lift, push, pull and/or move up to 10 pounds and occasionally required to lift, push, pull and/or move up to 35 pounds.\nWork Environment\nThe work environment is primarily an automated manufacturing plant with a concrete floor and is characterized by some temperature extremes, moderate noise, and forklift traffic. The individual must be able to perform all essential functions as appropriate on the plant floor, in meetings, and with employees, management, customers and suppliers.\nCandidate must perform the essential duties and responsibilities with or without reasonable accommodation efficiently and accurately, and without causing significant safety threat to self or others. The statements made herein are intended to describe the general nature and level of work being performed by employees assigned to this job classification. They are not intended to be construed as an exhaustive and inclusive list of all responsibilities, duties, and/or skills required of personnel so classified.\nHiring is contingent upon successful completion of drug screen and background check. AESC US LLC is a drug-free workplace.\nGo back\nApply\nShare this job\nEmail\nFacebook\nX\nWeChat\nWhatsApp\nLinkedIn",
        "application_url": "https://jobs.aesc-group.com/en_US/careers/Login?jobId=943&recommendation=&source=&tags=&user=&formValues=",
        "": {},
        "metadata": {
            "Job Title": "Associate General Counsel",
            "Ref #": "20000757",
            "Employment Type": "Permanent",
            "Department": "Legal",
            "Position level": "Specialist",
            "Date": "Saturday, November 1, 2025",
            "AESC Office Location": "Murfreesboro, Tennessee USA"
        },
        "link": "https://jobs.aesc-group.com/en_US/careers/JobDetail/Murfreesboro-Tennessee-United-States-Associate-General-Counsel/943"
    },
    {
        "title": "Ing\u00e9nieur Contamination",
        "description_html": null,
        "description_text": "General information\nJob Title\nIng\u00e9nieur Contamination\nRef #\n20001480\nEmployment Type\nPermanent\nDepartment\nEngineering\nPosition level\nEngineer\nDate\nFriday, October 24, 2025\nAESC Office Location\nDouai, Hauts-de-France, France\nDescription & Requirements\nJob Description\nReady to tackle the challenges of environmentally conscious mobility? \u267b\ufe0f\nJoin AESC and become a key player in the development and production of high-performance lithium-ion batteries!\nAESC is recruiting for the Contamination Control Manager position to join our Giga factory project in France. This role will be critical to the successful launch of the facility and will focus on process engineering, delivery, commissioning, and ongoing production support for the dedicated process area.\nThis is an exciting opportunity to contribute to a major European battery project and be part of a significant industrial transformation within the electric vehicle marketplace. The role will be based in Douai.\n#LI-EO1\nQualifications\nKey Responsibilities:\n- \u00a0Reduce contamination in the production process by ensuring ramp-up to production volume.\n- Oversee contamination control during ongoing production, providing quick issue resolution, continuous optimization, and root cause analysis.\n- Lead the assessment of equipment in term of contamination\n- Lead process contamination monitoring and problem-solving efforts for contamination-related issues.\n- Optimize dust removal and magnetization processes.\n- Inspect foreign bodies and contamination on-site, promote training for contamination control.\n- Lead the tracking of contamination control plans and optimize cleaning work instructions.\n- Conduct regular contamination audits across the facility and provide support during the ramp-up to mass production.\nRequired Skills:\n- Experience in process engineering with a focus on process control and optimization.\n- Leadership in problem-solving and root cause analysis for complex manufacturing issues.\n- Experience conducting lab-based analysis and operating lab equipment for contamination analysis.\n- Experience investigating product quality through tear-downs or investigations.\n- Strong report writing skills with the ability to drive issues to resolution.\n- Self-motivated, results-driven, and capable of leading teams in cross-functional environments.\nAdvantageous Experience:\n- Previous involvement in battery manufacturing or similar technologies (e.g., high-speed consumer goods, high-speed machining or assembly, printing, web conversion).\n- Background in high-volume, quality-focused environments.\nPrerequisites:\n- Degree in Engineering or a related field.\n- Excellent verbal and written communication skills in English and French\n- Willingness to travel internationally (<10%).\n-Proficiency in Microsoft Excel, PowerPoint, and word processing tools.\nGo back\nApply\nShare this job\nEmail\nFacebook\nX\nWeChat\nWhatsApp\nLinkedIn",
        "application_url": "https://jobs.aesc-group.com/en_US/careers/Login?jobId=934&recommendation=&source=&tags=&user=&formValues=",
        "": {},
        "metadata": {
            "Job Title": "Ing\u00e9nieur Contamination",
            "Ref #": "20001480",
            "Employment Type": "Permanent",
            "Department": "Engineering",
            "Position level": "Engineer",
            "Date": "Friday, October 24, 2025",
            "AESC Office Location": "Douai, Hauts-de-France, France"
        },
        "link": "https://jobs.aesc-group.com/en_US/careers/JobDetail/DOUAI-France-Ing-nieur-Contamination/934"
    },
    {
        "title": "Senior Counsel",
        "description_html": null,
        "description_text": "General information\nJob Title\nSenior Counsel\nRef #\nP1007974\nEmployment Type\nPermanent\nDepartment\nLegal\nPosition level\nSpecialist\nDate\nThursday, October 23, 2025\nAESC Office Location\nMurfreesboro, Tennessee USA\nDescription & Requirements\nJob Description\nAbout AESC US LLC\nAESC is an exciting, newly created global organization committed to solving the challenges of a sustainable future and becoming the leading supplier of full-value-chain battery solutions. Our lithium-ion batteries can be found in nearly one million electric vehicles worldwide and have a stellar safety record of zero-critical issues. AESC US is leading the way in battery technology. We design and manufacture EV battery technology for various electric vehicles and equipment. We are working hard towards unlocking the full potential of sustainable energy and climate change mitigation. We will continue to build upon our successes and expand into new markets and industries, producing innovative and competitive products and technologies that advance the goal of a zero-carbon emission future. AESC is headquartered in Japan and has battery manufacturing locations in Japan, UK, China, and the U.S.\nAESC Mission\nOur mission is to solve the challenges for a sustainable future. Together, we can make a meaningful impact.\nWhat You Will Do\nThis position reports to General Counsel Americas\nManage large-scale as well as routine legal projects on key substantive legal issues facing the organization.\nServe as a primary lawyer to review, draft, and negotiate customer and supply side commercial agreements, such as supply agreements, master services agreements, EPC and vendor agreements and other contracts.\nAnalyze, revise, and negotiate contractual provisions to facilitate the needs of the business as well as compliance with appropriate laws, regulations, as well as company policies and procedures.\nIdentify and solve legal and contractual risks with a focus on organizational profitability.\nAdvise internal sales, purchasing, trade, financial, and operations personnel on daily questions and long-term projects.\nImplement scalable contracting processes.\nWork with and supervise the work of junior legal professionals.\nPerform other related duties as required.\nWhat You Need\nAt least 5 years' experience in a law firm, in-house legal department, or equivalent setting.\nJ.D. from an ABA accredited law school.\nMember in good standing of a state bar such that legal work may be performed independently.\nExceptional organizational, analytical, and drafting skills with great attention to detail.\nStrong team player with a positive attitude and desire to work collectively to achieve team and company goals.\nAbility to work and think independently, possessing sound, creative problem-solving skills.\nResponsive, client-service focused, and professional.\nWilling to accept additional responsibility, challenging tasks, and/or projects.\nAble to flexibly react to multiple and shifting priorities.\nStrong communication (written and oral) and interpersonal skills.\nHigh achieving, win-focused, inquisitive nature.\nUnderstanding of how to practice law in a commercial setting as well as the rigors of the manufacturing environment.\nDesire to learn, grow, and promote continuous improvement in the legal department.\nStrong work ethic and sense of ownership and proactivity.\nAbility to work positively in an international work environment.\nWhat is \u201cNice to Have\u201d?\nTennessee bar admission is highly valued; Bar admission(s) in South Carolina and/or Kentucky are also useful\nForeign language fluency, especially in East Asian languages\nSpecialized legal ability to lead in a subject matter without sacrificing flexibility to be a generalist\nExperience leading the implementation of legal technology\nWhat We Offer\nWelcome to AESC, supporting our state-of-the-art Gigafactories, where you'll have the opportunity to tackle the world's most fascinating challenges alongside exceptionally talented individuals who are driven to make a difference. At AESC, we offer a comprehensive compensation package. In addition, we provide a range of valuable benefits, such as 401K,\nand health insurance. We strive to ensure that our employees are well taken care of, enabling them to focus on their work and contribute to our collective mission of changing the world.\nAn inclusive and diverse work environment that fosters and encourages professional and personal development.\nHighly automated, clean, safe, and temperature-controlled production environment\nMedical, Dental and Vision Insurance\nHSA and Flexible Spending Accounts\n401K with company match\nLife Insurance (Company paid and additional voluntary life available)\nPaid Vacation and 14 Paid Holidays\nShort term and long-term disability coverage (Company Paid)\nTuition reimbursement\nApplication Process\nEven if you don't meet every requirement listed, if you believe this role suits you well, we encourage you to apply. Your application gives us the opportunity to learn more about you and explore potential fits within our team.\nFollowing the submission of your application, we are committed to providing timely responses to all applicants, though response times may vary depending on the volume of submissions. If you do not receive an immediate response, please rest assured that this in no way reflects on the quality of your candidacy. Your application will be retained in our files, and we may reach out to you for future roles that align with your skills and interests. As our organization experiences rapid growth, we appreciate your patience in this process. We are actively working each day to enhance our application procedures to ensure a smoother and more efficient experience for all applicants. Thank you for your understanding and enthusiasm for joining our dynamic team.\nEqual Employment Opportunity\nAt AESC, we are committed to providing Equal Employment Opportunity (EEO) to all individuals. We participate in E-Verify and will provide the federal government with your Form I-9 information to confirm that you are authorized to work in the U.S Join us in our passion to design, manufacture, and sell high-performance products, contributing to a sustainable and zero-carbon emission future.\nPhysical Requirements\nThe physical demands described here are representative of those that must be met by an employee to successfully perform the essential functions of this job. Reasonable accommodation may be made to enable otherwise qualified individuals with disabilities to perform the essential job functions.\nAbility to sit for extended periods of time.\nAbility to read, write, speak, hear; stand; walk; use hands to finger, handle, or feel; reach and lift with hands and arms frequently throughout the day.\nWork Environment\nThe individual must be able to perform all essential functions as appropriate on the plant floor, in meetings, and with employees, management, customers and suppliers.\nCandidate must perform the essential duties and responsibilities with or without reasonable accommodation efficiently and accurately, and without causing significant safety threat to self or others. The statements made herein are intended to describe the general nature and level of work being performed by employees assigned to this job classification. They are not intended to be construed as an exhaustive and inclusive list of all responsibilities, duties, and/or skills required of personnel so classified.\nQualifications\nWhat You Need\nAt least 5 years' experience in a law firm, in-house legal department, or equivalent setting.\nJ.D. from an ABA accredited law school.\nMember in good standing of a state bar such that legal work may be performed independently.\nExceptional organizational, analytical, and drafting skills with great attention to detail.\nStrong team player with a positive attitude and desire to work collectively to achieve team and company goals.\nAbility to work and think independently, possessing sound, creative problem-solving skills.\nResponsive, client-service focused, and professional.\nWilling to accept additional responsibility, challenging tasks, and/or projects.\nAble to flexibly react to multiple and shifting priorities.\nStrong communication (written and oral) and interpersonal skills.\nHigh achieving, win-focused, inquisitive nature.\nUnderstanding of how to practice law in a commercial setting as well as the rigors of the manufacturing environment.\nDesire to learn, grow, and promote continuous improvement in the legal department.\nStrong work ethic and sense of ownership and proactivity.\nAbility to work positively in an international work environment.\nWhat is \u201cNice to Have\u201d?\nTennessee bar admission is highly valued; Bar admission(s) in South Carolina and/or Kentucky are also useful\nForeign language fluency, especially in East Asian languages\nSpecialized legal ability to lead in a subject matter without sacrificing flexibility to be a generalist\nExperience leading the implementation of legal technology\nWhat We Offer\nWelcome to AESC, supporting our state-of-the-art Gigafactories, where you'll have the opportunity to tackle the world's most fascinating challenges alongside exceptionally talented individuals who are driven to make a difference. At AESC, we offer a comprehensive compensation package. In addition, we provide a range of valuable benefits, such as 401K,\nand health insurance. We strive to ensure that our employees are well taken care of, enabling them to focus on their work and contribute to our collective mission of changing the world.\nAn inclusive and diverse work environment that fosters and encourages professional and personal development.\nHighly automated, clean, safe, and temperature-controlled production environment\nMedical, Dental and Vision Insurance\nHSA and Flexible Spending Accounts\n401K with company match\nLife Insurance (Company paid and additional voluntary life available)\nPaid Vacation and 14 Paid Holidays\nShort term and long-term disability coverage (Company Paid)\nTuition reimbursement\nApplication Process\nEven if you don't meet every requirement listed, if you believe this role suits you well, we encourage you to apply. Your application gives us the opportunity to learn more about you and explore potential fits within our team.\nFollowing the submission of your application, we are committed to providing timely responses to all applicants, though response times may vary depending on the volume of submissions. If you do not receive an immediate response, please rest assured that this in no way reflects on the quality of your candidacy. Your application will be retained in our files, and we may reach out to you for future roles that align with your skills and interests. As our organization experiences rapid growth, we appreciate your patience in this process. We are actively working each day to enhance our application procedures to ensure a smoother and more efficient experience for all applicants. Thank you for your understanding and enthusiasm for joining our dynamic team.\nEqual Employment Opportunity\nAt AESC, we are committed to providing Equal Employment Opportunity (EEO) to all individuals. We participate in E-Verify and will provide the federal government with your Form I-9 information to confirm that you are authorized to work in the U.S Join us in our passion to design, manufacture, and sell high-performance products, contributing to a sustainable and zero-carbon emission future.\nPhysical Requirements\nThe physical demands described here are representative of those that must be met by an employee to successfully perform the essential functions of this job. Reasonable accommodation may be made to enable otherwise qualified individuals with disabilities to perform the essential job functions.\nAbility to sit for extended periods of time.\nAbility to read, write, speak, hear; stand; walk; use hands to finger, handle, or feel; reach and lift with hands and arms frequently throughout the day.\nWork Environment\nThe individual must be able to perform all essential functions as appropriate on the plant floor, in meetings, and with employees, management, customers and suppliers.\nCandidate must perform the essential duties and responsibilities with or without reasonable accommodation efficiently and accurately, and without causing significant safety threat to self or others. The statements made herein are intended to describe the general nature and level of work being performed by employees assigned to this job classification. They are not intended to be construed as an exhaustive and inclusive list of all responsibilities, duties, and/or skills required of personnel so classified.\nGo back\nApply\nShare this job\nEmail\nFacebook\nX\nWeChat\nWhatsApp\nLinkedIn",
        "application_url": "https://jobs.aesc-group.com/en_US/careers/Login?jobId=933&recommendation=&source=&tags=&user=&formValues=",
        "": {},
        "metadata": {
            "Job Title": "Senior Counsel",
            "Ref #": "P1007974",
            "Employment Type": "Permanent",
            "Department": "Legal",
            "Position level": "Specialist",
            "Date": "Thursday, October 23, 2025",
            "AESC Office Location": "Murfreesboro, Tennessee USA"
        },
        "link": "https://jobs.aesc-group.com/en_US/careers/JobDetail/Murfreesboro-Tennessee-United-States-Senior-Counsel/933"
    },
    {
        "title": "Coordinateur HSE (H/F)",
        "description_html": null,
        "description_text": "General information\nJob Title\nCoordinateur HSE (H/F)\nRef #\nP1007533\nEmployment Type\nPermanent\nDepartment\nEnvironmental Health and Safety\nPosition level\nTechnician\nDate\nWednesday, October 1, 2025\nAESC Office Location\nDouai, Hauts-de-France, France\nDescription & Requirements\nJob Description\nMettre en \u0153uvre des actions via la politique de s\u00e9curit\u00e9, d'hygi\u00e8ne et de respect de l'environnement\nConcevoir et suivre les indicateurs\nInstaurer et coordonner syst\u00e8me de management en Sant\u00e9 et S\u00e9curit\u00e9 au Travail (SST).\nD\u00e9ployer la politique de s\u00e9curit\u00e9 pour limiter les accidents de travail, les maladies professionnelles et pr\u00e9server la sant\u00e9 des collaborateurs.\nD\u00e9ployer la politique environnementale\nPr\u00e9venir les risques professionnels et environnementaux\nAssurer des conditions de travail optimales pour les salari\u00e9s et garantir le respect des consignes de s\u00e9curit\u00e9 sur les chantiers (port obligatoire du casque, chaussures de s\u00e9curit\u00e9, etc.).\nGarantir le respect des normes en vigueur, suivre les mises \u00e0 jour des d\u00e9crets r\u00e9glementaires et les appliquer.\nR\u00e9aliser une \u00e9valuation des risques professionnels et chimiques en identifiant les risques potentiels et en conduisant des actions de ma\u00eetrise des risques.\nMettre \u00e0 jour le document unique.\nConduire des audits de chantiers.\nParticiper \u00e0 l'\u00e9laboration et au d\u00e9ploiement des Plans de Pr\u00e9vention (PDP)\nAnalyser les accidents du travail\nSuivre les plans d'actions\nQualifications\nConnaissances des normes et proc\u00e9dures de certification\nMa\u00eetrise des r\u00e9glementations relatives \u00e0 la sant\u00e9, \u00e0 la s\u00e9curit\u00e9 et \u00e0 l'environnement. Vous avez \u00e9galement des comp\u00e9tences avanc\u00e9es en gestion de projet et en r\u00e9solution de probl\u00e8mes.\nExp\u00e9rience en industrie\nExp\u00e9rience en milieu ATEX et risques chimiques\nBon communicant\nAutonome\nTravail en \u00e9quipe\nGo back\nApply\nShare this job\nEmail\nFacebook\nX\nWeChat\nWhatsApp\nLinkedIn",
        "application_url": "https://jobs.aesc-group.com/en_US/careers/Login?jobId=907&recommendation=&source=&tags=&user=&formValues=",
        "": {},
        "metadata": {
            "Job Title": "Coordinateur HSE (H/F)",
            "Ref #": "P1007533",
            "Employment Type": "Permanent",
            "Department": "Environmental Health and Safety",
            "Position level": "Technician",
            "Date": "Wednesday, October 1, 2025",
            "AESC Office Location": "Douai, Hauts-de-France, France"
        },
        "link": "https://jobs.aesc-group.com/en_US/careers/JobDetail/Douai-Hauts-de-Seine-France-Coordinateur-HSE-H-F/907"
    },
    {
        "title": "Ing\u00e9nieur process s\u00e9nior",
        "description_html": null,
        "description_text": "General information\nJob Title\nIng\u00e9nieur process s\u00e9nior\nRef #\nP1005096\nEmployment Type\nPermanent\nDepartment\nEngineering\nPosition level\nExecutive\nDate\nThursday, September 4, 2025\nAESC Office Location\nDouai, Hauts-de-France, France\nDescription & Requirements\nJob Description\n1. Comprendre les exigences techniques et op\u00e9rationnelles de l'entreprise en termes d'\u00e9quipements industriels.\n2. Concevoir et planifier l'implantation des \u00e9quipements industriels en fonction des exigences sp\u00e9cifiques de l'entreprise.\n3. Collaborer avec les fournisseurs pour s'assurer que les \u00e9quipements s\u00e9lectionn\u00e9s r\u00e9pondent aux normes de qualit\u00e9 et de s\u00e9curit\u00e9 requises, ainsi qu'aux d\u00e9lais de livraison convenus.\n4. G\u00e9rer l'ensemble du processus d'implantation des \u00e9quipements industriels, en veillant \u00e0 ce que les d\u00e9lais et les budgets soient respect\u00e9s. Cela peut impliquer la coordination de diff\u00e9rentes \u00e9quipes internes et externes, ainsi que la r\u00e9solution de probl\u00e8mes qui pourraient survenir en cours de route.\n5. Superviser l'installation des \u00e9quipements sur le site de l'entreprise, en veillant \u00e0 ce que tout soit mis en place conform\u00e9ment aux sp\u00e9cifications techniques et aux normes de s\u00e9curit\u00e9.\n6. Fournir une formation aux op\u00e9rateurs et au personnel de maintenance sur l'utilisation et l'entretien des nouveaux \u00e9quipements afin d'assurer une utilisation efficace et s\u00e9curis\u00e9e.\n7. Collaborer avec les \u00e9quipes op\u00e9rationnelles pour identifier et mettre en \u0153uvre des am\u00e9liorations continues des processus li\u00e9s \u00e0 l'utilisation des \u00e9quipements industriels, afin d'optimiser la productivit\u00e9 et l'efficacit\u00e9 globale de l'entreprise\nQualifications\nSavoir faire :\n- Ma\u00eetrise des outils de management\n- Ma\u00eetrise de la suite bureautique MS Office\n- Comp\u00e9tences dans la r\u00e9alisation de dispositions de proc\u00e9d\u00e9 et de la documentation technique\n- Connaissances avanc\u00e9es des processus de production, des m\u00e9thodes et technologies de production\n- Comp\u00e9tences en gestion de projet\n- Niveau ing\u00e9nieur \u00e0 dominante industrielle avec 10 ans d'exp\u00e9riences dans l'installation d'\u00e9quipements complexes\n- Anglais professionnel obligatoire (TOEIC 800 minimum)\nSavoir \u00eatre :\n- Rigueur\n- Autonomie\n- Sens de l'organisation\n- Aisance relationnelle\n- Esprit m\u00e9thodique\nGo back\nApply\nShare this job\nEmail\nFacebook\nX\nWeChat\nWhatsApp\nLinkedIn",
        "application_url": "https://jobs.aesc-group.com/en_US/careers/Login?jobId=822&recommendation=&source=&tags=&user=&formValues=",
        "": {},
        "metadata": {
            "Job Title": "Ing\u00e9nieur process s\u00e9nior",
            "Ref #": "P1005096",
            "Employment Type": "Permanent",
            "Department": "Engineering",
            "Position level": "Executive",
            "Date": "Thursday, September 4, 2025",
            "AESC Office Location": "Douai, Hauts-de-France, France"
        },
        "link": "https://jobs.aesc-group.com/en_US/careers/JobDetail/Douai-Hauts-de-Seine-France-Ing-nieur-process-s-nior/822"
    },
    {
        "title": "EHS Specialist  1-4 (All shifts)",
        "description_html": null,
        "description_text": "General information\nJob Title\nEHS Specialist  1-4 (All shifts)\nRef #\nP1001378\nEmployment Type\nPermanent\nDepartment\nEnvironmental Health and Safety\nPosition level\nSpecialist\nDate\nTuesday, September 2, 2025\nAESC Office Location\nSmyrna, Tennessee USA\nDescription & Requirements\nJob Description\nAbout AESC US LLC\nAESC is a global leader in the development and manufacturing of high-performance batteries for zero-emission electric vehicles and energy storage systems. Founded in Japan in 2007 and headquartered in Yokohama, AESC has been building manufacturing capabilities around the world in the U.S., U.K., Europe, Japan and China to serve key markets and leading customers locally for over 14 years. Today, AESC has become the partner of choice for the world\u2019s leading OEMs and energy storage providers in North America, Europe, and Asia. Its advanced technology powers over one million electric vehicles and provides more than 15GWh of installed capacity for battery energy systems in over 60 countries.\nAESC is expanding its footprint in the United States with gigafactories in Kentucky, South Carolina, and Tennessee to meet the growing demand for EV and BESS batteries and strengthen its presence in the North American market. AESC's Tennessee gigafactory in Smyrna, which has been operational and supplying electric vehicle batteries for the Nissan LEAF since 2012, was retooled in 2025 and now produces batteries for Energy Storage Systems. The South Carolina gigafactory in Florence will supply next generation cells for BMW starting in 2026. The Kentucky gigafactory in Bowling Green will supply high-performance batteries and components for other OEMs. AESC is committed to our local communities where it is making investments, creating jobs, and supporting local charities.\nAbout the Role\nAs the Environmental, Health & Safety Specialist, you will play a critical role in ensuring a safe, compliant, and environmentally responsible workplace at our state-of-the-art battery manufacturing facility. You will collaborate with cross-functional teams to support the development, implementation, and monitoring of EHS programs and initiatives, helping to drive continuous improvement in our gigafactories. You will support the compliance of EHS standards at the local, state, and federal levels, and work to promote a culture of safety and environmental stewardship.\nWhat You Will Do\nEHS Support and Compliance: Provide environmental, health, and safety (EHS) support to plant personnel, ensuring compliance with all applicable environmental, occupational safety, and health regulations.\nEHS Programs: Prepare, update, and maintain written safety, health, and environmental programs and policies, generating applicable metrics for tracking.\nPermit to work (PTW): Serve as the PTW expert, supporting job hazard assessments (JHA), job safety analysis (JSA), risk assessments, and personal protective equipment (PPE) matrix development, as well as auditing permit paperwork for compliance.\nAwareness and Training: Promote EHS awareness by developing and delivering internal company communications, safety training, and specialized EHS programs to the workforce.\nEngineering Collaboration: Support corporate and plant engineering in implementing engineering controls to reduce environmental, safety, and health hazards.\nRegulatory Compliance: Ensure facility compliance with federal, state, and local environmental regulations, covering aspects such as solid waste, hazardous waste, stormwater, air emissions, wastewater, community right-to-know, and petroleum storage.\nIncident Investigation: Review injury/illness reports and non-injury incident investigations, follow up on trends, recommend countermeasures, and support management in action planning.\nSDS Management: Support production areas with submittals of Safety Data Sheets (SDS) to ensure they are electronically maintained in a database to support site compliance with environmental and safety regulations.\nErgonomic Planning: Utilize ergonomic guidelines to address current manufacturing injury concerns and future model planning, contributing to overall employee safety.\nComplete other duties as assigned\nEqual Employment Opportunity\nAt AESC, we are committed to providing Equal Employment Opportunity (EEO) to all individuals. We participate in E-Verify and will provide the federal government with your Form I-9 information to confirm that you are authorized to work in the U.S Join us in our passion to design, manufacture, and sell high-performance products, contributing to a sustainable and zero-carbon emission future.\nPhysical Requirements\nThe physical demands described here are representative of those that must be met by an employee to successfully perform the essential functions of this job. Reasonable accommodation may be made to enable otherwise qualified individuals with disabilities to perform the essential job functions.\nAbility to sit for extended periods of time.\nAbility to read, write, speak, hear; stand; walk; use hands to finger, handle, or feel; reach and lift with hands and arms frequently throughout the day.\nRequired to occasionally lift, push, pull and/or move up to 10 pounds and occasionally required to lift, push, pull and/or move up to 35 pounds.\nWork Environment\nThe work environment is primarily an automated manufacturing plant with a concrete floor and is characterized by some temperature extremes, moderate noise, and forklift traffic. The individual must be able to perform all essential functions as appropriate on the plant floor, in meetings, and with employees, management, customers and suppliers.\nCandidate must perform the essential duties and responsibilities with or without reasonable accommodation efficiently and accurately, and without causing significant safety threat to self or others. The statements made herein are intended to describe the general nature and level of work being performed by employees assigned to this job classification. They are not intended to be construed as an exhaustive and inclusive list of all responsibilities, duties, and/or skills required of personnel so classified.\nHiring is contingent upon successful completion of drug screen and background check. AESC US LLC is a drug-free workplace.\nQualifications\nWhat You Need\nEducation: Bachelor's degree in safety science, engineering, or industrial engineering discipline is preferred.\nExperience: 2-5 years of experience supporting safety, health, and environmental operations within a manufacturing or production environment.\nTechnical Knowledge:\nLife Safety Design: Familiarity with IBC/IFC/NFPA101 for life safety design requirements.\nTitle V Air Permit: Experience with compliance, conditions, and tracking of CFC inventory logs, RICE MACT generator data logs, and chemical tracking.\nRCRA Compliance: Knowledge of hazardous waste regulations pertaining to Large Quantity Generators (LQGs) and management of hazardous waste tank systems.\nEPCRA Compliance: Knowledge of Tier 2 Reports, Toxic Release Inventory Reports, and other reporting requirements for industrial facilities.\nCross-Functional Collaboration: Proven ability to work cross-functionally with teams in Operations, Maintenance, Logistics, Engineering, and Quality.\nState and Federal Safety Standards: Extensive knowledge of state and federal safety standards and a working knowledge of the company\u2019s manufacturing processes.\nUnderstands and follows all standards of IATF16949 and VDA 6.3 quality standards. (training and awareness will be provided for those who are not familiar with these standards)\nUnderstands and follows all standards of ISO14001 environmental standards. (training and awareness will be provided for those who are not familiar with these standards)\nTravel Requirements\nOccasional domestic travel to other gigafactory locations or regional compliance meetings may be required.\nGo back\nApply\nShare this job\nEmail\nFacebook\nX\nWeChat\nWhatsApp\nLinkedIn",
        "application_url": "https://jobs.aesc-group.com/en_US/careers/Login?jobId=351&recommendation=&source=&tags=&user=&formValues=",
        "": {},
        "metadata": {
            "Job Title": "EHS Specialist  1-4 (All shifts)",
            "Ref #": "P1001378",
            "Employment Type": "Permanent",
            "Department": "Environmental Health and Safety",
            "Position level": "Specialist",
            "Date": "Tuesday, September 2, 2025",
            "AESC Office Location": "Smyrna, Tennessee USA"
        },
        "link": "https://jobs.aesc-group.com/en_US/careers/JobDetail/Smyrna-Tennessee-United-States-EHS-Specialist-1-4-All-shifts/351"
    },
    {
        "title": "Technicien M\u00e9trologie",
        "description_html": null,
        "description_text": "General information\nJob Title\nTechnicien M\u00e9trologie\nRef #\n20001469\nEmployment Type\nPermanent\nDepartment\nQuality\nPosition level\nTechnician\nDate\nThursday, August 21, 2025\nAESC Office Location\nDouai, Hauts-de-France, France\nDescription & Requirements\nJob Description\nPr\u00eat(e) \u00e0 relever les d\u00e9fis d\u2019une mobilit\u00e9 plus respectueuse de l\u2019environnement ? Rejoignez AESC et devenez un acteur cl\u00e9 dans le d\u00e9veloppement et la production de batteries lithium-ion \u00e0 haute performance !\nEn tant que technicien en m\u00e9trologie / MSA (Measurement System Analysis), vous serez rattach\u00e9(e) au Responsable M\u00e9trologue au sein du site de Douai class\u00e9 SEVESO seuil haut. Nous vous proposons un poste polyvalent qui vous permettra de mettre \u00e0 profit vos connaissances mais aussi monter en comp\u00e9tences dans un environnement industriel automobile.\nLe technicien MSA a la charge de l\u2019\u00e9valuation des syst\u00e8mes de mesure utilis\u00e9s dans le cadre du contr\u00f4le qualit\u00e9. Il r\u00e9alise les \u00e9tudes MSA afin de garantir la fiabilit\u00e9, la r\u00e9p\u00e9tabilit\u00e9 et la reproductibilit\u00e9 des instruments de mesure utilis\u00e9s dans les processus de fabrication et de contr\u00f4le.\nVos futures missions\n:\nPlanifier, piloter, r\u00e9aliser et \u00eatre moteur sur les activit\u00e9s des MSA (Gage R&R, lin\u00e9arit\u00e9, biais, stabilit\u00e9, Cg, Cgk\u2026),\nFaire un suivi des activit\u00e9s de MSA,\nIdentifier les sources de variation dans les syst\u00e8mes de mesure,\nAnalyser les r\u00e9sultats et r\u00e9diger les rapports associ\u00e9s,\nMise \u00e0 jour des indicateurs MSA,\nProposer des actions correctives en cas de non-conformit\u00e9 du syst\u00e8me de mesure,\nCollaborer avec les \u00e9quipes de Production, Qualit\u00e9, Ing\u00e9nieur Process et M\u00e9trologie,\nAssurer la mise \u00e0 jour des documents techniques et proc\u00e9dures internes,\nFormer les op\u00e9rateurs aux bonnes pratiques de mesure si n\u00e9cessaire,\nR\u00e9aliser les activit\u00e9s li\u00e9es aux MSA des appareils en respectant les r\u00e8gles d'hygi\u00e8ne et de s\u00e9curit\u00e9 lors des interventions, les d\u00e9lais et les proc\u00e9dures en vigueur,\n\u00catre force de proposition aupr\u00e8s des ing\u00e9nieurs process et responsables Qualit\u00e9 pour remonter les probl\u00e8mes rencontr\u00e9s,\nContribuer \u00e0 l'am\u00e9lioration continue de l'usine.\nQualifications\nQualifications, ce qui vous diff\u00e9rencie :\nFormation Bac+2 minimum en mesures physiques, qualit\u00e9, m\u00e9trologie ou domaine technique \u00e9quivalent,\nExp\u00e9rience en MSA souhait\u00e9e,\nMa\u00eetrise des outils qualit\u00e9 (MSA, SPC, AMDEC, etc.),\nConnaissance des normes ISO 9001, IATF 16949 (automobile),\nMa\u00eetrise des logiciels statistiques (Minitab, Excel avec macros, etc.)\nRigueur, autonomie, esprit d\u2019analyse et bon relationnel\nDe formation sup\u00e9rieure de niveau Bac +2 / 3 type Licence en M\u00e9trologie. Vous avez au minimum une premi\u00e8re exp\u00e9rience r\u00e9ussie sur un poste similaire dans le domaine industriel, id\u00e9alement dans l\u2019automobile. Vous avez des connaissances dans les domaines de la m\u00e9trologie: en \u00e9talonnage, v\u00e9rification, incertitude de mesure, EMT, capabilit\u00e9, MSA, \u2026 Vous avez d\u00e9montr\u00e9 dans vos exp\u00e9riences, votre esprit d\u2019analyse, votre sens de la communication et une aisance dans le travail collaboratif.\nComp\u00e9tences particuli\u00e8res recherch\u00e9es\n:\nExp\u00e9rience dans l\u2019automobile :\nIATF 16949 / APQP / PPAP / MSA / SPC / PFMEA,\nAMDEC Process\nMaitrise du plan de control.\nMaitrise du suivi des KPI, tableau de bord\nConnaissance des normes IATF/45001/14001/17025.\nAutonome, rigoureux, force de proposition\nConnaissance m\u00e9trologie analytique et instrumentation\nPossibilit\u00e9 poste en travail post\u00e9 3/8\n#LI-EO1\nGo back\nApply\nShare this job\nEmail\nFacebook\nX\nWeChat\nWhatsApp\nLinkedIn",
        "application_url": "https://jobs.aesc-group.com/en_US/careers/Login?jobId=813&recommendation=&source=&tags=&user=&formValues=",
        "": {},
        "metadata": {
            "Job Title": "Technicien M\u00e9trologie",
            "Ref #": "20001469",
            "Employment Type": "Permanent",
            "Department": "Quality",
            "Position level": "Technician",
            "Date": "Thursday, August 21, 2025",
            "AESC Office Location": "Douai, Hauts-de-France, France"
        },
        "link": "https://jobs.aesc-group.com/en_US/careers/JobDetail/Lambres-lez-Douai-Nord-France-Technicien-M-trologie/813"
    },
    {
        "title": "Engineer MES",
        "description_html": null,
        "description_text": "General information\nJob Title\nEngineer MES\nRef #\n20001465\nEmployment Type\nPermanent\nDepartment\nInformation Technology\nPosition level\nEngineer\nDate\nTuesday, August 12, 2025\nAESC Office Location\nDouai, Hauts-de-France, France\nDescription & Requirements\nJob Description\nJoin AESC, a global leader in lithium-ion battery technology, and become a key player in the development and production of high-performance batteries.\nAs part of our expansion in France, we are recruiting a MES (Manufacturing Execution System) Engineer for our new site in Lambres-lez-Douai.\nThe purpose of the MES:\n\u00b7 MES application is running 24/7 (Maintenance period 4h on Sat and 4h on Sun)\n\u00b7 MES ensure full traceability of production data.\n\u00b7 MES Capture information at every stage of the manufacturing process and trigger next stage.\n\u00b7 MES manage scheduling and production tracking.\nYou will play a pivotal role in deploying and ensuring the smooth operation of MES systems in our state-of-the-art facility.\nKey Responsibilities\n\u00b7 Coordinate hardware, software, and communication protocols between MES developments from Japan and China, and local equipment suppliers.\n\u00b7 Oversee and validate the work of the local MES integrator, including system deployment.\n\u00b7 Ensure all MES interfaces are properly integrated, including connections with production equipment and other systems (SAP, PLM, Maintenance).\n\u00b7 Manage and align testing, integration, and qualification phases.\n\u00b7 Provide regular progress reports and highlight critical issues.\n\u00b7 Collaborate with MES counterparts in the other countries to leverage lessons learned from ongoing projects.\n\u00b7 Coordinate with IT colleagues, especially those responsible for networks and data centers.\n\u00b7 Proactively propose actions to mitigate risks.\n\u00b7 Prepare post-deployment support and system maintenance strategies.\n\u00b7 Drive all necessary actions to ensure successful MES deployment and meet project objectives.\n\u00b7 Support company growth and adapt to evolving organizational needs.\n\u00b7 The MES Engineer may be required to participate in on-call duty to support system operations outside regular working hours. (1 Week per month)\nQualifications\nRequired Skills & Experience\n\u00b7 Fluent in English (French is not mandatory).\n\u00b7 Proven experience in international project management.\n\u00b7 Strong background in MES deployment in industrial environments (preferably DELMIA APRISO).\n\u00b7 Expertise in industrial control systems (various PLC brands).\n\u00b7 In-depth knowledge of industrial communication protocols.\nKey Competencies\n\u00b7 Strategic and analytical mindset.\n\u00b7 Resilience in solving complex, diverse challenges.\n\u00b7 Precision and reliability.\n\u00b7 Adaptability and flexibility.\n\u00b7 Strong organizational skills and autonomy.\n\u00b7 Curiosity and ability to work in multicultural, matrixed teams.\n\u00b7 Excellent communication, teaching, and interpersonal skills.\n\u00b7 Proactive and solution-oriented.\nPosition Requirements\n\u00b7 Engineering degree in industrial automation or IT.\n\u00b7 Minimum 5 years of experience on MES project deployment.\n\u00b7 Experience in international, matrixed industrial environments.\n\u00b7 Working language: English.\n#LI-EO1\nGo back\nApply\nShare this job\nEmail\nFacebook\nX\nWeChat\nWhatsApp\nLinkedIn",
        "application_url": "https://jobs.aesc-group.com/en_US/careers/Login?jobId=798&recommendation=&source=&tags=&user=&formValues=",
        "": {},
        "metadata": {
            "Job Title": "Engineer MES",
            "Ref #": "20001465",
            "Employment Type": "Permanent",
            "Department": "Information Technology",
            "Position level": "Engineer",
            "Date": "Tuesday, August 12, 2025",
            "AESC Office Location": "Douai, Hauts-de-France, France"
        },
        "link": "https://jobs.aesc-group.com/en_US/careers/JobDetail/Lambres-lez-Douai-Nord-France-Engineer-MES/798"
    },
    {
        "title": "SAP Engineer \u2013 Modules MM/PP/SD/EWM",
        "description_html": null,
        "description_text": "General information\nJob Title\nSAP Engineer \u2013 Modules MM/PP/SD/EWM\nRef #\n20001466\nEmployment Type\nPermanent\nDepartment\nInformation Technology\nPosition level\nEngineer\nDate\nTuesday, August 12, 2025\nAESC Office Location\nDouai, Hauts-de-France, France\nDescription & Requirements\nJob Description\nContext and Mission\nAs part of strengthening our IT team and optimizing our business processes, we are looking for an experienced SAP Engineer, capable of designing, configuring, and managing projects related to the MM (Purchasing and Inventory Management), PP (Production Planning), SD (Sales and Distribution), and EWM (Extended Warehouse Management) modules. The SAP Engineer will play a key role in implementing SAP solutions, supporting users, and managing functional developments.\nMain Responsibilities\n\u00b7 \u2022 Analyze business needs and write functional and technical specifications.\n\u00b7 \u2022 Configure SAP MM/PP/SD/EWM modules according to business requirements.\n\u00b7 \u2022 Participate in deployment, migration, or continuous improvement projects.\n\u00b7 \u2022 Manage interfaces with various systems connected to SAP (MES, EDI, PLM, etc.).\n\u00b7 \u2022 Provide level 2/3 support and incident resolution.\n\u00b7 \u2022 Collaborate with business teams, technical teams, and external partners.\n\u00b7 \u2022 Conduct unit and integration tests, and assist users during acceptance phases.\n\u00b7 \u2022 Document implemented solutions and train key users.\nQualifications\nRequired Profile\n\u00b7 \u2022 Higher education in computer science, engineering, or equivalent.\n\u00b7 \u2022 Significant experience (minimum 5 years) with SAP, with expertise in MM, PP, SD, and EWM modules.\n\u00b7 \u2022 Good understanding of industrial, logistics, and supply chain business processes.\n\u00b7 \u2022 Ability to work in project mode, with rigor and autonomy.\n\u00b7 \u2022 Excellent communication and analytical skills.\n\u00b7 \u2022 Working language: English\nAdditional Assets\n\u00b7 \u2022 Experience in an international matrix industrial environment.\n\u00b7 \u2022 Knowledge of S/4HANA.\n\u00b7 \u2022 SAP certification.\n\u00b7 \u2022 Proficiency in project management tools (JIRA, MS Project, etc.).\n#LI-EO1\nGo back\nApply\nShare this job\nEmail\nFacebook\nX\nWeChat\nWhatsApp\nLinkedIn",
        "application_url": "https://jobs.aesc-group.com/en_US/careers/Login?jobId=799&recommendation=&source=&tags=&user=&formValues=",
        "": {},
        "metadata": {
            "Job Title": "SAP Engineer \u2013 Modules MM/PP/SD/EWM",
            "Ref #": "20001466",
            "Employment Type": "Permanent",
            "Department": "Information Technology",
            "Position level": "Engineer",
            "Date": "Tuesday, August 12, 2025",
            "AESC Office Location": "Douai, Hauts-de-France, France"
        },
        "link": "https://jobs.aesc-group.com/en_US/careers/JobDetail/Lambres-lez-Douai-Nord-France-SAP-Engineer-Modules-MM-PP-SD-EWM/799"
    },
    {
        "title": "SAP Engineer \u2013 FI CO Modules",
        "description_html": null,
        "description_text": "General information\nJob Title\nSAP Engineer \u2013 FI CO Modules\nRef #\n20001463\nEmployment Type\nPermanent\nDepartment\nInformation Technology\nPosition level\nExecutive\nDate\nWednesday, August 6, 2025\nAESC Office Location\nDouai, Hauts-de-France, France\nDescription & Requirements\nJob Description\nReporting Line:\nIT Director France\nContext and Mission\nAs part of strengthening our IT team and optimizing our business processes, we are looking for an experienced SAP Engineer capable of designing, configuring, and managing projects related to the FICO (Financial Accounting and Controlling) modules.The SAP Engineer will play a key role in implementing SAP solutions, supporting users, and managing functional developments.\nMain Responsibilities\n\u2022 Analyze business needs and write functional and technical specifications.\n\u2022 Configure SAP FICO modules according to business requirements.\n\u2022 Participate in deployment, migration, and continuous improvement projects.\n\u2022 Manage interfaces with systems connected to SAP (e.g., EDI, third-party financial systems).\n\u2022 Provide level 2/3 support and resolve incidents.\n\u2022 Collaborate with business teams, technical teams, and external partners.\n\u2022 Perform unit and integration testing, and support users during acceptance phases.\n\u2022 Document implemented solutions and train key users.\nProfile Required\n\u2022 Higher education in IT, engineering, or equivalent.\n\u2022 Minimum 5 years of significant experience with SAP, with expertise in FICO modules.\n\u2022 Good understanding of financial and controlling processes.\n\u2022 Ability to work on IFRS and Secondary Ledgers standards.\n\u2022 Ability to work in project mode with rigor and autonomy.\n\u2022 Excellent communication and analytical skills.\n\u2022 Working language: English\nAdditional Assets\n\u2022 Experience in an international industrial matrix environment.\n\u2022 Knowledge of S/4HANA.\n\u2022 SAP certification.\n\u2022 Proficiency in project management tools (JIRA, MS Project, etc.).\n#LI-EO1\nQualifications\nx\nGo back\nApply\nShare this job\nEmail\nFacebook\nX\nWeChat\nWhatsApp\nLinkedIn",
        "application_url": "https://jobs.aesc-group.com/en_US/careers/Login?jobId=793&recommendation=&source=&tags=&user=&formValues=",
        "": {},
        "metadata": {
            "Job Title": "SAP Engineer \u2013 FI CO Modules",
            "Ref #": "20001463",
            "Employment Type": "Permanent",
            "Department": "Information Technology",
            "Position level": "Executive",
            "Date": "Wednesday, August 6, 2025",
            "AESC Office Location": "Douai, Hauts-de-France, France"
        },
        "link": "https://jobs.aesc-group.com/en_US/careers/JobDetail/Lambres-lez-Douai-Hauts-de-France-France-Nord-France-SAP-Engineer-FI-CO-Modules/793"
    },
    {
        "title": "Team Leader Utilit\u00e9s",
        "description_html": null,
        "description_text": "General information\nJob Title\nTeam Leader Utilit\u00e9s\nRef #\n20001462\nEmployment Type\nPermanent\nDepartment\nManufacturing\nPosition level\nTechnician\nDate\nThursday, July 31, 2025\nAESC Office Location\nDouai, Hauts-de-France, France\nDescription & Requirements\nJob Description\n\u267b\ufe0f Pr\u00eat(e) \u00e0 relever les d\u00e9fis d\u2019une mobilit\u00e9 plus respectueuse de\nl\u2019environnemen\nt ? \u267b\ufe0f\ud83c\udf0d\nRejoignez AESC Douai et devenez un acteur cl\u00e9 dans le d\u00e9veloppement et la production de batteries lithium-ion haute performance.\nDans le cadre de son implantation en France, AESC recrute pour le site de\nLambres-lez-Do\nuai\nLe team leader de maintenance Facilities senior est responsable de l\u2019animation d\u2019une \u00e9quipe de maintenance. Son \u00e9quipe a la charge de la maintenance pr\u00e9visionnelle, pr\u00e9ventive et corrective des \u00e9quipements de leur secteur et des b\u00e2timents et d\u2019en am\u00e9liorer la disponibilit\u00e9. Il prend en compte les contraintes de co\u00fbts, de qualit\u00e9 et de d\u00e9lais de l\u2019entreprise. Il r\u00e9alise ses activit\u00e9s en totale autonomie.\nAnimer l\u2019\u00e9quipe et planifier les activit\u00e9s sur les outils\n\u00b7 Mettre en \u0153uvre les indicateurs de suivi de l\u2019\u00e9quipe (MTBF ; MTTR ; Taux de r\u00e9alisation des pr\u00e9ventifs ; \u2026) avec son superviseur et les piloter\n\u00b7 Collecter les informations des pannes et de conduite sur les utilit\u00e9s et les b\u00e2timents\n\u00b7 Conduire et/ou accompagner l\u2019analyse et la r\u00e9solution des pannes sur les installations. D\u00e9terminer les solutions techniques et les conditions de remise en \u00e9tat des \u00e9quipements et/ou de retour aux valeurs de consignes\n\u00b7 Assurer le respect des op\u00e9rations d\u2019inspection, de pr\u00e9ventif, de curatif sur les \u00e9quipements avec respect strict des r\u00e8gles de s\u00e9curit\u00e9 et environnementales\n\u00b7 Assurer le respect des attendus r\u00e9glementaires concernant les \u00e9quipements et les b\u00e2timents rattach\u00e9s \u00e0 son d\u00e9partement au travers d'activit\u00e9s pr\u00e9ventives en priorit\u00e9 et curative le cas \u00e9ch\u00e9ant\n\u00b7 Planifier et encadrer des interventions de mise en conformit\u00e9 et d\u2019am\u00e9lioration\n\u00b7 Suivre les co\u00fbts g\u00e9n\u00e9r\u00e9s par son \u00e9quipe\n\u00b7 Piloter le passage des informations avec les interlocuteurs de son p\u00e9rim\u00e8tre\n\u00b7 R\u00e9aliser des comptes-rendus d\u2019intervention et piloter la tra\u00e7abilit\u00e9 pour l\u2019historisation\n\u00b7 Encadrer la bonne utilisation de la GMAO / EAM\n\u00b7 Participer \u00e0 et/ou dispenser des formations et des programmes de d\u00e9veloppement professionnel pour am\u00e9liorer ses comp\u00e9tences, sa connaissance des \u00e9quipements et celles de son \u00e9quipe\n\u00b7 Construire et diriger un plan de formation pour son \u00e9quipe en accord avec son superviseur / service formation\n\u00b7 Participer \u00e0 la r\u00e9daction et la mise \u00e0 jour des proc\u00e9dures, standards et modules de formation du d\u00e9partement maintenance\n\u00b7 Promouvoir l\u2019am\u00e9lioration continue et le perfectionnement des process de fabrication, de maintenance des \u00e9quipements et de gestion de l\u2019activit\u00e9 industrielle\n\u00b7 Valider la qualit\u00e9 de l\u2019intervention de son \u00e9quipe avec les \u00e9quipes de production pour la remise \u00e0 disposition des \u00e9quipements\n\u00b7 Promouvoir la s\u00e9curit\u00e9 afin qu\u2019elle soit toujours la priorit\u00e9 num\u00e9ro une de la culture d\u2019AESC ; promouvoir un environnement de travail s\u00fbr pour lui et l\u2019ensemble des salari\u00e9s en suivant tous les programmes et directives de l\u2019entreprise\n\u00b7 Appliquer tous les processus et proc\u00e9dures conform\u00e9ment aux directives de l\u2019entreprise\nRequirements / Required skills\nBuilding Maintenance\nQualifications\nPneumatique/Hydraulique/M\u00e9canique : Capacit\u00e9 \u00e0 lire des sch\u00e9mas/plans, \u00e0 comprendre les concepts de puissance des fluides/ la logique d\u2019assemblage.\n\u00b7 Maintenance \u00e9lectrique : capacit\u00e9 \u00e0 lire des plans, \u00e0 comprendre et d\u00e9panner les installations basses tension et \u00e0 r\u00e9aliser des travaux haute tension.\n\u00b7 Automates programmables (PLC) : La connaissance et la capacit\u00e9 de d\u00e9panner, extraire, modifier et cr\u00e9er si n\u00e9cessaire des programmes.\n\u00b7 Maintenance du b\u00e2timent : capacit\u00e9 \u00e0 lire des plans, \u00e0 comprendre et \u00e0 conduire et d\u00e9panner des installations de nature CVC, chaufferie, distribution de fluides, \u2026\n\u00b7 Ma\u00eetrise des outils de r\u00e9solution de probl\u00e8me\n\u00b7 \u00catre r\u00e9f\u00e9rent dans un ou plusieurs domaines techniques\n\u00b7 Connaissance du process de son p\u00e9rim\u00e8tre d\u2019action\n\u00b7 Capacit\u00e9 \u00e0 utiliser correctement les outils de mesure appropri\u00e9s\n\u00b7 Ma\u00eetrise de la suite Office et des logiciels de bureautique de base\n\u00b7 Capacit\u00e9 \u00e0 utiliser efficacement les logiciels \u00e0 disposition pour saisir des donn\u00e9es et rechercher des pi\u00e8ces.\n\u00b7 Capacit\u00e9 \u00e0 comprendre une documentation technique en anglais\n\u00b7 Capacit\u00e9 \u00e0 remplacer son Superviseur de fa\u00e7on ponctuelle, sur demande du Manager\n\u00b7 Capacit\u00e9 \u00e0 supporter son Superviseur dans la pr\u00e9paration d\u2019entretiens\nPostulez, notre \u00e9quipe prendra le soin de vous recontacter pour vous pr\u00e9senter le poste et r\u00e9pondre \u00e0 vos questions.\n#li-eo1\nGo back\nApply\nShare this job\nEmail\nFacebook\nX\nWeChat\nWhatsApp\nLinkedIn",
        "application_url": "https://jobs.aesc-group.com/en_US/careers/Login?jobId=791&recommendation=&source=&tags=&user=&formValues=",
        "": {},
        "metadata": {
            "Job Title": "Team Leader Utilit\u00e9s",
            "Ref #": "20001462",
            "Employment Type": "Permanent",
            "Department": "Manufacturing",
            "Position level": "Technician",
            "Date": "Thursday, July 31, 2025",
            "AESC Office Location": "Douai, Hauts-de-France, France"
        },
        "link": "https://jobs.aesc-group.com/en_US/careers/JobDetail/Nord-France-Team-Leader-Utilit-s/791"
    },
    {
        "title": "Sp\u00e9cialiste APS (AESC Production System) / CIP (Continuous Improvement Program)",
        "description_html": null,
        "description_text": "General information\nJob Title\nSp\u00e9cialiste APS (AESC Production System) / CIP (Continuous Improvement Program)\nRef #\n20001461\nEmployment Type\nPermanent\nDepartment\nCorporate & Business Services\nPosition level\nSpecialist\nDate\nMonday, July 28, 2025\nAESC Office Location\nDouai, Hauts-de-France, France\nDescription & Requirements\nJob Description\nMissions g\u00e9n\u00e9rales / Objectif du poste\nEn tant que leader APS, travailler avec les \u00e9quipes Production, Maintenance, Qualit\u00e9, PE et l\u2019\u00e9quipe APS globale pour promouvoir les activit\u00e9s de standardisation et d\u2019am\u00e9lioration continue, et piloter les actions d\u2019am\u00e9lioration de la performance de production du site de Douai.\nDescription des activit\u00e9s\nG\u00e9rer les indicateurs de performance de l\u2019usine (BSC, PIW, et toute donn\u00e9e n\u00e9cessaire pour l\u2019Obeya ou les r\u00e9unions de direction).\nOrganiser la planification des activit\u00e9s de standardisation et d\u2019am\u00e9lioration continue via des audits internes sur le terrain (shopfloor).\nParticiper aux activit\u00e9s globales APS concernant la mise \u00e0 jour et la validation des standards EPF, la mise en place de supports de formation, les projets usine digitale, l\u2019introduction du CIP, etc., en communiquant en anglais.\nPromouvoir la culture 5S et superviser sa mise en \u0153uvre efficace.\nResponsabilit\u00e9s hi\u00e9rarchiques / Animation de projets\nCe poste est rattach\u00e9 au sp\u00e9cialiste APS (\u00e9quivalent responsable de production).\nOrganiser et animer les DMD (Daily Management Diagnosis) en tant qu\u2019auditeur.\nOrganiser et animer les r\u00e9unions d\u2019\u00e9quipe et piloter les projets d\u2019am\u00e9lioration continue.\nRelations de travail internes / externes\nINTERNE :\nTous les d\u00e9partements et responsables\nSuperviseurs Production, Maintenance, Qualit\u00e9, Supply Chain, \u00e9quipe IE\n\u00c9quipe APS globale (\u00c9tats-Unis) et sp\u00e9cialistes APS des autres sites AESC (US, UK, CH, JP, etc.)\nEXTERNE :\nAuditeurs\nComp\u00e9tences professionnelles sp\u00e9cifiques\nConnaissance g\u00e9n\u00e9rale d\u2019un site de production\nGestion des indicateurs (KPI)\nGestion des comp\u00e9tences op\u00e9rationnelles\nPlanification\nManagement d\u2019\u00e9quipe\nMa\u00eetrise du Pack Office et des logiciels bureautiques de base\nAnglais technique\nSoft skills requises\nSens de la s\u00e9curit\u00e9\nP\u00e9dagogie\nEsprit d\u2019analyse\nSens de l\u2019organisation\nAttitude positive\nAisance relationnelle\nLeadership\nGestion du stress\nExigences du poste\nPlus de 10 ans d\u2019exp\u00e9rience en management d\u2019\u00e9quipe\nDipl\u00f4me de type Bac +2\nExp\u00e9rience de d\u00e9placements professionnels en France et \u00e0 l\u2019international (ponctuels)\nCapacit\u00e9 \u00e0 respecter les obligations de confidentialit\u00e9\nCapacit\u00e9 \u00e0 travailler en horaires post\u00e9s\n#LI-EO1\nQualifications\nGeneral missions / purpose\nAs an APS leader, work with Production, Maintenance, Quality Assurance, PE and Global APS team to promote standardization and continuous improvement activities and lead the improvement of production activities at the Douai plant.\nDescription of activities\nManage the plant performance indicators (BSC, PIW, and any required data release for Obeya and any senior management meeting materials.)\nOrganize standardization scheduling and continuous improvement activity through internal audit at the shop floor field.\nParticipate into Global APS activities for EPF standards update preview and validation, introduce training material, digital factory activity, CIP introduction etc. with communicating by English language.\nPromote the 5S culture and oversee its successful implementation\nHierarchical responsibility/project for animation\nThis position refers to the APS specialist (equivalent as production manager)\nOrganize and lead DMD (Daily management Diagnosis) as auditor\nOrganize and lead team meetings and manage continuous improvement projects.\nInternal/external working relationships\nINTERNAL\n:\nAll Department and management head members\nProduction, Maintenance, QA, SCM supervisors, IE team\nGlobal APS team (US) and APS specialist in the other AESC plant (US, UK, CH, JP etc.)\nEXTERNAL:\nAuditors\nSpecific professional knowledge\nGeneral production plant/factory knowledge\nKPI management\nOperation Skill management\nPlanning\nTeam management\nProficiency in the Office suite and basic office software\nTechnical English\nRequired soft skills\nEnsuring safety\n-\nDemonstrating pedagogy\n-\nAnalytical skills\n-\nOrganization\n-\nPositivity\n-\nInterpersonal skills\n-\nLeadership\n-\nStress management\nJob Requirements\n10+ years of experience in team management\n-\n2-year professional degree\n-\nDomestic and international business trip experience (irregular)\n-\nAbility to respect confidentiality obligations\n-\nAbility to work in a shift team\n#LI-EO1\nGo back\nApply\nShare this job\nEmail\nFacebook\nX\nWeChat\nWhatsApp\nLinkedIn",
        "application_url": "https://jobs.aesc-group.com/en_US/careers/Login?jobId=790&recommendation=&source=&tags=&user=&formValues=",
        "": {},
        "metadata": {
            "Job Title": "Sp\u00e9cialiste APS (AESC Production System) / CIP (Continuous Improvement Program)",
            "Ref #": "20001461",
            "Employment Type": "Permanent",
            "Department": "Corporate & Business Services",
            "Position level": "Specialist",
            "Date": "Monday, July 28, 2025",
            "AESC Office Location": "Douai, Hauts-de-France, France"
        },
        "link": "https://jobs.aesc-group.com/en_US/careers/JobDetail/Lambres-les-Douai-Nord-France-Sp-cialiste-APS-AESC-Production-System-CIP-Continuous-Improvement-Program/790"
    },
    {
        "title": "Technicien m\u00e9trologue/Technicienne m\u00e9trologue",
        "description_html": null,
        "description_text": "General information\nJob Title\nTechnicien m\u00e9trologue/Technicienne m\u00e9trologue\nRef #\n20001399\nEmployment Type\nPermanent\nDepartment\nQuality\nPosition level\nTechnician\nDate\nSunday, February 23, 2025\nAESC Office Location\nDouai, Hauts-de-France, France\nDescription & Requirements\nJob Description\n\ud83c\udf0d\u267b\ufe0f\nPr\u00eat(e) \u00e0 relever les d\u00e9fis d\u2019une mobilit\u00e9 plus respectueuse de l\u2019environnement ?\n\u267b\ufe0f\ud83c\udf0d\nRejoignez AESC et devenez un acteur cl\u00e9 dans le d\u00e9veloppement et la production de batteries lithium-ion haute performance !\nDans le cadre de notre implantation en France, AESC recrute un(e)\nTechnicien M\u00e9trologue (H/F)\npour le site de Douai, class\u00e9 SEVESO seuil haut. Ce poste polyvalent vous permettra de mettre \u00e0 profit vos connaissances tout en \u00e9voluant dans un environnement industriel automobile dynamique.\n\ud83c\udfaf T\u00e2ches essentielles et responsabilit\u00e9s :\nLa description suivante du travail \u00e0 effectuer ne se veut pas exhaustive. Elle met plut\u00f4t l'accent sur les principales t\u00e2ches qui doivent \u00eatre accomplies :\nR\u00e9aliser les activit\u00e9s li\u00e9es \u00e0 la m\u00e9trologie des appareils (interventions techniques : production et laboratoires) en respectant les r\u00e8gles d'hygi\u00e8ne et de s\u00e9curit\u00e9, les d\u00e9lais et les proc\u00e9dures en vigueur.\n\u00catre force de proposition aupr\u00e8s des ing\u00e9nieurs process pour remonter les mises \u00e0 jour de proc\u00e9dures.\nD\u00e9finir les modes op\u00e9ratoires de v\u00e9rification des appareils de mesure.\nApporter un soutien au Responsable M\u00e9trologie pour le service QHSE en suivant le registre de maintenance.\nContribuer \u00e0 l'am\u00e9lioration continue de l'usine.\nParticiper \u00e0 des projets relatifs \u00e0 la m\u00e9trologie.\n\u00catre moteur pour l'ex\u00e9cution des MSA (R&R) et capabilit\u00e9 (Cg et Cgk).\nRequirements / Required skills\nCapability Assessment\nQualifications\n\ud83d\udcbc\nSavoir-faire requis :\nFormation Bac +2/3 type Licence en M\u00e9trologie.\nPremi\u00e8re exp\u00e9rience r\u00e9ussie sur un poste similaire dans le domaine industriel, id\u00e9alement dans l\u2019automobile.\nConnaissances solides en m\u00e9trologie : \u00e9talonnage, v\u00e9rification, incertitude de mesure, EMT, capabilit\u00e9, etc.\nMa\u00eetrise des normes IATF 16949, APQP, PPAP, MSA, SPC, PFMEA, AMDEC Process.\nMa\u00eetrise du plan de contr\u00f4le et des m\u00e9thodes de r\u00e9solution de probl\u00e8mes.\nComp\u00e9tence dans le suivi des KPI et tableaux de bord.\nExp\u00e9rience avec les outils informatiques comme SAP et connaissances des normes IATF/45001/14001/17025.\n?\nSavoir-\u00eatre requis :\nAutonome, rigoureux et force de proposition.\nExcellent esprit d\u2019analyse et communication.\nAisance dans le travail collaboratif.\n\u2705\nExigences du poste :\nPoste en travail post\u00e9 3*8.\nConnaissance en m\u00e9trologie dimensionnelle, analytique et instrumentation.\n\ud83d\udce9\nInt\u00e9ress\u00e9(e) ?\nPostulez d\u00e8s maintenant et participez \u00e0 la construction d\u2019un avenir plus propre et plus durable avec AESC ! \ud83c\udf0d\ud83d\udd0b\n#LI-SD2\nGo back\nApply\nShare this job\nEmail\nFacebook\nX\nWeChat\nWhatsApp\nLinkedIn",
        "application_url": "https://jobs.aesc-group.com/en_US/careers/Login?jobId=308&recommendation=&source=&tags=&user=&formValues=",
        "": {},
        "metadata": {
            "Job Title": "Technicien m\u00e9trologue/Technicienne m\u00e9trologue",
            "Ref #": "20001399",
            "Employment Type": "Permanent",
            "Department": "Quality",
            "Position level": "Technician",
            "Date": "Sunday, February 23, 2025",
            "AESC Office Location": "Douai, Hauts-de-France, France"
        },
        "link": "https://jobs.aesc-group.com/en_US/careers/JobDetail/Lambres-lez-Douai-Hauts-de-France-France-Nord-France-Technicien-m-trologue-Technicienne-m-trologue/308"
    },
    {
        "title": "Responsable Comptabilit\u00e9",
        "description_html": null,
        "description_text": "General information\nJob Title\nResponsable Comptabilit\u00e9\nRef #\n20001400\nEmployment Type\nPermanent\nDepartment\nFinance\nPosition level\nManager\nDate\nSunday, February 23, 2025\nAESC Office Location\nDouai, Hauts-de-France, France\nDescription & Requirements\nJob Description\nR\u00f4les et responsabilit\u00e9s\n- Organiser et pr\u00e9parer les cl\u00f4tures mensuelles/annuelles, en respectant des d\u00e9lais de reporting serr\u00e9s.\n- Identifier et ajuster les diff\u00e9rences entre IFRS and GAAP Fran\u00e7ais\n- D\u00e9velopper de nouveaux processus pour les nouveaux business sc\u00e9narios\n- Constituer la r\u00e9conciliation avec les intercompanies (mat\u00e9riel premier et les charges etc.)\n- Constituer la r\u00e9conciliation des comptes avec subledger ( les fournisseurs, et les clients, les fix assets etc.)\n- Etablir les d\u00e9clarations fiscales p\u00e9riodiques (TVA, cave, c3s, etc.) et travailler avec un cabinet externe pour\u00a0la d\u00e9claration TP\n- Participer \u00e0 la mise en \u0153uvre de SAP (FICO, MM, BI) et apporter l\u2019am\u00e9lioration PEP processeurs\n- Pr\u00e9parer le rapport d'audit statutaire, l'annexe, le rapport de gestion, etc.\n- Pr\u00e9parer le rapport d'IFRS avec les analyses du Bilan et compte du r\u00e9sultat en d\u00e9tails\n- Dialoguer avec l'audit externe et interne pour les tests, la documentation et les processus.\n- Coordonner et suivre le processus d'injection de capital\n- Suivi du passif du contrat de pr\u00eat et de la comptabilit\u00e9 de couverture li\u00e9e aux devises \u00e9trang\u00e8res li\u00e9es \u00e0 ce\u00a0contrat\n- Manager une \u00e9quipe de 2-3 personnes\n---------------------------------------------------------------------------------\nRoles and responsibilities\n- Organize and prepare monthly/annual closings, meeting tight reporting deadlines.\n- Identify and adjust differences between IFRS and French GAAP.\n- Find solutions for new processes for new business scenarios.\n- Perform reconciliation with intercompany accounts (raw materials, expenses, etc.).\n- Reconcile accounts with subledgers (suppliers, customers, fixed assets, etc.).\n- Prepare periodic tax returns (VAT, cave, c3s, etc.) and work with an external firm for TP returns.\n- Participate in the implementation of SAP (FICO, MM, BI) and contribute to the improvement of PEP processors\n- Prepare the statutory audit report, notes to the financial statements, management report, etc.\n- Prepare the IFRS report with detailed analysis of the balance sheet and income statement.\n- Liaise with external and internal auditors for testing, documentation, and processes.\n- Coordinate and monitor the capital injection process.\n- Monitor the liabilities of the loan agreement and the hedge accounting related to foreign currencies linked to this agreement.\n- Manage a team of 2-3 people.\nQualifications\nExp\u00e9rience et comp\u00e9tences\n- Licence en finance ou comptabilit\u00e9. CMA/CPA/DSG/DSCG de pr\u00e9f\u00e9rence.\n- 5 \u00e0 10 ans d'exp\u00e9rience dans le domaine de la finance et de la comptabilit\u00e9.\n- L'exp\u00e9rience de SAP est indispensable.\n- Une exp\u00e9rience dans le domaine de la fabrication et des soci\u00e9t\u00e9s multinationales est fortement souhait\u00e9e avec une exp\u00e9rience de costing\n- Capacit\u00e9 \u00e0 d\u00e9velopper de solides relations de partenariat et d'\u00e9quipe dans un environnement multi-fonctionnel.\n- Comp\u00e9tences en mati\u00e8re de gestion du temps, d'organisation et de hi\u00e9rarchisation des priorit\u00e9s.\n- Capacit\u00e9 \u00e0 parler, lire et \u00e9crire couramment en anglais. Parler Chinois sera un plus.\n--------------------------------------------------------------------------\nExperience and skills\n- Bachelor's degree in finance or accounting. CMA/CPA/DSG/DSCG preferred.\n- 5 to 10 years of experience in finance and accounting.\n- SAP experience is essential.\n- Experience in manufacturing and multinational companies is highly desirable, with costing experience.\nGo back\nApply\nShare this job\nEmail\nFacebook\nX\nWeChat\nWhatsApp\nLinkedIn",
        "application_url": "https://jobs.aesc-group.com/en_US/careers/Login?jobId=309&recommendation=&source=&tags=&user=&formValues=",
        "": {},
        "metadata": {
            "Job Title": "Responsable Comptabilit\u00e9",
            "Ref #": "20001400",
            "Employment Type": "Permanent",
            "Department": "Finance",
            "Position level": "Manager",
            "Date": "Sunday, February 23, 2025",
            "AESC Office Location": "Douai, Hauts-de-France, France"
        },
        "link": "https://jobs.aesc-group.com/en_US/careers/JobDetail/Lambres-lez-Douai-Hauts-de-France-France-France-Responsable-Comptabilit/309"
    },
    {
        "title": "Technicien de laboratoire",
        "description_html": null,
        "description_text": "General information\nJob Title\nTechnicien de laboratoire\nRef #\n20001402\nEmployment Type\nPermanent\nDepartment\nQuality\nPosition level\nTechnician\nDate\nSunday, February 23, 2025\nAESC Office Location\nDouai, Hauts-de-France, France\nDescription & Requirements\nJob Description\n\ud83c\udf0d\u267b\ufe0f Pr\u00eat(e) \u00e0 relever les d\u00e9fis d\u2019une mobilit\u00e9 plus respectueuse de l\u2019environnement ? \u267b\ufe0f\ud83c\udf0d\nRejoignez AESC et devenez un acteur cl\u00e9 du d\u00e9veloppement et de la production de batteries lithium-ion haute performance !\nDans le cadre de notre implantation en France, AESC recrute un(e)\nTechnicien(ne) de laboratoire\npour le site de Douai, class\u00e9\nSEVESO seuil haut\n. Vous serez responsable de la r\u00e9alisation des tests, essais et analyses, avec un focus sur le contr\u00f4le des mati\u00e8res, composants, semi-finis et produits finis. Vous interviendrez \u00e9galement dans la qualification des produits finis et ponctuellement dans l\u2019analyse des retours clients et/ou des usines.\nNous vous proposons un poste polyvalent combinant chimie, m\u00e9canique et \u00e9lectricit\u00e9, vous permettant de mettre \u00e0 profit vos connaissances tout en d\u00e9veloppant de nouvelles comp\u00e9tences dans un environnement industriel automobile.\n\ud83c\udfaf T\u00e2ches essentielles et responsabilit\u00e9s\nLa description suivante du travail \u00e0 effectuer ne se veut pas exhaustive. Elle met plut\u00f4t l'accent sur les principales t\u00e2ches qui doivent \u00eatre accomplies :\nR\u00e9aliser les analyses      en suivant les modes op\u00e9ratoires\nContr\u00f4ler et assurer la      conformit\u00e9 des produits\nEffectuer la lib\u00e9ration      des lots\nSaisir les donn\u00e9es dans      l'ERP\nG\u00e9rer et suivre les      non-conformit\u00e9s des produits\nPlanifier et r\u00e9aliser      des pr\u00e9l\u00e8vements pour les contr\u00f4les d\u2019environnement et fluides, ainsi que      des produits (mati\u00e8res premi\u00e8res, en cours de production et produits      finis)\nR\u00e9aliser et approuver      les r\u00e9sultats des analyses\nParticiper \u00e0 la      v\u00e9rification m\u00e9trologique, \u00e0 la maintenance, qualification et validation      des \u00e9quipements/locaux\nContribuer aux      processus d\u2019am\u00e9lioration continue (5S, \u2026)\nParticiper \u00e0 la gestion      des r\u00e9actifs et \u00e9chantillons, ainsi qu\u2019\u00e0 la r\u00e9daction de la documentation      technique et s\u00e9curit\u00e9 (DUERP)\nIdentifier les risques      et proposer des actions pour limiter ces risques avec les fonctions      concern\u00e9es\nQualifications\n\ud83d\udcbc Savoir-faire requis :\nDe formation Bac+2      scientifiques (d\u00e9butants accept\u00e9s)\nConnaissances en      mesures physiques, m\u00e9tallurgie, m\u00e9canique, voire m\u00e9catronique, id\u00e9alement      chimie de la batterie\nAutonome, force de      proposition, avec un bon esprit d\u2019analyse et de synth\u00e8se\nBon relationnel et      capacit\u00e9 \u00e0 collaborer efficacement dans un environnement automobile\n? Savoir-\u00eatre requis :\nRigueur et pr\u00e9cision\nEsprit d\u2019\u00e9quipe\nProactivit\u00e9 et capacit\u00e9      \u00e0 r\u00e9soudre des probl\u00e8mes\n\u2705 Exigences du poste :\nFormation\nBac+2      scientifiques\nConnaissance      des outils informatiques\n, notamment SAP\nDisponibilit\u00e9 pour      travailler en \u00e9quipe\n3x8\n\ud83d\udce9 Int\u00e9ress\u00e9(e) ? Postulez d\u00e8s maintenant et participez \u00e0 la construction d\u2019un avenir plus propre et plus durable avec AESC ! \ud83c\udf0d\ud83d\udd0b\n#LI-SD2\nGo back\nApply\nShare this job\nEmail\nFacebook\nX\nWeChat\nWhatsApp\nLinkedIn",
        "application_url": "https://jobs.aesc-group.com/en_US/careers/Login?jobId=311&recommendation=&source=&tags=&user=&formValues=",
        "": {},
        "metadata": {
            "Job Title": "Technicien de laboratoire",
            "Ref #": "20001402",
            "Employment Type": "Permanent",
            "Department": "Quality",
            "Position level": "Technician",
            "Date": "Sunday, February 23, 2025",
            "AESC Office Location": "Douai, Hauts-de-France, France"
        },
        "link": "https://jobs.aesc-group.com/en_US/careers/JobDetail/Lambres-lez-Douai-Hauts-de-France-France-France-Technicien-de-laboratoire/311"
    },
    {
        "title": "Conducteur d'installations (H/F)",
        "description_html": null,
        "description_text": "General information\nJob Title\nConducteur d'installations (H/F)\nRef #\n242\nEmployment Type\nPermanent\nDepartment\nManufacturing\nPosition level\nTechnician\nDate\nTuesday, February 4, 2025\nAESC Office Location\nDouai, Hauts-de-France, France\nDescription & Requirements\nJob Description\n\ud83c\udf0d\u267b\ufe0f Pr\u00eat(e) \u00e0 relever les d\u00e9fis d\u2019une mobilit\u00e9 plus respectueuse de l\u2019environnement ? \u267b\ufe0f\ud83c\udf0d\nRejoignez AESC et devenez un acteur cl\u00e9 dans le d\u00e9veloppement et la production de batteries lithium-ion haute performance !\nDans le cadre de son implantation en France, AESC recrute des\nConducteurs d\u2019installation (H/F)\npour son site de\nLambres-lez-Douai\n. Vous serez en charge du pilotage des installations automatis\u00e9es et de leur bon fonctionnement, sous la supervision du Team Leader Production.\n\ud83c\udfaf\nT\u00e2ches essentielles et responsabilit\u00e9s :\nLa description suivante du travail \u00e0 effectuer ne se veut pas exhaustive. Elle met plut\u00f4t l\u2019accent sur les principales t\u00e2ches qui doivent \u00eatre accomplies :\nAssurer les productions au quotidien et en temps r\u00e9el sur votre p\u00e9rim\u00e8tre, conform\u00e9ment \u00e0 la fiche de poste\nConduire les \u00e9quipements de production dans le respect des r\u00e8gles de s\u00e9curit\u00e9 et qualit\u00e9, en environnement salle blanche \u00ab 0 poussi\u00e8re \u00bb\nG\u00e9rer les dysfonctionnements et intervenir pour les r\u00e9soudre rapidement\nParticiper \u00e0 l\u2019am\u00e9lioration continue et proposer des perfectionnements pour optimiser la production\n\ud83d\udcbc\nSavoir-faire requis :\nExp\u00e9rience confirm\u00e9e dans le secteur industriel, notamment en production\nBonne ma\u00eetrise des outils et des \u00e9quipements de production automatis\u00e9s\nComp\u00e9tences en gestion des dysfonctionnements et en am\u00e9lioration continue\n?\nSavoir-\u00eatre requis :\nAutonomie et capacit\u00e9 \u00e0 travailler en \u00e9quipe\nEsprit d\u2019analyse et r\u00e9solution de probl\u00e8mes\nDisponibilit\u00e9 pour des horaires post\u00e9s (3x8) ou le week-end\n\u2705\nExigences du poste :\nExp\u00e9rience dans un environnement industriel\nPr\u00eat \u00e0 travailler dans des conditions strictes de s\u00e9curit\u00e9 et qualit\u00e9\nDisponibilit\u00e9 pour des horaires post\u00e9s ou le week-end\n#LI-EO1\nQualifications\n\u2705\nExigences du poste :\nExp\u00e9rience dans un environnement industriel\nPr\u00eat \u00e0 travailler dans des conditions strictes de s\u00e9curit\u00e9 et qualit\u00e9\nDisponibilit\u00e9 pour des horaires post\u00e9s ou le week-end\nGo back\nApply\nShare this job\nEmail\nFacebook\nX\nWeChat\nWhatsApp\nLinkedIn",
        "application_url": "https://jobs.aesc-group.com/en_US/careers/Login?jobId=250&recommendation=&source=&tags=&user=&formValues=",
        "": {},
        "metadata": {
            "Job Title": "Conducteur d'installations (H/F)",
            "Ref #": "242",
            "Employment Type": "Permanent",
            "Department": "Manufacturing",
            "Position level": "Technician",
            "Date": "Tuesday, February 4, 2025",
            "AESC Office Location": "Douai, Hauts-de-France, France"
        },
        "link": "https://jobs.aesc-group.com/en_US/careers/JobDetail/LAMBRES-LEZ-DOUAI-France-Conducteur-d-installations-H-F/250"
    },
    {
        "title": "TECHNICIEN QUALITE MATIERES PREMIERES",
        "description_html": null,
        "description_text": "General information\nJob Title\nTECHNICIEN QUALITE MATIERES PREMIERES\nRef #\n235\nEmployment Type\nPermanent\nDepartment\nQuality\nPosition level\nTechnician\nDate\nWednesday, January 29, 2025\nAESC Office Location\nDouai, Hauts-de-France, France\nDescription & Requirements\nJob Description\nInt\u00e9gr\u00e9( e) \u00a0au d\u00e9partement qualit\u00e9, vous \u00eates notre prochain (e ) \u00a0technicien(e ) qualit\u00e9 fournisseur !\nVous avez une exp\u00e9rience dans l'automobile chez un fournisseur de niveau 1 ?\nVenez travailler chez nous !\nMission :\nVous serez en charge de la v\u00e9rification de la qualit\u00e9 des mati\u00e8res premi\u00e8res re\u00e7ues \u00e0 leur arriv\u00e9e sur le site.\nApr\u00e8s avoir proc\u00e9d\u00e9 aux analyses, et en cas de non-conformit\u00e9 des mat\u00e9riaux, vous serez en charge de remonter ces derni\u00e8res aupr\u00e8s du laboratoire et au SQE .\nCe que l'on vous demandera ?\nCette liste n'est pas exhaustive et peut \u00e9voluer.\nG\u00e9rer et s\u00e9curiser la manipulation des produits non conformes.\nComprendre les PFMEA et les plans de contr\u00f4le.\nG\u00e9n\u00e9rer des rapports techniques et de gestion.\nEffectuer des inspections dans l'entrep\u00f4t en suivant les instructions de travail pertinentes.\nEffectuer des activit\u00e9s de validation.\nEffectuer des analyses XRAY.\nActiver des activit\u00e9s de confinement.\nAvoir une bonne connaissance \u00a0 \u00a0 de la norme IATF16949:2016\nComp\u00e9tences particuli\u00e8res recherch\u00e9es\u00a0:\n- Capacit\u00e9 \u00e0 analyser, interpr\u00e9ter et pr\u00e9senter des donn\u00e9es pour prendre des d\u00e9cisions fond\u00e9es sur des faits.\n- Exp\u00e9rience de l'IATF16949\n- Exp\u00e9rience/compr\u00e9hension des outils de base de l'IATF/TS (PPAP, APQP, MSA, FMEA, SPC).\n- Solides comp\u00e9tences en mati\u00e8re de communication \u00e9crite et orale - des rapports \u00e0 tous les niveaux de l'entreprise et avec toutes les fonctions seront n\u00e9cessaires.\n- Connaissance du logiciel SAP (souhaitable)\n- Bonnes comp\u00e9tences en informatique, y compris MS Word, Excel, Access et PowerPoint.\n- Capacit\u00e9 \u00e0 travailler en \u00e9quipe\n- Connaissance de l'enqu\u00eate 8D.\n- Compr\u00e9hension de l'\u00e9talonnage et de la MSA (souhaitable)\n- Savoir confiner des pi\u00e8ces suspectes\nQualifications requises :\nDe formation Bac+2 / 3 dans \u00a0 \u00a0 un domaine scientifique\nAutonome\nCurieux\nForce de proposition\nUn bon esprit d\u2019analyse\nEsprit de synth\u00e8se\nBon \u00a0 \u00a0 relationnel qui vous permet de collaborer efficacement et de maitriser la \u00a0 \u00a0 relation fournisseur (client dans un environnement automobile)\n#LI-SD2\nQualifications\nComp\u00e9tences particuli\u00e8res recherch\u00e9es\u00a0:\n- Capacit\u00e9 \u00e0analyser, interpr\u00e9ter et pr\u00e9senter des donn\u00e9es pour prendre des d\u00e9cisionsfond\u00e9es sur des faits.\n- Exp\u00e9rience del'IATF16949\n-Exp\u00e9rience/compr\u00e9hension des outils de base de l'IATF/TS (PPAP, APQP, MSA,FMEA, SPC).\n- Solidescomp\u00e9tences en mati\u00e8re de communication \u00e9crite et orale - des rapports \u00e0 tousles niveaux de l'entreprise et avec toutes les fonctions seront n\u00e9cessaires.\n- Connaissance dulogiciel SAP (souhaitable)\n- Bonnes comp\u00e9tencesen informatique, y compris MS Word, Excel, Access et PowerPoint.\n- Capacit\u00e9 \u00e0travailler en \u00e9quipe\n- Connaissance del'enqu\u00eate 8D.\n- Compr\u00e9hension del'\u00e9talonnage et de la MSA (souhaitable)\n- Savoir confinerdes pi\u00e8ces suspectes\nQualifications requises :\nDe formation Bac+2 / 3 dans \u00a0 \u00a0 un domaine scientifique\nAutonome\nCurieux\nForcede proposition\nUn bonesprit d\u2019analyse\nEsprit de synth\u00e8se\nBon \u00a0 \u00a0 relationnel qui vous permet de collaborer efficacement et de maitriser la \u00a0 \u00a0 relation fournisseur (client dans un environnement automobile)\nGo back\nApply\nShare this job\nEmail\nFacebook\nX\nWeChat\nWhatsApp\nLinkedIn",
        "application_url": "https://jobs.aesc-group.com/en_US/careers/Login?jobId=243&recommendation=&source=&tags=&user=&formValues=",
        "": {},
        "metadata": {
            "Job Title": "TECHNICIEN QUALITE MATIERES PREMIERES",
            "Ref #": "235",
            "Employment Type": "Permanent",
            "Department": "Quality",
            "Position level": "Technician",
            "Date": "Wednesday, January 29, 2025",
            "AESC Office Location": "Douai, Hauts-de-France, France"
        },
        "link": "https://jobs.aesc-group.com/en_US/careers/JobDetail/Lambres-lez-Douai-Hauts-de-France-France-Nord-France-TECHNICIEN-QUALITE-MATIERES-PREMIERES/243"
    },
    {
        "title": "Technicien de Maintenance (H/F)",
        "description_html": null,
        "description_text": "General information\nJob Title\nTechnicien de Maintenance (H/F)\nRef #\n206\nEmployment Type\nPermanent\nDepartment\nOperations\nPosition level\nTechnician\nDate\nMonday, January 6, 2025\nAESC Office Location\nDouai, Hauts-de-France, France\nDescription & Requirements\nJob Description\n\ud83c\udf0d\u267b\ufe0f\nPr\u00eat(e) \u00e0 relever les d\u00e9fis d\u2019une mobilit\u00e9 plus respectueuse de l\u2019environnement ?\n\u267b\ufe0f\ud83c\udf0d\nRejoignez AESC Douai et devenez un acteur cl\u00e9 dans le d\u00e9veloppement et la production de batteries lithium-ion haute performance.\nDans le cadre de son implantation en France, AESC recrute pour le site de\nLambres-lez-Douai\n, des\nTechnicien(ne) de Maintenance\n.\nPlusieurs postes sont \u00e0 pourvoir en fonction de vos comp\u00e9tences:\nMaintenance Op\u00e9rationnelle\nTools & dies - usinage - pi\u00e8ces de l'usine\nUtilities - Infrastructure\nAutomaticien -\n?\nSavoir-\u00eatre requis :\nEsprit d\u2019\u00e9quipe et capacit\u00e9 \u00e0 travailler en horaires post\u00e9s.\nProactivit\u00e9, autonomie et rigueur.\nLe gout du challenge et l'envie de participer \u00e0 la cr\u00e9ation d'une nouvelle industrie\n\u2705\nExigences du poste :\nMobilit\u00e9 nationale et/ou internationale ponctuelle.\nTravail en horaires 4*12 pour la maintenance ( 3 jours travaill\u00e9s de 12h , 3 jours repos ) ET \u00a03*8 pour les utilit\u00e9s\n\ud83d\udcbc\nSavoir-faire requis :\nConnaissances en maintenance industrielle et \u00e9quipements automatis\u00e9s.\nPostulez, notre \u00e9quipe prendra le soin de vous recontacter pour vous pr\u00e9senter le poste et r\u00e9pondre \u00e0 vos questions.\n#LI-EO1\nRequirements / Required skills\nEquipment Maintenance\nMaintenance & Repair\nPlant Maintenance\nPreventive Maintenance\nQualifications\n\u2705\nExigences du poste :\nMobilit\u00e9 nationale et/ou internationale ponctuelle.\nTravail en horaires de journ\u00e9e OU 2*8 jusqu\u2019\u00e0 mars 2025, puis en 3*8.\nGo back\nApply\nShare this job\nEmail\nFacebook\nX\nWeChat\nWhatsApp\nLinkedIn",
        "application_url": "https://jobs.aesc-group.com/en_US/careers/Login?jobId=212&recommendation=&source=&tags=&user=&formValues=",
        "": {},
        "metadata": {
            "Job Title": "Technicien de Maintenance (H/F)",
            "Ref #": "206",
            "Employment Type": "Permanent",
            "Department": "Operations",
            "Position level": "Technician",
            "Date": "Monday, January 6, 2025",
            "AESC Office Location": "Douai, Hauts-de-France, France"
        },
        "link": "https://jobs.aesc-group.com/en_US/careers/JobDetail/LAMBRES-LEZ-DOUAI-France-Technicien-de-Maintenance-H-F/212"
    }
]