[
    {
        "title": null,
        "description_html": null,
        "description_text": "(Junior) Systemadministrator* Citrix\nGeneral information\nCountry\nGermany\nCity\nHamburg\nType of role\nProfessional\nWorking time\nFull-time\nType of contract\nPermanent\nRemaining openings\n1\nDescription & Requirements\nF\u00fcr unser Programm\nCore Infrastructure Services\nam\nStandort Hamburg\nsuchen wir zum\nn\u00e4chstm\u00f6glichen Zeitpunkt\ndich als\n(Junior) System Engineer Workspace*\nInnovation & Technology @ Berenberg\nIn einer \u00c4ra, in der Digitalisierung und moderne IT-Infrastrukturen das Banking revolutionieren, gestalten wir eine technologiegest\u00fctzte Bank, in der du als IT-Profi eng mit unseren Gesch\u00e4ftsbereichen zusammenarbeitest. Unsere Technology-Teams bieten dir ein Umfeld, das dich vor spannende Herausforderungen stellt \u2013 sei es durch den Support und die Weiterentwicklung von Legacy-Systemen oder die Einf\u00fchrung moderner Technologien wie KI, Machine Learning und hochgradig automatisierte Handelsapplikationen.\nUnsere IT-Abteilung mit etwa 300 Mitarbeitern arbeitet gr\u00f6\u00dftenteils agil nach einem Scrumban-Ansatz und deckt Bereiche wie Cloud Computing, Cybersecurity, Operations, Process and Governance, Software Development und Architecture ab. Wir sind besonders stolz darauf, fast alle unsere Applikationen Inhouse zu entwickeln, was uns eine einzigartige Flexibilit\u00e4t und Innovationskraft verleiht. Unser Tech Stack umfasst moderne Technologien wie Java, Kotlin, TypeScript und Python, CI/CD-Pipelines, Container, Kubernetes sowie Azure Cloud, Azure SQL Database und Oracle Datenbank mit PL/SQL.\nDeine Rolle im Team\nIm Team Windows Infrastructure and Workspace wirst Du die Administration und Weiterentwicklung unserer Microsoft- und Virtualisierungs-Infrastruktur \u00fcbernehmen. Du wirst dich mit den Fachbereichen abstimmen, an globalen Projekten mitarbeiten und hast die M\u00f6glichkeit Dich mit eigenen Ideen und Verbesserungen einzubringen.\nWelche Aufgaben erwarten Dich?\nPlanung, Bereitstellung und Betrieb moderner Windows-Arbeitsplatzumgebungen (Windows 10/11 sowie Server 2016, 2019 und 2022) auf Basis einer zentralisierten Citrix Virtual Apps and Desktops (CVAD) Infrastruktur\n\u00dcbernahme des 3rd-Level-Supports f\u00fcr komplexe Fragestellungen im Bereich Arbeitsplatzbereitstellung und Benutzerumgebung\nKonfiguration und Verwaltung von Endger\u00e4ten sowie Softwareverteilung mittels Microsoft Intune, ACMP und Ivanti DSM\nBetreuung und Weiterentwicklung der Thin-Client-Infrastruktur auf Basis von IGEL OS\nAutomatisierung und Standardisierung von Prozessen rund um den digitalen Arbeitsplatz mit Hilfe von PowerShell\nWen suchen wir?\nErfolgreich abgeschlossene Ausbildung zum Fachinformatiker f\u00fcr Systemintegration), IT-Systemelektroniker bzw. ein abgeschlossenes Studium im Bereich (Wirtschafts-)Informatik oder einer vergleichbaren Fachrichtung\nErfahrung in der Bereitstellung und Betreuung moderner Arbeitsplatzl\u00f6sungen im Microsoft-Umfeld (Windows 10/11, Server 2016, 2019 & 2022, Office, Intune)\nKenntnisse im Umgang mit Citrix CVAD, Citrix Gateway und Citrix Provisioning Services\nSicherer Umgang mit ACMP, Microsoft Intune, Ivanti DSM sowie Ivanti User Workspace Manager\nSehr gute Deutsch- und Englischkenntnisse in Wort und Schrift\nWas wir Dir bieten:\nFlexible Arbeitszeiten innerhalb einer 39-Stunden-Woche\n30 Tage Jahresurlaub sowie zus\u00e4tzliche freie Tage am 24. und 31. Dezember\nVielseitiges und spannendes Aufgabengebiet in einem modernen und dynamischen Umfeld sowie ein wertsch\u00e4tzendes Betriebsklima\nGezielte F\u00f6rderung durch interne und externe Schulungs- und Entwicklungsprogramme\nBerenberg-Patensystem f\u00fcr ein strukturiertes und reibungsloses Onboarding\nVielf\u00e4ltige Zusch\u00fcsse (z. B. Deutschlandticket, JobRad, verm\u00f6genswirksame Leistungen, betriebliche Altersvorsorge, Essenszusch\u00fcsse bzw. Betriebsrestaurant in Hamburg)\nZus\u00e4tzliche Leistungen wie Familienservice, Arbeitszeitkonto (z. B. f\u00fcr Sabbaticals), betriebliche Sozialleistungen, Gesundheits- und Sportprogramme\nBewirb dich jetzt online und werde Teil des Teams \u2013\nwir freuen uns auf deine Bewerbung!\nWir sind eine f\u00fchrende europ\u00e4ische Privatbank mit \u00fcber 430 Jahren Erfahrung und einer tief verwurzelten Geschichte, aber wir gestalten und investieren noch immer in Zukunft. Unser Fortschritt und unsere Entwicklung werden von unseren Mitarbeitern vorangetrieben. Wir ermutigen sie, neue Ans\u00e4tze auszuprobieren, ihre Meinung zu \u00e4u\u00dfern und auf ihre eigene Art und Weise erfolgreich zu sein.\nWir bieten ihnen die M\u00f6glichkeit, ihre Talente zu entwickeln, verschiedene Karrierewege zu erkunden und ihr Potenzial voll auszusch\u00f6pfen.\nWir sind ein ehrgeiziges, zukunftsorientiertes Unternehmen, das auf jahrhundertealte Traditionen zur\u00fcckgreift und auf Innovation baut. Du findest bei uns eine Kultur vor, die Menschen dazu ermutigt, unabh\u00e4ngig zu denken, unternehmerisch zu handeln und den Status quo in Frage zu stellen. Wir legen gro\u00dfen Wert auf die Zusammenarbeit vor Ort \u2013 unser B\u00fcro ist ein zentraler Ort des Dialogs, der Innovation und des gemeinsamen Wachstums. Gemeinsam arbeiten wir daran, unser Gesch\u00e4ft zu gestalten und unsere ehrgeizigen Ziele zu erreichen.\nWir freuen uns, wenn du dich uns anschlie\u00dft, um stets das Richtige f\u00fcr unsere Mitarbeiter, Kunden und unser Unternehmen zu tun \u2013\nOur future is where you take us!\nAus organisatorischen Gr\u00fcnden nehmen wir nur Bewerbungen an, die uns \u00fcber unser Online-Bewerbermanagementsystem auf der Website erreichen.\n*Aus Gr\u00fcnden der besseren Lesbarkeit wird auf die gleichzeitige Verwendung mehrgeschlechtlicher Sprachformen verzichtet. S\u00e4mtliche Personenbezeichnungen gelten gleichwohl f\u00fcr jegliches Geschlecht. Bei uns sind alle Bewerber willkommen, unabh\u00e4ngig von Geschlecht, Nationalit\u00e4t, ethnischer Herkunft, sozialem Hintergrund, Behinderung, Religion, Alter oder sexueller Orientierung. Bei Fragen wende dich bitte an unser Recruitment-Team unter recruitment@berenberg.de.\nBack to job list\nApply\nShare this job:\nShare (Junior) Systemadministrator* Citrix with a friend via e-mail",
        "application_url": "https://berenberg.avature.net/en_GB/careers/Login?jobId=2474",
        "metadata": {
            "Country": "Germany",
            "City": "Hamburg",
            "Type of role": "Professional",
            "Working time": "Full-time",
            "Type of contract": "Permanent",
            "Remaining openings": "1"
        },
        "link": "https://berenberg.avature.net/en_GB/careers/JobDetail/Junior-Systemadministrator-Citrix/2474"
    },
    {
        "title": null,
        "description_html": null,
        "description_text": "(Senior) Investment Manager* Private Debt\nGeneral information\nCountry\nGermany\nCity\nFrankfurt, Hamburg, Munich\nType of role\nProfessional\nWorking time\nFull-time\nType of contract\nPermanent\nRemaining openings\n1\nDescription & Requirements\nF\u00fcr unser Team\nInfrastructure & Energy\nam Standort\nHamburg, Frankfurt am Main oder M\u00fcnchen\nsuchen wir Sie als\n(Senior) Investment Manager* Private Debt\nIhre Rolle im Team\nAls Mitarbeiter im Team Origination arbeiten Sie an der Anbahnung und Umsetzung von Projekten im Be-reich Infrastructure & Energy, welches zum Zentralbereich Corporate, Wealth & Asset Management zugeordnet ist. Infrastructure & Energy hat mehrere Kreditfonds f\u00fcr Junior Debt- und Unitranchen Finanzierungen internati-onaler Projekte im Bereich Erneuerbare Energien, Energy Transition und Digitale Infrastruktur aufgelegt und agiert als Investment Advisor f\u00fcr diese Fonds. Das Team Origination ist dabei f\u00fcr das Deal Sourcing und ge-meinsam mit dem Team Structuring f\u00fcr die Umsetzung der Transaktionen zust\u00e4ndig.\nPrivate Debt geh\u00f6rt zu den Alternative Investments und vereint Projektfinanzierung und Kommunikation mit Projekteigent\u00fcmern sowie die Betreuung von Fondsinvestoren. Unser erfahrenes Team in Hamburg und Frank-furt verf\u00fcgt \u00fcber eine langj\u00e4hrige Expertise und verantwortet \u00fcber alle Kreditfonds ca. 1 Mrd. EUR Assets Under Management. Die Sektoren Erneuerbaren Energien und Infrastruktur sind stark wachsende und nachhaltige Assetklassen innerhalb welcher wir in den letzten Jahren ein starkes Wachstum generieren konnten.\nWelche Aufgaben erwarten Sie?\nProjektleitung und/oder Unterst\u00fctzung des Projektleiters f\u00fcr die Verhandlung der Kreditdokumentation und Strukturierung von Finanzierungen f\u00fcr weltweite Projekte mit Fokus auf Windkraft, Photovoltaik, Energy Transition und Digitale Infrastruktur\nSteuerung der an der Finanzierung beteiligten Parteien (z. B. technische Berater, Anwaltskanzleien, Steuerberater und Wirtschaftspr\u00fcfer)\nErstellung von Cashflow-Modellen der finanzierten Projekte auf MS-Excel Basis\nEigenst\u00e4ndige Kunden- und Projektakquisitionen\nMitwirkung an der Konzeptionierung von neuen Produkt- und Fondsideen im Bereich Infrastructure & Energy\nErstellung und Bearbeitung von Kreditvorlagen sowie Projektanalysen zur Aufbereitung von Investiti-onsentscheidungen f\u00fcr die Fonds\nWen suchen wir?\nErfolgreich abgeschlossenes Studium der Wirtschaftswissenschaften, Rechtswissenschaften oder In-genieurwesen\nEinschl\u00e4gige praktische Erfahrung in Transaktionsfinanzierung insbesondere in der Origination im Be-reich Infrastructure & Energy\nRelevante Kundenkontakte in diesem Bereich\nSehr gute Erfahrung von Kredit- und Sicherheitendokumentation (LMA-Standards) sowie ausgepr\u00e4gtes Verst\u00e4ndnis von GuV, Cashflow und Bilanzen\nGute Kenntnisse in der Anwendung von MS-Excel, insbesondere im Financial-Modeling\nFlie\u00dfende Deutsch- und verhandlungssichere Englischkenntnisse in Wort und Schrift\nWas wir Ihnen bieten:\nFlexible Arbeitszeiten innerhalb einer 39-Stunden-Woche\n30 Tage Jahresurlaub sowie zus\u00e4tzliche freie Tage am 24. und 31. Dezember\nVielseitiges und spannendes Aufgabengebiet in einem modernen und dynamischen Umfeld sowie wert-sch\u00e4tzendes Betriebsklima\nGezielte F\u00f6rderung durch interne und externe Schulungs- und Entwicklungsprogramme\nBerenberg-Patensystem f\u00fcr ein strukturiertes und reibungsloses Onboarding\nVielf\u00e4ltige Zusch\u00fcsse (z. B. Deutschlandticket, JobRad, verm\u00f6genswirksame Leistungen, betriebliche Altersvorsorge, Essenszusch\u00fcsse bzw. Betriebsrestaurant in Hamburg)\nZus\u00e4tzliche Leistungen wie Familienservice, Arbeitszeitkonto (z. B. f\u00fcr Sabbaticals), betriebliche Sozial-leistungen, Gesundheits- und Sportprogramme\nBewerben Sie sich jetzt online und werden Sie Teil des Teams \u2013\nwir freuen uns auf Ihre Bewerbung!\nAls eine f\u00fchrende europ\u00e4ische Privatbank mit \u00fcber 430 Jahren Erfahrung blicken wir auf eine lange Unterneh-mensgeschichte zur\u00fcck. Gleichzeitig gestalten wir mit umfassenden Investitionen aktiv unsere Zukunft. Grund-lage f\u00fcr unseren Fortschritt und unsere Weiterentwicklung sind unsere Mitarbeiter. Wir ermutigen diese, neue Ans\u00e4tze auszuprobieren, ihre Ideen mit einzubringen und ihren eigenen Weg zum Erfolg bei uns zu gehen. Wir sind ein ambitioniertes, zukunftsorientiertes Unternehmen, das jahrhundertelange Erfahrung und Innovations-kraft vereint.\nBei uns erleben Sie eine Kultur, die zum selbstst\u00e4ndigen Denken anregt, Unternehmertum f\u00f6rdert und dazu ermutigt, den Status quo zu hinterfragen. Wir legen gro\u00dfen Wert auf die Zusammenarbeit vor Ort \u2013 unser B\u00fcro ist ein zentraler Ort des Dialogs, der Innovation und des gemeinsamen Wachstums. Sie treffen hier auf talentier-te Kollegen, die es gewohnt sind, Verantwortung zu \u00fcbernehmen, und gemeinsam an einem Strang ziehen, um Ergebnisse zu erzielen.\nWerden Sie Teil von Berenberg und arbeiten Sie mit uns gemeinsam daran, das Richtige f\u00fcr unsere Kunden, unser Gesch\u00e4ft und unsere Mitarbeiter zu tun \u2013\nOur future is where you take us!\nAus organisatorischen Gr\u00fcnden nehmen wir nur Bewerbungen an, die uns \u00fcber unser Online-Bewerbermanagementsystem auf der Website erreichen.\n*Aus Gr\u00fcnden der besseren Lesbarkeit wird auf die gleichzeitige Verwendung mehrgeschlechtlicher Sprachfor-men verzichtet. S\u00e4mtliche Personenbezeichnungen gelten gleichwohl f\u00fcr jegliches Geschlecht. Bei uns sind alle Bewerbungen willkommen, unabh\u00e4ngig von Geschlecht, Nationalit\u00e4t, ethnischer Herkunft, sozialem Hintergrund, Behinderung, Religion, Alter oder sexueller Orientierung. Bei Fragen wenden Sie sich bitte an unser Recruitment-Team unter recruitment@berenberg.de.\nBack to job list\nApply\nShare this job:\nShare (Senior) Investment Manager* Private Debt with a friend via e-mail",
        "application_url": "https://berenberg.avature.net/en_GB/careers/Login?jobId=2810",
        "metadata": {
            "Country": "Germany",
            "City": "Frankfurt, Hamburg, Munich",
            "Type of role": "Professional",
            "Working time": "Full-time",
            "Type of contract": "Permanent",
            "Remaining openings": "1"
        },
        "link": "https://berenberg.avature.net/en_GB/careers/JobDetail/Senior-Investment-Manager-Private-Debt/2810"
    },
    {
        "title": null,
        "description_html": null,
        "description_text": "(Senior) Asset Manager* Real Estate\nGeneral information\nCountry\nGermany\nCity\nHamburg\nType of role\nProfessional\nType of contract\nPermanent\nRemaining openings\n1\nDescription & Requirements\nF\u00fcr unsere Abteilung\nReal Estate Asset Management\nam Standort\nHamburg\nsuchen wir Sie als\n(Senior) Asset Manager* Real Estate\nIhre Rolle im Team\nDer Bereich Real Estate initiiert und managt aktiv Investmentl\u00f6sungen f\u00fcr private und institutionelle Anleger \u2013 in Form offener und geschlossener Investmentfonds (AIFs) sowie Individualmandate. Die Umsetzung und laufende Betreuung der gewerblichen und wohnwirtschaftlichen Produkte erfolgt durch spezialisierte Expertenteams in den Einheiten Relationship Management, Investment, Fund Management und Asset Management.\nF\u00fcr unser kaufm\u00e4nnisches Asset Management suchen wir eine engagierte Pers\u00f6nlichkeit, die bereit ist, sich den vielf\u00e4ltigen Herausforderungen der heutigen Zeit \u2013 vom Bestandsmanagement bis hin zur Nachhaltigkeit \u2013 engagiert und mit ausgepr\u00e4gter Hands-on-Mentalit\u00e4t anzunehmen.\nOb strategische Projekte oder operative Details \u2013 wer Qualit\u00e4t lebt und Verantwortung sucht, ist bei uns genau richtig. Als ambitionierter Teamplayer mit Freude an der Zusammenarbeit mit internen und externen Stakeholdern gestalten Sie unser Wachstum aktiv mit.\nEin gewisses Ma\u00df an Reiset\u00e4tigkeit ist integraler Bestandteil der Position, da sich die f\u00fcr diese Aufgabe erforderliche Leidenschaft und das notwendige Verantwortungsbewusstsein insbesondere im direkten Kontakt mit den Mietern und den Assets vor Ort entfalten.\nWelche Aufgaben erwarten Sie?\nAktives eigenverantwortliches Asset Management eines \u201eCore/Core Plus\u201c-Immobilienportfolios mit regionalem Schwerpunkt in Norddeutschland\nIdentifizierung und Realisierung der Wertsteigerungspotenziale mit Verantwortung f\u00fcr die Wertentwicklung und Umsetzung von ESG-Strategien auf Objektebene\n\u00dcbernahme der Eigent\u00fcmerfunktion gegen\u00fcber Dritten sowie Auswahl, Controlling und aktive Steuerung externer Dienstleister (insbesondere Property Manager)\nDurchf\u00fchrung von Vertragsverhandlungen mit Bestands- und Neumietern\nErstellung objektspezifischer Businesspl\u00e4ne und periodischer Performance-Reports\nWen suchen wir?\nAbgeschlossenes betriebswirtschaftliches Studium mit immobilienwirtschaftlichem Hintergrund oder vergleichbare Qualifikation\nBerufserfahrung im Management von Immobilien unterschiedlicher Nutzungsklassen, gerne mit dem Fokus auf B\u00fcroimmobilien und / oder wohnwirtschaftlicher Nutzung\nSouver\u00e4ner Umgang mit MS Office, insbesondere Excel\nZielorientierter Arbeitsstil kombiniert mit wirtschaftlichem Denken und Verhandlungsgeschick\nFlie\u00dfendes Deutsch und gute Englischkenntnisse\nWas wir Ihnen bieten:\nFlexible Arbeitszeiten innerhalb einer 39-Stunden-Woche\n30 Tage Jahresurlaub sowie zus\u00e4tzliche freie Tage am 24. und 31. Dezember\nVielseitiges und spannendes Aufgabengebiet in einem modernen und dynamischen Umfeld sowie wertsch\u00e4tzendes Betriebsklima\nGezielte F\u00f6rderung durch interne und externe Schulungs- und Entwicklungsprogramme\nBerenberg-Patensystem f\u00fcr ein strukturiertes und reibungsloses Onboarding\nVielf\u00e4ltige Zusch\u00fcsse (z. B. Deutschlandticket, JobRad, verm\u00f6genswirksame Leistungen, betriebliche Altersvorsorge, Betriebsrestaurant in Hamburg)\nZus\u00e4tzliche Leistungen wie Familienservice, Arbeitszeitkonto (z. B. f\u00fcr Sabbaticals), betriebliche Sozialleistungen, Gesundheits- und Sportprogramme\nBewerben Sie sich jetzt online und werden Sie Teil des Teams \u2013\nwir freuen uns auf Ihre Bewerbung!\nAls eine f\u00fchrende europ\u00e4ische Privatbank mit \u00fcber 430 Jahren Erfahrung blicken wir auf eine lange Unternehmensgeschichte zur\u00fcck. Gleichzeitig gestalten wir mit umfassenden Investitionen aktiv unsere Zukunft. Grundlage f\u00fcr unseren Fortschritt und unsere Weiterentwicklung sind unsere Mitarbeiter. Wir ermutigen diese, neue Ans\u00e4tze auszuprobieren, ihre Ideen mit einzubringen und ihren eigenen Weg zum Erfolg bei uns zu gehen. Wir sind ein ambitioniertes, zukunftsorientiertes Unternehmen, das jahrhundertelange Erfahrung und Innovationskraft vereint.\nBei uns erleben Sie eine Kultur, die zum selbstst\u00e4ndigen Denken anregt, Unternehmertum f\u00f6rdert und\ndazu ermutigt, den Status quo zu hinterfragen. Wir legen gro\u00dfen Wert auf die Zusammenarbeit vor Ort \u2013 unser B\u00fcro ist ein zentraler Ort des Dialogs, der Innovation und des gemeinsamen Wachstums. Sie treffen hier auf talentierte Kollegen, die es gewohnt sind, Verantwortung zu \u00fcbernehmen, und gemeinsam an einem Strang ziehen, um Ergebnisse zu erzielen. Werden Sie Teil von Berenberg und arbeiten Sie mit uns gemeinsam daran, das Richtige f\u00fcr unsere Kunden, unser Gesch\u00e4ft und unsere Mitarbeiter zu tun \u2013\nOur future is where you take us!\nAus organisatorischen Gr\u00fcnden nehmen wir nur Bewerbungen an, die uns \u00fcber unser Online-Bewerbermanagementsystem auf der Website erreichen.\n*Aus Gr\u00fcnden der besseren Lesbarkeit wird auf die gleichzeitige Verwendung mehrgeschlechtlicher Sprachformen verzichtet. S\u00e4mtliche Personenbezeichnungen gelten gleichwohl f\u00fcr jegliches Geschlecht. Bei uns sind alle Bewerbungen willkommen, unabh\u00e4ngig von Geschlecht, Nationalit\u00e4t, ethnischer Herkunft, sozialem Hintergrund, Behinderung, Religion, Alter oder sexueller Orientierung. Bei Fragen wenden Sie sich bitte an unser Recruitment-Team unter recruitment@berenberg.de.\nBack to job list\nApply\nShare this job:\nShare (Senior) Asset Manager* Real Estate with a friend via e-mail",
        "application_url": "https://berenberg.avature.net/en_GB/careers/Login?jobId=2817",
        "metadata": {
            "Country": "Germany",
            "City": "Hamburg",
            "Type of role": "Professional",
            "Type of contract": "Permanent",
            "Remaining openings": "1"
        },
        "link": "https://berenberg.avature.net/en_GB/careers/JobDetail/Senior-Asset-Manager-Real-Estate/2817"
    },
    {
        "title": null,
        "description_html": null,
        "description_text": "Client Relationship Manager* Shipping\nGeneral information\nCountry\nGermany\nCity\nHamburg\nType of role\nProfessional\nWorking time\nFull-time\nType of contract\nPermanent\nRemaining openings\n1\nDescription & Requirements\nF\u00fcr unseren Abteilung\nShipping\nam Standort\nHamburg\nsuchen wir zum n\u00e4chstm\u00f6glichen Zeitpunkt Sie als\nClient Relationship Manager* Shipping\nIhre Rolle im Team\nAls Teil eines hoch motivierten Teams f\u00fcr die Betreuung von Unternehmen aus der maritimen Industrie mit dem Fokus auf Deutschland und Zypern arbeiten Sie in einem spannenden, international t\u00e4tigen Marktsegment. Mit unserer breiten Produktpalette decken Sie einen Gro\u00dfteil des Bankgesch\u00e4ftes ab, wodurch Sie von Ihrer Kundschaft als ernstzunehmender Dienstleister wertgesch\u00e4tzt werden. Unsere hohe Innovationsfreudigkeit und die Bereitschaft zu Ver\u00e4nderungen gibt Ihnen die M\u00f6glichkeit, aktiv an der Gestaltung Ihres Bereiches mitzuwirken und sicherzustellen, dass wir auch zuk\u00fcnftig zu den ersten Adressen f\u00fcr die die maritime Kundschaft z\u00e4hlen. Kommen Sie an Bord und seien Sie ein Teil unseres Teams!\nWelche Aufgaben erwarten Sie?\nDirekter vertrauensvoller Ansprechpartner f\u00fcr unsere Kunden mit einer ganzheitlichen Verantwortung f\u00fcr das entsprechende Kundenportfolio, inklusive Ertragsverantwortung \u2013 insbesondere mit Bezug auf das kommerzielle Bankgesch\u00e4ft\nAkquisition neuer Kunden sowie laufende Pflege und Ausbau bestehender Kundenbeziehungen in der Schifffahrt\nSicherstellung des reibungslosen, prozesskonformen Ablaufs des Tagesgesch\u00e4fts (u. a. Cash Management, Betriebsmittelfinanzierung, Garantiegesch\u00e4ft, Zins- und W\u00e4hrungsmanagement)\nTeam\u00fcbergreifende Weiterentwicklung von Prozessen und kommerziellen Bankprodukten\nKoordination und Durchf\u00fchrung des (digitalen) Client-Onboardings (Kontoer\u00f6ffnung inkl. KYC-Check)\nWen suchen wir?\nErfolgreich abgeschlossene Bankausbildung und/oder wirtschaftswissenschaftliches Studium\nEinschl\u00e4gige Erfahrung in der Firmenkundenbetreuung oder im kommerziellen Bankgesch\u00e4ft, idealerweise im Schifffahrtsbereich\nSehr gute Deutsch- und Englischkenntnisse in Wort und Schrift\nAusgezeichnete Serviceorientierung mit der F\u00e4higkeit, eine prominente und repr\u00e4sentative Rolle in einem internationalen Gesch\u00e4ftsumfeld zu \u00fcbernehmen.\nWas wir Ihnen bieten:\nFlexible Arbeitszeiten innerhalb einer 39-Stunden-Woche\n30 Tage Jahresurlaub sowie zus\u00e4tzliche freie Tage am 24. und 31. Dezember\nVielseitiges und spannendes Aufgabengebiet in einem modernen und dynamischen Umfeld sowie wertsch\u00e4tzendes Betriebsklima\nGezielte F\u00f6rderung durch interne und externe Schulungs- und Entwicklungsprogramme\nBerenberg-Patensystem f\u00fcr ein strukturiertes und reibungsloses Onboarding\nVielf\u00e4ltige Zusch\u00fcsse (z. B. Deutschlandticket, JobRad, verm\u00f6genswirksame Leistungen, betriebliche Altersvorsorge, Essenszusch\u00fcsse bzw. Betriebsrestaurant in Hamburg)\nZus\u00e4tzliche Leistungen wie Familienservice, Arbeitszeitkonto (z. B. f\u00fcr Sabbaticals), betriebliche Sozialleistungen, Gesundheits- und Sportprogramme\nBewerben Sie sich jetzt online und werden Sie Teil des Teams \u2013\nwir freuen uns auf Ihre Bewerbung!\nAls eine f\u00fchrende europ\u00e4ische Privatbank mit \u00fcber 430 Jahren Erfahrung blicken wir auf eine lange Unternehmensgeschichte zur\u00fcck. Gleichzeitig gestalten wir mit umfassenden Investitionen aktiv unsere Zukunft. Grundlage f\u00fcr unseren Fortschritt und unsere Weiterentwicklung sind unsere Mitarbeiter. Wir ermutigen diese, neue Ans\u00e4tze auszuprobieren, ihre Ideen mit einzubringen und ihren eigenen Weg zum Erfolg bei uns zu gehen. Wir sind ein ambitioniertes, zukunftsorientiertes Unternehmen, das jahrhundertelange Erfahrung und Innovationskraft vereint.\nBei uns erleben Sie eine Kultur, die zum selbstst\u00e4ndigen Denken anregt, Unternehmertum f\u00f6rdert und dazu ermutigt, den Status quo zu hinterfragen. Wir legen gro\u00dfen Wert auf die Zusammenarbeit vor Ort \u2013 unser B\u00fcro ist ein zentraler Ort des Dialogs, der Innovation und des gemeinsamen Wachstums. Sie treffen hier auf talentierte Kollegen, die es gewohnt sind, Verantwortung zu \u00fcbernehmen, und gemeinsam an einem Strang ziehen, um Ergebnisse zu erzielen.\nWerden Sie Teil von Berenberg und arbeiten Sie mit uns gemeinsam daran, das Richtige f\u00fcr unsere Kunden, unser Gesch\u00e4ft und unsere Mitarbeiter zu tun \u2013\nOur future is where you take us!\nAus organisatorischen Gr\u00fcnden nehmen wir nur Bewerbungen an, die uns \u00fcber unser Online-Bewerbermanagementsystem auf der Website erreichen.\n*Aus Gr\u00fcnden der besseren Lesbarkeit wird auf die gleichzeitige Verwendung mehrgeschlechtlicher Sprachformen verzichtet. S\u00e4mtliche Personenbezeichnungen gelten gleichwohl f\u00fcr jegliches Geschlecht. Bei uns sind alle Bewerbungen willkommen, unabh\u00e4ngig von Geschlecht, Nationalit\u00e4t, ethnischer Herkunft, sozialem Hintergrund, Behinderung, Religion, Alter oder sexueller Orientierung. Bei Fragen wenden Sie sich bitte an unser Recruitment-Team unter recruitment@berenberg.de.\nBack to job list\nApply\nShare this job:\nShare Client Relationship Manager* Shipping with a friend via e-mail",
        "application_url": "https://berenberg.avature.net/en_GB/careers/Login?jobId=2793",
        "metadata": {
            "Country": "Germany",
            "City": "Hamburg",
            "Type of role": "Professional",
            "Working time": "Full-time",
            "Type of contract": "Permanent",
            "Remaining openings": "1"
        },
        "link": "https://berenberg.avature.net/en_GB/careers/JobDetail/Client-Relationship-Manager-Shipping/2793"
    },
    {
        "title": null,
        "description_html": null,
        "description_text": "Anti-Financial Crime Compliance Spezialist*\nGeneral information\nCountry\nGermany\nCity\nFrankfurt, Hamburg\nType of role\nProfessional\nWorking time\nFull-time\nType of contract\nPermanent\nRemaining openings\n1\nDescription & Requirements\nZur Verst\u00e4rkung unserer\nAnti-Financial Crime Compliance (AFC Compliance)\nim Bereich Group Compliance in\nHamburg/Frankfurt\nsuchen wir zum\nn\u00e4chstm\u00f6glichen Zeitpunkt\nSie als\nAnti-Financial Crime Compliance Spezialist*\nIhre Rolle im Team\nSie stellen die Einhaltung nationaler und internationaler Sanktions- und Embargovorgaben sicher und pr\u00fcfen Zahlungen, Wertpapiertransaktionen sowie Vertragspartner risikoorientiert. Sie bearbeiten Treffer-Alerts im Zahlungsverkehr nach revisionssicheren Standards und stehen im engen Austausch mit internationalen Korrespondenzbanken. Dar\u00fcber hinaus beraten Sie Marktbereiche zu regulatorischen Anforderungen, begleiten KYC/CDD-Prozesse und entwickeln das AML/CTF-Framework inklusive Trainings- und Risikoanalysen kontinuierlich weiter.\nWelche Aufgaben erwarten Sie?\nPr\u00fcfung von Zahlungen, Wertpapiertransaktionen und Vertragspartnern auf (inter-)nationale Embargo- und Sanktionsbestimmungen\nBearbeitung von Treffer-Alerts im Zahlungsverkehr unter Einhaltung revisionssicherer Prozesse\nAbstimmung mit (internationalen) Korrespondenzbanken zur Umsetzung von Sanktionspr\u00e4ventionsma\u00dfnahmen\nBeratung der Marktbereiche zu regulatorischen Anforderungen, KYC/CDD und Kundenonboarding\nKonzeption von Awareness-Trainings, Aktualisierung von Risikoanalysen und des AML/CTF-Frameworks\nWen suchen wir?\nAbgeschlossene Bankausbildung oder fundiertes Fachwissen zu Prozessen, Produkten und Dienstleistungen in Kreditinstituten oder Wirtschaftspr\u00fcfungs-/Beratungsgesellschaften.\nMehrj\u00e4hrige Erfahrung in Pr\u00fcfung und Umsetzung (inter-)nationaler Sanktionsbestimmungen sowie in der Pr\u00e4vention von Geldw\u00e4sche, Terrorismusfinanzierung, Betrug und Korruption, idealerweise in internationalen Banken.\nPraktische Erfahrung mit AFC-Compliance-Monitoring-Systemen einschlie\u00dflich revisionssicherer Fallbearbeitung.\nErfahrung in Projektarbeit sowie analytische, proaktive und eigenmotivierte Arbeitsweise.\nSehr gute Deutsch- und Englischkenntnisse, sicheres Auftreten und Durchsetzungsverm\u00f6gen.\nWas wir Ihnen bieten:\nFlexible Arbeitszeiten innerhalb einer 39-Stunden-Woche\n30 Tage Jahresurlaub\nVielseitiges und spannendes Aufgabengebiet in einem modernen und dynamischen Umfeld sowie wert-sch\u00e4tzendes Betriebsklima\nGezielte F\u00f6rderung durch interne und externe Schulungs- und Entwicklungsprogramme\nBerenberg-Patensystem f\u00fcr ein strukturiertes und reibungsloses Onboarding\nVielf\u00e4ltige Zusch\u00fcsse (z. B. Deutschlandticket, JobRad, verm\u00f6genswirksame Leistungen, betriebliche Altersvorsorge)\nZus\u00e4tzliche Leistungen wie Familienservice, Arbeitszeitkonto (z. B. f\u00fcr Sabbaticals), betriebliche Sozialeistungen, Gesundheits- und Sportprogramme\nBewerben Sie sich jetzt online und werden Sie Teil des Teams \u2013\nwir freuen uns auf Ihre Bewerbung!\nAls eine f\u00fchrende europ\u00e4ische Privatbank mit \u00fcber 430 Jahren Erfahrung blicken wir auf eine lange Unternehmensgeschichte zur\u00fcck. Gleichzeitig gestalten wir mit umfassenden Investitionen aktiv unsere Zukunft. Grundlage f\u00fcr unseren Fortschritt und unsere Weiterentwicklung sind unsere Mitarbeiter. Wir ermutigen diese, neue Ans\u00e4tze auszuprobieren, ihre Ideen mit einzubringen und ihren eigenen Weg zum Erfolg bei uns zu gehen. Wir sind ein ambitioniertes, zukunftsorientiertes Unternehmen, das jahrhundertelange Erfahrung und Innovationskraft vereint. Bei uns erleben Sie eine Kultur, die zum selbstst\u00e4ndigen Denken anregt, Unternehmertum f\u00f6rdert und dazu ermutigt, den Status quo zu hinterfragen. Sie treffen hier auf talentierte Kollegen, die es gewohnt sind, Verantwortung zu \u00fcbernehmen, und gemeinsam an einem Strang ziehen, um Ergebnisse zu erzielen.\nWerden Sie Teil von Berenberg und arbeiten Sie mit uns gemeinsam daran, das Richtige f\u00fcr unsere Kunden, unser Gesch\u00e4ft und unsere Mitarbeiter zu tun \u2013\nOur future is where you take us!\nAus organisatorischen Gr\u00fcnden nehmen wir nur Bewerbungen an, die uns \u00fcber unser Online-Bewerbermanagementsystem auf der Website erreichen.\n*Aus Gr\u00fcnden der besseren Lesbarkeit wird auf die gleichzeitige Verwendung mehrgeschlechtlicher Sprachformen verzichtet. S\u00e4mtliche Personenbezeichnungen gelten gleichwohl f\u00fcr jegliches Geschlecht.Bei uns sind alle Bewerbungen willkommen, unabh\u00e4ngig von Geschlecht, Nationalit\u00e4t, ethnischer Herkunft, sozialem Hintergrund, Behinderung, Religion, Alter oder sexueller Orientierung.Bei Fragen wenden Sie sich bitte an unser Recruitment-Team unter recruitment@berenberg.de.\nBack to job list\nApply\nShare this job:\nShare Anti-Financial Crime Compliance Spezialist* with a friend via e-mail",
        "application_url": "https://berenberg.avature.net/en_GB/careers/Login?jobId=2814",
        "metadata": {
            "Country": "Germany",
            "City": "Frankfurt, Hamburg",
            "Type of role": "Professional",
            "Working time": "Full-time",
            "Type of contract": "Permanent",
            "Remaining openings": "1"
        },
        "link": "https://berenberg.avature.net/en_GB/careers/JobDetail/Anti-Financial-Crime-Compliance-Spezialist/2814"
    },
    {
        "title": null,
        "description_html": null,
        "description_text": "Praktikant Wealth Management Origination\nGeneral information\nCountry\nGermany\nCity\nHamburg\nType of role\nInternship (off-cycle)\nWorking time\nFull-time\nType of contract\nInternship\nRemaining openings\n1\nDescription & Requirements\nUnterst\u00fctzen Sie unser\nOrigination-Team\nin\nHamburg\nidealerweise\nab Mai 2026\nals\nPraktikant*\nim Bereich Wealth Management Origination\nWelche Aufgaben erwarten Sie?\nIdentifikation und Erstansprache potenzieller Kunden (Start-ups, mittelst\u00e4ndische Familienunternehmen, Stiftungen und b\u00f6rsennotierte Unternehmen) im Rahmen der Akquisition\nMitverantwortung f\u00fcr die Koordination und Weiterentwicklung der Akquisitionsaktivit\u00e4ten im Wealth Management inklusive systematischer Neukundenprozessstrategie\nSystematische Markt- und Transaktionsbeobachtung zur Identifikation relevanter Trends und Leadpotenziale\nAufbereitung, Pflege und Nutzung von Markt- und Kundendaten zur professionellen Leadgenerierung in den Datensystemen\nUnterst\u00fctzung der Marktpr\u00e4senz durch Organisation von Veranstaltungen, Vorbereitung bereichs\u00fcbergreifender Abstimmungen sowie Erstellung von Marketing- und Corporate-Unterlagen\nWen suchen wir?\nAbgeschlossenes Studium oder fortgeschrittene Ausbildung in Wirtschaftswissenschaften, Finanzen oder einem vergleichbaren Fachgebiet\nErste relevante Erfahrung im Wealth Management oder in der Neukundengewinnung (z. B. durch Praktika, Projekte) bzw. stark ausgepr\u00e4gtes Interesse an diesem Umfeld\nSehr gute Kommunikations- und Pr\u00e4sentationsf\u00e4higkeiten sowie die F\u00e4higkeit, komplexe Sachverhalte adressatengerecht aufzubereiten\nTiefgehendes Verst\u00e4ndnis der Zielgruppe Unternehmer, Gr\u00fcnder und NextGen kombiniert mit analytischer St\u00e4rke in der Auswertung von Markt- und Unternehmensdaten\nSicherer Umgang mit MS Office (insbesondere Excel und PowerPoint) sowie hohe Motivation, Eigeninitiative und Belastbarkeit in einem dynamischen Umfeld\nWas wir Ihnen bieten:\nVielseitiges und spannendes Aufgabengebiet in einem modernen und dynamischen Umfeld sowie wertsch\u00e4tzendes Betriebsklima\nStrukturiertes und reibungsloses Onboarding\nZugang zu unseren internen \u201eLearning & Development\u201c-Angeboten wie z. B. den \u201eLunch & Learn\u201c-Sessions, Seminaren oder inspirierenden Vortr\u00e4gen\nM\u00f6glichkeit, im Anschluss Teil unseres Future-Talent-Programms zu werden, das unser exklusives Talentbindungsprogramm ist\nVielf\u00e4ltige Zusch\u00fcsse f\u00fcr z. B. Deutschlandticket und Pluxee-Schecks\nZus\u00e4tzliche Leistungen wie betriebliche Sportprogramme sowie Zugang zu einem externen Vorteilsportal mit exklusiven Angeboten\nBewerben Sie sich jetzt online mit Ihren vollst\u00e4ndigen Bewerbungsunterlagen inklusive Immatrikulationsbescheinigung mit Angabe des Fachsemesters. Angeh\u00f6rige von Staaten au\u00dferhalb des europ\u00e4ischen Wirtschaftsraums schicken ggf. bitte ihre Aufenthalts- und Arbeitsgenehmigung mit.\nWir freuen uns auf Ihre Bewerbung!\nAls eine f\u00fchrende europ\u00e4ische Privatbank mit \u00fcber 430 Jahren Erfahrung blicken wir auf eine lange Unternehmensgeschichte zur\u00fcck. Gleichzeitig gestalten wir mit umfassenden Investitionen aktiv unsere Zukunft. Grundlage f\u00fcr unseren Fortschritt und unsere Weiterentwicklung sind unsere Mitarbeiter. Wir ermutigen diese, neue Ans\u00e4tze auszuprobieren, ihre Ideen mit einzubringen und ihren eigenen Weg zum Erfolg bei uns zu gehen. Wir sind ein ambitioniertes, zukunftsorientiertes Unternehmen, das jahrhundertelange Erfahrung und Innovationskraft vereint. Bei uns erleben Sie eine Kultur, die zum selbstst\u00e4ndigen Denken anregt, Unternehmertum f\u00f6rdert und dazu ermutigt, den Status quo zu hinterfragen. Sie treffen hier auf talentierte Kollegen, die es gewohnt sind, Verantwortung zu \u00fcbernehmen, und gemeinsam an einem Strang ziehen, um Ergebnisse zu erzielen.\nWerden Sie Teil von Berenberg und arbeiten Sie mit uns gemeinsam daran, das Richtige f\u00fcr unsere Kunden, unser Gesch\u00e4ft und unsere Mitarbeiter zu tun -\nOur future is where you take us!\nAus organisatorischen Gr\u00fcnden nehmen wir nur Bewerbungen an, die uns \u00fcber unser Online-Bewerbermanagementsystem auf der Website erreichen.\n*Aus Gr\u00fcnden der besseren Lesbarkeit wird auf die gleichzeitige Verwendung mehrgeschlechtlicher Sprachformen verzichtet. S\u00e4mtliche Personenbezeichnungen gelten gleichwohl f\u00fcr jegliches Geschlecht.\nBei uns sind alle Bewerbungen willkommen, unabh\u00e4ngig von Geschlecht, Nationalit\u00e4t, ethnischer Herkunft, sozialem Hintergrund, Behinderung, Religion, Alter oder sexueller Orientierung.\nBei Fragen wenden Sie sich bitte an unser Recruitment-Team unter recruitment@berenberg.de\nBack to job list\nApply\nShare this job:\nShare Praktikant Wealth Management Origination with a friend via e-mail",
        "application_url": "https://berenberg.avature.net/en_GB/careers/Login?jobId=2798",
        "metadata": {
            "Country": "Germany",
            "City": "Hamburg",
            "Type of role": "Internship (off-cycle)",
            "Working time": "Full-time",
            "Type of contract": "Internship",
            "Remaining openings": "1"
        },
        "link": "https://berenberg.avature.net/en_GB/careers/JobDetail/Praktikant-Wealth-Management-Origination/2798"
    },
    {
        "title": null,
        "description_html": null,
        "description_text": "Vertriebsunterst\u00fctzung International Shipping\nGeneral information\nCountry\nGermany\nCity\nHamburg\nType of role\nProfessional\nWorking time\nFull-time\nType of contract\nPermanent\nRemaining openings\n1\nDescription & Requirements\nF\u00fcr unseren Bereich\nCorporate Banking / Shipping\nam Standort\nHamburg\nsuchen wir zum n\u00e4chstm\u00f6glichen Zeitpunkt Sie als\nVertriebsunterst\u00fctzung International Shipping\nIhre Rolle im Team\nIm Bereich Corporate Banking / Shipping betreuen wir internationale Schifffahrtsunternehmen bei der Abwicklung ihrer anspruchsvollen t\u00e4glichen Bankgesch\u00e4fte. Daf\u00fcr setzen wir sowohl auf moderne digitale Vertriebswege als auch auf kompetenten Service.\nF\u00fcr diese h\u00e4ufig global aktive Kundenklientel suchen wir eine engagierte Teamunterst\u00fctzung mit Organisationsf\u00e4higkeit, Verst\u00e4ndnis f\u00fcr digitale Prozesse sowie Freude an Kommunikation in einem dynamischen Umfeld.\nWelche Aufgaben erwarten Sie?\nVertriebsorientierte Unterst\u00fctzung der Relationship Manager bei allen t\u00e4glich anfallenden Aufgaben rund um die Kundenbetreuung (inkl. On-/ Offboarding, Recherche, Systempflege und Erstellung/ Pflege von Pr\u00e4sentationen)\nErstellung und Aufbereitung von Kundenkorrespondenz sowie selbstst\u00e4ndige Bearbeitung fachlicher Kundenauftr\u00e4ge (z.B. Festgelder, Zahlungsauftr\u00e4ge, Kontoschlie\u00dfungen)\nAutomatisierung und Optimierung der bestehenden Prozesse sowie projektbezogene Sonderaufgaben\nKoordination und Organisation von Terminen (inkl. Reiseplanung und -abrechnung)\nAllgemeine B\u00fcroorganisation und Verantwortung f\u00fcr administrative Abl\u00e4ufe\nWen suchen wir?\nErfolgreich abgeschlossene (bank-)kaufm\u00e4nnische Ausbildung oder vergleichbare fachliche Qualifikation\nTeam-/ Kundenorientiertes und kommunikatives Auftreten\nProzessorientiertes Denken und Handel sowie ein hoher Anspruch an Qualit\u00e4t, Sorgfalt und eigenverantwortlichem Arbeiten\nRoutinierter Umgang mit dem MS-Office-Paket sowie Verst\u00e4ndnis und Erfahrung im Umgang mit digitalen Medien\nFlie\u00dfendes Deutsch und sehr gute Englischkenntnisse in Wort und Schrift\nWas wir Ihnen bieten:\nFlexible Arbeitszeiten innerhalb einer 39-Stunden-Woche\n30 Tage Jahresurlaub sowie zus\u00e4tzliche freie Tage am 24. und 31. Dezember\nVielseitiges und spannendes Aufgabengebiet in einem modernen und dynamischen Umfeld sowie wertsch\u00e4tzendes Betriebsklima\nGezielte F\u00f6rderung durch interne und externe Schulungs- und Entwicklungsprogramme\nBerenberg-Patensystem f\u00fcr ein strukturiertes und reibungsloses Onboarding\nVielf\u00e4ltige Zusch\u00fcsse (z. B. Deutschlandticket, JobRad, verm\u00f6genswirksame Leistungen, betriebliche Altersvorsorge, Essenszusch\u00fcsse bzw. Betriebsrestaurant in Hamburg)\nZus\u00e4tzliche Leistungen wie Familienservice, Arbeitszeitkonto (z. B. f\u00fcr Sabbaticals), betriebliche Sozialleistungen, Gesundheits- und Sportprogramme\nBewerben Sie sich jetzt online und werden Sie Teil des Teams \u2013\nwir freuen uns auf Ihre Bewerbung!\nAls eine f\u00fchrende europ\u00e4ische Privatbank mit \u00fcber 430 Jahren Erfahrung blicken wir auf eine lange Unternehmensgeschichte zur\u00fcck. Gleichzeitig gestalten wir mit umfassenden Investitionen aktiv unsere Zukunft. Grundlage f\u00fcr unseren Fortschritt und unsere Weiterentwicklung sind unsere Mitarbeiter. Wir ermutigen diese, neue Ans\u00e4tze auszuprobieren, ihre Ideen mit einzubringen und ihren eigenen Weg zum Erfolg bei uns zu gehen. Wir sind ein ambitioniertes, zukunftsorientiertes Unternehmen, das jahrhundertelange Erfahrung und Innovationskraft vereint.\nBei uns erleben Sie eine Kultur, die zum selbstst\u00e4ndigen Denken anregt, Unternehmertum f\u00f6rdert und dazu ermutigt, den Status quo zu hinterfragen. Wir legen gro\u00dfen Wert auf die Zusammenarbeit vor Ort \u2013 unser B\u00fcro ist ein zentraler Ort des Dialogs, der Innovation und des gemeinsamen Wachstums. Sie treffen hier auf talentierte Kollegen, die es gewohnt sind, Verantwortung zu \u00fcbernehmen, und gemeinsam an einem Strang ziehen, um Ergebnisse zu erzielen.\nWerden Sie Teil von Berenberg und arbeiten Sie mit uns gemeinsam daran, das Richtige f\u00fcr unsere Kunden, unser Gesch\u00e4ft und unsere Mitarbeiter zu tun \u2013\nOur future is where you take us!\nAus organisatorischen Gr\u00fcnden nehmen wir nur Bewerbungen an, die uns \u00fcber unser Online-Bewerbermanagementsystem auf der Website erreichen.\n*Aus Gr\u00fcnden der besseren Lesbarkeit wird auf die gleichzeitige Verwendung mehrgeschlechtlicher Sprachformen verzichtet. S\u00e4mtliche Personenbezeichnungen gelten gleichwohl f\u00fcr jegliches Geschlecht. Bei uns sind alle Bewerbungen willkommen, unabh\u00e4ngig von Geschlecht, Nationalit\u00e4t, ethnischer Herkunft, sozialem Hintergrund, Behinderung, Religion, Alter oder sexueller Orientierung. Bei Fragen wenden Sie sich bitte an unser Recruitment-Team unter recruitment@berenberg.de.\nBack to job list\nApply\nShare this job:\nShare Vertriebsunterst\u00fctzung International Shipping with a friend via e-mail",
        "application_url": "https://berenberg.avature.net/en_GB/careers/Login?jobId=2807",
        "metadata": {
            "Country": "Germany",
            "City": "Hamburg",
            "Type of role": "Professional",
            "Working time": "Full-time",
            "Type of contract": "Permanent",
            "Remaining openings": "1"
        },
        "link": "https://berenberg.avature.net/en_GB/careers/JobDetail/Vertriebsunterst-tzung-International-Shipping/2807"
    },
    {
        "title": null,
        "description_html": null,
        "description_text": "(Junior) Investment Manager* Private Debt\nGeneral information\nCountry\nGermany\nCity\nFrankfurt, Hamburg, Munich\nType of role\nProfessional\nWorking time\nFull-time\nType of contract\nPermanent\nRemaining openings\n1\nDescription & Requirements\nF\u00fcr unser Team\nInfrastructure & Energy\nam Standort\nHamburg, Frankfurt am Main oder M\u00fcnchen\nsuchen wir Sie als\n(Junior) Investment Manager* Private Debt\nIhre Rolle im Team\nAls Mitarbeiter im Team Origination arbeiten Sie an der Anbahnung und Umsetzung von Projekten im Bereich Infrastructure & Energy, welches zum Zentralbereich Corporate, Wealth & Asset Management zugeordnet ist. Infrastructure & Energy hat mehrere Kreditfonds f\u00fcr Junior Debt- und Unitranchen Finanzierungen internationaler Projekte im Bereich Erneuerbare Energien, Energy Transition und Digitale Infrastruktur aufgelegt und agiert als Investment Advisor f\u00fcr diese Fonds. Das Team Origination ist dabei f\u00fcr das Deal Sourcing und gemeinsam mit dem Team Structuring f\u00fcr die Umsetzung der Transaktionen zust\u00e4ndig.\nPrivate Debt geh\u00f6rt zu den Alternative Investments und vereint Projektfinanzierung und Kommunikation mit Projekteigent\u00fcmern sowie die Betreuung von Fondsinvestoren. Unser erfahrenes Team in Hamburg und Frankfurt verf\u00fcgt \u00fcber eine langj\u00e4hrige Expertise und verantwortet \u00fcber alle Kreditfonds ca. 1 Mrd. EUR Assets Under Management. Die Sektoren Erneuerbaren Energien und Infrastruktur sind stark wachsende und nachhaltige Assetklassen innerhalb welcher wir in den letzten Jahren ein starkes Wachstum generieren konnten.\nWelche Aufgaben erwarten Sie?\nUnterst\u00fctzung des Projektleiters f\u00fcr die Verhandlung der Kreditdokumentation und Strukturierung von Finanzierungen f\u00fcr weltweite Projekte mit Fokus auf Windkraft, Photovoltaik, Energy Transition und Digitale Infrastruktur\nSteuerung der an der Finanzierung beteiligten Parteien (z. B. technische Berater, Anwaltskanzleien, Steuerberater und Wirtschaftspr\u00fcfer)\nErstellung von Cashflow-Modellen der finanzierten Projekte auf MS-Excel Basis\nUnterst\u00fctzung bei der Kunden- und Projektakquisitionen\nMitwirkung an der Konzeptionierung von neuen Produkt- und Fondsideen im Bereich Infrastructure & Energy\nErstellung und Bearbeitung von Kreditvorlagen sowie Projektanalysen zur Aufbereitung von Investitionsentscheidungen f\u00fcr die Fonds\nWen suchen wir?\nErfolgreich abgeschlossenes Studium der Wirtschaftswissenschaften, Rechtswissenschaften oder Ingenieurwesen\nErste praktische Erfahrungen in Transaktionsfinanzierung insbesondere im Bereich Infrastructure & Energy\nErste Erfahrungen mit Kredit- und Sicherheitendokumentation (LMA-Standards) sowie gutes Verst\u00e4ndnis von GuV, Cashflow und Bilanzen\nGute Kenntnisse in der Anwendung von MS-Excel, insbesondere im Financial-Modeling\nAusgepr\u00e4gte Kundenorientierung und hohe Kommunikationsf\u00e4higkeit\nFlie\u00dfende Deutsch- und verhandlungssichere Englischkenntnisse in Wort und Schrift\nWas wir Ihnen bieten:\nFlexible Arbeitszeiten innerhalb einer 39-Stunden-Woche\n30 Tage Jahresurlaub sowie zus\u00e4tzliche freie Tage am 24. und 31. Dezember\nVielseitiges und spannendes Aufgabengebiet in einem modernen und dynamischen Umfeld sowie wertsch\u00e4tzendes Betriebsklima\nGezielte F\u00f6rderung durch interne und externe Schulungs- und Entwicklungsprogramme\nBerenberg-Patensystem f\u00fcr ein strukturiertes und reibungsloses Onboarding\nVielf\u00e4ltige Zusch\u00fcsse (z. B. Deutschlandticket, JobRad, verm\u00f6genswirksame Leistungen, betriebliche Altersvorsorge, Essenszusch\u00fcsse bzw. Betriebsrestaurant in Hamburg)\nZus\u00e4tzliche Leistungen wie Familienservice, Arbeitszeitkonto (z. B. f\u00fcr Sabbaticals), betriebliche Sozialleistungen, Gesundheits- und Sportprogramme\nBewerben Sie sich jetzt online und werden Sie Teil des Teams \u2013\nwir freuen uns auf Ihre Bewerbung!\nAls eine f\u00fchrende europ\u00e4ische Privatbank mit \u00fcber 430 Jahren Erfahrung blicken wir auf eine lange Unternehmensgeschichte zur\u00fcck. Gleichzeitig gestalten wir mit umfassenden Investitionen aktiv unsere Zukunft. Grundlage f\u00fcr unseren Fortschritt und unsere Weiterentwicklung sind unsere Mitarbeiter. Wir ermutigen diese, neue Ans\u00e4tze auszuprobieren, ihre Ideen mit einzubringen und ihren eigenen Weg zum Erfolg bei uns zu gehen. Wir sind ein ambitioniertes, zukunftsorientiertes Unternehmen, das jahrhundertelange Erfahrung und Innovationskraft vereint.\nBei uns erleben Sie eine Kultur, die zum selbstst\u00e4ndigen Denken anregt, Unternehmertum f\u00f6rdert und dazu ermutigt, den Status quo zu hinterfragen. Wir legen gro\u00dfen Wert auf die Zusammenarbeit vor Ort \u2013 unser B\u00fcro ist ein zentraler Ort des Dialogs, der Innovation und des gemeinsamen Wachstums. Sie treffen hier auf talentierte Kollegen, die es gewohnt sind, Verantwortung zu \u00fcbernehmen, und gemeinsam an einem Strang ziehen, um Ergebnisse zu erzielen.\nWerden Sie Teil von Berenberg und arbeiten Sie mit uns gemeinsam daran, das Richtige f\u00fcr unsere Kunden, unser Gesch\u00e4ft und unsere Mitarbeiter zu tun \u2013\nOur future is where you take us!\nAus organisatorischen Gr\u00fcnden nehmen wir nur Bewerbungen an, die uns \u00fcber unser Online-Bewerbermanagementsystem auf der Website erreichen.\n*Aus Gr\u00fcnden der besseren Lesbarkeit wird auf die gleichzeitige Verwendung mehrgeschlechtlicher Sprachformen verzichtet. S\u00e4mtliche Personenbezeichnungen gelten gleichwohl f\u00fcr jegliches Geschlecht. Bei uns sind alle Bewerbungen willkommen, unabh\u00e4ngig von Geschlecht, Nationalit\u00e4t, ethnischer Herkunft, sozialem Hintergrund, Behinderung, Religion, Alter oder sexueller Orientierung. Bei Fragen wenden Sie sich bitte an unser Recruitment-Team unter recruitment@berenberg.de.\nBack to job list\nApply\nShare this job:\nShare (Junior) Investment Manager* Private Debt with a friend via e-mail",
        "application_url": "https://berenberg.avature.net/en_GB/careers/Login?jobId=2811",
        "metadata": {
            "Country": "Germany",
            "City": "Frankfurt, Hamburg, Munich",
            "Type of role": "Professional",
            "Working time": "Full-time",
            "Type of contract": "Permanent",
            "Remaining openings": "1"
        },
        "link": "https://berenberg.avature.net/en_GB/careers/JobDetail/Junior-Investment-Manager-Private-Debt/2811"
    },
    {
        "title": null,
        "description_html": null,
        "description_text": "(Senior) Full Stack Software Enginneer*\nGeneral information\nCountry\nGermany\nCity\nHamburg\nType of role\nProfessional\nWorking time\nFull-time\nType of contract\nPermanent\nRemaining openings\n1\nDescription & Requirements\nF\u00fcr unser Programm\nTransaction Technology\nin\nHamburg\nsuchen wir zum\nn\u00e4chstm\u00f6glichen Zeitpunkt\ndich als\n(Senior) Full Stack Software Engineer*\nInnovation & Technology @ Berenberg\nIn einer \u00c4ra, in der Digitalisierung und moderne IT-Infrastrukturen das Banking revolutionieren, gestalten wir eine technologiegest\u00fctzte Bank, in der du als IT-Profi eng mit unseren Gesch\u00e4ftsbereichen zusammenarbeitest. Unsere Technology-Teams bieten dir ein Umfeld, das dich vor spannende Herausforderungen stellt \u2013 sei es durch den Support und die Weiterentwicklung von Legacy-Systemen oder die Einf\u00fchrung moderner Technologien wie KI, Machine Learning und hochgradig automatisierte Handelsapplikationen.\nUnsere IT-Abteilung mit etwa 300 Mitarbeitern arbeitet gr\u00f6\u00dftenteils agil nach einem Scrumban-Ansatz und deckt Bereiche wie Cloud Computing, Cybersecurity, Operations, Process and Governance, Software Development und Architecture ab. Wir sind besonders stolz darauf, fast alle unsere Applikationen Inhouse zu entwickeln, was uns eine einzigartige Flexibilit\u00e4t und Innovationskraft verleiht. Unser Tech Stack umfasst moderne Technologien wie Java, Kotlin, TypeScript und Python, CI/CD-Pipelines, Container, Kubernetes sowie Azure Cloud, Azure SQL Database und Oracle Datenbank mit PL/SQL.\nDeine Rolle im Team\nIn deiner Rolle \u00fcbernimmst du Verantwortung f\u00fcr die technische Planung, das Softwaredesign sowie die Umsetzung und Qualit\u00e4tssicherung unserer Anwendungen. Du arbeitest aktiv im gesamten Entwicklungsprozess mit, von der Analyse neuer Anforderungen \u00fcber die Implementierung bis hin zu Tests und Deployments. Dabei bringst du dich mit eigenen Ideen ein und tr\u00e4gst zur kontinuierlichen Weiterentwicklung unserer Systemlandschaft bei.\nWelche Aufgaben erwarten Dich?\nWeiterentwicklung und Betreuung unseres Softwaresystems f\u00fcr Kapitalma\u00dfnahmen\nKontinuierliche Modernisierung und Pflege unserer Bestandsanwendungen im Bereich Wertpapierertr\u00e4gnisse\nEnge Zusammenarbeit im funktions\u00fcbergreifenden, agilen Team (Scrum) mit echtem Gestaltungsspielraum und kurzen Entscheidungswegen\nAktive Mitgestaltung der Systemarchitektur sowie Innovationstreiben bei der Technologieauswahl und der Optimierung bestehender Prozesse\nVerantwortung f\u00fcr Qualit\u00e4tssicherung, Testing und Dokumentation\nWen suchen wir?\nErfolgreich abgeschlossenes Studium der (Wirtschafts-)Informatik oder vergleichbare Qualifikation\nFundierte Kenntnisse in der Softwareentwicklung mit Java (idealerweise Java 21)\nErfahrung mit Plattformen wie Quarkus und/oder Spring Boot sowie Kubernetes (idealerweise in Microsoft Azure)\nSicherer Umgang mit REST, JMS sowie JPA/Hibernate und Oracle Datenbanken (inkl. PL/SQL)\nKenntnisse der Frontend-Technologien (React, TypeScript, JavaScript, Java Swing)\nSehr gute Deutsch- und Englischkenntnisse in Wort und Schrift\nWas wir Dir bieten:\nFlexible Arbeitszeiten innerhalb einer 39-Stunden-Woche\n30 Tage Jahresurlaub\nVielseitiges und spannendes Aufgabengebiet in einem modernen und dynamischen Umfeld sowie ein wertsch\u00e4tzendes Betriebsklima\nGezielte F\u00f6rderung durch interne und externe Schulungs- und Entwicklungsprogramme\nBerenberg-Patensystem f\u00fcr ein strukturiertes und reibungsloses Onboarding\nVielf\u00e4ltige Zusch\u00fcsse (z. B. Deutschlandticket, JobRad, verm\u00f6genswirksame Leistungen, betriebliche Altersvorsorge, Essenszusch\u00fcsse bzw. Betriebsrestaurant in Hamburg)\nZus\u00e4tzliche Leistungen wie Familienservice, Arbeitszeitkonto (z. B. f\u00fcr Sabbaticals), betriebliche Sozialleistungen, Gesundheits- und Sportprogramme\nBewirb dich jetzt online und werde Teil des Teams \u2013\nwir freuen uns auf deine Bewerbung!\nWir sind eine f\u00fchrende europ\u00e4ische Privatbank mit \u00fcber 430 Jahren Erfahrung und einer tief verwurzelten Geschichte, aber wir gestalten und investieren noch immer in Zukunft. Unser Fortschritt und unsere Entwicklung werden von unseren Mitarbeitern vorangetrieben. Wir ermutigen sie, neue Ans\u00e4tze auszuprobieren, ihre Meinung zu \u00e4u\u00dfern und auf ihre eigene Art und Weise erfolgreich zu sein.\nWir bieten ihnen die M\u00f6glichkeit, ihre Talente zu entwickeln, verschiedene Karrierewege zu erkunden und ihr Potenzial voll auszusch\u00f6pfen.\nWir sind ein ehrgeiziges, zukunftsorientiertes Unternehmen, das auf jahrhundertealte Traditionen zur\u00fcckgreift und auf Innovation baut. Du findest bei uns eine Kultur vor, die Menschen dazu ermutigt, unabh\u00e4ngig zu denken, unternehmerisch zu handeln und den Status quo in Frage zu stellen. Wir legen gro\u00dfen Wert auf die Zusammenarbeit vor Ort \u2013 unser B\u00fcro ist ein zentraler Ort des Dialogs, der Innovation und des gemeinsamen Wachstums. Gemeinsam arbeiten wir daran, unser Gesch\u00e4ft zu gestalten und unsere ehrgeizigen Ziele zu erreichen.\nWir freuen uns, wenn du dich uns anschlie\u00dft, um stets das Richtige f\u00fcr unsere Mitarbeiter, Kunden und unser Unternehmen zu tun \u2013\nOur future is where you take us!\nAus organisatorischen Gr\u00fcnden nehmen wir nur Bewerbungen an, die uns \u00fcber unser Online-Bewerbermanagementsystem auf der Website erreichen.\n*Aus Gr\u00fcnden der besseren Lesbarkeit wird auf die gleichzeitige Verwendung mehrgeschlechtlicher Sprachformen verzichtet. S\u00e4mtliche Personenbezeichnungen gelten gleichwohl f\u00fcr jegliches Geschlecht. Bei uns sind alle Bewerber willkommen, unabh\u00e4ngig von Geschlecht, Nationalit\u00e4t, ethnischer Herkunft, sozialem Hintergrund, Behinderung, Religion, Alter oder sexueller Orientierung. Bei Fragen wende dich bitte an unser Recruitment-Team unter recruitment@berenberg.de.\nBack to job list\nApply\nShare this job:\nShare (Senior) Full Stack Software Enginneer* with a friend via e-mail",
        "application_url": "https://berenberg.avature.net/en_GB/careers/Login?jobId=2802",
        "metadata": {
            "Country": "Germany",
            "City": "Hamburg",
            "Type of role": "Professional",
            "Working time": "Full-time",
            "Type of contract": "Permanent",
            "Remaining openings": "1"
        },
        "link": "https://berenberg.avature.net/en_GB/careers/JobDetail/Senior-Full-Stack-Software-Enginneer/2802"
    },
    {
        "title": null,
        "description_html": null,
        "description_text": "(Senior) ServiceNow Developer*\nGeneral information\nCountry\nUnited Kingdom\nCity\nLondon\nType of role\nProfessional\nWorking time\nFull-time\nType of contract\nPermanent\nRemaining openings\n1\nDescription & Requirements\nFor our\nInnovation & Technology department\nin\nLondon\nwe are looking to hire a:\n(Senior) ServiceNow Developer\nInnovation & Technology @ Berenberg\nIn an era where digitalisation and modern IT infrastructure is revolutionizing banking, we are shaping a technology-driven bank in which you as an IT professional will work closely with our business units. Our technology teams offer you an environment that will present you with exciting challenges - be it through the support and further development of legacy systems or the introduction of modern technologies such as AI, machine learning and highly automated trading applications.\nWhat will you do:\nDesign and implementation of intelligent ServiceNow solutions with a focus on ITSM, CSM, ITOM/Discovery (CMDB/CSDM), workflow automation, and REST integrations (inbound/outbound)\nActive involvement in the conception, design, and implementation of new modules and functionalities on the ServiceNow platform\nAnalysis of existing processes and development of tailored, user-centric solution concepts in close collaboration with stakeholders, architects, and developers\nEnd-to-end ownership of the development lifecycle\u2014from feature development and testing through rollout, documentation, and knowledge transfer\nEnsuring an efficient, sustainable system architecture in line with current best practices and standards\nWho are we looking for?\nA completed degree in (Business) Informatics, Industrial Engineering, or a comparable qualification\nSeveral years of professional experience in ServiceNow development, ideally complemented by certifications such as CSA, CIS ITSM, CIS ITOM/Discovery (CMDB/CSDM), App Engine, Flow Designer, or Playbooks\nStrong understanding of ITSM, ITOM, and CSM processes, with solid skills in JavaScript, HTML, CSS, and REST/JSON\nKnowledge of the ITIL framework and experience working in agile environments (e.g., Scrum)\nVery good German language skills and solid written and spoken English proficiency\nA structured, solution-oriented working style and a strong team mindset, with enthusiasm for collaboration in interdisciplinary teams\nWhat we offer you:\nPrivate pension plan - 10% of base salary contribution by Berenberg\nGenerous 30 day holiday allowance\nPrivate Health Insurance\nLife Insurance scheme\nFlexible working hours\nEnhanced parental leave policies\nEmployee Assistance Programme offering counselling sessions related to mental health, financial wellbeing and other topics\nApply online now to join our team \u2013\nwe look forward to receiving your application!\nWe are a leading European private bank, with over 430 years of experience and deep rooted history, but we are still shaping and heavily investing in our future. Our progress and evolution are driven by our people. We encourage them to try new approaches, voice their opinions and achieve success in their own way.\nWe provide opportunities for them to develop their talents, explore different career paths and achieve their full potential.\nWe\u2019re an ambitious, forward-looking business, backed by centuries of tradition and built on innovation. You\u2019ll find a culture that encourages people to think independently, act entrepreneurially and challenge the status quo.\nWe place great importance on working on site, as we believe that being together in the office not only fosters creativity and efficiency, but also strengthens networks and builds trusting, collegial relationships. For us, this forms the foundation for productive and successful work. Together we collaborate to shape our business and fulfil our ambitious goals.\nWe welcome you to join us in our commitment to always do the right thing for our people, clients and our business \u2013\nOur future is where you take us!\nWe will only accept applications submitted through our online application management system on the website.\nBerenberg is an Equal Opportunities Employer and prides itself on being a modern, dynamic and internationally orientated organisation. We value the rich diversity, skills and abilities and creative potential that people from differing backgrounds and experiences bring to the workplace. Every employee plays a vital role in providing quality service to all our customers and helping to create and inclusive working environment, where everyone can realise their full potential. We\u2019re committed to finding reasonable accommodations for candidates who require adjustments during our recruiting process. Please contact us directly on recruitment@berenberg.com to discuss.\nBack to job list\nApply\nShare this job:\nShare (Senior) ServiceNow Developer* with a friend via e-mail",
        "application_url": "https://berenberg.avature.net/en_GB/careers/Login?jobId=2805",
        "metadata": {
            "Country": "United Kingdom",
            "City": "London",
            "Type of role": "Professional",
            "Working time": "Full-time",
            "Type of contract": "Permanent",
            "Remaining openings": "1"
        },
        "link": "https://berenberg.avature.net/en_GB/careers/JobDetail/Senior-ServiceNow-Developer/2805"
    },
    {
        "title": null,
        "description_html": null,
        "description_text": "K8s/Kubernetes Platform Engineer*\nGeneral information\nCountry\nGermany\nCity\nHamburg\nType of role\nProfessional\nWorking time\nFull-time\nType of contract\nPermanent\nRemaining openings\n1\nDescription & Requirements\nFor our\nInnovation & Technology\ndepartment in\nHamburg\nwe are looking to hire a:\nKubernetes Platform Engineer*\nInnovation & Technology @ Berenberg\nIn an era where digitalisation and modern IT infrastructure is revolutionizing banking, we are shaping a technology-driven bank in which you as an IT professional will work closely with our business units. Our technology teams offer you an environment that will present you with exciting challenges - be it through the support and further development of legacy systems or the introduction of modern technologies such as AI, machine learning and highly automated trading applications.\nYour Role in the team:\nThis role is all about Kubernetes (K8s) where a DevOps mind and experience is going to be paramount. You will get involved in the design, setup and management of our K8s clusters across various datacentres. We are building a value-add on-prem, bare-metal K8s platform (with the option to expand into the cloud when the use cases arise) which will cater to a wide range workloads with different resource demands, ranging from latency sensitive, fast paced algo trading to big data analytics, middle and back-office applications as well as client and exchange gateways.\nWhat will you do?\nClose collaboration with our datacentre infrastructure and network engineers and will also overlap with the monitoring and observability domain.\nWorking in a DevOps approach that involves concepts of code review, automated testing and release pipelines\nWork in an environment that is protected by PAM (Privileged Access Management)\nWho are we looking for?\nUNIX / Linux (Ubuntu & Red Hat)\nK8s (must; administration as well as best-practise for usage), Calico Enterprise (desirable)\nNetworking, in particular TCP/IP in general as well as understanding routes, routing tables, VLAN / VRF concepts, BGP\nBash, Python, Ansible, Terraform, Helm and Git\nAccustomed to working in a DevOps approach that involves concepts of code review, automated testing and release pipelines\nAccustomed to work in an environment that is protected by PAM (Privileged Access Management)\nWhat we offer you:\nPrivate pension plan - 10% of base salary contribution by Berenberg\nGenerous 30 day holiday allowance\nPrivate Health Insurance\nLife Insurance scheme\nFlexible working hours\nEnhanced parental leave policies\nEmployee Assistance Programme offering counselling sessions related to mental health, financial wellbeing and other topics\nApply online now to join our team \u2013\nwe look forward to receiving your application!\nWe are a leading European private bank, with over 430 years of experience and deep rooted history, but we are still shaping and heavily investing in our future. Our progress and evolution are driven by our people. We encourage them to try new approaches, voice their opinions and achieve success in their own way.\nWe provide opportunities for them to develop their talents, explore different career paths and achieve their full potential.\nWe\u2019re an ambitious, forward-looking business, backed by centuries of tradition and built on innovation. You\u2019ll find a culture that encourages people to think independently, act entrepreneurially and challenge the status quo.\nWe place great importance on working on site, as we believe that being together in the office not only fosters creativity and efficiency, but also strengthens networks and builds trusting, collegial relationships. For us, this forms the foundation for productive and successful work. Together we collaborate to shape our business and fulfil our ambitious goals.\nWe welcome you to join us in our commitment to always do the right thing for our people, clients and our business\n\u2013 Our future is where you take us!\nWe will only accept applications submitted through our online application management system on the website.\nBerenberg is an Equal Opportunities Employer and prides itself on being a modern, dynamic and internationally orientated organisation. We value the rich diversity, skills and abilities and creative potential that people from differing backgrounds and experiences bring to the workplace. Every employee plays a vital role in providing quality service to all our customers and helping to create and inclusive working environment, where everyone can realise their full potential. We\u2019re committed to finding reasonable accommodations for candidates who require adjustments during our recruiting process. Please contact us directly on recruitment@berenberg.com to discuss.\nBack to job list\nApply\nShare this job:\nShare K8s/Kubernetes Platform Engineer* with a friend via e-mail",
        "application_url": "https://berenberg.avature.net/en_GB/careers/Login?jobId=2806",
        "metadata": {
            "Country": "Germany",
            "City": "Hamburg",
            "Type of role": "Professional",
            "Working time": "Full-time",
            "Type of contract": "Permanent",
            "Remaining openings": "1"
        },
        "link": "https://berenberg.avature.net/en_GB/careers/JobDetail/K8s-Kubernetes-Platform-Engineer/2806"
    },
    {
        "title": null,
        "description_html": null,
        "description_text": "Werkstudent* Transaction Services\nGeneral information\nCountry\nGermany\nCity\nHamburg\nType of role\nWorking Student\nWorking time\nPart-time\nType of contract\nWorking Student\nRemaining openings\n1\nDescription & Requirements\nUnterst\u00fctzen Sie unser\nSecurities Clearing Team\nin Hamburg idealerweise f\u00fcr\n6\u201312 Monate\nmit\n15\u201320 Stunden w\u00f6chentlich\nals\nWerkstudent* Securities Clearing, Transaction Services\nWen suchen wir?\nUnterst\u00fctzung im Tagesgesch\u00e4ft bei Wertpapieren\nUnterst\u00fctzung bei der fachlichen Betreuung der Bewertungskurs- und Gattungsdaten f\u00fcr die Bank\nBearbeitung der Marktgerechtigkeitspr\u00fcfung\nWas wir Ihnen bieten:\nMindestens ein erfolgreich abgeschlossenes Semester eines Bachelorstudiums mit technischen oder betriebswirtschaftlichen Inhalten (z. B. Wirtschaftsinformatik)\nIdealerweise erste Erfahrung in der Unternehmensberatung oder im Bankenumfeld, z. B. durch Praktika\nIT-Affinit\u00e4t und sicherer Umgang mit MS Office (insbesondere Excel)\nSchnelle Auffassungsgabe\nSelbstst\u00e4ndige, sorgf\u00e4ltige und zielorientierte Arbeitsweise\nTeamf\u00e4higkeit, Flexibilit\u00e4t, Kontaktfreude und hohes Engagement\nWas wir Ihnen bieten:\nVielseitiges und spannendes Aufgabengebiet in einem modernen und dynamischen Umfeld sowie ein wertsch\u00e4tzendes Betriebsklima\nStrukturiertes und reibungsloses Onboarding\nZugang zu unseren internen \u201eLearning & Development\u201c-Angeboten wie z. B. den \u201eLunch & Learn\u201c-Sessions, Seminaren oder inspirierenden Vortr\u00e4gen\nM\u00f6glichkeit, im Anschluss Teil unseres Future Talent Programms zu werden, welches unser exklusives Talentbindungsprogramm ist\nVielf\u00e4ltige Zusch\u00fcsse, z. B. f\u00fcr das Deutschlandticket und Essenszusch\u00fcsse\nZus\u00e4tzliche Leistungen wie betriebliche Sportprogramme sowie Zugang zu einem externen Vorteilsportal mit exklusiven Angeboten\nBewerben Sie sich jetzt online mit Ihren vollst\u00e4ndigen Bewerbungsunterlagen inklusive Immatrikulationsbescheinigung mit Angabe des Fachsemesters. Angeh\u00f6rige von Staaten au\u00dferhalb des europ\u00e4ischen Wirtschaftsraums schicken ggf. bitte ihre Aufenthalts- und Arbeitsgenehmigung mit.\nWir freuen uns auf Ihre Bewerbung!\nAls eine f\u00fchrende europ\u00e4ische Privatbank mit \u00fcber 430 Jahren Erfahrung blicken wir auf eine lange Unternehmensgeschichte zur\u00fcck. Gleichzeitig gestalten wir mit umfassenden Investitionen aktiv unsere Zukunft. Grundlage f\u00fcr unseren Fortschritt und unsere Weiterentwicklung sind unsere Mitarbeiter. Wir ermutigen diese, neue Ans\u00e4tze auszuprobieren, ihre Ideen mit einzubringen und ihren eigenen Weg zum Erfolg bei uns zu gehen. Wir sind ein ambitioniertes, zukunftsorientiertes Unternehmen, das jahrhundertelange Erfahrung und Innovationskraft vereint.\nBei uns erleben Sie eine Kultur, die zum selbstst\u00e4ndigen Denken anregt, Unternehmertum f\u00f6rdert und dazu ermutigt, den Status quo zu hinterfragen. Wir legen gro\u00dfen Wert auf die Zusammenarbeit vor Ort \u2013 unser B\u00fcro ist ein zentraler Ort des Dialogs, der Innovation und des gemeinsamen Wachstums. Sie treffen hier auf talentierte Kollegen, die es gewohnt sind, Verantwortung zu \u00fcbernehmen, und gemeinsam an einem Strang ziehen, um Ergebnisse zu erzielen.\nWerden Sie Teil von Berenberg und arbeiten Sie mit uns gemeinsam daran, das Richtige f\u00fcr unsere Kunden, unser Gesch\u00e4ft und unsere Mitarbeiter zu tun \u2013\nOur future is where you take us!\nAus organisatorischen Gr\u00fcnden nehmen wir nur Bewerbungen an, die uns \u00fcber unser Online-Bewerbermanagementsystem auf der Website erreichen.\n*Aus Gr\u00fcnden der besseren Lesbarkeit wird auf die gleichzeitige Verwendung mehrgeschlechtlicher Sprachformen verzichtet. S\u00e4mtliche Personenbezeichnungen gelten gleichwohl f\u00fcr jegliches Geschlecht. Bei uns sind alle Bewerbungen willkommen, unabh\u00e4ngig von Geschlecht, Nationalit\u00e4t, ethnischer Herkunft, sozialem Hintergrund, Behinderung, Religion, Alter oder sexueller Orientierung. Bei Fragen wenden Sie sich bitte an unser Recruitment-Team unter recruitment@berenberg.de.\nBack to job list\nApply\nShare this job:\nShare Werkstudent* Transaction Services with a friend via e-mail",
        "application_url": "https://berenberg.avature.net/en_GB/careers/Login?jobId=2790",
        "metadata": {
            "Country": "Germany",
            "City": "Hamburg",
            "Type of role": "Working Student",
            "Working time": "Part-time",
            "Type of contract": "Working Student",
            "Remaining openings": "1"
        },
        "link": "https://berenberg.avature.net/en_GB/careers/JobDetail/Werkstudent-Transaction-Services/2790"
    },
    {
        "title": null,
        "description_html": null,
        "description_text": "Analyst, Equity Syndicate\nGeneral information\nCountry\nGermany\nCity\nFrankfurt\nType of role\nProfessional\nWorking time\nFull-time\nType of contract\nPermanent\nRemaining openings\n1\nDescription & Requirements\nOur\nEuropean Equity Syndicate\nteam in\nFrankfurt\nis looking to hire an\nAnalyst, Equity Syndicate\nOur Equity Syndicate team is part of the Investment Banking Division and is responsible for all our equity capital markets activity across Europe. The department covers all equity-related capital market transactions such as Initial Public Offerings, Capital Increases and Secondary Placings in Europe and has built a strong reputation as one of the leading equity capital markets houses, particularly in the DACH region and the UK, with a growing presence in the rest of Europe.\nThe team in Frankfurt offers a modern, dynamic and ambitious working environment with a steep learning curve. From day one, you will gain hands-on exposure to live transactions and work closely with senior bankers, investors and internal stakeholders. The role offers an attractive opportunity for an ambitious and motivated candidate to start a career in investment banking.\nWhat will you do?\nAssist in running equity and equity-linked transactions (such as IPOs, Rights Issues, Accelerated Book-buildings and Convertible Bonds), including investor marketing, bookbuilding and allocation\nClosely liaise with international institutional investors across key global markets as well as internal teams, including equity sales, research and traders\nSupport in investor marketing processes, including preparation for roadshows, investor education and wall-crossings;\nDevelopment of presentation materials for clients and investors, including pitch books, marketing and transaction documents, ongoing capital market updates and steering committee meetings;\nContinuous collaboration with senior management across all work streams and tasks;\nConduct in-depth equity market and transaction analyses and maintain various financial databases\nWho are we looking for?\nExcellent academic background with a degree from at a top university, ideally in Economics, Finance or Business\nPrevious experience within investment banking, corporate finance or equity sales\nStrong interest in equity capital markets with a good understanding of market dynamics and key drivers of company valuation\nQuick and keen learner with the ability to multitask and perform under time pressure, while keeping attention to detail\nStrong ability to work in a team, entrepreneurial mindset and commitment to further develop one of the leading equity franchises\nFluency in English and German is essential, familiarity with capital markets data platforms (e.g. Bloomberg) is an advantage\nWhat we offer you:\n30 days of annual leave\nA varied and exciting range of tasks in a modern and dynamic environment as well as a respectful working atmosphere\nTargeted support through internal and external training and development programmes\nBerenberg mentor system for structured and smooth onboarding\nHands-on exposure to live ECM transactions across Europe from an early stage\nVarious allowances (e.g. Germany ticket, JobRad, capital formation, a company-financed pension scheme, restaurant vouchers)\nAdditional benefits such as family services, working time account (e.g. for sabbaticals), corporate bene-fits and company health and sports programmes\nApply online now to join our team \u2013\nwe look forward to receiving your application!\nWe are a leading European private bank, with over 430 years of experience and deep rooted history, but we are still shaping and heavily investing in our future. Our progress and evolution are driven by our people. We encourage them to try new approaches, voice their opinions and achieve success in their own way. We provide opportunities for them to develop their talents, explore different career paths and achieve their full potential.\nWe\u2019re an ambitious, forward-looking business, backed by centuries of tradition and built on innovation. You\u2019ll find a culture that encourages people to think independently, act entrepreneurially and challenge the status quo. We place great importance on working on site, as we believe that being together in the office not only fosters creativity and efficiency, but also strengthens networks and builds trusting, collegial relationships. For us, this forms the foundation for productive and successful work. Together we collaborate to shape our business and fulfil our ambitious goals.\nWe welcome you to join us in our commitment to always do the right thing for our people, clients and our business \u2013\nOur future is where you take us!\nFor organisational reasons, we only accept applications that reach us via our online application management system on the website.\n*For reasons of better readability, the simultaneous use of multi-gender language forms is avoided. All personal designations apply equally to all genders. We welcome all applications, regardless of gender, nationality, ethnic origin, social background, disability, religion, age or sexual orientation. If you have any questions, please contact our recruitment team at recruitment@berenberg.de.\nBack to job list\nApply\nShare this job:\nShare Analyst, Equity Syndicate with a friend via e-mail",
        "application_url": "https://berenberg.avature.net/en_GB/careers/Login?jobId=2803",
        "metadata": {
            "Country": "Germany",
            "City": "Frankfurt",
            "Type of role": "Professional",
            "Working time": "Full-time",
            "Type of contract": "Permanent",
            "Remaining openings": "1"
        },
        "link": "https://berenberg.avature.net/en_GB/careers/JobDetail/Analyst-Equity-Syndicate/2803"
    },
    {
        "title": null,
        "description_html": null,
        "description_text": "(Junior) Equity Derivatives Sales Trader*\nGeneral information\nCountry\nGermany\nCity\nHamburg\nType of role\nProfessional\nWorking time\nFull-time\nType of contract\nPermanent\nRemaining openings\n1\nDescription & Requirements\nF\u00fcr unsere Abteilung\nEquity and Derivatives Trading Execution Europe\nin\nHamburg\nsuchen wir zum\nn\u00e4chstm\u00f6glichen\nZeitpunkt Sie als\n(Junior) Equity Derivatives Sales Trader*\nWelche Aufgaben erwarten Sie?\nHandelst\u00e4tigkeiten (Execution) an den weltweiten Terminm\u00e4rkten mit europ\u00e4ischem Fokus (Eurex)\nAnalyse und Beobachtung der relevanten Terminm\u00e4rkte, insbesondere der Eurex\nAnalyse von Volatilit\u00e4ten, Hedging-Parametern und weiteren wichtigen derivativen Kennziffern zur Steuerung von Portfolios unter Beachtung der jeweils g\u00fcltigen Richtlinien\nKontrolle und Berechnung von Risikopreisen an der Eurex und im OTC-Markt f\u00fcr institutionelle Kunden\nHandel des entsprechenden Basiswerts anhand der errechneten Parameter\nAkquisition neuer institutioneller Investoren\nWen suchen wir?\nErfolgreich abgeschlossene Ausbildung im Finanzbereich oder abgeschlossenes Studium mit dem Schwerpunkt BWL oder Finance\nBerufserfahrung in den beschriebenen Aufgabenfeldern sowie Besitz der entsprechenden Handelszulassungen\nKenntnisse im Umgang mit institutionellen Investoren und Erfahrung mit Equity Derivatives Sales sowie in der Execution derivativer Produkte\nRoutinierter Umgang mit Bloomberg und MS Office (insbesondere MS Excel); Kenntnisse in anderen Handelssystemen w\u00fcnschenswert\nGutes Deutsch und Englisch\nHervorragende analytische F\u00e4higkeiten, zielorientierte Vorgehensweise und Freude an dynamischen M\u00e4rkten\nHohe Teamf\u00e4higkeit, Flexibilit\u00e4t und Einsatzbereitschaft\nWas wir Ihnen bieten:\nFlexible Arbeitszeiten innerhalb einer 39-Stunden-Woche\n30 Tage Jahresurlaub sowie zus\u00e4tzliche freie Tage am 24. und 31. Dezember\nVielseitiges und spannendes Aufgabengebiet in einem modernen und dynamischen Umfeld sowie wertsch\u00e4tzendes Betriebsklima\nGezielte F\u00f6rderung durch interne und externe Schulungs- und Entwicklungsprogramme\nBerenberg-Patensystem f\u00fcr ein strukturiertes und reibungsloses Onboarding\nVielf\u00e4ltige Zusch\u00fcsse (z. B. Deutschlandticket, JobRad, verm\u00f6genswirksame Leistungen, betriebliche Altersvorsorge, Essenszusch\u00fcsse bzw. Betriebsrestaurant in Hamburg)\nZus\u00e4tzliche Leistungen wie Familienservice, Arbeitszeitkonto (z. B. f\u00fcr Sabbaticals), betriebliche Sozialleistungen, Gesundheits- und Sportprogramm\nBewerben Sie sich jetzt online und werden Sie Teil des Teams \u2013\nwir freuen uns auf Ihre Bewerbung!\nAls eine f\u00fchrende europ\u00e4ische Privatbank mit \u00fcber 430 Jahren Erfahrung blicken wir auf eine lange Unternehmensgeschichte zur\u00fcck. Gleichzeitig gestalten wir mit umfassenden Investitionen aktiv unsere Zukunft. Grundlage f\u00fcr unseren Fortschritt und unsere Weiterentwicklung sind unsere Mitarbeiter. Wir ermutigen diese, neue Ans\u00e4tze auszuprobieren, ihre Ideen mit einzubringen und ihren eigenen Weg zum Erfolg bei uns zu gehen. Wir sind ein ambitioniertes, zukunftsorientiertes Unternehmen, das jahrhundertelange Erfahrung und Innovationskraft vereint. Bei uns erleben Sie eine Kultur, die zum selbstst\u00e4ndigen Denken anregt, Unternehmertum f\u00f6rdert und dazu ermutigt, den Status quo zu hinterfragen. Sie treffen hier auf talentierte Kollegen, die es gewohnt sind, Verantwortung zu \u00fcbernehmen, und gemeinsam an einem Strang ziehen, um Ergebnisse zu erzielen.\nWerden Sie Teil von Berenberg und arbeiten Sie mit uns gemeinsam daran, das Richtige f\u00fcr unsere Kunden, unser Gesch\u00e4ft und unsere Mitarbeiter zu tun \u2013\nOur future is where you take us!\nAus organisatorischen Gr\u00fcnden nehmen wir nur Bewerbungen an, die uns \u00fcber unser Online-Bewerbermanagementsystem auf der Website erreichen.\n*Aus Gr\u00fcnden der besseren Lesbarkeit wird auf die gleichzeitige Verwendung mehrgeschlechtlicher Sprachformen verzichtet. S\u00e4mtliche Personenbezeichnungen gelten gleichwohl f\u00fcr jegliches Geschlecht. Bei uns sind alle Bewerbungen willkommen, unabh\u00e4ngig von Geschlecht, Nationalit\u00e4t, ethnischer Herkunft, sozialem Hintergrund, Behinderung, Religion, Alter oder sexueller Orientierung.\nBei Fragen wenden Sie sich bitte an unser Recruitment-Team unter recruitment@berenberg.de.\nBack to job list\nApply\nShare this job:\nShare (Junior) Equity Derivatives Sales Trader* with a friend via e-mail",
        "application_url": "https://berenberg.avature.net/en_GB/careers/Login?jobId=2783",
        "metadata": {
            "Country": "Germany",
            "City": "Hamburg",
            "Type of role": "Professional",
            "Working time": "Full-time",
            "Type of contract": "Permanent",
            "Remaining openings": "1"
        },
        "link": "https://berenberg.avature.net/en_GB/careers/JobDetail/Junior-Equity-Derivatives-Sales-Trader/2783"
    },
    {
        "title": null,
        "description_html": null,
        "description_text": "(Senior) Projektmanager*\nGeneral information\nCountry\nGermany\nCity\nHamburg\nType of role\nProfessional\nWorking time\nFull-time\nType of contract\nPermanent\nRemaining openings\n1\nDescription & Requirements\nF\u00fcr unser Programm\nOrganisational Development & Governance\nam\nStandort Hamburg\nsuchen wir zum\nn\u00e4chstm\u00f6glichen Zeitpunkt\ndich als\n(Senior) Projektmanager*\nInnovation & Technology @ Berenberg\nIn einer \u00c4ra, in der Digitalisierung und moderne IT-Infrastrukturen das Banking revolutionieren, gestalten wir eine technologiegest\u00fctzte Bank, in der du als IT-Profi eng mit unseren Gesch\u00e4ftsbereichen zusammenarbeitest. Unsere Technology-Teams bieten dir ein Umfeld, das dich vor spannende Herausforderungen stellt \u2013 sei es durch den Support und die Weiterentwicklung von Legacy-Systemen oder die Einf\u00fchrung moderner Technologien wie KI, Machine Learning und hochgradig automatisierte Handelsapplikationen.\nUnsere IT-Abteilung mit etwa 300 Mitarbeitern arbeitet gr\u00f6\u00dftenteils agil nach einem Scrumban-Ansatz und deckt Bereiche wie Cloud Computing, Cybersecurity, Operations, Process and Governance, Software Development und Architecture ab. Wir sind besonders stolz darauf, fast alle unsere Applikationen Inhouse zu entwickeln, was uns eine einzigartige Flexibilit\u00e4t und Innovationskraft verleiht. Unser Tech Stack umfasst moderne Technologien wie Java, Kotlin, TypeScript und Python, CI/CD-Pipelines, Container, Kubernetes sowie Azure Cloud, Azure SQL Database und Oracle Datenbank mit PL/SQL.\nWelche Aufgaben erwarten Dich?\nEigenverantwortliche Leitung komplexer und bankweiter Projekte von der Planung bis zur erfolgreichen Implementierung (u.a. mit Schwerpunkt Digitalisierungs- & IT-Projekte)\nF\u00fchrung von Mitarbeitern in (bereichs\u00fcbergreifenden) Projektteams und Steuerung der Zusammenarbeit mit externen Dienstleistern\nKoordination von bereichs\u00fcbergreifenden Abh\u00e4ngigkeiten\nVorantreiben von bankweiten Digitalisierungsinitiativen & IT-Modernisierungsprojekten mit bankfachlichem Bezug\nVerantwortung f\u00fcr die Projektbudgets sowie das Erreichen des Projektauftrags\nKreative, strukturierte L\u00f6sungsfindung auf h\u00f6chstem Qualit\u00e4tsniveau mit Fokus auf unsere Kunden und Services\nWeiterentwicklung der Methoden und Standards im Projektmanagement\nWen suchen wir?\nErfolgreich abgeschlossenes Studium, vorzugsweise der Wirtschaftsinformatik, Wirtschaftswissenschaften oder eines vergleichbaren Studiengangs\nFundierte Erfahrung im Management komplexer Projekte im Bankenumfeld oder in der Unternehmensberatung\nNachweisbare Erfahrung in der Leitung von IT-nahen Projekten ist von Vorteil\nSehr gutes bankfachliches Verst\u00e4ndnis, insbesondere in den Bereichen Prozesse, Regulatorik und Digitalisierung\nSouver\u00e4ne Anwendung klassischer sowie agiler Projektmanagement-Methoden\nAusgepr\u00e4gte analytische F\u00e4higkeiten, ein strukturiertes Vorgehen sowie eine pragmatische und l\u00f6sungsorientierte Arbeitsweise\nHohe Eigeninitiative, Flexibilit\u00e4t und ausgepr\u00e4gte Teamf\u00e4higkeit bei der gemeinsamen Entwicklung tragf\u00e4higer L\u00f6sungen\n\u00dcberzeugender und souver\u00e4ner Auftritt sowie Fingerspitzengef\u00fchl im Umgang mit Projektteams und Entscheidungstr\u00e4gern bis auf Bereichsleiterebene\nFreude an anspruchsvollen Aufgaben, hohe Leistungsbereitschaft sowie die F\u00e4higkeit, strategische Weitsicht mit operativer Umsetzungsst\u00e4rke zu verbinden\nAusgepr\u00e4gtes Interesse an digitalen Technologien im Bankenumfeld sowie ein solides Grundverst\u00e4ndnis moderner IT-Systeme\nVerhandlungssichere Deutsch- und Englischkenntnisse in Wort und Schrift\nWas wir Dir bieten:\nFlexible Arbeitszeiten innerhalb einer 39-Stunden-Woche\n30 Tage Jahresurlaub sowie zus\u00e4tzliche freie Tage am 24. und 31. Dezember\nVielseitiges und spannendes Aufgabengebiet in einem modernen und dynamischen Umfeld sowie ein wertsch\u00e4tzendes Betriebsklima\nGezielte F\u00f6rderung durch interne und externe Schulungs- und Entwicklungsprogramme\nBerenberg-Patensystem f\u00fcr ein strukturiertes und reibungsloses Onboarding\nVielf\u00e4ltige Zusch\u00fcsse (z. B. Deutschlandticket, JobRad, verm\u00f6genswirksame Leistungen, betriebliche Altersvorsorge, Essenszusch\u00fcsse bzw. Betriebsrestaurant in Hamburg)\nZus\u00e4tzliche Leistungen wie Familienservice, Arbeitszeitkonto (z. B. f\u00fcr Sabbaticals), betriebliche Sozialleistungen, Gesundheits- und Sportprogramme\nBewirb dich jetzt online und werde Teil des Teams \u2013\nwir freuen uns auf deine Bewerbung!\nWir sind eine f\u00fchrende europ\u00e4ische Privatbank mit \u00fcber 430 Jahren Erfahrung und einer tief verwurzelten Geschichte, aber wir gestalten und investieren noch immer in Zukunft. Unser Fortschritt und unsere Entwicklung werden von unseren Mitarbeitern vorangetrieben. Wir ermutigen sie, neue Ans\u00e4tze auszuprobieren, ihre Meinung zu \u00e4u\u00dfern und auf ihre eigene Art und Weise erfolgreich zu sein.\nWir bieten ihnen die M\u00f6glichkeit, ihre Talente zu entwickeln, verschiedene Karrierewege zu erkunden und ihr Potenzial voll auszusch\u00f6pfen.\nWir sind ein ehrgeiziges, zukunftsorientiertes Unternehmen, das auf jahrhundertealte Traditionen zur\u00fcckgreift und auf Innovation baut. Du findest bei uns eine Kultur vor, die Menschen dazu ermutigt, unabh\u00e4ngig zu denken, unternehmerisch zu handeln und den Status quo in Frage zu stellen. Wir legen gro\u00dfen Wert auf die Zusammenarbeit vor Ort \u2013 unser B\u00fcro ist ein zentraler Ort des Dialogs, der Innovation und des gemeinsamen Wachstums. Gemeinsam arbeiten wir daran, unser Gesch\u00e4ft zu gestalten und unsere ehrgeizigen Ziele zu erreichen.\nWir freuen uns, wenn du dich uns anschlie\u00dft, um stets das Richtige f\u00fcr unsere Mitarbeiter, Kunden und unser Unternehmen zu tun \u2013\nOur future is where you take us!\nAus organisatorischen Gr\u00fcnden nehmen wir nur Bewerbungen an, die uns \u00fcber unser Online-Bewerbermanagementsystem auf der Website erreichen.\n*Aus Gr\u00fcnden der besseren Lesbarkeit wird auf die gleichzeitige Verwendung mehrgeschlechtlicher Sprachformen verzichtet. S\u00e4mtliche Personenbezeichnungen gelten gleichwohl f\u00fcr jegliches Geschlecht. Bei uns sind alle Bewerber willkommen, unabh\u00e4ngig von Geschlecht, Nationalit\u00e4t, ethnischer Herkunft, sozialem Hintergrund, Behinderung, Religion, Alter oder sexueller Orientierung. Bei Fragen wende dich bitte an unser Recruitment-Team unter recruitment@berenberg.de.\nBack to job list\nApply\nShare this job:\nShare (Senior) Projektmanager* with a friend via e-mail",
        "application_url": "https://berenberg.avature.net/en_GB/careers/Login?jobId=2651",
        "metadata": {
            "Country": "Germany",
            "City": "Hamburg",
            "Type of role": "Professional",
            "Working time": "Full-time",
            "Type of contract": "Permanent",
            "Remaining openings": "1"
        },
        "link": "https://berenberg.avature.net/en_GB/careers/JobDetail/Senior-Projektmanager/2651"
    },
    {
        "title": null,
        "description_html": null,
        "description_text": "(Senior) IT Support Specialist* \u2013 Fokus Desk Support\nGeneral information\nCountry\nGermany\nCity\nHamburg\nType of role\nProfessional\nWorking time\nFull-time\nType of contract\nPermanent\nRemaining openings\n1\nDescription & Requirements\nF\u00fcr unser\nProgramm Workplace & Tech Services\nin\nHamburg\nsuchen wir zum\nn\u00e4chstm\u00f6glichen Zeitpunkt\ndich als\n(Senior) IT Support Specialist* \u2013 Fokus Desk Support\nInnovation & Technology @ Berenberg\nIn einer \u00c4ra, in der Digitalisierung und moderne IT-Infrastrukturen das Banking revolutionieren, gestalten wir eine technologiegest\u00fctzte Bank, in der du als IT-Profi eng mit unseren Gesch\u00e4ftsbereichen zusammenarbeitest. Unsere Technology-Teams bieten dir ein Umfeld, das dich vor spannende Herausforderungen stellt \u2013 sei es durch den Support und die Weiterentwicklung von Legacy-Systemen oder die Einf\u00fchrung moderner Technologien wie KI, Machine Learning und hochgradig automatisierte Handelsapplikationen.\nUnsere IT-Abteilung mit etwa 300 Mitarbeitern arbeitet gr\u00f6\u00dftenteils agil nach einem Scrumban-Ansatz und deckt Bereiche wie Cloud Computing, Cybersecurity, Operations, Process and Governance, Software Development und Architecture ab. Wir sind besonders stolz darauf, fast alle unsere Applikationen Inhouse zu entwickeln, was uns eine einzigartige Flexibilit\u00e4t und Innovationskraft verleiht. Unser Tech Stack umfasst moderne Technologien wie Java, Kotlin, TypeScript und Python, CI/CD-Pipelines, Container, Kubernetes sowie Azure Cloud, Azure SQL Database und Oracle Datenbank mit PL/SQL.\nWelche Aufgaben erwarten Dich?\nKompetente Beratung und Unterst\u00fctzung interner Kunden bei Hardware- und Softwareproblemen im 2nd Level Support\nEinrichtung, Konfiguration und Betreuung von Arbeitspl\u00e4tzen, Meetingr\u00e4umen und IT-Infrastruktur (Technikr\u00e4ume)\nVerst\u00e4ndliche Kommunikation und Dokumentation komplexer technischer L\u00f6sungen\nEnge Zusammenarbeit mit dem First Level Support unter Nutzung eines ITIL-basierten Ticketsystems\nInstallation, Konfiguration und Roll-out moderner Hard- und Softwarel\u00f6sungen sowie Durchf\u00fchrung von IMAC/RD-Prozessen\nAktive Mitwirkung an der Modernisierung, Digitalisierung und Pflege der internen IT-Systeme und Wissensdatenbanken\nWen suchen wir?\nErfolgreich abgeschlossene Ausbildung im IT-Bereich, vorzugsweise als Fachinformatiker f\u00fcr Systemintegration, oder vergleichbare Qualifikation\nEinschl\u00e4gige Berufserfahrung im IT-Support bzw. IT-Service-Management, idealerweise in Finanz-, Handels- oder Beratungsumgebungen\nTiefgehende Kenntnisse in Citrix, VDI, MS Office, Intune, Active Directory, Azure, Office 365, LAN/WLAN und Cisco-Systemen\nITIL-Zertifizierung w\u00fcnschenswert, sowie Erfahrung im Investment-Banking-Umfeld von Vorteil\nSehr gute Deutsch- und Englischkenntnisse, hohe Kommunikationsf\u00e4higkeit und Serviceorientierung\nEigenst\u00e4ndige, strukturierte Arbeitsweise und Bereitschaft zu gelegentlichen Dienstreisen (ca. 10 %, DE/UK)\nWas wir Dir bieten:\nFlexible Arbeitszeiten innerhalb einer 39-Stunden-Woche\n30 Tage Jahresurlaub sowie zus\u00e4tzliche freie Tage am 24. und 31. Dezember\nVielseitiges und spannendes Aufgabengebiet in einem modernen und dynamischen Umfeld sowie ein wertsch\u00e4tzendes Betriebsklima\nGezielte F\u00f6rderung durch interne und externe Schulungs- und Entwicklungsprogramme\nBerenberg-Patensystem f\u00fcr ein strukturiertes und reibungsloses Onboarding\nVielf\u00e4ltige Zusch\u00fcsse (z. B. Deutschlandticket, JobRad, verm\u00f6genswirksame Leistungen, betriebliche Altersvorsorge, Essenszusch\u00fcsse bzw. Betriebsrestaurant in Hamburg)\nZus\u00e4tzliche Leistungen wie Familienservice, Arbeitszeitkonto (z. B. f\u00fcr Sabbaticals), betriebliche Sozialleistungen, Gesundheits- und Sportprogramme\nBewirb dich jetzt online und werde Teil des Teams \u2013\nwir freuen uns auf deine Bewerbung!\nWir sind eine f\u00fchrende europ\u00e4ische Privatbank mit \u00fcber 430 Jahren Erfahrung und einer tief verwurzelten Geschichte, aber wir gestalten und investieren noch immer in Zukunft. Unser Fortschritt und unsere Entwicklung werden von unseren Mitarbeitern vorangetrieben. Wir ermutigen sie, neue Ans\u00e4tze auszuprobieren, ihre Meinung zu \u00e4u\u00dfern und auf ihre eigene Art und Weise erfolgreich zu sein.\nWir bieten ihnen die M\u00f6glichkeit, ihre Talente zu entwickeln, verschiedene Karrierewege zu erkunden und ihr Potenzial voll auszusch\u00f6pfen.\nWir sind ein ehrgeiziges, zukunftsorientiertes Unternehmen, das auf jahrhundertealte Traditionen zur\u00fcckgreift und auf Innovation baut. Du findest bei uns eine Kultur vor, die Menschen dazu ermutigt, unabh\u00e4ngig zu denken, unternehmerisch zu handeln und den Status quo in Frage zu stellen. Wir legen gro\u00dfen Wert auf die Zusammenarbeit vor Ort \u2013 unser B\u00fcro ist ein zentraler Ort des Dialogs, der Innovation und des gemeinsamen Wachstums. Gemeinsam arbeiten wir daran, unser Gesch\u00e4ft zu gestalten und unsere ehrgeizigen Ziele zu erreichen.\nWir freuen uns, wenn du dich uns anschlie\u00dft, um stets das Richtige f\u00fcr unsere Mitarbeiter, Kunden und unser Unternehmen zu tun \u2013\nOur future is where you take us!\nAus organisatorischen Gr\u00fcnden nehmen wir nur Bewerbungen an, die uns \u00fcber unser Online-Bewerbermanagementsystem auf der Website erreichen.\n*Aus Gr\u00fcnden der besseren Lesbarkeit wird auf die gleichzeitige Verwendung mehrgeschlechtlicher Sprachformen verzichtet. S\u00e4mtliche Personenbezeichnungen gelten gleichwohl f\u00fcr jegliches Geschlecht. Bei uns sind alle Bewerber willkommen, unabh\u00e4ngig von Geschlecht, Nationalit\u00e4t, ethnischer Herkunft, sozialem Hintergrund, Behinderung, Religion, Alter oder sexueller Orientierung. Bei Fragen wende dich bitte an unser Recruitment-Team unter recruitment@berenberg.de.\nBack to job list\nApply\nShare this job:\nShare (Senior) IT Support Specialist* \u2013 Fokus Desk Support with a friend via e-mail",
        "application_url": "https://berenberg.avature.net/en_GB/careers/Login?jobId=2789",
        "metadata": {
            "Country": "Germany",
            "City": "Hamburg",
            "Type of role": "Professional",
            "Working time": "Full-time",
            "Type of contract": "Permanent",
            "Remaining openings": "1"
        },
        "link": "https://berenberg.avature.net/en_GB/careers/JobDetail/Senior-IT-Support-Specialist-Fokus-Desk-Support/2789"
    },
    {
        "title": null,
        "description_html": null,
        "description_text": "Senior Roadshow Manager\nGeneral information\nCountry\nUnited Kingdom\nCity\nLondon\nType of role\nProfessional\nWorking time\nFull-time\nType of contract\nPermanent\nRemaining openings\n1\nDescription & Requirements\nFor our\nCorporate Access\ndivision in\nLondon\nwe are looking to hire a\nSenior Roadshow Manager\nin the\nCorporate Access Team\nYour role in the team\nWe are looking for a senior roadshow manager with 10+ years\u2019 experience in roadshow and investor trip management to join the Roadshow Manager team based in London to support the planning and delivery of corporate access.\u00a0 You will be working within a team of 3 other roadshow managers, two Originators and an Analyst in London and within a wider team of 12 based in London, Europe and North America. This is a busy role, the team arranged over 10,500 investor meetings with 600+ companies in 2024 throughout the UK, Europe and North America and you will be a key member of the team.\nWhat will you do?\nManage corporate roadshows from start to finish in London and Europe\nInvestor targeting and logistic management to ensure a seamless experience\nTake the lead on group as well as bespoke investor trips through the UK, Europe and North America\nMaintain strong relationships with c-suite, investor relations teams, investors and internal stakeholders to make sure all aims are met\nUtilise and update our internal CRM systems to ensure accurate data\nWho are we looking for?\n10+ years previous experience within a corporate access team\nOrganised, autonomous and very process driven\nProven team player with excellent attention to detail and happy to jump in where needed\nAbility to multi-task and work under pressure\nWhat we offer you:\nPrivate pension plan - 10% of base salary contribution by Berenberg\nGenerous 30 day holiday allowance\nPrivate Health Insurance\nLife Insurance scheme\nFlexible working hours\nEnhanced parental leave policies\nEmployee Assistance Programme offering counselling sessions related to mental health, financial well-being and other topics\nApply online now to join our team \u2013\nwe look forward to receiving your application!\nWe are a leading European private bank, with over 430 years of experience and deep rooted history, but we are still shaping and heavily investing in our future. Our progress and evolution are driven by our people. We encourage them to try new approaches, voice their opinions and achieve success in their own way.\nWe provide opportunities for them to develop their talents, explore different career paths and achieve their full potential.\nWe\u2019re an ambitious, forward-looking business, backed by centuries of tradition and built on innovation. You\u2019ll find a culture that encourages people to think independently, act entrepreneurially and challenge the status quo.\nWe place great importance on working on site, as we believe that being together in the office not only fosters creativity and efficiency, but also strengthens networks and builds trusting, collegial relationships. For us, this forms the foundation for productive and successful work. Together we collaborate to shape our business and fulfil our ambitious goals.\nWe welcome you to join us in our commitment to always do the right thing for our people, clients and our business \u2013\nOur future is where you take us!\nWe will only accept applications submitted through our online application management system on the website.\nBerenberg is an Equal Opportunities Employer and prides itself on being a modern, dynamic and internationally orientated organisation. We value the rich diversity, skills and abilities and creative potential that people from differing backgrounds and experiences bring to the workplace. Every employee plays a vital role in providing quality service to all our customers and helping to create and inclusive working environment, where everyone can realise their full potential.\nWe\u2019re committed to finding reasonable accommodations for candidates who require adjustments during our recruiting process. Please contact us directly on recruitment@berenberg.com to discuss.\nBack to job list\nApply\nShare this job:\nShare Senior Roadshow Manager with a friend via e-mail",
        "application_url": "https://berenberg.avature.net/en_GB/careers/Login?jobId=2782",
        "metadata": {
            "Country": "United Kingdom",
            "City": "London",
            "Type of role": "Professional",
            "Working time": "Full-time",
            "Type of contract": "Permanent",
            "Remaining openings": "1"
        },
        "link": "https://berenberg.avature.net/en_GB/careers/JobDetail/Senior-Roadshow-Manager/2782"
    },
    {
        "title": null,
        "description_html": null,
        "description_text": "Account Manager* Corporates\nGeneral information\nCountry\nGermany\nCity\nHamburg\nType of role\nProfessional\nType of contract\nPermanent\nRemaining openings\n1\nDescription & Requirements\nF\u00fcr unseren Bereich\nCorporates\nam Standort\nHamburg\nsuchen wir zum n\u00e4chstm\u00f6glichen Zeitpunkt Sie als\nAccount Manager* Corporates\nIhre Rolle im Team\nIm Team Account Management innerhalb des Bereichs Corporates unterst\u00fctzen Sie die Firmenkundenbetreuer insbesondere bei Konto- und Depoter\u00f6ffnungen inkl. KYC-Checks sowie im Tagesgesch\u00e4ft. Hierbei stimmen Sie sich stets enge mit den relevanten Stakeholdern ab und stehen im direkten Austausch mit den Kunden.\nUnsere Kundengruppen verteilen sich auf Familienunternehmen, b\u00f6rsennotierte Unternehmen, Wachstumsunternehmen, HNWIs sowie Unternehmen und Projektgesellschaften mit einem \u201eSponsorenhintergrund\u201c.\nWelche Aufgaben erwarten Sie?\nVerantwortung f\u00fcr das Client Onboarding: Konto- und Depoter\u00f6ffnung inkl. KYC-Checks\nFortlaufende \u00dcberwachung und Kl\u00e4rung KYC-bezogener Fragestellungen\nDirekter Ansprechpartner f\u00fcr die Kunden im Tagesgesch\u00e4ft, u. a. hinsichtlich Vollmachts\u00e4nderungen, Cash Management, Onlinebanking, Geldanlagen und W\u00e4hrungsmanagement\nUnterst\u00fctzung unserer Firmenkundenbetreuer bei den t\u00e4glichen Aufgaben im Vertrieb\nWen suchen wir?\nErfolgreich abgeschlossene Bankausbildung und erste Erfahrung im kommerziellen Bankgesch\u00e4ft, idealerweise im Firmenkundenbereich mit KYC-Erfahrung\nAffinit\u00e4t zu digitalen Prozessen und Freude am Detail im Kontext von Onboarding und KYC-Pr\u00fcfungen\nSouver\u00e4ne Kommunikation auf Deutsch sowie gute Englischkenntnisse\nAusgezeichnete Dienstleistungsorientierung sowie selbstst\u00e4ndiges, strukturiertes, eigenverantwortliches Handeln mit hohem Qualit\u00e4tsanspruch\nDas richtige Gesp\u00fcr f\u00fcr Priorit\u00e4ten, vor allem bei hoher Arbeitsbelastung\nWas wir Ihnen bieten:\nFlexible Arbeitszeiten innerhalb einer 39-Stunden-Woche\n30 Tage Jahresurlaub sowie zus\u00e4tzliche freie Tage am 24. und 31. Dezember\nVielseitiges und spannendes Aufgabengebiet in einem modernen und dynamischen Umfeld sowie wertsch\u00e4tzendes Betriebsklima\nGezielte F\u00f6rderung durch interne und externe Schulungs- und Entwicklungsprogramme\nBerenberg-Patensystem f\u00fcr ein strukturiertes und reibungsloses Onboarding\nVielf\u00e4ltige Zusch\u00fcsse (z. B. Deutschlandticket, JobRad, verm\u00f6genswirksame Leistungen, betriebliche Altersvorsorge, Essenszusch\u00fcsse bzw. Betriebsrestaurant in Hamburg)\nZus\u00e4tzliche Leistungen wie Familienservice, Arbeitszeitkonto (z. B. f\u00fcr Sabbaticals), betriebliche Sozialleistungen, Gesundheits- und Sportprogramme\nBewerben Sie sich jetzt online und werden Sie Teil des Teams \u2013\nwir freuen uns auf Ihre Bewerbung!\nAls eine f\u00fchrende europ\u00e4ische Privatbank mit \u00fcber 430 Jahren Erfahrung blicken wir auf eine lange Unternehmensgeschichte zur\u00fcck. Gleichzeitig gestalten wir mit umfassenden Investitionen aktiv unsere Zukunft. Grundlage f\u00fcr unseren Fortschritt und unsere Weiterentwicklung sind unsere Mitarbeiter. Wir ermutigen diese, neue Ans\u00e4tze auszuprobieren, ihre Ideen mit einzubringen und ihren eigenen Weg zum Erfolg bei uns zu gehen. Wir sind ein ambitioniertes, zukunftsorientiertes Unternehmen, das jahrhundertelange Erfahrung und Innovationskraft vereint.\nBei uns erleben Sie eine Kultur, die zum selbstst\u00e4ndigen Denken anregt, Unternehmertum f\u00f6rdert und dazu ermutigt, den Status quo zu hinterfragen. Wir legen gro\u00dfen Wert auf die Zusammenarbeit vor Ort \u2013 unser B\u00fcro ist ein zentraler Ort des Dialogs, der Innovation und des gemeinsamen Wachstums. Sie treffen hier auf talentierte Kollegen, die es gewohnt sind, Verantwortung zu \u00fcbernehmen, und gemeinsam an einem Strang ziehen, um Ergebnisse zu erzielen.\nWerden Sie Teil von Berenberg und arbeiten Sie mit uns gemeinsam daran, das Richtige f\u00fcr unsere Kunden, unser Gesch\u00e4ft und unsere Mitarbeiter zu tun \u2013\nOur future is where you take us!\nAus organisatorischen Gr\u00fcnden nehmen wir nur Bewerbungen an, die uns \u00fcber unser Online-Bewerbermanagementsystem auf der Website erreichen.\n*Aus Gr\u00fcnden der besseren Lesbarkeit wird auf die gleichzeitige Verwendung mehrgeschlechtlicher Sprachformen verzichtet. S\u00e4mtliche Personenbezeichnungen gelten gleichwohl f\u00fcr jegliches Geschlecht. Bei uns sind alle Bewerbungen willkommen, unabh\u00e4ngig von Geschlecht, Nationalit\u00e4t, ethnischer Herkunft, sozialem Hintergrund, Behinderung, Religion, Alter oder sexueller Orientierung. Bei Fragen wenden Sie sich bitte an unser Recruitment-Team unter recruitment@berenberg.de.\nBack to job list\nApply\nShare this job:\nShare Account Manager* Corporates with a friend via e-mail",
        "application_url": "https://berenberg.avature.net/en_GB/careers/Login?jobId=2785",
        "metadata": {
            "Country": "Germany",
            "City": "Hamburg",
            "Type of role": "Professional",
            "Type of contract": "Permanent",
            "Remaining openings": "1"
        },
        "link": "https://berenberg.avature.net/en_GB/careers/JobDetail/Account-Manager-Corporates/2785"
    },
    {
        "title": null,
        "description_html": null,
        "description_text": "Sales Trader\nGeneral information\nCountry\nUSA\nCity\nNew York\nType of role\nProfessional\nWorking time\nFull-time\nType of contract\nPermanent\nRemaining openings\n1\nDescription & Requirements\nFor our US Markets division in New York we are looking to hire into\nUS Equity Sales Trader \u2013 New York\nYour role in the team:\nJoin our dynamic US Markets division as an US Equity Sales Trader, where you will play a pivotal role in expanding our presence in the US equity markets. In this position, you will be responsible for building and nurturing relationships with US clients, providing insightful advice on equity market developments, and executing client orders efficiently. This role offers and exciting opportunity to be part of a collaborative team, leveraging your knowledge of the current equity market to drive success.\nWhat will you do?:\nBuild on existing and develop new relationships with US clients, providing advice on equity market developments and key issues that may affect their trading strategies for the US market\nExecute client orders for the US market; coordinating between the traders and the client as required\nGenerate new order flow in the secondary and primary markets \u2013 on existing Berenberg deals and help generate potential blocks with client order flow\nPrioritize resource allocation across clients and products to maximize revenue generation\nAbility to talk in detail your knowledge of the current market for Equities\nRequired to comply with applicable regulation, including the Conduct Rules, internal policies and procedures\nLiaise with and develop Berenberg\u2019s low touch offering and our Risk Arb team where possible\nWho are we looking for?:\nExperience within the Equity Trading Markets\nBachelor\u2019s degree preferred or equivalent experience required\nWillingness to spend time traveling and socializing with clients\nIT skills, including all standard Office applications\nStrong communication skills, ability to foster relationships\nDemonstrated ability to perform under pressure in a fast-paced environment\nWhat we offer you\n100% Company sponsored medical, dental, and vision insurance\n25 Paid vacation and sick time\nCompany-paid life insurance\nCompany-paid STD/LTD\nPaid parental leave\n401(k) plan with company match\nGym membership discounts\nApply now and join our Team \u2013\nwe look forward to receiving your application!\nWho We Are:\nBerenberg Capital Markets LLC (BCM) is a New York based FINRA member broker-dealer, and wholly owned independent subsidiary of Joh. Berenberg, Gossler & Co. KG (Berenberg), one of Europe\u2019s leading privately-owned banks, established in 1590. Together, BCM and Berenberg have built a franchise known for its \u201cclient first\u201d approach and a global reputation of high-quality coverage of both corporate and institutional clients. Leveraging our global network of institutional investors and deep corporate relationships, we developed a track record of raising capital on US exchange\u2019s raising over $27 billion across more than 80 transactions since opening our Equity Capital Markets division in 2018. Building on its strength and expertise across multiple industries, BCM continues to expand the breadth of Sales, Trading, and Investment Banking services it offers to better assist its institutional and corporate clients\u2019 access to the global equity markets. BCM adopts the same principles as its parent company and is committed to building long-term relationships with its clients based on high levels of accountability, responsibility, insight, vision, and expertise.\nWe place great importance on working on site, as we believe that being together in the office not only fosters creativity and efficiency, but also strengthens networks and builds trusting, collegial relationships. For us, this forms the foundation for productive and successful work. Together we collaborate to shape our business and fulfil our ambitious goals.\nWe welcome you to join us in our commitment to always do the right thing for our people, clients and our business \u2013\nOur future is where you take us!\nWe will only accept applications submitted through our online application management system on the website.\nWe\u2019re committed to finding reasonable accommodations for candidates who require adjustments during our recruiting process. Please contact us directly on recruitment@berenberg.com to discuss.\nBCM provides Equal Employment Opportunities (EEO) to all employees and applicants without regard to their actual or perceived age, race, creed, religious belief, color, gender, sexual orientation, gender identity, partnership status, marital status, physical or mental disability, national origin, alienage or citizenship status, military or veteran status, genetic predisposition or carrier status, or engaging in protected activity (such as opposition to prohibited discrimination or participation in proceedings covered by the anti-discrimination statutes) or any other characteristic protected by applicable federal, state and local law. BCM complies with applicable state and local laws governing non-discrimination in employment in every location in which the Company has facilities. This policy applies to all terms and conditions of employment, including hiring, placement, promotion, termination, layoff, recall, transfer, leaves of absence, compensation and training.\nSalary will vary based on role, education, level of experience, and expertise ranging between $200,000 to $250,000 dollars as a base salary with eligibility for a discretionary annual bonus plus comprehensive benefits package.\nBack to job list\nApply\nShare this job:\nShare Sales Trader with a friend via e-mail",
        "application_url": "https://berenberg.avature.net/en_GB/careers/Login?jobId=2784",
        "metadata": {
            "Country": "USA",
            "City": "New York",
            "Type of role": "Professional",
            "Working time": "Full-time",
            "Type of contract": "Permanent",
            "Remaining openings": "1"
        },
        "link": "https://berenberg.avature.net/en_GB/careers/JobDetail/Sales-Trader/2784"
    },
    {
        "title": null,
        "description_html": null,
        "description_text": "Werkstudent* Informationssicherheit\nGeneral information\nCountry\nGermany\nCity\nHamburg\nType of role\nWorking Student\nWorking time\nFull-time\nType of contract\nWorking Student\nRemaining openings\n1\nDescription & Requirements\nUnterst\u00fctzen Sie unser Information-Security-Team in Hamburg idealerweise ab Januar f\u00fcr 6-12 Monate als Werkstudent mit ca. 20 Stunden w\u00f6chentlich\nWerkstudent* Informationssicherheit\nDas Information-Security-Team verantwortet die Informationssicherheit bei Berenberg und nimmt im Three-Lines-of-Defense-Modell die 2nd Line wahr. Wir beraten und \u00fcberwachen die 1st Line in Bezug auf die Belange der Informationssicherheit. Wir gew\u00e4hrleisten so mit unserem Regelwerk den sicheren Betrieb und stellen die Compliance zu Gesetzen sowie externen Regulierungen sicher.\nWelche Aufgaben erwarten Sie?\nMitarbeit im operativen Tagesgesch\u00e4ft des Teams Information Security\nMitwirkung beim Ausbau und bei der kontinuierlichen Verbesserung des ISMS (Richtlinien, Prozesse, Si-cherheitsanforderungen)\nUnterst\u00fctzen von Pr\u00fcfungshandlungen in Bezug auf interne Sicherheitsma\u00dfnahmen\nWeiterentwicklung des bestehenden Security Information and Event Managements (SIEM) auf Basis von Splunk\nWen suchen wir?\nMindestens ein erfolgreich abgeschlossenes Semester eines Informatikstudiums oder eines verwandten Studienganges\nIdealerweise erste Erfahrung bzgl. der Informations- oder IT-Sicherheit, z. B. durch Praktika oder entsprechende Module\nSchnelle Auffassungsgabe sowie selbst\u00e4ndige, sorgf\u00e4ltige und zuverl\u00e4ssige Arbeitsweise\nGute Englischkenntnisse in Wort & Schrift\nFreude an Teamarbeit\nWas wir Ihnen bieten:\nVielseitiges und spannendes Aufgabengebiet in einem modernen und dynamischen Umfeld sowie ein wertsch\u00e4tzendes Betriebsklima\nStrukturiertes und reibungsloses Onboarding\nZugang zu unseren internen \u201eLearning & Development\u201c Angeboten wie z. B. den \u201eLunch & Learn\u201c- Sessions, Seminaren oder inspirierenden Vortr\u00e4gen\nM\u00f6glichkeit, im Anschluss Teil unseres Future Talent Programms zu werden, welches unser exklusives Talentbindungsprogramm ist\nVielf\u00e4ltige Zusch\u00fcsse f\u00fcr z. B. Deutschlandticket und Essenszusch\u00fcsse\nZus\u00e4tzliche Leistungen wie betriebliche Sportprogramme, sowie Zugang zu externem Vorteilsportal mit exklusiven Angeboten\nBewerben Sie sich jetzt online mit Ihren vollst\u00e4ndigen Bewerbungsunterlagen inklusive Immatrikulationsbescheinigung mit Angabe des Fachsemesters. Angeh\u00f6rige von Staaten au\u00dferhalb des europ\u00e4ischen Wirtschaftsraums schicken ggf. bitte ihre Aufenthalts- und Arbeitsgenehmigung mit.\nWir freuen uns auf Ihre Bewerbung!\nAls eine f\u00fchrende europ\u00e4ische Privatbank mit \u00fcber 430 Jahren Erfahrung blicken wir auf eine lange Unternehmensgeschichte zur\u00fcck. Gleichzeitig gestalten wir mit umfassenden Investitionen aktiv unsere Zukunft. Grundlage f\u00fcr unseren Fortschritt und unsere Weiterentwicklung sind unsere Mitarbeiter. Wir ermutigen diese, neue Ans\u00e4tze auszuprobieren, ihre Ideen mit einzubringen und ihren eigenen Weg zum Erfolg bei uns zu gehen. Wir sind ein ambitioniertes, zukunftsorientiertes Unternehmen, das jahrhundertelange Erfahrung und Innovationskraft vereint.\nBei uns erleben Sie eine Kultur, die zum selbstst\u00e4ndigen Denken anregt, Unternehmertum f\u00f6rdert und dazu ermutigt, den Status quo zu hinterfragen. Wir legen gro\u00dfen Wert auf die Zusammenarbeit vor Ort \u2013 unser B\u00fcro ist ein zentraler Ort des Dialogs, der Innovation und des gemeinsamen Wachstums. Sie treffen hier auf talentierte Kollegen, die es gewohnt sind, Verantwortung zu \u00fcbernehmen, und gemeinsam an einem Strang ziehen, um Ergebnisse zu erzielen.\nWerden Sie Teil von Berenberg und arbeiten Sie mit uns gemeinsam daran, das Richtige f\u00fcr unsere Kunden, unser Gesch\u00e4ft und unsere Mitarbeiter zu tun \u2013\nOur future is where you take us!\nAus organisatorischen Gr\u00fcnden nehmen wir nur Bewerbungen an, die uns \u00fcber unser Online-Bewerbermanagementsystem auf der Website erreichen.\n*Aus Gr\u00fcnden der besseren Lesbarkeit wird auf die gleichzeitige Verwendung mehrgeschlechtlicher Sprach-formen verzichtet. S\u00e4mtliche Personenbezeichnungen gelten gleichwohl f\u00fcr jegliches Geschlecht. Bei uns sind alle Bewerbungen willkommen, unabh\u00e4ngig von Geschlecht, Nationalit\u00e4t, ethnischer Herkunft, sozialem Hinter-grund, Behinderung, Religion, Alter oder sexueller Orientierung. Bei Fragen wenden Sie sich bitte an unser Recruitment-Team unter recruitment@berenberg.de.\nBack to job list\nApply\nShare this job:\nShare Werkstudent* Informationssicherheit with a friend via e-mail",
        "application_url": "https://berenberg.avature.net/en_GB/careers/Login?jobId=2779",
        "metadata": {
            "Country": "Germany",
            "City": "Hamburg",
            "Type of role": "Working Student",
            "Working time": "Full-time",
            "Type of contract": "Working Student",
            "Remaining openings": "1"
        },
        "link": "https://berenberg.avature.net/en_GB/careers/JobDetail/Werkstudent-Informationssicherheit/2779"
    },
    {
        "title": null,
        "description_html": null,
        "description_text": "(Senior) Backup Engineer / Architect*\nGeneral information\nCountry\nGermany\nCity\nFrankfurt, Hamburg\nType of role\nProfessional\nWorking time\nFull-time\nType of contract\nPermanent\nRemaining openings\n1\nDescription & Requirements\nF\u00fcr unser Programm\nCore Infrastructure Services\nam\nStandort Hamburg / Frankfurt am Main\nsuchen wir zum\nn\u00e4chstm\u00f6glichen Zeitpunkt\ndich als\n(Senior) Backup Engineer / Architect*\nInnovation & Technology @ Berenberg.\nIn einer \u00c4ra, in der Digitalisierung und moderne IT-Infrastrukturen das Banking revolutionieren, gestalten wir eine technologiegest\u00fctzte Bank, in der du als IT-Profi eng mit unseren Gesch\u00e4ftsbereichen zusammenarbeitest. Unsere Technology-Teams bieten dir ein Umfeld, das dich vor spannende Herausforderungen stellt \u2013 sei es durch den Support und die Weiterentwicklung von Legacy-Systemen oder die Einf\u00fchrung moderner Technologien wie KI, Machine Learning und hochgradig automatisierte Handelsapplikationen.\nUnsere IT-Abteilung mit etwa 300 Mitarbeitern arbeitet gr\u00f6\u00dftenteils agil nach einem Scrumban-Ansatz und deckt Bereiche wie Cloud Computing, Cybersecurity, Operations, Process and Governance, Software Development und Architecture ab. Wir sind besonders stolz darauf, fast alle unsere Applikationen Inhouse zu entwickeln, was uns eine einzigartige Flexibilit\u00e4t und Innovationskraft verleiht. Unser Tech Stack umfasst moderne Technologien wie Java, Kotlin, TypeScript und Python, CI/CD-Pipelines, Container, Kubernetes sowie Azure Cloud, Azure SQL Database und Oracle Datenbank mit PL/SQL.\nDeine Rolle im Team\nIn unserem Team \u201eLinux, Storage & Backup\u201c verbinden wir die Tradition einer Privatbank mit modernster IT-Infrastruktur. Wir befinden uns mitten in einer gro\u00dfen Modernisierungskampagne: Weg von Legacy, hin zu Rubrik. Daf\u00fcr suchen wir einen Experten, der nicht nur administriert, sondern die Architektur unserer Datensicherung mit gestaltet.\nDabei bist du der technische Lead f\u00fcr unsere neue Backup-Strategie. Du begleitest uns bei der Abl\u00f6sung von Dell-Networker/Data Domain und implementierst eine zukunftssichere Rubrik-Umgebung f\u00fcr unsere On-Premise- und Cloud-Dienste.\nWelche Aufgaben erwarten Dich?\nDu verantwortest das Design, die Installation und die Konfiguration der neuen Rubrik-L\u00f6sung\nPlanung und Steuerung der \u00dcberf\u00fchrung bestehender Backup-Verfahren in die neue Umgebung\nKonzeptionelle Erstellung von Backup-Designs f\u00fcr unsere Cloud-Integrationen (M365, Salesforce, Azure)\nSicherstellung des laufenden Betriebs (inkl. Troubleshooting) und \u00dcberwachung mittels BACKUP EAGLE\nDu bist der erste Ansprechpartner f\u00fcr Revision und Governance bei allen Fragen zur Datensicherheit und Wiederherstellbarkeit (Disaster Recovery)\nWen suchen wir?\nErfolgreich abgeschlossenes IT-Studium oder Ausbildung (z. B. Fachinformatiker Systemintegration) mit entsprechender Berufspraxis\nMehrj\u00e4hrige Erfahrung als System Engineer im Storage/Backup-Umfeld, idealerweise im Banken- oder Enterprise-Sektor\nFundierte Linux-Kenntnisse sind Pflicht. Erfahrung mit Rubrik ist ein gro\u00dfes Plus; alternativ tiefes Wissen in Enterprise-Backup-L\u00f6sungen (Dell Networker, Cohesity, Veeam, Commvault) und die Lust, sich in Rubrik einzuarbeiten\nSehr gute Deutsch- und Englischkenntnisse sind f\u00fcr die Arbeit in unseren internationalen Teams unerl\u00e4sslich\nWas wir Dir bieten:\nFlexible Arbeitszeiten innerhalb einer 39-Stunden-Woche\n30 Tage Jahresurlaub sowie zus\u00e4tzliche freie Tage am 24. und 31. Dezember\nVielseitiges und spannendes Aufgabengebiet in einem modernen und dynamischen Umfeld sowie ein wertsch\u00e4tzendes Betriebsklima\nGezielte F\u00f6rderung durch interne und externe Schulungs- und Entwicklungsprogramme\nBerenberg-Patensystem f\u00fcr ein strukturiertes und reibungsloses Onboarding\nVielf\u00e4ltige Zusch\u00fcsse (z. B. Deutschlandticket, JobRad, verm\u00f6genswirksame Leistungen, betriebliche Altersvorsorge, Essenszusch\u00fcsse bzw. Betriebsrestaurant in Hamburg)\nZus\u00e4tzliche Leistungen wie Familienservice, Arbeitszeitkonto (z. B. f\u00fcr Sabbaticals), betriebliche Sozialleistungen, Gesundheits- und Sportprogramme\nBewirb dich jetzt online und werde Teil des Teams \u2013\nwir freuen uns auf deine Bewerbung!\nWir sind eine f\u00fchrende europ\u00e4ische Privatbank mit \u00fcber 430 Jahren Erfahrung und einer tief verwurzelten Geschichte, aber wir gestalten und investieren noch immer in Zukunft. Unser Fortschritt und unsere Entwicklung werden von unseren Mitarbeitern vorangetrieben. Wir ermutigen sie, neue Ans\u00e4tze auszuprobieren, ihre Meinung zu \u00e4u\u00dfern und auf ihre eigene Art und Weise erfolgreich zu sein.\nWir bieten ihnen die M\u00f6glichkeit, ihre Talente zu entwickeln, verschiedene Karrierewege zu erkunden und ihr Potenzial voll auszusch\u00f6pfen.\nWir sind ein ehrgeiziges, zukunftsorientiertes Unternehmen, das auf jahrhundertealte Traditionen zur\u00fcckgreift und auf Innovation baut. Du findest bei uns eine Kultur vor, die Menschen dazu ermutigt, unabh\u00e4ngig zu denken, unternehmerisch zu handeln und den Status quo in Frage zu stellen. Wir legen gro\u00dfen Wert auf die Zusammenarbeit vor Ort \u2013 unser B\u00fcro ist ein zentraler Ort des Dialogs, der Innovation und des gemeinsamen Wachstums. Gemeinsam arbeiten wir daran, unser Gesch\u00e4ft zu gestalten und unsere ehrgeizigen Ziele zu erreichen.\nWir freuen uns, wenn du dich uns anschlie\u00dft, um stets das Richtige f\u00fcr unsere Mitarbeiter, Kunden und unser Unternehmen zu tun \u2013\nOur future is where you take us!\nAus organisatorischen Gr\u00fcnden nehmen wir nur Bewerbungen an, die uns \u00fcber unser Online-Bewerbermanagementsystem auf der Website erreichen.\n*Aus Gr\u00fcnden der besseren Lesbarkeit wird auf die gleichzeitige Verwendung mehrgeschlechtlicher Sprachformen verzichtet. S\u00e4mtliche Personenbezeichnungen gelten gleichwohl f\u00fcr jegliches Geschlecht. Bei uns sind alle Bewerber willkommen, unabh\u00e4ngig von Geschlecht, Nationalit\u00e4t, ethnischer Herkunft, sozialem Hintergrund, Behinderung, Religion, Alter oder sexueller Orientierung. Bei Fragen wende dich bitte an unser Recruitment-Team unter recruitment@berenberg.de.\nBack to job list\nApply\nShare this job:\nShare (Senior) Backup Engineer / Architect* with a friend via e-mail",
        "application_url": "https://berenberg.avature.net/en_GB/careers/Login?jobId=2770",
        "metadata": {
            "Country": "Germany",
            "City": "Frankfurt, Hamburg",
            "Type of role": "Professional",
            "Working time": "Full-time",
            "Type of contract": "Permanent",
            "Remaining openings": "1"
        },
        "link": "https://berenberg.avature.net/en_GB/careers/JobDetail/Senior-Backup-Engineer-Architect/2770"
    },
    {
        "title": null,
        "description_html": null,
        "description_text": "Teamlead* Hotline & Local Service Germany\nGeneral information\nCountry\nGermany\nCity\nHamburg\nType of role\nProfessional\nWorking time\nFull-time\nType of contract\nPermanent\nRemaining openings\n1\nDescription & Requirements\nF\u00fcr unsere\nAbteilung Workplace & Tech Services\nam Standort\nHamburg\nsuchen wir zum\nn\u00e4chstm\u00f6glichen Zeitpunkt\ndich als\nTeamlead* Hotline & Local Service Germany\nInnovation Technology @ Berenberg\nIn einer \u00c4ra, in der Digitalisierung und moderne IT-Infrastrukturen das Banking revolutionieren, gestalten wir eine technologiegest\u00fctzte Bank, in der du als IT-Profi eng mit unseren Gesch\u00e4ftsbereichen zusammenarbeitest. Unsere Technology-Teams bieten dir ein Umfeld, das dich vor spannende Herausforderungen stellt \u2013 sei es durch den Support und die Weiterentwicklung von Legacy-Systemen oder die Einf\u00fchrung moderner Technologien wie KI, Machine Learning und hochgradig automatisierte Handelsapplikationen.\nUnsere IT-Abteilung mit etwa 300 Mitarbeitern arbeitet gr\u00f6\u00dftenteils agil nach einem Scrumban-Ansatz und deckt Bereiche wie Cloud Computing, Cybersecurity, Operations, Process and Governance, Software Development und Architecture ab. Wir sind besonders stolz darauf, fast alle unsere Applikationen Inhouse zu entwickeln, was uns eine einzigartige Flexibilit\u00e4t und Innovationskraft verleiht. Unser Tech Stack umfasst moderne Technologien wie Java, Kotlin, TypeScript und Python, CI/CD-Pipelines, Container, Kubernetes sowie Azure Cloud, Azure SQL Database und Oracle Datenbank mit PL/SQL.\nWelche Aufgaben erwarten dich?\nFachliche und disziplinarische F\u00fchrung des Local-Service- und IT-Hotline-Teams (1st & 2nd Level)\nSicherstellung eines stabilen, effizienten und serviceorientierten IT-Supports inklusive VIP-Support\nSteuerung und \u00dcberwachung von Incident-, Request- und Problem-Management inkl. Priorisierung und Eskalation\nAnalyse, Optimierung und Standardisierung von Support-Prozessen sowie Etablierung relevanter KPIs\nEnge Zusammenarbeit mit internen IT-Einheiten (Infrastruktur, Office Services, Security) und externen Dienstleistern\nMitarbeit in IT-Projekten sowie \u00dcbernahme von (Teil-)Projektleitungen und Serviceverantwortung\nWen suchen wir?\nMehrj\u00e4hrige Erfahrung im IT-Support bzw. End-User-Service mit fundierter F\u00fchrungserfahrung\nTiefgehendes technisches Know-how in Client-Umgebungen, M365, Windows, Ticketsystemen und Endger\u00e4ten\nHohe Seniorit\u00e4t im Umgang mit komplexen Supportf\u00e4llen, Eskalationen und anspruchsvollen Stakeholdern\nIdealerweise Branchenkenntnisse in regulierten Umfeldern wie Finanzdienstleistung oder Banking\nAusgepr\u00e4gte F\u00fchrungs-, Kommunikations- und Servicekompetenz mit klarer Entscheidungsf\u00e4higkeit\nSehr gute Deutsch- sowie gute Englischkenntnisse in Wort und Schrift\nWas wir Dir bieten:\nFlexible Arbeitszeiten innerhalb einer 39-Stunden-Woche\n30 Tage Jahresurlaub sowie zus\u00e4tzliche freie Tage am 24. und 31. Dezember\nVielseitiges und spannendes Aufgabengebiet in einem modernen und dynamischen Umfeld sowie ein wertsch\u00e4tzendes Betriebsklima\nGezielte F\u00f6rderung durch interne und externe Schulungs- und Entwicklungsprogramme\nBerenberg-Patensystem f\u00fcr ein strukturiertes und reibungsloses Onboarding\nVielf\u00e4ltige Zusch\u00fcsse (z.B. Deutschlandticket, JobRad, verm\u00f6genswirksame Leistungen, betriebliche Altersvorsorge, Essenszusch\u00fcsse bzw. Betriebsrestaurant in Hamburg)\nZus\u00e4tzliche Leistungen wie Familienservice, Arbeitszeitkonto (z. B. f\u00fcr Sabbaticals), betriebliche Sozialleistungen, Gesundheits- und Sportprogramme\nBewirb dich jetzt online und werde Teil des Teams \u2013\nwir freuen uns auf deine Bewerbung!\nWir sind eine f\u00fchrende europ\u00e4ische Privatbank mit \u00fcber 430 Jahren Erfahrung und einer tief verwurzelten Geschichte, aber wir gestalten und investieren noch immer in Zukunft. Unser Fortschritt und unsere Entwicklung werden von unseren Mitarbeitern vorangetrieben. Wir ermutigen sie, neue Ans\u00e4tze auszuprobieren, ihre Meinung zu \u00e4u\u00dfern und auf ihre eigene Art und Weise erfolgreich zu sein.\nWir bieten ihnen die M\u00f6glichkeit, ihre Talente zu entwickeln, verschiedene Karrierewege zu erkunden und ihr Potenzial voll auszusch\u00f6pfen.\nWir sind ein ehrgeiziges, zukunftsorientiertes Unternehmen, das auf jahrhundertealte Traditionen zur\u00fcckgreift und auf Innovation baut. Du findest bei uns eine Kultur vor, die Menschen dazu ermutigt, unabh\u00e4ngig zu denken, unternehmerisch zu handeln und den Status quo in Frage zu stellen. Wir legen gro\u00dfen Wert auf die Zusammenarbeit vor Ort \u2013 unser B\u00fcro ist ein zentraler Ort des Dialogs, der Innovation und des gemeinsamen Wachstums. Gemeinsam arbeiten wir daran, unser Gesch\u00e4ft zu gestalten und unsere ehrgeizigen Ziele zu erreichen.\nWir freuen uns, wenn du dich uns anschlie\u00dft, um stets das Richtige f\u00fcr unsere Mitarbeiter, Kunden und unser Unternehmen zu tun \u2013\nOur future is where you take us!\nAus organisatorischen Gr\u00fcnden nehmen wir nur Bewerbungen an, die uns \u00fcber unser Online-Bewerbermanagementsystem auf der Website erreichen.\n*Aus Gr\u00fcnden der besseren Lesbarkeit wird auf die gleichzeitige Verwendung mehrgeschlechtlicher Sprachformen verzichtet. S\u00e4mtliche Personenbezeichnungen gelten gleichwohl f\u00fcr jegliches Geschlecht. Bei uns sind alle Bewerber willkommen, unabh\u00e4ngig von Geschlecht, Nationalit\u00e4t, ethnischer Herkunft, sozialem Hintergrund, Behinderung, Religion, Alter oder sexueller Orientierung. Bei Fragen wende dich bitte an unser Recruitment-Team unter recruitment@berenberg.de.\nBack to job list\nApply\nShare this job:\nShare Teamlead* Hotline & Local Service Germany with a friend via e-mail",
        "application_url": "https://berenberg.avature.net/en_GB/careers/Login?jobId=2771",
        "metadata": {
            "Country": "Germany",
            "City": "Hamburg",
            "Type of role": "Professional",
            "Working time": "Full-time",
            "Type of contract": "Permanent",
            "Remaining openings": "1"
        },
        "link": "https://berenberg.avature.net/en_GB/careers/JobDetail/Teamlead-Hotline-Local-Service-Germany/2771"
    },
    {
        "title": null,
        "description_html": null,
        "description_text": "Werkstudent* Cloud DevOps\nGeneral information\nCountry\nGermany\nCity\nHamburg\nType of role\nWorking Student\nWorking time\nPart-time\nType of contract\nWorking Student\nRemaining openings\n1\nDescription & Requirements\nUnterst\u00fctzen Sie unser\nCloud Adoption Team\nin\nHamburg\nidealerweise\nf\u00fcr 6\u201312 Monate\nmit\n15\u201320 Stunden w\u00f6chentlich\nals\nWerkstudent* Cloud DevOps\nWelche Aufgaben erwarten Sie?\nPflege und Weiterentwicklung der vorhandenen Automatisierung\nWeiterentwicklung der Governance in Azure oder GCP\nTechnische Dokumentation, technische und operative Bearbeitung von Cloud Projekten\nWen suchen wir?\nImmatrikulierter Student an einer Hochschule oder Fachhochschule mit dem Schwerpunkt Informatik, Wirtschaftsinformatik, Wirtschaft oder einem vergleichbaren Studiengang\nGrundkenntnisse in DevOps und Softwareentwicklung\nMS-Office-Kenntnisse\nGute Englischkenntnisse in Wort und Schrift\nSelbstst\u00e4ndige, sorgf\u00e4ltige und zielorientierte Arbeitsweise\nTeamf\u00e4higkeit, Engagement und Freude am Umgang mit Menschen\nWas wir Ihnen bieten:\nVielseitiges und spannendes Aufgabengebiet in einem modernen und dynamischen Umfeld sowie ein wertsch\u00e4tzendes Betriebsklima\nStrukturiertes und reibungsloses Onboarding\nZugang zu unseren internen \u201eLearning & Development\u201c-Angeboten wie z. B. den \u201eLunch & Learn\u201c-Sessions, Seminaren oder inspirierenden Vortr\u00e4gen\nM\u00f6glichkeit, im Anschluss Teil unseres Future Talent Programms zu werden, welches unser exklusives Talentbindungsprogramm ist\nVielf\u00e4ltige Zusch\u00fcsse, z. B. f\u00fcr das Deutschlandticket und Essenszusch\u00fcsse\nZus\u00e4tzliche Leistungen wie betriebliche Sportprogramme sowie Zugang zu einem externen Vorteilsportal mit exklusiven Angeboten\nBewerben Sie sich jetzt online mit Ihren vollst\u00e4ndigen Bewerbungsunterlagen inklusive Immatrikulationsbescheinigung mit Angabe des Fachsemesters. Angeh\u00f6rige von Staaten au\u00dferhalb des europ\u00e4ischen Wirtschaftsraums schicken ggf. bitte ihre Aufenthalts- und Arbeitsgenehmigung mit.\nWir freuen uns auf Ihre Bewerbung!\nAls eine f\u00fchrende europ\u00e4ische Privatbank mit \u00fcber 430 Jahren Erfahrung blicken wir auf eine lange Unternehmensgeschichte zur\u00fcck. Gleichzeitig gestalten wir mit umfassenden Investitionen aktiv unsere Zukunft. Grundlage f\u00fcr unseren Fortschritt und unsere Weiterentwicklung sind unsere Mitarbeiter. Wir ermutigen diese, neue Ans\u00e4tze auszuprobieren, ihre Ideen mit einzubringen und ihren eigenen Weg zum Erfolg bei uns zu gehen. Wir sind ein ambitioniertes, zukunftsorientiertes Unternehmen, das jahrhundertelange Erfahrung und Innovationskraft vereint.\nBei uns erleben Sie eine Kultur, die zum selbstst\u00e4ndigen Denken anregt, Unternehmertum f\u00f6rdert und dazu ermutigt, den Status quo zu hinterfragen. Wir legen gro\u00dfen Wert auf die Zusammenarbeit vor Ort \u2013 unser B\u00fcro ist ein zentraler Ort des Dialogs, der Innovation und des gemeinsamen Wachstums. Sie treffen hier auf talentierte Kollegen, die es gewohnt sind, Verantwortung zu \u00fcbernehmen, und gemeinsam an einem Strang ziehen, um Ergebnisse zu erzielen.\nWerden Sie Teil von Berenberg und arbeiten Sie mit uns gemeinsam daran, das Richtige f\u00fcr unsere Kunden, unser Gesch\u00e4ft und unsere Mitarbeiter zu tun \u2013\nOur future is where you take us!\nAus organisatorischen Gr\u00fcnden nehmen wir nur Bewerbungen an, die uns \u00fcber unser Online-Bewerbermanagementsystem auf der Website erreichen.\n*Aus Gr\u00fcnden der besseren Lesbarkeit wird auf die gleichzeitige Verwendung mehrgeschlechtlicher Sprachformen verzichtet. S\u00e4mtliche Personenbezeichnungen gelten gleichwohl f\u00fcr jegliches Geschlecht. Bei uns sind alle Bewerbungen willkommen, unabh\u00e4ngig von Geschlecht, Nationalit\u00e4t, ethnischer Herkunft, sozialem Hintergrund, Behinderung, Religion, Alter oder sexueller Orientierung. Bei Fragen wenden Sie sich bitte an unser Recruitment-Team unter recruitment@berenberg.de.\nBack to job list\nApply\nShare this job:\nShare Werkstudent* Cloud DevOps with a friend via e-mail",
        "application_url": "https://berenberg.avature.net/en_GB/careers/Login?jobId=2772",
        "metadata": {
            "Country": "Germany",
            "City": "Hamburg",
            "Type of role": "Working Student",
            "Working time": "Part-time",
            "Type of contract": "Working Student",
            "Remaining openings": "1"
        },
        "link": "https://berenberg.avature.net/en_GB/careers/JobDetail/Werkstudent-Cloud-DevOps/2772"
    },
    {
        "title": null,
        "description_html": null,
        "description_text": "Senior Backup Engineer / Architect\nGeneral information\nCountry\nUnited Kingdom\nCity\nLondon\nType of role\nProfessional\nWorking time\nFull-time\nType of contract\nPermanent\nRemaining openings\n1\nDescription & Requirements\nFor our Core Infrastructure Services programme at our\nLondon\nlocation, we are looking for you to join us as soon as possible as\nSenior Backup Engineer / Architect*\nInnovation & Technology @ Berenberg\nIn an era in which digitalisation and modern IT infrastructures are revolutionising banking, we are shaping a technology-driven bank in which you, as an IT professional, will work closely with our business divisions. Our technology teams offer you an environment that presents you with exciting challenges \u2013 whether through the support and further development of legacy systems or the introduction of modern technologies such as AI, machine learning and highly automated trading applications.\nOur IT department, with around 300 employees, works largely in an agile manner using a Scrumban approach and covers areas such as cloud computing, cybersecurity, operations, process and governance, software development and architecture. We are particularly proud to develop almost all of our applications in-house, which gives us unique flexibility and innovative strength. Our tech stack in the area of core infrastructure services is based on a highly available environment with VMWare virtualisation and Citrix. We rely on a hybrid server landscape consisting of Windows and RHEL, robust network and firewall architectures from Citrix, and storage systems from Pure and Netapp. At the heart of it all are our database systems with Oracle, MS-SQL, and Azure SQL. Everything is secured by modern backup solutions from\nDell\nand\nRubrik\n, and our stack is rounded off by M365 and Exchange for seamless collaboration.\nYour role in the team\nIn our \"Linux, Storage & Backup\" team, we combine the tradition of a private bank with state-of-the-art IT infrastructure. We are in the midst of a major modernisation: moving away from legacy systems and towards\nRubrik\n. To this end, we are looking for an expert who not only administers, but also helps to shape the architecture of our data backup.\nYou will be the technical lead for our new backup strategy. You will accompany us in replacing Dell Networker/Data Domain and implement a future-proof Rubrik environment for our on-premise and cloud services.\nWhat tasks await you?\nYou will be responsible for the design, installation and configuration of the new Rubrik solution.\nPlanning and managing the transfer of existing backup procedures to the new environment\nConceptual creation of backup designs for our cloud integrations (M365, Salesforce, Azure)\nEnsuring ongoing operation (including troubleshooting) and monitoring using BACKUP EAGLE\nYou will be the first point of contact for auditing and governance for all questions relating to data security and recoverability (disaster recovery)\nWho are we looking for?\nSuccessfully completed IT or Technology degree with relevant professional experience\nSeveral years of experience as a systems engineer in the storage/backup environment, ideally in the banking or enterprise sector\nIn-depth knowledge of Linux is essential. Experience with Rubrik is a big plus; alternatively, in-depth knowledge of enterprise backup solutions (Dell Networker, Cohesity, Veeam, Commvault) and a desire to learn Rubrik\nA very good English skill is essential for working in our international teams, knowledge of German would be a great plus.\nWhat we offer you:\nPrivate pension plan - 10% of base salary contribution by Berenberg\nGenerous 30 day holiday allowance\nPrivate Health Insurance\nLife Insurance scheme\nFlexible working hours\nEnhanced parental leave policies\nEmployee Assistance Programme offering counselling sessions related to mental health, financial wellbeing and other topics\nApply online now to join our team \u2013\nwe look forward to receiving your application!\nWe are a leading European private bank, with over 430 years of experience and deep rooted history, but we are still shaping and heavily investing in our future. Our progress and evolution are driven by our people. We encourage them to try new approaches, voice their opinions and achieve success in their own way.\nWe provide opportunities for them to develop their talents, explore different career paths and achieve their full potential.\nWe\u2019re an ambitious, forward-looking business, backed by centuries of tradition and built on innovation. You\u2019ll find a culture that encourages people to think independently, act entrepreneurially and challenge the status quo.\nWe place great importance on working on site, as we believe that being together in the office not only fosters creativity and efficiency, but also strengthens networks and builds trusting, collegial relationships. For us, this forms the foundation for productive and successful work. Together we collaborate to shape our business and fulfil our ambitious goals.\nWe welcome you to join us in our commitment to always do the right thing for our people, clients and our business \u2013\nOur future is where you take us!\nWe will only accept applications submitted through our online application management system on the website.\nBerenberg is an Equal Opportunities Employer and prides itself on being a modern, dynamic and internationally orientated organisation. We value the rich diversity, skills and abilities and creative potential that people from differing backgrounds and experiences bring to the workplace. Every employee plays a vital role in providing quality service to all our customers and helping to create and inclusive working environment, where everyone can realise their full potential. We\u2019re committed to finding reasonable accommodations for candidates who require adjustments during our recruiting process. Please contact us directly on recruitment@berenberg.com to discuss.\nBack to job list\nApply\nShare this job:\nShare Senior Backup Engineer / Architect with a friend via e-mail",
        "application_url": "https://berenberg.avature.net/en_GB/careers/Login?jobId=2781",
        "metadata": {
            "Country": "United Kingdom",
            "City": "London",
            "Type of role": "Professional",
            "Working time": "Full-time",
            "Type of contract": "Permanent",
            "Remaining openings": "1"
        },
        "link": "https://berenberg.avature.net/en_GB/careers/JobDetail/Senior-Backup-Engineer-Architect/2781"
    },
    {
        "title": null,
        "description_html": null,
        "description_text": "Praktikum Real Estate\nGeneral information\nCountry\nGermany\nCity\nHamburg\nType of role\nInternship (off-cycle)\nWorking time\nFull-time\nType of contract\nInternship\nRemaining openings\n1\nDescription & Requirements\nUnterst\u00fctzen Sie unser\nReal Estate Team\nam Standort\nHamburg\nf\u00fcr mind. 3 Monate ab August 2026 als\nPraktikant* Real Estate\nIhre Rolle im Team\nSie m\u00f6chten einen Einblick in die spannende Welt einer Privatbank gewinnen und sind daran interessiert, den Arbeitsalltag im Real Estate n\u00e4her kennenzulernen? Dann sind Sie bei Berenberg genau richtig.\nDer Bereich Real Estate initiiert und managt aktiv Investmentl\u00f6sungen f\u00fcr private und institutionelle Anleger in Form von offenen und geschlossenen Investmentfonds (AIFs) sowie Individualmandaten und in dieser Rolle wer-den Sie die Kollegen s\u00e4mtlicher Real Estate Bereiche unterst\u00fctzen.\nWelche Aufgaben erwarten Sie?\nMitwirkung am Due-Diligence-Prozess von An- und Verk\u00e4ufen (z. B. durch Objekt-, Standort- und Mieteranalysen, Teilnahme an Objektbegehungen, Auswertung externer Due-Diligence-Berichte, Er-stellung von Ankaufskalkulation und Gremienvorlagen)\nUnterst\u00fctzung beim aktiven strategischen und operativen Management zur Erreichung der Portfolio-ziele (u.a. mit Prozessen zur strategischen Performance-Entwicklung, Vermietungst\u00e4tigkeiten, Baumo-nitoring und Reporting)\nUnterst\u00fctzung bei der Umsetzung und Nachverfolgung der Fondsstrategien sowie Zusammenf\u00fchrung und Analyse unterschiedlicher Daten und Informationen, Mitarbeit beim periodischen Reporting und bei der Erstellung von Gesch\u00e4ftsberichten und Jahresabschl\u00fcssen\neteiligung bei der aktiven Marktansprache potenzieller Investoren, Erstellung strategischer Marketing- und Vertriebsunterlagen sowie Auswertung und Analyse aktueller Aktivit\u00e4ten\nWen suchen wir?\nStudent* eines immobilienwirtschaftlichen oder wirtschaftswissenschaftlichen Studiengangs. Ausbil-dung oder erste praktische Erfahrung in einem Unternehmen w\u00fcnschenswert\nSicherer Umgang mit den MS-Office-Produkten\nFlie\u00dfend Deutsch und gute Englischkenntnisse\nEngagierte, selbstst\u00e4ndige und eigenverantwortliche Arbeitsweise\nGute analytische F\u00e4higkeiten, schnelle Auffassungsgabe sowie Kommunikationsfreude und Teamorien-tierung\nWas wir Ihnen bieten:\nVielseitiges und spannendes Aufgabengebiet in einem modernen und dynamischen Umfeld sowie ein wertsch\u00e4tzendes Betriebsklima\nStrukturiertes und reibungsloses Onboarding\nZugang zu unseren internen \u201eLearning & Development\u201c Angeboten wie z. B. den \u201eLunch & Learn\u201c- Ses-sions, Seminaren oder inspirierenden Vortr\u00e4gen\nM\u00f6glichkeit, im Anschluss Teil unseres Future Talent Programms zu werden, welches unser exklusives Talentbindungsprogramm ist\nVielf\u00e4ltige Zusch\u00fcsse f\u00fcr z. B. Deutschlandticket und Essenszusch\u00fcsse\nZus\u00e4tzliche Leistungen wie betriebliche Sportprogramme, sowie Zugang zu externem Vorteilsportal mit exklusiven Angeboten\nBewerben Sie sich jetzt online mit Ihren vollst\u00e4ndigen Bewerbungsunterlagen inklusive Immatrikulationsbe-scheinigung mit Angabe des Fachsemesters. Angeh\u00f6rige von Staaten au\u00dferhalb des europ\u00e4ischen Wirtschafts-raums schicken ggf. bitte ihre Aufenthalts- und Arbeitsgenehmigung mit.\nWir freuen uns auf Ihre Bewerbung!\nAls eine f\u00fchrende europ\u00e4ische Privatbank mit \u00fcber 430 Jahren Erfahrung blicken wir auf eine lange Unterneh-mensgeschichte zur\u00fcck. Gleichzeitig gestalten wir mit umfassenden Investitionen aktiv unsere Zukunft. Grund-lage f\u00fcr unseren Fortschritt und unsere Weiterentwicklung sind unsere Mitarbeiter. Wir ermutigen diese, neue Ans\u00e4tze auszuprobieren, ihre Ideen mit einzubringen und ihren eigenen Weg zum Erfolg bei uns zu gehen. Wir sind ein ambitioniertes, zukunftsorientiertes Unternehmen, das jahrhundertelange Erfahrung und Innovations-kraft vereint.\nBei uns erleben Sie eine Kultur, die zum selbstst\u00e4ndigen Denken anregt, Unternehmertum f\u00f6rdert und dazu ermutigt, den Status quo zu hinterfragen. Wir legen gro\u00dfen Wert auf die Zusammenarbeit vor Ort \u2013 unser B\u00fcro ist ein zentraler Ort des Dialogs, der Innovation und des gemeinsamen Wachstums. Sie treffen hier auf talentier-te Kollegen, die es gewohnt sind, Verantwortung zu \u00fcbernehmen, und gemeinsam an einem Strang ziehen, um Ergebnisse zu erzielen.\nWerden Sie Teil von Berenberg und arbeiten Sie mit uns gemeinsam daran, das Richtige f\u00fcr unsere Kunden, unser Gesch\u00e4ft und unsere Mitarbeiter zu tun \u2013\nOur future is where you take us!\nAus organisatorischen Gr\u00fcnden nehmen wir nur Bewerbungen an, die uns \u00fcber unser Online-Bewerbermanagementsystem auf der Website erreichen.\n*Aus Gr\u00fcnden der besseren Lesbarkeit wird auf die gleichzeitige Verwendung mehrgeschlechtlicher Sprachformen verzichtet. S\u00e4mtliche Personenbezeichnungen gelten gleichwohl f\u00fcr jegliches Geschlecht. Bei uns sind alle Bewerbungen willkommen, unabh\u00e4ngig von Geschlecht, Nationalit\u00e4t, ethnischer Herkunft, sozialem Hintergrund, Behinderung, Religion, Alter oder sexu-eller Orientierung. Bei Fragen wenden Sie sich bitte an unser Recruitment-Team unter recruitment@berenberg.de.\nBack to job list\nApply\nShare this job:\nShare Praktikum Real Estate with a friend via e-mail",
        "application_url": "https://berenberg.avature.net/en_GB/careers/Login?jobId=2769",
        "metadata": {
            "Country": "Germany",
            "City": "Hamburg",
            "Type of role": "Internship (off-cycle)",
            "Working time": "Full-time",
            "Type of contract": "Internship",
            "Remaining openings": "1"
        },
        "link": "https://berenberg.avature.net/en_GB/careers/JobDetail/Praktikum-Real-Estate/2769"
    },
    {
        "title": null,
        "description_html": null,
        "description_text": "(Senior) Application Support Specialist* Onlinebanking\nGeneral information\nCountry\nGermany\nCity\nHamburg\nType of role\nProfessional\nWorking time\nFull-time\nType of contract\nPermanent\nRemaining openings\n1\nDescription & Requirements\nF\u00fcr unser Programm\nWorkplace & Tech Services\nam\nStandort Hamburg\nsuchen wir zum\nn\u00e4chstm\u00f6glichen Zeitpunkt\ndich als\n(Senior) Application Support Specialist* Onlinebanking\nInnovation & Technology @ Berenberg.\nIn einer \u00c4ra, in der Digitalisierung und moderne IT-Infrastrukturen das Banking revolutionieren, gestalten wir eine technologiegest\u00fctzte Bank, in der du als IT-Profi eng mit unseren Gesch\u00e4ftsbereichen zusammenarbeitest. Unsere Technology-Teams bieten dir ein Umfeld, das dich vor spannende Herausforderungen stellt \u2013 sei es durch den Support und die Weiterentwicklung von Legacy-Systemen oder die Einf\u00fchrung moderner Technologien wie KI, Machine Learning und hochgradig automatisierte Handelsapplikationen.\nUnsere IT-Abteilung mit etwa 300 Mitarbeitern arbeitet gr\u00f6\u00dftenteils agil nach einem Scrumban-Ansatz und deckt Bereiche wie Cloud Computing, Cybersecurity, Operations, Process and Governance, Software Development und Architecture ab. Wir sind besonders stolz darauf, fast alle unsere Applikationen Inhouse zu entwickeln, was uns eine einzigartige Flexibilit\u00e4t und Innovationskraft verleiht. Unser Tech Stack umfasst moderne Technologien wie Java, Kotlin, TypeScript und Python, CI/CD-Pipelines, Container, Kubernetes sowie Azure Cloud, Azure SQL Database und Oracle Datenbank mit PL/SQL.\nDeine Rolle im Team\nUnser Team Tech Support Center ist f\u00fcr den technischen Support im Bereich Onlinebanking f\u00fcr unsere Wealth Management und Corporate Banking Kunden verantwortlich, dar\u00fcber hinaus sind wir die erste Anlaufstelle f\u00fcr ausgew\u00e4hlte interne Mitarbeiter bei technischen St\u00f6rungen.\nWelche Aufgaben erwarten Dich?\nKompetente Beratung und Betreuung unserer anspruchsvollen Bankkunden im Helpdesk Support f\u00fcr das Onlinebanking (technisch)\nEinarbeitung in spezifische bankfachliche Abl\u00e4ufe und die dazugeh\u00f6renden IT-Systeme\nErl\u00e4uterung komplexer Probleml\u00f6sungen auf verst\u00e4ndliche Weise\nEnge Zusammenarbeit mit unseren Second-/Third-Level Teams, dem Backoffice und Bankfachbereichen\nBetreuung unserer (VIP)-Mitarbeiter bei Fragen und Problemen bzgl. Hardware- und Softwareanwendungen und Berechtigungen\nBearbeitung des Tagesgesch\u00e4fts auf Basis eines ITIL-basierten Ticketsystems\nMitarbeit in Projekten und \u00dcbernahme von Aufgaben neben dem Tagesgesch\u00e4ft\nPflege interner Systemdaten und unserer Wissensdatenbank\nWen suchen wir?\nErfolgreich abgeschlossene Ausbildung im Bankbereich, als Fachinformatiker f\u00fcr Systemintegration oder eine vergleichbare Qualifikation mit entsprechender Berufserfahrung\nErfahrungen im Bereich technischen Support f\u00fcr Onlinebanking und/oder IT-Support, idealerweise eines Finanzdienstleisters\nSehr gute Kommunikationsf\u00e4higkeit und Begeisterung f\u00fcr die Zusammenarbeit mit anspruchsvollen Kunden\nSehr gute Deutsch- und Englischkenntnisse in Wort und Schrift\nWas wir Dir bieten:\nFlexible Arbeitszeiten innerhalb einer 39-Stunden-Woche\n30 Tage Jahresurlaub sowie zus\u00e4tzliche freie Tage am 24. und 31. Dezember\nVielseitiges und spannendes Aufgabengebiet in einem modernen und dynamischen Umfeld sowie ein wertsch\u00e4tzendes Betriebsklima\nGezielte F\u00f6rderung durch interne und externe Schulungs- und Entwicklungsprogramme\nBerenberg-Patensystem f\u00fcr ein strukturiertes und reibungsloses Onboarding\nVielf\u00e4ltige Zusch\u00fcsse (z. B. Deutschlandticket, JobRad, verm\u00f6genswirksame Leistungen, betriebliche Altersvorsorge, Essenszusch\u00fcsse bzw. Betriebsrestaurant in Hamburg)\nZus\u00e4tzliche Leistungen wie Familienservice, Arbeitszeitkonto (z. B. f\u00fcr Sabbaticals), betriebliche Sozialleistungen, Gesundheits- und Sportprogramme\nBewirb dich jetzt online und werde Teil des Teams \u2013\nwir freuen uns auf deine Bewerbung!\nWir sind eine f\u00fchrende europ\u00e4ische Privatbank mit \u00fcber 430 Jahren Erfahrung und einer tief verwurzelten Geschichte, aber wir gestalten und investieren noch immer in Zukunft. Unser Fortschritt und unsere Entwicklung werden von unseren Mitarbeitern vorangetrieben. Wir ermutigen sie, neue Ans\u00e4tze auszuprobieren, ihre Meinung zu \u00e4u\u00dfern und auf ihre eigene Art und Weise erfolgreich zu sein.\nWir bieten ihnen die M\u00f6glichkeit, ihre Talente zu entwickeln, verschiedene Karrierewege zu erkunden und ihr Potenzial voll auszusch\u00f6pfen.\nWir sind ein ehrgeiziges, zukunftsorientiertes Unternehmen, das auf jahrhundertealte Traditionen zur\u00fcckgreift und auf Innovation baut. Du findest bei uns eine Kultur vor, die Menschen dazu ermutigt, unabh\u00e4ngig zu denken, unternehmerisch zu handeln und den Status quo in Frage zu stellen. Wir legen gro\u00dfen Wert auf die Zusammenarbeit vor Ort \u2013 unser B\u00fcro ist ein zentraler Ort des Dialogs, der Innovation und des gemeinsamen Wachstums. Gemeinsam arbeiten wir daran, unser Gesch\u00e4ft zu gestalten und unsere ehrgeizigen Ziele zu erreichen.\nWir freuen uns, wenn du dich uns anschlie\u00dft, um stets das Richtige f\u00fcr unsere Mitarbeiter, Kunden und unser Unternehmen zu tun \u2013\nOur future is where you take us!\nAus organisatorischen Gr\u00fcnden nehmen wir nur Bewerbungen an, die uns \u00fcber unser Online-Bewerbermanagementsystem auf der Website erreichen.\n*Aus Gr\u00fcnden der besseren Lesbarkeit wird auf die gleichzeitige Verwendung mehrgeschlechtlicher Sprachformen verzichtet. S\u00e4mtliche Personenbezeichnungen gelten gleichwohl f\u00fcr jegliches Geschlecht. Bei uns sind alle Bewerber willkommen, unabh\u00e4ngig von Geschlecht, Nationalit\u00e4t, ethnischer Herkunft, sozialem Hintergrund, Behinderung, Religion, Alter oder sexueller Orientierung. Bei Fragen wende dich bitte an unser Recruitment-Team unter recruitment@berenberg.de.\nBack to job list\nApply\nShare this job:\nShare (Senior) Application Support Specialist* Onlinebanking with a friend via e-mail",
        "application_url": "https://berenberg.avature.net/en_GB/careers/Login?jobId=2765",
        "metadata": {
            "Country": "Germany",
            "City": "Hamburg",
            "Type of role": "Professional",
            "Working time": "Full-time",
            "Type of contract": "Permanent",
            "Remaining openings": "1"
        },
        "link": "https://berenberg.avature.net/en_GB/careers/JobDetail/Senior-Application-Support-Specialist-Onlinebanking/2765"
    },
    {
        "title": null,
        "description_html": null,
        "description_text": "Anti-Financial Crime Compliance Spezialist*\nGeneral information\nCountry\nGermany\nCity\nFrankfurt, Hamburg\nType of role\nProfessional\nWorking time\nFull-time\nType of contract\nPermanent\nRemaining openings\n1\nDescription & Requirements\nZur Verst\u00e4rkung unserer\nAnti-Financial Crime Compliance (AFC Compliance)\nim Bereich\nGroup Compliance\nin\nHamburg/Frankfurt\nsuchen wir zum\nn\u00e4chstm\u00f6glichen\nZeitpunkt\nSie als\nAnti-Financial Crime Compliance Spezialist*\nIhre Rolle im Team\nSie stellen die Einhaltung nationaler und internationaler Sanktions- und Embargovorgaben sicher und pr\u00fcfen Zahlungen, Wertpapiertransaktionen sowie Vertragspartner risikoorientiert. Sie bearbeiten Treffer-Alerts im Zahlungsverkehr nach revisionssicheren Standards und stehen im engen Austausch mit internationalen Korrespondenzbanken. Dar\u00fcber hinaus beraten Sie Marktbereiche zu regulatorischen Anforderungen, begleiten KYC/CDD-Prozesse und entwickeln das AML/CTF-Framework inklusive Trainings- und Risikoanalysen kontinuierlich weiter.\nWelche Aufgaben erwarten Sie?\nPr\u00fcfung von Zahlungen, Wertpapiertransaktionen und Vertragspartnern auf (inter-)nationale Embargo- und Sanktionsbestimmungen\nBearbeitung von Treffer-Alerts im Zahlungsverkehr unter Einhaltung revisionssicherer Prozesse\nAbstimmung mit (internationalen) Korrespondenzbanken zur Umsetzung von Sanktionspr\u00e4ventionsma\u00dfnahmen\nBeratung der Marktbereiche zu regulatorischen Anforderungen, KYC/CDD und Kundenonboarding\nKonzeption von Awareness-Trainings, Aktualisierung von Risikoanalysen und des AML/CTF-Frameworks\nWen suchen wir?\nAbgeschlossene Bankausbildung oder fundiertes Fachwissen zu Prozessen, Produkten und Dienstleistungen in Kreditinstituten oder Wirtschaftspr\u00fcfungs-/Beratungsgesellschaften.\nMehrj\u00e4hrige Erfahrung in Pr\u00fcfung und Umsetzung (inter-)nationaler Sanktionsbestimmungen sowie in der Pr\u00e4vention von Geldw\u00e4sche, Terrorismusfinanzierung, Betrug und Korruption, idealerweise in internationalen Banken.\nPraktische Erfahrung mit AFC-Compliance-Monitoring-Systemen einschlie\u00dflich revisionssicherer Fallbearbeitung.\nErfahrung in Projektarbeit sowie analytische, proaktive und eigenmotivierte Arbeitsweise.\nSehr gute Deutsch- und Englischkenntnisse, sicheres Auftreten und Durchsetzungsverm\u00f6gen.\nWas wir Ihnen bieten:\nFlexible Arbeitszeiten innerhalb einer 39-Stunden-Woche\n30 Tage Jahresurlaub\nVielseitiges und spannendes Aufgabengebiet in einem modernen und dynamischen Umfeld sowie wert-sch\u00e4tzendes Betriebsklima\nGezielte F\u00f6rderung durch interne und externe Schulungs- und Entwicklungsprogramme\nBerenberg-Patensystem f\u00fcr ein strukturiertes und reibungsloses Onboarding\nVielf\u00e4ltige Zusch\u00fcsse (z. B. Deutschlandticket, JobRad, verm\u00f6genswirksame Leistungen, betriebliche Altersvorsorge)\nZus\u00e4tzliche Leistungen wie Familienservice, Arbeitszeitkonto (z. B. f\u00fcr Sabbaticals), betriebliche Sozialeistungen, Gesundheits- und Sportprogramme\nBewerben Sie sich jetzt online und werden Sie Teil des Teams \u2013\nwir freuen uns auf Ihre Bewerbung!\nAls eine f\u00fchrende europ\u00e4ische Privatbank mit \u00fcber 430 Jahren Erfahrung blicken wir auf eine lange Unternehmensgeschichte zur\u00fcck. Gleichzeitig gestalten wir mit umfassenden Investitionen aktiv unsere Zukunft. Grundlage f\u00fcr unseren Fortschritt und unsere Weiterentwicklung sind unsere Mitarbeiter. Wir ermutigen diese, neue Ans\u00e4tze auszuprobieren, ihre Ideen mit einzubringen und ihren eigenen Weg zum Erfolg bei uns zu gehen. Wir sind ein ambitioniertes, zukunftsorientiertes Unternehmen, das jahrhundertelange Erfahrung und Innovationskraft vereint. Bei uns erleben Sie eine Kultur, die zum selbstst\u00e4ndigen Denken anregt, Unternehmertum f\u00f6rdert und dazu ermutigt, den Status quo zu hinterfragen. Sie treffen hier auf talentierte Kollegen, die es gewohnt sind, Verantwortung zu \u00fcbernehmen, und gemeinsam an einem Strang ziehen, um Ergebnisse zu erzielen.\nWerden Sie Teil von Berenberg und arbeiten Sie mit uns gemeinsam daran, das Richtige f\u00fcr unsere Kunden, unser Gesch\u00e4ft und unsere Mitarbeiter zu tun \u2013\nOur future is where you take us!\nAus organisatorischen Gr\u00fcnden nehmen wir nur Bewerbungen an, die uns \u00fcber unser Online-Bewerbermanagementsystem auf der Website erreichen.\n*Aus Gr\u00fcnden der besseren Lesbarkeit wird auf die gleichzeitige Verwendung mehrgeschlechtlicher Sprachformen verzichtet. S\u00e4mtliche Personenbezeichnungen gelten gleichwohl f\u00fcr jegliches Geschlecht.Bei uns sind alle Bewerbungen willkommen, unabh\u00e4ngig von Geschlecht, Nationalit\u00e4t, ethnischer Herkunft, sozialem Hintergrund, Behinderung, Religion, Alter oder sexueller Orientierung.Bei Fragen wenden Sie sich bitte an unser Recruitment-Team unter recruitment@berenberg.de.\nBack to job list\nApply\nShare this job:\nShare Anti-Financial Crime Compliance Spezialist* with a friend via e-mail",
        "application_url": "https://berenberg.avature.net/en_GB/careers/Login?jobId=2763",
        "metadata": {
            "Country": "Germany",
            "City": "Frankfurt, Hamburg",
            "Type of role": "Professional",
            "Working time": "Full-time",
            "Type of contract": "Permanent",
            "Remaining openings": "1"
        },
        "link": "https://berenberg.avature.net/en_GB/careers/JobDetail/Anti-Financial-Crime-Compliance-Spezialist/2763"
    },
    {
        "title": null,
        "description_html": null,
        "description_text": "Business Manager* Transaction Services\nGeneral information\nCountry\nGermany\nCity\nHamburg\nType of role\nProfessional\nWorking time\nFull-time\nType of contract\nPermanent\nRemaining openings\n1\nDescription & Requirements\nF\u00fcr unseren\nBereich TS Projects, Regulation, Market & Reference Data\nam\nStandort Hamburg\nsuchen wir zum\nn\u00e4chstm\u00f6glichen Zeitpunkt\nSie als\nBusiness Manager*\nIhre Rolle im Team\nDas Team Business Management & Digitalisation \u00fcbernimmt eine zentrale Rolle bei der strategischen und operativen Weiterentwicklung\u00a0 des Bereichs Transaction Services. In dieser Rolle k\u00f6nnen Sie Teil eines Hands-on-Teams werden, das die Weiterentwicklung des Bereichs, unter\u00a0 Einhaltung der regulatorischer Anforderungen, vorantreibt.\nWelche Aufgaben erwarten Sie?\nWeiterentwicklung des Bereichs Transaction Services inklusive Implementierung neuer Produkte und Optimierung interner Prozesse durch Automatisierung und Digitalisierungsinitiativen\nAnalyse und Umsetzung regulatorischer Anforderungen sowie Begleitung von aufsichtsrechtlichen Pr\u00fcfungen\nErstellung von Management-Pr\u00e4sentationen, Entscheidungsvorlagen und bereichs\u00fcbergreifenden Abstimmungen\nEntwicklung aussagekr\u00e4ftiger Management-Reports, KPIs und datenbasierter Analysen\nStrukturierte und kundenorientierte L\u00f6sungsfindung sowie fungieren als zentrale Schnittstelle zu relevanten Stakeholdern der Gesamtbank\nWen suchen wir?\nErfolgreich abgeschlossene Bankausbildung oder ein wirtschaftswissenschaftliches Studium\nMehrj\u00e4hrige Berufserfahrung im Banken- oder Finanzdienstleistungsumfeld von Vorteil\nErste Erfahrungen mit SQL, Python oder VBA sind w\u00fcnschenswert\nSehr gute Kenntnisse in MS Office\nAusgepr\u00e4gte Hands-on-Mentalit\u00e4t, Kreativit\u00e4t, Teamf\u00e4higkeit sowie unternehmerisches Denken\nSehr gute Deutsch- und Englischkenntnisse in Wort und Schrift\nWas wir Ihnen bieten:\nFlexible Arbeitszeiten innerhalb einer 39-Stunden-Woche\n30 Tage Jahresurlaub sowie zus\u00e4tzliche freie Tage am 24. und 31. Dezember\nVielseitiges und spannendes Aufgabengebiet in einem modernen und dynamischen Umfeld sowie wertsch\u00e4tzendes Betriebsklima\nGezielte F\u00f6rderung durch interne und externe Schulungs- und Entwicklungsprogramme\nBerenberg-Patensystem f\u00fcr ein strukturiertes und reibungsloses Onboarding\nVielf\u00e4ltige Zusch\u00fcsse (z. B. Deutschlandticket, JobRad, verm\u00f6genswirksame Leistungen, betriebliche Altersvorsorge, Essenszusch\u00fcsse bzw. Betriebsrestaurant in Hamburg)\nZus\u00e4tzliche Leistungen wie Familienservice, Arbeitszeitkonto (z. B. f\u00fcr Sabbaticals), betriebliche Sozialleistungen, Gesundheits- und Sportprogramme\nBewerben Sie sich jetzt online und werden Sie Teil des Teams \u2013\nwir freuen uns auf Ihre Bewerbung!\nAls eine f\u00fchrende europ\u00e4ische Privatbank mit \u00fcber 430 Jahren Erfahrung blicken wir auf eine lange Unternehmensgeschichte zur\u00fcck. Gleichzeitig gestalten wir mit umfassenden Investitionen aktiv unsere Zukunft. Grundlage f\u00fcr unseren Fortschritt und unsere Weiterentwicklung sind unsere Mitarbeiter. Wir ermutigen diese, neue Ans\u00e4tze auszuprobieren, ihre Ideen mit einzubringen und ihren eigenen Weg zum Erfolg bei uns zu gehen. Wir sind ein ambitioniertes, zukunftsorientiertes Unternehmen, das jahrhundertelange Erfahrung und Innovationskraft vereint.\nBei uns erleben Sie eine Kultur, die zum selbstst\u00e4ndigen Denken anregt, Unternehmertum f\u00f6rdert und dazu ermutigt, den Status quo zu hinterfragen. Wir legen gro\u00dfen Wert auf die Zusammenarbeit vor Ort \u2013 unser B\u00fcro ist ein zentraler Ort des Dialogs, der Innovation und des gemeinsamen Wachstums. Sie treffen hier auf talentierte Kollegen, die es gewohnt sind, Verantwortung zu \u00fcbernehmen, und gemeinsam an einem Strang ziehen, um Ergebnisse zu erzielen.\nWerden Sie Teil von Berenberg und arbeiten Sie mit uns gemeinsam daran, das Richtige f\u00fcr unsere Kunden, unser Gesch\u00e4ft und unsere Mitarbeiter zu tun \u2013\nOur future is where you take us!\nAus organisatorischen Gr\u00fcnden nehmen wir nur Bewerbungen an, die uns \u00fcber unser Online-Bewerbermanagementsystem auf der Website erreichen.\n*Aus Gr\u00fcnden der besseren Lesbarkeit wird auf die gleichzeitige Verwendung mehrgeschlechtlicher Sprachformen verzichtet. S\u00e4mtliche Personenbezeichnungen gelten gleichwohl f\u00fcr jegliches Geschlecht. Bei uns sind alle Bewerbungen willkommen, unabh\u00e4ngig von Geschlecht, Nationalit\u00e4t, ethnischer Herkunft, sozialem Hintergrund, Behinderung, Religion, Alter oder sexueller Orientierung. Bei Fragen wenden Sie sich bitte an unser Recruitment-Team unter recruitment@berenberg.de.\nBack to job list\nApply\nShare this job:\nShare Business Manager* Transaction Services with a friend via e-mail",
        "application_url": "https://berenberg.avature.net/en_GB/careers/Login?jobId=2733",
        "metadata": {
            "Country": "Germany",
            "City": "Hamburg",
            "Type of role": "Professional",
            "Working time": "Full-time",
            "Type of contract": "Permanent",
            "Remaining openings": "1"
        },
        "link": "https://berenberg.avature.net/en_GB/careers/JobDetail/Business-Manager-Transaction-Services/2733"
    },
    {
        "title": null,
        "description_html": null,
        "description_text": "Network Engineer (Financial services/Electronic trading)\nGeneral information\nCountry\nUnited Kingdom\nCity\nLondon\nType of role\nProfessional\nWorking time\nFull-time\nType of contract\nPermanent\nRemaining openings\n1\nDescription & Requirements\nFor our\nInnovation & Technology\ndepartment in\nLondon\nwe are looking to hire a:\nSenior Network Engineer\nInnovation & Technology @ Berenberg\nIn an era where digitalisation and modern IT infrastructure is revolutionizing banking, we are shaping a technology-driven bank in which you as an IT professional will work closely with our business units. Our technology teams offer you an environment that will present you with exciting challenges - be it through the support and further development of legacy systems or the introduction of modern technologies such as AI, machine learning and highly automated trading applications.\nYour Role in the team.\nAs a Senior Network you will be contributing to the design, implementation, and maintenance of a highly availa-ble, secure, and scalable enterprise network infrastructure critical to trading and core operations. This position requires deep, practical expertise in Layer 3 routing and BGP on Arista platforms and Fortinet security devices. The successful candidate will play a critical role in translating architectural designs into operational reality, collaborating closely with the Lead Network Architect, and driving operational excellence while adhering to strict financial compliance and security standards.\nWhat will you do:\nArchitectural Collaboration: Work directly with the Lead Network Architect to review High-Level Designs, provide technical feasibility assessments, and translate the architecture into detailed Low-Level Designs (LLDs) and implementation plans (e.g. using NetBrain)\nLead the deployment and configuration of core network infrastructure projects focused on scalability and high availability, e.g. new exchange / trading venue connectivity via datacentre cross-connects\nAdminister and maintain the enterprise security posture using Fortinet devices, ensuring policy en-forcement aligns with security principles like PoLP.\nProvide 3rd-line escalation support for all critical network incidents.\nDevelop and enforce network standards, policies, and operational procedures, ensuring adherence to internal risk controls and external regulatory requirements.\nOnboard and setup new connectivity with new trading partners and venues\nWho are we looking for?\nDeep Expertise in BGP: Proven, hands-on experience designing, implementing, and troubleshooting complex Border Gateway Protocol (BGP) topologies, including route manipulation, path selection, multi-homing, and peering, VRF etc.\nNetwork Architecture: Demonstrated ability to design and implement highly resilient and scalable Lay-er 3 network architectures, including spine-and-leaf topologies, with a focus on low-latency and high-throughput environments (e.g., trading platforms)\nArista Networks: Hands-on experience with configuration, operation, and advanced troubleshooting of Arista switches and routers, including experience with Arista EOS\nPrinciple of Least Privilege (Security Concept) & Zero Trust: Strong foundational knowledge and practi-cal experience in applying the Principle of Least Privilege (PoLP) & Zero Trust to network device access, network segmentation, and firewall rule creation to minimize the network attack surface in a regulated financial environment\nComplex Troubleshooting: Ability to conduct deep-dive, packet-level analysis and root cause analysis (RCA) on complex, multi-protocol network issues across LAN, WAN, and Data Centre environments\nNice to have:\nPractical experience using Infrastructure as Code tools such as Terraform or Ansible for net-work configuration management, provisioning, and automated deployments\nScripting: Proficiency in scripting languages, preferably Python, for network automation, API in-teraction, data manipulation, and custom tooling development\nWhat we offer you:\nPrivate pension plan - 10% of base salary contribution by Berenberg\nGenerous 30 day holiday allowance\nPrivate Health Insurance\nLife Insurance scheme\nFlexible working hours\nEnhanced parental leave policies\nEmployee Assistance Programme offering counselling sessions related to mental health, financial wellbeing and other topics\nApply online now to join our team \u2013\nwe look forward to receiving your application!\nWe are a leading European private bank, with over 430 years of experience and deep rooted history, but we are still shaping and heavily investing in our future. Our progress and evolution are driven by our people. We encourage them to try new approaches, voice their opinions and achieve success in their own way.\nWe provide opportunities for them to develop their talents, explore different career paths and achieve their full potential.\nWe\u2019re an ambitious, forward-looking business, backed by centuries of tradition and built on innovation. You\u2019ll find a culture that encourages people to think independently, act entrepreneurially and challenge the status quo.\nWe place great importance on working on site, as we believe that being together in the office not only fosters creativity and efficiency, but also strengthens networks and builds trusting, collegial relationships. For us, this forms the foundation for productive and successful work. Together we collaborate to shape our business and fulfil our ambitious goals.\nWe welcome you to join us in our commitment to always do the right thing for our people, clients and our business \u2013\nOur future is where you take us!\nWe will only accept applications submitted through our online application management system on the website.\nBerenberg is an Equal Opportunities Employer and prides itself on being a modern, dynamic and internationally orientated organisation. We value the rich diversity, skills and abilities and creative potential that people from differing backgrounds and experiences bring to the workplace. Every employee plays a vital role in providing quality service to all our customers and helping to create and inclusive working environment, where everyone can realise their full potential. We\u2019re committed to finding reasonable accommodations for candidates who require adjustments during our recruiting process. Please contact us directly on recruitment@berenberg.com to discuss.\nBack to job list\nApply\nShare this job:\nShare Network Engineer (Financial services/Electronic trading) with a friend via e-mail",
        "application_url": "https://berenberg.avature.net/en_GB/careers/Login?jobId=2369",
        "metadata": {
            "Country": "United Kingdom",
            "City": "London",
            "Type of role": "Professional",
            "Working time": "Full-time",
            "Type of contract": "Permanent",
            "Remaining openings": "1"
        },
        "link": "https://berenberg.avature.net/en_GB/careers/JobDetail/Network-Engineer-Financial-services-Electronic-trading/2369"
    },
    {
        "title": null,
        "description_html": null,
        "description_text": "Teamlead* Accounting\nGeneral information\nCountry\nGermany\nCity\nHamburg\nType of role\nProfessional\nWorking time\nFull-time\nType of contract\nPermanent\nRemaining openings\n1\nDescription & Requirements\nF\u00fcr unseren\nBereich Risk & Finance\nam\nStandort Hamburg\nsuchen wir zum\nn\u00e4chstm\u00f6glichen Zeitpunkt\nSie als\nTeamlead* Accounting\nIhre Rolle im Team\nAls F\u00fchrungskraft \u00fcbernehmen Sie die fachliche und disziplinarische F\u00fchrung des Accounting-Teams an den Standorten Hamburg und Frankfurt und tragen die Gesamtverantwortung f\u00fcr die Abschlusserstellung nach HGB und RechKredV auf Bank- und Gruppenebene. Sie stellen eine reibungslose Finanzberichterstattung inklusive regulatorischer Meldungen an die Bundesbank sicher und agieren als zentrale Schnittstelle im operativen Tagesgesch\u00e4ft. Dar\u00fcber hinaus bringen Sie sich aktiv in bankweite Projekte ein und treiben die Weiterentwicklung moderner, datengetriebener Accounting-L\u00f6sungen in enger Abstimmung mit der Abteilungsleitung voran.\nWelche Aufgaben erwarten Sie?\nDisziplinarische und fachliche F\u00fchrung des Accounting-Teams an den Standorten Hamburg und Frankfurt\nVerantwortung f\u00fcr die Erstellung der Jahresabschl\u00fcsse nach HGB und RechKredV f\u00fcr die Bank sowie die Berenberg Gruppe\nErstellung und fristgerechter Versand von FinRep- und statistischen Meldungen (Bista, Austa etc.) an die Bundesbank\nSicherstellung reibungsloser Abstimmungen im Accounting-Tagesgesch\u00e4ft mit relevanten Fachbereichen\nMitwirkung an bankweiten Projekten mit Auswirkungen auf die Rechnungslegung (u. a. Konzeption, Anforderungsdefinition, Testing)\nWeiterentwicklung technischer L\u00f6sungen f\u00fcr das Accounting, z. B. durch den Einsatz von Dashboards in BI-Systemen, in enger Abstimmung mit der Abteilungsleitung\nWen suchen wir?\nErfolgreich abgeschlossene kaufm\u00e4nnische Ausbildung im Bereich Buchhaltung idealerweise mit einer einschl\u00e4gigen Weiterbildung zum Bilanzbuchhalter\nMehrj\u00e4hrige Erfahrung im HGB-Accounting, idealerweise erg\u00e4nzt durch erste F\u00fchrungserfahrung sowie Kenntnis der RechKredV\nFundierte Kenntnisse in der Konzernrechnungslegung und Abschlussprozessen\nTechnische Affinit\u00e4t und sicherer Umgang mit MS Excel und idealerweise Erfahrung mit SQL oder BI-Tools zur Unterst\u00fctzung von Reporting- und Analyseprozessen\nAnalytisches Denken, strukturierte Arbeitsweise und Kommunikationsst\u00e4rke in der Zusammenarbeit mit Fachbereichen\nSehr gute Deutsch- sowie Englischkenntnisse in Wort und Schrift\nWas wir Ihnen bieten:\nFlexible Arbeitszeiten innerhalb einer 39-Stunden-Woche\n30 Tage Jahresurlaub sowie zus\u00e4tzliche freie Tage am 24. und 31. Dezember\nVielseitiges und spannendes Aufgabengebiet in einem modernen und dynamischen Umfeld sowie ein wertsch\u00e4tzendes Betriebsklima\nGezielte F\u00f6rderung durch interne und externe Schulungs- und Entwicklungsprogramme\nBerenberg-Patensystem f\u00fcr ein strukturiertes und reibungsloses Onboarding\nVielf\u00e4ltige Zusch\u00fcsse (z. B. Deutschlandticket, JobRad, verm\u00f6genswirksame Leistungen, betriebliche Altersvorsorge, Essenszusch\u00fcsse bzw. Betriebsrestaurant in Hamburg)\nZus\u00e4tzliche Leistungen wie Familienservice, Arbeitszeitkonto (z. B. f\u00fcr Sabbaticals), betriebliche Sozialleistungen, Gesundheits- und Sportprogramme\nBewerben Sie sich jetzt online und werden Sie Teil des Teams \u2013\nwir freuen uns auf Ihre Bewerbung!\nAls eine f\u00fchrende europ\u00e4ische Privatbank mit \u00fcber 430 Jahren Erfahrung blicken wir auf eine lange Unternehmensgeschichte zur\u00fcck. Gleichzeitig gestalten wir mit umfassenden Investitionen aktiv unsere Zukunft. Grundlage f\u00fcr unseren Fortschritt und unsere Weiterentwicklung sind unsere Mitarbeiter. Wir ermutigen diese, neue Ans\u00e4tze auszuprobieren, ihre Ideen mit einzubringen und ihren eigenen Weg zum Erfolg bei uns zu gehen. Wir sind ein ambitioniertes, zukunftsorientiertes Unternehmen, das jahrhundertelange Erfahrung und Innovationskraft vereint.\nBei uns erleben Sie eine Kultur, die zum selbstst\u00e4ndigen Denken anregt, Unternehmertum f\u00f6rdert und dazu ermutigt, den Status quo zu hinterfragen. Wir legen gro\u00dfen Wert auf die Zusammenarbeit vor Ort \u2013 unser B\u00fcro ist ein zentraler Ort des Dialogs, der Innovation und des gemeinsamen Wachstums. Sie treffen hier auf talentierte Kollegen, die es gewohnt sind, Verantwortung zu \u00fcbernehmen, und gemeinsam an einem Strang ziehen, um Ergebnisse zu erzielen.\nWerden Sie Teil von Berenberg und arbeiten Sie mit uns gemeinsam daran, das Richtige f\u00fcr unsere Kunden, unser Gesch\u00e4ft und unsere Mitarbeiter zu tun \u2013\nOur future is where you take us!\nAus organisatorischen Gr\u00fcnden nehmen wir nur Bewerbungen an, die uns \u00fcber unser Online-Bewerbermanagementsystem auf der Website erreichen.\n*Aus Gr\u00fcnden der besseren Lesbarkeit wird auf die gleichzeitige Verwendung mehrgeschlechtlicher Sprachformen verzichtet. S\u00e4mtliche Personenbezeichnungen gelten gleichwohl f\u00fcr jegliches Geschlecht. Bei uns sind alle Bewerbungen willkommen, unabh\u00e4ngig von Geschlecht, Nationalit\u00e4t, ethnischer Herkunft, sozialem Hintergrund, Behinderung, Religion, Alter oder sexueller Orientierung. Bei Fragen wenden Sie sich bitte an unser Recruitment-Team unter recruitment@berenberg.de.\nBack to job list\nApply\nShare this job:\nShare Teamlead* Accounting with a friend via e-mail",
        "application_url": "https://berenberg.avature.net/en_GB/careers/Login?jobId=2697",
        "metadata": {
            "Country": "Germany",
            "City": "Hamburg",
            "Type of role": "Professional",
            "Working time": "Full-time",
            "Type of contract": "Permanent",
            "Remaining openings": "1"
        },
        "link": "https://berenberg.avature.net/en_GB/careers/JobDetail/Teamlead-Accounting/2697"
    },
    {
        "title": null,
        "description_html": null,
        "description_text": "(Senior) ServiceNow Developer*\nGeneral information\nCountry\nGermany\nCity\nHamburg\nType of role\nProfessional\nWorking time\nFull-time\nType of contract\nPermanent\nRemaining openings\n1\nDescription & Requirements\nF\u00fcr unser Programm\nOrganisational Development & Governance\nam\nStandort Hamburg\nsuchen wir zum\nn\u00e4chstm\u00f6glichen Zeitpunkt\ndich als\n(Senior) ServiceNow Developer*\nInnovation & Technology @ Berenberg\nIn einer \u00c4ra, in der Digitalisierung und moderne IT-Infrastrukturen das Banking revolutionieren, gestalten wir eine technologiegest\u00fctzte Bank, in der du als IT-Profi eng mit unseren Gesch\u00e4ftsbereichen zusammenarbeitest. Unsere Technology-Teams bieten dir ein Umfeld, das dich vor spannende Herausforderungen stellt \u2013 sei es durch den Support und die Weiterentwicklung von Legacy-Systemen oder die Einf\u00fchrung moderner Technologien wie KI, Machine Learning und hochgradig automatisierte Handelsapplikationen.\nUnsere IT-Abteilung mit etwa 300 Mitarbeitern arbeitet gr\u00f6\u00dftenteils agil nach einem Scrumban-Ansatz und deckt Bereiche wie Cloud Computing, Cybersecurity, Operations, Process and Governance, Software Development und Architecture ab. Wir sind besonders stolz darauf, fast alle unsere Applikationen Inhouse zu entwickeln, was uns eine einzigartige Flexibilit\u00e4t und Innovationskraft verleiht. Unser Tech Stack umfasst moderne Technologien wie Java, Kotlin, TypeScript und Python, CI/CD-Pipelines, Container, Kubernetes sowie Azure Cloud, Azure SQL Database und Oracle Datenbank mit PL/SQL.\nWelche Aufgaben erwarten Dich?\nGestaltung und Umsetzung intelligenter ServiceNow-L\u00f6sungen mit Schwerpunkt auf ITSM, CSM, ITOM/Discovery (CMDB/CSDM), Workflow-Automatisierung sowie REST-Integrationen (Inbound/Outbound)\nAktive Mitarbeit bei Konzeption, Design und Implementierung neuer Module und Funktionen auf der ServiceNow-Plattform\nAnalyse bestehender Prozesse sowie die Erarbeitung passgenauer, nutzerorientierter L\u00f6sungskonzepte in Zusammenarbeit mit Stakeholdern, Architekt:innen und Entwickler:innen\nEnd-to-End-Begleitung des Entwicklungsprozesses \u2013 von der Feature-Entwicklung \u00fcber Testing und Rollout bis hin zur Dokumentation und Wissensweitergabe\nSicherstellung einer effizienten und nachhaltigen Systemarchitektur unter Ber\u00fccksichtigung aktueller Best Practices und Standards\nWen suchen wir?\nAbgeschlossenes Studium der (Wirtschafts-)Informatik, des Wirtschaftsingenieurwesens oder eine vergleichbare Qualifikation\nMehrj\u00e4hrige Berufserfahrung in der ServiceNow-Entwicklung sowie idealerweise Zertifizierungen wie CSA, CIS ITSM, CIS ITOM/Discovery (CMDB/CSDM), AppEngine, Flow Designer oder Playbooks\nFundiertes Verst\u00e4ndnis von ITSM-, ITOM- und CSM-Prozessen sowie sicherer Umgang mit JavaScript, HTML, CSS und REST/JSON\nKenntnisse im ITIL-Framework sowie Erfahrung in der Arbeit nach agilen Methoden (z. B. Scrum)\nSehr gute Deutschkenntnisse sowie solide Englischkenntnisse in Wort und Schrift\nStrukturierte, l\u00f6sungsorientierte Arbeitsweise sowie Freude an der Zusammenarbeit in interdisziplin\u00e4ren Teams\nWas wir Dir bieten:\nFlexible Arbeitszeiten innerhalb einer 39-Stunden-Woche\n30 Tage Jahresurlaub sowie zus\u00e4tzliche freie Tage am 24. und 31. Dezember\nVielseitiges und spannendes Aufgabengebiet in einem modernen und dynamischen Umfeld sowie ein wertsch\u00e4tzendes Betriebsklima\nGezielte F\u00f6rderung durch interne und externe Schulungs- und Entwicklungsprogramme\nBerenberg-Patensystem f\u00fcr ein strukturiertes und reibungsloses Onboarding\nVielf\u00e4ltige Zusch\u00fcsse (z. B. Deutschlandticket, JobRad, verm\u00f6genswirksame Leistungen, betriebliche Altersvorsorge, Essenszusch\u00fcsse bzw. Betriebsrestaurant in Hamburg)\nZus\u00e4tzliche Leistungen wie Familienservice, Arbeitszeitkonto (z. B. f\u00fcr Sabbaticals), betriebliche Sozialleistungen, Gesundheits- und Sportprogramme\nBewirb dich jetzt online und werde Teil des Teams \u2013\nwir freuen uns auf deine Bewerbung!\nWir sind eine f\u00fchrende europ\u00e4ische Privatbank mit \u00fcber 430 Jahren Erfahrung und einer tief verwurzelten Geschichte, aber wir gestalten und investieren noch immer in Zukunft. Unser Fortschritt und unsere Entwicklung werden von unseren Mitarbeitern vorangetrieben. Wir ermutigen sie, neue Ans\u00e4tze auszuprobieren, ihre Meinung zu \u00e4u\u00dfern und auf ihre eigene Art und Weise erfolgreich zu sein.\nWir bieten ihnen die M\u00f6glichkeit, ihre Talente zu entwickeln, verschiedene Karrierewege zu erkunden und ihr Potenzial voll auszusch\u00f6pfen.\nWir sind ein ehrgeiziges, zukunftsorientiertes Unternehmen, das auf jahrhundertealte Traditionen zur\u00fcckgreift und auf Innovation baut. Du findest bei uns eine Kultur vor, die Menschen dazu ermutigt, unabh\u00e4ngig zu denken, unternehmerisch zu handeln und den Status quo in Frage zu stellen. Wir legen gro\u00dfen Wert auf die Zusammenarbeit vor Ort \u2013 unser B\u00fcro ist ein zentraler Ort des Dialogs, der Innovation und des gemeinsamen Wachstums. Gemeinsam arbeiten wir daran, unser Gesch\u00e4ft zu gestalten und unsere ehrgeizigen Ziele zu erreichen.\nWir freuen uns, wenn du dich uns anschlie\u00dft, um stets das Richtige f\u00fcr unsere Mitarbeiter, Kunden und unser Unternehmen zu tun \u2013\nOur future is where you take us!\nAus organisatorischen Gr\u00fcnden nehmen wir nur Bewerbungen an, die uns \u00fcber unser Online-Bewerbermanagementsystem auf der Website erreichen.\n*Aus Gr\u00fcnden der besseren Lesbarkeit wird auf die gleichzeitige Verwendung mehrgeschlechtlicher Sprachformen verzichtet. S\u00e4mtliche Personenbezeichnungen gelten gleichwohl f\u00fcr jegliches Geschlecht. Bei uns sind alle Bewerber willkommen, unabh\u00e4ngig von Geschlecht, Nationalit\u00e4t, ethnischer Herkunft, sozialem Hintergrund, Behinderung, Religion, Alter oder sexueller Orientierung. Bei Fragen wende dich bitte an unser Recruitment-Team unter recruitment@berenberg.de.\nBack to job list\nApply\nShare this job:\nShare (Senior) ServiceNow Developer* with a friend via e-mail",
        "application_url": "https://berenberg.avature.net/en_GB/careers/Login?jobId=2541",
        "metadata": {
            "Country": "Germany",
            "City": "Hamburg",
            "Type of role": "Professional",
            "Working time": "Full-time",
            "Type of contract": "Permanent",
            "Remaining openings": "1"
        },
        "link": "https://berenberg.avature.net/en_GB/careers/JobDetail/Senior-ServiceNow-Developer/2541"
    },
    {
        "title": null,
        "description_html": null,
        "description_text": "SOC Analyst\nGeneral information\nCountry\nUnited Kingdom\nCity\nLondon\nType of role\nProfessional\nWorking time\nFull-time\nType of contract\nPermanent\nRemaining openings\n1\nDescription & Requirements\nFor our\nInnovation & Technology\ndepartment in\nLondon\nwe are looking to hire a:\nSOC Analyst*\nInnovation & Technology @ Berenberg\nIn an era where digitalisation and modern IT infrastructure is revolutionizing banking, we are shaping a technology-driven bank in which you as an IT professional will work closely with our business units. Our technology teams offer you an environment that will present you with exciting challenges - be it through the support and further development of legacy systems or the introduction of modern technologies such as AI, machine learning and highly automated trading applications.\nYour Role in the team:\nBerenberg, one of Europe\u2019s leading investment banks, is seeking a SOC Analyst to strengthen our award-winning Cyber Security Operations team. With a history spanning more than four centuries, Berenberg has built its reputation on trust, innovation, and resilience. Today, as the financial sector faces increasingly complex cyber threats, our cyber security operations team are recognised across the industry for their excellence in defending against sophisticated adversaries and ensuring operational resilience. Joining this team means becoming part of a function that is not only critical to the bank\u2019s success but also highly respected within the wider cyber security community.\nAs a SOC Analyst, you will play a crucial role in our Cyber Security Operations responsible for managing and mitigating security incidents, performing thorough investigations, and producing detailed reports. This is a pivotal role in enhancing the monitoring and detection capabilities of the bank, ensuring a proactive and resilient security posture. You will also have the opportunity to extend our threat Intelligence capabilities in this role. This position requires an initiative-taking, energetic, and enthusiastic individual with extensive security operations experience in incident response and dealing with security-related topics facing financial services industry. You will be at the forefront of protecting Berenberg\u2019s digital assets, client relationships, and global reputation.\nWhat will you do:\nIncident Response: Lead and coordinate the response to security incident, ensuring timely and effective mitigation of threats\nMonitoring and Analysis: Continuously monitor security alerts from various sources, including SIEM tools, Splunk, IDS/IPS, firewalls, and other security technologies. Analyse and investigate suspicious activities and anomalies\nThreat Intelligence: Stay up to date with the latest threat intelligence and security trends. Apply this knowledge to enhance the organisation's security posture and response capabilities\nCollaboration: Work closely with other teams, such as IT, legal, compliance, governance, and risk management, to ensure a coordinated and effective response to security incidents. Collaborate with the broader Information Security (InfoSec) team to enhance overall security measures\nSecurity Initiatives: Play a significant role in driving innovative security initiatives in the IT organisation\nWho are we looking for?\nExperience: Minimum of 3 - 5 years of experience of working in a SOC role, with a focus on the financial services sector. As well as experience of working in Security Operations team conducting monitoring and detection and triage activities across the wider IT organisation and business. Strong written and verbal communication skills. And the ability to present technical information to non-technical stakeholders in a clear and concise manner\nTechnical Proficiency in SIEM tools with hands on expertise in Splunk and Microsoft Sentinel for log analysis, threat detection, and incident response. Real-world, practical engineering experience with Endpoint Detection and Response (EDR) tools, specifically Microsoft Defender for Endpoint, including deployment, monitoring, and remediation activities. Strong understanding of network protocols (TCP/IP, DNS, HTTP/S, SMTP, etc.) and the ability to analyse traffic patterns to identify anomalies and potential threats\nWorking knowledge of the MITRE ATT&CK framework, with proven ability to map adversary tactics, techniques, and procedures (TTPs) to defensive strategies. Including developing and implementing detection rules, response playbooks, and proactive measures to strengthen organizational resilience against cyber threats\nEducation & Professional Credibility: Degree in Computer Science, Cyber Security, or a related field. Relevant certifications (e.g., GCTI, CTIA, CISSP, CISM, CEH, OSCP) are highly desirable\nCollaboration & Team Ethos - A willingness to integrate into an award winning cyber security operations team, contributing to collective success. They should bring a collaborative spirit, sharing knowledge and supporting colleagues across Cyber Security Operations team and IT organisation\nWhat we offer you:\nPrivate pension plan - 10% of base salary contribution by Berenberg\nGenerous 30 day holiday allowance\nPrivate Health Insurance\nLife Insurance scheme\nFlexible working hours\nEnhanced parental leave policies\nEmployee Assistance Programme offering counselling sessions related to mental health, financial wellbeing and other topics\nApply online now to join our team \u2013\nwe look forward to receiving your application!\nWe are a leading European private bank, with over 430 years of experience and deep rooted history, but we are still shaping and heavily investing in our future. Our progress and evolution are driven by our people. We encourage them to try new approaches, voice their opinions and achieve success in their own way.\nWe provide opportunities for them to develop their talents, explore different career paths and achieve their full potential.\nWe\u2019re an ambitious, forward-looking business, backed by centuries of tradition and built on innovation. You\u2019ll find a culture that encourages people to think independently, act entrepreneurially and challenge the status quo.\nWe place great importance on working on site, as we believe that being together in the office not only fosters creativity and efficiency, but also strengthens networks and builds trusting, collegial relationships. For us, this forms the foundation for productive and successful work. Together we collaborate to shape our business and fulfil our ambitious goals.\nWe welcome you to join us in our commitment to always do the right thing for our people, clients and our business \u2013\nOur future is where you take us!\nWe will only accept applications submitted through our online application management system on the website.\nBerenberg is an Equal Opportunities Employer and prides itself on being a modern, dynamic and internationally orientated organisation. We value the rich diversity, skills and abilities and creative potential that people from differing backgrounds and experiences bring to the workplace. Every employee plays a vital role in providing quality service to all our customers and helping to create and inclusive working environment, where everyone can realise their full potential. We\u2019re committed to finding reasonable accommodations for candidates who require adjustments during our recruiting process. Please contact us directly on recruitment@berenberg.com to discuss.\nBack to job list\nApply\nShare this job:\nShare SOC Analyst with a friend via e-mail",
        "application_url": "https://berenberg.avature.net/en_GB/careers/Login?jobId=2734",
        "metadata": {
            "Country": "United Kingdom",
            "City": "London",
            "Type of role": "Professional",
            "Working time": "Full-time",
            "Type of contract": "Permanent",
            "Remaining openings": "1"
        },
        "link": "https://berenberg.avature.net/en_GB/careers/JobDetail/SOC-Analyst/2734"
    },
    {
        "title": null,
        "description_html": null,
        "description_text": "Auslagerungsmanager*/ Outsourcing Manager*, Hamburg\nGeneral information\nCountry\nGermany\nCity\nHamburg\nType of role\nProfessional\nWorking time\nFull-time\nType of contract\nPermanent\nRemaining openings\n1\nDescription & Requirements\nF\u00fcr unsere Abteilung\nProcurement\nin\nHamburg\noder\nFrankfurt\nsuchen wir\nzum n\u00e4chstm\u00f6glichen Zeitpunkt\ndich als\nAuslagerungsmanager*/ Outsourcing Manager*, Hamburg\nGlobal Technology @ Berenberg\nIn einer \u00c4ra, in der Digitalisierung und moderne IT-Infrastrukturen das Banking revolutionieren, gestalten wir eine technologiegest\u00fctzte Bank, in der du als IT-Profi eng mit unseren Gesch\u00e4ftsbereichen zusammenarbeitest. Unsere Technology-Teams bieten dir ein Umfeld, das dich vor spannende Herausforderungen stellt \u2013 sei es durch den Support und die Weiterentwicklung von Legacy-Systemen oder die Einf\u00fchrung moderner Technologien wie KI, Machine Learning und hochgradig automatisierte Handelsapplikationen.\nUnsere IT-Abteilung mit etwa 300 Mitarbeitern arbeitet gr\u00f6\u00dftenteils agil nach einem Scrumban-Ansatz und deckt Bereiche wie Cloud Computing, Cybersecurity, Operations, Process and Governance, Software Development und Architecture ab. Wir sind besonders stolz darauf, fast alle unsere Applikationen Inhouse zu entwickeln, was uns eine einzigartige Flexibilit\u00e4t und Innovationskraft verleiht. Unser Tech Stack umfasst moderne Technologien wie Java, Kotlin, TypeScript und Python, CI/CD-Pipelines, Container, Kubernetes sowie Azure Cloud, Azure SQL Database und Oracle Datenbank mit PL/SQL.\nDeine Rolle im Team\nDu agierst als zentrale Schnittstelle rund um Auslagerungen und Third-Party-Themen und ber\u00e4tst die Fachbereiche als kompetenter Sparringspartner. Du steuerst den gesamten Vertrags- und Auslagerungsprozess End-to-End \u2013 von der risikoorientierten Pr\u00fcfung bis zum Abschluss \u2013 und treibst die Weiterentwicklung regulatorischer Anforderungen (u. a. MaRisk, DORA) aktiv voran. Zudem verantwortest du Kontrollen, die Pflege der Register sowie die Zusammenarbeit mit internen und externen Pr\u00fcfungsinstanzen entlang der 2nd und 3rd Line of Defence.\nWelche Aufgaben erwarten Dich?\nErster Ansprechpartner und Experte f\u00fcr Auslagerungen sowie Beratung der Fachbereiche\nBegleitung des gesamten Vertragsprozesses von Due Diligence bis Vertragsabschluss\nWeiterentwicklung und Umsetzung regulatorischer Anforderungen (MaRisk, DORA) im Third-Party Risk Management\nDurchf\u00fchrung von Kontrollen und \u00dcberwachungshandlungen sowie Pflege des Auslagerungs- und Informationsregisters\nAnsprechpartner f\u00fcr interne/externe Audits und enge Zusammenarbeit mit 2nd / 3rd Line of Defence\nWen suchen wir?\nAbgeschlossene Bankausbildung, Studium der Wirtschaftswissenschaften bzw. Wirtschaftsinformatik oder juristische Qualifikation\nFundiertes regulatorisches Wissen (MaRisk, DORA) sowie Erfahrung im Audit-Umfeld\nMehrj\u00e4hrige Erfahrung im Outsourcing-Management inkl. Vertragsverhandlungen\nTechnisches Grundverst\u00e4ndnis sowie sehr gute Deutsch- und Englischkenntnisse\nAnalytische, strukturierte und l\u00f6sungsorientierte Arbeitsweise sowie hohe Kommunikationsst\u00e4rke und Teamorientierung\nWas wir Dir bieten:\nFlexible Arbeitszeiten innerhalb einer 39-Stunden-Woche\n30 Tage Jahresurlaub sowie zus\u00e4tzliche freie Tage am 24. und 31. Dezember\nVielseitiges und spannendes Aufgabengebiet in einem modernen und dynamischen Umfeld sowie ein wertsch\u00e4tzendes Betriebsklima\nGezielte F\u00f6rderung durch interne und externe Schulungs- und Entwicklungsprogramme\nBerenberg-Patensystem f\u00fcr ein strukturiertes und reibungsloses Onboarding\nVielf\u00e4ltige Zusch\u00fcsse (z. B. Deutschlandticket, JobRad, verm\u00f6genswirksame Leistungen, betriebliche Altersvorsorge, Essenszusch\u00fcsse bzw. Betriebsrestaurant in Hamburg)\nZus\u00e4tzliche Leistungen wie Familienservice, Arbeitszeitkonto (z. B. f\u00fcr Sabbaticals), betriebliche Sozialleistungen, Gesundheits- und Sportprogramme\nBewirb dich jetzt online und werde Teil des Teams \u2013\nwir freuen uns auf deine Bewerbung!\nWir sind eine f\u00fchrende europ\u00e4ische Privatbank mit \u00fcber 430 Jahren Erfahrung und einer tief verwurzelten Geschichte, aber wir gestalten und investieren noch immer in Zukunft. Unser Fortschritt und unsere Entwicklung werden von unseren Mitarbeitern vorangetrieben. Wir ermutigen sie, neue Ans\u00e4tze auszuprobieren, ihre Meinung zu \u00e4u\u00dfern und auf ihre eigene Art und Weise erfolgreich zu sein.\nWir bieten ihnen die M\u00f6glichkeit, ihre Talente zu entwickeln, verschiedene Karrierewege zu erkunden und ihr Potenzial voll auszusch\u00f6pfen.\nWir sind ein ehrgeiziges, zukunftsorientiertes Unternehmen, das auf jahrhundertealte Traditionen zur\u00fcckgreift und auf Innovation baut. Du findest bei uns eine Kultur vor, die Menschen dazu ermutigt, unabh\u00e4ngig zu denken, unternehmerisch zu handeln und den Status quo in Frage zu stellen. Wir legen gro\u00dfen Wert auf die Zusammenarbeit vor Ort \u2013 unser B\u00fcro ist ein zentraler Ort des Dialogs, der Innovation und des gemeinsamen Wachstums. Gemeinsam arbeiten wir daran, unser Gesch\u00e4ft zu gestalten und unsere ehrgeizigen Ziele zu erreichen.\nWir freuen uns, wenn du dich uns anschlie\u00dft, um stets das Richtige f\u00fcr unsere Mitarbeiter, Kunden und unser Unternehmen zu tun \u2013\nOur future is where you take us!\nAus organisatorischen Gr\u00fcnden nehmen wir nur Bewerbungen an, die uns \u00fcber unser Online-Bewerbermanagementsystem auf der Website erreichen.\n*Aus Gr\u00fcnden der besseren Lesbarkeit wird auf die gleichzeitige Verwendung mehrgeschlechtlicher Sprachformen verzichtet. S\u00e4mtliche Personenbezeichnungen gelten gleichwohl f\u00fcr jegliches Geschlecht. Bei uns sind alle Bewerber willkommen, unabh\u00e4ngig von Geschlecht, Nationalit\u00e4t, ethnischer Herkunft, sozialem Hintergrund, Behinderung, Religion, Alter oder sexueller Orientierung. Bei Fragen wende dich bitte an unser Recruitment-Team unter recruitment@berenberg.de.\nBack to job list\nApply\nShare this job:\nShare Auslagerungsmanager*/ Outsourcing Manager*, Hamburg with a friend via e-mail",
        "application_url": "https://berenberg.avature.net/en_GB/careers/Login?jobId=2737",
        "metadata": {
            "Country": "Germany",
            "City": "Hamburg",
            "Type of role": "Professional",
            "Working time": "Full-time",
            "Type of contract": "Permanent",
            "Remaining openings": "1"
        },
        "link": "https://berenberg.avature.net/en_GB/careers/JobDetail/Auslagerungsmanager-Outsourcing-Manager-Hamburg/2737"
    },
    {
        "title": null,
        "description_html": null,
        "description_text": "(Senior) Kreditanalyst* Akquisitionsfinanzierungen (Marktfolge)\nGeneral information\nCountry\nGermany\nCity\nHamburg\nType of role\nProfessional\nType of contract\nPermanent\nRemaining openings\n1\nDescription & Requirements\nF\u00fcr unsere Abteilung\nCredit Risk Management\nam Standort\nHamburg\nsuchen wir Sie als\n(Senior) Kreditanalyst* Akquisitionsfinanzierungen (Marktfolge)\nIhre Rolle im Team\nIm dynamischen Marktumfeld unserer strukturierten Finanzierungen ist das Credit Risk Management ein zentraler, gesch\u00e4ftskritischer Sparringspartner f\u00fcr Markt, Management und Investoren. Sie agieren in der Marktfolge mit tiefem Einblick in das transaktionsgetriebene Gesch\u00e4ft unserer Bank und begleiten komplexe Akquisitionsfinanzierungen.\nDer Schwerpunkt liegt auf Akquisitions- und Transaktionsfinanzierungen f\u00fcr mittelst\u00e4ndische Unternehmen, h\u00e4ufig im Kontext von LBO-Strukturen unter Beteiligung international agierender Finanzinvestoren. Als erfahrener Kreditanalyst \u00fcbernehmen Sie eine pr\u00e4gende Rolle bei der Risikobeurteilung anspruchsvoller Finanzierungen und bringen Ihre Expertise aktiv in Entscheidungsprozesse ein.\nSie sind Teil eines leistungsstarken Teams im Credit Risk Management, das neben der Kreditbeurteilung von Neuengagements auch die Risikofr\u00fcherkennung (Einzelrisiken, Portfolio- und Markttrends) sowie die (Weiter-)Entwicklung von Risikosystemen und -tools f\u00fcr das globale Kreditportfolio verantwortet.\nWelche Aufgaben erwarten Sie?\nEigenverantwortliche Beurteilung komplexer Kreditrisiken, insbesondere von LBO- Finanzierungen im Rahmen Private-Equity-initiierter Akquisitionen\nEigenst\u00e4ndige Analyse von Gesch\u00e4ftsmodellen, Due-Diligence-Berichten sowie Jahresabschl\u00fcssen zur Beurteilung der wirtschaftlichen Verh\u00e4ltnisse und der Marktposition des Unternehmens\nKritisches Hinterfragen und Plausibilisieren von Finanzmodellen, der Kreditstrukturen sowie der Risiko- und Marktlage des Unternehmens\nErstellung von Beschlussvorlagen und Festlegung des internen Ratings sowie Verantwortung f\u00fcr den korrekten Ablauf der Entscheidungsprozesse innerhalb der vorgegebenen organisatorischen Rahmenbedingungen\nLaufende \u00dcberwachung und Analyse der Performance und der Kreditrisiken von Portfoliounternehmen mit der proaktiven Herangehensweise, die Risiken jederzeit im Rahmen der Kreditrisikostrategie zu optimieren\nWen suchen wir?\nAbgeschlossenes Studium mit (betriebs-)wirtschaftlichem, wirtschaftsrechtlichem oder mathematischem Schwerpunkt bzw. Bankausbildung mit weiterf\u00fchrenden Qualifikationen in positionsrelevanten Schwerpunkten\nEinschl\u00e4gige Berufserfahrung in der Analyse von Unternehmen und Private-Equity-getriebener Transaktionen (LBOs) mit komplexen Finanzierungsstrukturen\nExzellentes Anwenderwissen in MS Office, insbesondere Excel\nSehr gute Deutsch- und Englischkenntnisse in Wort und Schrift\nSelbstst\u00e4ndige, strukturierte und verantwortungsbewusste Arbeitsweise sowie F\u00e4higkeit, auch in anspruchsvollen Transaktionsphasen souver\u00e4n zu agieren\nWas wir Ihnen bieten:\nFlexible Arbeitszeiten innerhalb einer 39-Stunden-Woche\n30 Tage Jahresurlaub sowie zus\u00e4tzliche freie Tage am 24. und 31. Dezember\nVielseitiges und spannendes Aufgabengebiet in einem modernen und dynamischen Umfeld sowie wertsch\u00e4tzendes Betriebsklima\nGezielte F\u00f6rderung durch interne und externe Schulungs- und Entwicklungsprogramme\nBerenberg-Patensystem f\u00fcr ein strukturiertes und reibungsloses Onboarding\nVielf\u00e4ltige Zusch\u00fcsse (z. B. Deutschlandticket, JobRad, verm\u00f6genswirksame Leistungen, betriebliche Altersvorsorge, Essenszusch\u00fcsse bzw. Betriebsrestaurant in Hamburg)\nZus\u00e4tzliche Leistungen wie Familienservice, Arbeitszeitkonto (z. B. f\u00fcr Sabbaticals), betriebliche Sozialleistungen, Gesundheits- und Sportprogramme\nBewerben Sie sich jetzt online und werden Sie Teil des Teams \u2013\nwir freuen uns auf Ihre Bewerbung!\nAls eine f\u00fchrende europ\u00e4ische Privatbank mit \u00fcber 430 Jahren Erfahrung blicken wir auf eine lange Unternehmensgeschichte zur\u00fcck. Gleichzeitig gestalten wir mit umfassenden Investitionen aktiv unsere Zukunft. Grundlage f\u00fcr unseren Fortschritt und unsere Weiterentwicklung sind unsere Mitarbeiter. Wir ermutigen diese, neue Ans\u00e4tze auszuprobieren, ihre Ideen mit einzubringen und ihren eigenen Weg zum Erfolg bei uns zu gehen. Wir sind ein ambitioniertes, zukunftsorientiertes Unternehmen, das jahrhundertelange Erfahrung und Innovationskraft vereint.\nBei uns erleben Sie eine Kultur, die zum selbstst\u00e4ndigen Denken anregt, Unternehmertum f\u00f6rdert und dazu ermutigt, den Status quo zu hinterfragen. Wir legen gro\u00dfen Wert auf die Zusammenarbeit vor Ort \u2013 unser B\u00fcro ist ein zentraler Ort des Dialogs, der Innovation und des gemeinsamen Wachstums. Sie treffen hier auf talentierte Kollegen, die es gewohnt sind, Verantwortung zu \u00fcbernehmen, und gemeinsam an einem Strang ziehen, um Ergebnisse zu erzielen.\nWerden Sie Teil von Berenberg und arbeiten Sie mit uns gemeinsam daran, das Richtige f\u00fcr unsere Kunden, unser Gesch\u00e4ft und unsere Mitarbeiter zu tun \u2013\nOur future is where you take us!\nAus organisatorischen Gr\u00fcnden nehmen wir nur Bewerbungen an, die uns \u00fcber unser Online-Bewerbermanagementsystem auf der Website erreichen.\n*Aus Gr\u00fcnden der besseren Lesbarkeit wird auf die gleichzeitige Verwendung mehrgeschlechtlicher Sprachformen verzichtet. S\u00e4mtliche Personenbezeichnungen gelten gleichwohl f\u00fcr jegliches Geschlecht. Bei uns sind alle Bewerbungen willkommen, unabh\u00e4ngig von Geschlecht, Nationalit\u00e4t, ethnischer Herkunft, sozialem Hintergrund, Behinderung, Religion, Alter oder sexueller Orientierung. Bei Fragen wenden Sie sich bitte an unser Recruitment-Team unter recruitment@berenberg.de.\nBack to job list\nApply\nShare this job:\nShare (Senior) Kreditanalyst* Akquisitionsfinanzierungen (Marktfolge) with a friend via e-mail",
        "application_url": "https://berenberg.avature.net/en_GB/careers/Login?jobId=2736",
        "metadata": {
            "Country": "Germany",
            "City": "Hamburg",
            "Type of role": "Professional",
            "Type of contract": "Permanent",
            "Remaining openings": "1"
        },
        "link": "https://berenberg.avature.net/en_GB/careers/JobDetail/Senior-Kreditanalyst-Akquisitionsfinanzierungen-Marktfolge/2736"
    },
    {
        "title": null,
        "description_html": null,
        "description_text": "Data Engineer* DWH & BI\nGeneral information\nCountry\nGermany\nCity\nHamburg\nType of role\nProfessional\nWorking time\nFull-time\nType of contract\nPermanent\nRemaining openings\n1\nDescription & Requirements\nF\u00fcr unser Programm\nCorporate Banking & Credit Risk Technology\nam\nStandort Hamburg\nsuchen wir zum\nn\u00e4chstm\u00f6glichen Zeitpunkt\ndich als\nData Engineer* DWH & BI\nInnovation & Technology @ Berenberg\nIn einer \u00c4ra, in der Digitalisierung und moderne IT-Infrastrukturen das Banking revolutionieren, gestalten wir eine technologiegest\u00fctzte Bank, in der du als IT-Profi eng mit unseren Gesch\u00e4ftsbereichen zusammenarbeitest. Unsere Technology-Teams bieten dir ein Umfeld, das dich vor spannende Herausforderungen stellt \u2013 sei es durch den Support und die Weiterentwicklung von Legacy-Systemen oder die Einf\u00fchrung moderner Technologien wie KI, Machine Learning und hochgradig automatisierte Handelsapplikationen.\nUnsere IT-Abteilung mit etwa 300 Mitarbeitern arbeitet gr\u00f6\u00dftenteils agil nach einem Scrumban-Ansatz und deckt Bereiche wie Cloud Computing, Cybersecurity, Operations, Process and Governance, Software Development und Architecture ab. Wir sind besonders stolz darauf, fast alle unsere Applikationen Inhouse zu entwickeln, was uns eine einzigartige Flexibilit\u00e4t und Innovationskraft verleiht. Unser Tech Stack umfasst moderne Technologien wie Java, Kotlin, TypeScript und Python, CI/CD-Pipelines, Container, Kubernetes sowie Azure Cloud, Azure SQL Database und Oracle Datenbank mit PL/SQL.\nDeine Rolle im Team\nUnser Team entwickelt und betreut Produkte im Kontext Data Warehouse, Regulatory & (Risk) Controlling sowie Reporting/BI. Als Data Engineer DWH & BI gestaltest du mit uns gemeinsam die Weiterentwicklung des Data Warehouses und der darauf aufbauenden Reporting-Plattform im Bereich Controlling und Meldewesen. Das DWH l\u00e4uft auf einer Oracle-Datenbank und ist nach Data Vault 2.0 modelliert. Die Reporting-Plattform basiert auf QlikView und NPrinting und wird um Qlik Sense erg\u00e4nzt. Lass uns dich \u00fcberzeugen und lerne uns kennen \u2013 wir freuen uns auf dich.\nWelche Aufgaben erwarten Dich?\nEntwicklung von End-to-End Data Pipelines vom Quellsystem \u00fcber das DWH bis ins Qlik-Reporting\nDurchf\u00fchrung technischer Abnahmen sowie Koordination bzw. Unterst\u00fctzung bei User-Acceptance-Tests\nVerantwortung f\u00fcr den t\u00e4glichen Betrieb unseres DWH sowie der abh\u00e4ngigen Tools und Prozesse\nDurchf\u00fchrung fachlicher Datenanalysen und Bearbeitung von Ad-hoc-Anfragen aus dem laufenden Tagesgesch\u00e4ft\nBeratung des Bankfachbereichs und Ableitung von Ma\u00dfnahmen zur Digitalisierung von Analyse- und Reportingprozessen\nEinf\u00fchrung neuer Tools und Prozesse im Rahmen von Projekten\nWen suchen wir?\nHands-on-Erfahrung im Bereich Data Engineering und/oder Business Intelligence, vorzugsweise in agilen Projektorganisationen (z. B. Scrum, Kanban)\nSehr gute SQL-Kenntnisse sowie Erfahrung im Aufbau von ETL-Prozessen und in der Datenmodellierung im Data Warehouse\nHohe Auffassungsgabe und analytische F\u00e4higkeiten, die es dir erm\u00f6glichen, dich in komplexe Datenstrukturen und Transformationen einzuarbeiten (z. B. Bankprodukte, Risikomanagement, aufsichtsrechtliches Meldewesen)\nEine Arbeitsweise, die gepr\u00e4gt ist von Zielorientierung und Pragmatismus; du arbeitest engagiert, selbstbestimmt, strukturiert und zuverl\u00e4ssig im Team\nSehr gute Deutsch- und Englischkenntnisse in Wort und Schrift\nZus\u00e4tzliche Pluspunkte sind:\nKenntnisse in Data Vault 2.0\nWissen zu Prozessen in Banken, insbesondere Regulatorik oder (Risk) Controlling\nWas wir Dir bieten:\nFlexible Arbeitszeiten innerhalb einer 39-Stunden-Woche\n30 Tage Jahresurlaub sowie zus\u00e4tzliche freie Tage am 24. und 31. Dezember\nVielseitiges und spannendes Aufgabengebiet in einem modernen und dynamischen Umfeld sowie ein wertsch\u00e4tzendes Betriebsklima\nGezielte F\u00f6rderung durch interne und externe Schulungs- und Entwicklungsprogramme\nBerenberg-Patensystem f\u00fcr ein strukturiertes und reibungsloses Onboarding\nVielf\u00e4ltige Zusch\u00fcsse (z. B. Deutschlandticket, JobRad, verm\u00f6genswirksame Leistungen, betriebliche Altersvorsorge, Essenszusch\u00fcsse bzw. Betriebsrestaurant in Hamburg)\nZus\u00e4tzliche Leistungen wie Familienservice, Arbeitszeitkonto (z. B. f\u00fcr Sabbaticals), betriebliche Sozialleistungen, Gesundheits- und Sportprogramme\nBewirb dich jetzt online und werde Teil des Teams \u2013\nwir freuen uns auf deine Bewerbung!\nWir sind eine f\u00fchrende europ\u00e4ische Privatbank mit \u00fcber 430 Jahren Erfahrung und einer tief verwurzelten Geschichte, aber wir gestalten und investieren noch immer in Zukunft. Unser Fortschritt und unsere Entwicklung werden von unseren Mitarbeitern vorangetrieben. Wir ermutigen sie, neue Ans\u00e4tze auszuprobieren, ihre Meinung zu \u00e4u\u00dfern und auf ihre eigene Art und Weise erfolgreich zu sein.\nWir bieten ihnen die M\u00f6glichkeit, ihre Talente zu entwickeln, verschiedene Karrierewege zu erkunden und ihr Potenzial voll auszusch\u00f6pfen.\nWir sind ein ehrgeiziges, zukunftsorientiertes Unternehmen, das auf jahrhundertealte Traditionen zur\u00fcckgreift und auf Innovation baut. Du findest bei uns eine Kultur vor, die Menschen dazu ermutigt, unabh\u00e4ngig zu denken, unternehmerisch zu handeln und den Status quo in Frage zu stellen. Wir legen gro\u00dfen Wert auf die Zusammenarbeit vor Ort \u2013 unser B\u00fcro ist ein zentraler Ort des Dialogs, der Innovation und des gemeinsamen Wachstums. Gemeinsam arbeiten wir daran, unser Gesch\u00e4ft zu gestalten und unsere ehrgeizigen Ziele zu erreichen.\nWir freuen uns, wenn du dich uns anschlie\u00dft, um stets das Richtige f\u00fcr unsere Mitarbeiter, Kunden und unser Unternehmen zu tun \u2013\nOur future is where you take us!\nAus organisatorischen Gr\u00fcnden nehmen wir nur Bewerbungen an, die uns \u00fcber unser Online-Bewerbermanagementsystem auf der Website erreichen.\n*Aus Gr\u00fcnden der besseren Lesbarkeit wird auf die gleichzeitige Verwendung mehrgeschlechtlicher Sprachformen verzichtet. S\u00e4mtliche Personenbezeichnungen gelten gleichwohl f\u00fcr jegliches Geschlecht. Bei uns sind alle Bewerber willkommen, unabh\u00e4ngig von Geschlecht, Nationalit\u00e4t, ethnischer Herkunft, sozialem Hintergrund, Behinderung, Religion, Alter oder sexueller Orientierung. Bei Fragen wende dich bitte an unser Recruitment-Team unter recruitment@berenberg.de.\nBack to job list\nApply\nShare this job:\nShare Data Engineer* DWH & BI with a friend via e-mail",
        "application_url": "https://berenberg.avature.net/en_GB/careers/Login?jobId=2729",
        "metadata": {
            "Country": "Germany",
            "City": "Hamburg",
            "Type of role": "Professional",
            "Working time": "Full-time",
            "Type of contract": "Permanent",
            "Remaining openings": "1"
        },
        "link": "https://berenberg.avature.net/en_GB/careers/JobDetail/Data-Engineer-DWH-BI/2729"
    },
    {
        "title": null,
        "description_html": null,
        "description_text": "(Senior) Eink\u00e4ufer* Market Data & Vendor Management\nGeneral information\nCountry\nGermany\nCity\nFrankfurt, Hamburg\nType of role\nProfessional\nWorking time\nFull-time\nType of contract\nPermanent\nRemaining openings\n1\nDescription & Requirements\nF\u00fcr unseren\nBereich Transaction Services Projects, Regulation, Market & Reference Data\nam\nStandort Hamburg\noder\nFrankfurt am Main\nsuchen wir zum\nn\u00e4chstm\u00f6glichen\nZeitpunkt\nSie als\n(Senior) Eink\u00e4ufer* Market Data & Vendor Management\nIhre Rolle im Team\nAls Senior-Eink\u00e4ufer* im Bereich Market & Reference Data \u00fcbernehmen Sie eine zentrale Rolle bei der Steuerung und Optimierung sowohl der Datennutzung als auch Datenanbieter-Beziehungen. In enger Zusammenarbeit mit verschiedenen Fachbereichen in der gesamten Bank sind Sie Ansprechpartner f\u00fcr Datenbed\u00fcrfnisse, Vertrags-fragen und Kostenanalysen der Finanzdaten.\nWelche Aufgaben erwarten Sie?\nZentrale Anlaufstelle f\u00fcr interne Stakeholder in allen Belangen rund um Markt- und Referenzdaten\nAnalyse der Datenbed\u00fcrfnisse mit den Fachbereichen\nVerantwortung f\u00fcr Vertragsgestaltung und -verhandlungen\nAnalyse und Pr\u00fcfung bestehender Vertr\u00e4ge hinsichtlich Aktualit\u00e4t, Wirtschaftlichkeit und Einhaltung der vertraglichen Nutzungsbestimmungen\nLaufende Betreuung sowie Auf- und Ausbau der Beziehungen zu internationalen Datenanbietern (Bloomberg, Deutsche B\u00f6rse, Indexdaten-Anbieter etc.)\nWeiterentwicklung bestehender Prozesse mit Fokus auf Automatisierung, Standardisierung und den Einsatz von KI \u2013 aktive Mitgestaltung und Einbringung eigener Ideen\nErstellung aussagekr\u00e4ftiger Reports f\u00fcr das Management\nWen suchen wir?\nErfolgreich abgeschlossenes Studium mit wirtschaftswissenschaftlichem Schwerpunkt oder vergleich-bare Qualifikation mit Fokus auf Finanzm\u00e4rkten\nEinschl\u00e4gige Berufserfahrung im Bankwesen oder im Vertrags- und Lizenzmanagement\nSichere Kommunikation mit internen Stakeholdern und externen Partnern \u2013 auf Deutsch wie auf Eng-lisch\nIdealerweise Erfahrung im Projektmanagement oder in der Prozessoptimierung\nBereitschaft zu gelegentlichen Dienstreisen\nWas wir Ihnen bieten:\nFlexible Arbeitszeiten innerhalb einer 39-Stunden-Woche\n30 Tage Jahresurlaub\nVielseitiges und spannendes Aufgabengebiet in einem modernen und dynamischen Umfeld sowie wertsch\u00e4tzendes Betriebsklima\nGezielte F\u00f6rderung durch interne und externe Schulungs- und Entwicklungsprogramme\nBerenberg-Patensystem f\u00fcr ein strukturiertes und reibungsloses Onboarding\nVielf\u00e4ltige Zusch\u00fcsse (z. B. Deutschlandticket, JobRad, verm\u00f6genswirksame Leistungen, betriebliche Altersvorsorge, Betriebsrestaurant/Essenszusch\u00fcsse)\nZus\u00e4tzliche Leistungen wie Familienservice, Arbeitszeitkonto (z. B. f\u00fcr Sabbaticals), betriebliche Sozialleistungen, Gesundheits- und Sportprogramme\nBewerben Sie sich jetzt online und werden Sie Teil des Teams \u2013\nwir freuen uns auf Ihre Bewerbung!\nAls eine f\u00fchrende europ\u00e4ische Privatbank mit \u00fcber 430 Jahren Erfahrung blicken wir auf eine lange Unternehmensgeschichte zur\u00fcck. Gleichzeitig gestalten wir mit umfassenden Investitionen aktiv unsere Zukunft. Grundlage f\u00fcr unseren Fortschritt und unsere Weiterentwicklung sind unsere Mitarbeiter. Wir ermutigen diese, neue Ans\u00e4tze auszuprobieren, ihre Ideen mit einzubringen und ihren eigenen Weg zum Erfolg bei uns zu gehen. Wir sind ein ambitioniertes, zukunftsorientiertes Unternehmen, das jahrhundertelange Erfahrung und Innovationskraft vereint.\nBei uns erleben Sie eine Kultur, die zum selbstst\u00e4ndigen Denken anregt, Unternehmertum f\u00f6rdert und dazu ermutigt, den Status quo zu hinterfragen. Wir legen gro\u00dfen Wert auf die Zusammenarbeit vor Ort \u2013 unser B\u00fcro ist ein zentraler Ort des Dialogs, der Innovation und des gemeinsamen Wachstums. Sie treffen hier auf talentierte Kollegen, die es gewohnt sind, Verantwortung zu \u00fcbernehmen, und gemeinsam an einem Strang ziehen, um Ergebnisse zu erzielen.\nWerden Sie Teil von Berenberg und arbeiten Sie mit uns gemeinsam daran, das Richtige f\u00fcr unsere Kunden, unser Gesch\u00e4ft und unsere Mitarbeiter zu tun \u2013\nOur future is where you take us!\nAus organisatorischen Gr\u00fcnden nehmen wir nur Bewerbungen an, die uns \u00fcber unser Online-Bewerbermanagementsystem auf der Website erreichen.\n*Aus Gr\u00fcnden der besseren Lesbarkeit wird auf die gleichzeitige Verwendung mehrgeschlechtlicher Sprachformen verzichtet. S\u00e4mtliche Personenbezeichnungen gelten gleichwohl f\u00fcr jegliches Geschlecht. Bei uns sind alle Bewerbungen willkommen, unabh\u00e4ngig von Geschlecht, Nationalit\u00e4t, ethnischer Herkunft, sozialem Hintergrund, Behinderung, Religion, Alter oder sexueller Orientierung. Bei Fragen wenden Sie sich bitte an unser Recruitment-Team unter recruitment@berenberg.de.\nBack to job list\nApply\nShare this job:\nShare (Senior) Eink\u00e4ufer* Market Data & Vendor Management with a friend via e-mail",
        "application_url": "https://berenberg.avature.net/en_GB/careers/Login?jobId=2676",
        "metadata": {
            "Country": "Germany",
            "City": "Frankfurt, Hamburg",
            "Type of role": "Professional",
            "Working time": "Full-time",
            "Type of contract": "Permanent",
            "Remaining openings": "1"
        },
        "link": "https://berenberg.avature.net/en_GB/careers/JobDetail/Senior-Eink-ufer-Market-Data-Vendor-Management/2676"
    },
    {
        "title": null,
        "description_html": null,
        "description_text": "Full Stack Software Developer / Softwareentwickler * - Core Banking\nGeneral information\nCountry\nGermany\nCity\nHamburg\nType of role\nProfessional\nWorking time\nFull-time\nType of contract\nPermanent\nRemaining openings\n4\nDescription & Requirements\nF\u00fcr unser Programm\nCorporate Banking & Credit Risk Technology\nam\nStandort Hamburg\nsuchen wir zum\nn\u00e4chstm\u00f6glichen Zeitpunkt\ndich als\nFull Stack Software Developer / Softwareentwickler* - Core Banking\nInnovation & Technology @ Berenberg.\nIn einer \u00c4ra, in der Digitalisierung und moderne IT-Infrastrukturen das Banking revolutionieren, gestalten wir eine technologiegest\u00fctzte Bank, in der du als IT-Profi eng mit unseren Gesch\u00e4ftsbereichen zusammenarbeitest. Unsere Technology-Teams bieten dir ein Umfeld, das dich vor spannende Herausforderungen stellt \u2013 sei es durch den Support und die Weiterentwicklung von Legacy-Systemen oder die Einf\u00fchrung moderner Technologien wie KI, Machine Learning und hochgradig automatisierte Handelsapplikationen.\nUnsere IT-Abteilung mit etwa 300 Mitarbeitern arbeitet gr\u00f6\u00dftenteils agil nach einem Scrumban-Ansatz und deckt Bereiche wie Cloud Computing, Cybersecurity, Operations, Process and Governance, Software Development und Architecture ab. Wir sind besonders stolz darauf, fast alle unsere Applikationen Inhouse zu entwickeln, was uns eine einzigartige Flexibilit\u00e4t und Innovationskraft verleiht. Unser Tech Stack umfasst moderne Technologien wie Java, Kotlin, TypeScript und Python, CI/CD-Pipelines, Container, Kubernetes sowie Azure Cloud, Azure SQL Database und Oracle Datenbank mit PL/SQL.\nWelche Aufgaben erwarten Dich?\nFull-Stack-Entwicklung sowie eigenverantwortliches Arbeiten in einem neu aufgebauten, leistungsstarken und agilen Team\nMitwirkung an der Neuentwicklung unseres Core-Banking-Systems \u2013 als zentraler Bestandteil des Teams gestaltest du die technologische Zukunft unserer Bank von Grund auf mit\nVerantwortung f\u00fcr Codequalit\u00e4t, Skalierbarkeit und Performance der entwickelten Services und Komponenten\nAktive Mitgestaltung der technischen Roadmap sowie kontinuierliche Einarbeitung in neue Technologien und Tools, um dein Team und die gesamte IT-Organisation voranzubringen\nWen suchen wir?\nErfolgreich abgeschlossene Ausbildung zum Fachinformatiker f\u00fcr Anwendungsentwicklung oder Studium der (Wirtschafts-)Informatik bzw. eine vergleichbare Qualifikation\nSehr gute Kenntnisse in Java/Kotlin, Erfahrung mit Spring Boot und RESTful Services\nSicherer Umgang mit TypeScript/JavaScript, HTML5 und CSS sowie Erfahrung mit Angular oder einem vergleichbaren modernen Frontend-Framework\nPraxiswissen in Docker, Kubernetes und CI/CD-Pipelines; idealerweise Erfahrung mit Microsoft Azure Cloud und MS SQL\nStrukturierte, qualit\u00e4tsbewusste und selbstst\u00e4ndige Arbeitsweise; Erfahrung im agilen Umfeld (Scrumban) und Interesse an neuen Technologien (z. B. KI, Machine Learning)\nVerst\u00e4ndnis f\u00fcr bankfachliche Kernprozesse von Vorteil; sehr gute Deutsch- und Englischkenntnisse in Wort und Schrift\nWas wir Dir bieten:\nFlexible Arbeitszeiten innerhalb einer 39-Stunden-Woche\n30 Tage Jahresurlaub sowie zus\u00e4tzliche freie Tage am 24. und 31. Dezember\nVielseitiges und spannendes Aufgabengebiet in einem modernen und dynamischen Umfeld sowie ein wertsch\u00e4tzendes Betriebsklima\nGezielte F\u00f6rderung durch interne und externe Schulungs- und Entwicklungsprogramme\nBerenberg-Patensystem f\u00fcr ein strukturiertes und reibungsloses Onboarding\nVielf\u00e4ltige Zusch\u00fcsse (z. B. Deutschlandticket, JobRad, verm\u00f6genswirksame Leistungen, betriebliche Altersvorsorge, Essenszusch\u00fcsse bzw. Betriebsrestaurant in Hamburg)\nZus\u00e4tzliche Leistungen wie Familienservice, Arbeitszeitkonto (z. B. f\u00fcr Sabbaticals), betriebliche Sozialleistungen, Gesundheits- und Sportprogramme\nBewirb dich jetzt online und werde Teil des Teams \u2013\nwir freuen uns auf deine Bewerbung!\nWir sind eine f\u00fchrende europ\u00e4ische Privatbank mit \u00fcber 430 Jahren Erfahrung und einer tief verwurzelten Geschichte, aber wir gestalten und investieren noch immer in Zukunft. Unser Fortschritt und unsere Entwicklung werden von unseren Mitarbeitern vorangetrieben. Wir ermutigen sie, neue Ans\u00e4tze auszuprobieren, ihre Meinung zu \u00e4u\u00dfern und auf ihre eigene Art und Weise erfolgreich zu sein.\nWir bieten ihnen die M\u00f6glichkeit, ihre Talente zu entwickeln, verschiedene Karrierewege zu erkunden und ihr Potenzial voll auszusch\u00f6pfen.\nWir sind ein ehrgeiziges, zukunftsorientiertes Unternehmen, das auf jahrhundertealte Traditionen zur\u00fcckgreift und auf Innovation baut. Du findest bei uns eine Kultur vor, die Menschen dazu ermutigt, unabh\u00e4ngig zu denken, unternehmerisch zu handeln und den Status quo in Frage zu stellen. Wir legen gro\u00dfen Wert auf die Zusammenarbeit vor Ort \u2013 unser B\u00fcro ist ein zentraler Ort des Dialogs, der Innovation und des gemeinsamen Wachstums. Gemeinsam arbeiten wir daran, unser Gesch\u00e4ft zu gestalten und unsere ehrgeizigen Ziele zu erreichen.\nWir freuen uns, wenn du dich uns anschlie\u00dft, um stets das Richtige f\u00fcr unsere Mitarbeiter, Kunden und unser Unternehmen zu tun \u2013\nOur future is where you take us!\nAus organisatorischen Gr\u00fcnden nehmen wir nur Bewerbungen an, die uns \u00fcber unser Online-Bewerbermanagementsystem auf der Website erreichen.\n*Aus Gr\u00fcnden der besseren Lesbarkeit wird auf die gleichzeitige Verwendung mehrgeschlechtlicher Sprachformen verzichtet. S\u00e4mtliche Personenbezeichnungen gelten gleichwohl f\u00fcr jegliches Geschlecht. Bei uns sind alle Bewerber willkommen, unabh\u00e4ngig von Geschlecht, Nationalit\u00e4t, ethnischer Herkunft, sozialem Hintergrund, Behinderung, Religion, Alter oder sexueller Orientierung. Bei Fragen wende dich bitte an unser Recruitment-Team unter recruitment@berenberg.de.\nBack to job list\nApply\nShare this job:\nShare Full Stack Software Developer / Softwareentwickler * - Core Banking with a friend via e-mail",
        "application_url": "https://berenberg.avature.net/en_GB/careers/Login?jobId=2720",
        "metadata": {
            "Country": "Germany",
            "City": "Hamburg",
            "Type of role": "Professional",
            "Working time": "Full-time",
            "Type of contract": "Permanent",
            "Remaining openings": "4"
        },
        "link": "https://berenberg.avature.net/en_GB/careers/JobDetail/Full-Stack-Software-Developer-Softwareentwickler-Core-Banking/2720"
    },
    {
        "title": null,
        "description_html": null,
        "description_text": "(Senior) Spezialist* Wertpapierabwicklung\nGeneral information\nCountry\nGermany\nCity\nHamburg\nType of role\nProfessional\nWorking time\nFull-time\nType of contract\nPermanent\nRemaining openings\n1\nDescription & Requirements\nF\u00fcr unseren\nBereich TS Corporate Actions and Custody Services\nin\nHamburg\nsuchen wir zum\nn\u00e4chstm\u00f6glichen Zeitpunkt\nSie als\n(Senior) Spezialist* Wertpapierabwicklung\nIhre Rolle im Team\nUnser vierk\u00f6pfiges Backoffice-Team sucht ab sofort Ihre unbefristete Unterst\u00fctzung. Wir spielen eine entscheidende Rolle bei der Abwicklung von Kapitalma\u00dfnahmen und R\u00fcckzahlungen, bieten Services rund um Hauptversammlungen an und \u00fcbernehmen die physische Bearbeitung von Schuldscheindarlehen. Dazu sind wir stets in engem Austausch mit zahlreichen Teams im Haus und unseren Lagerstellen.\nNur der Wandel ist best\u00e4ndig - daher optimieren und automatisieren wir stets unsere teaminternen Prozesse und Systeme und bleiben durch Fortbildungen auf der H\u00f6he der Zeit.\nIhre Aufgaben:\n\u00dcberwachung, Analyse und Bearbeitung s\u00e4mtlicher in- und ausl\u00e4ndischer Kapitalma\u00dfnahmen \u2013 von der Informationsauswertung bis zur Abrechnung und Buchung\nEigenst\u00e4ndige Identifikation und Umsetzung von Prozessoptimierungen sowie Weiterentwicklung der eingesetzten Systeme\nSicherstellung der Einhaltung neuer gesetzlicher und regulatorischer Anforderungen im Bereich Wertpapierabwicklung\nFachgerechte Bearbeitung und Verwaltung von Schuldscheinurkunden sowie zugeh\u00f6riger Dokumentationen\nEnge Zusammenarbeit und Abstimmung mit internen Fachbereichen, Lagerstellen und externen Partnern\nIhr Profil:\nErfolgreich abgeschlossene bankbezogene Ausbildung oder wirtschaftswissenschaftliches Studium\nMehrj\u00e4hrige relevante Berufserfahrung in der Wertpapierabwicklung oder im Kapitalmarktumfeld\nAusgepr\u00e4gte Serviceorientierung, Verantwortungsbewusstsein und Eigeninitiative zur Prozessverbesserung\nSehr gute Deutsch- und Englischkenntnisse in Wort und Schrift sowie sicherer Umgang mit MS Office\nAufgeschlossenheit gegen\u00fcber neuen Technologien und Interesse an der kontinuierlichen Weiterentwicklung interner Systeme\nWas wir Ihnen bieten:\nFlexible Arbeitszeiten innerhalb einer 39-Stunden-Woche\n30 Tage Jahresurlaub sowie zus\u00e4tzliche freie Tage am 24. und 31. Dezember\nVielseitiges und spannendes Aufgabengebiet in einem modernen und dynamischen Umfeld sowie wertsch\u00e4tzendes Betriebsklima\nGezielte F\u00f6rderung durch interne und externe Schulungs- und Entwicklungsprogramme\nBerenberg-Patensystem f\u00fcr ein strukturiertes und reibungsloses Onboarding\nVielf\u00e4ltige Zusch\u00fcsse (z. B. Deutschlandticket, JobRad, verm\u00f6genswirksame Leistungen, betriebliche Altersvorsorge, Essenszusch\u00fcsse bzw. Betriebsrestaurant in Hamburg)\nZus\u00e4tzliche Leistungen wie Familienservice, Arbeitszeitkonto (z. B. f\u00fcr Sabbaticals), betriebliche Sozialleistungen, Gesundheits- und Sportprogramme\nBewerben Sie sich jetzt online und werden Sie Teil des Teams \u2013\nwir freuen uns auf Ihre Bewerbung!\nAls eine f\u00fchrende europ\u00e4ische Privatbank mit \u00fcber 430 Jahren Erfahrung blicken wir auf eine lange Unternehmensgeschichte zur\u00fcck. Gleichzeitig gestalten wir mit umfassenden Investitionen aktiv unsere Zukunft. Grundlage f\u00fcr unseren Fortschritt und unsere Weiterentwicklung sind unsere Mitarbeiter. Wir ermutigen diese, neue Ans\u00e4tze auszuprobieren, ihre Ideen mit einzubringen und ihren eigenen Weg zum Erfolg bei uns zu gehen. Wir sind ein ambitioniertes, zukunftsorientiertes Unternehmen, das jahrhundertelange Erfahrung und Innovationskraft vereint.\nBei uns erleben Sie eine Kultur, die zum selbstst\u00e4ndigen Denken anregt, Unternehmertum f\u00f6rdert und dazu ermutigt, den Status quo zu hinterfragen. Wir legen gro\u00dfen Wert auf die Zusammenarbeit vor Ort \u2013 unser B\u00fcro ist ein zentraler Ort des Dialogs, der Innovation und des gemeinsamen Wachstums. Sie treffen hier auf talentierte Kollegen, die es gewohnt sind, Verantwortung zu \u00fcbernehmen, und gemeinsam an einem Strang ziehen, um Ergebnisse zu erzielen.\nWerden Sie Teil von Berenberg und arbeiten Sie mit uns gemeinsam daran, das Richtige f\u00fcr unsere Kunden, unser Gesch\u00e4ft und unsere Mitarbeiter zu tun \u2013\nOur future is where you take us!\nAus organisatorischen Gr\u00fcnden nehmen wir nur Bewerbungen an, die uns \u00fcber unser Online-Bewerbermanagementsystem auf der Website erreichen.\n*Aus Gr\u00fcnden der besseren Lesbarkeit wird auf die gleichzeitige Verwendung mehrgeschlechtlicher Sprachformen verzichtet. S\u00e4mtliche Personenbezeichnungen gelten gleichwohl f\u00fcr jegliches Geschlecht. Bei uns sind alle Bewerbungen willkommen, unabh\u00e4ngig von Geschlecht, Nationalit\u00e4t, ethnischer Herkunft, sozialem Hintergrund, Behinderung, Religion, Alter oder sexueller Orientierung. Bei Fragen wenden Sie sich bitte an unser Recruitment-Team unter recruitment@berenberg.de.\nBack to job list\nApply\nShare this job:\nShare (Senior) Spezialist* Wertpapierabwicklung with a friend via e-mail",
        "application_url": "https://berenberg.avature.net/en_GB/careers/Login?jobId=2714",
        "metadata": {
            "Country": "Germany",
            "City": "Hamburg",
            "Type of role": "Professional",
            "Working time": "Full-time",
            "Type of contract": "Permanent",
            "Remaining openings": "1"
        },
        "link": "https://berenberg.avature.net/en_GB/careers/JobDetail/Senior-Spezialist-Wertpapierabwicklung/2714"
    },
    {
        "title": null,
        "description_html": null,
        "description_text": "(Junior) Spezialist* Wertpapierabwicklung\nGeneral information\nCountry\nGermany\nCity\nHamburg\nType of role\nProfessional\nWorking time\nFull-time\nType of contract\nPermanent\nRemaining openings\n1\nDescription & Requirements\nF\u00fcr unseren\nBereich TS Corporate Actions and Custody Services\nin\nHamburg\nsuchen wir zum\nn\u00e4chstm\u00f6glichen Zeitpunkt\nSie als\n(Junior) Spezialist* Wertpapierabwicklung\nIhre Rolle im Team\nUnser vierk\u00f6pfiges Backoffice-Team sucht ab sofort Ihre unbefristete Unterst\u00fctzung. Wir spielen eine entscheidende Rolle bei der Abwicklung von Kapitalma\u00dfnahmen und R\u00fcckzahlungen, bieten Services rund um Hauptversammlungen an und \u00fcbernehmen die physische Bearbeitung von Schuldscheindarlehen. Dazu sind wir stets in engem Austausch mit zahlreichen Teams im Haus und unseren Lagerstellen.\nNur der Wandel ist best\u00e4ndig - daher optimieren und automatisieren wir stets unsere teaminternen Prozesse und Systeme und bleiben durch Fortbildungen auf der H\u00f6he der Zeit.\nIhre Aufgaben:\n\u00dcberwachung, Analyse und Bearbeitung s\u00e4mtlicher in- und ausl\u00e4ndischer Kapitalma\u00dfnahmen \u2013 von der Informationsauswertung bis zur Abrechnung und Buchung\nEigenst\u00e4ndige Identifikation und Umsetzung von Prozessoptimierungen sowie Weiterentwicklung der eingesetzten Systeme\nSicherstellung der Einhaltung neuer gesetzlicher und regulatorischer Anforderungen im Bereich Wertpapierabwicklung\nFachgerechte Bearbeitung und Verwaltung von Schuldscheinurkunden sowie zugeh\u00f6riger Dokumentationen\nEnge Zusammenarbeit und Abstimmung mit internen Fachbereichen, Lagerstellen und externen Partnern\nIhr Profil:\nErfolgreich abgeschlossene bankbezogene Ausbildung oder wirtschaftswissenschaftliches Studium\nErste Berufserfahrung in der Wertpapierabwicklung oder im Kapitalmarktumfeld w\u00fcnschenswert\nAusgepr\u00e4gte Serviceorientierung, Verantwortungsbewusstsein und Eigeninitiative zur Prozessverbesserung\nSehr gute Deutsch- und Englischkenntnisse in Wort und Schrift sowie sicherer Umgang mit MS Office\nAufgeschlossenheit gegen\u00fcber neuen Technologien und Interesse an der kontinuierlichen Weiterentwicklung interner Systeme\nWas wir Ihnen bieten:\nFlexible Arbeitszeiten innerhalb einer 39-Stunden-Woche\n30 Tage Jahresurlaub sowie zus\u00e4tzliche freie Tage am 24. und 31. Dezember\nVielseitiges und spannendes Aufgabengebiet in einem modernen und dynamischen Umfeld sowie wertsch\u00e4tzendes Betriebsklima\nGezielte F\u00f6rderung durch interne und externe Schulungs- und Entwicklungsprogramme\nBerenberg-Patensystem f\u00fcr ein strukturiertes und reibungsloses Onboarding\nVielf\u00e4ltige Zusch\u00fcsse (z. B. Deutschlandticket, JobRad, verm\u00f6genswirksame Leistungen, betriebliche Altersvorsorge, Essenszusch\u00fcsse bzw. Betriebsrestaurant in Hamburg)\nZus\u00e4tzliche Leistungen wie Familienservice, Arbeitszeitkonto (z. B. f\u00fcr Sabbaticals), betriebliche Sozialleistungen, Gesundheits- und Sportprogramme\nBewerben Sie sich jetzt online und werden Sie Teil des Teams \u2013\nwir freuen uns auf Ihre Bewerbung!\nAls eine f\u00fchrende europ\u00e4ische Privatbank mit \u00fcber 430 Jahren Erfahrung blicken wir auf eine lange Unternehmensgeschichte zur\u00fcck. Gleichzeitig gestalten wir mit umfassenden Investitionen aktiv unsere Zukunft. Grundlage f\u00fcr unseren Fortschritt und unsere Weiterentwicklung sind unsere Mitarbeiter. Wir ermutigen diese, neue Ans\u00e4tze auszuprobieren, ihre Ideen mit einzubringen und ihren eigenen Weg zum Erfolg bei uns zu gehen. Wir sind ein ambitioniertes, zukunftsorientiertes Unternehmen, das jahrhundertelange Erfahrung und Innovationskraft vereint.\nBei uns erleben Sie eine Kultur, die zum selbstst\u00e4ndigen Denken anregt, Unternehmertum f\u00f6rdert und dazu ermutigt, den Status quo zu hinterfragen. Wir legen gro\u00dfen Wert auf die Zusammenarbeit vor Ort \u2013 unser B\u00fcro ist ein zentraler Ort des Dialogs, der Innovation und des gemeinsamen Wachstums. Sie treffen hier auf talentierte Kollegen, die es gewohnt sind, Verantwortung zu \u00fcbernehmen, und gemeinsam an einem Strang ziehen, um Ergebnisse zu erzielen.\nWerden Sie Teil von Berenberg und arbeiten Sie mit uns gemeinsam daran, das Richtige f\u00fcr unsere Kunden, unser Gesch\u00e4ft und unsere Mitarbeiter zu tun \u2013\nOur future is where you take us!\nAus organisatorischen Gr\u00fcnden nehmen wir nur Bewerbungen an, die uns \u00fcber unser Online-Bewerbermanagementsystem auf der Website erreichen.\n*Aus Gr\u00fcnden der besseren Lesbarkeit wird auf die gleichzeitige Verwendung mehrgeschlechtlicher Sprachformen verzichtet. S\u00e4mtliche Personenbezeichnungen gelten gleichwohl f\u00fcr jegliches Geschlecht. Bei uns sind alle Bewerbungen willkommen, unabh\u00e4ngig von Geschlecht, Nationalit\u00e4t, ethnischer Herkunft, sozialem Hintergrund, Behinderung, Religion, Alter oder sexueller Orientierung. Bei Fragen wenden Sie sich bitte an unser Recruitment-Team unter recruitment@berenberg.de.\nBack to job list\nApply\nShare this job:\nShare (Junior) Spezialist* Wertpapierabwicklung with a friend via e-mail",
        "application_url": "https://berenberg.avature.net/en_GB/careers/Login?jobId=2722",
        "metadata": {
            "Country": "Germany",
            "City": "Hamburg",
            "Type of role": "Professional",
            "Working time": "Full-time",
            "Type of contract": "Permanent",
            "Remaining openings": "1"
        },
        "link": "https://berenberg.avature.net/en_GB/careers/JobDetail/Junior-Spezialist-Wertpapierabwicklung/2722"
    },
    {
        "title": null,
        "description_html": null,
        "description_text": "Experte* in Kapitalmarktprozesse und -abwicklung\nGeneral information\nCountry\nGermany\nCity\nFrankfurt, Hamburg\nType of role\nProfessional\nWorking time\nFull-time\nType of contract\nPermanent\nDescription & Requirements\nF\u00fcr unseren\nBereich Transaction Services Capital Markets and Custody\nServices am\nStandort Hamburg / Frankfurt am Main\nsuchen wir zum\nn\u00e4chstm\u00f6glichen Zeitpunkt\nSie als\nExperte* in Kapitalmarktprozesse und -abwicklung\nIhre Rolle im Team\nZur Verst\u00e4rkung unseres Capital Markets Services Teams suchen wir zum n\u00e4chstm\u00f6glichen Zeitpunkt einen Spezialisten, der das wachsende und erfolgreiche Equity/Debt Capital Markets Gesch\u00e4ft von Berenberg am europ\u00e4ischen Markt unterst\u00fctzt. Das Capital Markets Services Team hat sich kontinuierlich einen sehr guten Ruf am Markt aufgebaut und war in den letzten Jahren ma\u00dfgeblich an Berenbergs Erfolg bei der Abwicklung von Kapitalmarkttransaktionen beteiligt.\nWelche Aufgaben erwarten Sie?\nAntrags-/Zulassungsverfahren f\u00fcr Transaktionen am Prim\u00e4rmarkt mit Schwerpunkt auf dem deutschen Markt, aber auch in anderen L\u00e4ndern wie beispielsweise der Schweiz, Belgien, Niederlande etc.\nDokumentation und technische Durchf\u00fchrung von Kapitalmarkttransaktionen wie B\u00f6rseng\u00e4nge, Kapitalerh\u00f6hungen, \u00f6ffentliche \u00dcbernahmen, Aktienr\u00fcckk\u00e4ufe, Aktiendividenden, Sekund\u00e4rmarkt-Platzierungen und Anleiheemissionen\nKontrolle und Unterst\u00fctzung beim Clearing, Settlement und Payments im Zusammenhang mit den jeweiligen Transaktionen\nBeitrag zur laufenden Effizienz- und Prozessentwicklung des Capital Markets Services Teams\nVertrauensvolle Zusammenarbeit mit Kollegen aus diversen Bereichen, insbesondere dem Investment Banking, um das bestm\u00f6gliche Ergebnis f\u00fcr den Kunden zu gew\u00e4hrleisten\nBeitrag zur kontinuierlichen Entwicklung des Teams\nWen suchen wir?\nEinschl\u00e4gige Transaktionserfahrung auf dem deutschen Markt und anderen kontinentaleurop\u00e4ischen M\u00e4rkten, mit fundierten Kenntnissen in den Bereichen Zulassung, Kapitalma\u00dfnahmen, Global Custody, Payments und Settlement\nSehr gute Deutsch- und Englischkenntnisse in Wort und Schrift, Franz\u00f6sischkenntnisse sind von Vorteil\nF\u00e4higkeit zur effektiven Zusammenarbeit mit internen und externen Beteiligten (z. B. B\u00f6rse, Zentralverwahrer, Konsortialbanken usw.)\nProblemorientiertes Denken und l\u00f6sungsorientierter Arbeitsstil mit einem sehr hohen Ma\u00df an Genauigkeit und Aufmerksamkeit f\u00fcrs Detail\nHervorragende organisatorische F\u00e4higkeiten, um sicherzustellen, dass Aufgaben/Projekte erfolgreich innerhalb der entsprechenden Fristen bearbeitet werden\nWas wir Ihnen bieten:\nFlexible Arbeitszeiten innerhalb einer 39-Stunden-Woche\n30 Tage Jahresurlaub sowie zus\u00e4tzliche freie Tage am 24. und 31. Dezember\nVielseitiges und spannendes Aufgabengebiet in einem modernen und dynamischen Umfeld sowie wertsch\u00e4tzendes Betriebsklima\nGezielte F\u00f6rderung durch interne und externe Schulungs- und Entwicklungsprogramme\nBerenberg-Patensystem f\u00fcr ein strukturiertes und reibungsloses Onboarding\nVielf\u00e4ltige Zusch\u00fcsse (z. B. Deutschlandticket, JobRad, verm\u00f6genswirksame Leistungen, betriebliche Altersvorsorge, Essenszusch\u00fcsse bzw. Betriebsrestaurant in Hamburg)\nZus\u00e4tzliche Leistungen wie Familienservice, Arbeitszeitkonto (z. B. f\u00fcr Sabbaticals), betriebliche Sozialleistungen, Gesundheits- und Sportprogramme\nBewerben Sie sich jetzt online und werden Sie Teil des Teams \u2013\nwir freuen uns auf Ihre Bewerbung!\nAls eine f\u00fchrende europ\u00e4ische Privatbank mit \u00fcber 430 Jahren Erfahrung blicken wir auf eine lange Unternehmensgeschichte zur\u00fcck. Gleichzeitig gestalten wir mit umfassenden Investitionen aktiv unsere Zukunft. Grundlage f\u00fcr unseren Fortschritt und unsere Weiterentwicklung sind unsere Mitarbeiter. Wir ermutigen diese, neue Ans\u00e4tze auszuprobieren, ihre Ideen mit einzubringen und ihren eigenen Weg zum Erfolg bei uns zu gehen. Wir sind ein ambitioniertes, zukunftsorientiertes Unternehmen, das jahrhundertelange Erfahrung und Innovationskraft vereint.\nBei uns erleben Sie eine Kultur, die zum selbstst\u00e4ndigen Denken anregt, Unternehmertum f\u00f6rdert und dazu ermutigt, den Status quo zu hinterfragen. Wir legen gro\u00dfen Wert auf die Zusammenarbeit vor Ort \u2013 unser B\u00fcro ist ein zentraler Ort des Dialogs, der Innovation und des gemeinsamen Wachstums. Sie treffen hier auf talentierte Kollegen, die es gewohnt sind, Verantwortung zu \u00fcbernehmen, und gemeinsam an einem Strang ziehen, um Ergebnisse zu erzielen.\nWerden Sie Teil von Berenberg und arbeiten Sie mit uns gemeinsam daran, das Richtige f\u00fcr unsere Kunden, unser Gesch\u00e4ft und unsere Mitarbeiter zu tun \u2013\nOur future is where you take us!\nAus organisatorischen Gr\u00fcnden nehmen wir nur Bewerbungen an, die uns \u00fcber unser Online-Bewerbermanagementsystem auf der Website erreichen.\n*Aus Gr\u00fcnden der besseren Lesbarkeit wird auf die gleichzeitige Verwendung mehrgeschlechtlicher Sprachformen verzichtet. S\u00e4mtliche Personenbezeichnungen gelten gleichwohl f\u00fcr jegliches Geschlecht. Bei uns sind alle Bewerbungen willkommen, unabh\u00e4ngig von Geschlecht, Nationalit\u00e4t, ethnischer Herkunft, sozialem Hintergrund, Behinderung, Religion, Alter oder sexueller Orientierung. Bei Fragen wenden Sie sich bitte an unser Recruitment-Team unter recruitment@berenberg.de.\nBack to job list\nApply\nShare this job:\nShare Experte* in Kapitalmarktprozesse und -abwicklung with a friend via e-mail",
        "application_url": "https://berenberg.avature.net/en_GB/careers/Login?jobId=2761",
        "metadata": {
            "Country": "Germany",
            "City": "Frankfurt, Hamburg",
            "Type of role": "Professional",
            "Working time": "Full-time",
            "Type of contract": "Permanent"
        },
        "link": "https://berenberg.avature.net/en_GB/careers/JobDetail/Experte-in-Kapitalmarktprozesse-und-abwicklung/2761"
    },
    {
        "title": null,
        "description_html": null,
        "description_text": "IAM / PAM Specialist\nGeneral information\nCountry\nUnited Kingdom\nCity\nLondon\nType of role\nProfessional\nWorking time\nFull-time\nType of contract\nPermanent\nRemaining openings\n1\nDescription & Requirements\nFor our\nInnovation & Technology\ndepartment in\nLondon\nwe are looking to hire a:\nIAM / PAM Specialist\nInnovation & Technology @ Berenberg\nIn an era where digitalisation and modern IT infrastructure is revolutionizing banking, we are shaping a technology-driven bank in which you as an IT professional will work closely with our business units. Our technology teams offer you an environment that will present you with exciting challenges - be it through the support and further development of legacy systems or the introduction of modern technologies such as AI, machine learning and highly automated trading applications.\nWhat will you do?\nCompany-wide development of a comprehensive target vision for IAM and PAM to unify, consolidate, and define access management processes\nConceptual advancement, optimization, and automation of access management, including the development of standards in the IAM and PAM environment\nSupport in integrating IAM and PAM systems into the existing IT landscape (e.g., Active Directory, cloud platforms such as Azure AD)\nConsulting for users, role owners, and managers on technical and process-related issues, as well as coordination and continuous improvement of relevant IAM/PAM processes\nSecurity & Compliance: Support in developing and creating concepts and documentation based on regulatory requirements, including the definition of critical permissions\nWho are we looking for?\nExperience with common Identity and Access Management systems (such as Ping Identity, SailPoint, Omada) and specialized Privileged Access Management tools (such as CyberArk, BeyondTrust, Delinea)\nBasic knowledge of directory services (LDAP, AD, AAD) and authentication methods (MFA, SSO, OAuth, SAML, Kerberos) is an advantage\nUnderstanding of Zero Trust, Least Privilege, and Role-Based Access Control (RBAC) principles\nExperience with IT security standards and compliance requirements in the banking or insurance sector\nStrong teamwork and communication skills with both technical and non-technical stakeholders\nExcellent written and spoken English. Knowledge of\nGerman\nwould be an advantage\nWhat we offer you:\nPrivate pension plan - 10% of base salary contribution by Berenberg\nGenerous 30 day holiday allowance\nPrivate Health Insurance\nLife Insurance scheme\nFlexible working hours\nEnhanced parental leave policies\nEmployee Assistance Programme offering counselling sessions related to mental health, financial wellbeing and other topics\nApply online now to join our team \u2013\nwe look forward to receiving your application!\nWe are a leading European private bank, with over 430 years of experience and deep rooted history, but we are still shaping and heavily investing in our future. Our progress and evolution are driven by our people. We encourage them to try new approaches, voice their opinions and achieve success in their own way.\nWe provide opportunities for them to develop their talents, explore different career paths and achieve their full potential.\nWe\u2019re an ambitious, forward-looking business, backed by centuries of tradition and built on innovation. You\u2019ll find a culture that encourages people to think independently, act entrepreneurially and challenge the status quo.\nWe place great importance on working on site, as we believe that being together in the office not only fosters creativity and efficiency, but also strengthens networks and builds trusting, collegial relationships. For us, this forms the foundation for productive and successful work. Together we collaborate to shape our business and fulfil our ambitious goals.\nWe welcome you to join us in our commitment to always do the right thing for our people, clients and our business\n\u2013 Our future is where you take us!\nWe will only accept applications submitted through our online application management system on the website.\nBerenberg is an Equal Opportunities Employer and prides itself on being a modern, dynamic and internationally orientated organisation. We value the rich diversity, skills and abilities and creative potential that people from differing backgrounds and experiences bring to the workplace. Every employee plays a vital role in providing quality service to all our customers and helping to create and inclusive working environment, where everyone can realise their full potential. We\u2019re committed to finding reasonable accommodations for candidates who require adjustments during our recruiting process. Please contact us directly on recruitment@berenberg.com to discuss.\nBack to job list\nApply\nShare this job:\nShare IAM / PAM Specialist with a friend via e-mail",
        "application_url": "https://berenberg.avature.net/en_GB/careers/Login?jobId=2713",
        "metadata": {
            "Country": "United Kingdom",
            "City": "London",
            "Type of role": "Professional",
            "Working time": "Full-time",
            "Type of contract": "Permanent",
            "Remaining openings": "1"
        },
        "link": "https://berenberg.avature.net/en_GB/careers/JobDetail/IAM-PAM-Specialist/2713"
    },
    {
        "title": null,
        "description_html": null,
        "description_text": "Connectivity and Messaging Engineer\nGeneral information\nCountry\nUnited Kingdom\nCity\nLondon\nType of role\nProfessional\nWorking time\nFull-time\nType of contract\nPermanent\nRemaining openings\n1\nDescription & Requirements\nFor our\nInnovation & Technology\ndepartment in\nLondon\nwe are looking to hire a:\nConnectivity and Messaging Engineer\nInnovation & Technology @ Berenberg\nIn an era where digitalisation and modern IT infrastructure is revolutionizing banking, we are shaping a technology-driven bank in which you as an IT professional will work closely with our business units. Our technology teams offer you an environment that will present you with exciting challenges - be it through the support and further development of legacy systems or the introduction of modern technologies such as AI, machine learning and highly automated trading applications.\nYour Role in the team:\nWe are about to start the next major overhaul of ULTRA, Berenberg\u2019s connectivity and messaging platform. Working on this new version of ULTRA will offer ample opportunity to adopt new concepts, ideas and technologies what will allow ULTRA to stay ahead of future demands.\nAs engineer in this role you will be working on our in-house micro-service, fully Kubernetes (K8s) deployed connectivity & messaging platform ULTRA, which enables practically all application in our IB trading stack to talk to each other in a flexible, reliable and secure manner. ULTRA also provides our FIX based client and exchange connectivity.\nWhat will you do?\nWorking on ULTRA puts you right into the middle of IB engineering life as you will be collaborating and interfacing practically with all other IB teams and most other systems\nYou will also be responsible to work on new exchange gateway implementations, their ongoing maintenance as exchanges evolve their gateways\nBeing such a mission-critical system which typically runs 24/7, any new features and changes to ULTRA will have to be fully tested in an automated manner. The role also comes with support responsibilities of varying degree\nWho are we looking for?\nDeep and solid experience with Java creating scalable, understandable and fully tested code for low-latency, high-throughput applications\nProfound OOA & OOD skills, dee understanding of multi-threading as well as general concepts of messaging patterns (point-to-point, pub/sub etc, event-driven)\nExperienced with the full development life-cyle: implementation, review, full automated testing, release and familiarity with the processes and tools this typically includes (CI/CD pipelines etc)\nProfound understanding of the FIX protocol and how FIX engines generally work\nTCP/IP, UDP \u2013 good understanding of IP networks, such as routing tables, subnets, BGP\nWorking with containers (aka Docker) and Kubernetes highly advantageous\nSomebody who naturally and continuously strives to improve a product and its \u2018eco-system\u2019 (which includes CI/CD pipelines, automated [performance] testing, [performance] monitoring) and can do so by \u2018keeping things simple\u2019\nWhat we offer you:\nPrivate pension plan - 10% of base salary contribution by Berenberg\nGenerous 30 day holiday allowance\nPrivate Health Insurance\nLife Insurance scheme\nFlexible working hours\nEnhanced parental leave policies\nEmployee Assistance Programme offering counselling sessions related to mental health, financial wellbeing and other topics\nApply online now to join our team \u2013\nwe look forward to receiving your application!\nWe are a leading European private bank, with over 430 years of experience and deep rooted history, but we are still shaping and heavily investing in our future. Our progress and evolution are driven by our people. We encourage them to try new approaches, voice their opinions and achieve success in their own way.\nWe provide opportunities for them to develop their talents, explore different career paths and achieve their full potential.\nWe\u2019re an ambitious, forward-looking business, backed by centuries of tradition and built on innovation. You\u2019ll find a culture that encourages people to think independently, act entrepreneurially and challenge the status quo.\nWe place great importance on working on site, as we believe that being together in the office not only fosters creativity and efficiency, but also strengthens networks and builds trusting, collegial relationships. For us, this forms the foundation for productive and successful work. Together we collaborate to shape our business and fulfil our ambitious goals.\nWe welcome you to join us in our commitment to always do the right thing for our people, clients and our business\n\u2013 Our future is where you take us!\nWe will only accept applications submitted through our online application management system on the website.\nBerenberg is an Equal Opportunities Employer and prides itself on being a modern, dynamic and internationally orientated organisation. We value the rich diversity, skills and abilities and creative potential that people from differing backgrounds and experiences bring to the workplace. Every employee plays a vital role in providing quality service to all our customers and helping to create and inclusive working environment, where everyone can realise their full potential. We\u2019re committed to finding reasonable accommodations for candidates who require adjustments during our recruiting process. Please contact us directly on recruitment@berenberg.com to discuss.\nBack to job list\nApply\nShare this job:\nShare Connectivity and Messaging Engineer with a friend via e-mail",
        "application_url": "https://berenberg.avature.net/en_GB/careers/Login?jobId=2659",
        "metadata": {
            "Country": "United Kingdom",
            "City": "London",
            "Type of role": "Professional",
            "Working time": "Full-time",
            "Type of contract": "Permanent",
            "Remaining openings": "1"
        },
        "link": "https://berenberg.avature.net/en_GB/careers/JobDetail/Connectivity-and-Messaging-Engineer/2659"
    },
    {
        "title": null,
        "description_html": null,
        "description_text": "IT Controller*\nGeneral information\nCountry\nGermany\nCity\nHamburg\nType of role\nProfessional\nWorking time\nFull-time\nType of contract\nPermanent\nRemaining openings\n1\nDescription & Requirements\nF\u00fcr unseren\nBereich Risk & Finance\nam\nStandort Hamburg\nsuchen wir zum\nn\u00e4chstm\u00f6glichen Zeitpunkt\nSie als\nIT Controller*\nIhre Rolle im Team\nSie verantworten die transparente Steuerung und Analyse der IT-Kosten im Rahmen der monatlichen Profit-Center-Rechnung und behalten Budgets sowie Forecasts \u2013 insbesondere f\u00fcr externe Leistungen \u2013 sicher im Blick. Sie unterst\u00fctzen die j\u00e4hrliche IT-Planung in enger Abstimmung mit der IT-Bereichsleitung und den Program Leads und stellen ein belastbares Kosten-Reporting sicher. Dar\u00fcber hinaus entwickeln Sie die IT-Controlling-Strukturen, Artikel und Services kontinuierlich weiter und sorgen f\u00fcr eine saubere Abbildung der Kostentr\u00e4ger in den relevanten Systeme.\nWelche Aufgaben erwarten Sie?\nErmittlung, Analyse und Abgleich der IT-Kosten im Rahmen der monatlichen Profit-Center-Rechnung sowie Budget\u00fcberwachung\nErstellung und Auswertung von Forecasts f\u00fcr IT-Kosten mit Schwerpunkt auf externen Dienstleistungen\nPflege und Weiterentwicklung der IT-Artikel und Dienstleistungen im IT-Controlling-System\nMitwirkung bei der j\u00e4hrlichen IT-Planung in enger Abstimmung mit IT-Bereichsleitung und Program Leads\nPlausibilisierung und Reporting der gebuchten IT-Kosten sowie Pflege der Kostentr\u00e4ger im Anlagenbuchhaltungssystem\nWen suchen wir?\nErfolgreich abgeschlossenes betriebswirtschaftliches Studium mit Schwerpunkt Controlling/IT oder vergleichbare Qualifikation\nFundierte Excel-Kenntnisse sowie Erfahrung in der Arbeit mit Controlling- und Reporting-Tools\nErste praktische Erfahrung mit SQL, idealerweise im Kontext von Datenanalysen und Controlling\nHohe IT-Affinit\u00e4t, vorzugsweise Erfahrung mit BI-Tools wie QlikView\nAnalytisches Denken, strukturierte Arbeitsweise und Kommunikationsst\u00e4rke in der Zusammenarbeit mit Fachbereichen\nSehr gute Deutsch- und gute Englischkenntnisse in Wort und Schrift\nWas wir Ihnen bieten:\nFlexible Arbeitszeiten innerhalb einer 39-Stunden-Woche\n30 Tage Jahresurlaub sowie zus\u00e4tzliche freie Tage am 24. und 31. Dezember\nVielseitiges und spannendes Aufgabengebiet in einem modernen und dynamischen Umfeld sowie ein wertsch\u00e4tzendes Betriebsklima\nGezielte F\u00f6rderung durch interne und externe Schulungs- und Entwicklungsprogramme\nBerenberg-Patensystem f\u00fcr ein strukturiertes und reibungsloses Onboarding\nVielf\u00e4ltige Zusch\u00fcsse (z. B. Deutschlandticket, JobRad, verm\u00f6genswirksame Leistungen, betriebliche Altersvorsorge, Essenszusch\u00fcsse bzw. Betriebsrestaurant in Hamburg)\nZus\u00e4tzliche Leistungen wie Familienservice, Arbeitszeitkonto (z. B. f\u00fcr Sabbaticals), betriebliche Sozialleistungen, Gesundheits- und Sportprogramme\nBewerben Sie sich jetzt online und werden Sie Teil des Teams \u2013\nwir freuen uns auf Ihre Bewerbung!\nAls eine f\u00fchrende europ\u00e4ische Privatbank mit \u00fcber 430 Jahren Erfahrung blicken wir auf eine lange Unternehmensgeschichte zur\u00fcck. Gleichzeitig gestalten wir mit umfassenden Investitionen aktiv unsere Zukunft. Grundlage f\u00fcr unseren Fortschritt und unsere Weiterentwicklung sind unsere Mitarbeiter. Wir ermutigen diese, neue Ans\u00e4tze auszuprobieren, ihre Ideen mit einzubringen und ihren eigenen Weg zum Erfolg bei uns zu gehen. Wir sind ein ambitioniertes, zukunftsorientiertes Unternehmen, das jahrhundertelange Erfahrung und Innovationskraft vereint.\nBei uns erleben Sie eine Kultur, die zum selbstst\u00e4ndigen Denken anregt, Unternehmertum f\u00f6rdert und dazu ermutigt, den Status quo zu hinterfragen. Wir legen gro\u00dfen Wert auf die Zusammenarbeit vor Ort \u2013 unser B\u00fcro ist ein zentraler Ort des Dialogs, der Innovation und des gemeinsamen Wachstums. Sie treffen hier auf talentierte Kollegen, die es gewohnt sind, Verantwortung zu \u00fcbernehmen, und gemeinsam an einem Strang ziehen, um Ergebnisse zu erzielen.\nWerden Sie Teil von Berenberg und arbeiten Sie mit uns gemeinsam daran, das Richtige f\u00fcr unsere Kunden, unser Gesch\u00e4ft und unsere Mitarbeiter zu tun \u2013\nOur future is where you take us!\nAus organisatorischen Gr\u00fcnden nehmen wir nur Bewerbungen an, die uns \u00fcber unser Online-Bewerbermanagementsystem auf der Website erreichen.\n*Aus Gr\u00fcnden der besseren Lesbarkeit wird auf die gleichzeitige Verwendung mehrgeschlechtlicher Sprachformen verzichtet. S\u00e4mtliche Personenbezeichnungen gelten gleichwohl f\u00fcr jegliches Geschlecht. Bei uns sind alle Bewerbungen willkommen, unabh\u00e4ngig von Geschlecht, Nationalit\u00e4t, ethnischer Herkunft, sozialem Hintergrund, Behinderung, Religion, Alter oder sexueller Orientierung. Bei Fragen wenden Sie sich bitte an unser Recruitment-Team unter recruitment@berenberg.de.\nBack to job list\nApply\nShare this job:\nShare IT Controller* with a friend via e-mail",
        "application_url": "https://berenberg.avature.net/en_GB/careers/Login?jobId=2695",
        "metadata": {
            "Country": "Germany",
            "City": "Hamburg",
            "Type of role": "Professional",
            "Working time": "Full-time",
            "Type of contract": "Permanent",
            "Remaining openings": "1"
        },
        "link": "https://berenberg.avature.net/en_GB/careers/JobDetail/IT-Controller/2695"
    },
    {
        "title": null,
        "description_html": null,
        "description_text": "Werkstudent* Incident & Problem Management\nGeneral information\nCountry\nGermany\nCity\nHamburg\nType of role\nWorking Student\nWorking time\nPart-time\nType of contract\nWorking Student\nRemaining openings\n1\nDescription & Requirements\nUnterst\u00fctzen Sie unser\nProgramm Tech Services\nam Standort\nHamburg\nidealerweise f\u00fcr\n6-24 Monate\nals\nWerkstudent* Incident & Problem Management\nWelche Aufgaben erwarten Sie?\nUnterst\u00fctzung beim Dispatching und bei der Bearbeitung von Incidents & Problems im IT Service Management Tool (ServiceNow)\nErste Analyse und Priorisierung von gemeldeten Incidents\nUnterst\u00fctzung bei der Dokumentation von Workarounds und Fixes von Incidents und Problems\nMonitoring der offenen Tickets und Sicherstellung der SLA Einhaltung\nMitarbeit bei der Erstellung von Reports und Dashboards zu Incidents und Problems\nUnterst\u00fctzung bei der Organisation und Dokumentation von Problem-Reviews und lessons learned\nAbleiten von Korrelationen zwischen Incidents und Verkn\u00fcpfung von korrelierenden Incidents\nWen suchen wir?\nEingeschriebener Student in einem Studiengang mit Ausrichtung auf (Wirtschafts-) Informatik\nSicherer Umgang mit den M365 Tools und erste Erfahrungen mit einem ITSM Tool w\u00fcnschenswert\nAnalytische und strukturierte Arbeitsweise sowie Freude an Teamarbeit\nSehr gute Deutsch- und gute Englischkenntnisse in Wort und Schrift\nWas wir Ihnen bieten:\nVielseitiges und spannendes Aufgabengebiet in einem modernen und dynamischen Umfeld sowie ein wertsch\u00e4tzendes Betriebsklima\nStrukturiertes und reibungsloses Onboarding\nZugang zu unseren internen \u201eLearning & Development\u201c Angeboten wie z. B. den \u201eLunch & Learn\u201c- Sessions, Seminaren oder inspirierenden Vortr\u00e4gen\nM\u00f6glichkeit, im Anschluss Teil unseres Future Talent Programms zu werden, welches unser exklusives Talentbindungsprogramm ist\nVielf\u00e4ltige Zusch\u00fcsse f\u00fcr z. B. Deutschlandticket und Essenszusch\u00fcsse\nZus\u00e4tzliche Leistungen wie betriebliche Sportprogramme, sowie Zugang zu externem Vorteilsportal mit exklusiven Angeboten\nBewerben Sie sich jetzt online mit Ihren vollst\u00e4ndigen Bewerbungsunterlagen inklusive Immatrikulationsbescheinigung mit Angabe des Fachsemesters. Angeh\u00f6rige von Staaten au\u00dferhalb des europ\u00e4ischen Wirtschaftsraums schicken ggf. bitte ihre Aufenthalts- und Arbeitsgenehmigung mit.\nWir freuen uns auf Ihre Bewerbung!\nAls eine f\u00fchrende europ\u00e4ische Privatbank mit \u00fcber 430 Jahren Erfahrung blicken wir auf eine lange Unternehmensgeschichte zur\u00fcck. Gleichzeitig gestalten wir mit umfassenden Investitionen aktiv unsere Zukunft. Grundlage f\u00fcr unseren Fortschritt und unsere Weiterentwicklung sind unsere Mitarbeiter. Wir ermutigen diese, neue Ans\u00e4tze auszuprobieren, ihre Ideen mit einzubringen und ihren eigenen Weg zum Erfolg bei uns zu gehen. Wir sind ein ambitioniertes, zukunftsorientiertes Unternehmen, das jahrhundertelange Erfahrung und Innovationskraft vereint.\nBei uns erleben Sie eine Kultur, die zum selbstst\u00e4ndigen Denken anregt, Unternehmertum f\u00f6rdert und dazu ermutigt, den Status quo zu hinterfragen. Wir legen gro\u00dfen Wert auf die Zusammenarbeit vor Ort \u2013 unser B\u00fcro ist ein zentraler Ort des Dialogs, der Innovation und des gemeinsamen Wachstums. Sie treffen hier auf talentierte Kollegen, die es gewohnt sind, Verantwortung zu \u00fcbernehmen, und gemeinsam an einem Strang ziehen, um Ergebnisse zu erzielen.\nWerden Sie Teil von Berenberg und arbeiten Sie mit uns gemeinsam daran, das Richtige f\u00fcr unsere Kunden, unser Gesch\u00e4ft und unsere Mitarbeiter zu tun \u2013\nOur future is where you take us!\nAus organisatorischen Gr\u00fcnden nehmen wir nur Bewerbungen an, die uns \u00fcber unser Online-Bewerbermanagementsystem auf der Website erreichen.\n*Aus Gr\u00fcnden der besseren Lesbarkeit wird auf die gleichzeitige Verwendung mehrgeschlechtlicher Sprachformen verzichtet. S\u00e4mtliche Personenbezeichnungen gelten gleichwohl f\u00fcr jegliches Geschlecht. Bei uns sind alle Bewerbungen willkommen, unabh\u00e4ngig von Geschlecht, Nationalit\u00e4t, ethnischer Herkunft, sozialem Hintergrund, Behinderung, Religion, Alter oder sexueller Orientierung. Bei Fragen wenden Sie sich bitte an unser Recruitment-Team unter recruitment@berenberg.de.\nBack to job list\nApply\nShare this job:\nShare Werkstudent* Incident & Problem Management with a friend via e-mail",
        "application_url": "https://berenberg.avature.net/en_GB/careers/Login?jobId=2684",
        "metadata": {
            "Country": "Germany",
            "City": "Hamburg",
            "Type of role": "Working Student",
            "Working time": "Part-time",
            "Type of contract": "Working Student",
            "Remaining openings": "1"
        },
        "link": "https://berenberg.avature.net/en_GB/careers/JobDetail/Werkstudent-Incident-Problem-Management/2684"
    },
    {
        "title": null,
        "description_html": null,
        "description_text": "Specialist* Acquisition Origination Wealth Management\nGeneral information\nCountry\nGermany\nCity\nFrankfurt\nType of role\nProfessional\nWorking time\nFull-time\nType of contract\nPermanent\nRemaining openings\n3\nDescription & Requirements\nF\u00fcr unser Team\nOrigination\nim Wealth Management am Standort\nFrankfurt\nsuchen wir zum\nn\u00e4chstm\u00f6glichen\nZeitpunkt Sie als\nSpecialist* Acquisition Origination Wealth Management\nIhre Rolle im Team\nF\u00fcr unser neu aufgebautes Origination-Team im Wealth Management suchen wir Pers\u00f6nlichkeiten mit ausgepr\u00e4gter Leidenschaft f\u00fcr Akquisition und Vertrieb. Als erste Anlaufstelle f\u00fcr potenzielle Kunden identifizieren und qualifizieren Sie zielgerichtet neue Kontakte und legen so den Grundstein f\u00fcr unser Wachstum im deut-schen Markt.\nSie treten proaktiv an Entscheiderinnen und Entscheider heran und er\u00f6ffnen Zug\u00e4nge zu Unternehmern, Familienunternehmen, Stiftungen und b\u00f6rsennotierten Gesellschaften. Gemeinsam mit den Kolleginnen und Kollegen im Wealth Management tragen Sie entscheidend dazu bei, dass aus Kontakten langfristige Mandate entstehen.\nWelche Aufgaben erwarten Sie?\nAktive Ansprache potenzieller Neukunden \u00fcber Telefon und digitale Kan\u00e4le sowie Arbeit mit vorqualifizierten Leads aus Marketingkampagnen und Marktbeobachtung.\nVermittlung des Leistungsversprechens von Berenberg, Durchf\u00fchrung von Bedarfsanalysen und Qualifizierung von Interessenten f\u00fcr den weiteren Beratungsprozess.\nTerminvereinbarung und enge Zusammenarbeit mit unseren Relationship Managern.\nUnterst\u00fctzung durch Vor- und Nachbereitung von Kundenterminen.\nSorgf\u00e4ltige Dokumentation aller Aktivit\u00e4ten und Ergebnisse im CRM-System unter Beachtung der datenschutzrechtlichen Anforderungen.\nWen suchen wir?\nAbgeschlossene Bank- oder kaufm\u00e4nnische Ausbildung sowie einschl\u00e4gige Akquisitionserfahrung im Wealth Management.\nStarkes Interesse an der Identifizierung von Gesch\u00e4ftsm\u00f6glichkeiten.\nAusgepr\u00e4gte Kommunikationsst\u00e4rke, sicheres Auftreten in der Kundenansprache und ein starkes Netz-werkverst\u00e4ndnis.\nF\u00e4higkeit zur selbstst\u00e4ndigen Projektarbeit kombiniert mit Teamf\u00e4higkeit.\nProaktive Einstellung, hohe Eigeninitiative, Verantwortungsbereitschaft sowie sehr gute Deutsch- und Englischkenntnisse in Wort und Schrift.\nWas wir Ihnen bieten:\nFlexible Arbeitszeiten innerhalb einer 39-Stunden-Woche\n30 Tage Jahresurlaub sowie zus\u00e4tzliche freie Tage am 24. und 31. Dezember\nVielseitiges und spannendes Aufgabengebiet in einem modernen und dynamischen Umfeld sowie wertsch\u00e4tzendes Betriebsklima\nGezielte F\u00f6rderung durch interne und externe Schulungs- und Entwicklungsprogramme\nBerenberg-Patensystem f\u00fcr ein strukturiertes und reibungsloses Onboarding\nVielf\u00e4ltige Zusch\u00fcsse (z. B. Deutschlandticket, JobRad, verm\u00f6genswirksame Leistungen, betriebliche Altersvorsorge, Essenszusch\u00fcsse bzw. Betriebsrestaurant in Hamburg)\nZus\u00e4tzliche Leistungen wie Familienservice, Arbeitszeitkonto (z. B. f\u00fcr Sabbaticals), betriebliche Sozialleistungen, Gesundheits- und Sportprogramme\nBewerben Sie sich jetzt online und werden Sie Teil des Teams \u2013\nwir freuen uns auf Ihre Bewerbung!\nAls eine f\u00fchrende europ\u00e4ische Privatbank mit \u00fcber 430 Jahren Erfahrung blicken wir auf eine lange Unternehmensgeschichte zur\u00fcck. Gleichzeitig gestalten wir mit umfassenden Investitionen aktiv unsere Zukunft. Grundlage f\u00fcr unseren Fortschritt und unsere Weiterentwicklung sind unsere Mitarbeiter. Wir ermutigen diese, neue Ans\u00e4tze auszuprobieren, ihre Ideen mit einzubringen und ihren eigenen Weg zum Erfolg bei uns zu gehen. Wir sind ein ambitioniertes, zukunftsorientiertes Unternehmen, das jahrhundertelange Erfahrung und Innovationskraft vereint.\nBei uns erleben Sie eine Kultur, die zum selbstst\u00e4ndigen Denken anregt, Unternehmertum f\u00f6rdert und dazu ermutigt, den Status quo zu hinterfragen. Wir legen gro\u00dfen Wert auf die Zusammenarbeit vor Ort \u2013 unser B\u00fcro ist ein zentraler Ort des Dialogs, der Innovation und des gemeinsamen Wachstums. Sie treffen hier auf talentierte Kollegen, die es gewohnt sind, Verantwortung zu \u00fcbernehmen, und gemeinsam an einem Strang ziehen, um Ergebnisse zu erzielen.\nWerden Sie Teil von Berenberg und arbeiten Sie mit uns gemeinsam daran, das Richtige f\u00fcr unsere Kunden, unser Gesch\u00e4ft und unsere Mitarbeiter zu tun \u2013\nOur future is where you take us!\nAus organisatorischen Gr\u00fcnden nehmen wir nur Bewerbungen an, die uns \u00fcber unser Online-Bewerbermanagementsystem auf der Website erreichen.\n*Aus Gr\u00fcnden der besseren Lesbarkeit wird auf die gleichzeitige Verwendung mehrgeschlechtlicher Sprachformen verzichtet. S\u00e4mtliche Personenbezeichnungen gelten gleichwohl f\u00fcr jegliches Geschlecht. Bei uns sind alle Bewerbungen willkommen, unabh\u00e4ngig von Geschlecht, Nationalit\u00e4t, ethnischer Herkunft, sozialem Hintergrund, Behinderung, Religion, Alter oder sexueller Orientierung. Bei Fragen wenden Sie sich bitte an unser Recruitment-Team unter recruitment@berenberg.de.\nBack to job list\nApply\nShare this job:\nShare Specialist* Acquisition Origination Wealth Management with a friend via e-mail",
        "application_url": "https://berenberg.avature.net/en_GB/careers/Login?jobId=2688",
        "metadata": {
            "Country": "Germany",
            "City": "Frankfurt",
            "Type of role": "Professional",
            "Working time": "Full-time",
            "Type of contract": "Permanent",
            "Remaining openings": "3"
        },
        "link": "https://berenberg.avature.net/en_GB/careers/JobDetail/Specialist-Acquisition-Origination-Wealth-Management/2688"
    },
    {
        "title": null,
        "description_html": null,
        "description_text": "System Engineer Workspace*\nGeneral information\nCountry\nGermany\nCity\nHamburg\nType of role\nProfessional\nWorking time\nFull-time\nType of contract\nPermanent\nRemaining openings\n1\nDescription & Requirements\nF\u00fcr unser Programm\nCore Infrastructure Services\nam\nStandort Hamburg\nsuchen wir zum\nn\u00e4chstm\u00f6glichen Zeitpunkt\ndich als\nSystem Engineer* Workspace\nInnovation & Technology @ Berenberg\nIn einer \u00c4ra, in der Digitalisierung und moderne IT-Infrastrukturen das Banking revolutionieren, gestalten wir eine technologiegest\u00fctzte Bank, in der du als IT-Profi eng mit unseren Gesch\u00e4ftsbereichen zusammenarbeitest. Unsere Technology-Teams bieten dir ein Umfeld, das dich vor spannende Herausforderungen stellt \u2013 sei es durch den Support und die Weiterentwicklung von Legacy-Systemen oder die Einf\u00fchrung moderner Technologien wie KI, Machine Learning und hochgradig automatisierte Handelsapplikationen.\nUnsere IT-Abteilung mit etwa 300 Mitarbeitern arbeitet gr\u00f6\u00dftenteils agil nach einem Scrumban-Ansatz und deckt Bereiche wie Cloud Computing, Cybersecurity, Operations, Process and Governance, Software Development und Architecture ab. Wir sind besonders stolz darauf, fast alle unsere Applikationen Inhouse zu entwickeln, was uns eine einzigartige Flexibilit\u00e4t und Innovationskraft verleiht. Unser Tech Stack umfasst moderne Technologien wie Java, Kotlin, TypeScript und Python, CI/CD-Pipelines, Container, Kubernetes sowie Azure Cloud, Azure SQL Database und Oracle Datenbank mit PL/SQL.\nDeine Rolle im Team\nIm Team Windows Infrastructure and Workspace wirst Du die Administration und Weiterentwicklung unserer Microsoft- und Virtualisierungs-Infrastruktur \u00fcbernehmen. Du wirst dich mit den Fachbereichen abstimmen, an globalen Projekten mitarbeiten und hast die M\u00f6glichkeit Dich mit eigenen Ideen und Verbesserungen einzubringen.\nWelche Aufgaben erwarten Dich?\nPlanung, Bereitstellung und Betrieb moderner Windows-Arbeitsplatzumgebungen (Windows 10/11 und Server 2016, 2019 & 2022) auf Basis einer zentralisierten Citrix Virtual Apps and Desktops (CVAD) Infrastruktur\n\u00dcbernahme des 3rd-Level-Supports f\u00fcr komplexe Fragestellungen im Bereich Arbeitsplatzbereitstellung und Benutzerumgebung\nKonfiguration und Verwaltung von Endger\u00e4ten sowie Softwareverteilung mittels Microsoft Intune, ACMP und Ivanti DSM\nBetreuung und Weiterentwicklung der Thin-Client-Infrastruktur auf Basis von IGEL OS\nAutomatisierung und Standardisierung von Prozessen rund um den digitalen Arbeitsplatz mithilfe von PowerShell\nWen suchen wir?\nErfolgreich abgeschlossene Ausbildung zum Fachinformatiker (Systemintegration), IT-Systemelektroniker oder ein abgeschlossenes Studium im Bereich (Wirtschafts-)Informatik oder einer vergleichbaren Fachrichtung\nErfahrung in der Bereitstellung und Betreuung moderner Arbeitsplatzl\u00f6sungen im Microsoft-Umfeld (Windows 10/11, Server 2016, 2019 & 2022, Office, Intune)\nFundierte Kenntnisse im Umgang mit Citrix CVAD, Citrix Gateway und Citrix Provisioning Services\nSicherer Umgang mit ACMP, Microsoft Intune, Ivanti DSM sowie Ivanti User Workspace Manager\nSehr gute Deutsch- und Englischkenntnisse in Wort und Schrift\nWas wir Dir bieten:\nFlexible Arbeitszeiten innerhalb einer 39-Stunden-Woche\n30 Tage Jahresurlaub sowie zus\u00e4tzliche freie Tage am 24. und 31. Dezember\nVielseitiges und spannendes Aufgabengebiet in einem modernen und dynamischen Umfeld sowie ein wertsch\u00e4tzendes Betriebsklima\nGezielte F\u00f6rderung durch interne und externe Schulungs- und Entwicklungsprogramme\nBerenberg-Patensystem f\u00fcr ein strukturiertes und reibungsloses Onboarding\nVielf\u00e4ltige Zusch\u00fcsse (z. B. Deutschlandticket, JobRad, verm\u00f6genswirksame Leistungen, betriebliche Altersvorsorge, Essenszusch\u00fcsse bzw. Betriebsrestaurant in Hamburg)\nZus\u00e4tzliche Leistungen wie Familienservice, Arbeitszeitkonto (z. B. f\u00fcr Sabbaticals), betriebliche Sozialleistungen, Gesundheits- und Sportprogramme\nBewirb dich jetzt online und werde Teil des Teams \u2013\nwir freuen uns auf deine Bewerbung!\nWir sind eine f\u00fchrende europ\u00e4ische Privatbank mit \u00fcber 430 Jahren Erfahrung und einer tief verwurzelten Geschichte, aber wir gestalten und investieren noch immer in Zukunft. Unser Fortschritt und unsere Entwicklung werden von unseren Mitarbeitern vorangetrieben. Wir ermutigen sie, neue Ans\u00e4tze auszuprobieren, ihre Meinung zu \u00e4u\u00dfern und auf ihre eigene Art und Weise erfolgreich zu sein.\nWir bieten ihnen die M\u00f6glichkeit, ihre Talente zu entwickeln, verschiedene Karrierewege zu erkunden und ihr Potenzial voll auszusch\u00f6pfen.\nWir sind ein ehrgeiziges, zukunftsorientiertes Unternehmen, das auf jahrhundertealte Traditionen zur\u00fcckgreift und auf Innovation baut. Du findest bei uns eine Kultur vor, die Menschen dazu ermutigt, unabh\u00e4ngig zu denken, unternehmerisch zu handeln und den Status quo in Frage zu stellen. Wir legen gro\u00dfen Wert auf die Zusammenarbeit vor Ort \u2013 unser B\u00fcro ist ein zentraler Ort des Dialogs, der Innovation und des gemeinsamen Wachstums. Gemeinsam arbeiten wir daran, unser Gesch\u00e4ft zu gestalten und unsere ehrgeizigen Ziele zu erreichen.\nWir freuen uns, wenn du dich uns anschlie\u00dft, um stets das Richtige f\u00fcr unsere Mitarbeiter, Kunden und unser Unternehmen zu tun \u2013\nOur future is where you take us!\nAus organisatorischen Gr\u00fcnden nehmen wir nur Bewerbungen an, die uns \u00fcber unser Online-Bewerbermanagementsystem auf der Website erreichen.\n*Aus Gr\u00fcnden der besseren Lesbarkeit wird auf die gleichzeitige Verwendung mehrgeschlechtlicher Sprachformen verzichtet. S\u00e4mtliche Personenbezeichnungen gelten gleichwohl f\u00fcr jegliches Geschlecht. Bei uns sind alle Bewerber willkommen, unabh\u00e4ngig von Geschlecht, Nationalit\u00e4t, ethnischer Herkunft, sozialem Hintergrund, Behinderung, Religion, Alter oder sexueller Orientierung. Bei Fragen wende dich bitte an unser Recruitment-Team unter recruitment@berenberg.de.\nBack to job list\nApply\nShare this job:\nShare System Engineer Workspace* with a friend via e-mail",
        "application_url": "https://berenberg.avature.net/en_GB/careers/Login?jobId=2448",
        "metadata": {
            "Country": "Germany",
            "City": "Hamburg",
            "Type of role": "Professional",
            "Working time": "Full-time",
            "Type of contract": "Permanent",
            "Remaining openings": "1"
        },
        "link": "https://berenberg.avature.net/en_GB/careers/JobDetail/System-Engineer-Workspace/2448"
    },
    {
        "title": null,
        "description_html": null,
        "description_text": "(Senior) Information-Security-Manager\nGeneral information\nCountry\nGermany\nCity\nHamburg\nType of role\nProfessional\nWorking time\nFull-time\nType of contract\nPermanent\nRemaining openings\n1\nDescription & Requirements\nF\u00fcr unser\nInformation Security Team\nin\nHamburg\nsuchen wir zum n\u00e4chstm\u00f6glichen Zeitpunkt Sie als\n(Senior) Information Security Manager\n*\nIhre Rolle im Team\nSie agieren als zentrale Ansprechperson f\u00fcr Informationssicherheit und unterst\u00fctzen die 1st Line beratend und \u00fcberwachend bei der Umsetzung sicherheitsrelevanter Anforderungen. Sie begleiten strategische IT-Projekte, identifizieren Risiken fr\u00fchzeitig und koordinieren geeignete Gegenma\u00dfnahmen bis hin zur Analyse von Sicherheitsvorf\u00e4llen. Zudem treiben Sie den kontinuierlichen Ausbau des ISMS voran, \u00fcbersetzen externe regulatorische Vorgaben (u. a. DORA, BAIT/KAIT/VAIT) in interne Regelwerke und entwickeln das SIEM auf Basis von Splunk gezielt weiter.\nWelche Aufgaben erwarten Sie?\nAnsprechpartner f\u00fcr alle Fragen der Informationssicherheit und Beratung/\u00dcberwachung der 1st Line.\nBegleitung von IT-Projekten (z. B. Weiterentwicklung der Netzarchitektur, Einf\u00fchrung von Instant Payments).\nIdentifikation von Risiken, Unterst\u00fctzung bei Gegenma\u00dfnahmen sowie Analyse und Bearbeitung potenzieller Sicherheitsvorf\u00e4lle.\nAusbau und kontinuierliche Verbesserung des ISMS (Richtlinien, Prozesse, Soll-Ma\u00dfnahmen) sowie \u00dcberf\u00fchrung externer Anforderungen (DORA, BAIT/KAIT/VAIT etc.) in interne Regelwerke.\nErweiterung und Optimierung des Security Information and Event Managements (SIEM) auf Basis von Splunk\nWen suchen wir?\nAbgeschlossenes Studium der Informatik oder eine vergleichbare Ausbildung im IT-Umfeld, idealerweise erg\u00e4nzt durch erste Berufserfahrung in der Informationssicherheit und Kenntnisse relevanter Standards (z. B. ISO 27001, BSI IT-Grundschutz).\nAusgepr\u00e4gte Team- und Kommunikationsf\u00e4higkeit in der Zusammenarbeit, sowohl in Deutsch als auch in Englisch.\nHohe Lernbereitschaft sowie die Motivation, sich schnell und eigenst\u00e4ndig in neue Themengebiete einzuarbeiten.\nAnalytisches Denkverm\u00f6gen und die F\u00e4higkeit zu systematischem, strukturiertem Vorgehen.\nSelbstst\u00e4ndige, l\u00f6sungsorientierte Arbeitsweise kombiniert mit Engagement, Belastbarkeit und Verantwortungsbewusstsein.\nWas wir Ihnen bieten:\nFlexible Arbeitszeiten innerhalb einer 39-Stunden-Woche\n30 Tage Jahresurlaub sowie zus\u00e4tzliche freie Tage am 24. und 31. Dezember\nVielseitiges und spannendes Aufgabengebiet in einem modernen und dynamischen Umfeld sowie wertsch\u00e4tzendes Betriebsklima\nGezielte F\u00f6rderung durch interne und externe Schulungs- und Entwicklungsprogramme\nBerenberg-Patensystem f\u00fcr ein strukturiertes und reibungsloses Onboarding\nVielf\u00e4ltige Zusch\u00fcsse (z. B. Deutschlandticket, JobRad, verm\u00f6genswirksame Leistungen, betriebliche Altersvorsorge, Essenszusch\u00fcsse bzw. Betriebsrestaurant in Hamburg)\nZus\u00e4tzliche Leistungen wie Familienservice, Arbeitszeitkonto (z. B. f\u00fcr Sabbaticals), betriebliche Sozialleistungen, Gesundheits- und Sportprogramme\nBewerben Sie sich jetzt online und werden Sie Teil des Teams \u2013\nwir freuen uns auf Ihre Bewerbung!\nAls eine f\u00fchrende europ\u00e4ische Privatbank mit \u00fcber 430 Jahren Erfahrung blicken wir auf eine lange Unternehmensgeschichte zur\u00fcck. Gleichzeitig gestalten wir mit umfassenden Investitionen aktiv unsere Zukunft. Grundlage f\u00fcr unseren Fortschritt und unsere Weiterentwicklung sind unsere Mitarbeiter. Wir ermutigen diese, neue Ans\u00e4tze auszuprobieren, ihre Ideen mit einzubringen und ihren eigenen Weg zum Erfolg bei uns zu gehen. Wir sind ein ambitioniertes, zukunftsorientiertes Unternehmen, das jahrhundertelange Erfahrung und Innovationskraft vereint.\nBei uns erleben Sie eine Kultur, die zum selbstst\u00e4ndigen Denken anregt, Unternehmertum f\u00f6rdert und dazu ermutigt, den Status quo zu hinterfragen. Wir legen gro\u00dfen Wert auf die Zusammenarbeit vor Ort \u2013 unser B\u00fcro ist ein zentraler Ort des Dialogs, der Innovation und des gemeinsamen Wachstums. Sie treffen hier auf talentierte Kollegen, die es gewohnt sind, Verantwortung zu \u00fcbernehmen, und gemeinsam an einem Strang ziehen, um Ergebnisse zu erzielen.\nWerden Sie Teil von Berenberg und arbeiten Sie mit uns gemeinsam daran, das Richtige f\u00fcr unsere Kunden, unser Gesch\u00e4ft und unsere Mitarbeiter zu tun \u2013\nOur future is where you take us!\nAus organisatorischen Gr\u00fcnden nehmen wir nur Bewerbungen an, die uns \u00fcber unser Online-Bewerbermanagementsystem auf der Website erreichen.\n*Aus Gr\u00fcnden der besseren Lesbarkeit wird auf die gleichzeitige Verwendung mehrgeschlechtlicher Sprachformen verzichtet. S\u00e4mtliche Personenbezeichnungen gelten gleichwohl f\u00fcr jegliches Geschlecht. Bei uns sind alle Bewerbungen willkommen, unabh\u00e4ngig von Geschlecht, Nationalit\u00e4t, ethnischer Herkunft, sozialem Hintergrund, Behinderung, Religion, Alter oder sexueller Orientierung. Bei Fragen wenden Sie sich bitte an unser Recruitment-Team unter recruitment@berenberg.de.\nBack to job list\nApply\nShare this job:\nShare (Senior) Information-Security-Manager with a friend via e-mail",
        "application_url": "https://berenberg.avature.net/en_GB/careers/Login?jobId=2674",
        "metadata": {
            "Country": "Germany",
            "City": "Hamburg",
            "Type of role": "Professional",
            "Working time": "Full-time",
            "Type of contract": "Permanent",
            "Remaining openings": "1"
        },
        "link": "https://berenberg.avature.net/en_GB/careers/JobDetail/Senior-Information-Security-Manager/2674"
    },
    {
        "title": null,
        "description_html": null,
        "description_text": "Cloud Native Engineer*\nGeneral information\nCountry\nGermany\nCity\nHamburg\nType of role\nProfessional\nWorking time\nFull-time\nType of contract\nPermanent\nRemaining openings\n1\nDescription & Requirements\nF\u00fcr unser Programm\nDigital Innovation & Cloud Enablement\nam\nStandort Hamburg\nsuchen wir zum\nn\u00e4chstm\u00f6glichen Zeitpunkt\ndich als\nCloud Native Engineer*\nInnovation & Technology @ Berenberg\nIn einer \u00c4ra, in der Digitalisierung und moderne IT-Infrastrukturen das Banking revolutionieren, gestalten wir eine technologiegest\u00fctzte Bank, in der du als IT-Profi eng mit unseren Gesch\u00e4ftsbereichen zusammenarbeitest. Unsere Technology-Teams bieten dir ein Umfeld, das dich vor spannende Herausforderungen stellt \u2013 sei es durch den Support und die Weiterentwicklung von Legacy-Systemen oder die Einf\u00fchrung moderner Technologien wie KI, Machine Learning und hochgradig automatisierte Handelsapplikationen.\nUnsere IT-Abteilung mit etwa 300 Mitarbeitern arbeitet gr\u00f6\u00dftenteils agil nach einem Scrumban-Ansatz und deckt Bereiche wie Cloud Computing, Cybersecurity, Operations, Process and Governance, Software Development und Architecture ab. Wir sind besonders stolz darauf, fast alle unsere Applikationen Inhouse zu entwickeln, was uns eine einzigartige Flexibilit\u00e4t und Innovationskraft verleiht. Unser Tech Stack umfasst moderne Technologien wie Java, Kotlin, TypeScript und Python, CI/CD-Pipelines, Container, Kubernetes sowie Azure Cloud, Azure SQL Database und Oracle Datenbank mit PL/SQL.\nDeine Rolle im Team\nBei uns bist du Teil eines starken Cloud-Native-Teams, das mit modernen Technologien wie Kubernetes, Terraform und CI/CD \u2013 und viel Automatisierung \u2013 echte Erfolge m\u00f6glich macht.\nGemeinsam mit Kolleg:innen aus Development, Architektur und Security gestaltest du L\u00f6sungen, die das Banking von morgen pr\u00e4gen. Dabei treibt uns nicht nur die Technologie an, sondern vor allem unser Teamgeist.\nDu kannst dein Cloud-Know-how weiterentwickeln und gemeinsam mit uns die n\u00e4chste Etappe in Richtung AIOps, FinOps und zukunftsf\u00e4hige DevOps-Umgebungen gestalten.\nWir arbeiten eng zusammen, unterst\u00fctzen uns gegenseitig und feiern unsere Erfolge \u2013 im Arbeitsalltag und auch dar\u00fcber hinaus. Ob beim Wissensaustausch, beim gemeinsamen Mittagessen oder beim Mario-Kart-Turnier: Bei uns kommt der Spa\u00df nicht zu kurz!\nWelche Aufgaben erwarten Dich?\nAufbau und Pflege von Anwendungen, die auf Microservices-Architekturen, Containern und Cloud-Plattformen (z. B. Kubernetes, Docker) basieren\nAutomatisierte Bereitstellung und Verwaltung von Infrastruktur mittels Tools wie Terraform, Pulumi oder Ansible\nEinsatz von Orchestrierungsl\u00f6sungen wie Kubernetes zur effizienten Bereitstellung, Skalierung und Verwaltung von Container-Anwendungen\nAufbau und Pflege automatisierter Build-, Test- und Deployment-Pipelines (Continuous Integration/Continuous Delivery)\nSicherstellung von IT-Sicherheit, Compliance, Monitoring, Skalierbarkeit und Resilienz\nEntwurf von Anwendungen, die elastisch skalieren und ausfallresistent sind, um unter hoher Last oder bei Fehlern stabil zu bleiben\nWen suchen wir?\nAbgeschlossenes Studium der (Wirtschafts-)Informatik, Ausbildung im IT-Bereich oder vergleichbare Qualifikation\nErfahrung mit modernen DevOps-Praktiken und -Tools sowie Freude daran, Prozesse kontinuierlich zu optimieren\nErfahrung im Betrieb und in der Automatisierung von Cloud-Plattformen (Google Cloud, STACKIT, Azure oder vergleichbar)\nKenntnisse in Infrastructure as Code (z. B. Terraform, Ansible, Pulumi) oder \u00e4hnlich\nTeamgeist, agile Arbeitsweise, Lernbereitschaft \u2013 und gerne auch Mario-Kart-Skills\nGute Deutsch- und Englischkenntnisse in Wort und Schrift\nWas wir Dir bieten:\nFlexible Arbeitszeiten innerhalb einer 39-Stunden-Woche\n30 Tage Jahresurlaub sowie zus\u00e4tzliche freie Tage am 24. und 31. Dezember\nVielseitiges und spannendes Aufgabengebiet in einem modernen und dynamischen Umfeld sowie ein wertsch\u00e4tzendes Betriebsklima\nGezielte F\u00f6rderung durch interne und externe Schulungs- und Entwicklungsprogramme\nBerenberg-Patensystem f\u00fcr ein strukturiertes und reibungsloses Onboarding\nVielf\u00e4ltige Zusch\u00fcsse (z. B. Deutschlandticket, JobRad, verm\u00f6genswirksame Leistungen, betriebliche Altersvorsorge, Essenszusch\u00fcsse bzw. Betriebsrestaurant in Hamburg)\nZus\u00e4tzliche Leistungen wie Familienservice, Arbeitszeitkonto (z. B. f\u00fcr Sabbaticals), betriebliche Sozialleistungen, Gesundheits- und Sportprogramme\nBewirb dich jetzt online und werde Teil des Teams \u2013\nwir freuen uns auf deine Bewerbung!\nWir sind eine f\u00fchrende europ\u00e4ische Privatbank mit \u00fcber 430 Jahren Erfahrung und einer tief verwurzelten Geschichte, aber wir gestalten und investieren noch immer in Zukunft. Unser Fortschritt und unsere Entwicklung werden von unseren Mitarbeitern vorangetrieben. Wir ermutigen sie, neue Ans\u00e4tze auszuprobieren, ihre Meinung zu \u00e4u\u00dfern und auf ihre eigene Art und Weise erfolgreich zu sein.\nWir bieten ihnen die M\u00f6glichkeit, ihre Talente zu entwickeln, verschiedene Karrierewege zu erkunden und ihr Potenzial voll auszusch\u00f6pfen.\nWir sind ein ehrgeiziges, zukunftsorientiertes Unternehmen, das auf jahrhundertealte Traditionen zur\u00fcckgreift und auf Innovation baut. Du findest bei uns eine Kultur vor, die Menschen dazu ermutigt, unabh\u00e4ngig zu denken, unternehmerisch zu handeln und den Status quo in Frage zu stellen. Wir legen gro\u00dfen Wert auf die Zusammenarbeit vor Ort \u2013 unser B\u00fcro ist ein zentraler Ort des Dialogs, der Innovation und des gemeinsamen Wachstums. Gemeinsam arbeiten wir daran, unser Gesch\u00e4ft zu gestalten und unsere ehrgeizigen Ziele zu erreichen.\nWir freuen uns, wenn du dich uns anschlie\u00dft, um stets das Richtige f\u00fcr unsere Mitarbeiter, Kunden und unser Unternehmen zu tun \u2013\nOur future is where you take us!\nAus organisatorischen Gr\u00fcnden nehmen wir nur Bewerbungen an, die uns \u00fcber unser Online-Bewerbermanagementsystem auf der Website erreichen.\n*Aus Gr\u00fcnden der besseren Lesbarkeit wird auf die gleichzeitige Verwendung mehrgeschlechtlicher Sprachformen verzichtet. S\u00e4mtliche Personenbezeichnungen gelten gleichwohl f\u00fcr jegliches Geschlecht. Bei uns sind alle Bewerber willkommen, unabh\u00e4ngig von Geschlecht, Nationalit\u00e4t, ethnischer Herkunft, sozialem Hintergrund, Behinderung, Religion, Alter oder sexueller Orientierung. Bei Fragen wende dich bitte an unser Recruitment-Team unter recruitment@berenberg.de.\nBack to job list\nApply\nShare this job:\nShare Cloud Native Engineer* with a friend via e-mail",
        "application_url": "https://berenberg.avature.net/en_GB/careers/Login?jobId=2679",
        "metadata": {
            "Country": "Germany",
            "City": "Hamburg",
            "Type of role": "Professional",
            "Working time": "Full-time",
            "Type of contract": "Permanent",
            "Remaining openings": "1"
        },
        "link": "https://berenberg.avature.net/en_GB/careers/JobDetail/Cloud-Native-Engineer/2679"
    },
    {
        "title": null,
        "description_html": null,
        "description_text": "Internship, Investment Banking, Equity Capital Markets (Q2/Q4 2026)\nGeneral information\nCountry\nGermany\nCity\nFrankfurt\nType of role\nInternship (off-cycle)\nWorking time\nFull-time\nType of contract\nInternship\nRemaining openings\n3\nDescription & Requirements\nSupport our\nEquity Capital Markets\nteam in\nFrankfurt am Main\nideally for\n3-6 months\nas a\nfull-time intern\n(Q2 /Q4\n2026\n)\nOur Equity Capital Markets team is part of the Investment Banking Division and takes responsibility for all our activity across Continental Europe. The department covers all equity-related capital market transactions such as Initial Public Offerings, Capital Increases and Secondary Placings in the region and has built a strong reputation, being the #1 ECM bank in the DACH region with growing presence in Europe and the US.\nThe team in Frankfurt offers a modern, dynamic and ambitious working environment. The team is highly successful, demonstrated by multiple prestigious awards that Berenberg won in the Small and Mid Cap ECM sector in recent years. You will benefit from direct exposure on deals and transactions and interact with our industry leaders.\nYour role in the team\nDuring your internship in the ECM team, you will also be directly working together with the connected Origination and Equity Syndicate teams. As all your colleagues in the Investment Banking team, you will be working in the office during work hours, hereby allowing you to fully integrate in our collaboration-driven team composition, being fully involved in our live mandates and pitches, and eventually becoming a vital part of your colleagues\u2019 day-to-day business.\nWhat will you do?\nActive involvement in live transactions, across the DACH region as well as other Continental European countries, such as IPOs, capital increases, secondary placements as well as support in pre-IPO financing rounds\nSupport in all transaction work streams such as project coordination with involved parties (e.g. company management, syndicate banks, legal counsels and institutional investors), due diligence, prospectus drafting and further related tasks\nDevelopment of presentation materials for colleagues, clients and investors, including pitch books, marketing and transaction documents, ongoing capital market updates and steering committee meetings\nContinuous collaboration with senior management across all work streams and tasks\nConduct of sophisticated analyses on companies and sectors\nWho are we looking for?\nTop-university degree in Economics, Finance or Business with outstanding academic performance\nPrior internship experience in investment banking or corporate finance, ideally with exposure to ECM transactions\nStrong technical expertise, reflecting early responsibility and high level of exposure\nExcellent analytical skills, drive and focus, consistently delivering high-quality output\nImpeccable communication skills, strong team player mindset, and full professional fluency in English\nWhat we offer you:\nVaried and exciting area of responsibility in a modern, dynamic and fast-paced environment as well as an appreciative working atmosphere\nStructured and smooth onboarding process\nAccess to our internal Learning & Development programmes such as the \u2018Lunch & Learn Sessions\u2019, seminars or inspiring presentations\nOpportunity to subsequently become part of our Future Talent Programme, which is our exclusive talent retention programme\nAdditional benefits such as company sports programmes and access to an external benefits portal with exclusive offers\nLots of other extras such as for e.g. contribution to public transport use and lunch vouchers\nApply online now with your complete application documents, including a certificate of enrolment stating your semester of study. If you are a national of a country outside the European Economic Area, please send us your residence and work permit \u2013\nwe look forward to receiving your application!\nWe are a leading European private bank, with over 430 years of experience and deep rooted history, but we are still shaping and heavily investing in our future. Our progress and evolution are driven by our people. We encourage them to try new approaches, voice their opinions and achieve success in their own way.\nWe provide opportunities for them to develop their talents, explore different career paths and achieve their full potential.\nWe\u2019re an ambitious, forward-looking business, backed by centuries of tradition and built on innovation. You\u2019ll find a culture that encourages people to think independently, act entrepreneurially and challenge the status quo. Together we collaborate to shape our business and fulfil our ambitious goals.\nWe welcome you to join us in our commitment to always do the right thing for our people, clients and our business \u2013\nOur future is where you take us!\nFor organisational reasons, we only accept applications that reach us via our online application management system on the website.\n*For reasons of better readability, the simultaneous use of multi-gender language forms is avoided. All personal designations apply equally to all genders.\nWe welcome all applications, regardless of gender, nationality, ethnic origin, social background, disability, religion, age or sexual orientation.\nIf you have any questions, please contact our recruitment team at recruitment@berenberg.de.\nBack to job list\nApply\nShare this job:\nShare Internship, Investment Banking, Equity Capital Markets (Q2/Q4 2026) with a friend via e-mail",
        "application_url": "https://berenberg.avature.net/en_GB/careers/Login?jobId=2661",
        "metadata": {
            "Country": "Germany",
            "City": "Frankfurt",
            "Type of role": "Internship (off-cycle)",
            "Working time": "Full-time",
            "Type of contract": "Internship",
            "Remaining openings": "3"
        },
        "link": "https://berenberg.avature.net/en_GB/careers/JobDetail/Internship-Investment-Banking-Equity-Capital-Markets-Q2-Q4-2026/2661"
    },
    {
        "title": null,
        "description_html": null,
        "description_text": "(Senior) Kreditanalyst* Schwerpunkt Real Estate (Marktfolge)\nGeneral information\nCountry\nGermany\nCity\nHamburg\nType of role\nProfessional\nWorking time\nFull-time\nType of contract\nPermanent\nRemaining openings\n1\nDescription & Requirements\nF\u00fcr unsere Abteilung\nCredit Risk Management\nin\nHamburg\nsuchen wir zum n\u00e4chstm\u00f6glichen Zeitpunkt Sie als\n(Senior) Kreditanalyst* Schwerpunkt Real Estate (Marktfolge)\nIhre Rolle im Team\nIm dynamischen Marktumfeld unserer Real Estate Finance und Corporates ist das Credit Risk Management bei der Risikobeurteilung auf Basis komplexer Informationen ein zuverl\u00e4ssiger Sparringspartner. In der Marktfolge haben Sie einen umfassenden Einblick in das spannende Kreditgesch\u00e4ft unserer Bank. Um f\u00fcr unsere Kunden das Devisen- und Derivategesch\u00e4ft abwickeln zu k\u00f6nnen, arbeiten wir mit einer Vielzahl an Banken zusammen, f\u00fcr die ebenfalls eine Risikoanalyse vorgenommen wird.\nDas Credit Risk Management verantwortet neben der Kreditbeurteilung von Neuengagements die Risikofr\u00fcherkennung (Einzelrisiken, globale Trends) f\u00fcr das globale Kreditportfolio, inkl. der (Weiter-)Entwicklung von Risiko-systemen und -tools.\nIhre Aufgaben:\nEigenverantwortliche Beurteilung der Kreditrisiken, Schwerpunkt in der Assetklasse Immobilien. Dar\u00fcber hinaus auch Corporates und Banken.\nAnalyse von Gesch\u00e4fts- und Jahresabschlussberichten sowie weiteren transaktionsbezogenen Unterlagen zur Beurteilung der wirtschaftlichen Verh\u00e4ltnisse und der f\u00fcr das Engagement relevanten M\u00e4rkte\nHinterfragen, Plausibilisierung und Beurteilung von Finanzmodellen, Kreditstrukturen sowie von Risiko- und Marktlage der Unternehmen bzw. Transaktionen\nErstellung von Beschlussvorlagen und Festlegung des internen Ratings sowie Verantwortung f\u00fcr den korrekten Ablauf der Entscheidungsprozesse innerhalb der vorgegebenen organisatorischen Rahmenbedingungen\nLaufende \u00dcberwachung und Analyse der Performance und Kreditrisiken von Portfoliounternehmen mit der proaktiven Herangehensweise, die Risiken jederzeit im Rahmen der Kreditrisikostrategie zu minimieren\nAktive Mitarbeit bei der Optimierung unserer Prozesse und Systeme\nIhr Profil:\nErfolgreich abgeschlossenes Studium mit (betriebs-)wirtschaftlichem, wirtschaftsrechtlichem oder mathematischem Schwerpunkt bzw. Bankausbildung sowie weiterf\u00fchrende Qualifikationen mit f\u00fcr die Position geeigneten Schwerpunkten\nSolide Berufserfahrung in der Analyse von Corporates, Immobilien und/oder Banken\nFundiertes PC-Anwender-Know-how und routinierter Umgang mit MS Office (v. a. Excel)\nSehr gute Deutsch- und Englischkenntnisse in Wort und Schrift\nSorgf\u00e4ltige, selbstst\u00e4ndige und zielorientierte Arbeitsweise mit hohem Engagement\nWas wir Ihnen bieten:\nFlexible Arbeitszeiten innerhalb einer 39-Stunden-Woche\n30 Tage Jahresurlaub sowie zus\u00e4tzliche freie Tage am 24. und 31. Dezember\nVielseitiges und spannendes Aufgabengebiet in einem modernen und dynamischen Umfeld sowie wertsch\u00e4tzendes Betriebsklima\nGezielte F\u00f6rderung durch interne und externe Schulungs- und Entwicklungsprogramme\nBerenberg-Patensystem f\u00fcr ein strukturiertes und reibungsloses Onboarding\nVielf\u00e4ltige Zusch\u00fcsse (z. B. Deutschlandticket, JobRad, verm\u00f6genswirksame Leistungen, betriebliche Altersvorsorge, Essenszusch\u00fcsse bzw. Betriebsrestaurant in Hamburg)\nZus\u00e4tzliche Leistungen wie Familienservice, Arbeitszeitkonto (z. B. f\u00fcr Sabbaticals), betriebliche Sozialleistungen, Gesundheits- und Sportprogramme\nBewerben Sie sich jetzt online und werden Sie Teil des Teams \u2013\nwir freuen uns auf Ihre Bewerbung!\nAls eine f\u00fchrende europ\u00e4ische Privatbank mit \u00fcber 430 Jahren Erfahrung blicken wir auf eine lange Unternehmensgeschichte zur\u00fcck. Gleichzeitig gestalten wir mit umfassenden Investitionen aktiv unsere Zukunft. Grundlage f\u00fcr unseren Fortschritt und unsere Weiterentwicklung sind unsere Mitarbeiter. Wir ermutigen diese, neue Ans\u00e4tze auszuprobieren, ihre Ideen mit einzubringen und ihren eigenen Weg zum Erfolg bei uns zu gehen. Wir sind ein ambitioniertes, zukunftsorientiertes Unternehmen, das jahrhundertelange Erfahrung und Innovationskraft vereint.\nBei uns erleben Sie eine Kultur, die zum selbstst\u00e4ndigen Denken anregt, Unternehmertum f\u00f6rdert und dazu ermutigt, den Status quo zu hinterfragen. Wir legen gro\u00dfen Wert auf die Zusammenarbeit vor Ort \u2013 unser B\u00fcro ist ein zentraler Ort des Dialogs, der Innovation und des gemeinsamen Wachstums. Sie treffen hier auf talentierte Kollegen, die es gewohnt sind, Verantwortung zu \u00fcbernehmen, und gemeinsam an einem Strang ziehen, um Ergebnisse zu erzielen.\nWerden Sie Teil von Berenberg und arbeiten Sie mit uns gemeinsam daran, das Richtige f\u00fcr unsere Kunden, unser Gesch\u00e4ft und unsere Mitarbeiter zu tun \u2013\nOur future is where you take us!\nAus organisatorischen Gr\u00fcnden nehmen wir nur Bewerbungen an, die uns \u00fcber unser Online-Bewerbermanagementsystem auf der Website erreichen.\n*Aus Gr\u00fcnden der besseren Lesbarkeit wird auf die gleichzeitige Verwendung mehrgeschlechtlicher Sprachformen verzichtet. S\u00e4mtliche Personenbezeichnungen gelten gleichwohl f\u00fcr jegliches Geschlecht. Bei uns sind alle Bewerbungen willkommen, unabh\u00e4ngig von Geschlecht, Nationalit\u00e4t, ethnischer Herkunft, sozialem Hintergrund, Behinderung, Religion, Alter oder sexueller Orientierung. Bei Fragen wenden Sie sich bitte an unser Recruitment-Team unter recruitment@berenberg.de.\nBack to job list\nApply\nShare this job:\nShare (Senior) Kreditanalyst* Schwerpunkt Real Estate (Marktfolge) with a friend via e-mail",
        "application_url": "https://berenberg.avature.net/en_GB/careers/Login?jobId=2639",
        "metadata": {
            "Country": "Germany",
            "City": "Hamburg",
            "Type of role": "Professional",
            "Working time": "Full-time",
            "Type of contract": "Permanent",
            "Remaining openings": "1"
        },
        "link": "https://berenberg.avature.net/en_GB/careers/JobDetail/Senior-Kreditanalyst-Schwerpunkt-Real-Estate-Marktfolge/2639"
    },
    {
        "title": null,
        "description_html": null,
        "description_text": "(Senior) Business Analyst* Market Data & Vendor Management\nGeneral information\nCountry\nGermany\nCity\nFrankfurt, Hamburg\nType of role\nProfessional\nWorking time\nFull-time\nType of contract\nPermanent\nRemaining openings\n1\nDescription & Requirements\nF\u00fcr unseren Bereich\nTransaction Services Projects, Regulation, Market & Reference Data\nam Standort\nHamburg\noder\nFrankfurt am Main\nsuchen wir zum n\u00e4chstm\u00f6glichen Zeitpunkt Sie als\n(Senior) Business Analyst* Market Data & Vendor Management\nIhre Rolle im Team\nAls Senior Business Analyst im Bereich Market & Reference Data \u00fcbernehmen Sie eine zentrale Rolle bei der Steuerung und Optimierung unserer Datenanbieter-Beziehungen. In enger Zusammenarbeit mit verschiedenen Fachbereichen in der gesamten Bank sind Sie Ansprechpartner f\u00fcr Vertragsfragen und Kostenanalysen der Finanzdaten.\nWelche Aufgaben erwarten Sie?\nVerantwortung f\u00fcr Vertragsverhandlungen, Vertragsanalysen sowie die laufende Betreuung internationaler Datenanbieter (Bloomberg, Deutsche B\u00f6rse etc.)\nZentrale Anlaufstelle f\u00fcr interne Stakeholder in allen Belangen rund um Markt- und Referenzdaten\nAnalyse und Pr\u00fcfung bestehender Vertr\u00e4ge hinsichtlich Aktualit\u00e4t, Wirtschaftlichkeit und Einhaltung der vertraglichen Nutzungsbestimmungen\nBewertung und Abgleich der technischen Infrastruktur der Bank im Bereich Marktdaten mit den vertraglichen Anforderungen\nWeiterentwicklung bestehender Prozesse mit Fokus auf Automatisierung, Standardisierung und den Einsatz von KI \u2013 aktive Mitgestaltung und Einbringung eigener Ideen\nErstellung aussagekr\u00e4ftiger Reports und Entscheidungsvorlagen sowie Pr\u00e4sentation der Ergebnisse vor dem Management\nWen suchen wir?\nSie haben eine banknahe oder wirtschaftliche Ausbildung bzw. ein relevantes Studium abgeschlossen oder eine vergleichbare Qualifikation, z.\u202fB. mit Fokus auf Banken, Finanzm\u00e4rkte oder Beschaffung, erworben\nEinschl\u00e4gige Berufserfahrung im Umgang mit Finanzdaten bzw. im Bankwesen oder im Vertrags- und Lizenzmanagement bringen Sie mit\nSie kommunizieren sicher mit internen Stakeholdern und externen Partnern \u2013 auf Deutsch wie auf Englisch\nIdealerweise haben Sie Erfahrung im Projektmanagement oder in der Prozessoptimierung\nZu gelegentlichen Dienstreisen sind Sie bereit\nWas wir Ihnen bieten:\nFlexible Arbeitszeiten innerhalb einer 39-Stunden-Woche\n30 Tage Jahresurlaub sowie zus\u00e4tzliche freie Tage am 24. und 31. Dezember\nVielseitiges und spannendes Aufgabengebiet in einem modernen und dynamischen Umfeld sowie wertsch\u00e4tzendes Betriebsklima\nGezielte F\u00f6rderung durch interne und externe Schulungs- und Entwicklungsprogramme\nBerenberg-Patensystem f\u00fcr ein strukturiertes und reibungsloses Onboarding\nVielf\u00e4ltige Zusch\u00fcsse (z. B. Deutschlandticket, JobRad, verm\u00f6genswirksame Leistungen, betriebliche Altersvorsorge, Essenszusch\u00fcsse bzw. Betriebsrestaurant in Hamburg)\nZus\u00e4tzliche Leistungen wie Familienservice, Arbeitszeitkonto (z. B. f\u00fcr Sabbaticals), betriebliche Sozialleistungen, Gesundheits- und Sportprogramme\nBewerben Sie sich jetzt online und werden Sie Teil des Teams \u2013\nwir freuen uns auf Ihre Bewerbung!\nAls eine f\u00fchrende europ\u00e4ische Privatbank mit \u00fcber 430 Jahren Erfahrung blicken wir auf eine lange Unternehmensgeschichte zur\u00fcck. Gleichzeitig gestalten wir mit umfassenden Investitionen aktiv unsere Zukunft. Grundlage f\u00fcr unseren Fortschritt und unsere Weiterentwicklung sind unsere Mitarbeiter. Wir ermutigen diese, neue Ans\u00e4tze auszuprobieren, ihre Ideen mit einzubringen und ihren eigenen Weg zum Erfolg bei uns zu gehen. Wir sind ein ambitioniertes, zukunftsorientiertes Unternehmen, das jahrhundertelange Erfahrung und Innovationskraft vereint.\nBei uns erleben Sie eine Kultur, die zum selbstst\u00e4ndigen Denken anregt, Unternehmertum f\u00f6rdert und dazu ermutigt, den Status quo zu hinterfragen. Wir legen gro\u00dfen Wert auf die Zusammenarbeit vor Ort \u2013 unser B\u00fcro ist ein zentraler Ort des Dialogs, der Innovation und des gemeinsamen Wachstums. Sie treffen hier auf talentierte Kollegen, die es gewohnt sind, Verantwortung zu \u00fcbernehmen, und gemeinsam an einem Strang ziehen, um Ergebnisse zu erzielen.\nWerden Sie Teil von Berenberg und arbeiten Sie mit uns gemeinsam daran, das Richtige f\u00fcr unsere Kunden, unser Gesch\u00e4ft und unsere Mitarbeiter zu tun \u2013\nOur future is where you take us!\nAus organisatorischen Gr\u00fcnden nehmen wir nur Bewerbungen an, die uns \u00fcber unser Online-Bewerbermanagementsystem auf der Website erreichen.\n*Aus Gr\u00fcnden der besseren Lesbarkeit wird auf die gleichzeitige Verwendung mehrgeschlechtlicher Sprachformen verzichtet. S\u00e4mtliche Personenbezeichnungen gelten gleichwohl f\u00fcr jegliches Geschlecht. Bei uns sind alle Bewerbungen willkommen, unabh\u00e4ngig von Geschlecht, Nationalit\u00e4t, ethnischer Herkunft, sozialem Hintergrund, Behinderung, Religion, Alter oder sexueller Orientierung. Bei Fragen wenden Sie sich bitte an unser Recruitment-Team unter recruitment@berenberg.de.\nBack to job list\nApply\nShare this job:\nShare (Senior) Business Analyst* Market Data & Vendor Management with a friend via e-mail",
        "application_url": "https://berenberg.avature.net/en_GB/careers/Login?jobId=2621",
        "metadata": {
            "Country": "Germany",
            "City": "Frankfurt, Hamburg",
            "Type of role": "Professional",
            "Working time": "Full-time",
            "Type of contract": "Permanent",
            "Remaining openings": "1"
        },
        "link": "https://berenberg.avature.net/en_GB/careers/JobDetail/Senior-Business-Analyst-Market-Data-Vendor-Management/2621"
    },
    {
        "title": null,
        "description_html": null,
        "description_text": "Investment Banking Analyst\nGeneral information\nCountry\nUSA\nCity\nNew York\nType of role\nProfessional\nWorking time\nFull-time\nType of contract\nPermanent\nRemaining openings\n1\nDescription & Requirements\nFor our Investment Banking division in New York, we are looking to hire an\nInvestment Banking Analyst \u2013 New York\nYour role in the team:\nBerenberg is looking to hire an individual to work within the Investment Banking team who can support the firm\u2019s continued growth in US markets.\nIn this role, you will directly work with both mid-level and senior members of the Investment Banking team and report directly to the Head of US Investment Banking. A successful candidate in this role will assume responsibilities in the origination and execution of transactions by serving as a key stakeholder in various workstreams across the department. A candidate will be joining a very fast paced and dynamic, growing team here in the US.\nWhat will you do?\nPreparing materials for meetings with new and existing clients and investors for potential capital raising activity throughout the company lifecycle\nConducting in-depth market sector and company research to support pitches and deal execution\nBuilding and maintaining complex financial models, including equity valuation analyses\nParticipating directly in deal execution (IPOs, capital increases, block trades), including managing due diligence and data room processes\nCoordinating syndicate materials, internal presentations, and facilitate communication between Sales and Compliance teams\nWho are we looking for?\nFirst relevant experience, preferably with a U.S. investment bank or broker-dealer; strong proficiency in Excel, PowerPoint, and financial software\nDegree-level education with outstanding academic achievements, preferably in finance or a related field\nHighly ambitious and motivated, eager for significant exposure, and responsibility with top-tier clients in a dynamic environment\nExceptional written and verbal communication skills, demonstrating attention to detail and the ability to manage multiple workstreams under pressure\nA collaborative, entrepreneurial, and goal-oriented team player, willing to meet challenging deadlines\nWhat we offer you:\n100% Company sponsored medical, dental, and vision insurance\n25 Paid vacation and sick time\nCompany-paid life insurance\nCompany-paid STD/LTD\nPaid parental leave\n401(k) plan with company match\nGym membership discounts\nApply now and join our Team \u2013\nwe look forward to receiving your application!\nWho We Are:\nBerenberg Capital Markets LLC (BCM) is a New York based FINRA member broker-dealer, and wholly owned independent subsidiary of Joh. Berenberg, Gossler & Co. KG (Berenberg), one of Europe\u2019s leading privately-owned banks, established in 1590. Together, BCM and Berenberg have built a franchise known for its \u201cclient first\u201d approach and a global reputation of high-quality coverage of both corporate and institutional clients. Leveraging our global network of institutional investors and deep corporate relationships, we developed a track record of raising capital on US exchange\u2019s raising over $27 billion across more than 80 transactions since opening our Equity Capital Markets division in 2018. Building on its strength and expertise across multiple industries, BCM continues to expand the breadth of Sales, Trading, and Investment Banking services it offers to better assist its institutional and corporate clients\u2019 access to the global equity markets. BCM adopts the same principles as its parent company and is committed to building long-term relationships with its clients based on high levels of accountability, responsibility, insight, vision, and expertise.\nWe place great importance on working on site, as we believe that being together in the office not only fosters creativity and efficiency, but also strengthens network and builds trusting, collegial relationships. For us, this forms foundation for productive and successful work. Together we collaborate to shape our business and fulfil our ambitious goals.\nWe welcome you to join us in our commitment to always do the right thing for our people, clients and our business\n- Our future is where you take us!\nWe will only accept applications submitted through our online application management system on the website.\nWe\u2019re committed to finding reasonable accommodations for candidates who require adjustments during our recruiting process. Please contact us directly on recruitment@berenberg.com to discuss.\nBCM provides Equal Employment Opportunities (EEO) to all employees and applicants without regard to their actual or perceived age, race, creed, religious belief, color, gender, sexual orientation, gender identity, partnership status, marital status, physical or mental disability, national origin, alienage or citizenship status, military or veteran status, genetic predisposition or carrier status, or engaging in protected activity (such as opposition to prohibited discrimination or participation in proceedings covered by the anti-discrimination statutes) or any other characteristic protected by applicable federal, state and local law. BCM complies with applicable state and local laws governing non-discrimination in employment in every location in which the Company has facilities. This policy applies to all terms and conditions of employment, including hiring, placement, promotion, termination, layoff, recall, transfer, leaves of absence, compensation and training.\nSalary will vary based on role, education, level of experience, and expertise ranging between $90,000 to $115,000 as a base salary with eligibility for a discretionary annual bonus plus comprehensive benefits package.\nBack to job list\nApply\nShare this job:\nShare Investment Banking Analyst with a friend via e-mail",
        "application_url": "https://berenberg.avature.net/en_GB/careers/Login?jobId=2619",
        "metadata": {
            "Country": "USA",
            "City": "New York",
            "Type of role": "Professional",
            "Working time": "Full-time",
            "Type of contract": "Permanent",
            "Remaining openings": "1"
        },
        "link": "https://berenberg.avature.net/en_GB/careers/JobDetail/Investment-Banking-Analyst/2619"
    },
    {
        "title": null,
        "description_html": null,
        "description_text": "Java / Kotlin Developer* Digital Assets\nGeneral information\nCountry\nGermany\nCity\nHamburg\nType of role\nProfessional\nWorking time\nFull-time\nType of contract\nPermanent\nRemaining openings\n1\nDescription & Requirements\nF\u00fcr unser Programm\nCorporate Banking & Credit Risk Technology\nam\nStandort Hamburg\nsuchen wir zum\nn\u00e4chstm\u00f6glichen Zeitpunkt\ndich als\nJava / Kotlin Developer* Digital Assets\nInnovation & Technology @ Berenberg.\nIn einer \u00c4ra, in der Digitalisierung und moderne IT-Infrastrukturen das Banking revolutionieren, gestalten wir eine technologiegest\u00fctzte Bank, in der du als IT-Profi eng mit unseren Gesch\u00e4ftsbereichen zusammenarbeitest. Unsere Technology-Teams bieten dir ein Umfeld, das dich vor spannende Herausforderungen stellt \u2013 sei es durch den Support und die Weiterentwicklung von Legacy-Systemen oder die Einf\u00fchrung moderner Technologien wie KI, Machine Learning und hochgradig automatisierte Handelsapplikationen.\nUnsere IT-Abteilung mit etwa 300 Mitarbeitern arbeitet gr\u00f6\u00dftenteils agil nach einem Scrumban-Ansatz und deckt Bereiche wie Cloud Computing, Cybersecurity, Operations, Process and Governance, Software Development und Architecture ab. Wir sind besonders stolz darauf, fast alle unsere Applikationen Inhouse zu entwickeln, was uns eine einzigartige Flexibilit\u00e4t und Innovationskraft verleiht. Unser Tech Stack umfasst moderne Technologien wie Java, Kotlin, TypeScript und Python, CI/CD-Pipelines, Container, Kubernetes sowie Azure Cloud, Azure SQL Database und Oracle Datenbank mit PL/SQL.\nWelche Aufgaben erwarten Dich?\nEntwicklung und Erweiterung von Produktfeatures f\u00fcr unsere Plattform \u201eDigital Assets\u201c\nMa\u00dfgebliche Mitgestaltung unserer langfristigen Softwarearchitektur\nBetreuung der Plattform in einem dynamischen, internationalen Umfeld\nAktive Mitarbeit bei Evaluation und Testen innovativer Technologien und Trends\nWen suchen wir?\nErfolgreich abgeschlossene Ausbildung zum Fachinformatiker f\u00fcr Anwendungsentwicklung bzw. abgeschlossenes Studium der Informatik oder Wirtschaftsinformatik\nFachliches Interesse an Digital Assets / Kryptow\u00e4hrungen\nSehr gute Kenntnisse in Java oder Kotlin\nPraktische Erfahrung in der Entwicklung REST-basierter Webservices (z.B. SpringBoot)\nOffenheit f\u00fcr neue (Frontend-) Frameworks und Sprachen sowie gute Kenntnisse in relationalen Datenbanken\nSehr gute Deutsch- und gute Englischkenntnisse in Wort und Schrift\nWas wir Dir bieten:\nFlexible Arbeitszeiten innerhalb einer 39-Stunden-Woche\n30 Tage Jahresurlaub sowie zus\u00e4tzliche freie Tage am 24. und 31. Dezember\nVielseitiges und spannendes Aufgabengebiet in einem modernen und dynamischen Umfeld sowie ein wertsch\u00e4tzendes Betriebsklima\nGezielte F\u00f6rderung durch interne und externe Schulungs- und Entwicklungsprogramme\nBerenberg-Patensystem f\u00fcr ein strukturiertes und reibungsloses Onboarding\nVielf\u00e4ltige Zusch\u00fcsse (z. B. Deutschlandticket, JobRad, verm\u00f6genswirksame Leistungen, betriebliche Altersvorsorge, Essenszusch\u00fcsse bzw. Betriebsrestaurant in Hamburg)\nZus\u00e4tzliche Leistungen wie Familienservice, Arbeitszeitkonto (z. B. f\u00fcr Sabbaticals), betriebliche Sozialleistungen, Gesundheits- und Sportprogramme\nBewirb dich jetzt online und werde Teil des Teams \u2013\nwir freuen uns auf deine Bewerbung!\nWir sind eine f\u00fchrende europ\u00e4ische Privatbank mit \u00fcber 430 Jahren Erfahrung und einer tief verwurzelten Geschichte, aber wir gestalten und investieren noch immer in Zukunft. Unser Fortschritt und unsere Entwicklung werden von unseren Mitarbeitern vorangetrieben. Wir ermutigen sie, neue Ans\u00e4tze auszuprobieren, ihre Meinung zu \u00e4u\u00dfern und auf ihre eigene Art und Weise erfolgreich zu sein.\nWir bieten ihnen die M\u00f6glichkeit, ihre Talente zu entwickeln, verschiedene Karrierewege zu erkunden und ihr Potenzial voll auszusch\u00f6pfen.\nWir sind ein ehrgeiziges, zukunftsorientiertes Unternehmen, das auf jahrhundertealte Traditionen zur\u00fcckgreift und auf Innovation baut. Du findest bei uns eine Kultur vor, die Menschen dazu ermutigt, unabh\u00e4ngig zu denken, unternehmerisch zu handeln und den Status quo in Frage zu stellen. Wir legen gro\u00dfen Wert auf die Zusammenarbeit vor Ort \u2013 unser B\u00fcro ist ein zentraler Ort des Dialogs, der Innovation und des gemeinsamen Wachstums. Gemeinsam arbeiten wir daran, unser Gesch\u00e4ft zu gestalten und unsere ehrgeizigen Ziele zu erreichen.\nWir freuen uns, wenn du dich uns anschlie\u00dft, um stets das Richtige f\u00fcr unsere Mitarbeiter, Kunden und unser Unternehmen zu tun \u2013\nOur future is where you take us!\nAus organisatorischen Gr\u00fcnden nehmen wir nur Bewerbungen an, die uns \u00fcber unser Online-Bewerbermanagementsystem auf der Website erreichen.\n*Aus Gr\u00fcnden der besseren Lesbarkeit wird auf die gleichzeitige Verwendung mehrgeschlechtlicher Sprachformen verzichtet. S\u00e4mtliche Personenbezeichnungen gelten gleichwohl f\u00fcr jegliches Geschlecht. Bei uns sind alle Bewerber willkommen, unabh\u00e4ngig von Geschlecht, Nationalit\u00e4t, ethnischer Herkunft, sozialem Hintergrund, Behinderung, Religion, Alter oder sexueller Orientierung. Bei Fragen wende dich bitte an unser Recruitment-Team unter recruitment@berenberg.de.\nBack to job list\nApply\nShare this job:\nShare Java / Kotlin Developer* Digital Assets with a friend via e-mail",
        "application_url": "https://berenberg.avature.net/en_GB/careers/Login?jobId=2766",
        "metadata": {
            "Country": "Germany",
            "City": "Hamburg",
            "Type of role": "Professional",
            "Working time": "Full-time",
            "Type of contract": "Permanent",
            "Remaining openings": "1"
        },
        "link": "https://berenberg.avature.net/en_GB/careers/JobDetail/Java-Kotlin-Developer-Digital-Assets/2766"
    },
    {
        "title": null,
        "description_html": null,
        "description_text": "Dual Studierende* f\u00fcr den Studiengang Informatik B.Sc. (BHH)  zum 01.08.2026, Hamburg\nGeneral information\nCountry\nGermany\nCity\nHamburg\nType of role\nDual Student\nWorking time\nFull-time\nType of contract\nDual Study Programme\nRemaining openings\n3\nDescription & Requirements\nF\u00fcr unsere studienintegrierende Ausbildung suchen wir f\u00fcr unseren Ha\nuptsitz zum\n1. August 2026\nDoppelabschluss Informatik:\nDual Studierende* f\u00fcr den Studiengang Informatik (Bachelor of Science, B.Sc.)\nInklusive\n: Ausbildung zum Fachinformatiker* in Kooperation mit der Beruflichen Hochschule Hamburg (BHH)\nUnsere studienintegrierende Ausbildung bietet Ihnen die einmalige Gelegenheit, theoretische Kenntnisse aus einem Hochschulstudium mit einer praxisnahen Berufsausbildung zu kombinieren. Sie erwerben nicht nur den Bachelor of Science (B.Sc.) im Bereich Informatik, sondern erhalten gleichzeitig eine umfassende Berufsausbildung zum Fachinformatiker.\nWie funktioniert die studienintegrierende Ausbildung?\nSie wechseln      regelm\u00e4\u00dfig zwischen dem Studium an der Beruflichen Hochschule Hamburg      (BHH), der Berufsschule und den Praxisphasen in den Fachabteilungen bei      Berenberg.\nErfahrene      Ausbilder und Ausbildungsbeauftragte begleiten Sie durch die gesamte      Ausbildung, f\u00f6rdern Ihre pers\u00f6nliche und fachliche Entwicklung und stehen      Ihnen bei Fragen und Herausforderungen zur Seite.\nDie direkte      Einbindung in unsere Teams gew\u00e4hrt Ihnen wertvolle Einblicke in die Praxis      und bereitet Sie optimal auf Ihren Berufseinstieg vor.\nBesonderheiten der studienintegrierenden Ausbildung:\nSie erwerben      gleichzeitig einen Bachelor-Abschluss und eine anerkannte Berufsausbildung      zum Fachinformatiker.\nDie      studienintegrierende Ausbildung findet an drei Lernorten statt: an der      Beruflichen Hochschule Hamburg (BHH), an der Berufsschule und im Office      von Berenberg.\nDas      erworbene theoretische Wissen wird direkt in den Abteilungen angewendet,      was eine enge Verbindung zwischen Studium und Berufspraxis erm\u00f6glicht.\nSie haben      die Chance, direkt in verantwortungsvolle Positionen einzusteigen oder      weitere akademische Qualifikationen zu erwerben.\nWelche Aufgaben erwarten Sie?\nIn Ihren Praxisphasen sammeln Sie vielf\u00e4ltige Eindr\u00fccke und erhalten      einen wertvollen Einblick in unseren Bereich \u201aGlobal Technology\u2018.\nM\u00f6gliche Eins\u00e4tze: Softwareentwicklung und Projektmanagement/Business      Analyse, Infrastrukturbereiche (\nu. a. Systemtechnik      sowie Windows/Netzwerk/UNIX/Cloud/ Datenbankadministration)\nSie arbeiten aktiv und konstruktiv mit und eignen sich      praxisorientiertes Wissen an, welches Sie idealerweise mit den      theoretischen Inhalten des Studiums verkn\u00fcpfen k\u00f6nnen.\nDie M\u00f6glichkeit bei der Mitarbeit bei spannenden Projekten (z. B. Zukunftstag).\nWen suchen wir?\nAusgepr\u00e4gtes Interesse an innovativen Technologien und Informatik      (ggfs. erste Kenntnisse in objektorientierten Programmiersprachen oder in      der Systemintegration)\nSpa\u00df an selbstst\u00e4ndiger und abwechslungsreicher Arbeit\nAusgepr\u00e4gte Kommunikationsf\u00e4higkeit und Freude an Teamarbeit\nEin (Fach-)Abitur mit guten Leistungen\nWas wir Ihnen bieten:\nEine qualitativ hochwertige und abwechslungsreiche Ausbildung im internationalen Umfeld verbunden mit sehr guten \u00dcbernahmechancen\nIndividuelle Unterst\u00fctzung unserer dual Studierenden durch Ausbilder und Ausbildungsbeauftragte\nEine gute Vorbereitung auf den Berufseinstieg, z. B. durch die direkte Integration in unsere Teams\nSpannende Azubi-Events, z. B. Einf\u00fchrungsveranstaltungen, Workshops und Co.\n\u2026und weitere Vorteile, wie ein attraktives, tarifliches Azubi-Gehalt, monatlich 40,-\u20ac verm\u00f6genswirksame Leistungen, eine betriebliche Altersvorsorge, einen j\u00e4hrlichen Urlaubsanspruch von 30 Tagen, vielf\u00e4ltige Zusch\u00fcsse f\u00fcr z.B. Deutschlandticket und die Teilnahme an Seminaren und Trainings\nBewerben Sie sich jetzt online und werden Sie Teil des Teams \u2013\nwir freuen uns auf Ihre Bewerbung!\nAls eine f\u00fchrende europ\u00e4ische Privatbank mit \u00fcber 430 Jahren Erfahrung blicken wir auf eine lange Unternehmensgeschichte zur\u00fcck. Gleichzeitig gestalten wir mit umfassenden Investitionen aktiv unsere Zukunft. Grundlage f\u00fcr unseren Fortschritt und unsere Weiterentwicklung sind unsere Mitarbeiter. Wir ermutigen diese, neue Ans\u00e4tze auszuprobieren, ihre Ideen mit einzubringen und ihren eigenen Weg zum Erfolg bei uns zu gehen.\nWir sind ein ambitioniertes, zukunftsorientiertes Unternehmen, das jahrhundertelange Erfahrung und Innovationskraft vereint. Bei uns erleben Sie eine Kultur, die zum selbstst\u00e4ndigen Denken anregt, Unternehmertum f\u00f6rdert und dazu ermutigt, den Status quo zu hinterfragen. Sie treffen hier auf talentierte Kollegen, die es gewohnt sind, Verantwortung zu \u00fcbernehmen, und gemeinsam an einem Strang ziehen, um Ergebnisse zu erzielen.\nWerden Sie Teil von Berenberg und arbeiten Sie mit uns gemeinsam daran, das Richtige f\u00fcr unsere Kunden, unser Gesch\u00e4ft und unsere Mitarbeiter zu tun \u2013\nOur future is where you take us!\nAus organisatorischen Gr\u00fcnden nehmen wir nur Bewerbungen an, die uns \u00fcber unser Online-Bewerbermanagementsystem auf der Website erreichen.\n*Aus Gr\u00fcnden der besseren Lesbarkeit wird auf die gleichzeitige Verwendung mehrgeschlechtlicher Sprachformen verzichtet. S\u00e4mtliche Personenbezeichnungen gelten gleichwohl f\u00fcr jegliches Geschlecht.\nBei uns sind alle Bewerbungen willkommen, unabh\u00e4ngig von Geschlecht, Nationalit\u00e4t, ethnischer Herkunft, sozialem Hintergrund, Behinderung, Religion, Alter oder sexueller Orientierung.\nBei Fragen wenden Sie sich bitte an unser Recruitment-Team unter recruitment@berenberg.de.\nBack to job list\nApply\nShare this job:\nShare Dual Studierende* f\u00fcr den Studiengang Informatik B.Sc. (BHH)  zum 01.08.2026, Hamburg with a friend via e-mail",
        "application_url": "https://berenberg.avature.net/en_GB/careers/Login?jobId=2569",
        "metadata": {
            "Country": "Germany",
            "City": "Hamburg",
            "Type of role": "Dual Student",
            "Working time": "Full-time",
            "Type of contract": "Dual Study Programme",
            "Remaining openings": "3"
        },
        "link": "https://berenberg.avature.net/en_GB/careers/JobDetail/Dual-Studierende-f-r-den-Studiengang-Informatik-B-Sc-BHH-zum-01-08-2026-Hamburg/2569"
    },
    {
        "title": null,
        "description_html": null,
        "description_text": "Auszubildende* zum Fachinformatiker mit Schwerpunkt Anwendungsentwicklung zum 01.08.2026, Hamburg\nGeneral information\nCountry\nGermany\nCity\nHamburg\nType of role\nApprentice\nWorking time\nFull-time\nType of contract\nApprenticeship\nRemaining openings\n1\nDescription & Requirements\nF\u00fcr unsere Ausbildung in\nHamburg\nsuchen wir zum\n1. August 2026\nDich als\nAuszubildenden* zum Fachinformatiker mit Schwerpunkt Anwendungsentwicklung\nInnovation & Technology @ Berenberg\nIn einer \u00c4ra, in der Digitalisierung und moderne IT-Infrastrukturen das Banking revolutionieren, gestalten wir eine technologiegest\u00fctzte Bank, in der du als IT-Profi eng mit unseren Gesch\u00e4ftsbereichen zusammenarbeitest. Unsere Technology-Teams bieten dir ein Umfeld, das dich vor spannende Herausforderungen stellt \u2013 sei es durch den Support und die Weiterentwicklung von Legacy-Systemen oder die Einf\u00fchrung moderner Technologien wie KI, Machine Learning und hochgradig automatisierte Handelsapplikationen.\nUnsere IT-Abteilung mit etwa 300 Mitarbeitern arbeitet gr\u00f6\u00dftenteils agil nach einem Scrumban-Ansatz und deckt Bereiche wie Cloud Computing, Cybersecurity, Operations, Process and Governance, Software Development und Architecture ab. Wir sind besonders stolz darauf, fast alle unsere Applikationen Inhouse zu entwickeln, was uns eine einzigartige Flexibilit\u00e4t und Innovationskraft verleiht. Unser Tech Stack umfasst moderne Technologien wie Java, Kotlin, TypeScript und Python, CI/CD-Pipelines, Container, Kubernetes sowie Azure Cloud, Azure SQL Database und Oracle Datenbank mit PL/SQL.\nWelche Aufgaben erwarten Dich?\nW\u00e4hrend Deiner Ausbildung im Global Technology Bereich bei Berenberg kannst Du Dich unter anderem auf folgende Aufgaben freuen:\nDurch Deine Mitarbeit in cross-funktionalen Teams lernst Du die verschiedenen Phasen der Softwareentwicklung kennen\nDu unterst\u00fctzt Deine Kollegen* beim Tagesgesch\u00e4ft sowie bei spannenden Projekten\nTeilnahme an aufregenden Azubi-Projekten (z. B. Umsetzung von Projekten im Rahmen der BerenbergKids Stiftung\nWen wir suchen?\nMittlerer Schulabschluss oder Fachhochschulreife/Abitur mit guten Leistungen\nInteresse an Softwareentwicklung und innovativen Technologien\nTechnisches Verst\u00e4ndnis\nSpa\u00df an selbstst\u00e4ndiger und abwechslungsreicher Arbeit\nAusgepr\u00e4gte Kommunikationsf\u00e4higkeit und Freude an Teamarbeit\nWas wir Dir bieten:\nEine qualitativ hochwertige und abwechslungsreiche Ausbildung im internationalen Umfeld verbunden mit sehr guten \u00dcbernahmechancen\nIndividuelle Unterst\u00fctzung unserer Auszubildenden und eine gute Vorbereitung auf den Berufseinstieg\nDie direkte Integration in unsere Entwicklerteams\nSpannende Azubi-Events, z. B. Einf\u00fchrungsveranstaltungen, Workshops und co.\n\u2026und weitere Vorteile, wie ein attraktives, tarifliches Azubi-Gehalt, monatlich 40,-\u20ac verm\u00f6genswirksame Leistungen, eine betriebliche Altersvorsorge, einen j\u00e4hrlichen Urlaubsanspruch von 30 Tagen, vielf\u00e4ltige Zusch\u00fcsse f\u00fcr z .B. Deutschlandticket und die Teilnahme an Seminaren und Trainings (z. B. Englischunterricht)\nBewirb Dich jetzt online und werde Teil des Teams\n\u2013 wir freuen uns auf Deine Bewerbung!\nWir sind eine f\u00fchrende europ\u00e4ische Privatbank mit \u00fcber 430 Jahren Erfahrung und einer tief verwurzelten Geschichte, aber wir gestalten und investieren noch immer in Zukunft. Unser Fortschritt und unsere Entwicklung werden von unseren Mitarbeitern vorangetrieben. Wir ermutigen Euch, neue Ans\u00e4tze auszuprobieren, Eure Meinung zu \u00e4u\u00dfern und auf Eure eigene Art und Weise erfolgreich zu sein.\nWir bieten Dir die M\u00f6glichkeit, Deine Talente zu entwickeln, verschiedene Karrierewege zu erkunden und Dein Potenzial voll auszusch\u00f6pfen.\nWir sind ein ehrgeiziges, zukunftsorientiertes Unternehmen, das auf jahrhundertealte Traditionen zur\u00fcckgreift und auf Innovation baut. Du findest bei uns eine Kultur vor, die Menschen dazu ermutigt, unabh\u00e4ngig zu denken, unternehmerisch zu handeln und den Status quo in Frage zu stellen. Gemeinsam arbeiten wir daran, unser Gesch\u00e4ft zu gestalten und unsere ehrgeizigen Ziele zu erreichen.\nWir freuen uns, wenn Du Dich uns anschlie\u00dft, um stets das Richtige f\u00fcr unsere Mitarbeiter, Kunden und unser Unternehmen zu tun \u2013\nOur future is where you take us!\nAus organisatorischen Gr\u00fcnden nehmen wir nur Bewerbungen an, die uns \u00fcber unser Online-Bewerbermanagementsystem auf der Website erreichen.\n*Aus Gr\u00fcnden der besseren Lesbarkeit wird auf die gleichzeitige Verwendung mehrgeschlechtlicher Sprachformen verzichtet. S\u00e4mtliche Personenbezeichnungen gelten gleichwohl f\u00fcr jegliches Geschlecht.\nBei uns sind alle Bewerber willkommen, unabh\u00e4ngig von Geschlecht, Nationalit\u00e4t, ethnischer Herkunft, sozialem Hintergrund, Behinderung, Religion, Alter oder sexueller Orientierung.\nBei Fragen wende Dich bitte an unser Recruitment-Team unter recruitment@berenberg.de\nBack to job list\nApply\nShare this job:\nShare Auszubildende* zum Fachinformatiker mit Schwerpunkt Anwendungsentwicklung zum 01.08.2026, Hamburg with a friend via e-mail",
        "application_url": "https://berenberg.avature.net/en_GB/careers/Login?jobId=2570",
        "metadata": {
            "Country": "Germany",
            "City": "Hamburg",
            "Type of role": "Apprentice",
            "Working time": "Full-time",
            "Type of contract": "Apprenticeship",
            "Remaining openings": "1"
        },
        "link": "https://berenberg.avature.net/en_GB/careers/JobDetail/Auszubildende-zum-Fachinformatiker-mit-Schwerpunkt-Anwendungsentwicklung-zum-01-08-2026-Hamburg/2570"
    },
    {
        "title": null,
        "description_html": null,
        "description_text": "Auszubildende* zum Fachinformatiker mit Schwerpunkt Systemintegration zum 01.08.2026, Hamburg\nGeneral information\nCountry\nGermany\nCity\nHamburg\nType of role\nApprentice\nWorking time\nFull-time\nType of contract\nApprenticeship\nRemaining openings\n2\nDescription & Requirements\nF\u00fcr unsere Ausbildung in Hamburg suchen wir zum\n1. August 2026\nDich als\nAuszubildenden* zum Fachinformatiker mit Schwerpunkt Systemintegration\nInnovation & Technology @ Berenberg\nIn einer \u00c4ra, in der Digitalisierung und moderne IT-Infrastrukturen das Banking revolutionieren, gestalten wir eine technologiegest\u00fctzte Bank, in der du als IT-Profi eng mit unseren Gesch\u00e4ftsbereichen zusammenarbeitest. Unsere Technology-Teams bieten dir ein Umfeld, das dich vor spannende Herausforderungen stellt \u2013 sei es durch den Support und die Weiterentwicklung von Legacy-Systemen oder die Einf\u00fchrung moderner Technologien wie KI, Machine Learning und hochgradig automatisierte Handelsapplikationen.\nUnsere IT-Abteilung mit etwa 300 Mitarbeitern arbeitet gr\u00f6\u00dftenteils agil nach einem Scrumban-Ansatz und deckt Bereiche wie Cloud Computing, Cybersecurity, Operations, Process and Governance, Software Development und Architecture ab. Wir sind besonders stolz darauf, fast alle unsere Applikationen Inhouse zu entwickeln, was uns eine einzigartige Flexibilit\u00e4t und Innovationskraft verleiht. Unser Tech Stack umfasst moderne Technologien wie Java, Kotlin, TypeScript und Python, CI/CD-Pipelines, Container, Kubernetes sowie Azure Cloud, Azure SQL Database und Oracle Datenbank mit PL/SQL.\nWelche Aufgaben erwarten Dich?\nW\u00e4hrend Deiner Ausbildung im Global Technology Bereich bei Berenberg kannst Du Dich unter anderem auf folgende Aufgaben freuen:\nDu arbeitest aktiv mit und lernst so verschiedene Bereiche der      Informations- und Telekommunikationstechniksysteme, u. a. die      Systemtechnik sowie Windows/Netzwerk/Infrastruktur UNIX, die      Datenbankadministration und das Rechenzentrum kennen\nDurch Deine Mitarbeit in cross-funktionalen Teams erh\u00e4ltst Du\u00a0Einblicke      in unsere Systemarchitektur, Hardware, Betriebssysteme und Netzwerke\nDu unterst\u00fctzt Deine Kollegen* beim Tagesgesch\u00e4ft sowie bei spannenden      Projekten\nTeilnahme an aufregenden Azubi-Projekten (z. B. Umsetzung von      Projekten im Rahmen der BerenbergKids Stiftung\nWen suchen wir?\nMittlerer Schulabschluss oder Fachhochschulreife/Abitur mit guten      Leistungen\nInteresse an Systemintegration und innovativen Technologien\nTechnisches Verst\u00e4ndnis\nSpa\u00df an selbstst\u00e4ndiger und abwechslungsreicher Arbeit\nAusgepr\u00e4gte Kommunikationsf\u00e4higkeit und Freude an Teamarbeit\nWas wir Dir bieten:\nEine qualitativ hochwertige und abwechslungsreiche Ausbildung im      internationalen Umfeld verbunden mit sehr guten \u00dcbernahmechancen\nIndividuelle Unterst\u00fctzung unserer Auszubildenden und eine gute      Vorbereitung auf den Berufseinstieg\nDie direkte Integration in unsere Supportteams\nSpannende Azubi-Events, z. B. Einf\u00fchrungsveranstaltungen, Workshops      und co.\n\u2026und weitere Vorteile, wie ein attraktives, tarifliches Azubi-Gehalt,      monatlich 40,-\u20ac verm\u00f6genswirksame Leistungen, eine betriebliche      Altersvorsorge, einen j\u00e4hrlichen Urlaubsanspruch von 30 Tagen, vielf\u00e4ltige      Zusch\u00fcsse f\u00fcr z .B. Deutschlandticket und die Teilnahme      an Seminaren und Trainings (z. B. Englischunterricht)\nBewirb Dich jetzt online und werde Teil des Teams \u2013\nwir freuen uns auf Deine Bewerbung!\nWir sind eine f\u00fchrende europ\u00e4ische Privatbank mit \u00fcber 430 Jahren Erfahrung und einer tief verwurzelten Geschichte, aber wir gestalten und investieren noch immer in Zukunft. Unser Fortschritt und unsere Entwicklung werden von unseren Mitarbeitern vorangetrieben. Wir ermutigen Euch, neue Ans\u00e4tze auszuprobieren, Eure Meinung zu \u00e4u\u00dfern und auf Eure eigene Art und Weise erfolgreich zu sein.\nWir bieten Dir die M\u00f6glichkeit, Deine Talente zu entwickeln, verschiedene Karrierewege zu erkunden und Dein Potenzial voll auszusch\u00f6pfen.\nWir sind ein ehrgeiziges, zukunftsorientiertes Unternehmen, das auf jahrhundertealte Traditionen zur\u00fcckgreift und auf Innovation baut. Du findest bei uns eine Kultur vor, die Menschen dazu ermutigt, unabh\u00e4ngig zu denken, unternehmerisch zu handeln und den Status quo in Frage zu stellen. Gemeinsam arbeiten wir daran, unser Gesch\u00e4ft zu gestalten und unsere ehrgeizigen Ziele zu erreichen.\nWir freuen uns, wenn Du Dich uns anschlie\u00dft, um stets das Richtige f\u00fcr unsere Mitarbeiter, Kunden und unser Unternehmen zu tun \u2013\nOur future is where you take us!\nAus organisatorischen Gr\u00fcnden nehmen wir nur Bewerbungen an, die uns \u00fcber unser Online-Bewerbermanagementsystem auf der Website erreichen.\n*Aus Gr\u00fcnden der besseren Lesbarkeit wird auf die gleichzeitige Verwendung mehrgeschlechtlicher Sprachformen verzichtet. S\u00e4mtliche Personenbezeichnungen gelten gleichwohl f\u00fcr jegliches Geschlecht.\nBei uns sind alle Bewerber willkommen, unabh\u00e4ngig von Geschlecht, Nationalit\u00e4t, ethnischer Herkunft, sozialem Hintergrund, Behinderung, Religion, Alter oder sexueller Orientierung. Bei Fragen wende Dich bitte an unser Recruitment-Team unter recruitment@berenberg.d\ne\nBack to job list\nApply\nShare this job:\nShare Auszubildende* zum Fachinformatiker mit Schwerpunkt Systemintegration zum 01.08.2026, Hamburg with a friend via e-mail",
        "application_url": "https://berenberg.avature.net/en_GB/careers/Login?jobId=2571",
        "metadata": {
            "Country": "Germany",
            "City": "Hamburg",
            "Type of role": "Apprentice",
            "Working time": "Full-time",
            "Type of contract": "Apprenticeship",
            "Remaining openings": "2"
        },
        "link": "https://berenberg.avature.net/en_GB/careers/JobDetail/Auszubildende-zum-Fachinformatiker-mit-Schwerpunkt-Systemintegration-zum-01-08-2026-Hamburg/2571"
    },
    {
        "title": null,
        "description_html": null,
        "description_text": "Product Owner* Modern Workplace\nGeneral information\nCountry\nGermany\nCity\nHamburg\nType of role\nProfessional\nWorking time\nFull-time\nType of contract\nPermanent\nRemaining openings\n1\nDescription & Requirements\nF\u00fcr unser Programm\nWorkplace & Tech Services\nam\nStandort Hamburg\nsuchen wir zum\nn\u00e4chstm\u00f6glichen Zeitpunkt\ndich als\nProduct Owner Modern Workplace*\nInnovation & Technology @ Berenberg\nIn einer \u00c4ra, in der Digitalisierung und moderne IT-Infrastrukturen das Banking revolutionieren, gestalten wir eine technologiegest\u00fctzte Bank, in der du als IT-Profi eng mit unseren Gesch\u00e4ftsbereichen zusammenarbeitest. Unsere Technology-Teams bieten dir ein Umfeld, das dich vor spannende Herausforderungen stellt \u2013 sei es durch den Support und die Weiterentwicklung von Legacy-Systemen oder die Einf\u00fchrung moderner Technologien wie KI, Machine Learning und hochgradig automatisierte Handelsapplikationen.\nUnsere IT-Abteilung mit etwa 300 Mitarbeitern arbeitet gr\u00f6\u00dftenteils agil nach einem Scrumban-Ansatz und deckt Bereiche wie Cloud Computing, Cybersecurity, Operations, Process and Governance, Software Development und Architecture ab. Wir sind besonders stolz darauf, fast alle unsere Applikationen Inhouse zu entwickeln, was uns eine einzigartige Flexibilit\u00e4t und Innovationskraft verleiht. Unser Tech Stack umfasst moderne Technologien wie Java, Kotlin, TypeScript und Python, CI/CD-Pipelines, Container, Kubernetes sowie Azure Cloud, Azure SQL Database und Oracle Datenbank mit PL/SQL.\nDeine Rolle im Team\nAls Product Owner \u00fcbernimmst du die fachliche Verantwortung f\u00fcr die Endger\u00e4te unserer Kollegen im Bereich Modern Workplace. Dabei erarbeitest du Produktstrategien und passt das Life Cycle Management auf die Bed\u00fcrfnisse deiner Stakeholder an.\nWelche Aufgaben erwarten Dich?\nWeiterentwickeln des Produktes in Kooperation mit den relevanten Stakeholdern, dem Management und den relevanten IT Teams\nFachliches Verantwortung f\u00fcr den Modern Workplace\nPlanen, Steuern und \u00dcberwachen des Produktbudgets\nBetreuen des Product Backlogs inkl. Moderation von User Story Workshops\n\u00dcberwachen der SLAs und Produkt KPIs, sowie die regelm\u00e4\u00dfige Optimierung dieser\nEntwickeln von Sourcing Strategien (make or buy)\nWen suchen wir?\nAufgabenbezogene Berufserfahrung sowie Budget- und (internationaler) Projektverantwortung\nGrundlegende Kenntnisse in agilen Methoden\nUmfassendes Knowhow im IT-Betrieb von Client L\u00f6sungen\nInteresse an \"Leading Edge\" Technologien\nErste Erfahrung in der (fachlichen) F\u00fchrung von Mitarbeitern sowie F\u00e4higkeit\u00a0 es, Arbeitsabl\u00e4ufe zielf\u00fchrend zu strukturieren\nAusgepr\u00e4gte Kommunikationsst\u00e4rke in Deutsch und Englisch sowie die F\u00e4higkeit, Positionen situationsgerecht und adressatengerecht gegen\u00fcber internen und externen Stakeholdern zu vermitteln\nWas wir Dir bieten:\nFlexible Arbeitszeiten innerhalb einer 39-Stunden-Woche\n30 Tage Jahresurlaub sowie zus\u00e4tzliche freie Tage am 24. und 31. Dezember\nVielseitiges und spannendes Aufgabengebiet in einem modernen und dynamischen Umfeld sowie ein wertsch\u00e4tzendes Betriebsklima\nGezielte F\u00f6rderung durch interne und externe Schulungs- und Entwicklungsprogramme\nBerenberg-Patensystem f\u00fcr ein strukturiertes und reibungsloses Onboarding\nVielf\u00e4ltige Zusch\u00fcsse (z. B. Deutschlandticket, JobRad, verm\u00f6genswirksame Leistungen, betriebliche Altersvorsorge, Essenszusch\u00fcsse bzw. Betriebsrestaurant in Hamburg)\nZus\u00e4tzliche Leistungen wie Familienservice, Arbeitszeitkonto (z. B. f\u00fcr Sabbaticals), betriebliche Sozialleistungen, Gesundheits- und Sportprogramme\nBewirb dich jetzt online und werde Teil des Teams \u2013\nwir freuen uns auf deine Bewerbung!\nWir sind eine f\u00fchrende europ\u00e4ische Privatbank mit \u00fcber 430 Jahren Erfahrung und einer tief verwurzelten Geschichte, aber wir gestalten und investieren noch immer in Zukunft. Unser Fortschritt und unsere Entwicklung werden von unseren Mitarbeitern vorangetrieben. Wir ermutigen sie, neue Ans\u00e4tze auszuprobieren, ihre Meinung zu \u00e4u\u00dfern und auf ihre eigene Art und Weise erfolgreich zu sein.\nWir bieten ihnen die M\u00f6glichkeit, ihre Talente zu entwickeln, verschiedene Karrierewege zu erkunden und ihr Potenzial voll auszusch\u00f6pfen.\nWir sind ein ehrgeiziges, zukunftsorientiertes Unternehmen, das auf jahrhundertealte Traditionen zur\u00fcckgreift und auf Innovation baut. Du findest bei uns eine Kultur vor, die Menschen dazu ermutigt, unabh\u00e4ngig zu denken, unternehmerisch zu handeln und den Status quo in Frage zu stellen. Wir legen gro\u00dfen Wert auf die Zusammenarbeit vor Ort \u2013 unser B\u00fcro ist ein zentraler Ort des Dialogs, der Innovation und des gemeinsamen Wachstums. Gemeinsam arbeiten wir daran, unser Gesch\u00e4ft zu gestalten und unsere ehrgeizigen Ziele zu erreichen.\nWir freuen uns, wenn du dich uns anschlie\u00dft, um stets das Richtige f\u00fcr unsere Mitarbeiter, Kunden und unser Unternehmen zu tun \u2013\nOur future is where you take us!\nAus organisatorischen Gr\u00fcnden nehmen wir nur Bewerbungen an, die uns \u00fcber unser Online-Bewerbermanagementsystem auf der Website erreichen.\n*Aus Gr\u00fcnden der besseren Lesbarkeit wird auf die gleichzeitige Verwendung mehrgeschlechtlicher Sprachformen verzichtet. S\u00e4mtliche Personenbezeichnungen gelten gleichwohl f\u00fcr jegliches Geschlecht. Bei uns sind alle Bewerber willkommen, unabh\u00e4ngig von Geschlecht, Nationalit\u00e4t, ethnischer Herkunft, sozialem Hintergrund, Behinderung, Religion, Alter oder sexueller Orientierung. Bei Fragen wende dich bitte an unser Recruitment-Team unter recruitment@berenberg.de.\nBack to job list\nApply\nShare this job:\nShare Product Owner* Modern Workplace with a friend via e-mail",
        "application_url": "https://berenberg.avature.net/en_GB/careers/Login?jobId=2555",
        "metadata": {
            "Country": "Germany",
            "City": "Hamburg",
            "Type of role": "Professional",
            "Working time": "Full-time",
            "Type of contract": "Permanent",
            "Remaining openings": "1"
        },
        "link": "https://berenberg.avature.net/en_GB/careers/JobDetail/Product-Owner-Modern-Workplace/2555"
    },
    {
        "title": null,
        "description_html": null,
        "description_text": "Database Administrator Oracle\nGeneral information\nCountry\nUnited Kingdom\nCity\nLondon\nType of role\nProfessional\nWorking time\nFull-time\nType of contract\nPermanent\nRemaining openings\n1\nDescription & Requirements\nFor our\nInnovation & Technology\ndepartment in\nLondon\nwe are looking to hire a:\nDatabase Administrator Oracle\nInnovation & Technology @ Berenberg\nIn an era where digitalisation and modern IT infrastructure is revolutionizing banking, we are shaping a technology-driven bank in which you as an IT professional will work closely with our business units. Our technology teams offer you an environment that will present you with exciting challenges - be it through the support and further development of legacy systems or the introduction of modern technologies such as AI, machine learning and highly automated trading applications.\nWhat will you do?\nAdministration, configuration, and implementation of databases in a demanding high-availability environment (Oracle)\nPlanning and provisioning of new databases\nAutomation of existing processes\nPerforming database migrations, patches, and upgrades\nConsulting and support of projects\nEnsuring that storage and archiving procedures work smoothly\nWho are we looking for?\nSuccessfully completed vocational training as an IT specialist or a degree in the IT field\nIn-depth experience with Oracle RAC\nIdeally, initial experience in database administration, especially with relational database systems\nKnowledge of SQL, PL/SQL, Ansible, and scripting (Shell) is an advantage\nKnow-how in Linux is a plus\nVery good written and spoken English skills\nWhat we offer you:\nPrivate pension plan - 10% of base salary contribution by Berenberg\nGenerous 30 day holiday allowance\nPrivate Health Insurance\nLife Insurance scheme\nFlexible working hours\nEnhanced parental leave policies\nEmployee Assistance Programme offering counselling sessions related to mental health, financial wellbeing and other topics\nApply online now to join our team \u2013\nwe look forward to receiving your application!\nWe are a leading European private bank, with over 430 years of experience and deep rooted history, but we are still shaping and heavily investing in our future. Our progress and evolution are driven by our people. We encourage them to try new approaches, voice their opinions and achieve success in their own way.\nWe provide opportunities for them to develop their talents, explore different career paths and achieve their full potential.\nWe\u2019re an ambitious, forward-looking business, backed by centuries of tradition and built on innovation. You\u2019ll find a culture that encourages people to think independently, act entrepreneurially and challenge the status quo.\nWe place great importance on working on site, as we believe that being together in the office not only fosters creativity and efficiency, but also strengthens networks and builds trusting, collegial relationships. For us, this forms the foundation for productive and successful work. Together we collaborate to shape our business and fulfil our ambitious goals.\nWe welcome you to join us in our commitment to always do the right thing for our people, clients and our business\n\u2013 Our future is where you take us!\nWe will only accept applications submitted through our online application management system on the website.\nBerenberg is an Equal Opportunities Employer and prides itself on being a modern, dynamic and internationally orientated organisation. We value the rich diversity, skills and abilities and creative potential that people from differing backgrounds and experiences bring to the workplace. Every employee plays a vital role in providing quality service to all our customers and helping to create and inclusive working environment, where everyone can realise their full potential. We\u2019re committed to finding reasonable accommodations for candidates who require adjustments during our recruiting process. Please contact us directly on recruitment@berenberg.com to discuss.\nBack to job list\nApply\nShare this job:\nShare Database Administrator Oracle with a friend via e-mail",
        "application_url": "https://berenberg.avature.net/en_GB/careers/Login?jobId=2554",
        "metadata": {
            "Country": "United Kingdom",
            "City": "London",
            "Type of role": "Professional",
            "Working time": "Full-time",
            "Type of contract": "Permanent",
            "Remaining openings": "1"
        },
        "link": "https://berenberg.avature.net/en_GB/careers/JobDetail/Database-Administrator-Oracle/2554"
    },
    {
        "title": null,
        "description_html": null,
        "description_text": "IAM / PAM Specialist*\nGeneral information\nCountry\nGermany\nCity\nHamburg\nType of role\nProfessional\nWorking time\nFull-time\nType of contract\nPermanent\nRemaining openings\n1\nDescription & Requirements\nF\u00fcr unser Programm\nOrganisational Development & Governance\nam Standort\nHamburg\nsuchen wir zum\nn\u00e4chstm\u00f6glichen Zeitpunkt\ndich als\nIAM / PAM Specialist*\nInnovation & Technology @ Berenberg.\nIn einer \u00c4ra, in der Digitalisierung und moderne IT-Infrastrukturen das Banking revolutionieren, gestalten wir eine technologiegest\u00fctzte Bank, in der du als IT-Profi eng mit unseren Gesch\u00e4ftsbereichen zusammenarbeitest. Unsere Technology-Teams bieten dir ein Umfeld, das dich vor spannende Herausforderungen stellt \u2013 sei es durch den Support und die Weiterentwicklung von Legacy-Systemen oder die Einf\u00fchrung moderner Technologien wie KI, Machine Learning und hochgradig automatisierte Handelsapplikationen.\nUnsere IT-Abteilung mit etwa 300 Mitarbeitern arbeitet gr\u00f6\u00dftenteils agil nach einem Scrumban-Ansatz und deckt Bereiche wie Cloud Computing, Cybersecurity, Operations, Process and Governance, Software Development und Architecture ab. Wir sind besonders stolz darauf, fast alle unsere Applikationen Inhouse zu entwickeln, was uns eine einzigartige Flexibilit\u00e4t und Innovationskraft verleiht. Unser Tech Stack umfasst moderne Technologien wie Java, Kotlin, TypeScript und Python, CI/CD-Pipelines, Container, Kubernetes sowie Azure Cloud, Azure SQL Database und Oracle Datenbank mit PL/SQL.\nWelche Aufgaben erwarten Dich?\nUnternehmensweiter Ausbau eines ganzheitlichen Zielbilds zu IAM und PAM zur Vereinheitlichung, Zusammenf\u00fchrung und Definition der Berechtigungsmanagement-Prozesse\nKonzeptionelle Weiterentwicklung, Optimierung und Automatisierung des Berechtigungsmanagement sowie Entwicklung von Standards im IAM- und PAM-Umfeld\nUnterst\u00fctzung bei der Anbindung von IAM- und PAM-Systemen an bestehende IT Landschaft (z.B. Active Directory, Cloud-Plattformen wie Azure AD)\nBeratung von Anwendern, Rollenverantwortlichen und F\u00fchrungskr\u00e4ften bei technischen sowie prozessualen Fragestellungen und Koordination und Weiterentwicklung relevanter Prozesse im IAM/PAM Kontext\nSicherheitsrichtlinien & Compliance: Unterst\u00fctzung bei der Erarbeitung und Erstellung von Konzepten sowie Dokumentationen auf Basis von regulatorischen Anforderungen sowie Definition von kritischen Berechtigungen\nWen suchen wir?\nErfahrung mit einem g\u00e4ngigen Identit\u00e4ts- und Access-Management-Systemen (wie Ping Identity, SailPoint, Omada) sowie spezialisierten Privileged Access Management-Tools (wie CyberArk, BeyondTrust, Delinea)\nGrundkenntnisse in Verzeichnisdiensten (LDAP, AD, AAD) und Authentifizierungsmethoden (MFA, SSO, OAuth, SAML, Kerberos) sind von Vorteil\nVerst\u00e4ndnis f\u00fcr Zero Trust, Least Privilege und Role-Based Access Control (RBAC)\nErfahrung mit IT-Sicherheitsstandards und Compliance Anforderungen im Banken- oder Versicherungsumfeld\nTeamf\u00e4higkeit und Kommunikation mit technischen und nicht-technischen Stakeholdern\nSehr gute Deutsch- und Englischkenntisse in Wort und Schrift\nWas wir Dir bieten:\nFlexible Arbeitszeiten innerhalb einer 39-Stunden-Woche\n30 Tage Jahresurlaub sowie zus\u00e4tzliche freie Tage am 24. und 31. Dezember\nVielseitiges und spannendes Aufgabengebiet in einem modernen und dynamischen Umfeld sowie ein wertsch\u00e4tzendes Betriebsklima\nGezielte F\u00f6rderung durch interne und externe Schulungs- und Entwicklungsprogramme\nBerenberg-Patensystem f\u00fcr ein strukturiertes und reibungsloses Onboarding\nVielf\u00e4ltige Zusch\u00fcsse (z. B. Deutschlandticket, JobRad, verm\u00f6genswirksame Leistungen, betriebliche Altersvorsorge, Essenszusch\u00fcsse bzw. Betriebsrestaurant in Hamburg)\nZus\u00e4tzliche Leistungen wie Familienservice, Arbeitszeitkonto (z. B. f\u00fcr Sabbaticals), betriebliche Sozialleistungen, Gesundheits- und Sportprogramme\nBewirb dich jetzt online und werde Teil des Teams \u2013\nwir freuen uns auf deine Bewerbung!\nWir sind eine f\u00fchrende europ\u00e4ische Privatbank mit \u00fcber 430 Jahren Erfahrung und einer tief verwurzelten Geschichte, aber wir gestalten und investieren noch immer in Zukunft. Unser Fortschritt und unsere Entwicklung werden von unseren Mitarbeitern vorangetrieben. Wir ermutigen sie, neue Ans\u00e4tze auszuprobieren, ihre Meinung zu \u00e4u\u00dfern und auf ihre eigene Art und Weise erfolgreich zu sein.\nWir bieten ihnen die M\u00f6glichkeit, ihre Talente zu entwickeln, verschiedene Karrierewege zu erkunden und ihr Potenzial voll auszusch\u00f6pfen.\nWir sind ein ehrgeiziges, zukunftsorientiertes Unternehmen, das auf jahrhundertealte Traditionen zur\u00fcckgreift und auf Innovation baut. Du findest bei uns eine Kultur vor, die Menschen dazu ermutigt, unabh\u00e4ngig zu denken, unternehmerisch zu handeln und den Status quo in Frage zu stellen. Wir legen gro\u00dfen Wert auf die Zusammenarbeit vor Ort \u2013 unser B\u00fcro ist ein zentraler Ort des Dialogs, der Innovation und des gemeinsamen Wachstums. Gemeinsam arbeiten wir daran, unser Gesch\u00e4ft zu gestalten und unsere ehrgeizigen Ziele zu erreichen.\nWir freuen uns, wenn du dich uns anschlie\u00dft, um stets das Richtige f\u00fcr unsere Mitarbeiter, Kunden und unser Unternehmen zu tun \u2013\nOur future is where you take us!\nAus organisatorischen Gr\u00fcnden nehmen wir nur Bewerbungen an, die uns \u00fcber unser Online-Bewerbermanagementsystem auf der Website erreichen.\n*Aus Gr\u00fcnden der besseren Lesbarkeit wird auf die gleichzeitige Verwendung mehrgeschlechtlicher Sprachformen verzichtet. S\u00e4mtliche Personenbezeichnungen gelten gleichwohl f\u00fcr jegliches Geschlecht. Bei uns sind alle Bewerber willkommen, unabh\u00e4ngig von Geschlecht, Nationalit\u00e4t, ethnischer Herkunft, sozialem Hintergrund, Behinderung, Religion, Alter oder sexueller Orientierung. Bei Fragen wende dich bitte an unser Recruitment-Team unter recruitment@berenberg.de.\nBack to job list\nApply\nShare this job:\nShare IAM / PAM Specialist* with a friend via e-mail",
        "application_url": "https://berenberg.avature.net/en_GB/careers/Login?jobId=2527",
        "metadata": {
            "Country": "Germany",
            "City": "Hamburg",
            "Type of role": "Professional",
            "Working time": "Full-time",
            "Type of contract": "Permanent",
            "Remaining openings": "1"
        },
        "link": "https://berenberg.avature.net/en_GB/careers/JobDetail/IAM-PAM-Specialist/2527"
    },
    {
        "title": null,
        "description_html": null,
        "description_text": "(Senior) QA Test Manager*\nGeneral information\nCountry\nGermany\nCity\nHamburg\nType of role\nProfessional\nWorking time\nFull-time\nType of contract\nPermanent\nRemaining openings\n1\nDescription & Requirements\nF\u00fcr unser Programm\nTransaction Technology\nam\nStandort Hamburg\nsuchen wir zum\nn\u00e4chstm\u00f6glichen Zeitpunkt\ndich als\n(Senior) QA Test Manager*\nInnovation & Technology @ Berenberg\nIn einer \u00c4ra, in der Digitalisierung und moderne IT-Infrastrukturen das Banking revolutionieren, gestalten wir eine technologiegest\u00fctzte Bank, in der du als IT-Profi eng mit unseren Gesch\u00e4ftsbereichen zusammenarbeitest. Unsere Technology-Teams bieten dir ein Umfeld, das dich vor spannende Herausforderungen stellt \u2013 sei es durch den Support und die Weiterentwicklung von Legacy-Systemen oder die Einf\u00fchrung moderner Technologien wie KI, Machine Learning und hochgradig automatisierte Handelsapplikationen.\nUnsere IT-Abteilung mit etwa 300 Mitarbeitern arbeitet gr\u00f6\u00dftenteils agil nach einem Scrumban-Ansatz und deckt Bereiche wie Cloud Computing, Cybersecurity, Operations, Process and Governance, Software Development und Architecture ab. Wir sind besonders stolz darauf, fast alle unsere Applikationen Inhouse zu entwickeln, was uns eine einzigartige Flexibilit\u00e4t und Innovationskraft verleiht. Unser Tech Stack umfasst moderne Technologien wie Java, Kotlin, TypeScript und Python, CI/CD-Pipelines, Container, Kubernetes sowie Azure Cloud, Azure SQL Database und Oracle Datenbank mit PL/SQL.\nDeine Rolle im Team\nDas Team Central Quality Assurance versteht sich als Dienstleister und Ansprechpartner f\u00fcr die Fachbereiche und Produktteams rund um das Thema Software-Qualit\u00e4tssicherung und QA Governance.\nWelche Aufgaben erwarten Dich?\nTestmanagement und Testplanung unter Ber\u00fccksichtigung der geltenden regulatorischen Anforderungen im Bankwesen\nErstellung von Testkonzepten und -pl\u00e4nen in Zusammenarbeit mit den jeweiligen Projektteams\nErmittlung von Testf\u00e4llen gemeinsam mit den Produktteams auf Basis einer risikobasierten Vorgehensweise\nUnterst\u00fctzung der Produktteams bei der Durchf\u00fchrung von Integrations- und User-Acceptance-Tests\nErweiterung und Pflege des automatisierten Testportfolios\nKoordination und Organisation von Testprojekten\nWen suchen wir?\nErfolgreich abgeschlossenes Studium im Bereich (Wirtschafts-)Informatik oder einer vergleichbaren Fachrichtung sowie einschl\u00e4gige Branchenerfahrung\nSehr gute Kenntnisse im Testmanagement, zertifiziert nach ISTQB Tester Foundation sowie Advanced Level \u2013 Test Manager\nErfahrung mit agilen Methoden und Begeisterung f\u00fcr dynamische, teamorientierte Arbeitsprozesse\nW\u00fcnschenswert sind Kenntnisse in Oracle PL/SQL sowie Kenntnisse in HTML und/oder Java\nAusgepr\u00e4gte analytische und konzeptionelle F\u00e4higkeiten, um komplexe Aufgabenstellungen zu erfassen und umzusetzen\nSehr gute Deutsch- und Englischkenntnisse in Wort und Schrift\nWas wir Dir bieten:\nFlexible Arbeitszeiten innerhalb einer 39-Stunden-Woche\n30 Tage Jahresurlaub sowie zus\u00e4tzliche freie Tage am 24. und 31. Dezember\nVielseitiges und spannendes Aufgabengebiet in einem modernen und dynamischen Umfeld sowie ein wertsch\u00e4tzendes Betriebsklima\nGezielte F\u00f6rderung durch interne und externe Schulungs- und Entwicklungsprogramme\nBerenberg-Patensystem f\u00fcr ein strukturiertes und reibungsloses Onboarding\nVielf\u00e4ltige Zusch\u00fcsse (z. B. Deutschlandticket, JobRad, verm\u00f6genswirksame Leistungen, betriebliche Altersvorsorge, Essenszusch\u00fcsse bzw. Betriebsrestaurant in Hamburg)\nZus\u00e4tzliche Leistungen wie Familienservice, Arbeitszeitkonto (z. B. f\u00fcr Sabbaticals), betriebliche Sozialleistungen, Gesundheits- und Sportprogramme\nBewirb dich jetzt online und werde Teil des Teams \u2013\nwir freuen uns auf deine Bewerbung!\nWir sind eine f\u00fchrende europ\u00e4ische Privatbank mit \u00fcber 430 Jahren Erfahrung und einer tief verwurzelten Geschichte, aber wir gestalten und investieren noch immer in Zukunft. Unser Fortschritt und unsere Entwicklung werden von unseren Mitarbeitern vorangetrieben. Wir ermutigen sie, neue Ans\u00e4tze auszuprobieren, ihre Meinung zu \u00e4u\u00dfern und auf ihre eigene Art und Weise erfolgreich zu sein.\nWir bieten ihnen die M\u00f6glichkeit, ihre Talente zu entwickeln, verschiedene Karrierewege zu erkunden und ihr Potenzial voll auszusch\u00f6pfen.\nWir sind ein ehrgeiziges, zukunftsorientiertes Unternehmen, das auf jahrhundertealte Traditionen zur\u00fcckgreift und auf Innovation baut. Du findest bei uns eine Kultur vor, die Menschen dazu ermutigt, unabh\u00e4ngig zu denken, unternehmerisch zu handeln und den Status quo in Frage zu stellen. Wir legen gro\u00dfen Wert auf die Zusammenarbeit vor Ort \u2013 unser B\u00fcro ist ein zentraler Ort des Dialogs, der Innovation und des gemeinsamen Wachstums. Gemeinsam arbeiten wir daran, unser Gesch\u00e4ft zu gestalten und unsere ehrgeizigen Ziele zu erreichen.\nWir freuen uns, wenn du dich uns anschlie\u00dft, um stets das Richtige f\u00fcr unsere Mitarbeiter, Kunden und unser Unternehmen zu tun \u2013\nOur future is where you take us!\nAus organisatorischen Gr\u00fcnden nehmen wir nur Bewerbungen an, die uns \u00fcber unser Online-Bewerbermanagementsystem auf der Website erreichen.\n*Aus Gr\u00fcnden der besseren Lesbarkeit wird auf die gleichzeitige Verwendung mehrgeschlechtlicher Sprachformen verzichtet. S\u00e4mtliche Personenbezeichnungen gelten gleichwohl f\u00fcr jegliches Geschlecht. Bei uns sind alle Bewerber willkommen, unabh\u00e4ngig von Geschlecht, Nationalit\u00e4t, ethnischer Herkunft, sozialem Hintergrund, Behinderung, Religion, Alter oder sexueller Orientierung. Bei Fragen wende dich bitte an unser Recruitment-Team unter recruitment@berenberg.de.\nBack to job list\nApply\nShare this job:\nShare (Senior) QA Test Manager* with a friend via e-mail",
        "application_url": "https://berenberg.avature.net/en_GB/careers/Login?jobId=2471",
        "metadata": {
            "Country": "Germany",
            "City": "Hamburg",
            "Type of role": "Professional",
            "Working time": "Full-time",
            "Type of contract": "Permanent",
            "Remaining openings": "1"
        },
        "link": "https://berenberg.avature.net/en_GB/careers/JobDetail/Senior-QA-Test-Manager/2471"
    },
    {
        "title": null,
        "description_html": null,
        "description_text": "Monitoring & Observability Engineer\nGeneral information\nCountry\nUnited Kingdom\nCity\nLondon\nType of role\nProfessional\nWorking time\nFull-time\nType of contract\nPermanent\nRemaining openings\n1\nDescription & Requirements\nFor our\nInnovation & Technology\ndepartment in\nLondon\nwe are looking to hire a:\nMonitoring & Observability Engineer\nInnovation & Technology @ Berenberg\nIn an era where digitalisation and modern IT infrastructure is revolutionizing banking, we are shaping a technology-driven bank in which you as an IT professional will work closely with our business units. Our technology teams offer you an environment that will present you with exciting challenges - be it through the support and further development of legacy systems or the introduction of modern technologies such as AI, machine learning and highly automated trading applications.\nYour Role in the team:\nWe are seeking an experienced Splunk Engineer (very much with a DevOps mindset) to join our Berenberg\u2019s Investment Banking Technology department. They will be expected to closely collaborate with a wide range of different teams (infrastructure, development, InfoSec etc). This role is responsible for designing, implementing, and maintaining our Splunk environment, ensuring the effective monitoring and security of financial systems and data. The ideal candidate will have a solid understanding of monitoring and observability tools and possesses the necessary skills and experiences to administer and operate them in an on-prem as well as cloud environment.\nWhat will you do:\nSplunk Enterprise Administration: Responsible for ensuring the overall health, stability, and performance of the Splunk deployment through regular maintenance, including patching, version upgrades, and performance tuning. This includes implementing best practices for patch management to keep the Splunk environment up to date, secure, and compatible with current infrastructure\nData Source Onboarding: Skilled in the end-to-end process of onboarding various data sources into Splunk, with a focus on diverse financial applications, security devices, network appliances, and cloud environments\nObservability: With a clear trend to enhance traditional monitoring with observability, the engineer should be familiar with tool sets as well as the approaches that underpin a successful observability approach\nCollaboration: Proven ability to collaborate with incident response (IR) teams and provide actionable insights during (security) incidents. Furthermore, support other teams in their adoption journey with Splunk in particular the use and implementation of effective and efficient dashboards, alerts etc\nWho are we looking for?\n5+ years of experience as a Splunk Engineer, ideally with a background in the financial services industry, with solid in-depth experience in administering and operating a distributed Splunk Enterprise setup\nProficiency with SPL/SPL2 (Splunk Query language), Linux and networking\nExperience in a range of monitoring tools, such as Grafana and Prometheus (setup, administration and operating), Solarwinds, Cribl\nHas exposure of working with security and network operations teams\nA DevOps approach to implementing, testing and releasing features, i.e. code reviews, fully automated build, test and deployment pipeline\nContainers (aka Docker) and Kubernetes, e.g. operating Splunk component in a K8s cluster using Splunk Operator for Kubernetes\nExperience with EDR, NDR and XDR solutions\nIncident Management process understanding\nExperience in capacity management concepts and implementations\nWhat we offer you:\nPrivate pension plan - 10% of base salary contribution by Berenberg\nGenerous 30 day holiday allowance\nPrivate Health Insurance\nLife Insurance scheme\nFlexible working hours\nEnhanced parental leave policies\nEmployee Assistance Programme offering counselling sessions related to mental health, financial wellbeing and other topics\nApply online now to join our team \u2013\nwe look forward to receiving your application!\nWe are a leading European private bank, with over 430 years of experience and deep rooted history, but we are still shaping and heavily investing in our future. Our progress and evolution are driven by our people. We encourage them to try new approaches, voice their opinions and achieve success in their own way.\nWe provide opportunities for them to develop their talents, explore different career paths and achieve their full potential.\nWe\u2019re an ambitious, forward-looking business, backed by centuries of tradition and built on innovation. You\u2019ll find a culture that encourages people to think independently, act entrepreneurially and challenge the status quo.\nWe place great importance on working on site, as we believe that being together in the office not only fosters creativity and efficiency, but also strengthens networks and builds trusting, collegial relationships. For us, this forms the foundation for productive and successful work. Together we collaborate to shape our business and fulfil our ambitious goals.\nWe welcome you to join us in our commitment to always do the right thing for our people, clients and our business \u2013\nOur future is where you take us!\nWe will only accept applications submitted through our online application management system on the website.\nBerenberg is an Equal Opportunities Employer and prides itself on being a modern, dynamic and internationally orientated organisation. We value the rich diversity, skills and abilities and creative potential that people from differing backgrounds and experiences bring to the workplace. Every employee plays a vital role in providing quality service to all our customers and helping to create and inclusive working environment, where everyone can realise their full potential. We\u2019re committed to finding reasonable accommodations for candidates who require adjustments during our recruiting process. Please contact us directly on recruitment@berenberg.com to discuss.\nBack to job list\nApply\nShare this job:\nShare Monitoring & Observability Engineer with a friend via e-mail",
        "application_url": "https://berenberg.avature.net/en_GB/careers/Login?jobId=2401",
        "metadata": {
            "Country": "United Kingdom",
            "City": "London",
            "Type of role": "Professional",
            "Working time": "Full-time",
            "Type of contract": "Permanent",
            "Remaining openings": "1"
        },
        "link": "https://berenberg.avature.net/en_GB/careers/JobDetail/Monitoring-Observability-Engineer/2401"
    },
    {
        "title": null,
        "description_html": null,
        "description_text": "Junior Equity Salesperson (Boston)\nGeneral information\nCountry\nUSA\nCity\nBoston\nType of role\nProfessional\nWorking time\nFull-time\nType of contract\nPermanent\nRemaining openings\n1\nDescription & Requirements\nFor our\nSales\ndivision in\nBoston\n, we are looking to hire a\nJunior Equity Salesperson, full time - Boston\nYour role in the team:\nBerenberg Capital Markets is looking to hire an ambitious and energetic Boston-based junior equity salesperson to continue to build on the team\u2019s success. This role would suit someone seeking early responsibility, and who is looking to build their career at a firm that is wholly committed to its growth and success across North America.\nThe role would suit somebody at or near the start of their career, a recent graduate or someone who has experience in financial sales before but is keen to become a specialist in Equity Sales. The role will provide fantastic exposure to senior members of the team, well-versed in developing juniors, giving them significant business exposure, and offering them a steep and exciting career trajectory.\nWhat will you do?\nHelp to support and advise institutional clients (e.g. insurance firms, investment companies, banks) on the basis of our research products and distribution capabilities, with a focus on clients based in Boston and Canada\nSupport members of the team in the marketing and sales of the European and US equity research product\nCreation and development of investment ideas for investors in the Boston area and beyond\nOrganization of investor meetings for IPOs and other capital market transactions in North America\nOrganize and attend corporate and analyst roadshows\nBecome an integral member of our Boston Sales team and, over time, take responsibility for the day-to-day servicing of your own book of clients\nWhat are we looking for?\nInternship or trainee experience within an Investment Bank, investment, or securities firm\nPassion for all things Equities, and a natural flare for a Sales-oriented role\nAmbitious and motivated individual looking for significant exposure and responsibility with highly valued clients of the firm, looking to push their career to the next level\nDegree-level education (or equivalent experience) required, with exceptional academics, preferably with a financial focus\nEnthusiasm and interest in securities and capital markets, with a particular focus on Equities and a passion for building their career within Equity Sales\nMust understand how to focus and prioritize client needs and requirements as the work is fast-paced and busy\nAble to deliver a consistently high standard of work, and handle their workload effectively in order to meet strict deadlines\nFlexible, adaptable, and strong at building relationships\nAn entrepreneurial mindset and goal-oriented approach are important to succeed\nMust possess excellent communication skills, love to work in a small team and is eager to succeed\nWhat we offer you:\n100% Company sponsored medical, dental, and vision insurance\n25 Paid vacation and sick time\nCompany-paid life insurance\nCompany-paid STD/LTD\nPaid parental leave\n401(k) plan with company match\nGym membership discounts\nApply now and join our Team \u2013\nwe look forward to receiving your application!\nWho we are:\nBerenberg Capital Markets LLC (BCM) is a New York based FINRA member broker-dealer, and wholly owned independent subsidiary of Joh. Berenberg, Gossler & Co. KG (Berenberg), one of Europe\u2019s leading privately-owned banks, established in 1590. Together, BCM and Berenberg have built a franchise known for its \u201cclient first\u201d approach and a global reputation of high-quality coverage of both corporate and institutional clients. As a combined entity, Berenberg covers over 770 European and US equities, with a 100+ person research department based out of London. Leveraging our global network of institutional investors and deep corporate relationships, we developed a track record of raising capital on US exchange\u2019s raising over $28 billion for 72 corporates since opening our Equity Capital Markets division in 2018. Building on its strength and expertise across multiple industries, BCM continues to expand the breadth of Sales, Trading, and Investment Banking services it offers to better assist its institutional and corporate clients\u2019 access to the global equity markets. BCM adopts the same principles as its parent company and is committed to building long-term relationships with its clients based on high levels of accountability, responsibility, insight, vision, and expertise.\nWe will only accept applications submitted through our online application management system on the website.\nWe\u2019re committed to finding reasonable accommodations for candidates who require adjustments during our recruiting process. Please contact us directly on recruitment@berenberg.com to discuss.\nBCM provides Equal Employment Opportunities (EEO) to all employees and applicants without regard to their actual or perceived age, race, creed, religious belief, color, gender, sexual orientation, gender identity, partnership status, marital status, physical or mental disability, national origin, alienage or citizenship status, military or veteran status, genetic predisposition or carrier status, or engaging in protected activity (such as opposition to prohibited discrimination or participation in proceedings covered by the anti-discrimination statutes) or any other characteristic protected by applicable federal, state and local law. BCM complies with applicable state and local laws governing non-discrimination in employment in every location in which the Company has facilities. This policy applies to all terms and conditions of employment, including hiring, placement, promotion, termination, layoff, recall, transfer, leaves of absence, compensation and training.\nSalary will vary based on role, education, level of experience, and expertise ranging between $80,000 and $115,000 dollars as a base salary with eligibility for a discretionary annual bonus plus comprehensive benefits package.\nBack to job list\nApply\nShare this job:\nShare Junior Equity Salesperson (Boston) with a friend via e-mail",
        "application_url": "https://berenberg.avature.net/en_GB/careers/Login?jobId=2434",
        "metadata": {
            "Country": "USA",
            "City": "Boston",
            "Type of role": "Professional",
            "Working time": "Full-time",
            "Type of contract": "Permanent",
            "Remaining openings": "1"
        },
        "link": "https://berenberg.avature.net/en_GB/careers/JobDetail/Junior-Equity-Salesperson-Boston/2434"
    },
    {
        "title": null,
        "description_html": null,
        "description_text": "Cloud DevOps Engineer*\nGeneral information\nCountry\nGermany\nCity\nHamburg\nType of role\nProfessional\nWorking time\nFull-time\nType of contract\nPermanent\nRemaining openings\n1\nDescription & Requirements\nF\u00fcr unser Programm\nDigital Innovation & Cloud Enablement\nam\nStandort Hamburg\nsuchen wir zum\nn\u00e4chstm\u00f6glichen Zeitpunkt\ndich als\nCloud DevOps Engineer*\nInnovation & Technology @ Berenberg\nIn einer \u00c4ra, in der Digitalisierung und moderne IT-Infrastrukturen das Banking revolutionieren, gestalten wir eine technologiegest\u00fctzte Bank, in der du als IT-Profi eng mit unseren Gesch\u00e4ftsbereichen zusammenarbeitest. Unsere Technology-Teams bieten dir ein Umfeld, das dich vor spannende Herausforderungen stellt \u2013 sei es durch den Support und die Weiterentwicklung von Legacy-Systemen oder die Einf\u00fchrung moderner Technologien wie KI, Machine Learning und hochgradig automatisierte Handelsapplikationen.\nUnsere IT-Abteilung mit etwa 300 Mitarbeitern arbeitet gr\u00f6\u00dftenteils agil nach einem Scrumban-Ansatz und deckt Bereiche wie Cloud Computing, Cybersecurity, Operations, Process and Governance, Software Development und Architecture ab. Wir sind besonders stolz darauf, fast alle unsere Applikationen Inhouse zu entwickeln, was uns eine einzigartige Flexibilit\u00e4t und Innovationskraft verleiht. Unser Tech Stack umfasst moderne Technologien wie Java, Kotlin, TypeScript und Python, CI/CD-Pipelines, Container, Kubernetes sowie Azure Cloud, Azure SQL Database und Oracle Datenbank mit PL/SQL.\nWelche Aufgaben erwarten Dich?\nEntwicklung operativer Standards bzw. Best Practices f\u00fcr die Umsetzung der Cloud-Strategie und -Architekturplanung\nMitgestaltung und Entwicklung der Cloud-Plattform mit den Architekten und Stakeholdern aus der Softwareentwicklung\nUnterst\u00fctzung der Entwicklerteams auf dem Weg in die Private oder Public Cloud (prim\u00e4r Google und Azure)\nF\u00f6rderung der Nutzung von Best Practices (z. B. der OWASP Top 10 sowie Twelve-Factor App)\nIdentifizierung passender Cloud Services, um die Infrastruktur zu optimieren und Prozesse zu automatisieren\n3rd-Level-Support f\u00fcr die Teams\nWen suchen wir?\nFachbezogenes Studium oder einschl\u00e4gige Berufserfahrung bzw. gleichwertige, in Fortbildungsma\u00dfnahmen erworbene Kenntnisse\nIdealerweise fundierte Kenntnisse im Betrieb von Containern: Linux, Docker, Git, Terraform, CloudShell, IP-Protokoll, Routing und Switching etc.\nKnow-how in CI/CD-Tools (Bamboo oder Azure DevOps) w\u00fcnschenswert\nKenntnisse in Microsoft Cloud Adoption Framework oder Google Cloud Adoption Framework\nTiefes Verst\u00e4ndnis von sicherheitsrelevanten Aspekten in der IT und von Infrastrukturautomatisierungen in der Cloud\nSehr gute Deutsch- und gute Englischkenntnisse in Wort und Schrift\nVorteilhaft sind Kenntnisse in Kubernetes, Jenkins, Bamboo und Cloudtechnologien (z. B. Azure)\nWas wir Dir bieten:\nFlexible Arbeitszeiten innerhalb einer 39-Stunden-Woche\n30 Tage Jahresurlaub sowie zus\u00e4tzliche freie Tage am 24. und 31. Dezember\nVielseitiges und spannendes Aufgabengebiet in einem modernen und dynamischen Umfeld sowie ein wertsch\u00e4tzendes Betriebsklima\nGezielte F\u00f6rderung durch interne und externe Schulungs- und Entwicklungsprogramme\nBerenberg-Patensystem f\u00fcr ein strukturiertes und reibungsloses Onboarding\nVielf\u00e4ltige Zusch\u00fcsse (z. B. Deutschlandticket, JobRad, verm\u00f6genswirksame Leistungen, betriebliche Altersvorsorge, Essenszusch\u00fcsse bzw. Betriebsrestaurant in Hamburg)\nZus\u00e4tzliche Leistungen wie Familienservice, Arbeitszeitkonto (z. B. f\u00fcr Sabbaticals), betriebliche Sozialleistungen, Gesundheits- und Sportprogramme\nBewirb dich jetzt online und werde Teil des Teams \u2013\nwir freuen uns auf deine Bewerbung!\nWir sind eine f\u00fchrende europ\u00e4ische Privatbank mit \u00fcber 430 Jahren Erfahrung und einer tief verwurzelten Geschichte, aber wir gestalten und investieren noch immer in Zukunft. Unser Fortschritt und unsere Entwicklung werden von unseren Mitarbeitern vorangetrieben. Wir ermutigen sie, neue Ans\u00e4tze auszuprobieren, ihre Meinung zu \u00e4u\u00dfern und auf ihre eigene Art und Weise erfolgreich zu sein.\nWir bieten ihnen die M\u00f6glichkeit, ihre Talente zu entwickeln, verschiedene Karrierewege zu erkunden und ihr Potenzial voll auszusch\u00f6pfen.\nWir sind ein ehrgeiziges, zukunftsorientiertes Unternehmen, das auf jahrhundertealte Traditionen zur\u00fcckgreift und auf Innovation baut. Du findest bei uns eine Kultur vor, die Menschen dazu ermutigt, unabh\u00e4ngig zu denken, unternehmerisch zu handeln und den Status quo in Frage zu stellen. Wir legen gro\u00dfen Wert auf die Zusammenarbeit vor Ort \u2013 unser B\u00fcro ist ein zentraler Ort des Dialogs, der Innovation und des gemeinsamen Wachstums. Gemeinsam arbeiten wir daran, unser Gesch\u00e4ft zu gestalten und unsere ehrgeizigen Ziele zu erreichen.\nWir freuen uns, wenn du dich uns anschlie\u00dft, um stets das Richtige f\u00fcr unsere Mitarbeiter, Kunden und unser Unternehmen zu tun \u2013\nOur future is where you take us!\nAus organisatorischen Gr\u00fcnden nehmen wir nur Bewerbungen an, die uns \u00fcber unser Online-Bewerbermanagementsystem auf der Website erreichen.\n*Aus Gr\u00fcnden der besseren Lesbarkeit wird auf die gleichzeitige Verwendung mehrgeschlechtlicher Sprachformen verzichtet. S\u00e4mtliche Personenbezeichnungen gelten gleichwohl f\u00fcr jegliches Geschlecht. Bei uns sind alle Bewerber willkommen, unabh\u00e4ngig von Geschlecht, Nationalit\u00e4t, ethnischer Herkunft, sozialem Hintergrund, Behinderung, Religion, Alter oder sexueller Orientierung. Bei Fragen wende dich bitte an unser Recruitment-Team unter recruitment@berenberg.de.\nBack to job list\nApply\nShare this job:\nShare Cloud DevOps Engineer* with a friend via e-mail",
        "application_url": "https://berenberg.avature.net/en_GB/careers/Login?jobId=2396",
        "metadata": {
            "Country": "Germany",
            "City": "Hamburg",
            "Type of role": "Professional",
            "Working time": "Full-time",
            "Type of contract": "Permanent",
            "Remaining openings": "1"
        },
        "link": "https://berenberg.avature.net/en_GB/careers/JobDetail/Cloud-DevOps-Engineer/2396"
    },
    {
        "title": null,
        "description_html": null,
        "description_text": "Senior Anti-Financial Crime Compliance Expert*\nGeneral information\nCountry\nGermany\nCity\nFrankfurt, Hamburg\nType of role\nProfessional\nWorking time\nFull-time\nType of contract\nPermanent\nRemaining openings\n1\nDescription & Requirements\nZur Verst\u00e4rkung unserer Abteilung\nAnti-Financial Crime Compliance (AFC Compliance)\nim Bereich Group Compliance in\nHamburg oder Frankfurt\nsuchen wir zum\nn\u00e4chstm\u00f6glichen Zeitpunkt\nSie als\nSenior Anti-Financial Crime Compliance Expert*\nIhre Rolle im Team:\nDie Arbeit im Team ist durch ein hohes Ma\u00df an Eigenverantwortung und selbstst\u00e4ndiger Arbeit gepr\u00e4gt. Wer Herausforderungen liebt, findet hier gro\u00dfen Gestaltungsspielraum, Freiheit f\u00fcr Ideen und die M\u00f6glichkeit, schnell einen signifikanten Einfluss zu haben. Insbesondere treiben Sie Themen rund um Kryptow\u00e4hrungen und Distributed-Ledger-Technologien (DLT) voran.\nWelche Aufgaben erwarten Sie?\nPr\u00fcfung von Transaktionen und Vertragspartnern hinsichtlich geldw\u00e4sche- und sanktionsrechtlicher Anforderungen\nEntwicklung und Implementierung von internen Richtlinien und Verfahren gem\u00e4\u00df MiCAR-Anforderungen.Fachliche und technische Weiterentwicklung der Monitoring- und Screening-Systeme im Hinblick auf digitale Technologien und neue Zahlungs- und Transaktionsmethoden (Kryptow\u00e4hrungen u. a. Tokens usw.)\nIdentifizierung und Analyse regulatorischer Risiken im Krypto-Gesch\u00e4ft\nOperative Beratung der Fachabteilungen (Produkt, Technik) zu rechtlichen Rahmenbedingungen\n\u00dcberpr\u00fcfung der Einhaltung gesetzlicher und regulatorischer Anforderungen\nTrefferbearbeitung (\u201eAlerts\u201c) des Sanktions-Monitorings sowie Transaktions-Monitorings unter Einhaltung interner Prozesse und revisionssicherer Dokumentation\nWen suchen wir?\nErfolgreich abgeschlossenes Studium der Informatik oder Wirtschaftswissenschaften; Kenntnisse in re-gulatorischen Rahmenwerken wie MiCAR und FinmadiG sind von Vorteil.\nErfahrung mit digitalen Technologien (DLT) und Zahlungsmethoden im Banken-, Finanzdienstleistungs- oder Beratungsumfeld.\nAusgepr\u00e4gte technische Kenntnisse, starkes Systemverst\u00e4ndnis sowie sicherer Umgang mit komplexen digitalen Zusammenh\u00e4ngen.\nSelbstst\u00e4ndige, analytische, strukturierte und pr\u00e4zise Arbeitsweise; hohe Eigenmotivation, proaktives Handeln und ausgepr\u00e4gtes analytisches Denken.\nEngagierter Teamplayer mit schneller Auffassungsgabe, souver\u00e4nem Auftreten und Durchsetzungsverm\u00f6gen sowie exzellenten Deutsch- und Englischkenntnissen in Wort und Schrift.\nWas wir Ihnen bieten:\nFlexible Arbeitszeiten innerhalb einer 39-Stunden-Woche\n30 Tage Jahresurlaub\nVielseitiges und spannendes Aufgabengebiet in einem modernen und dynamischen Umfeld sowie ein wertsch\u00e4tzendes Betriebsklima\nGezielte F\u00f6rderung durch interne und externe Schulungs- und Entwicklungsprogramme\nBerenberg-Patensystem f\u00fcr ein strukturiertes und reibungsloses Onboarding\nVielf\u00e4ltige Zusch\u00fcsse (z.B. Deutschlandticket, JobRad, verm\u00f6genswirksame Leistungen, betriebliche Al-tersvorsorge, Pluxee-Checks)\nZus\u00e4tzliche Leistungen wie Familienservice, Arbeitszeitkonto (z.B. f\u00fcr Sabbaticals), betriebliche Sozial-leistungen, Gesundheits- und Sportprogramme\nBewerben Sie sich jetzt online und werden Sie Teil des Teams \u2013\nwir freuen uns auf Ihre Bewerbung!\nAls eine f\u00fchrende europ\u00e4ische Privatbank mit \u00fcber 430 Jahren Erfahrung blicken wir auf eine lange Unternehmensgeschichte zur\u00fcck. Gleichzeitig gestalten wir mit umfassenden Investitionen aktiv unsere Zukunft. Grundlage f\u00fcr unseren Fortschritt und unsere Weiterentwicklung sind unsere Mitarbeiter. Wir ermutigen diese, neue Ans\u00e4tze auszuprobieren, ihre Ideen mit einzubringen und ihren eigenen Weg zum Erfolg bei uns zu gehen. Wir sind ein ambitioniertes, zukunftsorientiertes Unternehmen, das jahrhundertelange Erfahrung und Innovationskraft vereint. Bei uns erleben Sie eine Kultur, die zum selbstst\u00e4ndigen Denken anregt, Unternehmertum f\u00f6rdert und dazu ermutigt, den Status quo zu hinterfragen. Sie treffen hier auf talentierte Kollegen, die es gewohnt sind, Verantwortung zu \u00fcbernehmen, und gemeinsam an einem Strang ziehen, um Ergebnisse zu erzielen.\nWerden Sie Teil von Berenberg und arbeiten Sie mit uns gemeinsam daran, das Richtige f\u00fcr unsere Kunden, unser Gesch\u00e4ft und unsere Mitarbeiter zu tun \u2013\nOur future is where you take us!\nAus organisatorischen Gr\u00fcnden nehmen wir nur Bewerbungen an, die uns \u00fcber unser Online-Bewerbermanagementsystem auf der Website erreichen.\n*Aus Gr\u00fcnden der besseren Lesbarkeit wird auf die gleichzeitige Verwendung mehrgeschlechtlicher Sprachformen verzichtet. S\u00e4mtliche Personenbezeichnungen gelten gleichwohl f\u00fcr jegliches Geschlecht.\nBei uns sind alle Bewerbungen willkommen, unabh\u00e4ngig von Geschlecht, Nationalit\u00e4t, ethnischer Herkunft, sozialem Hintergrund, Behinderung, Religion, Alter oder sexueller Orientierung.\nBei Fragen wenden Sie sich bitte an unser Recruitment-Team unter recruitment@berenberg.de\nBack to job list\nApply\nShare this job:\nShare Senior Anti-Financial Crime Compliance Expert* with a friend via e-mail",
        "application_url": "https://berenberg.avature.net/en_GB/careers/Login?jobId=2815",
        "metadata": {
            "Country": "Germany",
            "City": "Frankfurt, Hamburg",
            "Type of role": "Professional",
            "Working time": "Full-time",
            "Type of contract": "Permanent",
            "Remaining openings": "1"
        },
        "link": "https://berenberg.avature.net/en_GB/careers/JobDetail/Senior-Anti-Financial-Crime-Compliance-Expert/2815"
    },
    {
        "title": null,
        "description_html": null,
        "description_text": "K8s/Kubernetes Platform Engineer\nGeneral information\nCountry\nUnited Kingdom\nCity\nLondon\nType of role\nProfessional\nWorking time\nFull-time\nType of contract\nPermanent\nRemaining openings\n1\nDescription & Requirements\nFor our\nInnovation & Technology\ndepartment in\nLondon\nwe are looking to hire a:\nKubernetes Platform Engineer\nInnovation & Technology @ Berenberg\nIn an era where digitalisation and modern IT infrastructure is revolutionizing banking, we are shaping a technology-driven bank in which you as an IT professional will work closely with our business units. Our technology teams offer you an environment that will present you with exciting challenges - be it through the support and further development of legacy systems or the introduction of modern technologies such as AI, machine learning and highly automated trading applications.\nYour Role in the team:\nThis role is all about Kubernetes (K8s) where a DevOps mind and experience is going to be paramount. You will get involved in the design, setup and management of our K8s clusters across various datacentres. We are building a value-add on-prem, bare-metal K8s platform (with the option to expand into the cloud when the use cases arise) which will cater to a wide range workloads with different resource demands, ranging from latency sensitive, fast paced algo trading to big data analytics, middle and back-office applications as well as client and exchange gateways.\nWhat will you do?\nClose collaboration with our datacentre infrastructure and network engineers and will also overlap with the monitoring and observability domain.\nWorking in a DevOps approach that involves concepts of code review, automated testing and release pipelines\nWork in an environment that is protected by PAM (Privileged Access Management)\nWho are we looking for?\nUNIX / Linux (Ubuntu & Red Hat)\nK8s (must; administration as well as best-practise for usage), Calico Enterprise (desirable)\nNetworking, in particular TCP/IP in general as well as understanding routes, routing tables, VLAN / VRF concepts, BGP\nBash, Python, Ansible, Terraform, Helm and Git\nAccustomed to working in a DevOps approach that involves concepts of code review, automated testing and release pipelines\nAccustomed to work in an environment that is protected by PAM (Privileged Access Management)\nWhat we offer you:\nPrivate pension plan - 10% of base salary contribution by Berenberg\nGenerous 30 day holiday allowance\nPrivate Health Insurance\nLife Insurance scheme\nFlexible working hours\nEnhanced parental leave policies\nEmployee Assistance Programme offering counselling sessions related to mental health, financial wellbeing and other topics\nApply online now to join our team \u2013\nwe look forward to receiving your application!\nWe are a leading European private bank, with over 430 years of experience and deep rooted history, but we are still shaping and heavily investing in our future. Our progress and evolution are driven by our people. We encourage them to try new approaches, voice their opinions and achieve success in their own way.\nWe provide opportunities for them to develop their talents, explore different career paths and achieve their full potential.\nWe\u2019re an ambitious, forward-looking business, backed by centuries of tradition and built on innovation. You\u2019ll find a culture that encourages people to think independently, act entrepreneurially and challenge the status quo.\nWe place great importance on working on site, as we believe that being together in the office not only fosters creativity and efficiency, but also strengthens networks and builds trusting, collegial relationships. For us, this forms the foundation for productive and successful work. Together we collaborate to shape our business and fulfil our ambitious goals.\nWe welcome you to join us in our commitment to always do the right thing for our people, clients and our business\n\u2013 Our future is where you take us!\nWe will only accept applications submitted through our online application management system on the website.\nBerenberg is an Equal Opportunities Employer and prides itself on being a modern, dynamic and internationally orientated organisation. We value the rich diversity, skills and abilities and creative potential that people from differing backgrounds and experiences bring to the workplace. Every employee plays a vital role in providing quality service to all our customers and helping to create and inclusive working environment, where everyone can realise their full potential. We\u2019re committed to finding reasonable accommodations for candidates who require adjustments during our recruiting process. Please contact us directly on recruitment@berenberg.com to discuss.\nBack to job list\nApply\nShare this job:\nShare K8s/Kubernetes Platform Engineer with a friend via e-mail",
        "application_url": "https://berenberg.avature.net/en_GB/careers/Login?jobId=2330",
        "metadata": {
            "Country": "United Kingdom",
            "City": "London",
            "Type of role": "Professional",
            "Working time": "Full-time",
            "Type of contract": "Permanent",
            "Remaining openings": "1"
        },
        "link": "https://berenberg.avature.net/en_GB/careers/JobDetail/K8s-Kubernetes-Platform-Engineer/2330"
    },
    {
        "title": null,
        "description_html": null,
        "description_text": "IT Governance Manager*\nGeneral information\nCountry\nGermany\nCity\nHamburg\nType of role\nProfessional\nWorking time\nFull-time\nType of contract\nPermanent\nRemaining openings\n1\nDescription & Requirements\nF\u00fcr unser Programm\nOrganisational Development & Governance\nam Standort\nHamburg\nsuchen wir zum\nn\u00e4chstm\u00f6glichen Zeitpunkt\ndich als\nIT Governance Manager*\nInnovation & Technology @ Berenberg\nIn einer \u00c4ra, in der Digitalisierung und moderne IT-Infrastrukturen das Banking revolutionieren, gestalten wir eine technologiegest\u00fctzte Bank, in der du als IT-Profi eng mit unseren Gesch\u00e4ftsbereichen zusammenarbeitest. Unsere Technology-Teams bieten dir ein Umfeld, das dich vor spannende Herausforderungen stellt \u2013 sei es durch den Support und die Weiterentwicklung von Legacy-Systemen oder die Einf\u00fchrung moderner Technologien wie KI, Machine Learning und hochgradig automatisierte Handelsapplikationen.\nUnsere IT-Abteilung mit etwa 300 Mitarbeitern arbeitet gr\u00f6\u00dftenteils agil nach einem Scrumban-Ansatz und deckt Bereiche wie Cloud Computing, Cybersecurity, Operations, Process and Governance, Software Development und Architecture ab. Wir sind besonders stolz darauf, fast alle unsere Applikationen Inhouse zu entwickeln, was uns eine einzigartige Flexibilit\u00e4t und Innovationskraft verleiht. Unser Tech Stack umfasst moderne Technologien wie Java, Kotlin, TypeScript und Python, CI/CD-Pipelines, Container, Kubernetes sowie Azure Cloud, Azure SQL Database und Oracle Datenbank mit PL/SQL.\nWelche Aufgaben erwarten Dich?\nEigenverantwortliche Analyse, Entwicklung und Optimierung von Prozessen und Richtlinien nach Best Practice zur Umsetzung betriebswirtschaftlicher und regulatorischer Anforderungen\nUnterst\u00fctzung des Managements zur angemessenen und wirksamen Ausgestaltung und Implementierung der IT-Prozessorganisation und des internen Kontrollsystems\nSicherstellung der Transparenz und Nachvollziehbarkeit sowie Kommunikation und Reporting an das IT-Management\nAktive Mitgestaltung in der Entwicklung der Funktion IT-Governance und der Weiterentwicklung und Automatisierung unserer Prozesse\nModellierung von Prozessen in SAP Signavio sowie Management der IT-Prozesslandkarte & Prozesscompliance\nWen suchen wir?\nErfolgreich abgeschlossenes Studium mit relevanter fachlicher Ausrichtung\nErste einschl\u00e4gige Berufserfahrung im IT-Umfeld, idealerweise in den Bereichen IT-Consulting,\u00a0 IT-Steuerung IT-Prozessmanagement oder IT-Revision\nHohes Interesse an Regulatorik (DORA, MaRisk, BAIT, IDW FAIT etc.) und einschl\u00e4gigen IT-Standards (ITIL, COBIT)\nAusgepr\u00e4gte analytische F\u00e4higkeiten zur Erfassung und Strukturierung komplexer Sachverhalte\nSehr gute Deutsch- und Englischkenntnisse in Wort und Schrift\nWas wir Dir bieten:\nFlexible Arbeitszeiten innerhalb einer 39-Stunden-Woche\n30 Tage Jahresurlaub sowie zus\u00e4tzliche freie Tage am 24. und 31. Dezember\nVielseitiges und spannendes Aufgabengebiet in einem modernen und dynamischen Umfeld sowie ein wertsch\u00e4tzendes Betriebsklima\nGezielte F\u00f6rderung durch interne und externe Schulungs- und Entwicklungsprogramme\nBerenberg-Patensystem f\u00fcr ein strukturiertes und reibungsloses Onboarding\nVielf\u00e4ltige Zusch\u00fcsse (z. B. Deutschlandticket, JobRad, verm\u00f6genswirksame Leistungen, betriebliche Altersvorsorge, Essenszusch\u00fcsse bzw. Betriebsrestaurant in Hamburg)\nZus\u00e4tzliche Leistungen wie Familienservice, Arbeitszeitkonto (z. B. f\u00fcr Sabbaticals), betriebliche Sozialleistungen, Gesundheits- und Sportprogramme\nBewirb dich jetzt online und werde Teil des Teams \u2013\nwir freuen uns auf deine Bewerbung!\nWir sind eine f\u00fchrende europ\u00e4ische Privatbank mit \u00fcber 430 Jahren Erfahrung und einer tief verwurzelten Geschichte, aber wir gestalten und investieren noch immer in Zukunft. Unser Fortschritt und unsere Entwicklung werden von unseren Mitarbeitern vorangetrieben. Wir ermutigen sie, neue Ans\u00e4tze auszuprobieren, ihre Meinung zu \u00e4u\u00dfern und auf ihre eigene Art und Weise erfolgreich zu sein.\nWir bieten ihnen die M\u00f6glichkeit, ihre Talente zu entwickeln, verschiedene Karrierewege zu erkunden und ihr Potenzial voll auszusch\u00f6pfen.\nWir sind ein ehrgeiziges, zukunftsorientiertes Unternehmen, das auf jahrhundertealte Traditionen zur\u00fcckgreift und auf Innovation baut. Du findest bei uns eine Kultur vor, die Menschen dazu ermutigt, unabh\u00e4ngig zu denken, unternehmerisch zu handeln und den Status quo in Frage zu stellen. Wir legen gro\u00dfen Wert auf die Zusammenarbeit vor Ort \u2013 unser B\u00fcro ist ein zentraler Ort des Dialogs, der Innovation und des gemeinsamen Wachstums. Gemeinsam arbeiten wir daran, unser Gesch\u00e4ft zu gestalten und unsere ehrgeizigen Ziele zu erreichen.\nWir freuen uns, wenn du dich uns anschlie\u00dft, um stets das Richtige f\u00fcr unsere Mitarbeiter, Kunden und unser Unternehmen zu tun \u2013\nOur future is where you take us!\nAus organisatorischen Gr\u00fcnden nehmen wir nur Bewerbungen an, die uns \u00fcber unser Online-Bewerbermanagementsystem auf der Website erreichen.\n*Aus Gr\u00fcnden der besseren Lesbarkeit wird auf die gleichzeitige Verwendung mehrgeschlechtlicher Sprachformen verzichtet. S\u00e4mtliche Personenbezeichnungen gelten gleichwohl f\u00fcr jegliches Geschlecht. Bei uns sind alle Bewerber willkommen, unabh\u00e4ngig von Geschlecht, Nationalit\u00e4t, ethnischer Herkunft, sozialem Hintergrund, Behinderung, Religion, Alter oder sexueller Orientierung. Bei Fragen wende dich bitte an unser Recruitment-Team unter recruitment@berenberg.de.\nBack to job list\nApply\nShare this job:\nShare IT Governance Manager* with a friend via e-mail",
        "application_url": "https://berenberg.avature.net/en_GB/careers/Login?jobId=2129",
        "metadata": {
            "Country": "Germany",
            "City": "Hamburg",
            "Type of role": "Professional",
            "Working time": "Full-time",
            "Type of contract": "Permanent",
            "Remaining openings": "1"
        },
        "link": "https://berenberg.avature.net/en_GB/careers/JobDetail/IT-Governance-Manager/2129"
    },
    {
        "title": null,
        "description_html": null,
        "description_text": "European Equities Summer Internship Programme 2026, London\nGeneral information\nCountry\nUnited Kingdom\nCity\nLondon\nType of role\nInternship programme\nWorking time\nFull-time\nType of contract\nInternship\nRemaining openings\n18\nDescription & Requirements\nEuropean Equities Summer Internship Programme\nInvestment Bank Division | London\n20-25 positions available\nStart date: 22 June 2026 (10 weeks)\nBuild your career in Equities\nIf you\u2019re curious about markets, driven by ideas, and want real exposure inside a leading investment bank, our\nEuropean Equities Summer Internship Programme\noffers a front-row seat to how capital markets actually work.\nAt Berenberg, interns are part of the team. You\u2019ll be learning from experienced professionals, contributing to active work, and building the skills that matter in\nEquity Research\nand\nEquity Sales\n.\nHigh-performing interns may be\nfast-tracked to interview for our Investment Bank Graduate Programme,\nstarting in\nOctober 2027\n.\nHow the programme works\nWeek 1: Foundations\nYour internship begins with a structured induction designed to set you up for success, including:\nInsight sessions with senior business leaders\nClassroom-based technical and market training\nA full introduction to Berenberg\u2019s culture, people and platform\nWeeks 2\u201310: Real experience, real responsibility\nYou\u2019ll join one of two front-office teams: Equity Research or Equity Sales\nYou\u2019ll work alongside professionals on live projects, gaining exposure to how ideas turn into investment decisions and client outcomes. You\u2019ll also be paired with a senior mentor, giving you support, guidance and space to ask the questions that matter.\nThe teams\nEquity Research\nBerenberg has one of Europe\u2019s largest and most established equity research teams. Our analysts combine:\nDeep industry and company knowledge\nRigorous financial modelling and valuation\nIndependent thinking and original insight\nEquity Sales\nOur Equity Sales team sits at the heart of the market, connecting investors with our research and ideas. You\u2019ll see how relationships, market insight and commercial thinking come together to:\nDistribute Berenberg\u2019s best-in-class research\nProvide context around markets and stocks\nBuild long-term investor relationships\nYou\u2019ll work with a mix of experienced professionals and high-performing early-career talent.\nWe actively encourage freedom of thought. Interns are expected to ask smart questions, challenge assumptions and form their own views, while being supported by experienced colleagues.\nWho we\u2019re looking for\nWe\u2019re less focused on a specific degree and more interested in\npotential, curiosity and motivation\n. You\u2019ll thrive at Berenberg if you:\nAre inquisitive, driven and keen to learn\nCommunicate clearly and enjoy working with others\nAre comfortable in a fast-paced, high-performance environment\nHave a genuine interest in equities, markets and investing\nEligibility\nPenultimate-year student, graduating in summer 2027\nStudents from all degree disciplines encouraged to apply\nExpected or achieved 2:1 or above\nMinimum AAB at A-Level (or equivalent)\nFluency in English required; additional languages are an advantage\nRight to work in the UK for the full duration of the programme\nWhy Berenberg?\nWe\u2019re a leading European private bank with over 430 years of history, but our focus is firmly on the future. Our progress is driven by people who think independently, take responsibility early, and are encouraged to challenge the status quo.\nWe invest heavily in developing talent, reward collaboration and mutual support, and offer an environment where individuals can build long-term careers across teams, departments and geographies.\nKey information\nProgramme dates: 22 June \u2013 30 August 2026\nLocation: London - we are office based, 5 days a week\nApplications: Online only via our application management system, we recruit on a rolling basis.\nInternships available on the scheme: 20-25\nBerenberg is an Equal Opportunities Employer and values diversity of background, thought and experience. We are committed to creating an inclusive working environment where everyone can realise their full potential.\nWe\u2019re also committed to providing reasonable adjustments for candidates who require support during the recruitment process. Please contact graduates@berenberg.com to discuss.\nBack to job list\nApply\nShare this job:\nShare European Equities Summer Internship Programme 2026, London with a friend via e-mail",
        "application_url": "https://berenberg.avature.net/en_GB/careers/Login?jobId=2698",
        "metadata": {
            "Country": "United Kingdom",
            "City": "London",
            "Type of role": "Internship programme",
            "Working time": "Full-time",
            "Type of contract": "Internship",
            "Remaining openings": "18"
        },
        "link": "https://berenberg.avature.net/en_GB/careers/JobDetail/European-Equities-Summer-Internship-Programme-2026-London/2698"
    },
    {
        "title": null,
        "description_html": null,
        "description_text": "Fixed Income Sales Trader*\nGeneral information\nCountry\nGermany\nCity\nFrankfurt\nType of role\nProfessional\nWorking time\nFull-time\nType of contract\nPermanent\nDescription & Requirements\nFor our\nFixed Income Special Solutions Team\nin\nFrankfurt\nwe are looking to hire an:\nFixed Income Sales Trader*\nYour role in the team\nYou contribute to the desk\u2019s commercial performance by actively executing fixed income transactions and serving as a knowledgeable point of contact for clients. By closely monitoring market dynamics and macroeconomic signals, you provide informed insights that support client decision-making and trading strategies. You help strengthen long-term client relationships through continuous dialogue and market guidance, while also supporting the team with analytical input on pricing opportunities and handling essential operational tasks to ensure smooth daily desk operations.\nWhat will you do?\nTrading for commission in all relevant fixed income segments\nUnderstand drivers of relevant markets and establish a high degree of competence with clients around executing trades\nEnhancing relationships with clients, providing advice on Fixed Income market developments and key issues that may affect their trading strategies\nProvide support analysis of economic, market trends and other financial data to identify undervalued and overvalued Fixed Income products\nResponsibility for day-to-day administration work on the desk\nWho are we looking for?\nDegree-level education or equivalent professional experience, with a strong interest in financial markets, particularly fixed income\nAdvanced IT skills, including proficient use of standard Office applications and Bloomberg\nHigh standards of reliability, integrity and honesty, demonstrated through accurate, fair and trustworthy work\nRespectful and collaborative team behavior, with a commitment to sharing information and promoting compliance, ethics and integrity within the business\nStrong attention to detail and resilience when working under pressure in volatile market environments\nWhat we offer you:\nFlexible working hours within a 39-hour week\n30 days of annual leave plus additional days off on December 24 and 31\nA varied and exciting range of tasks in a modern and dynamic environment as well as a respectful working atmosphere\nTargeted support through internal and external training and development programmes\nBerenberg mentor system for structured and smooth onboarding\nVarious allowances (e.g. Germany ticket, JobRad, capital formation, a company-financed pension scheme, lunch subsidies or staff restaurant in Hamburg)\nAdditional benefits such as family services, working time account (e.g. for sabbaticals), corporate benefits and company health and sports programmes\nApply online now to join our team \u2013\nwe look forward to receiving your application!\nWe are a leading European private bank, with over 430 years of experience and deep rooted history, but we are still shaping and heavily investing in our future. Our progress and evolution are driven by our people. We encourage them to try new approaches, voice their opinions and achieve success in their own way. We provide opportunities for them to develop their talents, explore different career paths and achieve their full potential.\nWe\u2019re an ambitious, forward-looking business, backed by centuries of tradition and built on innovation. You\u2019ll find a culture that encourages people to think independently, act entrepreneurially and challenge the status quo. We place great importance on working on site, as we believe that being together in the office not only fosters creativity and efficiency, but also strengthens networks and builds trusting, collegial relationships. For us, this forms the foundation for productive and successful work. Together we collaborate to shape our business and fulfil our ambitious goals.\nWe welcome you to join us in our commitment to always do the right thing for our people, clients and our business \u2013\nOur future is where you take us!\nFor organisational reasons, we only accept applications that reach us via our online application management system on the website.\n*For reasons of better readability, the simultaneous use of multi-gender language forms is avoided. All personal designations apply equally to all genders. We welcome all applications, regardless of gender, nationality, ethnic origin, social background, disability, religion, age or sexual orientation. If you have any questions, please contact our recruitment team at recruitment@berenberg.de.\nBack to job list\nApply\nShare this job:\nShare Fixed Income Sales Trader* with a friend via e-mail",
        "application_url": "https://berenberg.avature.net/en_GB/careers/Login?jobId=2813",
        "metadata": {
            "Country": "Germany",
            "City": "Frankfurt",
            "Type of role": "Professional",
            "Working time": "Full-time",
            "Type of contract": "Permanent"
        },
        "link": "https://berenberg.avature.net/en_GB/careers/JobDetail/Fixed-Income-Sales-Trader/2813"
    }
]