[
    {
        "title": "Financial Controller",
        "description_html": null,
        "description_text": "General information\nOffice\nMadrid\nCountry\nSpain\nDate Published\n29-Jan-2026\nRef #\n2277\nArea\nAccounting\nType of Presence\nHybrid\nDescription & Requirements\nBuscamos un/a profesional para el puesto de Control de Gesti\u00f3n dentro del departamento financiero de nuestra filial en Iberia.\nEl candidato ideal contar\u00e1 con una experiencia entre 3 y 5 a\u00f1os en el \u00e1rea de control de gesti\u00f3n y finanzas, desempe\u00f1\u00e1ndose de manera eficaz en un entorno din\u00e1mico y con reportes a nivel internacional.\nEste puesto requiere un enfoque anal\u00edtico y detallado, as\u00ed como habilidades para trabajar en equipo y colaborar con diversas \u00e1reas de la empresa.\nFunciones:\nControl Financiero: Prestar soporte en el seguimiento y control de los indicadores financieros clave (KPI), asegurando la correcta alineaci\u00f3n con los objetivos estrat\u00e9gicos de la empresa.\nElaboraci\u00f3n de Informes: Prestar apoyo en la preparaci\u00f3n de informes financieros peri\u00f3dicos, an\u00e1lisis de variaciones y proyecciones para la alta direcci\u00f3n.Estos informes deber\u00e1n ser presentados tanto a nivel local como internacional.\nAn\u00e1lisis de Costes y Rentabilidad: Llevar a cabo an\u00e1lisis de rentabilidad por l\u00edneas de negocio, productos o servicios, ayudando a la toma de decisiones basadas en datos.\nSeguimiento del Desempe\u00f1o: Colaborar en la definici\u00f3n y seguimiento de presupuestos y previsiones financieras, y proponer acciones correctivas en caso de desv\u00edos.\nForecasting\n. Participar en la elaboraci\u00f3n y seguimiento del\nforecasting\nperi\u00f3dico de ventas y control de costes.\nMejora Continua: Identificar oportunidades de mejora en los procesos financieros y operativos, recomendando e implementando cambios que optimicen la eficiencia del control financiero.\nCumplimiento Normativo y Reportes Internacionales: Asegurar que todos los procesos y reportes cumplan con las normativas locales e internacionales, incluyendo las pol\u00edticas corporativas globales.\nControl y seguimiento de proyectos y resoluci\u00f3n de incidencias a petici\u00f3n de losresponsablesde negocio.\nRequisitos:\nFormaci\u00f3n Acad\u00e9mica:Grado en Econom\u00eda, Finanzas, Contabilidad o afines. Se valorar\u00e1 formaci\u00f3n adicional como un m\u00e1ster o cursos especializados en control de gesti\u00f3n o finanzas.\nExperiencia: Entre 3 y 5 a\u00f1os de experiencia en control de gesti\u00f3n, an\u00e1lisis financiero o \u00e1reas relacionadas dentro de un entorno corporativo o multinacional.\nConocimientos T\u00e9cnicos:\nDominio de herramientas de an\u00e1lisis financiero y control (Excel avanzado, Salesforce).\nConocimientos s\u00f3lidos y demostrables en contabilidad y an\u00e1lisis de costes.\nManejo de herramientas de visualizaci\u00f3n de datos (\nPower\nBI,\nTableu\n..)\nHabilidades y Competencias:\nCapacidad anal\u00edtica y atenci\u00f3n al detalle.\nAlta capacidad de organizaci\u00f3n y gesti\u00f3n de m\u00faltiples tareas.\nHabilidad para comunicar resultados y recomendaciones de manera clara y efectiva.\nProactividad y enfoque en la mejora continua.\nIdiomas:\nIngl\u00e9s\nfluido\n\u00bfQu\u00e9 ofrecemos?\nUbicaci\u00f3n:\nMadrid(Espa\u00f1a)\nModelo h\u00edbrido\nde asistencia a la oficina (2 d\u00edas/semana presencialidad).\nTres semanas al a\u00f1o de full remote.\nSeguro m\u00e9dico de salud.\nWellhub\n, para cuidar tu salud f\u00edsica y mental.\nRetribuci\u00f3n flexible, tendr\u00e1s ahorros fiscales en restauraci\u00f3n, transporte, guarder\u00eda, etc.\n28 d\u00edas de vacaciones al a\u00f1o.\nFormaci\u00f3n en idiomas.\nDescripci\u00f3n de la empresa\nSomos una empresa de datos, IA y experiencias que crea un impacto significativo y duradero a nivel global.\nTrabajamos estrechamente con nuestros clientes para dise\u00f1ar trayectorias de crecimiento basadas en datos y en\ninsights\norientados al impacto, asegurando la entrega de resultados concretos y medibles. Nuestro profundo conocimiento tecnol\u00f3gico y de arquitectura nos permite adem\u00e1s implementar de forma consistente soluciones relevantes, integradas y sostenibles a largo plazo.\nNuestro foco es siempre generar resultados con sentido; por eso dise\u00f1amos y ejecutamos activaciones impulsadas por datos que crean valor tangible a lo largo de todo el\nfunnel\ny optimizan la inversi\u00f3n en marketing, conectando con la audiencia de nuestros clientes all\u00ed donde se encuentra.\nDesde que\nMatteo\nde\nBrabant\nfund\u00f3 la compa\u00f1\u00eda en el a\u00f1o 2000, hemos crecido hasta convertirnos en un equipo internacional, diverso y altamente cualificado. En 2021, el fondo de inversi\u00f3n privado l\u00edder a nivel mundial\nArdian\nadquiri\u00f3 una participaci\u00f3n mayoritaria en JAKALA. Actualmente, tenemos nuestra sede en Mil\u00e1n y contamos con m\u00faltiples centros de excelencia y oficinas en todo el mundo.\nBack\nApply\nShare this job:\nFacebook\nLinkedIn\nEmail",
        "application_url": "https://careers.jakala.com/en_US/careers/ApplicationMethods?jobId=2309",
        "": {},
        "metadata": {
            "Office": "Madrid",
            "Country": "Spain",
            "Date Published": "29-Jan-2026",
            "Ref #": "2277",
            "Area": "Accounting",
            "Type of Presence": "Hybrid"
        },
        "link": "https://careers.jakala.com/en_US/careers/JobDetail/Financial-Controller/2309"
    },
    {
        "title": "CX Solutions Senior Consultant",
        "description_html": null,
        "description_text": "General information\nOffice\nGij\u00f3n, Madrid\nCountry\nSpain\nDate Published\n27-Jan-2026\nRef #\n2272\nArea\nMarketing\nType of Presence\nHybrid\nDescription & Requirements\nEn JAKALA buscamos un\nCX Solutions\n, con ganas de\ndise\u00f1ar, implementar y escalar soluciones de personalizaci\u00f3n y experimentaci\u00f3n\nque impacten directamente en la experiencia de cliente y en la conversi\u00f3n.\nSer\u00e1s responsable de la\nimplementaci\u00f3n t\u00e9cnica, optimizaci\u00f3n y evoluci\u00f3n de experiencias de personalizaci\u00f3n y experimentaci\u00f3n en Adobe Target\n, trabajando en entornos de\nalto tr\u00e1fico\ny con un fuerte\nfoco en conversi\u00f3n\n.\nResponsabilidades\nDise\u00f1o y ejecuci\u00f3n de experimentos y personalizaciones en Adobe Target\nImplementar tests A/B, multivariantes y experiencias de personalizaci\u00f3n avanzada, asegurando calidad t\u00e9cnica, performance y correcta medici\u00f3n de resultados.\nMaquetaci\u00f3n y desarrollo frontend\nDesarrollar e integrar experiencias utilizando\nJavaScript, HTML y CSS\n, aplicando buenas pr\u00e1cticas de\nresponsive design\n, accesibilidad y optimizaci\u00f3n de carga.\nIntegraci\u00f3n de audiencias y se\u00f1ales de datos\nConsumir audiencias y atributos procedentes de\nAdobe Experience Platform\nu otras fuentes de datos para habilitar segmentaciones y personalizaciones m\u00e1s precisas en Adobe Target.\nQA t\u00e9cnico y validaci\u00f3n de experimentos\nGarantizar la correcta ejecuci\u00f3n de las experiencias en distintos navegadores, dispositivos y contextos, validando tracking, condiciones de targeting y consistencia visual.\nAn\u00e1lisis y optimizaci\u00f3n continua\nColaborar en la lectura e interpretaci\u00f3n de resultados de experimentos, identificando insights t\u00e9cnicos y oportunidades de mejora para futuros tests.\nEficiencia y reutilizaci\u00f3n\nCrear componentes, snippets y patrones reutilizables que aceleren la ejecuci\u00f3n de experimentos y mejoren la escalabilidad del programa CRO.\nColaboraci\u00f3n con equipos CRO\nTrabajar estrechamente con perfiles de\nUX/UI, anal\u00edtica y negocio\npara traducir hip\u00f3tesis de conversi\u00f3n en soluciones t\u00e9cnicas bien ejecutadas.\nRequisitos\nMust have\nExperiencia s\u00f3lida en Adobe Target\nAl menos\n2 a\u00f1os de experiencia pr\u00e1ctica\nimplementando experimentos y personalizaciones en Adobe Target en entornos reales de CRO.\nDominio t\u00e9cnico frontend\nJavaScript, HTML y CSS con foco en asincron\u00eda, control de condiciones y compatibilidad cross\u2011browser.\nExperiencia en testing y personalizaci\u00f3n\nA/B testing, MVT, targeting por audiencias, condiciones contextuales y activaci\u00f3n de experiencias en producci\u00f3n.\nCapacidad de QA y debugging avanzado\nIdentificaci\u00f3n y resoluci\u00f3n de problemas en experiencias activas, validaci\u00f3n de tracking y an\u00e1lisis de incidencias.\nOrientaci\u00f3n a resultados y calidad\nAtenci\u00f3n al detalle, foco en impacto en conversi\u00f3n y compromiso con la excelencia t\u00e9cnica.\nIngl\u00e9s fluido (B2/C1)\nPara documentaci\u00f3n t\u00e9cnica y colaboraci\u00f3n con equipos internacionales.\nQu\u00e9\u00a0ofrecemos\nModelo\u00a0de\u00a0asistencia\u00a0a\u00a0la\u00a0oficina\u00a0h\u00edbrido.\nSeguro\u00a0m\u00e9dico\u00a0privado.\nAcceso\u00a0a\u00a0Wellhub\u00a0para\u00a0bienestar\u00a0f\u00edsico\u00a0y\u00a0mental.\nRetribuci\u00f3n\u00a0flexible\u00a0(restauraci\u00f3n,\u00a0transporte,\u00a0guarder\u00eda,\u00a0etc.).\n28\u00a0d\u00edas\u00a0de\u00a0vacaciones\u00a0al\u00a0a\u00f1o.\nTres\u00a0semanas\u00a0al\u00a0a\u00f1o\u00a0de\u00a0full\u00a0remote.\nPlan\u00a0de\u00a0carrera\u00a0adaptado\u00a0a\u00a0tus\u00a0inquietudes\u00a0profesionales.\nAcceso\u00a0a\u00a0certificaciones\u00a0(Google,\u00a0Salesforce,\u00a0Adobe).\nProgramas\u00a0de\u00a0formaci\u00f3n\u00a0tecnol\u00f3gica\u00a0(Jxpert).\nLaboratorio\u00a0de\u00a0pruebas\u00a0de\u00a0soluciones\u00a0tecnol\u00f3gicas\u00a0(Jlab).\nFormaci\u00f3n\u00a0en\u00a0idiomas.\nDescripci\u00f3n de la empresa:\nSomos\u00a0un\u00a0ecosistema\u00a0dise\u00f1ado\u00a0para\u00a0que\u00a0el\u00a0talento\u00a0y\u00a0las\u00a0soluciones\u00a0innovadoras\u00a0se\u00a0unan\u00a0para\u00a0impulsar\u00a0el\u00a0valor\u00a0para\u00a0las\u00a0organizaciones,\u00a0las\u00a0personas\u00a0y\u00a0la\u00a0sociedad.\nHoy\u00a0en\u00a0d\u00eda,\u00a0somos\u00a0la\u00a0empresa\u00a0l\u00edder\u00a0en\u00a0Martech\u00a0en\u00a0Europa,\u00a0con\u00a0sede\u00a0en\u00a0Mil\u00e1n\u00a0y\u00a0oficinas\u00a0en\u00a0todo\u00a0el\u00a0mundo.\u00a0Nuestro\u00a0enfoque\u00a0impulsado\u00a0por\u00a0datos,\u00a0respaldado\u00a0por\u00a0una\u00a0f\u00f3rmula\u00a0ganadora\u00a0de\u00a0estrategia,\u00a0innovaci\u00f3n,\u00a0transformaci\u00f3n\u00a0tecnol\u00f3gica,\u00a0compromiso\u00a0y\u00a0activaci\u00f3n,\u00a0es\u00a0la\u00a0piedra\u00a0angular\u00a0de\u00a0nuestro\u00a0trabajo.\nCon un equipo de 3,000 empleados, m\u00e1s de 900 clientes y proyectos en m\u00e1s de 30 pa\u00edses, y una facturaci\u00f3n que supera los 500 millones de euros, JAKALA emerge como un verdadero punto de referencia en el vasto panorama digital. Gracias a la contribuci\u00f3n de un equipo internacional compuesto por talentos vers\u00e1tiles y altamente calificados, la empresa ofrece soluciones \u00fanicas y personalizadas, anticipando los desaf\u00edos de un mercado en constante evoluci\u00f3n. Reconocida como\nEmpresa Great Place to Work 2024\n, JAKALA persigue sus objetivos con la firme creencia de que el bienestar de los empleados y un impacto positivo en el medio ambiente son elementos esenciales para garantizar un crecimiento sostenible.\nBack\nApply\nShare this job:\nFacebook\nLinkedIn\nEmail",
        "application_url": "https://careers.jakala.com/en_US/careers/ApplicationMethods?jobId=2304",
        "": {},
        "metadata": {
            "Office": "Gij\u00f3n, Madrid",
            "Country": "Spain",
            "Date Published": "27-Jan-2026",
            "Ref #": "2272",
            "Area": "Marketing",
            "Type of Presence": "Hybrid"
        },
        "link": "https://careers.jakala.com/en_US/careers/JobDetail/CX-Solutions-Senior-Consultant/2304"
    },
    {
        "title": "Head of UI Design (all genders)",
        "description_html": null,
        "description_text": "General information\nOffice\nHamburg\nCountry\nGermany\nDate Published\n27-Jan-2026\nRef #\n2274\nArea\nDesign\nType of Presence\nHybrid\nDescription & Requirements\nDu kannst komplexe digitale Interfaces branchen\u00fcbergreifend gestalten, verstehst es, Markenwelten in skalierbare UI\u2011Systeme zu \u00fcbersetzen und Teams sicher zu f\u00fchren? Du bist\nExpert:in\ndarin, eine klare kreative Vision im\nUI Design\naufzubauen und\nKolleg:innen\nfachlich wie disziplinarisch weiterzuentwickeln?\nWenn du in einer dynamischen Umgebung zugleich\nf\u00fchren\nund\noperativ gestalten\nm\u00f6chtest, bist du bei uns genau richtig.\nZum n\u00e4chstm\u00f6glichen Zeitpunkt suchen wir\neine:n\nmotivierten und engagierten\nHead\nof\nUI Design\n(all\ngenders\n)\nin Hamburg\n,\nhybrid\n.\nResponsibilities\nDu leitest das gesamte UI\u2011Gewerk fachlich und disziplinarisch und st\u00e4rkst die strategische Weiterentwi\ncklung\naller\nUI\u2011D\nesigner:innen\n.\nDu verantwortest die Ressourcenplanung und steuerst die Auslastung des UI\u2011Teams in enger Abstimmung mit\nProduct\nDesign Leads in unseren Projekten und anderen Gewerken.\nDu begleitest Recruiting\u2011Prozesse ma\u00dfgeblich, triffst Auswahlentscheidungen und sorgst f\u00fcr strukturiertes Onboarding neuer\nKolleg:innen\n.\nDu f\u00f6rderst eine inspirierende Designkultur, teilst Best Practices standort\u00fcbergreifend und agierst als\nSparringspartner:in\nf\u00fcr\nDesigner:innen\nund Leads.\nDu wirkst durch das Coaching deiner Teammitglieder indirekt an Projekten mit, arbeitest\nsituativ\naber\nauch\nhands\n-on in unseren laufenden Projekten mit\noder\nber\u00e4tst\nbei Bedarf\u00a0bei Pitches\nDu pr\u00e4sentierst UI\u2011Konzepte und Designentscheidungen \u00fcberzeugend gegen\u00fcber\nKund:innen\nund internen Stakeholdern.\nDu arbeitest eng mit den F\u00fchrungskr\u00e4ften weiterer Gewerke (z.B. UX) zusammen, um die fachliche Qualit\u00e4t sicherzustellen und den Reifegrad des Experience Departments zu steigern\nOverview\nJAKALA ist ein weltweit t\u00e4tiges IT\u2011 und Consulting\u2011Unternehmen im Bereich\nMartech\n, mit einem starken Fokus auf Daten und KI. Von den weltweit \u00fcber 3.300 Mitarbeitenden sind rund 230 in Hamburg und Berlin t\u00e4tig. Bei JAKALA Germany liegt der Schwerpunkt auf der Entwicklung\nvon individuellen Software\n\u2011L\u00f6sungen, haupts\u00e4chlich von sogenannten Digital Experience\nPlatforms\n(DXP), in denen Gesch\u00e4ftsprozesse entlang der Customer Journey digitalisiert werden. An der Schnittstelle von Strategie, Design und Technologie entwickelt JAKALA digitale Plattformen, Apps und andere Services, welche die digitalen Erlebnisse gro\u00dfer Marken ma\u00dfgeblich pr\u00e4gen. Zu den Kunden in Deutschland z\u00e4hlen beispielsweise TUI Cruises, Leica, die Hamburger Hochbahn oder das ZDF.\nQualifications\nDu verf\u00fcgst \u00fcber langj\u00e4hrige Erfahrung im\nUI Design\ndigitaler Produkte, Plattformen oder Services.\nDu gestaltest visuelle Systeme, Typografie, Layout, Motion und Farbwelten auf hohem Niveau und denkst in skalierbaren Designsystemen.\nDu nutzt\nFigma\nund andere UI\u2011Tools sicher und arbeitest routiniert in kollaborativen Design\u2011Setups.\nDu f\u00fchrst Teams empathisch, klar und mit fachlicher wie disziplinarischer Erfahrung.\nDu bewegst dich sicher in agilen Projektstrukturen und arbeitest gern eng mit UX, Tech, Strategie und Produktmanagement.\nDu argumentierst Designentscheidungen verst\u00e4ndlich, kommunizierst sicher auf Deutsch und Englisch und \u00fcberzeugst in Pr\u00e4sentationen.\nOffer\nDas bieten wir dir:\nJob in Vollzeit oder Teilzeit - du entscheidest\nHybrides Arbeitsmodell (Remote und/oder B\u00fcro) mit flexiblen Arbeitszeiten\nOffene und teamorientierte Unternehmenskultur\nWertsch\u00e4tzung deiner Ideen\nZuschuss f\u00fcr \u00d6PNV und\nBikeleasing\n-Option\nUrban Sports Club Membership\nW\u00f6chentliches gemeinsames Fr\u00fchst\u00fcck oder Mittagessen\nWenn du willst: Einstieg in unsere Hamburger Band (\nSchlagzeuger:in\ngesucht)\nWhat\nElse?\nWir wollen einen positiven Impact auf unsere Erde haben. Deshalb streben wir danach, auf nachhaltige Weise Wert f\u00fcr alle Interessengruppen zu schaffen und ber\u00fccksichtigen dabei Klima, Ethik und Qualit\u00e4t. 2021 haben wir uns entschieden, eine Benefit Corporation zu werden, um unser langfristiges Engagement f\u00fcr den Schutz der Prinzipien und Werte, die unser Handeln leiten, zu unterstreichen.\nBewirb dich noch heute. Wir freuen uns darauf, dich kennenzulernen.\nBack\nApply\nShare this job:\nFacebook\nLinkedIn\nEmail",
        "application_url": "https://careers.jakala.com/en_US/careers/ApplicationMethods?jobId=2306",
        "": {},
        "metadata": {
            "Office": "Hamburg",
            "Country": "Germany",
            "Date Published": "27-Jan-2026",
            "Ref #": "2274",
            "Area": "Design",
            "Type of Presence": "Hybrid"
        },
        "link": "https://careers.jakala.com/en_US/careers/JobDetail/Head-of-UI-Design-all-genders/2306"
    },
    {
        "title": "Experienced Professional | Data Scientist",
        "description_html": null,
        "description_text": "General information\nOffice\nMilano\nCountry\nItaly\nDate Published\n26-Jan-2026\nRef #\n2271\nArea\nManagement Consulting\nType of Presence\nHybrid\nDescription & Requirements\n\ud83d\udccd\nSede\n:\nMilano\n\ud83d\udc40\nRank: Senior Associate\nChi siamo\nJAKALA \u00e8 un'azienda che lavora su dati, intelligenza artificiale e sviluppo di esperienze per generare un impatto significativo e duraturo a livello globale.\nPresenti in oltre 30 citt\u00e0 in 21 paesi, i nostri team uniscono competenze su strategia, tecnologia, creativit\u00e0 e\noperations\nper offrire esperienze personalizzate e soluzioni trasformative ai nostri clienti, grazie al supporto di dati e intelligenza artificiale. I\nJakalers\nsono un gruppo eterogeneo di oltre 3.000 persone, animate da passione, ambizione e idee brillanti. Proprio questa combinazione unica di talenti \u00e8 il fattore distintivo che ha ispirato il nostro\npurpose\n:\nTogether\nto\nget\nthere\n.\nCreare un mondo migliore \u00e8 il nostro obiettivo ultimo: la nostra ambizione \u00e8 generare valore per tutti i nostri stakeholder in modo sostenibile, con particolare attenzione a etica, clima e qualit\u00e0. Nel 2021, abbiamo scelto di diventare una Societ\u00e0 Benefit, dimostrando il nostro impegno di lungo periodo e la volont\u00e0 di proteggere i principi e i valori che ogni giorno guidano le nostre azioni.\nCrediamo che la diversit\u00e0 sia la chiave del nostro successo e, per questo, siamo impegnati a creare un ambiente di lavoro inclusivo, dove ciascuno possa sentirsi valorizzato per la propria unicit\u00e0. Tutte le nostre opportunit\u00e0 di lavoro sono aperte ai candidati appartenenti alle categorie protette L.68/99.\nScopri il team Marketing Science\nAll\u2019interno della Service Line Marketing Science di JAKALA, siamo alla ricerca di un professionista con un forte orientamento analitico, spirito di collaborazione e voglia di crescere in un contesto dinamico e stimolante.\nEntrerai a far parte del team Marketing Data Science e contribuirai attivamente alla progettazione, implementazione e gestione di processi Big Data e pipeline di Machine Learning, lavorando fianco a fianco con Data Engineers e specialisti di Data Visualization, su progetti sfidanti ad alto impatto per clienti nazionali e internazionali.\n\ud83c\udfaf Le tue responsabilit\u00e0:\nEsplorare, interrogare e modellare grandi volumi di dati su Cloud Data Warehouse (es. Google BigQuery, Databricks) e su fonti marketing (adv platform, CRM, web/app analytics), trasformandoli in insight azionabili per guidare decisioni di crescita, efficienza media e redditivit\u00e0\nApplicazione di modelli di Marketing Mix Model e di Modelli di attribuzione per il marketing per valutare l'impatto dei canali media sulle vendite\nCostruire modelli di customer analytics (segmentazione, clustering, churn/propensity, CLV) per identificare opportunit\u00e0 di retention e upsell, e supportare strategie di personalizzazione e audience strategy (attivazioni su CRM/media)\nCreare report brevi e di alta qualit\u00e0 per spiegare i risultati e discuterne le implicazioni con i membri dei team interessati\nCollaborare con team cross-funzionali (media, CRO, CRM, tech) per tradurre domande di business in analisi e sperimentazioni, e portare in produzione output (dashboard, tabelle, automazioni)\nUtilizzo di modelli di Generative AI (OpenAI, Google, Open Source) applicati ad use-cases di marketing come creazione e generazione di contenuti, traduzione, generazione di immagini, valorizzazione di know how aziendale\n\ud83d\ude4c Se ti riconosci in queste caratteristiche, potremmo essere il perfetto match:\nLaurea in Informatica, Matematica, Statistica, Ingegneria o altre discipline scientifiche\nAlmeno 3 o 4 anni di esperienza nella progettazione di soluzioni analitiche in ambito gestione e analisi dei dati, data visualization, advanced analytics e machine learning\nConoscenza dei principali linguaggi di programmazione per la Data Science: Python, SQL, R.\nPassione/Interesse per il\u00a0digital\u00a0marketing\nFamiliarit\u00e0 con le principali soluzioni cloud (GCP, AWS, Azure) o precedenti esperienze nel\u00a0digital\u00a0marketing costituiranno elemento preferenziale\nCapacit\u00e0 di lavorare in\u00a0team\nBuona conoscenza lingua inglese scritta e orale\nConoscenza di base del framework di elaborazione di Big Data Spark\nsar\u00e0 considerato un plus\nPrecedenti esperienze lavorative nel marketing digitale, inclusa esperienza di consulenza\nsaranno considerati un plus\nEsperienza / progetti con librerie di Bayesian Modeling\nsaranno considerati un plus\n\ud83d\udc9c\nScopri nel video le ragioni per cui scegliere JAKALA come prossimo step di carriera:\nIn JAKALA crediamo che il tempo e il benessere delle persone vadano rispettati, sempre: incoraggiamo una presenza in ufficio di 10 giorni al mese, lasciando piena libert\u00e0 di lavorare da dove preferisci, sia in Italia che all\u2019interno della Comunit\u00e0 Europea.\nIl nostro sistema di Total Reward include convenzioni esclusive per viaggi, ristoranti, shopping, palestra e tempo libero, oltre a servizi gratuiti di telemedicina e supporto psicologico, pensati per te e per chi ami.\nInvestire nel nostro processo di selezione significa ricevere supporto autentico: un Recruiter dedicato ti accompagner\u00e0 con feedback personalizzati, consigli di carriera e insight sul tuo CV, a prescindere dall\u2019esito della candidatura. Niente AI, solo persone. E, grazie all\u2019iniziativa Your Time Back, ti restituiamo il tempo investito nei colloqui con un percorso di empowerment firmato Unobravo.\n\ud83c\udf31 Ready to start?\nNon \u00e8 solo una candidatura. \u00c8 un percorso che comincia ora. Inviaci il tuo CV: non vediamo l\u2019ora di conoscerti!\nBack\nApply\nShare this job:\nFacebook\nLinkedIn\nEmail",
        "application_url": "https://careers.jakala.com/en_US/careers/ApplicationMethods?jobId=2303",
        "": {},
        "metadata": {
            "Office": "Milano",
            "Country": "Italy",
            "Date Published": "26-Jan-2026",
            "Ref #": "2271",
            "Area": "Management Consulting",
            "Type of Presence": "Hybrid"
        },
        "link": "https://careers.jakala.com/en_US/careers/JobDetail/Experienced-Professional-Data-Scientist/2303"
    },
    {
        "title": "Creative Director (all genders)",
        "description_html": null,
        "description_text": "General information\nOffice\nHamburg\nCountry\nGermany\nDate Published\n25-Jan-2026\nRef #\n2273\nArea\nCreative\nType of Presence\nHybrid\nDescription & Requirements\nDu kannst ganzheitliche Markenerlebnisse entwickeln, die Menschen inspirieren, ber\u00fchren und in neue Welten eintauchen lassen? Du setzt neue Technologien kreativ ein und denkst kanal\u00fcbergreifen, um digitale Services und Kampagnen f\u00fcr unseren Touristikkunden zu gestalten? Du bist\nE\nxpert:in\ndarin, komplexe Inhalte in klare kreative Visionen zu \u00fcbersetzen? Wenn du in einer dynamischen Umgebung innovative Erlebnisse f\u00fcr\neine gro\u00dfe\nMarke schaffen m\u00f6chtest, bist du bei uns genau richtig.\nZum n\u00e4chstm\u00f6glichen Zeitpunkt suchen wir\neine:n\nmotivierte:n\nund\nengagierte:n\nCreative\nDirector\n(all\ngenders\n)\nin Hamburg\n,\nhybrid.\nResponsibilities\nDu konzipierst\nunter Einsatz von Technologien wie KI und neuen Plattform-Formaten kreative Kampagnen und digitale Erlebnisse, die Reisewelten, Sehns\u00fcchte und Markenidentit\u00e4ten emotional miteinander verbinden.\nDu entwickelst kanal\u00fcbergreifende Markenkommunikation und passt sie an spezifische Touchpoints wieTV,\nS\nocial\nMedia, Digitale Werbemittel, Funk und kreative Sonderideen\nan.\nDu begleitest Produktionen und Shootings und stellst sicher, dass kreative Konzepte konsistent umgesetzt werden.\nDu arbeitest eng mit Strategie-, Tech- und Entwicklungsteams zusammen\nDu koordinierst kreative Gewerke und sorgst f\u00fcr einen reibungslosen Wissenstransfer innerhalb der Projekte.\nDu\npr\u00e4sentierst\nKonzepte und L\u00f6sungen\nselbstbewusst gegen\u00fcber internen und externen Stakeholdern.\nDu f\u00fchrst Design Reviews durch, sicherst hohe Qualit\u00e4t und \u00fcberpr\u00fcfst die Konsistenz der Markenkommunikation.\nDu beobachtest Markt- und Technologietrends und leitest daraus kreative Impulse f\u00fcr neue Konzepte ab.\nOverview\nJAKALA ist ein weltweit t\u00e4tiges IT- und Consulting-Unternehmen im Bereich\nMartech\n, mit einem starken Fokus auf Daten und KI. Von den weltweit \u00fcber 3.300 Mitarbeitenden sind rund 230 in Hamburg und Berlin t\u00e4tig. Bei JAKALA Germany liegt der Schwerpunkt auf der Entwicklung von individuellen Software-L\u00f6sungen, haupts\u00e4chlich von sogenannten Digital Experience\nPlatforms\n(DXP), in denen Gesch\u00e4ftsprozesse entlang der Customer Journey digitalisiert werden. An der Schnittstelle von Strategie, Design und Technologie entwickelt JAKALA digitale Plattformen, Apps und andere Services, welche die digitalen Erlebnisse gro\u00dfer Marken ma\u00dfgeblich pr\u00e4gen. Zu den Kunden in Deutschland z\u00e4hlen beispielsweise TUI Cruises, Leica, die Hamburger Hochbahn oder das ZDF.\nQualifications\nDu verf\u00fcgst \u00fcber\nErfahrung\nauf CD-Level in Werbung, Design, Branding oder digitaler Kommunikation.\nDu bringst die F\u00e4higkeit mit, kreative Visionen langfristig zu entwickeln und zu \u00fcbersetzen.\nDu passt dich schnell ver\u00e4ndernden M\u00e4rkten, Technologien und Kundenanforderungen an.\nDu hast ein ausgepr\u00e4gtes Verst\u00e4ndnis f\u00fcr Kundenbed\u00fcrfnisse und ber\u00e4tst sicher auf Augenh\u00f6he.\nDu arbeitest empathisch und kollaborativ.\nDu bringst strategisches Denken mit und verstehst die Ausrichtung von Marken und Gesch\u00e4ftsmodellen.\nDu nutzt neue Technologien und Tools selbstverst\u00e4ndlich und explorativ.\nDu verf\u00fcgst \u00fcber Sicherheit in Pr\u00e4sentationen und Stakeholder-Kommunikation.\nOffer\nDas bieten wir dir:\nHybrides Arbeitsmodell (Remote undB\u00fcro) mit flexiblen Arbeitszeiten\nOffene und teamorientierte Unternehmenskultur\nWertsch\u00e4tzung deiner Ideen\nZuschuss f\u00fcr \u00d6PNV und\nBikeleasing\n-Option\nUrban Sports Club Membership\nW\u00f6chentliches gemeinsames Fr\u00fchst\u00fcck oder Mittagessen\nWenn du willst: Einstieg in unsere Hamburger Band (\nSchlagzeuger:in\ngesucht)\nWhat\nElse?\nWir wollen einen positiven Impact auf unsere Erde haben. Deshalb streben wir danach, auf nachhaltige Weise Wert f\u00fcr alle Interessengruppen zu schaffen und ber\u00fccksichtigen dabei Klima, Ethik und Qualit\u00e4t. 2021 haben wir uns entschieden, eine Benefit Corporation zu werden, um unser langfristiges Engagement f\u00fcr den Schutz der Prinzipien und Werte, die unser Handeln leiten, zu unterstreichen.\nBewirb dich noch heute. Wir freuen uns darauf, dich kennenzulernen.\nBack\nApply\nShare this job:\nFacebook\nLinkedIn\nEmail",
        "application_url": "https://careers.jakala.com/en_US/careers/ApplicationMethods?jobId=2305",
        "": {},
        "metadata": {
            "Office": "Hamburg",
            "Country": "Germany",
            "Date Published": "25-Jan-2026",
            "Ref #": "2273",
            "Area": "Creative",
            "Type of Presence": "Hybrid"
        },
        "link": "https://careers.jakala.com/en_US/careers/JobDetail/Creative-Director-all-genders/2305"
    },
    {
        "title": "AEM Architect Sites + Forms",
        "description_html": null,
        "description_text": "General information\nOffice\nMadrid, Full Remote\nCountry\nSpain\nDate Published\n23-Jan-2026\nRef #\n2256\nArea\nMarketing\nType of Presence\nHybrid\nDescription & Requirements\nEn Jakala buscamos un/a profesional con visi\u00f3n arquitect\u00f3nica, expertise profundo en AEM \u2014especialmente en\nAEM Forms\n\u2014 y la capacidad de trabajar de manera cercana, estrat\u00e9gica y colaborativa con nuestros. Si te apasiona dise\u00f1ar soluciones de alto impacto y quieres trabajar en proyectos de primer nivel, esta oportunidad es para ti.\nResponsabilidades / Funciones\nArquitectura de Vanguardia: Dise\u00f1ar\u00e1s soluciones integrales que conecten los servicios core del banco con la capa de experiencia de AEM.\nEspecialista en Forms: Liderar\u00e1s la implementaci\u00f3n de formularios adaptativos complejos, flujos de trabajo (workflows) y servicios de documentos (DoC), asegurando la seguridad y el cumplimiento normativo bancario.\nMentor\u00eda y Liderazgo: Actuar\u00e1s como referente t\u00e9cnico para el equipo de desarrollo, promoviendo mejores pr\u00e1cticas, revisiones de c\u00f3digo y patrones de dise\u00f1o scalables.\nVisi\u00f3n Estrat\u00e9gica: Colaborar\u00e1s mano a mano con los stakeholders del cliente para traducir necesidades de negocio en soluciones t\u00e9cnicas de alto rendimiento.\nRequisitos\nMust (imprescindibles)\nBuscamos a alguien que hable 'AEM' de forma nativa, pero que tambi\u00e9n sepa explicar conceptos complejos de forma clara.\nExperiencia s\u00f3lida: Al menos 5 a\u00f1os trabajando con AEM (6.5 o Cloud Service), habiendo evolucionado desde el desarrollo hasta la arquitectura.\nDominio de AEM Forms: Este es nuestro punto clave. Necesitamos que conozcas a fondo Adaptive Forms, Form Data Model (FDM), Adobe Sign integration y la gesti\u00f3n de procesos (OSGi workflows).\nStack Tecnol\u00f3gico: Experiencia profunda en Java, Sling, OSGi, JCR (Jackrabbit Oak) y Dispatcher.\nMentalidad de Integraci\u00f3n: Experiencia conectando AEM con APIs externas, microservicios y sistemas legacy (t\u00edpicos en entornos bancarios).\nSoft Skills: Capacidad anal\u00edtica, proactividad y ese toque de cercan\u00eda que nos define. En Jakala, el 'c\u00f3mo' importa tanto como el 'qu\u00e9'.\nNivel de ingl\u00e9s intermedio.\nQu\u00e9\u00a0ofrecemos\nModelo\u00a0de\u00a0asistencia\u00a0a\u00a0la\u00a0oficina\u00a0h\u00edbrido.\nSeguro\u00a0m\u00e9dico\u00a0privado.\nAcceso\u00a0a\u00a0Wellhub\u00a0para\u00a0bienestar\u00a0f\u00edsico\u00a0y\u00a0mental.\nRetribuci\u00f3n\u00a0flexible\u00a0(restauraci\u00f3n,\u00a0transporte,\u00a0guarder\u00eda,\u00a0etc.).\n28\u00a0d\u00edas\u00a0de\u00a0vacaciones\u00a0al\u00a0a\u00f1o.\nTres\u00a0semanas\u00a0al\u00a0a\u00f1o\u00a0de\u00a0full\u00a0remote.\nPlan\u00a0de\u00a0carrera\u00a0adaptado\u00a0a\u00a0tus\u00a0inquietudes\u00a0profesionales.\nAcceso\u00a0a\u00a0certificaciones\u00a0(Google,\u00a0Salesforce,\u00a0Adobe).\nProgramas\u00a0de\u00a0formaci\u00f3n\u00a0tecnol\u00f3gica\u00a0(Jxpert).\nLaboratorio\u00a0de\u00a0pruebas\u00a0de\u00a0soluciones\u00a0tecnol\u00f3gicas\u00a0(Jlab).\nFormaci\u00f3n\u00a0en\u00a0idiomas.\nDescripci\u00f3n de la empresa:\nSomos\u00a0un\u00a0ecosistema\u00a0dise\u00f1ado\u00a0para\u00a0que\u00a0el\u00a0talento\u00a0y\u00a0las\u00a0soluciones\u00a0innovadoras\u00a0se\u00a0unan\u00a0para\u00a0impulsar\u00a0el\u00a0valor\u00a0para\u00a0las\u00a0organizaciones,\u00a0las\u00a0personas\u00a0y\u00a0la\u00a0sociedad.\nHoy\u00a0en\u00a0d\u00eda,\u00a0somos\u00a0la\u00a0empresa\u00a0l\u00edder\u00a0en\u00a0Martech\u00a0en\u00a0Europa,\u00a0con\u00a0sede\u00a0en\u00a0Mil\u00e1n\u00a0y\u00a0oficinas\u00a0en\u00a0todo\u00a0el\u00a0mundo.\u00a0Nuestro\u00a0enfoque\u00a0impulsado\u00a0por\u00a0datos,\u00a0respaldado\u00a0por\u00a0una\u00a0f\u00f3rmula\u00a0ganadora\u00a0de\u00a0estrategia,\u00a0innovaci\u00f3n,\u00a0transformaci\u00f3n\u00a0tecnol\u00f3gica,\u00a0compromiso\u00a0y\u00a0activaci\u00f3n,\u00a0es\u00a0la\u00a0piedra\u00a0angular\u00a0de\u00a0nuestro\u00a0trabajo.\nCon un equipo de 3,000 empleados, m\u00e1s de 900 clientes y proyectos en m\u00e1s de 30 pa\u00edses, y una facturaci\u00f3n que supera los 500 millones de euros, JAKALA emerge como un verdadero punto de referencia en el vasto panorama digital. Gracias a la contribuci\u00f3n de un equipo internacional compuesto por talentos vers\u00e1tiles y altamente calificados, la empresa ofrece soluciones \u00fanicas y personalizadas, anticipando los desaf\u00edos de un mercado en constante evoluci\u00f3n. Reconocida como\nEmpresa Great Place to Work 2024\n, JAKALA persigue sus objetivos con la firme creencia de que el bienestar de los empleados y un impacto positivo en el medio ambiente son elementos esenciales para garantizar un crecimiento sostenible.\nBack\nApply\nShare this job:\nFacebook\nLinkedIn\nEmail",
        "application_url": "https://careers.jakala.com/en_US/careers/ApplicationMethods?jobId=2288",
        "": {},
        "metadata": {
            "Office": "Madrid, Full Remote",
            "Country": "Spain",
            "Date Published": "23-Jan-2026",
            "Ref #": "2256",
            "Area": "Marketing",
            "Type of Presence": "Hybrid"
        },
        "link": "https://careers.jakala.com/en_US/careers/JobDetail/AEM-Architect-Sites-Forms/2288"
    },
    {
        "title": "Intern | IT Headquarter",
        "description_html": null,
        "description_text": "General information\nOffice\nMilano\nCountry\nItaly\nDate Published\n23-Jan-2026\nRef #\n2267\nArea\nIT and Information Systems\nType of Presence\nHybrid\nDescription & Requirements\n\ud83d\udccd\nSede\n:\nMilano\nChi siamo\nJAKALA \u00e8 un'azienda che lavora su dati, intelligenza artificiale e sviluppo di esperienze per generare un impatto significativo e duraturo a livello globale.\nPresenti in oltre 30 citt\u00e0 in 21 paesi, i nostri team uniscono competenze su strategia, tecnologia, creativit\u00e0 e\noperations\nper offrire esperienze personalizzate e soluzioni trasformative ai nostri clienti, grazie al supporto di dati e intelligenza artificiale. I\nJakalers\nsono un gruppo eterogeneo di oltre 3.000 persone, animate da passione, ambizione e idee brillanti. Proprio questa combinazione unica di talenti \u00e8 il fattore distintivo che ha ispirato il nostro\npurpose\n:\nTogether\nto\nget\nthere\n.\nCreare un mondo migliore \u00e8 il nostro obiettivo ultimo: la nostra ambizione \u00e8 generare valore per tutti i nostri stakeholder in modo sostenibile, con particolare attenzione a etica, clima e qualit\u00e0. Nel 2021, abbiamo scelto di diventare una Societ\u00e0 Benefit, dimostrando il nostro impegno di lungo periodo e la volont\u00e0 di proteggere i principi e i valori che ogni giorno guidano le nostre azioni.\nCrediamo che la diversit\u00e0 sia la chiave del nostro successo e, per questo, siamo impegnati a creare un ambiente di lavoro inclusivo, dove ciascuno possa sentirsi valorizzato per la propria unicit\u00e0. Tutte le nostre opportunit\u00e0 di lavoro sono aperte ai candidati appartenenti alle categorie protette L.68/99.\nScopri\nil team\nIT\nNel team IT Headquarter\nsiamo alla ricerca di\ngiovani appassionati alle attivit\u00e0 di gestione ed evolutive dell\u2019intera infrastruttura IT\n. Come IT Analyst in stage entrerai in un ambiente dinamico\u00a0e collaborativo\u00a0dove potrai sviluppare competenze concrete nella gestione di un\u2019infrastruttura Enterprise moderna, sia on premise sia in Cloud.\n\ud83c\udfaf Ogni giorno sar\u00e0 diverso, ma eccoti un assaggio di quello che ti aspetta\nConfigurare ed installare gli strumenti aziendali in ambiente Microsoft/Apple (Pc e smartphone)\nGestire le segnalazioni degli utenti, risolvendole in autonomia o interfacciandosi con i supporti tecnici di II livello\nGestire le esigenze e i problemi, sia hardware che software, legate alle postazioni di lavoro (pc, stampanti, smartphone)\n\ud83d\udca1 Queste caratteristiche sono un ottimo punto di partenza per crescere insieme\nDiploma di istruzione secondaria di secondo grado o Laurea in informatica\nConoscenza di sistemi operativi\nMicrosoft/Apple client\nConoscenza base delle tecnologie di Collaboration di Microsoft 365\nForte propensione a precisione e cura al dettaglio\n\ud83d\ude80Ci brillano gli occhi se hai anche\nBuona conoscenza della lingua inglese\nspiccate capacit\u00e0 relazionali, propensione al lavoro di\nteam\ne di\nproblem\nsolving.\nEntusiasmo, curiosit\u00e0 e passione\n\ud83d\udc9c\nScopri nel video le ragioni per cui scegliere JAKALA come prossimo step di carriera\n:\nIn JAKALA crediamo che il tempo e il benessere delle persone vadano rispettati, sempre: incoraggiamo una presenza in ufficio di\n10\ngiorni al mese.\nIl nostro sistema di Total\nReward\ninclude convenzioni esclusive per viaggi, ristoranti, shopping, palestra e tempo libero, oltre a servizi gratuiti di telemedicina e supporto psicologico, pensati per te e per chi ami.\nInvestire nel nostro processo di selezione significa ricevere supporto autentico: un Recruiter dedicato ti accompagner\u00e0 con feedback personalizzati, consigli di carriera e insight sul tuo CV, a prescindere dall\u2019esito della candidatura. Niente AI, solo persone. E, grazie all\u2019iniziativa Your Time Back, ti restituiamo il tempo investito nei colloqui con un percorso di empowerment firmato\nUnobravo\n.\n\ud83c\udf31\u00a0Ready to start?\nNon \u00e8 solo una candidatura. \u00c8 un percorso che comincia ora. Inviaci il tuo CV: non vediamo l\u2019ora di conoscerti!\nBack\nApply\nShare this job:\nFacebook\nLinkedIn\nEmail",
        "application_url": "https://careers.jakala.com/en_US/careers/ApplicationMethods?jobId=2299",
        "": {},
        "metadata": {
            "Office": "Milano",
            "Country": "Italy",
            "Date Published": "23-Jan-2026",
            "Ref #": "2267",
            "Area": "IT and Information Systems",
            "Type of Presence": "Hybrid"
        },
        "link": "https://careers.jakala.com/en_US/careers/JobDetail/Intern-IT-Headquarter/2299"
    },
    {
        "title": "Experienced Professional | AI Solution Designer",
        "description_html": null,
        "description_text": "General information\nOffice\nMilano\nCountry\nItaly\nDate Published\n23-Jan-2026\nRef #\n2268\nArea\nOther\nType of Presence\nHybrid\nDescription & Requirements\n\ud83d\udccd\nSede\n:\nMilano\n\ud83d\udc40\nRank:\nManager\nChi siamo\nJAKALA \u00e8 un'azienda che lavora su dati, intelligenza artificiale e sviluppo di esperienze per generare un impatto significativo e duraturo a livello globale.\nPresenti in oltre 30 citt\u00e0 in 21 paesi, i nostri team uniscono competenze su strategia, tecnologia, creativit\u00e0 e\noperations\nper offrire esperienze personalizzate e soluzioni trasformative ai nostri clienti, grazie al supporto di dati e intelligenza artificiale. I\nJakalers\nsono un gruppo eterogeneo di oltre 3.000 persone, animate da passione, ambizione e idee brillanti. Proprio questa combinazione unica di talenti \u00e8 il fattore distintivo che ha ispirato il nostro\npurpose\n:\nTogether\nto\nget\nthere\n.\nCreare un mondo migliore \u00e8 il nostro obiettivo ultimo: la nostra ambizione \u00e8 generare valore per tutti i nostri stakeholder in modo sostenibile, con particolare attenzione a etica, clima e qualit\u00e0. Nel 2021, abbiamo scelto di diventare una Societ\u00e0 Benefit, dimostrando il nostro impegno di lungo periodo e la volont\u00e0 di proteggere i principi e i valori che ogni giorno guidano le nostre azioni.\nCrediamo che la diversit\u00e0 sia la chiave del nostro successo e, per questo, siamo impegnati a creare un ambiente di lavoro inclusivo, dove ciascuno possa sentirsi valorizzato per la propria unicit\u00e0. Tutte le nostre opportunit\u00e0 di lavoro sono aperte ai candidati appartenenti alle categorie protette L.68/99.\nScopri il team J-Science e Solution Design\nTi appassionano i dati, l\u2019intelligenza artificiale e la tecnologia? Nel team J-Science di JAKALA lavoriamo ogni giorno per trasformare queste tecnologie in soluzioni concrete e ad alto impatto per le aziende.\nSiamo un centro di eccellenza con sedi a Milano, Torino, Rende e Roma, e ci occupiamo di GenAI, Data Science, Location Intelligence e sviluppo di piattaforme, progettando e sviluppando soluzioni avanzate per clienti di grandi dimensioni su molte industry.\nInnoviamo per creare valore reale e accessibile, in contesti complessi e sfidanti.\nAll'interno di J-Science, il team di Solution Design si occupa di dialogare con i clienti nelle fasi iniziali dei progetti, per trasformare brief in progettualit\u00e0 concrete, confrontandosi con tutti gli esperti di ogni area per creare piani di progetto solidi e di impatto.\nSolution Design \u00e8 anche in prima linea su tutti quei progetti di AI dove sono richieste competenze pi\u00f9 legate ai mondi di AI Strategy e AI Adoption.\n\ud83c\udfaf\nLe tue responsabilit\u00e0:\nAnalizzare e interpretare le esigenze di clienti appartenenti a differenti industry, traducendo bisogni di business complessi in soluzioni di Artificial Intelligence ad alto impatto strategico\nGuidare l\u2019ideazione, la strutturazione e la presentazione di proposte progettuali AI (Machine Learning, Generative AI, RAG, soluzioni di automazione e piattaforme SaaS), operando con elevato grado di autonomia e responsabilit\u00e0\nGestire end-to-end i nostri progetti AI, dalla fase di prevendita e definizione dell\u2019offerta fino alla delivery funzionale, garantendo il coordinamento tecnico e il rispetto di tempi, qualit\u00e0 e obiettivi\nDefinire e validare architetture logiche e funzionali (schemi, flussi, use case) volte a rappresentare in modo chiaro il valore di business e la sostenibilit\u00e0 delle soluzioni proposte\nCollaborare in modo strutturato e continuativo con team multidisciplinari assicurando l\u2019efficace implementazione delle soluzioni progettate\nContribuire a iniziative di AI Strategy e AI Adoption, supportando i clienti anche nei processi di trasformazione organizzativa, change management e adozione delle nuove tecnologie\nMantenere una costante attivit\u00e0 di aggiornamento sull\u2019evoluzione dell\u2019ecosistema AI, traducendo le principali innovazioni in opportunit\u00e0 concrete e applicabili per il business\nPresentare in autonomia progetti, avanzamenti e risultati a stakeholder di livello executive e C-level, garantendo chiarezza, solidit\u00e0 analitica e orientamento ai risultati.\n\ud83d\ude4c\nSe ti riconosci in queste caratteristiche, potremmo essere il perfetto match:\nEsperienza significativa (5+ anni) in ruoli di consulenza, vendita consulenziale o project/program management su progetti tecnologici e di Artificial Intelligence, maturata in contesti mediamente complessi e orientati al valore\nUtilizzo avanzato e quotidiano di strumenti di AI generativa, accompagnato da una forte curiosit\u00e0 intellettuale e dalla capacit\u00e0 di anticipare le evoluzioni del settore\nSolida comprensione dei concetti principali del mondo dell'AI e dello sviluppo software, con comprovata capacit\u00e0 di tradurli in benefici concreti per il business e comunicarli efficacemente a stakeholder non tecnici\nCapacit\u00e0 di gestione autonoma di clienti e iniziative complesse, con responsabilit\u00e0 diretta su obiettivi, priorit\u00e0 e risultati\nEccellenti capacit\u00e0 analitiche, di sintesi e comunicazione, unite a una spiccata attitudine alla presentazione e alla negoziazione\nEsperienze in consulenza, startup, scale-up o contesti ad alta velocit\u00e0 e innovazione saranno considerate un forte elemento distintivo\nInglese fluente\n\ud83d\udc9c\nScopri in questo video le ragioni per cui scegliere JAKALA come prossimo step di carriera\nIn JAKALA crediamo che il tempo e il benessere delle persone vadano rispettati, sempre: incoraggiamo una presenza in ufficio di10giorni al mese, lasciando piena libert\u00e0 di lavorare da dove preferisci, sia in Italia che all\u2019interno della Comunit\u00e0 Europea.\nIl nostro sistema di Total Reward include convenzioni esclusive per viaggi, ristoranti, shopping, palestra e tempo libero, oltre a servizi gratuiti di telemedicina e supporto psicologico, pensati per te e per chi ami.\nInvestire nel nostro processo di selezione significa ricevere supporto autentico: un Recruiter dedicato ti accompagner\u00e0 con feedback personalizzati, consigli di carriera e insight sul tuo CV, a prescindere dall\u2019esito della candidatura. Niente AI, solo persone. E, grazie all\u2019iniziativa Your Time Back, ti restituiamo il tempo investito nei colloqui con un percorso di empowerment firmato\u00a0Unobravo.\n\ud83c\udf31\nReady to start?\nIl ruolo \u00e8 solo il punto di partenza. Il resto lo metti tu. Inviaci il tuo CV, noi non vediamo l\u2019ora di conoscerti!\nBack\nApply\nShare this job:\nFacebook\nLinkedIn\nEmail",
        "application_url": "https://careers.jakala.com/en_US/careers/ApplicationMethods?jobId=2300",
        "": {},
        "metadata": {
            "Office": "Milano",
            "Country": "Italy",
            "Date Published": "23-Jan-2026",
            "Ref #": "2268",
            "Area": "Other",
            "Type of Presence": "Hybrid"
        },
        "link": "https://careers.jakala.com/en_US/careers/JobDetail/Experienced-Professional-AI-Solution-Designer/2300"
    },
    {
        "title": "Feria de Empleo de la Facultad de Ciencias",
        "description_html": null,
        "description_text": "General information\nOffice\nGij\u00f3n\nCountry\nSpain\nDate Published\n23-Jan-2026\nRef #\n2270\nArea\nMarketing\nType of Presence\nHybrid\nDescription & Requirements\n\u00a1En JAKALA te estamos buscando!\nSi te gustar\u00eda trabajar con nosotros d\u00e9janos el CV en esta oferta y nuestro equipo de Recruiting se pondr\u00e1 en contacto contigo.\nBack\nApply\nShare this job:\nFacebook\nLinkedIn\nEmail",
        "application_url": "https://careers.jakala.com/en_US/careers/ApplicationMethods?jobId=2302",
        "": {},
        "metadata": {
            "Office": "Gij\u00f3n",
            "Country": "Spain",
            "Date Published": "23-Jan-2026",
            "Ref #": "2270",
            "Area": "Marketing",
            "Type of Presence": "Hybrid"
        },
        "link": "https://careers.jakala.com/en_US/careers/JobDetail/Feria-de-Empleo-de-la-Facultad-de-Ciencias/2302"
    },
    {
        "title": "Experienced Professional | Order Management (Loyalty)",
        "description_html": null,
        "description_text": "General information\nOffice\nNichelino\nCountry\nItaly\nDate Published\n22-Jan-2026\nRef #\n2260\nArea\nSupply Chain\nType of Presence\nHybrid\nDescription & Requirements\n\ud83d\udccd\nSede\n:\nNichelino (TO)\n\ud83d\udc40\nRank:\nManager, Senior Manager\nChi siamo\nJAKALA \u00e8 un'azienda che lavora su dati, intelligenza artificiale e sviluppo di esperienze per generare un impatto significativo e duraturo a livello globale.\nPresenti in oltre 30 citt\u00e0 in 21 paesi, i nostri team uniscono competenze su strategia, tecnologia, creativit\u00e0 e\noperations\nper offrire esperienze personalizzate e soluzioni trasformative ai nostri clienti, grazie al supporto di dati e intelligenza artificiale. I\nJakalers\nsono un gruppo eterogeneo di oltre 3.000 persone, animate da passione, ambizione e idee brillanti. Proprio questa combinazione unica di talenti \u00e8 il fattore distintivo che ha ispirato il nostro\npurpose\n:\nTogether\nto\nget\nthere\n.\nCreare un mondo migliore \u00e8 il nostro obiettivo ultimo: la nostra ambizione \u00e8 generare valore per tutti i nostri stakeholder in modo sostenibile, con particolare attenzione a etica, clima e qualit\u00e0. Nel 2021, abbiamo scelto di diventare una Societ\u00e0 Benefit, dimostrando il nostro impegno di lungo periodo e la volont\u00e0 di proteggere i principi e i valori che ogni giorno guidano le nostre azioni.\nCrediamo che la diversit\u00e0 sia la chiave del nostro successo e, per questo, siamo impegnati a creare un ambiente di lavoro inclusivo, dove ciascuno possa sentirsi valorizzato per la propria unicit\u00e0. Tutte le nostre opportunit\u00e0 di lavoro sono aperte ai candidati appartenenti alle categorie protette L.68/99.\nScopri il team Order Management\nIl team Order Management si occupa della supervisione e del monitoraggio della produzione della supply chain, garantendo il corretto flusso degli ordini e dei processi operativi. Lavora a supporto del team Procurement, collaborando con fornitori e stakeholder interni per assicurare efficienza e continuit\u00e0.\n\ud83c\udfaf Le tue responsabilit\u00e0:\nGestione delle relazioni con i fornitori per individuare le migliori soluzioni di consegna, in linea con gli accordi di procurement\nElaborazione delle richieste e aggiornamento costante sullo stato degli ordini\nMonitoraggio degli ordini per garantire consegne puntuali e segnalazione di eventuali discrepanze a fornitori e management aziendale\nSupervisione delle produzioni presso terzi di prodotti a marchio JAKALA, con presidio delle fasi di produzione (verifica della reale capacit\u00e0 produttiva, gestione delle criticit\u00e0 ed elaborazione di piani alternativi per assicurare il risultato)\nOttimizzazione dei flussi operativi\n\ud83d\ude4c Se ti riconosci in queste caratteristiche, potremmo essere il perfetto match:\nLaurea, preferibilmente in ambito economico\nConoscenza dei flussi di acquisto merce e della supply chain, con esperienza pregressa nel ruolo di almeno 5 anni\nConoscenza dei processi di spedizione e importazione della merce (loading, booking, documentazione necessaria), con esclusione della gestione dei rapporti con gli spedizionieri\nSpiccate capacit\u00e0 di analisi, problem solving e proattivit\u00e0\nOttime capacit\u00e0 organizzative e relazionali\nEsperienza pregressa nel coordinamento di un team\nOttima conoscenza della lingua inglese\nOttima padronanza del pacchetto MS Office\n\ud83d\udc9c\nScopri in questo video le ragioni per cui scegliere JAKALA come prossimo step di carriera\nIn JAKALA crediamo che il tempo e il benessere delle persone vadano rispettati, sempre: incoraggiamo una presenza in ufficio di 10 giorni al mese, lasciando piena libert\u00e0 di lavorare da dove preferisci, sia in Italia che all\u2019interno della Comunit\u00e0 Europea.\nIl nostro sistema di Total Reward include convenzioni esclusive per viaggi, ristoranti, shopping, palestra e tempo libero, oltre a servizi gratuiti di telemedicina e supporto psicologico, pensati per te e per chi ami.\nInvestire nel nostro processo di selezione significa ricevere supporto autentico: un Recruiter dedicato ti accompagner\u00e0 con feedback personalizzati, consigli di carriera e insight sul tuo CV, a prescindere dall\u2019esito della candidatura. Niente AI, solo persone. E, grazie all\u2019iniziativa Your Time Back, ti restituiamo il tempo investito nei colloqui con un percorso di empowerment firmato Unobravo.\n\ud83c\udf31 Ready to start?\nNon \u00e8 solo una candidatura. \u00c8 un percorso che comincia ora. Inviaci il tuo CV: non vediamo l\u2019ora di conoscerti!\nBack\nApply\nShare this job:\nFacebook\nLinkedIn\nEmail",
        "application_url": "https://careers.jakala.com/en_US/careers/ApplicationMethods?jobId=2292",
        "": {},
        "metadata": {
            "Office": "Nichelino",
            "Country": "Italy",
            "Date Published": "22-Jan-2026",
            "Ref #": "2260",
            "Area": "Supply Chain",
            "Type of Presence": "Hybrid"
        },
        "link": "https://careers.jakala.com/en_US/careers/JobDetail/Experienced-Professional-Order-Management-Loyalty/2292"
    },
    {
        "title": "Experienced Professional | Compliance & Quality Control (Loyalty)",
        "description_html": null,
        "description_text": "General information\nOffice\nNichelino\nCountry\nItaly\nDate Published\n22-Jan-2026\nRef #\n2263\nArea\nQuality\nType of Presence\nHybrid\nDescription & Requirements\n\ud83d\udccd\nSede\n:\nNichelino (TO)\n\ud83d\udc40\nRank:\nManager, Senior Manager\nChi siamo\nJAKALA \u00e8 un'azienda che lavora su dati, intelligenza artificiale e sviluppo di esperienze per generare un impatto significativo e duraturo a livello globale.\nPresenti in oltre 30 citt\u00e0 in 21 paesi, i nostri team uniscono competenze su strategia, tecnologia, creativit\u00e0 e\noperations\nper offrire esperienze personalizzate e soluzioni trasformative ai nostri clienti, grazie al supporto di dati e intelligenza artificiale. I\nJakalers\nsono un gruppo eterogeneo di oltre 3.000 persone, animate da passione, ambizione e idee brillanti. Proprio questa combinazione unica di talenti \u00e8 il fattore distintivo che ha ispirato il nostro\npurpose\n:\nTogether\nto\nget\nthere\n.\nCreare un mondo migliore \u00e8 il nostro obiettivo ultimo: la nostra ambizione \u00e8 generare valore per tutti i nostri stakeholder in modo sostenibile, con particolare attenzione a etica, clima e qualit\u00e0. Nel 2021, abbiamo scelto di diventare una Societ\u00e0 Benefit, dimostrando il nostro impegno di lungo periodo e la volont\u00e0 di proteggere i principi e i valori che ogni giorno guidano le nostre azioni.\nCrediamo che la diversit\u00e0 sia la chiave del nostro successo e, per questo, siamo impegnati a creare un ambiente di lavoro inclusivo, dove ciascuno possa sentirsi valorizzato per la propria unicit\u00e0. Tutte le nostre opportunit\u00e0 di lavoro sono aperte ai candidati appartenenti alle categorie protette L.68/99.\nScopri il team Compliance & Quality Control\nIl team Compliance & Quality Control si occupa di garantire la conformit\u00e0 normativa e gli standard qualitativi dei prodotti, collaborando con Procurement e con le funzioni coinvolte nello sviluppo. Coordina le attivit\u00e0 di certificazione e di verifica qualit\u00e0 prodotto relativamente alle produzioni assegnate ai fornitori JAKALA.\n\ud83c\udfaf Le tue responsabilit\u00e0:\nInterfaccia con il team Procurement e con tutte le funzioni aziendali coinvolte nelle fasi di definizione e sviluppo del prodotto\nCollaborazione alla definizione degli standard qualitativi, con verifica del rispetto dei requisiti di sicurezza in conformit\u00e0 alle normative vigenti a livello europeo e internazionale\nGestione dei rapporti con Enti Terzi di Certificazione per la definizione dei piani di test e delle attivit\u00e0 di ispezione del prodotto\nApplicazione e presidio dello standard ISO 9001 e dei principali elementi del Sistema di Gestione della Qualit\u00e0 nelle attivit\u00e0 operative\nUtilizzo dei principali strumenti di analisi, controllo e miglioramento in ambito qualit\u00e0 (es. 5 Why, Risk Assessment, FMEA, 8D Report, diagramma di Ishikawa, analisi di Pareto)\n\ud83d\ude4c Se ti riconosci in queste caratteristiche, potremmo essere il perfetto match:\nEsperienza pregressa in ruolo analogo di almeno 5 anni\nConoscenza delle principali normative di conformit\u00e0 prodotto, in particolare MOCA ed EN71\nOttima conoscenza della lingua inglese\nOttima padronanza del pacchetto MS Office\nSpiccate capacit\u00e0 di analisi, problem solving e proattivit\u00e0\nOttime capacit\u00e0 organizzative e relazionali\nEsperienza pregressa nel coordinamento di un team\n\ud83d\udc9c\nScopri in questo video le ragioni per cui scegliere JAKALA come prossimo step di carriera\nIn JAKALA crediamo che il tempo e il benessere delle persone vadano rispettati, sempre: incoraggiamo una presenza in ufficio di 10 giorni al mese, lasciando piena libert\u00e0 di lavorare da dove preferisci, sia in Italia che all\u2019interno della Comunit\u00e0 Europea.\nIl nostro sistema di Total Reward include convenzioni esclusive per viaggi, ristoranti, shopping, palestra e tempo libero, oltre a servizi gratuiti di telemedicina e supporto psicologico, pensati per te e per chi ami.\nInvestire nel nostro processo di selezione significa ricevere supporto autentico: un Recruiter dedicato ti accompagner\u00e0 con feedback personalizzati, consigli di carriera e insight sul tuo CV, a prescindere dall\u2019esito della candidatura. Niente AI, solo persone. E, grazie all\u2019iniziativa Your Time Back, ti restituiamo il tempo investito nei colloqui con un percorso di empowerment firmato Unobravo.\n\ud83c\udf31 Ready to start?\nNon \u00e8 solo una candidatura. \u00c8 un percorso che comincia ora. Inviaci il tuo CV: non vediamo l\u2019ora di conoscerti!\nBack\nApply\nShare this job:\nFacebook\nLinkedIn\nEmail",
        "application_url": "https://careers.jakala.com/en_US/careers/ApplicationMethods?jobId=2295",
        "": {},
        "metadata": {
            "Office": "Nichelino",
            "Country": "Italy",
            "Date Published": "22-Jan-2026",
            "Ref #": "2263",
            "Area": "Quality",
            "Type of Presence": "Hybrid"
        },
        "link": "https://careers.jakala.com/en_US/careers/JobDetail/Experienced-Professional-Compliance-Quality-Control-Loyalty/2295"
    },
    {
        "title": "(Junior) UX Designer (all genders)",
        "description_html": null,
        "description_text": "General information\nOffice\nFull Remote, Berlin, Hamburg, Vienna\nCountry\nGermany\nDate Published\n22-Jan-2026\nRef #\n2265\nArea\nDesign\nType of Presence\nHybrid\nDescription & Requirements\nDu kannst Nutzerbed\u00fcrfnisse erkennen und in intuitive Interfaces \u00fcbersetzen? Du verstehst, wie man komplexe Anforderungen in\u00a0klar\u00a0strukturierte Konzepte\u00a0verwandelt? Wenn du Lust hast, in einer dynamischen Umgebung f\u00fcr verschiedene Kunden und spannende Pitches kreative L\u00f6sungen zu entwickeln, bist du bei uns genau richtig.\nZum n\u00e4chstm\u00f6glichen Zeitpunkt suchen wir einen motivierten und engagierten (Junior)\nUX Designer\n(all\ngenders\n)\nin Hamburg, Berlin oder Wien, hybrid oder remote.\nResponsibilities\nDu arbeitest interdisziplin\u00e4r mit Teams aus\nUI Design\n, Development und Projektmanagement zusammen, um gemeinsam vielseitige Projekte zu realisieren\nDu erstellst Informationsarchitekturen und zielf\u00fchrende\nUserflows\nund achtest dabei auf eine gute Nutzerf\u00fchrung\nDuunterst\u00fctzt bei der Entwicklung vonKonzeptenf\u00fcr digitale Produkte, sei es \"\nfrom\nScratch\" oder als Optimierung bereits bestehender Konzepte - du bringst frische Perspektiven ein\nDu \u00fcbernimmstSt\u00fcck f\u00fcr St\u00fcckdie konzeptionelle Verantwortung f\u00fcr deine Ideen und entwickelst diese Konzepte proaktiv weiter, um Innovationen voranzutreiben\nDu bist\nAnsprechpartner:in\nf\u00fcr deine Produkt-Konzepte, sowohl intern im Team als auch externbegleitendin Kunden-Meetings und Workshops, und vertrittst deine Visionen \u00fcberzeugend\nOverview\nJAKALA ist ein weltweit t\u00e4tiges IT- und Consulting-Unternehmen im Bereich\nMartech\n, mit einem starken Fokus auf Daten und KI. Von den weltweit \u00fcber 3.300 Mitarbeitenden sind rund 230 in Hamburg und Berlin t\u00e4tig.\nBei JAKALA Germany liegt der Schwerpunkt auf der Entwicklung von individuellen Software-L\u00f6sungen, haupts\u00e4chlich von sogenannten Digital Experience\nPlatforms\n(DXP), in denen Gesch\u00e4ftsprozesse entlang der Customer Journey digitalisiert werden. An der Schnittstelle von Strategie, Design und Technologie entwickelt JAKALA digitale Plattformen, Apps und andere Services, welche die digitalen Erlebnisse gro\u00dfer Marken ma\u00dfgeblich pr\u00e4gen. Zu den Kunden in Deutschland z\u00e4hlen beispielsweise TUI Cruises, Leica, die Hamburger Hochbahn oder das ZDF.\nQualifications\nDu bringst erste Erfahrung im UX-Bereich mit, idealerweise im Agentur-Umfeld\nDeine analytischen F\u00e4higkeiten bef\u00e4higen dich, Probleme zu erkennen und nutzerzentrierte L\u00f6sungen zu entwickeln, ohne die Gesch\u00e4ftsziele unsererKunden aus den Augen zu verlieren\nDu bist versiert im Umgang mit Tools wie\nFigma\nund Keynote und kennst dich idealerweise bereits mit Design-\nThinking\n-Methoden aus\nStrategisches Denken, ein Blick f\u00fcr das gro\u00dfe Ganze und eine Leidenschaft f\u00fcr die L\u00f6sung komplexer Herausforderungen zeichnen dich aus\nMotivation und L\u00f6sungsorientierung kennzeichnen deine t\u00e4gliche Arbeit, mit dem Ziel, Produkte und Kundenbeziehungen weiterzuentwickeln\nDu pr\u00e4sentierst konzeptionelle Ans\u00e4tze digitaler Produkte mit Begeisterung und \u00dcberzeugungskraft\nDu kommunizierst auch in einem remote-/hybrid-Umfeld gerne intensiv auf deutsch und englisch\nOffer\nDas bieten wir dir:\nJob in Vollzeit oder Teilzeit - du entscheidest\nHybrides Arbeitsmodell (Remote und B\u00fcro) mit flexiblen Arbeitszeiten\nOffene und teamorientierte Unternehmenskultur\nWertsch\u00e4tzung deiner Ideen\nZuschuss f\u00fcr \u00d6PNV und\nBikeleasing\n-Option\nUrban Sports Club Membership\nW\u00f6chentliches gemeinsames Fr\u00fchst\u00fcck oder Mittagessen\nWenn du willst: Einstieg in unsere Hamburger Band (\nSchlagzeuger:in\ngesucht)\nWhat\nelse\n?\nWir wollen einen positiven Impact auf unsere Erde haben. Deshalb streben wir danach, auf nachhaltige Weise Wert f\u00fcr alle Interessengruppen zu schaffen und ber\u00fccksichtigen dabei Klima, Ethik und Qualit\u00e4t. 2021 haben wir uns entschieden, eine Benefit Corporation zu werden, um unser langfristiges Engagement f\u00fcr den Schutz der Prinzipien und Werte, die unser Handeln leiten, zu unterstreichen.\nBewirb dich noch heute. Wir freuen uns darauf, dich kennenzulernen.\nBack\nApply\nShare this job:\nFacebook\nLinkedIn\nEmail",
        "application_url": "https://careers.jakala.com/en_US/careers/ApplicationMethods?jobId=2297",
        "": {},
        "metadata": {
            "Office": "Full Remote, Berlin, Hamburg, Vienna",
            "Country": "Germany",
            "Date Published": "22-Jan-2026",
            "Ref #": "2265",
            "Area": "Design",
            "Type of Presence": "Hybrid"
        },
        "link": "https://careers.jakala.com/en_US/careers/JobDetail/Junior-UX-Designer-all-genders/2297"
    },
    {
        "title": "(Junior) Product Designer (all genders) - Schwerpunkt UX",
        "description_html": null,
        "description_text": "General information\nOffice\nFull Remote, Berlin, Hamburg, Vienna\nCountry\nGermany\nDate Published\n22-Jan-2026\nRef #\n2266\nArea\nDesign\nType of Presence\nHybrid\nDescription & Requirements\nDu denkst digitale Produkte ganzheitlich \u2013 aus Nutzer-\nund\nGesch\u00e4ftsperspektive? Du verbindest UX-Konzeption mit einem guten Gesp\u00fcr f\u00fcr UI-Details und Produktlogik und m\u00f6chtest digitale Produkte nicht nur gestalten, sondern aktiv weiterentwickeln?\nWenn du Lust hast, Verantwortung f\u00fcr Produktbereiche zu \u00fcbernehmen, Business-Ziele mitzudenken und gemeinsam mit interdisziplin\u00e4ren Teams nachhaltige Produktl\u00f6sungen zu schaffen, bist du bei uns genau richtig.\nZum n\u00e4chstm\u00f6glichen Zeitpunkt suchen wir einen motivierten und engagierten (Junior)\nProduct\nDesigner (all\ngenders\n)\nmit dem Schwerpunkt auf UX\nin Hamburg, Berlin oder Wien, hybrid oder remote.\nResponsibilities\nDu arbeitest interdisziplin\u00e4r mit Teams ausUX &UI Design, Development und Projektmanagement zusammen,\num digitale Produkte ganzheitlich zu konzipieren und weiterzuentwickeln\nDu entwickelst UX-Konzepte,\nUserflows\nund Informationsarchitekturen und triffst darauf aufbauend UI-nahe Detailentscheidungen\nDu denkst Business-Ziele aktiv mit, hinterfragst Anforderungen kritisch und bringst eigene Produktideen ein\nDu unterst\u00fctzt bei der Entwicklung digitaler Produkte \u2013 sowohl \u201e\nfrom\nScratch\u201c als auch bei der strategischen Weiterentwicklung bestehender Produktbereiche\nDu \u00fcbernimmst schrittweise Verantwortung f\u00fcr die konzeptionelle und inhaltliche Weiterentwicklung von Produktbereichen \u00fcber mehrere Iterationen hinweg\nDu vertrittst deine Konzepte \u00fcberzeugend in internen Abstimmungen sowie in Kunden-Meetings und Workshops\nOverview\nJAKALA ist ein weltweit t\u00e4tiges IT- und Consulting-Unternehmen im Bereich\nMartech\n, mit einem starken Fokus auf Daten und KI. Von den weltweit \u00fcber 3.300 Mitarbeitenden sind rund 230 in Hamburg und Berlin t\u00e4tig. Bei JAKALA Germany liegt der Schwerpunkt auf der Entwicklung von individuellen Software-L\u00f6sungen, haupts\u00e4chlich von sogenannten Digital Experience\nPlatforms\n(DXP), in denen Gesch\u00e4ftsprozesse entlang der Customer Journey digitalisiert werden. An der Schnittstelle von Strategie, Design und Technologie entwickelt JAKALA digitale Plattformen, Apps und andere Services, welche die digitalen Erlebnisse gro\u00dfer Marken ma\u00dfgeblich pr\u00e4gen. Zu den Kunden in Deutschland z\u00e4hlen beispielsweise TUI Cruises, Leica, die Hamburger Hochbahn oder das ZDF.\nQualifications\nDu bringst erste Erfahrung imProduct-/UX-Bereich mit, idealerweise im Agentur-Umfeld\nDu denkst nutzerzentriert, beh\u00e4ltst dabei aber stets gesch\u00e4ftliche Ziele und Produktanforderungen im Blick\nDu hast Erfahrung mit UX- und Product-Design-Methoden sowie ein grundlegendes Verst\u00e4ndnis f\u00fcr UI-Design\nDu arbeitest sicher mit Tools wie\nFigma\nund Keynote und kennst dich idealerweise auch bereits mit Design-\nThinking\n-Methoden aus\nDu hast ein gutes Gesp\u00fcr f\u00fcr Produktlogiken, Zusammenh\u00e4nge und konsistente Nutzererlebnisse\nStrategisches Denken, Eigeninitiative und der Wunsch, Verantwortung zu \u00fcbernehmen, zeichnen dich aus\nDu kommunizierst auch in einem remote-/hybrid-Umfeld gerne intensiv auf deutsch und englisch\nOffer\nDas bieten wir dir:\nJob in Vollzeit oder Teilzeit - du entscheidest\nHybrides Arbeitsmodell (Remote und B\u00fcro) mit flexiblen Arbeitszeiten\nOffene und teamorientierte Unternehmenskultur\nWertsch\u00e4tzung deiner Ideen\nZuschuss f\u00fcr \u00d6PNV und\nBikeleasing\n-Option\nUrban Sports Club Membership\nW\u00f6chentliches gemeinsames Fr\u00fchst\u00fcck oder Mittagessen\nWenn du willst: Einstieg in unsere Hamburger Band (\nSchlagzeuger:in\ngesucht)\nWhat\nelse\n?\nWir wollen einen positiven Impact auf unsere Erde haben. Deshalb streben wir danach, auf nachhaltige Weise Wert f\u00fcr alle Interessengruppen zu schaffen und ber\u00fccksichtigen dabei Klima, Ethik und Qualit\u00e4t. 2021 haben wir uns entschieden, eine Benefit Corporation zu werden, um unser langfristiges Engagement f\u00fcr den Schutz der Prinzipien und Werte, die unser Handeln leiten, zu unterstreichen.\nBewirb dich noch heute. Wir freuen uns darauf, dich kennenzulernen.\nBack\nApply\nShare this job:\nFacebook\nLinkedIn\nEmail",
        "application_url": "https://careers.jakala.com/en_US/careers/ApplicationMethods?jobId=2298",
        "": {},
        "metadata": {
            "Office": "Full Remote, Berlin, Hamburg, Vienna",
            "Country": "Germany",
            "Date Published": "22-Jan-2026",
            "Ref #": "2266",
            "Area": "Design",
            "Type of Presence": "Hybrid"
        },
        "link": "https://careers.jakala.com/en_US/careers/JobDetail/Junior-Product-Designer-all-genders-Schwerpunkt-UX/2298"
    },
    {
        "title": "Data Scientist Senior Consultant",
        "description_html": null,
        "description_text": "General information\nOffice\nGij\u00f3n\nCountry\nSpain\nDate Published\n21-Jan-2026\nRef #\n2257\nArea\nReward Marketing\nType of Presence\nHybrid\nDescription & Requirements\nEn Jakala buscamos un\nSenior Data Scientist\ncon experiencia consolidada en proyectos de Machine Learning, Anal\u00edtica Avanzada y MLOps. La persona seleccionada liderar\u00e1 iniciativas t\u00e9cnicas y estrat\u00e9gicas, aportando visi\u00f3n, madurez t\u00e9cnica y capacidad de gesti\u00f3n en proyectos complejos y de alto valor para nuestros clientes.\nResponsabilidades / Funciones\nLiderar proyectos de\nMachine Learning y Anal\u00edtica Avanzada\nen los clientes asignados, garantizando calidad, rigor t\u00e9cnico y orientaci\u00f3n a negocio.\nDirigir proyectos internacionales dentro de su \u00e1mbito de especialidad, aportando seniority y experiencia; disponibilidad para viajar cuando sea necesario.\nImpulsar la profesionalizaci\u00f3n del \u00e1rea mediante:\nDesarrollo y actualizaci\u00f3n del\noffering\n.\nDise\u00f1o y ejecuci\u00f3n de\ncasos de uso propios\n.\nProductivizaci\u00f3n y escalado de soluciones.\nLiderazgo t\u00e9cnico en nuevos proyectos que requieran mayor expertise.\nDise\u00f1o y evoluci\u00f3n de\narquitecturas avanzadas\n, incluyendo modelos, pipelines y entornos MLOps.\nRequisitos\nMust (imprescindibles)\nPerfil proactivo, aut\u00f3nomo y orientado a generar impacto.\nTitulaci\u00f3n t\u00e9cnica: f\u00edsica, matem\u00e1ticas, ingenier\u00eda (telecomunicaciones, ciencia de datos o similar).\nM\u00ednimo\n3 a\u00f1os de experiencia como Data Scientist en consultor\u00eda\n.\nConocimiento s\u00f3lido de las principales familias de modelos de ML, tanto supervisados como no supervisados: Random Forest, XGBoost, LSTM, modelos de series temporales, etc.\nHabilidades avanzadas de programaci\u00f3n, especialmente en\nPython\n.\nExperiencia en el despliegue de modelos de ML en producci\u00f3n (\nMLOps\n) en todas sus fases: dise\u00f1o, desarrollo del modelo, operativizaci\u00f3n y monitorizaci\u00f3n.\nDisponibilidad para viajar.\nNice to have (valorables)\nConocimientos en\nInteligencia Artificial Generativa\n: principales frameworks, guardrails, observabilidad, etc.\nExperiencia en las principales plataformas cloud:\nGCP, AWS o Azure\n.\nManejo de herramientas de visualizaci\u00f3n: Looker Studio, Power BI, Tableau, entre otras.\nQu\u00e9\u00a0ofrecemos\nModelo\u00a0de\u00a0asistencia\u00a0a\u00a0la\u00a0oficina\u00a0h\u00edbrido.\nSeguro\u00a0m\u00e9dico\u00a0privado.\nAcceso\u00a0a\u00a0Wellhub\u00a0para\u00a0bienestar\u00a0f\u00edsico\u00a0y\u00a0mental.\nRetribuci\u00f3n\u00a0flexible\u00a0(restauraci\u00f3n,\u00a0transporte,\u00a0guarder\u00eda,\u00a0etc.).\n28\u00a0d\u00edas\u00a0de\u00a0vacaciones\u00a0al\u00a0a\u00f1o.\nTres\u00a0semanas\u00a0al\u00a0a\u00f1o\u00a0de\u00a0full\u00a0remote.\nPlan\u00a0de\u00a0carrera\u00a0adaptado\u00a0a\u00a0tus\u00a0inquietudes\u00a0profesionales.\nAcceso\u00a0a\u00a0certificaciones\u00a0(Google,\u00a0Salesforce,\u00a0Adobe).\nProgramas\u00a0de\u00a0formaci\u00f3n\u00a0tecnol\u00f3gica\u00a0(Jxpert).\nLaboratorio\u00a0de\u00a0pruebas\u00a0de\u00a0soluciones\u00a0tecnol\u00f3gicas\u00a0(Jlab).\nFormaci\u00f3n\u00a0en\u00a0idiomas.\nDescripci\u00f3n de la empresa:\nSomos\u00a0un\u00a0ecosistema\u00a0dise\u00f1ado\u00a0para\u00a0que\u00a0el\u00a0talento\u00a0y\u00a0las\u00a0soluciones\u00a0innovadoras\u00a0se\u00a0unan\u00a0para\u00a0impulsar\u00a0el\u00a0valor\u00a0para\u00a0las\u00a0organizaciones,\u00a0las\u00a0personas\u00a0y\u00a0la\u00a0sociedad.\nHoy\u00a0en\u00a0d\u00eda,\u00a0somos\u00a0la\u00a0empresa\u00a0l\u00edder\u00a0en\u00a0Martech\u00a0en\u00a0Europa,\u00a0con\u00a0sede\u00a0en\u00a0Mil\u00e1n\u00a0y\u00a0oficinas\u00a0en\u00a0todo\u00a0el\u00a0mundo.\u00a0Nuestro\u00a0enfoque\u00a0impulsado\u00a0por\u00a0datos,\u00a0respaldado\u00a0por\u00a0una\u00a0f\u00f3rmula\u00a0ganadora\u00a0de\u00a0estrategia,\u00a0innovaci\u00f3n,\u00a0transformaci\u00f3n\u00a0tecnol\u00f3gica,\u00a0compromiso\u00a0y\u00a0activaci\u00f3n,\u00a0es\u00a0la\u00a0piedra\u00a0angular\u00a0de\u00a0nuestro\u00a0trabajo.\nCon un equipo de 3,000 empleados, m\u00e1s de 900 clientes y proyectos en m\u00e1s de 30 pa\u00edses, y una facturaci\u00f3n que supera los 500 millones de euros, JAKALA emerge como un verdadero punto de referencia en el vasto panorama digital. Gracias a la contribuci\u00f3n de un equipo internacional compuesto por talentos vers\u00e1tiles y altamente calificados, la empresa ofrece soluciones \u00fanicas y personalizadas, anticipando los desaf\u00edos de un mercado en constante evoluci\u00f3n. Reconocida como\nEmpresa Great Place to Work 2024\n, JAKALA persigue sus objetivos con la firme creencia de que el bienestar de los empleados y un impacto positivo en el medio ambiente son elementos esenciales para garantizar un crecimie\nnto sostenible.\nBack\nApply\nShare this job:\nFacebook\nLinkedIn\nEmail",
        "application_url": "https://careers.jakala.com/en_US/careers/ApplicationMethods?jobId=2289",
        "": {},
        "metadata": {
            "Office": "Gij\u00f3n",
            "Country": "Spain",
            "Date Published": "21-Jan-2026",
            "Ref #": "2257",
            "Area": "Reward Marketing",
            "Type of Presence": "Hybrid"
        },
        "link": "https://careers.jakala.com/en_US/careers/JobDetail/Data-Scientist-Senior-Consultant/2289"
    },
    {
        "title": "Intern | Junior CMS specialist",
        "description_html": null,
        "description_text": "General information\nOffice\nMilano\nCountry\nItaly\nDate Published\n21-Jan-2026\nRef #\n2259\nArea\nIT and Information Systems\nType of Presence\nHybrid\nDescription & Requirements\n\ud83d\udccd\nSede\n:\nMilano\nChi siamo\nJAKALA \u00e8 un'azienda che lavora su dati, intelligenza artificiale e sviluppo di esperienze per generare un impatto significativo e duraturo a livello globale.\nPresenti in oltre 30 citt\u00e0 in 21 paesi, i nostri team uniscono competenze su strategia, tecnologia, creativit\u00e0 e\noperations\nper offrire esperienze personalizzate e soluzioni trasformative ai nostri clienti, grazie al supporto di dati e intelligenza artificiale. I\nJakalers\nsono un gruppo eterogeneo di oltre 3.000 persone, animate da passione, ambizione e idee brillanti. Proprio questa combinazione unica di talenti \u00e8 il fattore distintivo che ha ispirato il nostro\npurpose\n:\nTogether\nto\nget\nthere\n.\nCreare un mondo migliore \u00e8 il nostro obiettivo ultimo: la nostra ambizione \u00e8 generare valore per tutti i nostri stakeholder in modo sostenibile, con particolare attenzione a etica, clima e qualit\u00e0. Nel 2021, abbiamo scelto di diventare una Societ\u00e0 Benefit, dimostrando il nostro impegno di lungo periodo e la volont\u00e0 di proteggere i principi e i valori che ogni giorno guidano le nostre azioni.\nCrediamo che la diversit\u00e0 sia la chiave del nostro successo e, per questo, siamo impegnati a creare un ambiente di lavoro inclusivo, dove ciascuno possa sentirsi valorizzato per la propria unicit\u00e0. Tutte le nostre opportunit\u00e0 di lavoro sono aperte ai candidati appartenenti alle categorie protette L.68/99.\nScopri\nil team Smart Solutions\nNel team Smart Solutions\ndi JAKALA progettiamo e realizziamo siti web, piattaforme e infrastrutture tecnologiche che supportano le strategie digitali dei\nbrand\n. Lavoriamo a stretto contatto con\nteam creativi\ne di marketing per sviluppare soluzioni scalabili, performanti e\nmanutenibili\n, seguendo tutte le fasi: dall\u2019analisi tecnica allo sviluppo, fino all\u2019ottimizzazione continua. Entrerai in un contesto dinamico dove tecnologia, collaborazione e qualit\u00e0 dell\u2019esecuzione fanno la differenza.\n\ud83c\udfaf Ogni giorno sar\u00e0 diverso, ma eccoti un assaggio di quello che ti aspetta\nGestione e aggiornamento dei contenuti\nCreare, modificare e pubblicare contenuti su piattaforme CMS in base alle richieste del cliente.\nGarantire la coerenza grafica e testuale rispetto alle linee guida del\nbrand\n.\nMonitoraggio e manutenzione del CMS\nControllare periodicamente performance e sicurezza del sistema.\nRisolvere eventuali bug o anomalie segnalate dai clienti.\nSupporto tecnico e coordinamento operativo\nFornire assistenza ai clienti nell\u2019utilizzo del CMS e nella risoluzione di problematiche operative.\nCoordinarsi con i clienti per le attivit\u00e0 quotidiane e la pianificazione delle pubblicazioni.\nOttimizzazione SEO e performance\nApplicare best practice SEO sui contenuti pubblicati.\nAnalizzare e migliorare velocit\u00e0 e usabilit\u00e0 del sito.\n\ud83d\udca1 Queste caratteristiche sono un ottimo punto di partenza per crescere insieme\nBuona padronanza del pacchetto Office (Excel e\nPowerpoint\nin particolare)\nSpiccate capacit\u00e0 analitiche e\nproblem\nsolving\nInteresse e passione per il mondo digitale e le piattaforme web\nBuona conoscenza della lingua i\nnglese\n\ud83d\ude80\nCi brillano gli occhi se hai anche\nConoscenza di strumenti di performance e qualit\u00e0 come Google\nPage Speed\nInsights, Lighthouse,\nGTmetrix\no simili.\nFamiliarit\u00e0 con CMS diffusi (WordPress, Adobe Experience Manager,\nSitecore\n,\nDrupal\n\u2026).\nConoscenza base di HTML/CSS per piccole correzioni o personalizzazioni.\nEsperienza con strumenti di debugging e ispezione browser (Chrome\nDev Tools\n).\nNozioni di best practice UX/UI e\naccessibility\nguidelines\n.\nEsperienza con workflow editoriali complessi o\nmulti-lingua\n.\n\ud83d\udc9c\nScopri\u00a0nel\u00a0video le ragioni per cui scegliere JAKALA come prossimo step di carriera\nIn JAKALA crediamo che il tempo e il benessere delle persone vadano rispettati, sempre: incoraggiamo una presenza in ufficio di\n10\ngiorni al mese.\nIl nostro sistema di Total\nReward\ninclude convenzioni esclusive per viaggi, ristoranti, shopping, palestra e tempo libero, oltre a servizi gratuiti di telemedicina e supporto psicologico, pensati per te e per chi ami.\nInvestire nel nostro processo di selezione significa ricevere supporto autentico: un Recruiter dedicato ti accompagner\u00e0 con feedback personalizzati, consigli di carriera e insight sul tuo CV, a prescindere dall\u2019esito della candidatura. Niente AI, solo persone. E, grazie all\u2019iniziativa Your Time Back, ti restituiamo il tempo investito nei colloqui con un percorso di empowerment firmato\nUnobravo\n.\n\ud83c\udf31 Ready to start?\nNon \u00e8 solo una candidatura. \u00c8 un percorso che comincia ora. Inviaci il tuo CV: non vediamo l\u2019ora di conoscerti!\nBack\nApply\nShare this job:\nFacebook\nLinkedIn\nEmail",
        "application_url": "https://careers.jakala.com/en_US/careers/ApplicationMethods?jobId=2291",
        "": {},
        "metadata": {
            "Office": "Milano",
            "Country": "Italy",
            "Date Published": "21-Jan-2026",
            "Ref #": "2259",
            "Area": "IT and Information Systems",
            "Type of Presence": "Hybrid"
        },
        "link": "https://careers.jakala.com/en_US/careers/JobDetail/Intern-Junior-CMS-specialist/2291"
    },
    {
        "title": "UI Designer (all genders)",
        "description_html": null,
        "description_text": "General information\nOffice\nBerlin, Hamburg, Vienna\nCountry\nGermany\nDate Published\n19-Jan-2026\nRef #\n2250\nArea\nDesign\nType of Presence\nHybrid\nDescription & Requirements\nDu bist\nUI Designer\n(all\ngenders\n) und\nhast\neinen ausgepr\u00e4gten Sinn f\u00fcr digitale \u00c4sthetik? In unserem\ncrossfunktionalen\nTeam entwickelst du kreative L\u00f6sungen, die Nutzer begeistern. In dieser Position tr\u00e4gst du zur Optimierung unserer Kundenprodukte im Bereich Nachrichten/Streaming bei und pr\u00e4gst das visuelle Erlebnis. Klingt spannend? Dann bist du bei uns genau richtig.\nZum n\u00e4chstm\u00f6glichen Zeitpunkt suchen wir einen motivierten und engagierten\nUI Designer\n(all\ngenders\n) in Hamburg, Berlin oder Wien, hybrid oder remote.\nResponsibilities\nDu arbeitest an der kreativen Gestaltung digitaler Produkte f\u00fcr verschiedene Plattformen: Web, Mobile und TV\nDu designst au\u00dfergew\u00f6hnliche Interface-Konzepte f\u00fcr unseren Kunden und entwickelst diese proaktiv weiter\nDu definierst Design-Patterns, UI Design Guidelines und Styleguides oder ein komplettes Design-System\nDie User Experience denkst du in deiner Arbeit stets mit und l\u00e4sst bereits erste eigene Ideen einflie\u00dfen\nDu unterst\u00fctzt bei der Durchf\u00fchrung und Auswertung von Usability-Tests\nDu arbeitest interdisziplin\u00e4r mit\nUX Design\n,Front-End / Back-End Development und Projektmanagement zusammen\nOverview\nJAKALA ist ein weltweit t\u00e4tiges IT- und Consulting-Unternehmen im Bereich\nMartech\n, mit einem starken Fokus auf Daten und KI. Von den weltweit \u00fcber 3.300 Mitarbeitenden sind rund 230 in Hamburg und Berlin t\u00e4tig. Bei JAKALA Germany liegt der Schwerpunkt auf der Entwicklung von individuellen Software-L\u00f6sungen, haupts\u00e4chlich von sogenannten Digital Experience\nPlatforms\n(DXP), in denen Gesch\u00e4ftsprozesse entlang der Customer Journey digitalisiert werden. An der Schnittstelle von Strategie, Design und Technologie entwickelt JAKALA digitale Plattformen, Apps und andere Services, welche die digitalen Erlebnisse gro\u00dfer Marken ma\u00dfgeblich pr\u00e4gen. Zu den Kunden in Deutschland z\u00e4hlen beispielsweise TUI Cruises, Leica, die Hamburger Hochbahn oder das ZDF.\nQualifications\nDu hast mindestens 2 Jahre Erfahrung im UI-Design, vorzugsweise in einer Agentur oder\nProduct\nCompany\nDein Portfolio zeigt beeindruckende digitale Produkte und nutzerzentrierte Interface-Konzepte\nDu achtest auf pr\u00e4zise Details, ohne das gro\u00dfe Ganze und die Konsistenz aus den Augen zu verlieren\nFigma\n, inklusive g\u00e4ngiger Plugins, geh\u00f6rt zu deinem sicheren Werkzeugkasten, genauso wie der Umgang mit einem Design System\nDu kennst Design Sprints, Design\nThinking\nund hast Spa\u00df an der Moderation von Workshops\nDu sprichst flie\u00dfend Deutsch und gutes Englisch und kommunizierst klar und \u00fcberzeugend, sowohl im Team als auch gegen\u00fcber dem Kunden\nOffer\nDas bieten wir dir:\nJob in Vollzeit oder Teilzeit - du entscheidest\nHybrides Arbeitsmodell (Remote und B\u00fcro) mit flexiblen Arbeitszeiten\nOffene und teamorientierte Unternehmenskultur\nWertsch\u00e4tzung deiner Ideen\nZuschuss f\u00fcr \u00d6PNV und\nBikeleasing\n-Option\nUrban Sports Club Membership\nW\u00f6chentliches gemeinsames Fr\u00fchst\u00fcck oder Mittagessen\nWenn du willst: Einstieg in unsere Hamburger Band (\nSchlagzeuger:in\ngesucht)\nWhat\nelse\n?\nWir wollen einen positiven Impact auf unsere Erde haben. Deshalb streben wir danach, auf nachhaltige Weise Wert f\u00fcr alle Interessengruppen zu schaffen und ber\u00fccksichtigen dabei Klima, Ethik und Qualit\u00e4t. 2021 haben wir uns entschieden, eine Benefit Corporation zu werden, um unser langfristiges Engagement f\u00fcr den Schutz der Prinzipien und Werte, die unser Handeln leiten, zu unterstreichen.\nBewirb dich noch heute. Wir freuen uns darauf, dich kennenzulernen.\nBack\nApply\nShare this job:\nFacebook\nLinkedIn\nEmail",
        "application_url": "https://careers.jakala.com/en_US/careers/ApplicationMethods?jobId=2282",
        "": {},
        "metadata": {
            "Office": "Berlin, Hamburg, Vienna",
            "Country": "Germany",
            "Date Published": "19-Jan-2026",
            "Ref #": "2250",
            "Area": "Design",
            "Type of Presence": "Hybrid"
        },
        "link": "https://careers.jakala.com/en_US/careers/JobDetail/UI-Designer-all-genders/2282"
    },
    {
        "title": "QA Manager / Software Tester (all genders)",
        "description_html": null,
        "description_text": "General information\nOffice\nBerlin, Hamburg, Vienna\nCountry\nGermany\nDate Published\n19-Jan-2026\nRef #\n2251\nArea\nIT and Information Systems\nType of Presence\nHybrid\nDescription & Requirements\nDu liebst es, Software bis an ihre Grenzen zu testen und damit hervorragendes Benutzererlebnis zu gew\u00e4hrleisten? Du bringst Erfahrung in der Konzeptionierung und Umsetzung von umfassenden Teststrategien mit und suchst ein Umfeld, in dem du direkt zur Verbesserung und Sicherung der Produktqualit\u00e4t beitragen kannst? Dann bist du bei uns genau richtig.\nZum n\u00e4chstm\u00f6glichen Zeitpunkt suchen wir einen motivierten und engagierten QA Manager / Software Tester (all genders) in Hamburg, Berlin, Wien, hybrid oder remote.\nResponsibilities\nDu unterst\u00fctzt unsere Development-Teams, indem du sicherstellst, dass unsere digitalen Produkte wie Apps, WebApps und Portale unserem hohen Qualit\u00e4tsanspruch gerecht werden\nDu testest Produkte f\u00fcr renommierte Kunden wie ZDF, Hochbahn oder TUI Cruises auf verschiedenen Devices und nutzt unser Bugtracking-Tool, um deine Ergebnisse effizient zu reporten. Deine akribische Arbeit hilft uns, die Qualit\u00e4t unserer Produkte kontinuierlich zu verbessern\nDu bist verantwortlich f\u00fcr das Erstellen und Pflegen von Testdokumentationen f\u00fcr Apps und Websites sowie Wearables und Sprachassistenten. Deine Dokumentationen sind die Grundlage f\u00fcr unsere best\u00e4ndige Qualit\u00e4tssicherung und Weiterentwicklung\nDu agierst als zentrale Schnittstelle zwischen Product Owner und Entwicklungsteam\nMit deinem tiefen Verst\u00e4ndnis f\u00fcr Apps tr\u00e4gst du wesentlich zur Weiterentwicklung und Verbesserung unserer Produkte bei\nOverview\nAls Partner f\u00fcr die digitale Transformation helfen wir Unternehmen, ihr volles Potenzial zu entfalten. JAKALA Germany verbindet Expertise in den Bereichen Data, Brand und Tech. Indem wir dieses Know-how zusammenf\u00fchren, entwickeln wir Plattformen und Kampagnen, die \u00fcberzeugen.\nWir vereinen Kompetenzen, die zusammen st\u00e4rker sind. Zu unseren langj\u00e4hrigen Kunden z\u00e4hlen die Hamburger Hochbahn, das ZDF, TUI Cruises und viele weitere.\nQualifications\nDu hast ein starkes Interesse an neuen Technologien und mobilen Ger\u00e4ten, gepaart mit einer Affinit\u00e4t f\u00fcr das Testen digitaler Produkte\nDu bringst einschl\u00e4gige Erfahrung in einer vergleichbaren Position oder T\u00e4tigkeit mit, die deine F\u00e4higkeiten untermauert\nDu legst Wert auf Software-Qualit\u00e4t und bringst Erfahrung im explorativen sowie systematischen Testen mit\nDu bringst ein grundlegendes Verst\u00e4ndnis f\u00fcr Benutzerf\u00fchrung und -erlebnis, sowie dem Konzept von Wireframes auf verschiedenen Devices mit, was dich im Bereich User Experience auszeichnet\nDeine Vertrautheit mit Automatisierungstools und Frameworks wie Selenium, Appium oder WebDriver unterstreicht deine technische Versiertheit\nDie Arbeit mit *.xml und *.json ist dir vertraut, und du kannst damit souver\u00e4n als Input- oder Outputformat arbeiten\nDu sprichst\nflie\u00dfend Deutsch\nund verf\u00fcgst \u00fcber gute Englischkenntnisse.\nOffer\nDas bieten wir dir:\nJob in Vollzeit oder Teilzeit \u2013 du entscheidest\nHybrides Arbeitsmodell (Remote und/oder B\u00fcro) mit flexiblen Arbeitszeiten\nOffene und teamorientierte Unternehmenskultur\nWertsch\u00e4tzung deiner Ideen\nZuschuss f\u00fcr \u00d6PNV und Bikeleasing-Option\nUrban Sports Club Membership\nW\u00f6chentliches gemeinsames Fr\u00fchst\u00fcck oder Mittagessen\nWenn du willst: Einstieg in unsere Hamburger Band (Schlagzeuger:in gesucht)\nWhat else?\nBei JAKALA wissen wir, wie wertvoll unsere Teammitglieder sind und bieten ihnen die M\u00f6glichkeit, ihr volles Potenzial zu entfalten. Dynamik, Ambition, Kreativit\u00e4t \u2013 Du suchst nach einem Arbeitsumfeld, in dem du wirklich etwas bewegen kannst? Dann bist du bei uns genau richtig. Wir f\u00f6rdern Weiterentwicklung und Innovation f\u00fcr unsere Communities und unsere Kunden. In unseren Teams z\u00e4hlt jede:r Einzelne. \u201eTogether to get there\u201c \u2013 das ist nicht zuletzt unser Commitment an dich.\nBewirb dich noch heute. Wir freuen uns darauf, dich kennenzulernen.\nBack\nApply\nShare this job:\nFacebook\nLinkedIn\nEmail",
        "application_url": "https://careers.jakala.com/en_US/careers/ApplicationMethods?jobId=2283",
        "": {},
        "metadata": {
            "Office": "Berlin, Hamburg, Vienna",
            "Country": "Germany",
            "Date Published": "19-Jan-2026",
            "Ref #": "2251",
            "Area": "IT and Information Systems",
            "Type of Presence": "Hybrid"
        },
        "link": "https://careers.jakala.com/en_US/careers/JobDetail/QA-Manager-Software-Tester-all-genders/2283"
    },
    {
        "title": "Senior UI Designer (all genders)",
        "description_html": null,
        "description_text": "General information\nOffice\nBerlin, Hamburg, Vienna\nCountry\nGermany\nDate Published\n16-Jan-2026\nRef #\n2246\nArea\nDesign\nType of Presence\nHybrid\nDescription & Requirements\nDu bist erfahrener\nUI Designer\n(all\ngenders\n) und\nhast\neinen ausgepr\u00e4gten Sinn f\u00fcr digitale \u00c4sthetik? In unserem\ncrossfunktionalen\nTeam entwickelst du kreative L\u00f6sungen, die Nutzende begeistern. In dieser Position tr\u00e4gst du zur Optimierung unseres Kundenprodukts im Bereich Mobility bei und pr\u00e4gst das visuelle Erlebnis. Klingt spannend? Dann bist du bei uns genau richtig.\nZum n\u00e4chstm\u00f6glichen Zeitpunkt suchen wir einen motivierten und engagierten Senior UI Designer (all\ngenders\n) f\u00fcr unser Mobility-Studio in Hamburg, Berlin oder Wien, hybrid oder remote.\nResponsibilities\nDu arbeitest an der kreativen Gestaltung einer nativen Mobilit\u00e4tsapp f\u00fcr Hamburg und weitere St\u00e4dte\nDu designst au\u00dfergew\u00f6hnliche Interface-Konzepte f\u00fcr unsere Kunden und entwickelst diese proaktiv weiter\nDu definierst Design-Patterns, UI Design Guidelines und Styleguides oder komplette Design-Systeme\nDie User Experience denkst du in deiner Arbeit stets mit und l\u00e4sst bereits erste eigene Ideen einflie\u00dfen\nDu unterst\u00fctzt bei der Durchf\u00fchrung und Auswertung von Usability-Tests\nDu arbeitest interdisziplin\u00e4r mit\nUX Design\n, Development und Projektmanagement zusammen\nOverview\nJAKALA ist ein weltweit t\u00e4tiges IT- und Consulting-Unternehmen im Bereich\nMartech\n, mit einem starken Fokus auf Daten und KI. Von den weltweit \u00fcber 3.300 Mitarbeitenden sind rund 230 in Hamburg und Berlin t\u00e4tig. Bei JAKALA Germany liegt der Schwerpunkt auf der Entwicklung von individuellen Software-L\u00f6sungen, haupts\u00e4chlich von sogenannten Digital Experience\nPlatforms\n(DXP), in denen Gesch\u00e4ftsprozesse entlang der Customer Journey digitalisiert werden. An der Schnittstelle von Strategie, Design und Technologie entwickelt JAKALA digitale Plattformen, Apps und andere Services, welche die digitalen Erlebnisse gro\u00dfer Marken ma\u00dfgeblich pr\u00e4gen. Zu den Kunden in Deutschland z\u00e4hlen beispielsweise TUI Cruises, Leica, die Hamburger Hochbahn oder das ZDF.\nQualifications\nDu hast mindestens vier Jahre Erfahrung im UI-Design, vorzugsweise in einem gro\u00dfen Produktteam\nDein Portfolio zeigt beeindruckende digitale Produkte, mobile Apps und nutzerzentrierte Interface-Konzepte\nDu achtest auf pr\u00e4zise Details, ohne das gro\u00dfe Ganze und die Konsistenz aus den Augen zu verlieren\nFigma\n, inklusive g\u00e4ngiger Plugins, geh\u00f6rt zu deinem sicheren Werkzeugkasten, genauso wie der Umgang mit einem Designsystem\nDu kennst Design Sprints, Design\nThinking\nund hast Spa\u00df an der Moderation von Workshops\nDu sprichst flie\u00dfend Deutsch und gutes Englisch und kommunizierst klar und \u00fcberzeugend, sowohl im Team als auch gegen\u00fcber dem Kunden\nOffer\nDas bieten wir dir:\nJob in Vollzeit oder Teilzeit - du entscheidest\nHybrides Arbeitsmodell (Remote und B\u00fcro) mit flexiblen Arbeitszeiten\nOffene und teamorientierte Unternehmenskultur\nWertsch\u00e4tzung deiner Ideen\nZuschuss f\u00fcr \u00d6PNV und\nBikeleasing\n-Option\nUrban Sports Club Membership\nW\u00f6chentliches gemeinsames Fr\u00fchst\u00fcck oder Mittagessen\nWenn du willst: Einstieg in unsere Hamburger Band (\nSchlagzeuger:in\ngesucht)\nWhat\nelse\n?\nWir wollen einen positiven Impact auf unsere Erde haben. Deshalb streben wir danach, auf nachhaltige Weise Wert f\u00fcr alle Interessengruppen zu schaffen und ber\u00fccksichtigen dabei Klima, Ethik und Qualit\u00e4t. 2021 haben wir uns entschieden, eine Benefit Corporation zu werden, um unser langfristiges Engagement f\u00fcr den Schutz der Prinzipien und Werte, die unser Handeln leiten, zu unterstreichen.\nBewirb dich noch heute. Wir freuen uns darauf, dich kennenzulernen.\nBack\nApply\nShare this job:\nFacebook\nLinkedIn\nEmail",
        "application_url": "https://careers.jakala.com/en_US/careers/ApplicationMethods?jobId=2278",
        "": {},
        "metadata": {
            "Office": "Berlin, Hamburg, Vienna",
            "Country": "Germany",
            "Date Published": "16-Jan-2026",
            "Ref #": "2246",
            "Area": "Design",
            "Type of Presence": "Hybrid"
        },
        "link": "https://careers.jakala.com/en_US/careers/JobDetail/Senior-UI-Designer-all-genders/2278"
    },
    {
        "title": "Experienced Professional | Client Strategy Automotive",
        "description_html": null,
        "description_text": "General information\nOffice\nMilano\nCountry\nItaly\nDate Published\n16-Jan-2026\nRef #\n2247\nArea\nManagement Consulting\nType of Presence\nHybrid\nDescription & Requirements\n\ud83d\udccd\nSede\n:\u00a0Milano\n\ud83d\udc40\nRank:\u00a0Consultant\nChi siamo\nJAKALA \u00e8 un'azienda che lavora su dati, intelligenza artificiale e sviluppo di esperienze per generare un impatto significativo e duraturo a livello globale.\nPresenti in oltre 30 citt\u00e0 in 21 paesi,\ni nostri team\nuniscono competenze su strategia, tecnologia, creativit\u00e0 e\noperations\nper offrire esperienze personalizzate e soluzioni trasformative ai nostri clienti, grazie al supporto di dati e intelligenza artificiale. I\nJakalers\nsono un gruppo eterogeneo di oltre 3.000 persone, animate da passione, ambizione e idee brillanti. Proprio questa combinazione unica di talenti \u00e8 il fattore distintivo che ha ispirato il nostro\npurpose\n:\nTogether\nto\nget\nthere\n.\nCreare un mondo migliore \u00e8 il nostro obiettivo ultimo: la nostra ambizione \u00e8 generare valore per tutti i nostri stakeholder in modo sostenibile, con particolare attenzione a etica, clima e qualit\u00e0. Nel 2021, abbiamo scelto di diventare una Societ\u00e0 Benefit, dimostrando il nostro impegno di lungo periodo e la volont\u00e0 di proteggere i principi e i valori che ogni giorno guidano le nostre azioni.\nCrediamo che la diversit\u00e0 sia la chiave del nostro successo e, per questo, siamo impegnati a creare un ambiente di lavoro inclusivo, dove ciascuno possa sentirsi valorizzato per la propria unicit\u00e0. Tutte le nostre opportunit\u00e0 di lavoro sono aperte ai candidati appartenenti alle categorie protette L.68/99.\nScopri\nil team\nClient Strategy\nTi appassiona lavorare con dati e insight per contribuire alla definizione di strategie di crescita dei clienti? Entrerai a far parte di\nun team multidisciplinare e dinamico\n, dove avrai l\u2019opportunit\u00e0 di lavorare su iniziative strategiche ad alto impatto volte a valorizzare il patrimonio informativo dei\nbrand\n.\nIl team\nClient Strategy \u00e8 il motore consulenziale di JAKALA: guida la progettazione strategica, la gestione operativa e lo sviluppo di nuove opportunit\u00e0 di business, trasformando insight, tecnologia e creativit\u00e0 in soluzioni su misura. Approfondirai tematiche legate al mondo Strategy & Consulting con un approccio proattivo e data-\ndriven\n, all\u2019interno di un ambiente in continua evoluzione.\n\ud83c\udfaf Le tue responsabilit\u00e0:\nTrasformare dati e analisi di mercato in insight strategici e opportunit\u00e0 di crescita, con focus sulle evoluzioni tecnologiche e competitive del mondo Industrial & Automotive\nDefinizione di strategie di Customer\nRelationship\nManagement (CRM) in ottica full-\nfunnel\n, integrate con i principali\ntouchpoint\ndigitali e fisici del cliente\nCoordinare\nworkstream\ncomplessi e collaborare con\nteam multidisciplinari\n(Digital, Tech, Data, Analytics) per integrare la strategia del cliente all\u2019interno di progetti digitali e omnichannel\nPresentazione autonoma di progetti e risultati al cliente, anche in contesti C-\nlevel\n, con capacit\u00e0 di sintesi e storytelling strategico\nGestire il rapporto con il cliente, presentando documentazione e reportistica con elevato grado di autonomia\n\ud83d\ude4c Se\nti riconosci\nin queste caratteristiche, potremmo essere il perfetto match:\nLaurea, preferibilmente indiscipline economiche o scientifiche\nEsperienzadi 2-3 anni maturata presso societ\u00e0 di consulenza\nCoinvolgimento\nin\nprogetti\nSales & Marketing,\nquali\n: CRM, Lead Acquisition,\nOminichannel\nStrategy, Digital Marketing, Go to Market Strategy, Customer Experience e/o Customer Journey\nAttitudine al problem solving e approccio analitico, coniugando analisi qualitative\ne business driven\ncon analisi quantitative della customer base\nOttima padronanza del pacchetto Microsoft Office (in particolare, Excel e PowerPoint)\nBuona conoscenza della lingua inglese\nAttitudine al project management\nPrecisione e cura del dettaglio, unita a capacit\u00e0 di sintesi\nConoscenza\ndel linguaggio SQL e pregressa esperienza nel settore Automotive\nsaranno considerate un plus\n\ud83d\udc9c\nScopri in questo video le ragioni per cui scegliere JAKALA come prossimo step di carriera\nIn JAKALA crediamo che il tempo e il benessere delle persone vadano rispettati, sempre: incoraggiamo una presenza in ufficio di\n10\ngiorni al mese, lasciando piena libert\u00e0 di lavorare da dove preferisci, sia in Italia che all\u2019interno della Comunit\u00e0 Europea.\nIl nostro sistema di Total\nReward\ninclude convenzioni esclusive per viaggi, ristoranti, shopping, palestra e tempo libero, oltre a servizi gratuiti di telemedicina e supporto psicologico, pensati per te e per chi ami.\nInvestire nel nostro processo di selezione significa ricevere supporto autentico: un Recruiter dedicato ti accompagner\u00e0 con feedback personalizzati, consigli di carriera e insight sul tuo CV, a prescindere dall\u2019esito della candidatura. Niente AI, solo persone. E, grazie all\u2019iniziativa Your Time Back, ti restituiamo il tempo investito nei colloqui con un percorso di empowerment firmato\nUnobravo\n.\n\ud83c\udf31 Ready to start?\nNon \u00e8 solo una candidatura. \u00c8 un percorso che comincia ora. Inviaci il tuo CV: non vediamo l\u2019ora di conoscerti!\nBack\nApply\nShare this job:\nFacebook\nLinkedIn\nEmail",
        "application_url": "https://careers.jakala.com/en_US/careers/ApplicationMethods?jobId=2279",
        "": {},
        "metadata": {
            "Office": "Milano",
            "Country": "Italy",
            "Date Published": "16-Jan-2026",
            "Ref #": "2247",
            "Area": "Management Consulting",
            "Type of Presence": "Hybrid"
        },
        "link": "https://careers.jakala.com/en_US/careers/JobDetail/Experienced-Professional-Client-Strategy-Automotive/2279"
    },
    {
        "title": "Intern | Web Analytics",
        "description_html": null,
        "description_text": "General information\nOffice\nMilano\nCountry\nItaly\nDate Published\n15-Jan-2026\nRef #\n2243\nArea\nMarketing\nType of Presence\nHybrid\nDescription & Requirements\n\ud83d\udccd\nSede\n: Milano\nChi siamo\nJAKALA \u00e8 un'azienda che lavora su dati, intelligenza artificiale e sviluppo di esperienze per generare un impatto significativo e duraturo a livello globale.\nPresenti in oltre 30 citt\u00e0 in 21 paesi, i nostri team uniscono competenze su strategia, tecnologia, creativit\u00e0 e operations per offrire esperienze personalizzate e soluzioni trasformative ai nostri clienti, grazie al supporto di dati e intelligenza artificiale. I Jakalers sono un gruppo eterogeneo di oltre 3.000 persone, animate da passione, ambizione e idee brillanti. Proprio questa combinazione unica di talenti \u00e8 il fattore distintivo che ha ispirato il nostro purpose: Together to get there.\nCreare un mondo migliore \u00e8 il nostro obiettivo ultimo: la nostra ambizione \u00e8 generare valore per tutti i nostri stakeholder in modo sostenibile, con particolare attenzione a etica, clima e qualit\u00e0. Nel 2021, abbiamo scelto di diventare una Societ\u00e0 Benefit, dimostrando il nostro impegno di lungo periodo e la volont\u00e0 di proteggere i principi e i valori che ogni giorno guidano le nostre azioni.\nCrediamo che la diversit\u00e0 sia la chiave del nostro successo e, per questo, siamo impegnati a creare un ambiente di lavoro inclusivo, dove ciascuno possa sentirsi valorizzato per la propria unicit\u00e0. Tutte le nostre opportunit\u00e0 di lavoro sono aperte ai candidati appartenenti alle categorie protette L.68/99.\nScopri il team Web Analytics\nAll\u2019interno della Service Line Web Analytics di JAKALA, lavoriamo ogni giorno per contribuire in maniera concreta allo sviluppo e alla realizzazione di progetti innovativi da portare sul mercato su grandi clienti, che vogliano crescere rapidamente ed essere pronti a raccogliere le sfide giornaliere in maniera flessibile e con un approccio \u201copen minded\u201d.\nI nostri nuovi colleghi verranno coinvolti nello sviluppo di progetti di implementazione su piattaforme di tag management e Web Analytics e tool di Dashboarding.\n\ud83c\udfaf\nOgni giorno sar\u00e0 diverso, ma eccoti un assaggio di quello che ti aspetta\nAttivit\u00e0 di audit di tracciamento e analitica, web e app\nRealizzazione documenti di tracking strategy\nImplementazione tracking, in particolare mediante Google Tag Manager e Adobe e relativi debug\nConoscenza approfondita di tool di Web Analytics, Google e Adobe\nAnalisi del dato raccolto, mediante creazione di reportistica o dashboard ad hoc\n\ud83d\udca1\nQueste caratteristiche sono un ottimo punto di partenza per crescere insieme\nCompetenze analitiche e di gestione del dato\nBuona conoscenza di Office365, in particolare Excel\nLa Conoscenza di Javascript e Html sar\u00e0 considerato un plus\nConoscenza solida della lingua inglese\n\ud83d\ude80\nCi brillano gli occhi se hai anche\nCapacit\u00e0 di alternare un mindset analitico ad una forte attitudine alla comunicazione e alla gestione degli stakeholder (Partner, Employee, Talent)\nAutonomia nella ricerca di informazioni utili sui progetti e spirito di iniziativa\nEntusiasmo, curiosit\u00e0 e passione\n\ud83d\udc9c\nScopri in questo video le ragioni per cui scegliere JAKALA come prossimo step di carriera\nIn JAKALA crediamo che il tempo e il benessere delle persone vadano rispettati, sempre: incoraggiamo una presenza in ufficio di 10 giorni al mese.\nIl nostro sistema di Total Reward include convenzioni esclusive per viaggi, ristoranti, shopping, palestra e tempo libero, oltre a servizi gratuiti di telemedicina e supporto psicologico, pensati per te e per chi ami.\nInvestire nel nostro processo di selezione significa ricevere supporto autentico: un Recruiter dedicato ti accompagner\u00e0 con feedback personalizzati, consigli di carriera e insight sul tuo CV, a prescindere dall\u2019esito della candidatura. Niente AI, solo persone. E, grazie all\u2019iniziativa Your Time Back, ti restituiamo il tempo investito nei colloqui con un percorso di empowerment firmato Unobravo.\n\ud83c\udf31\nReady to start?\nNon \u00e8 solo una candidatura. \u00c8 un percorso che comincia ora. Inviaci il tuo CV: non vediamo l\u2019ora di conoscerti!\nBack\nApply\nShare this job:\nFacebook\nLinkedIn\nEmail",
        "application_url": "https://careers.jakala.com/en_US/careers/ApplicationMethods?jobId=2275",
        "": {},
        "metadata": {
            "Office": "Milano",
            "Country": "Italy",
            "Date Published": "15-Jan-2026",
            "Ref #": "2243",
            "Area": "Marketing",
            "Type of Presence": "Hybrid"
        },
        "link": "https://careers.jakala.com/en_US/careers/JobDetail/Intern-Web-Analytics/2275"
    },
    {
        "title": "Tealium | Martech Engineer Consultant",
        "description_html": null,
        "description_text": "General information\nOffice\nBarcelona, Gij\u00f3n, Madrid, Pamplona, Full Remote\nCountry\nSpain\nDate Published\n09-Jan-2026\nRef #\n2230\nArea\nMarketing\nType of Presence\nHybrid\nDescription & Requirements\nEn\nJAKALA\nbuscamos un perfil que combine atenci\u00f3n al detalle y curiosidad tecnol\u00f3gica para garantizar que nuestras soluciones digitales funcionen de forma impecable. Ser\u00e1s parte de un equipo que trabaja en proyectos innovadores, asegurando que cada etiqueta, evento y dato se implemente correctamente y aporte valor real al negocio.\nQu\u00e9 har\u00e1s (Responsabilidades)\nDise\u00f1ar, ejecutar y documentar planes de prueba funcionales y no funcionales (usabilidad, rendimiento, seguridad) para sitios web y aplicaciones m\u00f3viles.\nValidar la implementaci\u00f3n correcta de etiquetas y eventos definidos en Tealium iQ.\nVerificar la trazabilidad completa de datos enviados a herramientas de anal\u00edtica (GA4, etc.).\nTrabajar con equipos de desarrollo y MarTech para asegurar que los requerimientos t\u00e9cnicos y de negocio est\u00e9n correctamente implementados y medidos.\nDocumentar incidencias y generar informes de calidad con foco en los KPIs digitales del negocio.\nRequisitos (Must)\nCertificaci\u00f3n oficial en Tealium iQ y/o Tealium EventStream / AudienceStream.\nExperiencia en validaci\u00f3n de etiquetado digital con plataformas de tag management y gesti\u00f3n de eventos en Tealium.\nFamiliaridad con herramientas de anal\u00edtica digital: GA4, Firebase Analytics.\nConocimiento b\u00e1sico de protocolos de red (HTTP, HTTPS) y uso de herramientas como Charles.\nComprensi\u00f3n de HTML, CSS y JavaScript b\u00e1sico para debugging.\nConocimiento en soluciones de privacidad (Didomi).\n\u00bfQu\u00e9 ofrecemos?\nModelo h\u00edbrido de asistencia a la oficina (2 d\u00edas/semana presencial).\nTres semanas al a\u00f1o de full remote.\nSeguro m\u00e9dico.\nWellhub para cuidar tu salud f\u00edsica y mental.\nRetribuci\u00f3n flexible.\n28 d\u00edas de vacaciones al a\u00f1o.\nPath de carrera adaptado a tus inquietudes profesionales.\nAcceso a certificaciones (somos partners de Google y Salesforce).\nJxpert\n: programas de capacitaci\u00f3n tecnol\u00f3gica de las distintas disciplinas de JAKALA.\nJlab\n: nuestro laboratorio de pruebas de soluciones tecnol\u00f3gicas.\nFormaci\u00f3n en idiomas.\nDeporte en la oficina (entrenamiento funcional y yoga).\nOficina de Madrid: servicio de lanzadera.\nDescripci\u00f3n de la empresa\nSomos un ecosistema dise\u00f1ado para que el talento y las soluciones innovadoras se unan para impulsar el valor para las organizaciones, las personas y la sociedad.\nHoy en d\u00eda, somos la empresa l\u00edder en Martech en Europa, con sede en Mil\u00e1n y oficinas en todo el mundo. Nuestro enfoque impulsado por datos, respaldado por una f\u00f3rmula ganadora de estrategia, innovaci\u00f3n, transformaci\u00f3n tecnol\u00f3gica, compromiso y activaci\u00f3n, es la piedra angular de nuestro trabajo.\nCon un equipo de 3.000 empleados, m\u00e1s de 900 clientes y proyectos en m\u00e1s de 30 pa\u00edses, y una facturaci\u00f3n que supera los 500 millones de euros, JAKALA emerge como un verdadero punto de referencia en el vasto panorama digital. Gracias a la contribuci\u00f3n de un equipo internacional compuesto por talentos vers\u00e1tiles y altamente calificados, la empresa ofrece soluciones \u00fanicas y personalizadas, anticipando los desaf\u00edos de un mercado en constante evoluci\u00f3n. Reconocida como Empresa\nGreat Place to Work 2024\n, JAKALA persigue sus objetivos con la firme creencia de que el bienestar de los empleados y un impacto positivo en el medio ambiente son elementos esenciales para garantizar un crecimiento sostenible.\nBack\nApply\nShare this job:\nFacebook\nLinkedIn\nEmail",
        "application_url": "https://careers.jakala.com/en_US/careers/ApplicationMethods?jobId=2262",
        "": {},
        "metadata": {
            "Office": "Barcelona, Gij\u00f3n, Madrid, Pamplona, Full Remote",
            "Country": "Spain",
            "Date Published": "09-Jan-2026",
            "Ref #": "2230",
            "Area": "Marketing",
            "Type of Presence": "Hybrid"
        },
        "link": "https://careers.jakala.com/en_US/careers/JobDetail/Tealium-Martech-Engineer-Consultant/2262"
    },
    {
        "title": "Beca en Marketing Digital-con portugu\u00e9s nativo",
        "description_html": null,
        "description_text": "General information\nOffice\nBarcelona, Madrid\nCountry\nSpain\nDate Published\n09-Jan-2026\nRef #\n2232\nArea\nManagement Consulting\nType of Presence\nHybrid\nDescription & Requirements\n\u00bfTe gustar\u00eda comenzar tu carrera en el mundo de la consultor\u00eda estrat\u00e9gica, con un enfoque en marketing digital y tecnolog\u00eda?\nEn\nJAKALA Iberia\nestamos buscando incorporar a una persona con actitud proactiva, curiosidad y muchas ganas de aprender para unirse a nuestro equipo de Advisory como analista en pr\u00e1cticas.\nResponsabilidades\nApoyar la conceptualizaci\u00f3n de campa\u00f1as de marketing y comunicaciones con cliente.\nDefinir los objetivos de las campa\u00f1as, los mensajes clave, el p\u00fablico objetivo y las propuestas de valor, trabajando estrechamente con los equipos internos y los stakeholders del cliente.\nElaborar briefings de campa\u00f1a claros y estructurados para su ejecuci\u00f3n por parte de los equipos especializados de Marketing Automation y Salesforce Marketing Cloud.\nCoordinarse con m\u00faltiples \u00e1reas y equipos involucrados en las campa\u00f1as (negocio, marketing, atenci\u00f3n al cliente, operaciones y equipos de delivery).\nContribuir a la preparaci\u00f3n de presentaciones y documentaci\u00f3n de apoyo para campa\u00f1as e iniciativas.\nAnalizar los resultados de las campa\u00f1as, el feedback de los clientes y los insights operativos para identificar oportunidades de optimizaci\u00f3n.\nProponer mejoras y nuevas iniciativas con una mentalidad de mejora continua.\nAsumir la responsabilidad de las iniciativas asignadas, garantizando la calidad, coherencia y seguimiento end-to-end en un entorno de trabajo colaborativo.\nRequisitos\nMUST\nReci\u00e9n graduado en ADE, Ingenier\u00eda, Marketing, Econom\u00eda o titulaciones afines.\nGran inter\u00e9s en estrategia de marketing, comunicaciones con clientes y conceptualizaci\u00f3n de campa\u00f1as (rol no t\u00e9cnico).\nActitud proactiva, iniciativa y gran disposici\u00f3n para aprender.\nExcelentes habilidades de comunicaci\u00f3n, tanto escritas como verbales.\nMentalidad anal\u00edtica, con capacidad para extraer insights y traducirlos en propuestas y mejoras concretas.\nS\u00f3lidas habilidades organizativas, atenci\u00f3n al detalle y capacidad para priorizar tareas de forma eficaz.\nAlto sentido de la responsabilidad sobre las tareas asignadas.\nPerfil colaborativo, con facilidad para trabajar con equipos multidisciplinares.\nNivel fluido de espa\u00f1ol y portugu\u00e9s; se valorar\u00e1 especialmente un nivel nativo o casi nativo de portugu\u00e9s.\nNICE TO HAVE\nConocimientos b\u00e1sicos o formaci\u00f3n acad\u00e9mica en conceptos de Marketing Automation.\nFamiliaridad con Salesforce Marketing Cloud a nivel funcional o conceptual (no t\u00e9cnico)\nExperiencia previa en pr\u00e1cticas o experiencia acad\u00e9mica en marketing, consultor\u00eda, an\u00e1lisis de datos o proyectos digitales.\nQu\u00e9 ofrecemos\nModelo h\u00edbrido de trabajo (2 d\u00edas presenciales por semana)\nTres semanas al a\u00f1o 100% remoto\nPlan de carrera adaptado a tus intereses profesionales\nAcceso a certificaciones (somos partners de Google y Salesforce)\nProgramas de formaci\u00f3n tecnol\u00f3gica (Jxpert) y laboratorio de innovaci\u00f3n (Jlab)\nSobre Nosotros\nSomos un ecosistema dise\u00f1ado para que el talento y las soluciones innovadoras se unan para impulsar el valor para las organizaciones, las personas y la sociedad.\nHoy en d\u00eda, somos la empresa l\u00edder en Martech en Europa, con sede en Mil\u00e1n y oficinas en todo el mundo. Nuestro enfoque impulsado por datos, respaldado por una f\u00f3rmula ganadora de estrategia, innovaci\u00f3n, transformaci\u00f3n tecnol\u00f3gica, compromiso y activaci\u00f3n, es la piedra angular de nuestro trabajo.\nCon un equipo de 3,000 empleados, m\u00e1s de 900 clientes y proyectos en m\u00e1s de 30 pa\u00edses, y una facturaci\u00f3n que supera los 500 millones de euros, JAKALA emerge como un verdadero punto de referencia en el vasto panorama digital. Gracias a la contribuci\u00f3n de un equipo internacional compuesto por talentos vers\u00e1tiles y altamente calificados, la empresa ofrece soluciones \u00fanicas y personalizadas, anticipando los desaf\u00edos de un mercado en constante evoluci\u00f3n. Reconocida como\nEmpresa Great Place to Work 2024\n, JAKALA persigue sus objetivos con la firme creencia de que el bienestar de los empleados y un impacto positivo en el medio ambiente son elementos esenciales para garantizar un crecimiento sostenible.\nBack\nApply\nShare this job:\nFacebook\nLinkedIn\nEmail",
        "application_url": "https://careers.jakala.com/en_US/careers/ApplicationMethods?jobId=2264",
        "": {},
        "metadata": {
            "Office": "Barcelona, Madrid",
            "Country": "Spain",
            "Date Published": "09-Jan-2026",
            "Ref #": "2232",
            "Area": "Management Consulting",
            "Type of Presence": "Hybrid"
        },
        "link": "https://careers.jakala.com/en_US/careers/JobDetail/Beca-en-Marketing-Digital-con-portugu-s-nativo/2264"
    },
    {
        "title": "Experienced Professional | Marketing Operations",
        "description_html": null,
        "description_text": "General information\nOffice\nMilano\nCountry\nItaly\nDate Published\n08-Jan-2026\nRef #\n2231\nArea\nMarketing\nType of Presence\nHybrid\nDescription & Requirements\n\ud83d\udccd\nSede\n:\nMilano\n\ud83d\udc40\nRank: Consultant\nChi siamo\nJAKALA \u00e8 un'azienda che lavora su dati, intelligenza artificiale e sviluppo di esperienze per generare un impatto significativo e duraturo a livello globale.\nPresenti in oltre 30 citt\u00e0 in 21 paesi, i nostri team uniscono competenze su strategia, tecnologia, creativit\u00e0 e\noperations\nper offrire esperienze personalizzate e soluzioni trasformative ai nostri clienti, grazie al supporto di dati e intelligenza artificiale. I\nJakalers\nsono un gruppo eterogeneo di oltre 3.000 persone, animate da passione, ambizione e idee brillanti. Proprio questa combinazione unica di talenti \u00e8 il fattore distintivo che ha ispirato il nostro\npurpose\n:\nTogether\nto\nget\nthere\n.\nCreare un mondo migliore \u00e8 il nostro obiettivo ultimo: la nostra ambizione \u00e8 generare valore per tutti i nostri stakeholder in modo sostenibile, con particolare attenzione a etica, clima e qualit\u00e0. Nel 2021, abbiamo scelto di diventare una Societ\u00e0 Benefit, dimostrando il nostro impegno di lungo periodo e la volont\u00e0 di proteggere i principi e i valori che ogni giorno guidano le nostre azioni.\nCrediamo che la diversit\u00e0 sia la chiave del nostro successo e, per questo, siamo impegnati a creare un ambiente di lavoro inclusivo, dove ciascuno possa sentirsi valorizzato per la propria unicit\u00e0. Tutte le nostre opportunit\u00e0 di lavoro sono aperte ai candidati appartenenti alle categorie protette L.68/99.\nScopri il team Marketing Operations\nJAKALA\n\u00e8 alla ricerca di un Email Marketing Consultant con una comprovata esperienza in ambito disegno, gestione ed esecuzione di campagne di email marketing, attraverso l\u2019utilizzo di diverse piattaforme di Marketing Automation.\nIl ruolo sar\u00e0 inserito all\u2019interno del team Marketing Operations, il cuore operativo che coordina, ottimizza e monitora tutte le campagne digitali a livello internazionale e sar\u00e0 fondamentale per garantire che le comunicazioni dei clienti siano efficaci, coerenti e di alto impatto.\n\ud83c\udfaf\nLe tue responsabilit\u00e0:\nRecepire dal cliente il piano di invii per le diverse country e i target di contatto\nRaccogliere i materiali e le indicazioni propedeutiche all\u2019esecuzione delle campagne di email marketing e verificare la loro correttezza, consistenza e completezza\nRicevere le traduzioni e le localizzazioni dei contenuti da agenzie e partner esterni\nVeicolare i brief verso il team che si occupa della progettazione creativa e assicurare l\u2019efficacia degli output e la loro coerenza rispetto agli obiettivi del cliente e le best practice di mercato\nComporre le comunicazioni inserendo i contenuti testuali e visual all\u2019interno dei template HTML gi\u00e0 sviluppati, utilizzando i moduli predisposti dal team operation, nelle varie lingue di riferimento\nVerificare la correttezza e la qualit\u00e0 delle campagne in fase di testing e di schedulazione dell\u2019invio\nOrientare e verificare i report di performance delle campagne\nMonitorare e rispettare le deadline di progetto concordate con il cliente\nIn ambito di customer journeys ricorsivi, raccogliere i requisiti dal cliente e analizzare la fattibilit\u00e0 tecnica, essendo in grado di suggerire soluzioni ottimali lato piattaforma\n\ud83d\ude4c Se ti riconosci in queste caratteristiche, potremmo essere il perfetto match:\nEsperienza da 1 a 3 anni nello stesso ruolo o in ruolo affine\nSpiccato interesse per l\u2019email marketing e familiarit\u00e0 con le leve di comunicazione utilizzate in questo campo ai fini dell\u2019ingaggio e della conversione dei clienti\nConoscenza delle principali dinamiche del digital marketing e dell\u2019approccio omnichannel\nOttima conoscenza della lingua inglese e del pacchetto Office, in particolare Excel e PowerPoint\nConoscenza\u00a0della piattaforma Salesforce Marketing Cloud\nConoscenza di linguaggio SQL e AMPScript a livello intermedio per la creazione di target e dinamicizzazione dei template email\nApprezzata esperienza nel lavorare/coordinare un piccolo team di progetto\nPrecisione, flessibilit\u00e0 e affidabilit\u00e0\nPredisposizione al lavoro in team e ottime capacit\u00e0 relazionali\nPensiero critico\nProblem solving\n\ud83d\udc9c\nScopri nel video le ragioni per cui scegliere JAKALA come prossimo step di carriera\nIn JAKALA crediamo che il tempo e il benessere delle persone vadano rispettati, sempre: incoraggiamo una presenza in ufficio di 10 giorni al mese, lasciando piena libert\u00e0 di lavorare da dove preferisci, sia in Italia che all\u2019interno della Comunit\u00e0 Europea.\nIl nostro sistema di Total Reward include convenzioni esclusive per viaggi, ristoranti, shopping, palestra e tempo libero, oltre a servizi gratuiti di telemedicina e supporto psicologico, pensati per te e per chi ami.\nInvestire nel nostro processo di selezione significa ricevere supporto autentico: un Recruiter dedicato ti accompagner\u00e0 con feedback personalizzati, consigli di carriera e insight sul tuo CV, a prescindere dall\u2019esito della candidatura. Niente AI, solo persone. E, grazie all\u2019iniziativa Your Time Back, ti restituiamo il tempo investito nei colloqui con un percorso di empowerment firmato Unobravo.\n\ud83c\udf31 Ready to start?\nNon \u00e8 solo una candidatura. \u00c8 un percorso che comincia ora. Inviaci il tuo CV: non vediamo l\u2019ora di conoscerti!\nBack\nApply\nShare this job:\nFacebook\nLinkedIn\nEmail",
        "application_url": "https://careers.jakala.com/en_US/careers/ApplicationMethods?jobId=2263",
        "": {},
        "metadata": {
            "Office": "Milano",
            "Country": "Italy",
            "Date Published": "08-Jan-2026",
            "Ref #": "2231",
            "Area": "Marketing",
            "Type of Presence": "Hybrid"
        },
        "link": "https://careers.jakala.com/en_US/careers/JobDetail/Experienced-Professional-Marketing-Operations/2263"
    },
    {
        "title": "Mobile Developer (all genders)",
        "description_html": null,
        "description_text": "General information\nOffice\nFull Remote, Berlin, Hamburg, Vienna\nCountry\nGermany\nDate Published\n22-Dec-2025\nRef #\n2222\nArea\nIT and Information Systems\nType of Presence\nHybrid\nDescription & Requirements\nDu bist Mobile Developer (all\ngenders\n)\nmit F\u00e4higkeiten in der nativen sowie der Cross-Plattform-Entwicklung f\u00fcr Android (\nKotlin\n) und/oder iOS (Swift)? Du hast Freude daran, die Welt der mobilen Apps zu gestalten und gemeinsam im Team individuelle Software-L\u00f6sungen f\u00fcr unsere Kunden zu realisieren? Dann sollten wir uns kennenlernen.\nZum n\u00e4chstm\u00f6glichen Zeitpunkt suchen wir die Unterst\u00fctzung eines motivierten und engagierten Mobile Developers (all\ngenders\n) in Hamburg, Berlin, Wien, hybrid oder remote.\nResponsibilities\nDu arbeitest aktiv in agilen und\ncross\n-funktionalen Entwicklungsteams mit\nDu konzipierst und realisierst anspruchsvolle mobile L\u00f6sungen unter Verwendung relevanter Technologien wie\nKotlin\noder Swift\nDu setzt Produktanforderungen und Designs mit hochwertigem Code um, unabh\u00e4ngig von der Zielplattform (iOS und Android)\nDu passt dich verschiedenen Technologien und Plattformen flexibel an und setzt die unterschiedlichsten Projekte erfolgreich um\nGemeinsam mit verschiedenen interdisziplin\u00e4ren Teams arbeitest du daran, neue Funktionen zu definieren, zu gestalten und zu entwickeln\nOverview\nJAKALA ist ein weltweit t\u00e4tiges IT- und Consulting-Unternehmen im Bereich\nMartech\n, mit einem starken Fokus auf Daten und KI. Von den weltweit \u00fcber 3.300 Mitarbeitenden sind rund 230 in Hamburg und Berlin t\u00e4tig. Bei JAKALA Germany liegt der Schwerpunkt auf der Entwicklung von individuellen Software-L\u00f6sungen, haupts\u00e4chlich von sogenannten Digital Experience\nPlatforms\n(DXP), in denen Gesch\u00e4ftsprozesse entlang der Customer Journey digitalisiert werden. An der Schnittstelle von Strategie, Design und Technologie entwickelt JAKALA digitale Plattformen, Apps und andere Services, welche die digitalen Erlebnisse gro\u00dfer Marken ma\u00dfgeblich pr\u00e4gen. Zu den Kunden in Deutschland z\u00e4hlen beispielsweise TUI Cruises, Leica, die Hamburger Hochbahn oder das ZDF.\nQualifications\nDu hast eine Leidenschaft f\u00fcr herausragende Apps und Benutzererfahrungen, egal ob auf Android oder iOS\nDu besitzt umfassende Kenntnisse in\nKotlin\nund/oder Swift und bist erfahren im Umgang mit den zugeh\u00f6rigen Tools und Frameworks\nDu kennst dich gut mit dem Release- und Review-Prozess in den App-Stores aus\nErfahrung mit Cross-Plattform-Entwicklung,\nKotlin\nMultiplattform, ist ein Plus\nDu bist vertraut mit agilen Arbeitsmethoden wie\nScrum\noder Kanban und der Nutzung aktueller Technologien und Tools\nDu sprichst flie\u00dfend Deutsch und kommunizierst auch auf Englisch sicher\nOffer\nDas bieten wir dir:\nJob in Vollzeit oder Teilzeit - du entscheidest\nHybrides Arbeitsmodell (Remote und/oder B\u00fcro) mit flexiblen Arbeitszeiten\nOffene und teamorientierte Unternehmenskultur\nWertsch\u00e4tzung deiner Ideen\nZuschuss f\u00fcr \u00d6PNV und\nBikeleasing\n-Option\nW\u00f6chentliches gemeinsames Fr\u00fchst\u00fcck oder Mittagessen\nWenn du willst: Einstieg in unsere Hamburger Band (\nSchlagzeuger:in\ngesucht)\nWhat\nelse\n?\nWir wollen einen positiven Impact auf unsere Erde haben. Deshalb streben wir danach, auf nachhaltige Weise Wert f\u00fcr alle Interessengruppen zu schaffen und ber\u00fccksichtigen dabei Klima, Ethik und Qualit\u00e4t. 2021 haben wir uns entschieden, eine Benefit Corporation zu werden, um unser langfristiges Engagement f\u00fcr den Schutz der Prinzipien und Werte, die unser Handeln leiten, zu unterstreichen.\nBewirb dich noch heute. Wir freuen uns darauf, dich kennenzulernen.\nBack\nApply\nShare this job:\nFacebook\nLinkedIn\nEmail",
        "application_url": "https://careers.jakala.com/en_US/careers/ApplicationMethods?jobId=2254",
        "": {},
        "metadata": {
            "Office": "Full Remote, Berlin, Hamburg, Vienna",
            "Country": "Germany",
            "Date Published": "22-Dec-2025",
            "Ref #": "2222",
            "Area": "IT and Information Systems",
            "Type of Presence": "Hybrid"
        },
        "link": "https://careers.jakala.com/en_US/careers/JobDetail/Mobile-Developer-all-genders/2254"
    },
    {
        "title": "Experienced Professional | AMS Junior Service Manager",
        "description_html": null,
        "description_text": "General information\nOffice\nBari, Milano, Napoli, Roma\nCountry\nItaly\nDate Published\n17-Dec-2025\nRef #\n2220\nArea\nIT and Information Systems\nType of Presence\nHybrid\nDescription & Requirements\n\ud83d\udccd\nSede\n:\nMilano, Napoli, Roma, Bari\n\ud83d\udc40\nRank\n:\u00a0Associate\nChi siamo\nJAKALA \u00e8 un'azienda che lavora su dati, intelligenza artificiale e sviluppo di esperienze per generare un impatto significativo e duraturo a livello globale.\nPresenti in oltre 30 citt\u00e0 in 21 paesi,\ni nostri team\nuniscono competenze su strategia, tecnologia, creativit\u00e0 e\noperations\nper offrire esperienze personalizzate e soluzioni trasformative ai nostri clienti, grazie al supporto di dati e intelligenza artificiale. I\nJakalers\nsono un gruppo eterogeneo di oltre 3.000 persone, animate da passione, ambizione e idee brillanti. Proprio questa combinazione unica di talenti \u00e8 il fattore distintivo che ha ispirato il nostro\npurpose\n:\nTogether\nto\nget\nthere\n.\nCreare un mondo migliore \u00e8 il nostro obiettivo ultimo: la nostra ambizione \u00e8 generare valore per tutti i nostri stakeholder in modo sostenibile, con particolare attenzione a etica, clima e qualit\u00e0. Nel 2021, abbiamo scelto di diventare una Societ\u00e0 Benefit, dimostrando il nostro impegno di lungo periodo e la volont\u00e0 di proteggere i principi e i valori che ogni giorno guidano le nostre azioni.\nCrediamo che la diversit\u00e0 sia la chiave del nostro successo e, per questo, siamo impegnati a creare un ambiente di lavoro inclusivo, dove ciascuno possa sentirsi valorizzato per la propria unicit\u00e0. Tutte le nostre opportunit\u00e0 di lavoro sono aperte ai candidati appartenenti alle categorie protette L.68/99.\nScopri\nil team\nCX Solutions\nIl team\nCX Solutions di JAKALA si occupa principalmente della progettazione, implementazione, sviluppo e integrazione di soluzioni tecnologiche in ambito customer\nexperience\n.\nIl team\n\u00e8 formato da oltre\n100\nprofessionisti coinvolti su progettualit\u00e0 tech che coinvolgono diverse tecnologie come ad esempio Salesforce, Adobe, Dynamics e tante altre.\n\ud83c\udfaf Le tue responsabilit\u00e0:\nGestire l\u2019operativa della coda dei ticket e monitorar gli SLA\nCoordinare\nteam tecnici\ne stakeholder per garantire livelli di servizio ottimali\nSupportare i colleghi senior nelle attivit\u00e0 quotidiane, nel reporting e nell\u2019analisi\nd\nei trend\nContribuire al miglioramento dei processi e allo sviluppo della knowledge base\nGestire le comunicazioni, escalation ed attivit\u00e0 di manutenzione ordinaria e straordinaria\n\ud83d\ude4c Se\nti riconosci\nin queste caratteristiche, potremmo essere il perfetto match:\n1\u20133 anni di esperienza nella gestione di flussi di Application\nMaintenance\nConoscenza dei processi di\nIncident\nManagement e\nRequest\nManagement\nFamiliarit\u00e0 con strumenti di ticketing (\nService Now\n,\nJira\n,\necc\n)\nOttima conoscenza della lingua inglese (C1 scritto e parlato)\nSolide capacit\u00e0 organizzative, attenzione al dettaglio e orientamento alla qualit\u00e0\nComprensione di base di architetture applicative e infrastrutture IT\nConoscenza del framework ITIL e best practice di Service Management\nEsperienza con Salesforce o CRM affini\nFamiliarit\u00e0\ncon\nmetodologie\nAgile\n\ud83d\udc9c\nScopri nel video le ragioni per cui scegliere JAKALA come prossimo step di carriera\n:\nIn JAKALA crediamo che il tempo e il benessere delle persone vadano rispettati, sempre: incoraggiamo una presenza in ufficio di\n10\ngiorni al mese, lasciando piena libert\u00e0 di lavorare da dove preferisci, sia in Italia che all\u2019interno della Comunit\u00e0 Europea.\nIl nostro sistema di Total\nReward\ninclude convenzioni esclusive per viaggi, ristoranti, shopping, palestra e tempo libero, oltre a servizi gratuiti di telemedicina e supporto psicologico, pensati per te e per chi ami.\nInvestire nel nostro processo di selezione significa ricevere supporto autentico: un Recruiter dedicato ti accompagner\u00e0 con feedback personalizzati, consigli di carriera e insight sul tuo CV, a prescindere dall\u2019esito della candidatura. Niente AI, solo persone. E, grazie all\u2019iniziativa Your Time Back, ti restituiamo il tempo investito nei colloqui con un percorso di empowerment firmato U\nnobravo\n.\n\ud83c\udf31 Ready to start?\nNon \u00e8 solo una candidatura. \u00c8 un percorso che comincia ora. Inviaci il tuo CV: non vediamo l\u2019ora di conoscerti!\nBack\nApply\nShare this job:\nFacebook\nLinkedIn\nEmail",
        "application_url": "https://careers.jakala.com/en_US/careers/ApplicationMethods?jobId=2252",
        "": {},
        "metadata": {
            "Office": "Bari, Milano, Napoli, Roma",
            "Country": "Italy",
            "Date Published": "17-Dec-2025",
            "Ref #": "2220",
            "Area": "IT and Information Systems",
            "Type of Presence": "Hybrid"
        },
        "link": "https://careers.jakala.com/en_US/careers/JobDetail/Experienced-Professional-AMS-Junior-Service-Manager/2252"
    },
    {
        "title": "Experienced Professional | CRO",
        "description_html": null,
        "description_text": "General information\nOffice\nMilano\nCountry\nItaly\nDate Published\n16-Dec-2025\nRef #\n2218\nArea\nManagement Consulting\nType of Presence\nHybrid\nDescription & Requirements\n\ud83d\udccd\nSede\n:\nMilano\n\ud83d\udc40\nRank: Senior Consultant\nChi siamo\nJAKALA \u00e8 un'azienda che lavora su dati, intelligenza artificiale e sviluppo di esperienze per generare un impatto significativo e duraturo a livello globale.\nPresenti in oltre 30 citt\u00e0 in 21 paesi, i nostri team uniscono competenze su strategia, tecnologia, creativit\u00e0 e\noperations\nper offrire esperienze personalizzate e soluzioni trasformative ai nostri clienti, grazie al supporto di dati e intelligenza artificiale. I\nJakalers\nsono un gruppo eterogeneo di oltre 3.000 persone, animate da passione, ambizione e idee brillanti. Proprio questa combinazione unica di talenti \u00e8 il fattore distintivo che ha ispirato il nostro\npurpose\n:\nTogether\nto\nget\nthere\n.\nCreare un mondo migliore \u00e8 il nostro obiettivo ultimo: la nostra ambizione \u00e8 generare valore per tutti i nostri stakeholder in modo sostenibile, con particolare attenzione a etica, clima e qualit\u00e0. Nel 2021, abbiamo scelto di diventare una Societ\u00e0 Benefit, dimostrando il nostro impegno di lungo periodo e la volont\u00e0 di proteggere i principi e i valori che ogni giorno guidano le nostre azioni.\nCrediamo che la diversit\u00e0 sia la chiave del nostro successo e, per questo, siamo impegnati a creare un ambiente di lavoro inclusivo, dove ciascuno possa sentirsi valorizzato per la propria unicit\u00e0. Tutte le nostre opportunit\u00e0 di lavoro sono aperte ai candidati appartenenti alle categorie protette L.68/99.\nScopri il team CRO\nSiamo alla ricerca di un Conversion Rate Optimization & Business Consultant da inserire all'interno del team CRO pi\u00f9 grande d\u2019Italia, un team eterogeneo in cui l'analisi quantitativa degli analytics convive con quella qualitativa della ricerca. Qui potrai applicare le tue competenze analitiche in un settore in forte sviluppo come quello della CRO e utilizzare le tue abilit\u00e0 per contribuire all'ottimizzazione del tasso di conversione per e-commerce internazionali, siti di aziende leader delle telecomunicazioni, mobilit\u00e0, energia, fashion luxury e molto altro conducendo analisi sul comportamento degli utenti e progettando A/B Test innovativi ed ingaggianti per gli utenti.\n\ud83c\udfaf\nLe tue responsabilit\u00e0:\nAnalisi del comportamento degli utenti utilizzando strumenti come Google Analytics per sviluppare soluzioni mirate ad incrementare le conversioni\nUtilizzo di strumenti come Hotjar, Clarity o Contentsquare per comprendere a fondo l\u2019esperienza degli utenti grazie a Heatmap, Scrollmap e Session Recording\nIdeazione di AB Test e personalizzazioni per testare nuove versioni del sito o app in base alle analisi condotte\nCoordinamento efficace di attivit\u00e0 su diversi flussi progettuali contemporaneamente\n\ud83d\ude4c Se ti riconosci in queste caratteristiche, potremmo essere il perfetto match:\nEsperienza di almeno 1-2 anni in ambito Digital Analytics e Conversion Rate Optimization.\nCompetenza nell'utilizzo di Google Analytics. La conoscenza di Adobe Analytics\nrappresenta un plus.\nCapacit\u00e0 di usare strumenti come Hotjar, Clarity o Contentsquare per analizzare Heatmap, Scrollmap e Session Recording\nEsperienze pregressa in progetti di CRO e AB Testing\nOttime doti analitiche e attitudine al problem solving\nForte passione per il mondo digitale\nBuona conoscenza della lingua inglese\n\ud83d\udc9c\nScopri in questo video le ragioni per cui scegliere JAKALA come prossimo step di carriera\nIn JAKALA crediamo che il tempo e il benessere delle persone vadano rispettati, sempre: incoraggiamo una presenza in ufficio di 10 giorni al mese, lasciando piena libert\u00e0 di lavorare da dove preferisci, sia in Italia che all\u2019interno della Comunit\u00e0 Europea.\nIl nostro sistema di Total Reward include convenzioni esclusive per viaggi, ristoranti, shopping, palestra e tempo libero, oltre a servizi gratuiti di telemedicina e supporto psicologico, pensati per te e per chi ami.\nInvestire nel nostro processo di selezione significa ricevere supporto autentico: un Recruiter dedicato ti accompagner\u00e0 con feedback personalizzati, consigli di carriera e insight sul tuo CV, a prescindere dall\u2019esito della candidatura. Niente AI, solo persone. E, grazie all\u2019iniziativa Your Time Back, ti restituiamo il tempo investito nei colloqui con un percorso di empowerment firmato Unobravo.\n\ud83c\udf31 Ready to start?\nNon \u00e8 solo una candidatura. \u00c8 un percorso che comincia ora. Inviaci il tuo CV: non vediamo l\u2019ora di conoscerti!\nBack\nApply\nShare this job:\nFacebook\nLinkedIn\nEmail",
        "application_url": "https://careers.jakala.com/en_US/careers/ApplicationMethods?jobId=2250",
        "": {},
        "metadata": {
            "Office": "Milano",
            "Country": "Italy",
            "Date Published": "16-Dec-2025",
            "Ref #": "2218",
            "Area": "Management Consulting",
            "Type of Presence": "Hybrid"
        },
        "link": "https://careers.jakala.com/en_US/careers/JobDetail/Experienced-Professional-CRO/2250"
    },
    {
        "title": "Experienced Professional | Azure Data Engineer",
        "description_html": null,
        "description_text": "General information\nOffice\nMilano, Napoli, Rende, Roma\nCountry\nItaly\nDate Published\n16-Dec-2025\nRef #\n2219\nArea\nIT and Information Systems\nType of Presence\nHybrid\nDescription & Requirements\n\ud83d\udccd\nSede\n:\u00a0Milano, Rende, Roma, Napoli\n\ud83d\udc40\nRank:\u00a0Expert Lead\nChi siamo\nJAKALA \u00e8 un'azienda che lavora su dati, intelligenza artificiale e sviluppo di esperienze per generare un impatto significativo e duraturo a livello globale.\nPresenti in oltre 30 citt\u00e0 in 21 paesi,\ni nostri team\nuniscono competenze su strategia, tecnologia, creativit\u00e0 e\noperations\nper offrire esperienze personalizzate e soluzioni trasformative ai nostri clienti, grazie al supporto di dati e intelligenza artificiale. I\nJakalers\nsono un gruppo eterogeneo di oltre 3.000 persone, animate da passione, ambizione e idee brillanti. Proprio questa combinazione unica di talenti \u00e8 il fattore distintivo che ha ispirato il nostro\npurpose\n:\nTogether\nto\nget\nthere\n.\nCreare un mondo migliore \u00e8 il nostro obiettivo ultimo: la nostra ambizione \u00e8 generare valore per tutti i nostri stakeholder in modo sostenibile, con particolare attenzione a etica, clima e qualit\u00e0. Nel 2021, abbiamo scelto di diventare una Societ\u00e0 Benefit, dimostrando il nostro impegno di lungo periodo e la volont\u00e0 di proteggere i principi e i valori che ogni giorno guidano le nostre azioni.\nCrediamo che la diversit\u00e0 sia la chiave del nostro successo e, per questo, siamo impegnati a creare un ambiente di lavoro inclusivo, dove ciascuno possa sentirsi valorizzato per la propria unicit\u00e0. Tutte le nostre opportunit\u00e0 di lavoro sono aperte ai candidati appartenenti alle categorie protette L.68/99.\nScopri\nil team\nData Management & Architecture\nIl team\nData Management and Architecture di JAKALA si occupa prevalentemente della progettazione, implementazione e manutenzione di architetture dati scalabili, sicure e affidabili in ambienti cloud\nenterprise\n. La nostra squadra \u00e8 formata da Data\nEngineer\ne Data Architect che offrono quotidianamente il loro contributo e la loro expertise su progetti di trasformazione digitale lavorando con tecnologie cloud moderne, collaborando con\nteam\ndi data\nanalytics\ne business\n.\n\ud83c\udfaf Le tue responsabilit\u00e0:\nProgettazione e implementazione di soluzioni dati in ambienti cloud (Azure, GCP,\nDatabricks\n), contribuendo alla creazione di sistemi scalabili e resilienti sotto la guida di figure senior\nPartecipare alla costruzione e manutenzione di pipeline di dati (ETL/ELT), e flussi di lavoro correlati, utilizzando strumenti cloud-native come Azure Data\nFactory\n,\nDatabricks\no\nDataflow\nLavorare con team cross-funzionali per raccogliere requisiti e supportare l\u2019analisi, trasformando i bisogni di business in soluzioni tecniche con il supporto di colleghi pi\u00f9 esperti.\n\ud83d\ude4c Se\nti riconosci\nin queste caratteristiche, potremmo essere il perfetto match:\nLaurea\nin Informatica, Ingegneria Informatica o affini\n5-7anni di esperienza come Data\nEngineer\ne\nd e\nsperienza comprovata su Microsoft Azure: preferibilmente\ncon servizi come Azure Data\nFactory\n, Azure\nSynapse\n, Azure Storage, Azure\nFunctions\n,\nAzure\nLogic\nAPP,\nDataBricks\ne\nFabric\nConoscenza approfondita di programmazione Java/Python\nOttima conoscenza di SQL Server e preferibilmente di Scala\nBuona conoscenza della lingua inglese\nForte interesse all\u2019innovazione e allo studio di nuove soluzioni tecniche in ambito Data Management\nOttime doti relazionali e comunicative, orientamento\nal team\ne attenzione verso stakeholder\n\ud83d\udc9c\nScopri nel video le ragioni per cui scegliere JAKALA come prossimo step di carriera\n:\nIn JAKALA crediamo che il tempo e il benessere delle persone vadano rispettati, sempre: incoraggiamo una presenza in ufficio di\n10\ngiorni al mese, lasciando piena libert\u00e0 di lavorare da dove preferisci, sia in Italia che all\u2019interno della Comunit\u00e0 Europea.\nIl nostro sistema di Total\nReward\ninclude convenzioni esclusive per viaggi, ristoranti, shopping, palestra e tempo libero, oltre a servizi gratuiti di telemedicina e supporto psicologico, pensati per te e per chi ami.\nInvestire nel nostro processo di selezione significa ricevere supporto autentico: un Recruiter dedicato ti accompagner\u00e0 con feedback personalizzati, consigli di carriera e insight sul tuo CV, a prescindere dall\u2019esito della candidatura. Niente AI, solo persone. E, grazie all\u2019iniziativa Your Time Back, ti restituiamo il tempo investito nei colloqui con un percorso di empowerment firmato\nUnobravo\n.\n\ud83c\udf31 Ready to start?\nNon \u00e8 solo una candidatura. \u00c8 un percorso che comincia ora. Inviaci il tuo CV: non vediamo l\u2019ora di conoscerti!\nBack\nApply\nShare this job:\nFacebook\nLinkedIn\nEmail",
        "application_url": "https://careers.jakala.com/en_US/careers/ApplicationMethods?jobId=2251",
        "": {},
        "metadata": {
            "Office": "Milano, Napoli, Rende, Roma",
            "Country": "Italy",
            "Date Published": "16-Dec-2025",
            "Ref #": "2219",
            "Area": "IT and Information Systems",
            "Type of Presence": "Hybrid"
        },
        "link": "https://careers.jakala.com/en_US/careers/JobDetail/Experienced-Professional-Azure-Data-Engineer/2251"
    },
    {
        "title": "Intern | HR Learning & Development (People Growth)",
        "description_html": null,
        "description_text": "General information\nOffice\nMilano\nCountry\nItaly\nDate Published\n15-Dec-2025\nRef #\n2215\nArea\nHuman Resources\nType of Presence\nHybrid\nDescription & Requirements\n\ud83d\udccd\nSede\n: Milano\nChi siamo\nJAKALA \u00e8 un'azienda che lavora su dati, intelligenza artificiale e sviluppo di esperienze per generare un impatto significativo e duraturo a livello globale.\nPresenti in oltre 30 citt\u00e0 in 21 paesi,\ni nostri team\nuniscono competenze su strategia, tecnologia, creativit\u00e0 e\noperations\nper offrire esperienze personalizzate e soluzioni trasformative ai nostri clienti, grazie al supporto di dati e intelligenza artificiale. I\nJakalers\nsono un gruppo eterogeneo di oltre 3.000 persone, animate da passione, ambizione e idee brillanti. Proprio questa combinazione unica di talenti \u00e8 il fattore distintivo che ha ispirato il nostro\npurpose\n:\nTogether\nto\nget\nthere\n.\nCreare un mondo migliore \u00e8 il nostro obiettivo ultimo: la nostra ambizione \u00e8 generare valore per tutti i nostri stakeholder in modo sostenibile, con particolare attenzione a etica, clima e qualit\u00e0. Nel 2021, abbiamo scelto di diventare una Societ\u00e0 Benefit, dimostrando il nostro impegno di lungo periodo e la volont\u00e0 di proteggere i principi e i valori che ogni giorno guidano le nostre azioni.\nCrediamo che la diversit\u00e0 sia la chiave del nostro successo e, per questo, siamo impegnati a creare un ambiente di lavoro inclusivo, dove ciascuno possa sentirsi valorizzato per la propria unicit\u00e0. Tutte le nostre opportunit\u00e0 di lavoro sono aperte ai candidati appartenenti alle categorie protette L.68/99.\nScopri il team People\nGrowth\nTi piacerebbe esplorare il mondo delle risorse umane da una prospettiva innovativa? Vorresti contribuire a promuovere un approccio pionieristico e avere un impatto reale sulla crescita delle persone intorno a te? Ti entusiasma lavorare con colleghi distribuiti in oltre 50 uffici in 30 paesi e combinare dati, idee e cambiamento per ottenere risultati concreti? Se ti rispecchi in questa descrizione, prenditi cinque minuti per inviarci la tua candidatura: con pochi click potresti influenzare il tuo futuro.\n\ud83c\udfaf Ogni giorno sar\u00e0 diverso, ma eccoti un assaggio di quello che ti aspetta\nCollabora con\nil team\nper identificare le esigenze di formazione dei nostri\nJakaler\ne progetta contenuti ed iniziative ad hoc insieme a\ntrainer\ninterni/esterni\nSupporta l\u2019organizzazione di aule formative, workshop, eventi di team building e attivit\u00e0 di sviluppo, curandone la logistica e garantendo un\u2019esperienza coinvolgente per tutti i partecipanti\nContribuisci alla definizione del target dei partecipanti, alla pianificazione del calendario formativo e alla scelta della modalit\u00e0 di delivery pi\u00f9 efficace (in presenza, on-line, blended)\nMettiti alla prova svolgendo in prima persona attivit\u00e0 di tutoraggio, registrazione presenze e preparazione di materiale di comunicazione (presentazioni, Intranet aziendale, ecc.)\nMonitora KPI formativi e operativi, sviluppa e analizza survey di gradimento e raccogli feedback qualitativi, contribuendo alla reportistica periodica e all\u2019identificazione di azioni di miglioramento per valutare l\u2019efficacia delle iniziative L&D\nSupporta\nil team\nnelle attivit\u00e0 di Performance Management, con un focus sui colleghi in Italia e in collaborazione con le altre\nregion\n, contribuendo alla raccolta e sistematizzazione dei dati di valutazione e alla preparazione dei materiali per le diverse fasi del ciclo di performance, oltre all\u2019aggiornamento dei nostri sistemi\nPartecipa all\u2019analisi dei risultati delle valutazioni e aiuta a identificare insight utili\u202fper individuare\ntrend\n, aree di forza e opportunit\u00e0 di crescita, fornendo un contributo alla definizione di azioni di miglioramento e piani di sviluppo\nTogether\n\u00e8 il nostro motto: lavora a stretto contatto con tutti i colleghi HR, contribuisci a progetti trasversali e supporta\nil team\nnel raggiungimento di risultati condivisi\n\ud83d\udca1 Queste caratteristiche sono un ottimo punto di partenza per crescere insieme\nLaurea in discipline umanistiche, economiche o affini\nOttima conoscenza dei principali strumenti del pacchetto MS Office\nOttima conoscenza della lingua italiana e inglese\nCapacit\u00e0 di comunicare in modo chiaro ed efficace, con una naturale attitudine alla relazione\nSpiccata attitudine all\u2019organizzazione, precisione e puntualit\u00e0\n\ud83d\ude80 Ci brillano gli occhi se hai anche\nMente creativa e curiosa, pronta a proporre idee innovative che facciano la differenza\nOrientamento al risultato e attitudine al lavoro di squadra\nProattivit\u00e0, intraprendenza e motivazione\n\ud83d\udc9c Scopri in questo video le ragioni per cui scegliere JAKALA come prossimo step di carriera\nIn JAKALA crediamo che il tempo e il benessere delle persone vadano rispettati, sempre: incoraggiamo una presenza in ufficio di10giorni al mese.\nIl nostro sistema di TotalRewardinclude convenzioni esclusive per viaggi, ristoranti, shopping, palestra e tempo libero, oltre a servizi gratuiti di telemedicina e supporto psicologico, pensati per te e per chi ami.\nInvestire nel nostro processo di selezione significa ricevere supporto autentico: un Recruiter dedicato ti accompagner\u00e0 con feedback personalizzati, consigli di carriera e insight sul tuo CV, a prescindere dall\u2019esito della candidatura. Niente AI, solo persone. E, grazie all\u2019iniziativa Your Time Back, ti restituiamo il tempo investito nei colloqui con un percorso di empowerment firmatoUnobravo.\n\ud83c\udf31 Ready to start?\nNon \u00e8 solo una candidatura. \u00c8 un percorso che comincia ora. Inviaci il tuo CV: non vediamo l\u2019ora di conoscerti!\nBack\nApply\nShare this job:\nFacebook\nLinkedIn\nEmail",
        "application_url": "https://careers.jakala.com/en_US/careers/ApplicationMethods?jobId=2247",
        "": {},
        "metadata": {
            "Office": "Milano",
            "Country": "Italy",
            "Date Published": "15-Dec-2025",
            "Ref #": "2215",
            "Area": "Human Resources",
            "Type of Presence": "Hybrid"
        },
        "link": "https://careers.jakala.com/en_US/careers/JobDetail/Intern-HR-Learning-Development-People-Growth/2247"
    },
    {
        "title": "Senior Frontend Developer (all genders) - React",
        "description_html": null,
        "description_text": "General information\nOffice\nFull Remote\nCountry\nGermany\nDate Published\n12-Dec-2025\nRef #\n2214\nArea\nIT and Information Systems\nType of Presence\nRemote\nDescription & Requirements\nDu bist erfahrener Frontend Developer (all\ngenders\n) mit einer Leidenschaft f\u00fcr innovative L\u00f6sungen? Du bringst tiefgehende Erfahrung in der Entwicklung von Webanwendungen mit und liebst es, im Team anspruchsvolle Projekte mit React im Frontend zu realisieren? Dann suchen wir genau dich.\nZum n\u00e4chstm\u00f6glichen Zeitpunkt suchen wir einen motivierten und engagierten Senior Frontend Developer (all\ngenders\n) in Hamburg, Berlin, Wien, hybrid oder remote.\nResponsibilities\nDu entwickelst die Plattform eines unserer Kunden innovativ und nach neuesten Standards weiter\nDu arbeitest eng mit UX/UI-Design und Backend-Entwicklung\nzusammen\num zur herausragende Benutzererlebnissen innerhalb der Produktteams zu schaffen\nDu bindest die AWS Cloud Services an das Frontend an\nDu integrierst Inhalte aus dem\nHeadless\nCMS\nDu entwickelst die Personalisierung und Messbarkeit der Nutzererfahrung weiter\nDu gew\u00e4hrleistest hohe Code-Qualit\u00e4t und setzt Clean Code-Prinzipien konsequent um, um wartbare und erweiterbare Anwendungen zu schaffen\nOverview\nJAKALA ist ein weltweit t\u00e4tiges IT- und Consulting-Unternehmen im Bereich\nMartech\n, mit einem starken Fokus auf Daten und KI. Von den weltweit \u00fcber 3.300 Mitarbeitenden sind rund 230 in Hamburg und Berlin t\u00e4tig. Bei JAKALA Germany liegt der Schwerpunkt auf der Entwicklung von individuellen Software-L\u00f6sungen, haupts\u00e4chlich von sogenannten Digital Experience\nPlatforms\n(DXP), in denen Gesch\u00e4ftsprozesse entlang der Customer Journey digitalisiert werden. An der Schnittstelle von Strategie, Design und Technologie entwickelt JAKALA digitale Plattformen, Apps und andere Services, welche die digitalen Erlebnisse gro\u00dfer Marken ma\u00dfgeblich pr\u00e4gen. Zu den Kunden in Deutschland z\u00e4hlen beispielsweise TUI Cruises, Leica, die Hamburger Hochbahn oder das ZDF.\nQualifications\nDu besitzt tiefe Kenntnisse in\nJavascript\n/\nTypescript\n, React und Next.js und hast mit diesen Technologien bereits erfolgreich in Projekten gearbeitet\nDu hast einen technologischen Weitblick und breite Erfahrungswerte \u00fcber das Kernarbeitsgebiet hinaus (Personalisierung, Daten, SEO, Analytics,\nContentful\nCMS, AWS, Designsystem)\nDu bist vertraut mit agilen Entwicklungsmethoden und f\u00fchlst dich in integrierten Teams wohl\nDu verf\u00fcgst \u00fcber eine schnelle Auffassungsgabe\nDu hast ein wirtschaftliches Bewusstsein f\u00fcr ein angemessenes Ma\u00df zwischen Effizienz und h\u00f6chster Qualit\u00e4t\nDu bist\nein:e\nstarke:r\nKommunikator:in\n, der oder die sich sowohl in der Zusammenarbeit mit interdisziplin\u00e4ren Teams als auch im Austausch mit Kunden souver\u00e4n bewegt, mindestens auf Deutsch und besser noch zus\u00e4tzlich auf Englisch\nOffer\nDas bieten wir dir:\nJob in Vollzeit oder Teilzeit - du entscheidest\nHybrides Arbeitsmodell (Remote und B\u00fcro) mit flexiblen Arbeitszeiten\nOffene und teamorientierte Unternehmenskultur\nWertsch\u00e4tzung deiner Ideen\nZuschuss f\u00fcr \u00d6PNV und\nBikeleasing\n-Option\nUrban Sports Club Membership\nW\u00f6chentliches gemeinsames Fr\u00fchst\u00fcck oder Mittagessen\nWenn du willst: Einstieg in unsere Hamburger Band (\nSchlagzeuger:in\ngesucht)\nWhat\nelse\n?\nWir wollen einen positiven Impact auf unsere Erde haben. Deshalb streben wir danach, auf nachhaltige Weise Wert f\u00fcr alle Interessengruppen zu schaffen und ber\u00fccksichtigen dabei Klima, Ethik und Qualit\u00e4t. 2021 haben wir uns entschieden, eine Benefit Corporation zu werden, um unser langfristiges Engagement f\u00fcr den Schutz der Prinzipien und Werte, die unser Handeln leiten, zu unterstreichen.\nBewirb dich noch heute. Wir freuen uns darauf, dich kennenzulernen.\nBack\nApply\nShare this job:\nFacebook\nLinkedIn\nEmail",
        "application_url": "https://careers.jakala.com/en_US/careers/ApplicationMethods?jobId=2246",
        "": {},
        "metadata": {
            "Office": "Full Remote",
            "Country": "Germany",
            "Date Published": "12-Dec-2025",
            "Ref #": "2214",
            "Area": "IT and Information Systems",
            "Type of Presence": "Remote"
        },
        "link": "https://careers.jakala.com/en_US/careers/JobDetail/Senior-Frontend-Developer-all-genders-React/2246"
    },
    {
        "title": "Experienced Professional | Cloud Data Architect",
        "description_html": null,
        "description_text": "General information\nOffice\nMilano, Rende, Roma\nCountry\nItaly\nDate Published\n11-Dec-2025\nRef #\n2210\nArea\nIT and Information Systems\nType of Presence\nHybrid\nDescription & Requirements\n\ud83d\udccd\nSede\n: Milano, Rende, Roma\n\ud83d\udc40\nRank: Expert Lead\nChi siamo\nJAKALA \u00e8 un'azienda che lavora su dati, intelligenza artificiale e sviluppo di esperienze per generare un impatto significativo e duraturo a livello globale.\nPresenti in oltre 30 citt\u00e0 in 21 paesi,\ni nostri team\nuniscono competenze su strategia, tecnologia, creativit\u00e0 e\noperations\nper offrire esperienze personalizzate e soluzioni trasformative ai nostri clienti, grazie al supporto di dati e intelligenza artificiale. I\nJakalers\nsono un gruppo eterogeneo di oltre 3.000 persone, animate da passione, ambizione e idee brillanti. Proprio questa combinazione unica di talenti \u00e8 il fattore distintivo che ha ispirato il nostro\npurpose\n:\nTogether\nto\nget\nthere\n.\nCreare un mondo migliore \u00e8 il nostro obiettivo ultimo: la nostra ambizione \u00e8 generare valore per tutti i nostri stakeholder in modo sostenibile, con particolare attenzione a etica, clima e qualit\u00e0. Nel 2021, abbiamo scelto di diventare una Societ\u00e0 Benefit, dimostrando il nostro impegno di lungo periodo e la volont\u00e0 di proteggere i principi e i valori che ogni giorno guidano le nostre azioni.\nCrediamo che la diversit\u00e0 sia la chiave del nostro successo e, per questo, siamo impegnati a creare un ambiente di lavoro inclusivo, dove ciascuno possa sentirsi valorizzato per la propria unicit\u00e0. Tutte le nostre opportunit\u00e0 di lavoro sono aperte ai candidati appartenenti alle categorie protette L.68/99.\nScopri\nil team\nData Management & Architecture\nIl team\nData Management and Architecture di JAKALA si occupa prevalentemente della progettazione, implementazione e manutenzione di architetture dati scalabili, sicure e affidabili in ambienti cloud\nenterprise\n. La nostra squadra \u00e8 formata da Data\nEngineer\ne Data Architect che offrono quotidianamente il loro contributo e la loro expertise su progetti di trasformazione digitale lavorando con tecnologie cloud moderne, collaborando con\nteam\ndi data\nanalytics\ne business\n.\n\ud83c\udfaf Le tue responsabilit\u00e0:\nProgettare e implementare soluzioni dati scalabili, resilienti e ottimizzate in ambienti Azure, GCP e\nDatabricks\nCostruire e mantenere pipeline di dati (ETL/ELT) attraverso strumenti cloud-native (es. Azure Data\nFactory\n,\nDatabricks\n,\nDataflow\n, etc.).\nGuidare l\u2019evoluzione architetturale dei progetti dati, garantendo scalabilit\u00e0, performance e sicurezza\nCollaborare con team cross-funzionali per raccogliere requisiti, supportare l\u2019analisi e trasformare i bisogni di business in soluzioni tecniche concrete\nEssere punto di riferimento per\nil team\nsu tecnologia Azure, mantenendo una buona conoscenza anche di GCP e\nDatabricks\nper integrazioni multi-cloud\n\ud83d\ude4c Se\nti riconosci\nin queste caratteristiche, potremmo essere il perfetto match:\nLaurea in Informatica, Ingegneria Informatica o affini\n5-7 anni di esperienza come Cloud Data Architect ed esperienza comprovata su Microsoft Azure: preferibilmente con servizi come Azure Data\nFactory\n, Azure, Azure\nSynapse\n, Azure Storage, Azure\nFunctions\n,\nFabric\nOttima conoscenza di\nDatabricks\nEsperienza nello sviluppo di pipeline dati e trasformazioni ETL/ELT.\nConoscenza approfondita di Spark e buona padronanza dei linguaggi Python, SQL e preferibilmente Scala\nConoscenza dei principi CI/CD e strumenti come\nGitLab\n, GitHub\nForte interesse all\u2019innovazione e allo studio di nuove soluzioni tecniche in ambito DM\nOttime doti relazionali e comunicative, orientamento\nal team\ne attenzione verso stakeholder\nBuona conoscenza della lingua inglese\nCostituisce titolo preferenziale la conoscenza di Google Cloud Platform (GCP) ed il possesso di certificazioni cloud (Azure, GCP,\nDatabricks\n)\n\ud83d\udc9c\nScopri nel video le ragioni per cui scegliere JAKALA come prossimo step di carriera\n:\nIn JAKALA crediamo che il tempo e il benessere delle persone vadano rispettati, sempre: incoraggiamo una presenza in ufficio di\n10\ngiorni al mese, lasciando piena libert\u00e0 di lavorare da dove preferisci, sia in Italia che all\u2019interno della Comunit\u00e0 Europea.\nIl nostro sistema di Total\nReward\ninclude convenzioni esclusive per viaggi, ristoranti, shopping, palestra e tempo libero, oltre a servizi gratuiti di telemedicina e supporto psicologico, pensati per te e per chi ami.\nInvestire nel nostro processo di selezione significa ricevere supporto autentico: un Recruiter dedicato ti accompagner\u00e0 con feedback personalizzati, consigli di carriera e insight sul tuo CV, a prescindere dall\u2019esito della candidatura. Niente AI, solo persone. E, grazie all\u2019iniziativa Your Time Back, ti restituiamo il tempo investito nei colloqui con un percorso di empowerment firmato\nUnobravo\n.\n\ud83c\udf31 Ready to start?\nNon \u00e8 solo una candidatura. \u00c8 un percorso che comincia ora. Inviaci il tuo CV: non vediamo l\u2019ora di conoscerti!\nBack\nApply\nShare this job:\nFacebook\nLinkedIn\nEmail",
        "application_url": "https://careers.jakala.com/en_US/careers/ApplicationMethods?jobId=2242",
        "": {},
        "metadata": {
            "Office": "Milano, Rende, Roma",
            "Country": "Italy",
            "Date Published": "11-Dec-2025",
            "Ref #": "2210",
            "Area": "IT and Information Systems",
            "Type of Presence": "Hybrid"
        },
        "link": "https://careers.jakala.com/en_US/careers/JobDetail/Experienced-Professional-Cloud-Data-Architect/2242"
    },
    {
        "title": "Privacy | Martech Engineer Consultant",
        "description_html": null,
        "description_text": "General information\nOffice\nBarcelona, Gij\u00f3n, Madrid, Pamplona, Full Remote\nCountry\nSpain\nDate Published\n10-Dec-2025\nRef #\n2199\nArea\nMarketing\nType of Presence\nHybrid\nDescription & Requirements\nEn Jakala buscamos a una persona con ganas de aprender, que nos ayude en la\nimplementaci\u00f3n t\u00e9cnica de herramientas de privacidad\ndentro de nuestro ecosistema\nMarTech\n.\nTu misi\u00f3n ser\u00e1 colaborar en que la\ngesti\u00f3n de consentimientos y preferencias de comunicaci\u00f3n\nde los usuarios se orqueste correctamente a trav\u00e9s de todo el\nstack tecnol\u00f3gico\n(web/app, tag managers, CDPs, plataformas de marketing y data), siempre con el apoyo de perfiles\nsenior\ndel equipo.\nTrabajar\u00e1s\nmano a mano\ncon los equipos de\nMarketing, Data, Tecnolog\u00eda y Legal\n, participando en tareas de configuraci\u00f3n, pruebas y documentaci\u00f3n para garantizar que la experiencia de usuario sea\ncumplidora, confiable y medible\n, habilitando casos de uso de personalizaci\u00f3n\nprivacy\u2011first\n.\nQu\u00e9 har\u00e1s (Responsabilidades)\nImplementar y operar\nherramientas de gesti\u00f3n de privacidad (p. ej.,\nOneTrust\n: CMP, UCPM), asegurando su\ncorrecto funcionamiento\ny gobierno.\nConfigurar y documentar APIs\npara la entrada/salida de datos entre la plataforma de consentimientos y el stack (web/app, CRM, CDP, SFMC/Adobe, etc.).\nDise\u00f1ar y validar journeys de usuario\nteniendo en cuenta estados de consentimiento, preferencias de canal y reglas de exclusi\u00f3n (legal grounds, frequency caps, do\u2011not\u2011contact).\nAuditar y monitorizar\nse\u00f1ales de consentimiento (web/app events, SDKs, data pipelines) y su\ntrazabilidad\nhasta activaci\u00f3n de campa\u00f1as.\nColaborar con Legal/Privacy\npara traducir requisitos normativos (RGPD/ePrivacy) a\ncontroles t\u00e9cnicos\ny flujos operativos.\nDefinir est\u00e1ndares y playbooks\n(naming, taxonom\u00eda, QA, versionado, alertas) que garanticen\ncalidad de datos y cumplimiento\nen escala.\nParticipar en incident response\ny planes de mejora continua (testing, A/B sobre UX de consentimientos, reducci\u00f3n de fricci\u00f3n, accesibilidad).\nRequisitos (Must)\nExperiencia pr\u00e1ctica en\nsoluciones de privacidad\ny\ngesti\u00f3n de consentimientos\nde usuarios (comunicaciones, cookies, preferencias).\nDominio de\nOneTrust\n(p. ej.,\nCMP, UCPM\n) y sus componentes de despliegue/configuraci\u00f3n.\nCapacidad para\nvalidar journeys\ny traducir condiciones de consentimiento a reglas de activaci\u00f3n/capado en herramientas de marketing.\nDeseable (Nice to have)\nExperiencia\nconfigurando APIs\ny\nwebhooks\n(REST/JSON), as\u00ed como integraci\u00f3n con CRM/CDP.\nConocimiento de\nTag Managers\n(GTM, Tealium) o\nCDPs\n(Salesforce Data Cloud, Adobe RTCDP, Segment).\nFundamentos de\ndata quality\n(event design, schema, governance) y\nobservabilidad\n(logs, alertas, dashboards).\nExperiencia con\nentornos cloud\n(Azure/AWS/GCP) y flujos ETL/ELT.\nIngl\u00e9s profesional.\n\u00bfQu\u00e9 ofrecemos?\nModelo h\u00edbrido de asistencia a la oficina (2 d\u00edas/semana presencial).\nTres semanas al a\u00f1o de full remote.\nSeguro m\u00e9dico.\nWellhub para cuidar tu salud f\u00edsica y mental.\nRetribuci\u00f3n flexible.\n28 d\u00edas de vacaciones al a\u00f1o.\nPath de carrera adaptado a tus inquietudes profesionales.\nAcceso a certificaciones (somos partners de Google y Salesforce).\nJxpert: programas de capacitaci\u00f3n tecnol\u00f3gica de las distintas disciplinas de JAKALA.\nJlab: nuestro laboratorio de pruebas de soluciones tecnol\u00f3gicas.\nFormaci\u00f3n en idiomas.\nDeporte en la oficina (entrenamiento funcional y yoga).\nOficina de Madrid: Servicio de lanzadera.\nDescripci\u00f3n de la empresa:\nSomos un ecosistema dise\u00f1ado para que el talento y las soluciones innovadoras se unan para impulsar el valor para las organizaciones, las personas y la sociedad.\nHoy en d\u00eda, somos la empresa l\u00edder en Martech en Europa, con sede en Mil\u00e1n y oficinas en todo el mundo. Nuestro enfoque impulsado por datos, respaldado por una f\u00f3rmula ganadora de estrategia, innovaci\u00f3n, transformaci\u00f3n tecnol\u00f3gica, compromiso y activaci\u00f3n, es la piedra angular de nuestro trabajo.\nCon un equipo de 3,000 empleados, m\u00e1s de 900 clientes y proyectos en m\u00e1s de 30 pa\u00edses, y una facturaci\u00f3n que supera los 500 millones de euros, JAKALA emerge como un verdadero punto de referencia en el vasto panorama digital. Gracias a la contribuci\u00f3n de un equipo internacional compuesto por talentos vers\u00e1tiles y altamente calificados, la empresa ofrece soluciones \u00fanicas y personalizadas, anticipando los desaf\u00edos de un mercado en constante evoluci\u00f3n. Reconocida como\nEmpresa Great Place to Work 2024\n, JAKALA persigue sus objetivos con la firme creencia de que el bienestar de los empleados y un impacto positivo en el medio ambiente son elementos esenciales para garantizar un crecimiento sostenible.\nBack\nApply\nShare this job:\nFacebook\nLinkedIn\nEmail",
        "application_url": "https://careers.jakala.com/en_US/careers/ApplicationMethods?jobId=2231",
        "": {},
        "metadata": {
            "Office": "Barcelona, Gij\u00f3n, Madrid, Pamplona, Full Remote",
            "Country": "Spain",
            "Date Published": "10-Dec-2025",
            "Ref #": "2199",
            "Area": "Marketing",
            "Type of Presence": "Hybrid"
        },
        "link": "https://careers.jakala.com/en_US/careers/JobDetail/Privacy-Martech-Engineer-Consultant/2231"
    },
    {
        "title": "Experienced Professional | GCP Data Engineer",
        "description_html": null,
        "description_text": "General information\nOffice\nMilano, Napoli, Rende, Roma\nCountry\nItaly\nDate Published\n10-Dec-2025\nRef #\n2205\nArea\nIT and Information Systems\nType of Presence\nHybrid\nDescription & Requirements\n\ud83d\udccd\nSede\n: Milano, Rende, Roma, Napoli\n\ud83d\udc40\nRank\n: Senior Associate\nChi siamo\nJAKALA \u00e8 un'azienda che lavora su dati, intelligenza artificiale e sviluppo di esperienze per generare un impatto significativo e duraturo a livello globale.\nPresenti in oltre 30 citt\u00e0 in 21 paesi,\ni nostri team\nuniscono competenze su strategia, tecnologia, creativit\u00e0 e\noperations\nper offrire esperienze personalizzate e soluzioni trasformative ai nostri clienti, grazie al supporto di dati e intelligenza artificiale. I\nJakalers\nsono un gruppo eterogeneo di oltre 3.000 persone, animate da passione, ambizione e idee brillanti. Proprio questa combinazione unica di talenti \u00e8 il fattore distintivo che ha ispirato il nostro\npurpose\n:\nTogether\nto\nget\nthere\n.\nCreare un mondo migliore \u00e8 il nostro obiettivo ultimo: la nostra ambizione \u00e8 generare valore per tutti i nostri stakeholder in modo sostenibile, con particolare attenzione a etica, clima e qualit\u00e0. Nel 2021, abbiamo scelto di diventare una Societ\u00e0 Benefit, dimostrando il nostro impegno di lungo periodo e la volont\u00e0 di proteggere i principi e i valori che ogni giorno guidano le nostre azioni.\nCrediamo che la diversit\u00e0 sia la chiave del nostro successo e, per questo, siamo impegnati a creare un ambiente di lavoro inclusivo, dove ciascuno possa sentirsi valorizzato per la propria unicit\u00e0. Tutte le nostre opportunit\u00e0 di lavoro sono aperte ai candidati appartenenti alle categorie protette L.68/99.\nScopri\nil team\nData Management & Architecture\nIl team\nData Management and Architecture di JAKALA si occupa prevalentemente della progettazione, implementazione e manutenzione di architetture dati scalabili, sicure e affidabili in ambienti cloud\nenterprise\n. La nostra squadra \u00e8 formata da Data\nEngineer\ne Data Architect che offrono quotidianamente il loro contributo e la loro expertise su progetti di trasformazione digitale lavorando con tecnologie cloud moderne, collaborando con\nteam\ndi data\nanalytics\ne business\n.\n\ud83c\udfaf Le tue responsabilit\u00e0:\nProgettare, costruire e\ninstrumentare\nsoluzioni di dati efficienti, flessibili e scalabili\nCreare, costruire e mantenere pipeline di dati, ETL/ELT, e flussi di lavoro correlati\nLavorare con\nun team\ndi data engineering e con\nteam\ndi analisi\ne business\nper comprendere i requisiti dei dati e utilizzare questa conoscenza per progettare sistemi di dati\n\ud83d\ude4c Se\nti riconosci\nin queste caratteristiche, potremmo essere il perfetto match:\nLaurea in Informatica, Ingegneria Informatica o affini\n3-4 anni di esperienza come Data\nEngineer\ncon ecosistema GCP e strumenti correlati (\nGBig\nQuery,\nDataproc\n,\nDataflow\n, Composer, Cloud Storage e Apache\nbeam\n)\nConoscenza delle tecniche di ETL/ELT e dei processi di trasformazione dei dati\nEsperienza con linguaggi come Python/Scala, SQL. Consolidata esperienza con Spark\nFamiliarit\u00e0 con le tecniche di modellazione dei dati e relative best practice.\nCapacit\u00e0 di lavorare con tecnologie CI/CD come\nGitLab\n, GitHub\nEsperienza con database relazionali e non relazionali\nOttime doti relazionali e comunicative\n\ud83d\udc9c\nScopri nel video le ragioni per cui scegliere JAKALA come prossimo step di carriera\n:\nIn JAKALA crediamo che il tempo e il benessere delle persone vadano rispettati, sempre: incoraggiamo una presenza in ufficio di\n10\ngiorni al mese, lasciando piena libert\u00e0 di lavorare da dove preferisci, sia in Italia che all\u2019interno della Comunit\u00e0 Europea.\nIl nostro sistema di Total\nReward\ninclude convenzioni esclusive per viaggi, ristoranti, shopping, palestra e tempo libero, oltre a servizi gratuiti di telemedicina e supporto psicologico, pensati per te e per chi ami.\nInvestire nel nostro processo di selezione significa ricevere supporto autentico: un Recruiter dedicato ti accompagner\u00e0 con feedback personalizzati, consigli di carriera e insight sul tuo CV, a prescindere dall\u2019esito della candidatura. Niente AI, solo persone. E, grazie all\u2019iniziativa Your Time Back, ti restituiamo il tempo investito nei colloqui con un percorso di empowerment firmato\nUnobravo\n.\n\ud83c\udf31 Ready to start?\nNon \u00e8 solo una candidatura. \u00c8 un percorso che comincia ora. Inviaci il tuo CV: non vediamo l\u2019ora di conoscerti!\nBack\nApply\nShare this job:\nFacebook\nLinkedIn\nEmail",
        "application_url": "https://careers.jakala.com/en_US/careers/ApplicationMethods?jobId=2237",
        "": {},
        "metadata": {
            "Office": "Milano, Napoli, Rende, Roma",
            "Country": "Italy",
            "Date Published": "10-Dec-2025",
            "Ref #": "2205",
            "Area": "IT and Information Systems",
            "Type of Presence": "Hybrid"
        },
        "link": "https://careers.jakala.com/en_US/careers/JobDetail/Experienced-Professional-GCP-Data-Engineer/2237"
    },
    {
        "title": "Intern | Graphic Designer",
        "description_html": null,
        "description_text": "General information\nOffice\nRoncade\nCountry\nItaly\nDate Published\n10-Dec-2025\nRef #\n2206\nArea\nIT and Information Systems\nType of Presence\nHybrid\nDescription & Requirements\n\ud83d\udccd\nSede\n: Roncade\nChi siamo\nJAKALA \u00e8 un'azienda che lavora su dati, intelligenza artificiale e sviluppo di esperienze per generare un impatto significativo e duraturo a livello globale.\nPresenti in oltre 30 citt\u00e0 in 21 paesi, i nostri team uniscono competenze su strategia, tecnologia, creativit\u00e0 e operations per offrire esperienze personalizzate e soluzioni trasformative ai nostri clienti, grazie al supporto di dati e intelligenza artificiale. I Jakalers sono un gruppo eterogeneo di oltre 3.000 persone, animate da passione, ambizione e idee brillanti. Proprio questa combinazione unica di talenti \u00e8 il fattore distintivo che ha ispirato il nostro purpose: Together to get there.\nCreare un mondo migliore \u00e8 il nostro obiettivo ultimo: la nostra ambizione \u00e8 generare valore per tutti i nostri stakeholder in modo sostenibile, con particolare attenzione a etica, clima e qualit\u00e0. Nel 2021, abbiamo scelto di diventare una Societ\u00e0 Benefit, dimostrando il nostro impegno di lungo periodo e la volont\u00e0 di proteggere i principi e i valori che ogni giorno guidano le nostre azioni.\nCrediamo che la diversit\u00e0 sia la chiave del nostro successo e, per questo, siamo impegnati a creare un ambiente di lavoro inclusivo, dove ciascuno possa sentirsi valorizzato per la propria unicit\u00e0. Tutte le nostre opportunit\u00e0 di lavoro sono aperte ai candidati appartenenti alle categorie protette L.68/99.\nScopri il team Solution Design\nSei pronto/a a mettere la tua passione per il tech al servizio di progetti innovativi? Questa \u00e8 l\u2019occasione perfetta per iniziare il tuo percorso professionale in un team strategico orientato alla progettazione di soluzioni digitali per aziende globali.\nNel team Solution Design trasformiamo i brief dei clienti in architetture tecnologiche avanzate, integrando piattaforme enterprise e collaborando con diverse funzioni. Lavoriamo su 7 industry e 22 mercati, progettando soluzioni su misura che generano valore reale e misurabile.\n\ud83c\udfaf\nOgni giorno sar\u00e0 diverso, ma eccoti un assaggio di quello che ti aspetta\nCollaborazione con team multidisciplinari nella creazione di presentazioni ad alto impatto per progetti innovativi\nCura e valorizzazione della parte grafica delle presentazioni, aumentando l\u2019efficacia visiva di proposte strategiche e complesse\nSupporto ai progetti DX, Commerce e Mobile nella creazione di concept, mockup e wireframe preliminari\nProduzione di materiali a supporto del presales e della condivisione interna: infografiche, pitch deck, presentazioni sintetiche su topic specifici\nContributo al miglioramento continuo del visual design del team, portando creativit\u00e0, attenzione ai dettagli e competenze in trend UX/UI\n\ud83d\udca1\nQueste caratteristiche sono un ottimo punto di partenza per crescere insieme\nDiploma o Laurea in Design, Grafica o discipline affini\nForte sensibilit\u00e0 estetica e passione per grafica, tipografia e trend UX/UI\nOttime capacit\u00e0 di comunicazione visiva e progettazione di presentazioni efficaci (presentation design)\nConoscenza di Excel e PowerPoint, con attenzione ai layout e alla struttura narrativa\nConoscenza dei principali strumenti grafici (es. Adobe, Figma)\nAttitudine alla collaborazione, desiderio di imparare e curiosit\u00e0 verso i progetti digitali e le tecnologie\n\ud83d\udcac\nCosa dicono di noi?\nEcco i fattori chiave che spingono colleghe e colleghi a sceglierci ogni giorno:\nFlessibilit\u00e0 e smart working:\nin JAKALA crediamo nel work-life balance. Per questo, abbiamo deciso di incoraggiare la presenza in ufficio per 10 giorni al mese, da scegliere autonomamente in base alle tue esigenze.\nTotal Reward\ncreato per te (e per chi ami):\nin JAKALA offriamo un Total Reward personalizzato, ricco di iniziative pensate per migliorare la qualit\u00e0 della vita dentro e fuori dall\u2019ufficio, non solo per te ma anche per le persone che ti stanno a cuore.\u00a0Tra i benefit troverai accesso gratuito a servizi di telemedicina e supporto psicologico, perch\u00e9 prendersi cura di s\u00e9 \u00e8 fondamentale. E poi ancora sconti su viaggi, ristoranti, shopping, palestra e tante altre esperienze per vivere al meglio il tuo tempo libero.\nCrescita e formazione continua:\nlavorerai a fianco di team esperti che ti guideranno e ti aiuteranno a sviluppare nuove competenze e a crescere professionalmente. Ogni giorno avrai la possibilit\u00e0 di apprendere, ricevere feedback costruttivi e applicare le tue idee in un ambiente stimolante.\n\ud83d\udc9c\nIl nostro impegno verso di te inizia ora\nSe investi tempo nel nostro percorso di Recruiting, avrai tutto il nostro impegno. E oltre.\nLa tua candidatura verr\u00e0 presa in carico da un Recruiter del nostro Team Talent Acquisition, che esaminer\u00e0 il tuo CV e le informazioni fornite. Sar\u00e0 poi il tuo Recruiter di riferimento a ricontattarti per condividere il nostro feedback, indipendentemente dall\u2019esito. Riceverai sempre suggerimenti per ottimizzare il tuo CV, spunti per consolidare il tuo percorso di carriera e insight sull\u2019arena competitiva in cui operi.\nNiente AI\n: lo facciamo a mano, con il cuore, per te.\nOgni ora che investirai per conoscere\nJAKALA\n, te la restituiamo per conoscerti meglio: grazie all\u2019iniziativa\nYour Time Back\ne alla nostra partnership con\nUnobravo\n, hai diritto a un percorso di empowerment con sessioni equivalenti al numero di interviste sostenute. Potrai spenderle come meglio credi. Sappiamo che cercare lavoro pu\u00f2 essere sfidante, e siamo qui per supportarti, anche se ancora non ci conosciamo.\n\ud83c\udf31\nReady to start?\nIl ruolo \u00e8 solo il punto di partenza. Il resto lo metti tu. Inviaci il tuo CV, noi non vediamo l\u2019ora di conoscerti!\nBack\nApply\nShare this job:\nFacebook\nLinkedIn\nEmail",
        "application_url": "https://careers.jakala.com/en_US/careers/ApplicationMethods?jobId=2238",
        "": {},
        "metadata": {
            "Office": "Roncade",
            "Country": "Italy",
            "Date Published": "10-Dec-2025",
            "Ref #": "2206",
            "Area": "IT and Information Systems",
            "Type of Presence": "Hybrid"
        },
        "link": "https://careers.jakala.com/en_US/careers/JobDetail/Intern-Graphic-Designer/2238"
    },
    {
        "title": "Business Development Manager (all genders) Shopify \u00d6kosystem",
        "description_html": null,
        "description_text": "General information\nOffice\nHamburg\nCountry\nGermany\nDate Published\n10-Dec-2025\nRef #\n2207\nArea\nSales\nType of Presence\nHybrid\nDescription & Requirements\nWir suchen einen strategischen Berater, der technische Anforderungen in kommerzielle L\u00f6sungen \u00fcbersetzt. Deine Hauptaufgabe ist die Akquise und Beratung von H\u00e4ndlern (Merchants) f\u00fcr Agenturleistungen / SaaS-L\u00f6sungen im Shopify-Umfeld. Die Rolle entwickelt f\u00fcr JAKALA Germany den DACH-Markt und arbeitet dabei eng mit dem eCommerce\nDelivery\nCenter von JAKALA in Italien\nsowie dem\nSoftware-Anbieter\nzusammen.\nResponsibilities\nConsultative\nSelling\n: Analyse der technischen und kaufm\u00e4nnischen Anforderungen potenzieller Kunden (B2B/B2C) und Ableitung passgenauerweiterer JAKALAL\u00f6sungen (z.B. Migration zu Shopify Plus,\nHeadless\n-Architekturen oder App-Integrationen).\nPipeline Management\n: End-\nto\n-End Verantwortung von der Qualifizierung (Inbound/Outbound) \u00fcber die Demo bis zum Vertragsabschluss (Closing)sowie \u00dcbergabe an das\nDelivery\n-Team\n.\n\u00d6kosystem-Networking\n: Aktive Pflege von Beziehungen zu Shopify-Partnermanagern und Tech-Partnern (z.B.\nKlaviyo\n,\nYotpo\n), um Empfehlungsgesch\u00e4ft zu generieren.\nMarktbeobachtung\n: Identifikation von Trends im D2C-Markt (\nDirect\n-\nto\n-Consumer) zur Anpassung der Pitch-Decks und Argumentationslinien.\n\u00dcber den Tellerrand hinausdenken:\nDu kennst das gesamte Leistungsportfolio von\nJakala\nGermany und bist in der Lage eCommerce-L\u00f6sungen mit weiteren Leistungen im Technologiebereich zu verkn\u00fcpfen.\nOverview\nJAKALA ist ein weltweit t\u00e4tiges IT- und Consulting-Unternehmen im Bereich\nMartech\n, mit einem starken Fokus auf Daten und KI. Von den weltweit \u00fcber 3.300 Mitarbeitenden sind rund\n230 in Hamburg und Berlin t\u00e4tig. Bei JAKALA Germany liegt der Schwerpunkt auf der Entwicklung von individuellen Software-L\u00f6sungen, haupts\u00e4chlich von sogenannten Digital Experience\nPlatforms\n(DXP), in denen Gesch\u00e4ftsprozesse entlang der Customer Journey digitalisiert werden\n.\nAn der Schnittstelle von Strategie, Design und Technologie entwickelt JAKALA digitale Plattformen, Apps und andere Services, welche die digitalen Erlebnisse gro\u00dfer Mark\nen ma\u00dfgeblich pr\u00e4gen. Zu den Kunden in Deutschland z\u00e4hlen beispielsweise TUI Cruises, Leica, die Hamburger Hochbahn oder das ZDF.\nQualifications\nVertriebserfahrung:\nNachweisbare Erfolge im B2C & B2B-Vertrieb\nim Bereich E-Commerce, SaaS oder Digitalagenturen. Erfahrung mit Methoden wie MEDDIC oder SPIN\nSelling\nist ein Plus.\nPlattform-Wissen:\nFundiertes Verst\u00e4ndnis von Shopify (Unterschiede Core vs. Plus, API-M\u00f6glichkeiten, Liquid-Grundkenntnisse) ist essenziell, um auf Augenh\u00f6he mit E-Commerce Managern zu sprechenund entsprechende L\u00fccken in der Wertsch\u00f6pfungskette zu identifizieren.\nAnalytische F\u00e4higkeiten:\nDu kannst Unit Economics (CAC, CLV, AOV) eines H\u00e4ndlers interpretieren und nutzen, um den ROI unserer Dienstleistung zu berechnen.\nSprache:\nVerhandlungssicheres Deutsch (C-Level Kommunikation) und Englisch.\nTech-Stack:\nSicherer Umgang mit Salesforce und Sales-\nIntelligence\n-Tools\nOffer\nDas bieten wir dir:\nJob in Vollzeit\n(mindestens 36 h/Woche)\nHybrides Arbeitsmodell (Remote und B\u00fcro in Hamburg) mit flexiblen Arbeitszeiten\nOffene und teamorientierte Unternehmenskultur\nWertsch\u00e4tzung deiner Ideen\nZuschuss f\u00fcr \u00d6PNVund\nBikeleasing\n-Option\nZuschuss f\u00fcr deine Urban Sportclub Membership\nW\u00f6chentliches gemeinsames Fr\u00fchst\u00fcckoder Mittagessen\nWenn du willst: Einstieg in unsere Hamburger Band (\nSchlagzeuger:in\ngesucht)\nWhat\nelse\n?\nWir wollen einen positiven Impact auf unsere Erde haben. Deshalb streben wir danach, auf nachhaltige Weise Wert f\u00fcr alle Interessengruppen zu schaffen und ber\u00fccksichtigen dabei Klima, Ethik und Qualit\u00e4t. 2021 haben wir uns entschieden, eine Benefit Corporation zu werden, um unser langfristiges Engagement f\u00fcr den Schutz der Prinzipien und Werte, die unser Handeln leiten, zu unterstreichen.\nBewirb dich noch heute. Wir freuen uns darauf, dich kennenzulernen.\nBack\nApply\nShare this job:\nFacebook\nLinkedIn\nEmail",
        "application_url": "https://careers.jakala.com/en_US/careers/ApplicationMethods?jobId=2239",
        "": {},
        "metadata": {
            "Office": "Hamburg",
            "Country": "Germany",
            "Date Published": "10-Dec-2025",
            "Ref #": "2207",
            "Area": "Sales",
            "Type of Presence": "Hybrid"
        },
        "link": "https://careers.jakala.com/en_US/careers/JobDetail/Business-Development-Manager-all-genders-Shopify-kosystem/2239"
    },
    {
        "title": "Experienced Professional | Engagement Contents",
        "description_html": null,
        "description_text": "General information\nOffice\nMilano\nCountry\nItaly\nDate Published\n09-Dec-2025\nRef #\n2200\nArea\nReward Marketing\nType of Presence\nHybrid\nDescription & Requirements\n\ud83d\udccd\nSede\n: Milano\n\ud83d\udc40 Rank: Consultant\nChi siamo\nJAKALA \u00e8 un'azienda che lavora su dati, intelligenza artificiale e sviluppo di esperienze per generare un impatto significativo e duraturo a livello globale.\nPresenti in oltre 30 citt\u00e0 in 21 paesi, i nostri team uniscono competenze su strategia, tecnologia, creativit\u00e0 e operations per offrire esperienze personalizzate e soluzioni trasformative ai nostri clienti, grazie al supporto di dati e intelligenza artificiale. I Jakalers sono un gruppo eterogeneo di oltre 3.000 persone, animate da passione, ambizione e idee brillanti. Proprio questa combinazione unica di talenti \u00e8 il fattore distintivo che ha ispirato il nostro purpose: Together to get there.\nCreare un mondo migliore \u00e8 il nostro obiettivo ultimo: la nostra ambizione \u00e8 generare valore per tutti i nostri stakeholder in modo sostenibile, con particolare attenzione a etica, clima e qualit\u00e0. Nel 2021, abbiamo scelto di diventare una Societ\u00e0 Benefit, dimostrando il nostro impegno di lungo periodo e la volont\u00e0 di proteggere i principi e i valori che ogni giorno guidano le nostre azioni.\nCrediamo che la diversit\u00e0 sia la chiave del nostro successo e, per questo, siamo impegnati a creare un ambiente di lavoro inclusivo, dove ciascuno possa sentirsi valorizzato per la propria unicit\u00e0. Tutte le nostre opportunit\u00e0 di lavoro sono aperte ai candidati appartenenti alle categorie protette L.68/99.\nScopri il team Engagement Contents\nPer il nostro team Engagement Contents siamo alla ricerca di una persona curiosa, proattiva e con una forte passione per il marketing e la user experience. Se ti entusiasma lavorare su progetti innovativi, contribuire alla creazione di contenuti ingaggianti e partecipare attivamente alla gestione operativa dei processi, questa potrebbe essere l\u2019opportunit\u00e0 giusta per te. Avrai l\u2019occasione di collaborare con team multidisciplinari e interfunzionali, sviluppando soluzioni che valorizzano l\u2019esperienza del cliente all\u2019interno di un contesto dinamico e in continua evoluzione.\n\ud83c\udfaf Le tue responsabilit\u00e0:\nSupportare l\u2019analisi dei brief e contribuire alla definizione di soluzioni contenutistiche efficaci in base alle esigenze del cliente\nCollaborare alla raccolta di materiali, immagini e insight sulla UX, con focus su asset di comunicazione e creazione di preview\nGestire il processo di pubblicazione dei contenuti: mockup per fornitori/clienti, approvazione materiali e test end-to-end dell\u2019esperienza utente\nCurare la codifica degli item, la creazione dei codici catalogo e il settaggio dei cataloghi digitali\nInterfacciarti con team interni e stakeholder (es. Acquisti, Delivery, Logistica) per garantire l\u2019allineamento operativo dei progetti\n\ud83d\ude4c\nSe ti riconosci in queste caratteristiche, potremmo essere il perfetto match:\n2- 4 anni di esperienza nella gestione di contenuti o settori affini a marketing/reward\nLaurea in Marketing, International Management, Economia o discipline affini\nCapacit\u00e0 di elaborare testi chiari e sintetici finalizzati alla descrizione delle caratteristiche distintive di prodotti e servizi\nOttima padronanza della lingua italiana e inglese\nBuone capacit\u00e0 comunicative, attitudine al lavoro in team e proattivit\u00e0\nBuone doti organizzative e di gestione delle priorit\u00e0\n\ud83d\udc9c\nScopri in questo video le ragioni per cui scegliere JAKALA come prossimo step di carriera\nIn JAKALA crediamo che il tempo e il benessere delle persone vadano rispettati, sempre: incoraggiamo una presenza in ufficio di\n10\ngiorni al mese, lasciando piena libert\u00e0 di lavorare da dove preferisci, sia in Italia che all\u2019interno della Comunit\u00e0 Europea.\nIl nostro sistema di Total\nReward\ninclude convenzioni esclusive per viaggi, ristoranti, shopping, palestra e tempo libero, oltre a servizi gratuiti di telemedicina e supporto psicologico, pensati per te e per chi ami.\nInvestire nel nostro processo di selezione significa ricevere supporto autentico: un Recruiter dedicato ti accompagner\u00e0 con feedback personalizzati, consigli di carriera e insight sul tuo CV, a prescindere dall\u2019esito della candidatura. Niente AI, solo persone. E, grazie all\u2019iniziativa Your Time Back, ti restituiamo il tempo investito nei colloqui con un percorso di empowerment firmato\nUnobravo\n.\n\ud83c\udf31 Ready to start?\nNon \u00e8 solo una candidatura. \u00c8 un percorso che comincia ora. Inviaci il tuo CV: non vediamo l\u2019ora di conoscerti!\nBack\nApply\nShare this job:\nFacebook\nLinkedIn\nEmail",
        "application_url": "https://careers.jakala.com/en_US/careers/ApplicationMethods?jobId=2232",
        "": {},
        "metadata": {
            "Office": "Milano",
            "Country": "Italy",
            "Date Published": "09-Dec-2025",
            "Ref #": "2200",
            "Area": "Reward Marketing",
            "Type of Presence": "Hybrid"
        },
        "link": "https://careers.jakala.com/en_US/careers/JobDetail/Experienced-Professional-Engagement-Contents/2232"
    },
    {
        "title": "Experienced Professional | Salesforce Tech Lead",
        "description_html": null,
        "description_text": "General information\nOffice\nBari, Milano, Napoli, Roma\nCountry\nItaly\nDate Published\n09-Dec-2025\nRef #\n2201\nArea\nIT and Information Systems\nType of Presence\nHybrid\nDescription & Requirements\n\ud83d\udccd\nSede\n: Milano, Napoli, Roma, Bari\n\ud83d\udc40\nRank:\nEpert\nLead\nChi siamo\nJAKALA \u00e8 un'azienda che lavora su dati, intelligenza artificiale e sviluppo di esperienze per generare un impatto significativo e duraturo a livello globale.\nPresenti in oltre 30 citt\u00e0 in 21 paesi,\ni nostri team\nuniscono competenze su strategia, tecnologia, creativit\u00e0 e\noperations\nper offrire esperienze personalizzate e soluzioni trasformative ai nostri clienti, grazie al supporto di dati e intelligenza artificiale. I\nJakalers\nsono un gruppo eterogeneo di oltre 3.000 persone, animate da passione, ambizione e idee brillanti. Proprio questa combinazione unica di talenti \u00e8 il fattore distintivo che ha ispirato il nostro\npurpose\n:\nTogether\nto\nget\nthere\n.\nCreare un mondo migliore \u00e8 il nostro obiettivo ultimo: la nostra ambizione \u00e8 generare valore per tutti i nostri stakeholder in modo sostenibile, con particolare attenzione a etica, clima e qualit\u00e0. Nel 2021, abbiamo scelto di diventare una Societ\u00e0 Benefit, dimostrando il nostro impegno di lungo periodo e la volont\u00e0 di proteggere i principi e i valori che ogni giorno guidano le nostre azioni.\nCrediamo che la diversit\u00e0 sia la chiave del nostro successo e, per questo, siamo impegnati a creare un ambiente di lavoro inclusivo, dove ciascuno possa sentirsi valorizzato per la propria unicit\u00e0. Tutte le nostre opportunit\u00e0 di lavoro sono aperte ai candidati appartenenti alle categorie protette L.68/99.\nScopri\nil team\nCX Solutions\nIl team\nCX Solutions di JAKALA si occupa principalmente della progettazione, implementazione, sviluppo e integrazione di soluzioni tecnologiche in ambito customer\nexperience\n.\nIl team\n\u00e8 formato da oltre\n100\nprofessionisti coinvolti su progettualit\u00e0 tech che coinvolgono diverse tecnologie come ad esempio Salesforce, Adobe, Dynamics e tante altre.\n\ud83c\udfaf Le tue responsabilit\u00e0:\nProgettare architetture e soluzioni tecniche per requisiti business complessi\nDefinire standard di sviluppo, best practice e linee guida per\nil team\nSupervisionare lo sviluppo di componenti personalizzati (\nApex\n, LWC, Flow)\nGarantire la qualit\u00e0 del codice attraverso code review e\npair\nprogramming\nGestire aspetti tecnici complessi come integrazioni, performance\noptimization\ne scalabilit\u00e0\nProdurre documentazione tecnica (design\ndocument\n, API\ndocumentation\n,\nsolution\nblueprint\n)\nGuidare\nil team\nSalesforce garantendo traduzione dei requisiti business in soluzioni tecniche, stima degli\neffort\ne comunicazione efficace con gli stakeholder\nCoordinare l\u2019esecuzione dei progetti assicurando avanzamento, gestione dei rischi, rispetto di scadenze e qualit\u00e0, con reporting trasparente a management e stakeholder\n\ud83d\ude4c Se\nti riconosci\nin queste caratteristiche, potremmo essere il perfetto match:\n3-5 anni di esperienza nello sviluppo su piattaforma Salesforce, uniti a una comprovata capacit\u00e0 di guida tecnica e coordinamento di\nteam\ndi sviluppo.\nPadronanza avanzata di\nApex\nCode per lo sviluppo di logiche business complesse\nEsperienza consolidata nello sviluppo di Lightning Web Components (LWC)\nCompetenza nella creazione e gestione di Flow (Screen Flow, Record-\nTriggered\nFlow,\nAutolaunched\nFlow)\nSviluppo di Batch\nApex\ne gestione di processi asincroni\nProfonda comprensione e gestione dei\nGovernor\nLimits di Salesforce\nEsperienza nella progettazione e implementazione di integrazioni con sistemi esterni (REST/SOAP\nAPIs\n)\nConoscenza approfondita dei Design Pattern di sviluppo (Trigger Framework, Service Layer, Domain Layer, etc.)\nCapacit\u00e0 di progettare architetture e soluzioni tecniche scalabili\nOttima conoscenza della lingua inglese: livello B2/C1 (scritto e parlato)\nCompetenze relazionali e di leadership: comunicazione efficace, mentoring di sviluppatori junior e guida tecnica\ndel team\nGestione operativa e metodologica: pianificazione, organizzazione e suddivisione dei progetti in task, con esperienza Agile e capacit\u00e0 di design e documentazione tecnica\nCompetenze tecniche Salesforce e\nDevOps\n: certificazioni avanzate, conoscenza di Salesforce DX, CI/CD e pratiche di sviluppo\nGestione e qualit\u00e0 del processo: utilizzo di strumenti di project management, esperienza in backlog e sprint planning, code review e\nassessment\ntecnici\n\ud83d\udc9c\nScopri nel video le ragioni per cui scegliere JAKALA come prossimo step di carriera\n:\nIn JAKALA crediamo che il tempo e il benessere delle persone vadano rispettati, sempre: incoraggiamo una presenza in ufficio di\n10\ngiorni al mese, lasciando piena libert\u00e0 di lavorare da dove preferisci, sia in Italia che all\u2019interno della Comunit\u00e0 Europea.\nIl nostro sistema di Total\nReward\ninclude convenzioni esclusive per viaggi, ristoranti, shopping, palestra e tempo libero, oltre a servizi gratuiti di telemedicina e supporto psicologico, pensati per te e per chi ami.\nInvestire nel nostro processo di selezione significa ricevere supporto autentico: un Recruiter dedicato ti accompagner\u00e0 con feedback personalizzati, consigli di carriera e insight sul tuo CV, a prescindere dall\u2019esito della candidatura. Niente AI, solo persone. E, grazie all\u2019iniziativa Your Time Back, ti restituiamo il tempo investito nei colloqui con un percorso di empowerment firmato\nUnobravo\n.\n\ud83c\udf31 Ready to start?\nNon \u00e8 solo una candidatura. \u00c8 un percorso che comincia ora. Inviaci il tuo CV: non vediamo l\u2019ora di conoscerti!\nBack\nApply\nShare this job:\nFacebook\nLinkedIn\nEmail",
        "application_url": "https://careers.jakala.com/en_US/careers/ApplicationMethods?jobId=2233",
        "": {},
        "metadata": {
            "Office": "Bari, Milano, Napoli, Roma",
            "Country": "Italy",
            "Date Published": "09-Dec-2025",
            "Ref #": "2201",
            "Area": "IT and Information Systems",
            "Type of Presence": "Hybrid"
        },
        "link": "https://careers.jakala.com/en_US/careers/JobDetail/Experienced-Professional-Salesforce-Tech-Lead/2233"
    },
    {
        "title": "Experienced Professional |  Salesforce Service Cloud Developer",
        "description_html": null,
        "description_text": "General information\nOffice\nBari, Milano, Napoli, Roma\nCountry\nItaly\nDate Published\n09-Dec-2025\nRef #\n2202\nArea\nIT and Information Systems\nType of Presence\nHybrid\nDescription & Requirements\n\ud83d\udccd\nSede\n: Milano, Napoli, Roma, Bari\n\ud83d\udc40\nRank\n: Associate\nChi siamo\nJAKALA \u00e8 un'azienda che lavora su dati, intelligenza artificiale e sviluppo di esperienze per generare un impatto significativo e duraturo a livello globale.\nPresenti in oltre 30 citt\u00e0 in 21 paesi,\ni nostri team\nuniscono competenze su strategia, tecnologia, creativit\u00e0 e\noperations\nper offrire esperienze personalizzate e soluzioni trasformative ai nostri clienti, grazie al supporto di dati e intelligenza artificiale. I\nJakalers\nsono un gruppo eterogeneo di oltre 3.000 persone, animate da passione, ambizione e idee brillanti. Proprio questa combinazione unica di talenti \u00e8 il fattore distintivo che ha ispirato il nostro\npurpose\n:\nTogether\nto\nget\nthere\n.\nCreare un mondo migliore \u00e8 il nostro obiettivo ultimo: la nostra ambizione \u00e8 generare valore per tutti i nostri stakeholder in modo sostenibile, con particolare attenzione a etica, clima e qualit\u00e0. Nel 2021, abbiamo scelto di diventare una Societ\u00e0 Benefit, dimostrando il nostro impegno di lungo periodo e la volont\u00e0 di proteggere i principi e i valori che ogni giorno guidano le nostre azioni.\nCrediamo che la diversit\u00e0 sia la chiave del nostro successo e, per questo, siamo impegnati a creare un ambiente di lavoro inclusivo, dove ciascuno possa sentirsi valorizzato per la propria unicit\u00e0. Tutte le nostre opportunit\u00e0 di lavoro sono aperte ai candidati appartenenti alle categorie protette L.68/99.\nScopri\nil team\nCX Solutions\nIl team\nCX Solutions di JAKALA si occupa principalmente della progettazione, implementazione, sviluppo e integrazione di soluzioni tecnologiche in ambito customer\nexperience\n.\nIl team\n\u00e8 formato da oltre\n100\nprofessionisti coinvolti su progettualit\u00e0 tech che coinvolgono diverse tecnologie come ad esempio Salesforce, Adobe, Dynamics e tante altre.\n\ud83c\udfaf Le tue responsabilit\u00e0:\nSviluppare e mantenere componenti personalizzati utilizzando\nApex\n, LWC e Flow\nProgettare e implementare processi batch per l'elaborazione di grandi volumi di dati\nCreare e gestire integrazioni con applicazioni esterne\nOttimizzare il codice rispettando i\nGovernor\nLimits della piattaforma\nCollaborare con\nil team\nper definire requisiti tecnici e soluzioni architetturali\nScrivere documentazione tecnica e garantire la qualit\u00e0 del codice attraverso testing appropriato\nPartecipare a code review e contribuire al miglioramento continuo delle best practice di sviluppo\n\ud83d\ude4c Se\nti riconosci\nin queste caratteristiche, potremmo essere il perfetto match:\n1\u20133 anni di esperienza nello sviluppo su piattaforma Salesforce\nConoscenza approfondita di\nApex\nCode per lo sviluppo di logiche business complesse\nEsperienza nello sviluppo di Lightning Web Components (LWC)\nCompetenza nella creazione e gestione di\nFlow (\nScreen Flow, Record-\nTriggered\nFlow,\nAutolaunched\nFlow), garantendo automazioni robuste e processi semplificati per il cliente\nSviluppo di Batch\nApex\nper l'elaborazione massiva di dati\nSolida comprensione e gestione dei\nGovernor\nLimits di Salesforce\nEsperienza nell'implementazione di integrazioni con sistemi esterni (REST/SOAP\nAPIs\n)\nConoscenza dei principali Design Pattern\u00a0di sviluppo (Trigger Framework, Service Layer, etc.)\nCertificazione Salesforce Platform Developer I\nEsperienza con\nGit\ne metodologie di Version Control, conoscenza di Salesforce DX e ambienti di sviluppo moderni, familiarit\u00e0 con strumenti di CI/CD per Salesforce\nEsperienza nella scrittura di Test Class e ottimizzazione del Code Coverage\nBuona conoscenza della lingua inglese, livello B2 (scritto e parlato)\n\ud83d\udc9c\nScopri in questo video le ragioni per cui scegliere JAKALA come prossimo step di carriera\nIn JAKALA crediamo che il tempo e il benessere delle persone vadano rispettati, sempre: incoraggiamo una presenza in ufficio di\n10\ngiorni al mese, lasciando piena libert\u00e0 di lavorare da dove preferisci, sia in Italia che all\u2019interno della Comunit\u00e0 Europea.\nIl nostro sistema di Total\nReward\ninclude convenzioni esclusive per viaggi, ristoranti, shopping, palestra e tempo libero, oltre a servizi gratuiti di telemedicina e supporto psicologico, pensati per te e per chi ami.\nInvestire nel nostro processo di selezione significa ricevere supporto autentico: un Recruiter dedicato ti accompagner\u00e0 con feedback personalizzati, consigli di carriera e insight sul tuo CV, a prescindere dall\u2019esito della candidatura. Niente AI, solo persone. E, grazie all\u2019iniziativa Your Time Back, ti restituiamo il tempo investito nei colloqui con un percorso di empowerment firmato\nUnobravo\n.\n\ud83c\udf31 Ready to start?\nNon \u00e8 solo una candidatura. \u00c8 un percorso che comincia ora. Inviaci il tuo CV: non vediamo l\u2019ora di conoscerti!\nBack\nApply\nShare this job:\nFacebook\nLinkedIn\nEmail",
        "application_url": "https://careers.jakala.com/en_US/careers/ApplicationMethods?jobId=2234",
        "": {},
        "metadata": {
            "Office": "Bari, Milano, Napoli, Roma",
            "Country": "Italy",
            "Date Published": "09-Dec-2025",
            "Ref #": "2202",
            "Area": "IT and Information Systems",
            "Type of Presence": "Hybrid"
        },
        "link": "https://careers.jakala.com/en_US/careers/JobDetail/Experienced-Professional-Salesforce-Service-Cloud-Developer/2234"
    },
    {
        "title": "Experienced Professional | SEO Consultant",
        "description_html": null,
        "description_text": "General information\nOffice\nMilano\nCountry\nItaly\nDate Published\n09-Dec-2025\nRef #\n2203\nArea\nManagement Consulting\nType of Presence\nHybrid\nDescription & Requirements\n\ud83d\udccd\nLocation\n: Milano\n\ud83d\udc40\nRank:\nConsultant\nAbout us\nJAKALA is a data, AI, and experiences company that creates meaningful and lasting impact globally.\nAcross more than 30 cities in 21 countries, our people combine strategy, technology, creativity, and operations to deliver tailored experiences and transformative solutions with data and AI at the heart. Jakalers are a diverse and multifaceted group of more than 3,000 individuals with passion, ambition and bright ideas. This unique mix of talents has become the distinctive factor that inspired our purpose: Together to get there.\nAt JAKALA, creating a better world is our ultimate purpose; we aim at creating value for all stakeholders in a sustainable way with a focus on ethics, climate and quality. In 2021, we decided to become a Benefit Corporation, demonstrating our long-term commitment to protecting the principles and values that guide our actions.We believe that diversity is the key to our success and for this reason we are committed to create an inclusive workplace, where everyone can feel valued for their uniqueness.\nAll our job opportunities are open to candidates belonging to categorie protette L.68/99.\nDiscover the SEO team\nWe are looking for a versatile and enthusiastic SEO Consultant to join a fast-growing unit within one of Europe\u2019s top MarTech companies. The role involves working with leading Italian and international clients and being responsible for supporting SEO strategy execution, ensuring SEO compliance, and contributing to the successful migration and optimization of websites.\n\ud83c\udfaf\nYour responsibilities:\nSupport pre-launch and launch of new websites from an SEO-compliance point of view, collaborating with developers and creating efficient migration and redirect plans\nOptimize content, semantic tags, and metadata to better match user queries and improve website rankings\nMonitor site health, identify technical issues, and implement fixes\nConduct SEO audits and produce detailed analytical reports, including traffic analysis, organic performance, and optimization proposals\nAnalyze business requirements and translate them into actionable SEO solutions\nAssist in content and link-building initiatives to improve organic visibility\nContribute to the coordination of projects, building strong relationships with clients and planning workflows to deliver SEO activities efficiently\nStay up to date with SEO trends, ranking factors, and search engine updates\n\ud83d\ude4c\nIf you see yourself in these characteristics, we could be the perfect match:\n2-5 years of proven SEO experience, ideally on medium to high-complexity projects\nFluency in English, both written and spoken\nSome experience with Technical SEO for e-commerce and/or multi-country websites is a plus\nFamiliarity with SEO and analytics tools such as Google Analytics, Google Search Console, Screaming Frog, SEMrush, Ahrefs, or similar\nExperience supporting content optimization and link-building strategies\nGeneral understanding of ranking factors and search engine algorithms, with interest in staying updated on SEO trends\nExperience contributing to project coordination and interacting with clients or internal stakeholders\nStrong organizational and analytical skills, attention to detail, and a proactive mindset\n\ud83d\udc9c\nDiscover in this video why choosing JAKALA could be your next career move.\nAt JAKALA, we believe that people\u2019s time and well-being must always be respected: we encourage an office presence of 10 days per month, giving you the freedom to work from anywhere you prefer, either in Italy or elsewhere within the European Union.\nOur Total Reward system includes exclusive discounts for travel, restaurants, shopping, gyms, and leisure activities, as well as free telemedicine and psychological support services, designed for you and your loved ones.\nInvesting your time in our selection process means receiving genuine support: a dedicated Recruiter will guide you with personalized feedback, career advice, and insights on your CV\u2014regardless of the outcome of your application. No AI, just people. And thanks to the Your Time Back initiative, we give back the time you\u2019ve spent in interviews with an empowerment program by Unobravo.\n\ud83c\udf31\nReady to start?\nIt\u2019s not just an application \u2014 it\u2019s a journey that starts now.\u00a0Send us your CV: we can\u2019t wait to meet you!\nBack\nApply\nShare this job:\nFacebook\nLinkedIn\nEmail",
        "application_url": "https://careers.jakala.com/en_US/careers/ApplicationMethods?jobId=2235",
        "": {},
        "metadata": {
            "Office": "Milano",
            "Country": "Italy",
            "Date Published": "09-Dec-2025",
            "Ref #": "2203",
            "Area": "Management Consulting",
            "Type of Presence": "Hybrid"
        },
        "link": "https://careers.jakala.com/en_US/careers/JobDetail/Experienced-Professional-SEO-Consultant/2235"
    },
    {
        "title": "Experienced Professional | AWS Data Engineer",
        "description_html": null,
        "description_text": "General information\nOffice\nMilano, Napoli, Rende, Roma\nCountry\nItaly\nDate Published\n09-Dec-2025\nRef #\n2204\nArea\nIT and Information Systems\nType of Presence\nHybrid\nDescription & Requirements\n\ud83d\udccd\nSede\n: Milano, Rende, Roma, Napoli\n\ud83d\udc40\nRank\n: Associate\nChi siamo\nJAKALA \u00e8 un'azienda che lavora su dati, intelligenza artificiale e sviluppo di esperienze per generare un impatto significativo e duraturo a livello globale.\nPresenti in oltre 30 citt\u00e0 in 21 paesi,\ni nostri team\nuniscono competenze su strategia, tecnologia, creativit\u00e0 e\noperations\nper offrire esperienze personalizzate e soluzioni trasformative ai nostri clienti, grazie al supporto di dati e intelligenza artificiale. I\nJakalers\nsono un gruppo eterogeneo di oltre 3.000 persone, animate da passione, ambizione e idee brillanti. Proprio questa combinazione unica di talenti \u00e8 il fattore distintivo che ha ispirato il nostro\npurpose\n:\nTogether\nto\nget\nthere\n.\nCreare un mondo migliore \u00e8 il nostro obiettivo ultimo: la nostra ambizione \u00e8 generare valore per tutti i nostri stakeholder in modo sostenibile, con particolare attenzione a etica, clima e qualit\u00e0. Nel 2021, abbiamo scelto di diventare una Societ\u00e0 Benefit, dimostrando il nostro impegno di lungo periodo e la volont\u00e0 di proteggere i principi e i valori che ogni giorno guidano le nostre azioni.\nCrediamo che la diversit\u00e0 sia la chiave del nostro successo e, per questo, siamo impegnati a creare un ambiente di lavoro inclusivo, dove ciascuno possa sentirsi valorizzato per la propria unicit\u00e0. Tutte le nostre opportunit\u00e0 di lavoro sono aperte ai candidati appartenenti alle categorie protette L.68/99.\nScopri\nil team\nData Management & Architecture\nIl team\nData Management and Architecture di JAKALA si occupa prevalentemente della progettazione, implementazione e manutenzione di architetture dati scalabili, sicure e affidabili in ambienti cloud\nenterprise\n. La nostra squadra \u00e8 formata da Data\nEngineer\ne Data Architect che offrono quotidianamente il loro contributo e la loro expertise su progetti di trasformazione digitale lavorando con tecnologie cloud moderne, collaborando con\nteam\ndi data\nanalytics\ne business\n.\n\ud83c\udfaf Le tue responsabilit\u00e0:\nCreare soluzioni ETL innovative, performanti e facilmente scalabili.\nProgettare e mantenere pipeline di dati e flussi ETL, garantendo qualit\u00e0 e affidabilit\u00e0 dei processi.\nLavorare a stretto contatto con\nteam interni\n, trasformando requisiti complessi in architetture dati funzionali.\n\ud83d\ude4c Se\nti riconosci\nin queste caratteristiche, potremmo essere il perfetto match:\nLaurea in Informatica, Ingegneria Informatica o affini\n2-3 anni di esperienza come Data\nEngineer\ncon ecosistema AWS e strumenti correlati (\nGlue\n, Spark, S3, Redshift,\nAirflow\n)\nPadronanza dei processi ETL (\nExtract\n,\nTransform\n, Load) e delle tecniche di trasformazione dati per garantire qualit\u00e0 e performance.\nEsperienza con linguaggi come Python/Scala e SQL.\nConoscenza delle tecniche di modellazione dei dati.\nFamiliarit\u00e0 con tecnologie CI/CD come\nGitLab\n, GitHub e con strumenti di\nContinuous\nDeployment (CD), come ad esempio\nTerraform\n.\nEsperienza con database relazionali e non relazionali.\nOttime doti relazionali e comunicative\nOttima conoscenza della lingua italiana e inglese\n\ud83d\udc9c\nScopri nel video le ragioni per cui scegliere JAKALA come prossimo step di carriera\n:\nIn JAKALA crediamo che il tempo e il benessere delle persone vadano rispettati, sempre: incoraggiamo una presenza in ufficio di\n10\ngiorni al mese, lasciando piena libert\u00e0 di lavorare da dove preferisci, sia in Italia che all\u2019interno della Comunit\u00e0 Europea.\nIl nostro sistema di Total\nReward\ninclude convenzioni esclusive per viaggi, ristoranti, shopping, palestra e tempo libero, oltre a servizi gratuiti di telemedicina e supporto psicologico, pensati per te e per chi ami.\nInvestire nel nostro processo di selezione significa ricevere supporto autentico: un Recruiter dedicato ti accompagner\u00e0 con feedback personalizzati, consigli di carriera e insight sul tuo CV, a prescindere dall\u2019esito della candidatura. Niente AI, solo persone. E, grazie all\u2019iniziativa Your Time Back, ti restituiamo il tempo investito nei colloqui con un percorso di empowerment firmato\nUnobravo\n.\n\ud83c\udf31 Ready to start?\nNon \u00e8 solo una candidatura. \u00c8 un percorso che comincia ora. Inviaci il tuo CV: non vediamo l\u2019ora di conoscerti!\nBack\nApply\nShare this job:\nFacebook\nLinkedIn\nEmail",
        "application_url": "https://careers.jakala.com/en_US/careers/ApplicationMethods?jobId=2236",
        "": {},
        "metadata": {
            "Office": "Milano, Napoli, Rende, Roma",
            "Country": "Italy",
            "Date Published": "09-Dec-2025",
            "Ref #": "2204",
            "Area": "IT and Information Systems",
            "Type of Presence": "Hybrid"
        },
        "link": "https://careers.jakala.com/en_US/careers/JobDetail/Experienced-Professional-AWS-Data-Engineer/2236"
    },
    {
        "title": "Experienced Professional | Media Advertising",
        "description_html": null,
        "description_text": "General information\nOffice\nMilano\nCountry\nItaly\nDate Published\n05-Dec-2025\nRef #\n2197\nArea\nManagement Consulting\nType of Presence\nHybrid\nDescription & Requirements\n\ud83d\udccd\nSede\n:\nMilano\n\ud83d\udc40\nRank: Consultant\nChi siamo\nJAKALA \u00e8 un'azienda che lavora su dati, intelligenza artificiale e sviluppo di esperienze per generare un impatto significativo e duraturo a livello globale.\nPresenti in oltre 30 citt\u00e0 in 21 paesi, i nostri team uniscono competenze su strategia, tecnologia, creativit\u00e0 e\noperations\nper offrire esperienze personalizzate e soluzioni trasformative ai nostri clienti, grazie al supporto di dati e intelligenza artificiale. I\nJakalers\nsono un gruppo eterogeneo di oltre 3.000 persone, animate da passione, ambizione e idee brillanti. Proprio questa combinazione unica di talenti \u00e8 il fattore distintivo che ha ispirato il nostro\npurpose\n:\nTogether\nto\nget\nthere\n.\nCreare un mondo migliore \u00e8 il nostro obiettivo ultimo: la nostra ambizione \u00e8 generare valore per tutti i nostri stakeholder in modo sostenibile, con particolare attenzione a etica, clima e qualit\u00e0. Nel 2021, abbiamo scelto di diventare una Societ\u00e0 Benefit, dimostrando il nostro impegno di lungo periodo e la volont\u00e0 di proteggere i principi e i valori che ogni giorno guidano le nostre azioni.\nCrediamo che la diversit\u00e0 sia la chiave del nostro successo e, per questo, siamo impegnati a creare un ambiente di lavoro inclusivo, dove ciascuno possa sentirsi valorizzato per la propria unicit\u00e0. Tutte le nostre opportunit\u00e0 di lavoro sono aperte ai candidati appartenenti alle categorie protette L.68/99.\nScopri il team Media\nIl\nteam Media Italia \u00e8 un gruppo dinamico e multidisciplinare che si occupa di strategie di\nPaid Media omni-canale, con l\u2019obiettivo di massimizzare le performance delle campagne digitali attraverso un mix efficace di creativit\u00e0, dati e tecnologia. Operiamo su progetti di rilievo, gestendo direttamente i principali canali di advertising (Search, Social, Programmatic, ecc.) e curando sia la parte strategica sia quella operativa. Al centro del nostro lavoro c\u2019\u00e8 l\u2019analisi: interpretiamo i dati per ottimizzare le performance e trasformiamo i risultati in insight concreti da condividere con i clienti\n\ud83c\udfaf Le tue responsabilit\u00e0:\nSviluppo di strategie di Paid Media Omni-channel\nGestione operativa delle campagne sui principali canali digitali (Search, Social, Programmatic, ecc.)\nDefinizione e implementazione delle strategie media\nOttimizzazione delle performance attraverso l\u2019analisi dei dati\nInterpretazione e sintesi dei risultati per trasformarli in insight utili\nCondivisione e presentazione dei risultati ai clienti\nIntegrazione di creativit\u00e0, dati e tecnologia per massimizzare l\u2019efficacia delle campagne\n\ud83d\ude4c Se ti riconosci in queste caratteristiche, potremmo essere il perfetto match:\nEsperienza diretta di almeno 2 anni nella gestione di progetti di digital advertising\nIntraprendenza\ne capacit\u00e0 di decision making\nCapacit\u00e0 di produzione documenti ed esposizione / presentazione\nPensiero strategico\ne capacit\u00e0 di problem solving\nConoscenza e capacit\u00e0 di gestione dei principali canali utilizzabili all'interno di una strategia di acquisition online (SEA, Social, Display, Native, Affiliation)\nConoscenza delle principali piattaforme di Web Analytics\nOttima conoscenza degli applicativi MS Office e in particolare di Microsoft Excel e Power Point\nConoscenza evoluta di piattaforme di programmatic advertising (DSP, SSP, Ad Server)\nsar\u00e0 considerata un plus\nConoscenza evoluta di strumenti di tracking (Tag Manager) e CRO (Hotjar, Optimize etc.)\nsar\u00e0 considerata un plus\nBuona conoscenza di strumenti di sviluppo landing page (Unbounce, Instapage)\nsar\u00e0 considerata un plus\nConoscenza base di linguaggio HTML5\nsar\u00e0 considerata un plus\n\ud83d\udc9c\nScopri nel video le ragioni per cui scegliere JAKALA come prossimo step di carriera\nIn JAKALA crediamo che il tempo e il benessere delle persone vadano rispettati, sempre: incoraggiamo una presenza in ufficio di 10 giorni al mese, lasciando piena libert\u00e0 di lavorare da dove preferisci, sia in Italia che all\u2019interno della Comunit\u00e0 Europea.\nIl nostro sistema di Total Reward include convenzioni esclusive per viaggi, ristoranti, shopping, palestra e tempo libero, oltre a servizi gratuiti di telemedicina e supporto psicologico, pensati per te e per chi ami.\nInvestire nel nostro processo di selezione significa ricevere supporto autentico: un Recruiter dedicato ti accompagner\u00e0 con feedback personalizzati, consigli di carriera e insight sul tuo CV, a prescindere dall\u2019esito della candidatura. Niente AI, solo persone. E, grazie all\u2019iniziativa Your Time Back, ti restituiamo il tempo investito nei colloqui con un percorso di empowerment firmato Unobravo.\n\ud83c\udf31 Ready to start?\nNon \u00e8 solo una candidatura. \u00c8 un percorso che comincia ora. Inviaci il tuo CV: non vediamo l\u2019ora di conoscerti!\nBack\nApply\nShare this job:\nFacebook\nLinkedIn\nEmail",
        "application_url": "https://careers.jakala.com/en_US/careers/ApplicationMethods?jobId=2229",
        "": {},
        "metadata": {
            "Office": "Milano",
            "Country": "Italy",
            "Date Published": "05-Dec-2025",
            "Ref #": "2197",
            "Area": "Management Consulting",
            "Type of Presence": "Hybrid"
        },
        "link": "https://careers.jakala.com/en_US/careers/JobDetail/Experienced-Professional-Media-Advertising/2229"
    },
    {
        "title": "Senior Account Manager (all genders)",
        "description_html": null,
        "description_text": "General information\nOffice\nHamburg\nCountry\nGermany\nDate Published\n02-Dec-2025\nRef #\n2191\nArea\nMarketing\nType of Presence\nHybrid\nDescription & Requirements\nDu hast mehrere Jahre Agenturerfahrung und liebst es, Marken \u00fcber alle Kan\u00e4le hinweg stark zu inszenieren \u2013 von klassischer ATL-Kommunikation \u00fcber BTL bis Digital,\nSocial\nund Online. In integrierten 360\u00b0-Kampagnen f\u00fchlst du dich zuhause, beh\u00e4ltst Budgets und KPIs ebenso im Blick wie Kreativqualit\u00e4t und Timing. Als zentrale Ansprechperson f\u00fcr deine\nKund:innen\nverantwortest du Strategie, Umsetzung und Steuerung des gesamten Kampagnenprozesses.\nZum n\u00e4chstm\u00f6glichen Zeitpunkt suchen wir einen motivierten und engagierten\nSenior Account Manager (all\ngenders\n)\nf\u00fcr unseren Standort Hamburg.\nResponsibilities\nDu bist\nzentrale:r\nAnsprechpartner:in\nf\u00fcr deine\nKund:innen\nund f\u00fchrst sie strategisch wie operativ durch integrierte 360\u00b0-Kampagnen (ATL, BTL, Digital,\nSocial\n, Online).\nDu verantwortest den gesamten Kampagnenprozess \u2013 von Briefing, Strategie und Kreation \u00fcber Produktion und Media-Abstimmung bis zu Roll-out und Optimierung.\nIn der markenstrategischen Kundenberatung treibst du zentrale Themen proaktiv voran, denkst entlang der Customer Journey und hast Ziele und KPIs klar im Blick.\nDu \u00fcbernimmst die Etat- und Budgetverantwortung: Planung, Controlling,\nForecasting\nsowie Monitoring der wirtschaftlichen Performance fallen in deinen Verantwortungsbereich.\nDu bist\nSparringspartner:in\nf\u00fcr dein Beratungsteam und unterst\u00fctzt bei ihrer Weiterentwicklung.\nDu orchestrierst interdisziplin\u00e4re Teams (z. B. Strategie, Kreation, Media, Tech) und sorgst daf\u00fcr, dass alle Gewerke reibungslos zusammenarbeiten.\nDu verantwortest das Schnittstellenmanagement zu externen Dienstleistern, Partneragenturen und Produktionsfirmen und stellst Qualit\u00e4t, Timing und Budgeteinhaltung sicher.\nOverview\nJAKALA ist ein weltweit t\u00e4tiges IT- und Consulting-Unternehmen im Bereich\nMartech\n, mit einem starken Fokus auf Daten und KI. Von den weltweit \u00fcber 3.300 Mitarbeitenden sind rund 230 in Hamburg und Berlin t\u00e4tig. Bei JAKALA Germany liegt der Schwerpunkt auf der Entwicklung von individuellen Software-L\u00f6sungen, haupts\u00e4chlich von sogenannten Digital Experience\nPlatforms\n(DXP), in denen Gesch\u00e4ftsprozesse entlang der Customer Journey digitalisiert werden. An der Schnittstelle von Strategie, Design und Technologie entwickelt JAKALA digitale Plattformen, Apps und andere Services, welche die digitalen Erlebnisse gro\u00dfer Marken ma\u00dfgeblich pr\u00e4gen. Zu den Kunden in Deutschland z\u00e4hlen beispielsweise TUI Cruises, Leica, die Hamburger Hochbahn oder das ZDF.\nQualifications\nDu hast mehrj\u00e4hrige Erfahrung in einer Beratungsposition, idealerweise auf Agenturseite, mit Verantwortung f\u00fcr integrierte 360\u00b0-Kommunikationsprojekte.\nDu bringst starke Expertise in der Entwicklung, Umsetzung und Produktionsprozessen von Kommunikationskonzepten \u00fcber alle Kan\u00e4le mit \u2013 ATL, BTL, Digital/Online,\nSocial\n\u2013 und hast ein gutes Gesp\u00fcr f\u00fcr starke Kreation und Markenf\u00fchrung.\nDu beherrschst Etat- und Projektcontrolling (Budgetplanung, Forecast, Wirtschaftlichkeitsbetrachtung) und verstehst es, Kennzahlen zu interpretieren und Ma\u00dfnahmen daraus abzuleiten.\nDu kennst dich mit komplexen Kampagnenprozessen aus und arbeitest strukturiert, l\u00f6sungsorientiert und vorausschauend.\nDu bist ein echter Teamplayer und hast idealerweise bereits Erfahrung in der F\u00fchrung und Weiterentwicklung eines Teams.\nSouver\u00e4ne Kundenkommunikation, Pr\u00e4sentationssicherheit und Verhandlungsgeschick zeichnen dich aus.\nDu motivierst das interne Team mit deiner positiven, klaren Art und guten Briefings.\nSprachkompetenz: Du beherrschst Deutsch sicher in Wort und Schrift und kommunizierst auch auf Englisch souver\u00e4n.\nEine schnelle Auffassungsgabe, hohe Zahlenaffinit\u00e4t und Freude an datengetriebener Optimierung runden dein Profil ab.\nOffer\nDas bieten wir dir:\nJob in Vollzeit oder Teilzeit - du entscheidest\nHybrides Arbeitsmodell (Remote und B\u00fcro) mit flexiblen Arbeitszeiten\nOffene und teamorientierte Unternehmenskultur\nWertsch\u00e4tzung deiner Ideen\nZuschuss f\u00fcr \u00d6PNV, Mobilit\u00e4tsbudget,\nBikeleasing\n-Option\nUrban Sports Club Membership\nW\u00f6chentliches gemeinsames Fr\u00fchst\u00fcck oder Mittagessen\nWenn du willst: Einstieg in unsere Hamburger Band (\nS\u00e4nger:in\ngesucht)\nWhat\nelse\n?\nWir wollen einen positiven Impact auf unsere Erde haben. Deshalb streben wir danach, auf nachhaltige Weise Wert f\u00fcr alle Interessengruppen zu schaffen und ber\u00fccksichtigen dabei Klima, Ethik und Qualit\u00e4t. 2021 haben wir uns entschieden, eine Benefit Corporation zu werden, um unser langfristiges Engagement f\u00fcr den Schutz der Prinzipien und Werte, die unser Handeln leiten, zu unterstreichen.\nBewirb dich noch heute. Wir freuen uns darauf, dich kennenzulernen.\nBack\nApply\nShare this job:\nFacebook\nLinkedIn\nEmail",
        "application_url": "https://careers.jakala.com/en_US/careers/ApplicationMethods?jobId=2223",
        "": {},
        "metadata": {
            "Office": "Hamburg",
            "Country": "Germany",
            "Date Published": "02-Dec-2025",
            "Ref #": "2191",
            "Area": "Marketing",
            "Type of Presence": "Hybrid"
        },
        "link": "https://careers.jakala.com/en_US/careers/JobDetail/Senior-Account-Manager-all-genders/2223"
    },
    {
        "title": "Senior iOS Developer (all genders)",
        "description_html": null,
        "description_text": "General information\nOffice\nHamburg\nCountry\nGermany\nDate Published\n28-Nov-2025\nRef #\n2186\nArea\nIT and Information Systems\nType of Presence\nHybrid\nDescription & Requirements\nDu entwickelst komplexe iOS-Apps und verstehst, wie man intuitive User Interfaces f\u00fcr mobile Anwendungen umsetzt? Du bist\nExpert:in\ndarin, Swift und moderne Frameworks einzusetzen, um leistungsstarke L\u00f6sungen f\u00fcr innovative Apps zu realisieren? Wenn du in einer dynamischen Umgebung die Mobilit\u00e4t in Hamburg und Deutschland vorantreiben m\u00f6chtest, bist du bei uns genau richtig.\nZum n\u00e4chstm\u00f6glichen Zeitpunkt suchen wir einen motivierten und engagierten Senior iOS Developer (all\ngenders\n) in Hamburg, hybrid.\nResponsibilities\nDu arbeitest in\ncross\n-funktionalen und agilen Entwicklungsteams mit, um gemeinsam innovative L\u00f6sungen zu schaffen\nDu setzt Produktanforderungen und Designs um, indem du hochqualitativen Swift Code schreibst, der die Mobilit\u00e4tsapp f\u00fcr Hamburg auf ein neues Level hebt\nDu bist verantwortlich f\u00fcr die Konzeptionierung und Realisierung von anspruchsvollen mobilen L\u00f6sungen, die\nNutzer:innen\nbegeistern\nDu genie\u00dft die Vielfalt deiner Aufgabenbereiche, die es dir erm\u00f6glichen, dich mit einer breiten Palette von Technologien auseinanderzusetzen und stetig weiterzuentwickeln\nDu entwickelst agil inhouse nach\nScrum\n. Das Produkt, an dem du arbeitest, verf\u00fcgt \u00fcber ein eigenes Backlog und einen eigenen\nProduct\nOwner\n, was dir eine klare Struktur und Fokussierung bietet\nDu profitierst von einem modernen Tech-Stack, den wir stets auf dem neuesten Stand halten, um innovative und effiziente L\u00f6sungen zu gew\u00e4hrleisten\nOverview\nJAKALA ist ein weltweit t\u00e4tiges IT- und Consulting-Unternehmen im Bereich\nMartech\n, mit einem starken Fokus auf Daten und KI. Von den weltweit \u00fcber 3.300 Mitarbeitenden sind rund 230 in Hamburg und Berlin t\u00e4tig. Bei JAKALA Germany liegt der Schwerpunkt auf der Entwicklung von individuellen Software-L\u00f6sungen, haupts\u00e4chlich von sogenannten Digital Experience\nPlatforms\n(DXP), in denen Gesch\u00e4ftsprozesse entlang der Customer Journey digitalisiert werden. An der Schnittstelle von Strategie, Design und Technologie entwickelt JAKALA digitale Plattformen, Apps und andere Services, welche die digitalen Erlebnisse gro\u00dfer Marken ma\u00dfgeblich pr\u00e4gen. Zu den Kunden in Deutschland z\u00e4hlen beispielsweise TUI Cruises, Leica, die Hamburger Hochbahn oder das ZDF.\nQualifications\nDu hast mehrj\u00e4hrige Erfahrung in der Entwicklung nativer iOS-Apps mit Swift und\nXcode\nDu kennst\nUIKit\n,\nSwiftUI\n, Architektur-Patterns (MVVM/MVC) sowie Swift Package Manager\nDu arbeitest sicher mit REST-APIs, JSON, Networking (gern auch\nWebSockets\n/MQTT)\nDu nutzt\nGit\nund CI/CD-Pipelines (z.\u202fB.\nXcode\nCloud, GitHub Actions) und hast Erfahrung mit\nDeployment\n(App Store,\nTestFlight\n)\nDu setzt Designs aus\nFigma\nanhand eines Designsystems um und achtest auf eine gute User Experience\nDu bringst Kenntnisse in\nTesting\n(\nXCTest\n,\nXCUITest\n), Performance-Optimierung, Security (\nKeychain\n, Secure\nEnclave\n), Datenschutz (DSGVO) und\nAccessibility\n(\nVoiceOver\n) mit\nDu verstehst Tracking-Frameworks (\nFirebase\n,\nAdjust\n, GTM) und interessierst dich f\u00fcr neue Apple-Technologien wie\nVisionOS\n,\nARKit\noder\nWidgetKit\nDu hast idealerweise Erfahrung mit Mobilit\u00e4tsl\u00f6sungen oder\nKotlin\nMultiplatform\nDu bist kommunikativ, arbeitest strukturiert und eigenverantwortlich und teilst dein Wissen gerne\nDu sprichst flie\u00dfend\u00a0Deutsch und gutes Englisch\nOffer\nDas bieten wir dir:\nJob in Vollzeit oder Teilzeit - du entscheidest\nHybrides Arbeitsmodell mit flexiblen Arbeitszeiten\nOffene und teamorientierte Unternehmenskultur\nWertsch\u00e4tzung deiner Ideen\nZuschuss f\u00fcr \u00d6PNV und\nBikeleasing\n-Option\nW\u00f6chentliches gemeinsames Fr\u00fchst\u00fcck oder Mittagessen\nWenn du willst: Einstieg in unsere Hamburger Band (\nSchlagzeuger:in\ngesucht)\nWhat\nelse\n?\nWir wollen einen positiven Impact auf unsere Erde haben. Deshalb streben wir danach, auf nachhaltige Weise Wert f\u00fcr alle Interessengruppen zu schaffen und ber\u00fccksichtigen dabei Klima, Ethik und Qualit\u00e4t. 2021 haben wir uns entschieden, eine Benefit Corporation zu werden, um unser langfristiges Engagement f\u00fcr den Schutz der Prinzipien und Werte, die unser Handeln leiten, zu unterstreichen.\nBewirb dich noch heute. Wir freuen uns darauf, dich kennenzulernen.\nBack\nApply\nShare this job:\nFacebook\nLinkedIn\nEmail",
        "application_url": "https://careers.jakala.com/en_US/careers/ApplicationMethods?jobId=2218",
        "": {},
        "metadata": {
            "Office": "Hamburg",
            "Country": "Germany",
            "Date Published": "28-Nov-2025",
            "Ref #": "2186",
            "Area": "IT and Information Systems",
            "Type of Presence": "Hybrid"
        },
        "link": "https://careers.jakala.com/en_US/careers/JobDetail/Senior-iOS-Developer-all-genders/2218"
    },
    {
        "title": "CRO Senior Consultant",
        "description_html": null,
        "description_text": "General information\nOffice\nMadrid\nCountry\nSpain\nDate Published\n24-Nov-2025\nRef #\n1958\nArea\nMarketing\nType of Presence\nHybrid\nDescription & Requirements\nEn Jakala buscamos un/a Digital CRO Specialist para liderar la optimizaci\u00f3n de experiencias digitales y maximizar la conversi\u00f3n en nuestros activos web y app. Ser\u00e1s responsable de idear, implementar y analizar experimentos y personalizaciones, colaborando con equipos multidisciplinares y gestionando herramientas avanzadas de CRO y orquestaci\u00f3n.\nResponsabilidades\nLiderar la ideaci\u00f3n, implementaci\u00f3n y an\u00e1lisis de experimentos y personalizaciones en activos digitales (web y app) para maximizar la conversi\u00f3n y mejorar la experiencia de usuario.\nIdentificar puntos fuertes y \u00e1reas de mejora utilizando herramientas de medici\u00f3n cuantitativa y cualitativa.\nDefinir y ejecutar estrategias de optimizaci\u00f3n alineadas con la estrategia de la compa\u00f1\u00eda.\nColaborar en la definici\u00f3n e implementaci\u00f3n de flujos y campa\u00f1as personalizadas para garantizar una experiencia omnicanal coherente y efectiva.\nAnalizar y visualizar datos para identificar oportunidades de mejora y generar insights accionables.\nAdministrar y optimizar herramientas relacionadas con CRO y orquestaci\u00f3n (experimentaci\u00f3n, personalizaci\u00f3n, CDPs, etc.).\nTrabajar de forma transversal con equipos de desarrollo, dise\u00f1o, marketing y datos para asegurar la alineaci\u00f3n estrat\u00e9gica en proyectos y campa\u00f1as.\nRequisitos (imprescindibles)\nExperiencia demostrable liderando proyectos de CRO (Conversion Rate Optimization) con clientes de diferentes sectores.\nConocimiento profundo de la metodolog\u00eda CRO.\nDominio de herramientas de anal\u00edtica web y testing, especialmente Adobe Analytics (imprescindible), Google Analytics, Optimizely, Firebase, Google Optimize, etc.\nExperiencia con herramientas de an\u00e1lisis cuantitativo y cualitativo (ContentSquare, Hotjar, Mouseflow, etc.).\nExperiencia con suites de experimentaci\u00f3n como Adobe Target (imprescindible), Dynamic Yield, AB Tasty, Convert, VWO, etc.\nBuen nivel de ingl\u00e9s hablado y escrito, capaz de trabajar en proyectos donde este sea el \u00fanico idioma de comunicaci\u00f3n.\nExcelentes habilidades de interlocuci\u00f3n con clientes de diferentes perfiles y necesidades.\nCapacidad de an\u00e1lisis y resoluci\u00f3n de problemas.\nRequisitos valorables (Nice to have)\nFormaci\u00f3n o conocimiento profundo en Behavioral Economics.\nNivel alto de ingl\u00e9s (B2 Upper o superior).\nQu\u00e9\u00a0ofrecemos\nModelo\u00a0de\u00a0asistencia\u00a0a\u00a0la\u00a0oficina\u00a0h\u00edbrido.\nSeguro\u00a0m\u00e9dico\u00a0privado.\nAcceso\u00a0a\u00a0Wellhub\u00a0para\u00a0bienestar\u00a0f\u00edsico\u00a0y\u00a0mental.\nRetribuci\u00f3n\u00a0flexible\u00a0(restauraci\u00f3n,\u00a0transporte,\u00a0guarder\u00eda,\u00a0etc.).\n28\u00a0d\u00edas\u00a0de\u00a0vacaciones\u00a0al\u00a0a\u00f1o.\nTres\u00a0semanas\u00a0al\u00a0a\u00f1o\u00a0de\u00a0full\u00a0remote.\nPlan\u00a0de\u00a0carrera\u00a0adaptado\u00a0a\u00a0tus\u00a0inquietudes\u00a0profesionales.\nAcceso\u00a0a\u00a0certificaciones\u00a0(Google,\u00a0Salesforce,\u00a0Adobe).\nProgramas\u00a0de\u00a0formaci\u00f3n\u00a0tecnol\u00f3gica\u00a0(Jxpert).\nLaboratorio\u00a0de\u00a0pruebas\u00a0de\u00a0soluciones\u00a0tecnol\u00f3gicas\u00a0(Jlab).\nFormaci\u00f3n en idiomas.\nDescripci\u00f3n de la empresa:\nSomos\u00a0un\u00a0ecosistema\u00a0dise\u00f1ado\u00a0para\u00a0que\u00a0el\u00a0talento\u00a0y\u00a0las\u00a0soluciones\u00a0innovadoras\u00a0se\u00a0unan\u00a0para\u00a0impulsar\u00a0el\u00a0valor\u00a0para\u00a0las\u00a0organizaciones,\u00a0las\u00a0personas\u00a0y\u00a0la\u00a0sociedad.\nHoy\u00a0en\u00a0d\u00eda,\u00a0somos\u00a0la\u00a0empresa\u00a0l\u00edder\u00a0en\u00a0Martech\u00a0en\u00a0Europa,\u00a0con\u00a0sede\u00a0en\u00a0Mil\u00e1n\u00a0y\u00a0oficinas\u00a0en\u00a0todo\u00a0el\u00a0mundo.\u00a0Nuestro\u00a0enfoque\u00a0impulsado\u00a0por\u00a0datos,\u00a0respaldado\u00a0por\u00a0una\u00a0f\u00f3rmula\u00a0ganadora\u00a0de\u00a0estrategia,\u00a0innovaci\u00f3n,\u00a0transformaci\u00f3n\u00a0tecnol\u00f3gica,\u00a0compromiso\u00a0y\u00a0activaci\u00f3n,\u00a0es\u00a0la\u00a0piedra\u00a0angular\u00a0de\u00a0nuestro\u00a0trabajo.\nCon\u00a0un\u00a0equipo\u00a0de\u00a03,000\u00a0empleados,\u00a0m\u00e1s\u00a0de\u00a0900\u00a0clientes\u00a0y\u00a0proyectos\u00a0en\u00a0m\u00e1s\u00a0de\u00a030\u00a0pa\u00edses,\u00a0y\u00a0una\u00a0facturaci\u00f3n\u00a0que\u00a0supera\u00a0los\u00a0500\u00a0millones\u00a0de\u00a0euros,\u00a0JAKALA\u00a0emerge\u00a0como\u00a0un\u00a0verdadero\u00a0punto\u00a0de\u00a0referencia\u00a0en\u00a0el\u00a0vasto\u00a0panorama\u00a0digital.\u00a0Gracias\u00a0a\u00a0la\u00a0contribuci\u00f3n\u00a0de\u00a0un\u00a0equipo\u00a0internacional\u00a0compuesto\u00a0por\u00a0talentos\u00a0vers\u00e1tiles\u00a0y\u00a0altamente\u00a0calificados,\u00a0la\u00a0empresa\u00a0ofrece\u00a0soluciones\u00a0\u00fanicas\u00a0y\u00a0personalizadas,\u00a0anticipando\u00a0los\u00a0desaf\u00edos\u00a0de\u00a0un\u00a0mercado\u00a0en\u00a0constante\u00a0evoluci\u00f3n.\u00a0Reconocida\u00a0como\nEmpresa Great Place to Work 2024\n, JAKALA persigue sus objetivos con la firme creencia de que el bienestar de los empleados y un impacto positivo en el medio ambiente son elementos esenciales para garantizar un crecimiento sostenible.\nBack\nApply\nShare this job:\nFacebook\nLinkedIn\nEmail",
        "application_url": "https://careers.jakala.com/en_US/careers/ApplicationMethods?jobId=1988",
        "": {},
        "metadata": {
            "Office": "Madrid",
            "Country": "Spain",
            "Date Published": "24-Nov-2025",
            "Ref #": "1958",
            "Area": "Marketing",
            "Type of Presence": "Hybrid"
        },
        "link": "https://careers.jakala.com/en_US/careers/JobDetail/CRO-Senior-Consultant/1988"
    },
    {
        "title": "SEM & Paid Social SR Consultant",
        "description_html": null,
        "description_text": "General information\nOffice\nMadrid\nCountry\nSpain\nDate Published\n20-Nov-2025\nRef #\n2165\nArea\nMarketing\nType of Presence\nHybrid\nDescription & Requirements\nEn\nJAKALA Iberia\nestamos buscando un perfil de\nSEM\u00a0&\u00a0Paid\u00a0Social\u00a0Senior\u00a0Consultant\nque participar\u00e1 en proyectos a nivel transversal centrados en el mundo del dato y la tecnolog\u00eda dentro del equipo de Media, en nuestras oficinas de Madrid.\nFunciones\nLiderar, definir y activar estrategia de Performance de clientes en entornos de SEM y Paid Social.\nCoordinar\u00a0perfiles\u00a0junior\u00a0en\u00a0la\u00a0ejecuci\u00f3n\u00a0y\u00a0seguimiento\u00a0de\u00a0campa\u00f1as.\nDise\u00f1ar\u00a0estrategias\u00a0de\u00a0publicidad\u00a0pagada\u00a0en\u00a0motores\u00a0de\u00a0b\u00fasqueda\u00a0(SEM)\u00a0y\u00a0redes\u00a0sociales\u00a0(Paid\u00a0Social)\u00a0alineadas\u00a0con\u00a0los\u00a0objetivos\u00a0del\u00a0cliente.\nCrear,\u00a0gestionar\u00a0y\u00a0optimizar\u00a0campa\u00f1as\u00a0en\u00a0plataformas\u00a0como\u00a0Google\u00a0Ads,\u00a0Bing\u00a0Ads,\u00a0Yandex,\u00a0Baidu,\u00a0Meta\u00a0Ads\u00a0(Facebook/Instagram),\u00a0entre\u00a0otras.\nRealizar\u00a0investigaci\u00f3n\u00a0de\u00a0palabras\u00a0clave\u00a0y\u00a0an\u00e1lisis\u00a0de\u00a0competencia\u00a0para\u00a0identificar\u00a0oportunidades\u00a0de\u00a0mejora.\nRedactar\u00a0y\u00a0optimizar\u00a0copys\u00a0publicitarios,\u00a0segmentar\u00a0audiencias\u00a0y\u00a0establecer\u00a0estrategias\u00a0de\u00a0pujas\u00a0orientadas\u00a0a\u00a0maximizar\u00a0el\u00a0ROI.\nRealizar\u00a0pruebas\u00a0A/B\u00a0y\u00a0experimentos\u00a0para\u00a0mejorar\u00a0continuamente\u00a0el\u00a0rendimiento\u00a0de\u00a0las\u00a0campa\u00f1as.\nAnalizar\u00a0m\u00e9tricas\u00a0clave\u00a0y\u00a0elaborar\u00a0informes\u00a0de\u00a0rendimiento,\u00a0aportando\u00a0recomendaciones\u00a0estrat\u00e9gicas\u00a0basadas\u00a0en\u00a0datos.\nColaborar\u00a0de\u00a0forma\u00a0transversal\u00a0con\u00a0los\u00a0equipos\u00a0creativos\u00a0y\u00a0de\u00a0marketing\u00a0para\u00a0asegurar\u00a0coherencia\u00a0en\u00a0el\u00a0mensaje\u00a0de\u00a0marca.\nMantenerse\u00a0al\u00a0d\u00eda\u00a0con\u00a0las\u00a0tendencias\u00a0y\u00a0mejores\u00a0pr\u00e1cticas\u00a0en\u00a0marketing\u00a0digital,\u00a0SEM,\u00a0Paid\u00a0Social\u00a0y\u00a0anal\u00edtica.\nRequisitos\nMUST:\nExperiencia\u00a0demostrable\u00a0en\u00a0la\u00a0gesti\u00f3n\u00a0operativa\u00a0de\u00a0campa\u00f1as\u00a0de\u00a0performance\u00a0en\u00a0Google\u00a0Ads\u00a0y\u00a0Meta\u00a0Ads.\nIngl\u00e9s\u00a0alto,\u00a0tanto\u00a0escrito\u00a0como\u00a0oral.\u00a0Interlocuci\u00f3n\u00a0con\u00a0cliente\u00a0en\u00a0ingl\u00e9s.\nExperiencia\u00a0en\u00a0entorno\u00a0GMP\u00a0(Google\u00a0Marketing\u00a0Platform):\u00a0Search\u00a0Ads\u00a0360,\u00a0Campaign\u00a0Manager\u00a0360\u00a0y\u00a0GA4.\nExcelentes\u00a0habilidades\u00a0anal\u00edticas\u00a0y\u00a0con\u00a0capacidad\u00a0para\u00a0interpretar\u00a0m\u00e9tricas\u00a0de\u00a0rendimiento\u00a0y\u00a0tomar\u00a0decisiones\u00a0basadas\u00a0en\u00a0datos.\nFuertes\u00a0habilidades\u00a0de\u00a0comunicaci\u00f3n\u00a0verbal\u00a0y\u00a0escrita.\nNICE TO HAVE:\nValorable\u00a0experiencia\u00a0en\u00a0clientes\u00a0de\u00a0Travel.\nExperiencia\u00a0en\u00a0agencia\u00a0digital\nQu\u00e9\u00a0ofrecemos\nModelo\u00a0de\u00a0asistencia\u00a0a\u00a0la\u00a0oficina\u00a0h\u00edbrido.\nSeguro\u00a0m\u00e9dico\u00a0privado.\nAcceso\u00a0a\u00a0Wellhub\u00a0para\u00a0bienestar\u00a0f\u00edsico\u00a0y\u00a0mental.\nRetribuci\u00f3n\u00a0flexible\u00a0(restauraci\u00f3n,\u00a0transporte,\u00a0guarder\u00eda,\u00a0etc.).\n28\u00a0d\u00edas\u00a0de\u00a0vacaciones\u00a0al\u00a0a\u00f1o.\nTres\u00a0semanas\u00a0al\u00a0a\u00f1o\u00a0de\u00a0full\u00a0remote.\nPlan\u00a0de\u00a0carrera\u00a0adaptado\u00a0a\u00a0tus\u00a0inquietudes\u00a0profesionales.\nAcceso\u00a0a\u00a0certificaciones\u00a0(Google,\u00a0Salesforce,\u00a0Adobe).\nProgramas\u00a0de\u00a0formaci\u00f3n\u00a0tecnol\u00f3gica\u00a0(Jxpert).\nLaboratorio\u00a0de\u00a0pruebas\u00a0de\u00a0soluciones\u00a0tecnol\u00f3gicas\u00a0(Jlab).\nFormaci\u00f3n\u00a0en\u00a0idiomas.\nDescripci\u00f3n de la empresa:\nSomos\u00a0un\u00a0ecosistema\u00a0dise\u00f1ado\u00a0para\u00a0que\u00a0el\u00a0talento\u00a0y\u00a0las\u00a0soluciones\u00a0innovadoras\u00a0se\u00a0unan\u00a0para\u00a0impulsar\u00a0el\u00a0valor\u00a0para\u00a0las\u00a0organizaciones,\u00a0las\u00a0personas\u00a0y\u00a0la\u00a0sociedad.\nHoy\u00a0en\u00a0d\u00eda,\u00a0somos\u00a0la\u00a0empresa\u00a0l\u00edder\u00a0en\u00a0Martech\u00a0en\u00a0Europa,\u00a0con\u00a0sede\u00a0en\u00a0Mil\u00e1n\u00a0y\u00a0oficinas\u00a0en\u00a0todo\u00a0el\u00a0mundo.\u00a0Nuestro\u00a0enfoque\u00a0impulsado\u00a0por\u00a0datos,\u00a0respaldado\u00a0por\u00a0una\u00a0f\u00f3rmula\u00a0ganadora\u00a0de\u00a0estrategia,\u00a0innovaci\u00f3n,\u00a0transformaci\u00f3n\u00a0tecnol\u00f3gica,\u00a0compromiso\u00a0y\u00a0activaci\u00f3n,\u00a0es\u00a0la\u00a0piedra\u00a0angular\u00a0de\u00a0nuestro\u00a0trabajo.\nCon\u00a0un\u00a0equipo\u00a0de\u00a03,000\u00a0empleados,\u00a0m\u00e1s\u00a0de\u00a0900\u00a0clientes\u00a0y\u00a0proyectos\u00a0en\u00a0m\u00e1s\u00a0de\u00a030\u00a0pa\u00edses,\u00a0y\u00a0una\u00a0facturaci\u00f3n\u00a0que\u00a0supera\u00a0los\u00a0500\u00a0millones\u00a0de\u00a0euros,\u00a0JAKALA\u00a0emerge\u00a0como\u00a0un\u00a0verdadero\u00a0punto\u00a0de\u00a0referencia\u00a0en\u00a0el\u00a0vasto\u00a0panorama\u00a0digital.\u00a0Gracias\u00a0a\u00a0la\u00a0contribuci\u00f3n\u00a0de\u00a0un\u00a0equipo\u00a0internacional\u00a0compuesto\u00a0por\u00a0talentos\u00a0vers\u00e1tiles\u00a0y\u00a0altamente\u00a0calificados,\u00a0la\u00a0empresa\u00a0ofrece\u00a0soluciones\u00a0\u00fanicas\u00a0y\u00a0personalizadas,\u00a0anticipando\u00a0los\u00a0desaf\u00edos\u00a0de\u00a0un\u00a0mercado\u00a0en\u00a0constante\u00a0evoluci\u00f3n.\u00a0Reconocida\u00a0como\nEmpresa Great Place to Work 2024\n, JAKALA persigue sus objetivos con la firme creencia de que el bienestar de los empleados y un impacto positivo en el medio ambiente son elementos esenciales para garantizar un crecimiento sostenible.\nBack\nApply\nShare this job:\nFacebook\nLinkedIn\nEmail",
        "application_url": "https://careers.jakala.com/en_US/careers/ApplicationMethods?jobId=2197",
        "": {},
        "metadata": {
            "Office": "Madrid",
            "Country": "Spain",
            "Date Published": "20-Nov-2025",
            "Ref #": "2165",
            "Area": "Marketing",
            "Type of Presence": "Hybrid"
        },
        "link": "https://careers.jakala.com/en_US/careers/JobDetail/SEM-Paid-Social-SR-Consultant/2197"
    },
    {
        "title": "Activation Associate Manager",
        "description_html": null,
        "description_text": "General information\nOffice\nMadrid\nCountry\nSpain\nDate Published\n19-Nov-2025\nRef #\n2166\nArea\nMarketing\nType of Presence\nHybrid\nDescription & Requirements\nEn\nJAKALA Iberia\nbuscamos un perfil\nAssociate Manager\ncon una s\u00f3lida trayectoria en entornos de Performance Marketing (SEM & Paid Social), capaz de liderar la estrategia, coordinar equipos, gestionar la relaci\u00f3n directa con clientes internacionales y garantizar el delivery operativo con m\u00e1xima calidad. El rol combina visi\u00f3n estrat\u00e9gica, gesti\u00f3n de personas y capacidad anal\u00edtica, siendo un punto clave entre el liderazgo del proyecto y el equipo operativo.\nFunciones:\nLiderar la estrategia global de performance en SEM y Paid Social, definiendo frameworks, roadmaps y planes de optimizaci\u00f3n conectados con los objetivos de negocio del cliente.\nGestionar y mentorizar perfiles junior y senior, garantizando su desarrollo, correcto reparto de cargas y excelencia operativa.\nSer el punto de contacto principal con el cliente, participando en reuniones estrat\u00e9gicas, QBRs y sesiones de planificaci\u00f3n.\nSupervisar y validar la activaci\u00f3n de campa\u00f1as avanzadas en Google Ads, Meta Ads, Search Ads 360 y entornos GMP.\nCoordinar y supervisar la calidad del delivery, asegurando que todas las ejecuciones cumplen con best practices y est\u00e1ndares internos.\nIntegrar la estrategia paid con otros canales (SEO, CRM, CRO, Program\u00e1tica, Anal\u00edtica), asegurando una visi\u00f3n full-funnel y omnicanal.\nAportar visi\u00f3n consultiva, anticipando riesgos, proponiendo nuevos enfoques y generando oportunidades de crecimiento.\nControlar presupuestos y pacing, asegurando un uso eficiente de la inversi\u00f3n mensual.\nImpulsar la innovaci\u00f3n, incorporando nuevas soluciones, automatizaciones y tests con impacto medible.\nDise\u00f1ar estrategias avanzadas de SEM y Paid Social orientadas a maximizar revenue, ROAS, eficiencia y crecimiento digital.\nSupervisar la configuraci\u00f3n, optimizaci\u00f3n y reporting de campa\u00f1as realizadas por el equipo operativo.\nGarantizar el uso correcto de herramientas como Search Ads 360, Campaign Manager 360, GA4, Meta Ads Manager, etc.\nImplementar frameworks de testing y medici\u00f3n (A/B, incrementality, bids, audiences).\nCoordinar flujos con equipos creativos y data para asegurar una estrategia integrada.\nConstruir dashboards de seguimiento, an\u00e1lisis y narrativa de resultados para stakeholders senior del cliente.\nPreparar presentaciones estrat\u00e9gicas y recomendaciones de alto nivel basadas en datos.\nDetectar oportunidades de eficiencia, escalado o mejora del funnel, y traducirlas a acciones concretas para el equipo.\nRequisitos:\nMust\n5-7 a\u00f1os de experiencia en performance marketing, con foco claro en SEM & Paid Social.\nExperiencia demostrada liderando equipos o perfiles junior/senior.\nNivel de\ningl\u00e9s muy alto\n, escrito y oral (proyectos y cliente 100% en ingl\u00e9s).\nDominio avanzado del ecosistema Google Marketing Platform: Search Ads 360, Campaign Manager 360 y GA4.\nExperiencia consolidada con Google Ads, Meta Ads y estrategias full-funnel.\nPerfil anal\u00edtico con capacidad de convertir datos en insights accionables.\nAlta capacidad de comunicaci\u00f3n y liderazgo, con experiencia gestionando clientes internacionales.\nNice to have\nConocimiento de herramientas de automatizaci\u00f3n o feed management.\nExperiencia en medici\u00f3n avanzada: incrementalidad, MMM, data pipelines.\nBackground en consultor\u00eda digital o agencias multinacionales.\nConocimiento de CRO y experimentaci\u00f3n.\nExperiencia en vertical Travel.\nQu\u00e9 ofrecemos\nModelo de asistencia a la oficina h\u00edbrido.\nSeguro m\u00e9dico privado.\nAcceso a Wellhub para bienestar f\u00edsico y mental.\nRetribuci\u00f3n flexible (restauraci\u00f3n, transporte, guarder\u00eda, etc.).\n28 d\u00edas de vacaciones al a\u00f1o.\nTres semanas al a\u00f1o de full remote.\nPlan de carrera adaptado a tus inquietudes profesionales.\nAcceso a certificaciones (Google, Salesforce, Adobe).\nProgramas de formaci\u00f3n tecnol\u00f3gica (Jxpert).\nLaboratorio de pruebas de soluciones tecnol\u00f3gicas (Jlab).\nFormaci\u00f3n en idiomas.\nDescripci\u00f3n de la empresa:\nSomos un ecosistema dise\u00f1ado para que el talento y las soluciones innovadoras se unan para impulsar el valor para las organizaciones, las personas y la sociedad.\nHoy en d\u00eda, somos la empresa l\u00edder en Martech en Europa, con sede en Mil\u00e1n y oficinas en todo el mundo. Nuestro enfoque impulsado por datos, respaldado por una f\u00f3rmula ganadora de estrategia, innovaci\u00f3n, transformaci\u00f3n tecnol\u00f3gica, compromiso y activaci\u00f3n, es la piedra angular de nuestro trabajo.\nCon un equipo de 3,000 empleados, m\u00e1s de 900 clientes y proyectos en m\u00e1s de 30 pa\u00edses, y una facturaci\u00f3n que supera los 500 millones de euros, JAKALA emerge como un verdadero punto de referencia en el vasto panorama digital. Gracias a la contribuci\u00f3n de un equipo internacional compuesto por talentos vers\u00e1tiles y altamente calificados, la empresa ofrece soluciones \u00fanicas y personalizadas, anticipando los desaf\u00edos de un mercado en constante evoluci\u00f3n. Reconocida como\nEmpresa Great Place to Work 2024\n, JAKALA persigue sus objetivos con la firme creencia de que el bienestar de los empleados y un impacto positivo en el medio ambiente son elementos esenciales para garantizar un crecimiento sostenible.\nBack\nApply\nShare this job:\nFacebook\nLinkedIn\nEmail",
        "application_url": "https://careers.jakala.com/en_US/careers/ApplicationMethods?jobId=2198",
        "": {},
        "metadata": {
            "Office": "Madrid",
            "Country": "Spain",
            "Date Published": "19-Nov-2025",
            "Ref #": "2166",
            "Area": "Marketing",
            "Type of Presence": "Hybrid"
        },
        "link": "https://careers.jakala.com/en_US/careers/JobDetail/Activation-Associate-Manager/2198"
    },
    {
        "title": "Experienced Professional | Senior Frontend Developer",
        "description_html": null,
        "description_text": "General information\nOffice\nMilano, Roma, Roncade\nCountry\nItaly\nDate Published\n19-Nov-2025\nRef #\n2170\nArea\nManagement Consulting\nType of Presence\nHybrid\nDescription & Requirements\n\ud83d\udccd\nSede\n:\nMilano\n\ud83d\udc40\nRank: Senior Associate\nChi siamo\nJAKALA \u00e8 un'azienda che lavora su dati, intelligenza artificiale e sviluppo di esperienze per generare un impatto significativo e duraturo a livello globale.\nPresenti in oltre 30 citt\u00e0 in 21 paesi, i nostri team uniscono competenze su strategia, tecnologia, creativit\u00e0 e\noperations\nper offrire esperienze personalizzate e soluzioni trasformative ai nostri clienti, grazie al supporto di dati e intelligenza artificiale. I\nJakalers\nsono un gruppo eterogeneo di oltre 3.000 persone, animate da passione, ambizione e idee brillanti. Proprio questa combinazione unica di talenti \u00e8 il fattore distintivo che ha ispirato il nostro\npurpose\n:\nTogether\nto\nget\nthere\n.\nCreare un mondo migliore \u00e8 il nostro obiettivo ultimo: la nostra ambizione \u00e8 generare valore per tutti i nostri stakeholder in modo sostenibile, con particolare attenzione a etica, clima e qualit\u00e0. Nel 2021, abbiamo scelto di diventare una Societ\u00e0 Benefit, dimostrando il nostro impegno di lungo periodo e la volont\u00e0 di proteggere i principi e i valori che ogni giorno guidano le nostre azioni.\nCrediamo che la diversit\u00e0 sia la chiave del nostro successo e, per questo, siamo impegnati a creare un ambiente di lavoro inclusivo, dove ciascuno possa sentirsi valorizzato per la propria unicit\u00e0. Tutte le nostre opportunit\u00e0 di lavoro sono aperte ai candidati appartenenti alle categorie protette L.68/99.\nScopri il team CRO & Analytics\nPer il potenziamento della Service Line Digital & Media, siamo alla ricerca di un Senior Frontend Developer da inserire nel team CRO & Analytics. In questo ruolo avrai l\u2019opportunit\u00e0 di utilizzare le tue competenze di frontend per modellare l\u2019esperienza digitale degli utenti attraverso attivit\u00e0 di A/B Testing e personalizzazioni on-site.\nCollaborerai con aziende leader nei principali settori di mercato ed entrerai a far parte del pi\u00f9 grande team di CRO e A/B Testing in Italia, contribuendo a progetti ad alto impatto e guidando l\u2019innovazione nel campo della digital optimization.\n\ud83c\udfaf Le tue responsabilit\u00e0:\nImplementare soluzioni front-end utilizzando HTML, CSS, JavaScript e librerie JS per ottimizzare i percorsi di conversione su siti e applicazioni dei nostri clienti\nSupportare le attivit\u00e0 di analisi configurando e inviando correttamente i dati verso strumenti di web analytics come Google Analytics e Adobe Analytics, con l\u2019obiettivo di sviluppare soluzioni mirate all\u2019aumento delle conversioni\nLavorare con piattaforme come Google Cloud e database come BigQuery, Firestore e altri strumenti di terze parti per la gestione, l\u2019organizzazione e l\u2019elaborazione dei dati\nPromuovere l\u2019innovazione studiando e integrando nuovi processi, metodologie e strumenti per migliorare l\u2019efficienza del workflow e favorire un\u2019evoluzione continua delle attivit\u00e0\n\ud83d\ude4c Se ti riconosci in queste caratteristiche, potremmo essere il perfetto match:\nEsperienza comprovata di tre o pi\u00f9 anni in front-end development con conoscenza approfondita di Vanilla JavaScript e librerie JS, HTML, CSS\nPassione per il mondo digitale e UX\nOttime capacit\u00e0 analitiche e di problem solving, unite a forte attitudine al lavoro di squadra\nOttima conoscenza della lingua inglese\nConoscenza linguaggi di programmazione/scripting e framework (PHP, Angular, React, Bootstrap, Foundation \u2026)\nsar\u00e0 considerata un plus\nConoscenza di database e scrittura query\nsar\u00e0 considerata un plus\nBuona padronanza del pacchetto Office (Excel e Powerpoint in particolare)\nsar\u00e0 considerata un plus\n\ud83d\udc9c\nScopri nel video le ragioni per cui scegliere JAKALA come prossimo step di carriera\nIn JAKALA crediamo che il tempo e il benessere delle persone vadano rispettati, sempre: incoraggiamo una presenza in ufficio di 10 giorni al mese, lasciando piena libert\u00e0 di lavorare da dove preferisci, sia in Italia che all\u2019interno della Comunit\u00e0 Europea.\nIl nostro sistema di Total Reward include convenzioni esclusive per viaggi, ristoranti, shopping, palestra e tempo libero, oltre a servizi gratuiti di telemedicina e supporto psicologico, pensati per te e per chi ami.\nInvestire nel nostro processo di selezione significa ricevere supporto autentico: un Recruiter dedicato ti accompagner\u00e0 con feedback personalizzati, consigli di carriera e insight sul tuo CV, a prescindere dall\u2019esito della candidatura. Niente AI, solo persone. E, grazie all\u2019iniziativa Your Time Back, ti restituiamo il tempo investito nei colloqui con un percorso di empowerment firmato Unobravo.\n\ud83c\udf31 Ready to start?\nNon \u00e8 solo una candidatura. \u00c8 un percorso che comincia ora. Inviaci il tuo CV: non vediamo l\u2019ora di conoscerti!\nBack\nApply\nShare this job:\nFacebook\nLinkedIn\nEmail",
        "application_url": "https://careers.jakala.com/en_US/careers/ApplicationMethods?jobId=2202",
        "": {},
        "metadata": {
            "Office": "Milano, Roma, Roncade",
            "Country": "Italy",
            "Date Published": "19-Nov-2025",
            "Ref #": "2170",
            "Area": "Management Consulting",
            "Type of Presence": "Hybrid"
        },
        "link": "https://careers.jakala.com/en_US/careers/JobDetail/Experienced-Professional-Senior-Frontend-Developer/2202"
    },
    {
        "title": "Experienced Professional | System Administrator",
        "description_html": null,
        "description_text": "General information\nOffice\nRiga\nCountry\nLatvia\nDate Published\n19-Nov-2025\nRef #\n2171\nArea\nIT and Information Systems\nType of Presence\nOn-site\nDescription & Requirements\n\ud83d\udccd\nLocation:\nRiga, Latvia\n\ud83d\udc40 Rank: Consultant\nAbout us\nJAKALA is a data, AI, and experiences company that creates meaningful and lasting impact globally.\nAcross more than 30 cities in 21 countries, our people combine strategy, technology, creativity, and operations to deliver tailored experiences and transformative solutions with data and AI at the heart. Jakalers are a diverse and multifaceted group of more than 3,000 individuals with passion, ambition and bright ideas. This unique mix of talents has become the distinctive factor that inspired our purpose: Together to get there.\nAt JAKALA, creating a better world is our ultimate purpose; we aim at creating value for all stakeholders in a sustainable way with a focus on ethics, climate and quality. In 2021, we decided to become a Benefit Corporation, demonstrating our long-term commitment to protecting the principles and values that guide our actions.We believe that diversity is the key to our success and for this reason we are committed to create an inclusive workplace, where everyone can feel valued for their uniqueness.\nDiscover the team\nWe are looking for a System Administrator to join our international IT team at our Riga office. The role involves managing and maintaining our server infrastructure, network services, office infrastructure support and application delivery stack. The ideal candidate understands core system administration concepts and is ready to grow into broader responsibilities, including participation in a rotating 24/7 support schedule in the future.\n\ud83c\udfaf Your responsibilities:\nMaintain and support Linux and Windows based servers and associated Web and Database services\nSupport the Development Team in their day to day activity (DevOp)\nManage network equipment, routing, VPNs, firewalls, and access controls\nAssist with provisioning, monitoring, and maintaining CDN and caching layers\nPerform troubleshooting across infrastructure, network, application layers\nParticipate in documentation of procedures, system configurations, and knowledge base materials\nCollaborate with other IT verticals: security, DevOps, application support, hosting environments, and cloud providers\nSupport incident response and root cause analysis\nAs a mandatory requirement, join a rotating on-call / 24x7 support schedule after sufficient onboarding and training\n\ud83d\ude4c\nIf you see yourself in these characteristics, we could be the perfect match:\nUnderstanding of Linux and Windows system administration and willingness to learn\nPractical knowledge of IP networking, routing, DNS, TLS certificates, and general network troubleshooting\nUnderstanding of least one CDN platform (Akamai, Cloudflare, Fastly, etc.) and willingness to learn\nFamiliarity with command-line tools, configuration files, and basic scripting\nAbility to work independently, take ownership, and collaborate within a distributed team\nGood English communication skills (written and verbal)\nExperience with monitoring systems (e.g., Prometheus, Zabbix, Site24x7, Grafana)\nwill be considered a plus\nFamiliarity with CI/CD, containerization, or virtualization (Docker, Proxmox, VMware, KVM)\nwill be considered a plus\nExperience with web stack components (Nginx, Apache, PHP, Node.js, etc.)\nwill be considered a plus\nExposure to cloud environments (AWS, Azure, Oracle Cloud, OVH, etc.)\nwill be considered a plus\n\ud83d\udc9c\nCompensation & Benefits:\nPremium Health insurance after the trial period\nPersonal accident insurance\nFast-paced, young and international environment\nOpportunities for hybrid working and international experiences\n2000-4000 \u20ac gross salary, based on experience\n\ud83c\udf31\nIf you invest time in our Recruiting process, you will have all our commitment.\nAnd beyond.\nYou application will be taken in charge by a Recruiter from our Talent Acquisition Team. Your Recruiter will review the CV and the set of info you provided to us and will come back to you with our feedback for you, regardless of the outcome. In any case, you will receive development suggestions about your CV optimization, hints to consolidate your professional journey and insights on the competitive arena you are in. No AI: we do it ourselves, with our heart, for you.\nAs JAKALA is an international company, your application may be reviewed by recruiters worldwide.\nTherefore, please upload your resume in English.\nBack\nApply\nShare this job:\nFacebook\nLinkedIn\nEmail",
        "application_url": "https://careers.jakala.com/en_US/careers/ApplicationMethods?jobId=2203",
        "": {},
        "metadata": {
            "Office": "Riga",
            "Country": "Latvia",
            "Date Published": "19-Nov-2025",
            "Ref #": "2171",
            "Area": "IT and Information Systems",
            "Type of Presence": "On-site"
        },
        "link": "https://careers.jakala.com/en_US/careers/JobDetail/Experienced-Professional-System-Administrator/2203"
    },
    {
        "title": "Product Design Lead (all genders)",
        "description_html": null,
        "description_text": "General information\nOffice\nHamburg\nCountry\nGermany\nDate Published\n19-Nov-2025\nRef #\n2172\nArea\nDesign\nType of Presence\nHybrid\nDescription & Requirements\nDu verstehst es, Design nicht nur zu gestalten, sondern zu f\u00fchren \u2013 strategisch, operativ und immer mit Blick auf das gro\u00dfe Ganze? Du bist\nExpert:in\ndarin Klarheit in komplexe Prozesse zu bringen und Designentscheidungen fundiert zu steuern? In dieser Rolle \u00fcbernimmst du die fachliche Verantwortung f\u00fcr die gesamte Designarbeit innerhalb der Projekte unseres Kunden im Bereich Streaming/Nachrichten und agierst als zentrale Schnittstelle zwischen Kreativteam, Produktmanagement, Strategie, Agile und Kundenseite. Wenn du Innovation f\u00f6rdern, hohe Qualit\u00e4tsstandards setzen und die Wirksamkeit eines interdisziplin\u00e4ren Teams aktiv vorantreiben m\u00f6chtest, bist du bei uns genau richtig.\nZum n\u00e4chstm\u00f6glichen Zeitpunkt suchen wir\neine:n\nerfahrene:n\nund\nvision\u00e4re:n\nProduct\nDesign Lead (all\ngenders\n) f\u00fcr unser Team in Hamburg, hybrid.\nResponsibilities\nDu planst und priorisierst UX-/UI-Kapazit\u00e4ten und stimmst Ressourcen eng mit Head\nof\u2019s\n, Projektmanagement und anderen Teams ab\nDu entwickelst im agilen Team\u00a0effiziente Arbeits- und Terminstrukturen und f\u00fchrst das Team durch Kreationstermine\nDu sorgst f\u00fcr klare Kommunikation und f\u00f6rderst den Austausch innerhalb der Kreation, mit angrenzenden Disziplinen und produkt\u00fcbergreifend, um Wissen und Best Practices zu teilen\nDu etablierst Qualit\u00e4ts- und Arbeitsstandards, sorgst f\u00fcr reibungslose Abl\u00e4ufe und organisierst effektive On- und\nOffboardings\nzur Sicherung von Wissenstransfer und Kontinuit\u00e4t\nDu pr\u00e4sentierst Experience-Konzepte und -L\u00f6sungen gegen\u00fcber internen und externen Stakeholdern und arbeitest eng mit Produktmanagement und Experience\nStrategy\nzusammen.\nDu verantwortest die UX-/UI-Strategie im Produkt und stellst nutzerzentrierte Designentscheidungen sicher, die auf Produktvision, Businessziele und Nutzerbed\u00fcrfnisse einzahlen\nDu st\u00e4rkst Teamgeist, Feedbackkultur sowie die Weiterentwicklung deiner Teammitglieder in Zusammenarbeit mit den Head\nof\u2019s\nUX und -\nUI\n, z.B.\ndurch Coaching im Arbeitsalltag oder Review-Sessions\nOverview\nJAKALA ist ein weltweit t\u00e4tiges IT- und Consulting-Unternehmen im Bereich\nMartec\nh\n, mit einem starken Fokus auf Daten und KI. Von den weltweit \u00fcber 3.300 Mitarbeitenden sind rund 230 in Hamburg und Berlin t\u00e4tig. Bei JAKALA Germany liegt der Schwerpunkt auf der Entwicklung von individuellen Software-L\u00f6sungen, haupts\u00e4chlich von sogenannten Digital Experience\nPlatform\ns\n(DXP), in denen Gesch\u00e4ftsprozesse entlang der Customer Journey digitalisiert werden. An der Schnittstelle von Strategie, Design und Technologie entwickelt JAKALA digitale Plattformen, Apps und andere Services, welche die digitalen Erlebnisse gro\u00dfer Marken ma\u00dfgeblich pr\u00e4gen. Zu den Kunden in Deutschland z\u00e4hlen beispielsweise TUI Cruises, Leica, die Hamburger Hochbahn oder das ZDF.\nQualifications\nDu verf\u00fcgst \u00fcber Erfahrung im Design Management, UX-/UI- oder Service Design mit Projekt- und Kundenverantwortung\nDu bringst fundierte Kenntnisse in UX-/UI-Strategie, nutzerzentriertem Design und der Verzahnung von Produktvision und Businesszielen mit\nDu arbeitest eigenst\u00e4ndig, proaktiv und \u00fcbernimmst Ownership, auch im Kundenkontakt\nDu besitzt ein breites Verst\u00e4ndnis aller Designprozesse und kannst bei Bedarf auch operative Aufgaben im UX-/UI-Bereich \u00fcbernehmen\nDu hast Erfahrung darin, Designteams zu f\u00fchren, die Teamkultur zu f\u00f6rdern und die Weiterentwicklung der Mitarbeitenden zu unterst\u00fctzen\nDu kennst dich mit Ressourcenplanung und bereichs\u00fcbergreifender Zusammenarbeit aus\nOffer\nDas bieten wir dir:\nJob in Vollzeit oder Teilzeit \u2013 du entscheidest\nHybrides Arbeitsmodell (Remote und/oder B\u00fcro) mit flexiblen Arbeitszeiten\nOffene und teamorientierte Unternehmenskultur\nWertsch\u00e4tzung deiner Ideen\nZuschuss f\u00fcr \u00d6PNV und\nBikeleasing\n-Option\nUrban Sports Club Membership\nW\u00f6chentliches gemeinsames Fr\u00fchst\u00fcck oder Mittagessen\nWenn du willst: Einstieg in unsere Hamburger Band (\nSchlagzeuger:in\ngesucht)\nWhat\nElse?\nWir wollen einen positiven Impact auf unsere Erde haben. Deshalb streben wir danach, auf nachhaltige Weise Wert f\u00fcr alle Interessengruppen zu schaffen und ber\u00fccksichtigen dabei Klima, Ethik und Qualit\u00e4t. 2021 haben wir uns entschieden, eine Benefit Corporation zu werden, um unser langfristiges Engagement f\u00fcr den Schutz der Prinzipien und Werte, die unser Handeln leiten, zu unterstreichen.\nBewirb dich noch heute. Wir freuen uns darauf, dich kennenzulernen.\nBack\nApply\nShare this job:\nFacebook\nLinkedIn\nEmail",
        "application_url": "https://careers.jakala.com/en_US/careers/ApplicationMethods?jobId=2204",
        "": {},
        "metadata": {
            "Office": "Hamburg",
            "Country": "Germany",
            "Date Published": "19-Nov-2025",
            "Ref #": "2172",
            "Area": "Design",
            "Type of Presence": "Hybrid"
        },
        "link": "https://careers.jakala.com/en_US/careers/JobDetail/Product-Design-Lead-all-genders/2204"
    },
    {
        "title": "Senior React Native Developer (all genders)",
        "description_html": null,
        "description_text": "General information\nOffice\nBerlin, Hamburg, Vienna\nCountry\nGermany\nDate Published\n17-Nov-2025\nRef #\n2163\nArea\nIT and Information Systems\nType of Presence\nHybrid\nDescription & Requirements\nDescription &\nRequirements\nDu bist erfahrener Mobile Developer mit einer Leidenschaft f\u00fcr moderne, innovative App-Entwicklung? Du hast tiefgehende, langj\u00e4hrige Erfahrung mit\nReact Native\n, liebst es, anspruchsvolle, auch native Features f\u00fcr iOS und Android umzusetzen und m\u00f6chtest innerhalb eines starken Produktteams Mobile\nExperiences\nentwickeln, die von hunderttausenden von Nutzern t\u00e4glich verwendet werden?\nDann suchen wir genau dich.\nWir suchen zum n\u00e4chstm\u00f6glichen Zeitpunkt\neine:n\nmotivierte:n\nund\nengagierte:n\nSenior React Native Developer (all\ngenders\n) i\nn Hamburg, Berlin, Wien, hybrid oder remote.\nResponsibilities\nDu entwickelst die mobile App eines unserer Kunden\u00a0innovativ, performant, skalierbar und nach aktuellen Mobile-Standards weiter\nDu arbeitest eng mit\nUX/UI-Design\n,\nBackend\n, QA und Produktmanagement zusammen und schaffst herausragende mobile Nutzererlebnisse\nDu\nintegrierst\nCloud-Services\n(AWS),\nOAuth-Authentifizierung\nsowie Profil- und Nutzerdaten.\nDu\nbindest ein\nHeadless\nCMS\n(\nContentful\n) f\u00fcr dynamische Inhalte und flexibel steuerbare App-Bereiche ein.\nDu entwickelst\nPersonalisierungs-Features\nsowie ein belastbares\nTracking & Analytics\n-Setup zur Messbarkeit der App Experience (\nTealium\n, GA4)\nDu\nsetzt\nPush-Services\n, Deep Links und In-App-Kommunikation um.\nDu\nrealisierst\nOffline-f\u00e4hige Bereiche\n,\nWebViews\nund hybride Feature-Komponenten\nDu\nentwickelst smarte Systemintegrationen wie automatisierte Netzwerk- und Connectivity-Flows.\nDu\nstellst\nPerformance, Stabilit\u00e4t und Monitoring\nsicher (Sentry) und arbeitest mit automatisierten Tests (\nMaestr\no).\nDu\nber\u00fccksichtigst\nAccessibility\n, Mehrsprachigkeit und moderne UI/UX-Standards.\nDu\ngestaltest zuk\u00fcnftige Erweiterungen mit \u2013 z. B. KI-basierte Personalisierung, Voice Interaction, Wearables oder Widgets.\nDu tr\u00e4gst zu einem modernen UI unter Nutzung eines Design Systems f\u00fcr mobile Komponenten bei\nOverview\nJAKALA ist ein weltweit t\u00e4tiges IT- und Consulting-Unternehmen im Bereich\nMartech\n, mit einem starken Fokus auf Daten und KI. Von den weltweit rund 3.200 Mitarbeitenden sind knapp 240 in Hamburg und Berlin t\u00e4tig. Bei JAKALA Germany liegt der Schwerpunkt auf der Entwicklung von individuellen Software-L\u00f6sungen, haupts\u00e4chlich von sogenannten Digital Experience\nPlatforms\n(DXP). An der Schnittstelle von Strategie, Design und Technologie entwickeln wir digitale Plattformen, Apps und andere Services, welche die digitalen Erlebnisse gro\u00dfer Marken ma\u00dfgeblich pr\u00e4gen. Zu den Kunden in Deutschland z\u00e4hlen beispielsweise TUI Cruises, Leica, die Hamburger Hochbahn oder das ZDF.\nQualifications\nDu besitzt tiefe, langj\u00e4hrige Kenntnisse in JavaScript/\nTypeScript\nund React Native und hast mit diesen Technologien bereits erfolgreich komplexe mobile Projekte umgesetzt\nDu hast einen technologischen Weitblick und breite Erfahrungswerte \u00fcber das Kernarbeitsgebiet hinaus (Personalisierung, Daten, Analytics, Headless CMS,\nAWS Cloud\n, Designsysteme, Offline-Funktionalit\u00e4t, native F\u00e4higkeiten und Module und automatisierte QA-Tools).\nDu bist vertraut mit agilen Entwicklungsmethoden und f\u00fchlst dich in integrierten,\ncrossfunktionalen\nTeams wohl.\nDu verf\u00fcgst \u00fcber eine schnelle Auffassungsgabe und ein hohes Verst\u00e4ndnis f\u00fcr die technischen Zusammenh\u00e4nge einer komplexen mobilen Plattform.\nDu hast ein wirtschaftliches Bewusstsein f\u00fcr ein angemessenes Ma\u00df zwischen Effizienz und h\u00f6chster Code-Qualit\u00e4t, um wartbare und skalierbare L\u00f6sungen zu schaffen.\nDu bist\nein:e\nstarke:r\nKommunikator:in\n, der oder die sich sowohl in der Zusammenarbeit mit interdisziplin\u00e4ren Teams souver\u00e4n\nbewegt,\nals auch technische Sachverhalte verst\u00e4ndlich vermitteln kann, mindestens auf Deutsch und idealerweise zus\u00e4tzlich auf Englisch.\nOffer\nDas bieten wir dir:\nJob in Vollzeit oder Teilzeit \u2013 du entscheidest\nHybrides Arbeitsmodell (Remote und/oder B\u00fcro) mit flexiblen Arbeitszeiten\nOffene und teamorientierte Unternehmenskultur\nWertsch\u00e4tzung deiner Ideen\nZuschuss f\u00fcr \u00d6PNV und Bikeleasing-Option\nUrban Sports Club Membership\nW\u00f6chentliches gemeinsames Fr\u00fchst\u00fcck oder Mittagessen\nWenn du willst: Einstieg in unsere Hamburger Band (Schlagzeuger:in gesucht)\nWhat\nelse\n?\nWir wollen einen positiven Impact auf unsere Erde haben. Deshalb streben wir danach, auf nachhaltige Weise Wert f\u00fcr alle Interessengruppen zu schaffen und ber\u00fccksichtigen dabei Klima, Ethik und Qualit\u00e4t. 2021 haben wir uns entschieden, eine Benefit Corporation zu werden, um unser langfristiges Engagement f\u00fcr den Schutz der Prinzipien und Werte, die unser Handeln leiten, zu unterstreichen.\nBewirb dich noch heute. Wir freuen uns darauf, dich kennenzulernen.\nBack\nApply\nShare this job:\nFacebook\nLinkedIn\nEmail",
        "application_url": "https://careers.jakala.com/en_US/careers/ApplicationMethods?jobId=2195",
        "": {},
        "metadata": {
            "Office": "Berlin, Hamburg, Vienna",
            "Country": "Germany",
            "Date Published": "17-Nov-2025",
            "Ref #": "2163",
            "Area": "IT and Information Systems",
            "Type of Presence": "Hybrid"
        },
        "link": "https://careers.jakala.com/en_US/careers/JobDetail/Senior-React-Native-Developer-all-genders/2195"
    },
    {
        "title": "Drupal Frontend Developer (all genders)",
        "description_html": null,
        "description_text": "General information\nOffice\nFull Remote, Berlin, Hamburg, Vienna\nCountry\nGermany\nDate Published\n11-Nov-2025\nRef #\n2152\nArea\nIT and Information Systems\nType of Presence\nRemote\nDescription & Requirements\nDu entwickelst responsive Webanwendungen, modifizierst\nThemes\nund integrierst kreative Konzepte in funktionale\nFrontends\n? Du bist\nExpert:in\ndarin, HTML, CSS und JavaScript in Drupal-Projekte zu \u00fcberf\u00fchren und arbeitest gerne eng mit UX/UI, Backend und Projektmanagement zusammen? Wenn du in einer dynamischen Umgebung f\u00fcr verschiedene Kunden digitale L\u00f6sungen mitgestalten m\u00f6chtest, bist du bei uns genau richtig.\nZum n\u00e4chstm\u00f6glichen Zeitpunkt suchen wir\neine:n\nmotivierte:n\nund\nengagierte:n\nDrupal Frontend Developer (all\ngenders\n)\nin Hamburg, Berlin oder Wien \u2013 hybrid oder remote.\nResponsibilities\nDu entwickelst Drupal-\nThemes\nund responsive Webanwendungen\nDu analysierst Anforderungen und ber\u00e4tst zu technischen L\u00f6sungen\nDu arbeitest eng mit\nProjektmanager:innen\n,\nDesigner:innen\nund weiteren\nEntwickler:innen\nzusammen\nDu integrierst statisches HTML in dynamische Seiten\nDu entwickelst innovative Ideen f\u00fcr die Umsetzung von Mockups und Prototypen\nDu beteiligst dich an der technischen Dokumentation\nDu sch\u00e4tzt den Aufwand deiner Aufgaben zuverl\u00e4ssig\nOverview\nJAKALA ist ein weltweit t\u00e4tiges IT- und Consulting-Unternehmen im Bereich\nMartech\n, mit einem starken Fokus auf Daten und KI. Von den weltweit \u00fcber 3.300 Mitarbeitenden sind rund 230 in Hamburg und Berlin t\u00e4tig. Bei JAKALA Germany liegt der Schwerpunkt auf der Entwicklung von individuellen Software-L\u00f6sungen, haupts\u00e4chlich von sogenannten Digital Experience\nPlatforms\n(DXP), in denen Gesch\u00e4ftsprozesse entlang der Customer Journey digitalisiert werden. An der Schnittstelle von Strategie, Design und Technologie entwickelt JAKALA digitale Plattformen, Apps und andere Services, welche die digitalen Erlebnisse gro\u00dfer Marken ma\u00dfgeblich pr\u00e4gen. Zu den Kunden in Deutschland z\u00e4hlen beispielsweise TUI Cruises, Leica, die Hamburger Hochbahn oder das ZDF.\nQualifications\nDu beherrschst HTML, XHTML und CSS sicher und entwickelst W3C-konformen Code\nDu nutzt moderne CSS3-Features und Frameworks wie Bootstrap\nDu bringst Erfahrung mit JavaScript und\njQuery\nmit und kannst eigene\njQuery\n-Plugins und JavaScript-Funktionen entwickeln\nDu kennst dich mit AJAX und serverseitiger Programmierung aus\nDu verstehst die Anforderungen an barrierefreie Webentwicklung\nDu arbeitest sicher mit Versionskontrollsystemen wie\nGit\nDu modifizierst Drupal-\nThemes\nmit HTML, CSS, JS und PHP\nDu entwickelst Templates mit Twig und nutzt SDC f\u00fcr modulare Komponenten\nDu sprichst flie\u00dfend Deutsch und Englisch\nOffer\nDas bieten wir dir:\nJob in Vollzeit oder Teilzeit \u2013 du entscheidest\nHybrides Arbeitsmodell (Remote und/oder B\u00fcro) mit flexiblen Arbeitszeiten\nOffene und teamorientierte Unternehmenskultur\nWertsch\u00e4tzung deiner Ideen\nZuschuss f\u00fcr \u00d6PNV und\nBikeleasing\n-Option\nUrban Sports Club Membership\nW\u00f6chentliches gemeinsames Fr\u00fchst\u00fcck oder Mittagessen\nWenn du willst: Einstieg in unsere Hamburger Band (\nSchlagzeuger:in\ngesucht)\nWhat\nElse?\nWir wollen einen positiven Impact auf unsere Erde haben. Deshalb streben wir danach, auf nachhaltige Weise Wert f\u00fcr alle Interessengruppen zu schaffen und ber\u00fccksichtigen dabei Klima, Ethik und Qualit\u00e4t. 2021 haben wir uns entschieden, eine Benefit Corporation zu werden, um unser langfristiges Engagement f\u00fcr den Schutz der Prinzipien und Werte, die unser Handeln leiten, zu unterstreichen.\nBewirb dich noch heute. Wir freuen uns darauf, dich kennenzulernen.\nBack\nApply\nShare this job:\nFacebook\nLinkedIn\nEmail",
        "application_url": "https://careers.jakala.com/en_US/careers/ApplicationMethods?jobId=2184",
        "": {},
        "metadata": {
            "Office": "Full Remote, Berlin, Hamburg, Vienna",
            "Country": "Germany",
            "Date Published": "11-Nov-2025",
            "Ref #": "2152",
            "Area": "IT and Information Systems",
            "Type of Presence": "Remote"
        },
        "link": "https://careers.jakala.com/en_US/careers/JobDetail/Drupal-Frontend-Developer-all-genders/2184"
    },
    {
        "title": "Intern | Client Strategy TMT & Energy",
        "description_html": null,
        "description_text": "General information\nOffice\nMilano\nCountry\nItaly\nDate Published\n10-Nov-2025\nRef #\n2149\nArea\nManagement Consulting\nType of Presence\nHybrid\nDescription & Requirements\n\ud83d\udccd\nSede\n:\u00a0Milano\nChi siamo\nJAKALA \u00e8 un'azienda che lavora su dati, intelligenza artificiale e sviluppo di esperienze per generare un impatto significativo e duraturo a livello globale.\nPresenti in oltre 30 citt\u00e0 in 21 paesi,\ni nostri team\nuniscono competenze su strategia, tecnologia, creativit\u00e0 e\noperations\nper offrire esperienze personalizzate e soluzioni trasformative ai nostri clienti, grazie al supporto di dati e intelligenza artificiale. I\nJakalers\nsono un gruppo eterogeneo di oltre 3.000 persone, animate da passione, ambizione e idee brillanti. Proprio questa combinazione unica di talenti \u00e8 il fattore distintivo che ha ispirato il nostro\npurpose\n:\nTogether\nto\nget\nthere\n.\nCreare un mondo migliore \u00e8 il nostro obiettivo ultimo: la nostra ambizione \u00e8 generare valore per tutti i nostri stakeholder in modo sostenibile, con particolare attenzione a etica, clima e qualit\u00e0. Nel 2021, abbiamo scelto di diventare una Societ\u00e0 Benefit, dimostrando il nostro impegno di lungo periodo e la volont\u00e0 di proteggere i principi e i valori che ogni giorno guidano le nostre azioni.\nCrediamo che la diversit\u00e0 sia la chiave del nostro successo e, per questo, siamo impegnati a creare un ambiente di lavoro inclusivo, dove ciascuno possa sentirsi valorizzato per la propria unicit\u00e0. Tutte le nostre opportunit\u00e0 di lavoro sono aperte ai candidati appartenenti alle categorie protette L.68/99.\nScopri\nil team\nTMT & Energy\nHai passione per il mondo dei dati, della consulenza e dell\u2019innovazione digitale? In JAKALA,\nil team\nClient Strategy TMT & Energy lavora su progetti sfidanti per clienti leader di mercato, coniugando insight analitici, creativit\u00e0 e tecnologia in un contesto dinamico e stimolante.\n\ud83c\udfaf Ogni giorno sar\u00e0 diverso, ma eccoti un assaggio di quello che ti aspetta\nUn\u2019esperienza concreta all\u2019interno di un gruppo di lavoro multidisciplinare, dove potrai contribuire alla valorizzazione del patrimonio informativo dei clienti, approfondendo tematiche di Strategy & Consulting\nUn coinvolgimento nello sviluppo e nella realizzazione di progetti innovativi per grandi clienti in ambito Energy e Utilities\nUn\u2019attivit\u00e0 focalizzata su Data Analytics, Intelligenza Artificiale e trasformazione digitale, con l\u2019obiettivo di analizzare dati e sviluppare soluzioni innovative in un contesto in continua evoluzione\n\ud83d\udca1 Queste caratteristiche sono un ottimo punto di partenza per crescere insieme\nLaurea Magistrale, preferibilmente in Economia e Management, Marketing o discipline STEM\nOttime capacit\u00e0 analitiche, di sintesi e cura al dettaglio\nForte passione per il mondo della Consulenza in ambito Energy & Utilities\nOttima conoscenza del pacchetto Office\nFluenza nella lingua italiana e inglese\n\ud83d\ude80Ci brillano gli occhi se hai anche\nForte orientamento al risultato\nVolont\u00e0 di implicarsi e incidere in un ambiente dinamico\nProblem\nsolving e orientamento al lavoro per obiettivi\nAttitudine al project management\nTeam working\nSpiccate capacit\u00e0 relazionali\n\ud83d\udc9c\nScopri in questo video le ragioni per cui scegliere JAKALA come prossimo step di carriera\nIn JAKALA crediamo che il tempo e il benessere delle persone vadano rispettati, sempre: incoraggiamo una presenza in ufficio di 10 giorni al mese.\nIl nostro sistema di Total Reward include convenzioni esclusive per viaggi, ristoranti, shopping, palestra e tempo libero, oltre a servizi gratuiti di telemedicina e supporto psicologico, pensati per te e per chi ami.\nInvestire nel nostro processo di selezione significa ricevere supporto autentico: un Recruiter dedicato ti accompagner\u00e0 con feedback personalizzati, consigli di carriera e insight sul tuo CV, a prescindere dall\u2019esito della candidatura. Niente AI, solo persone. E, grazie all\u2019iniziativa Your Time Back, ti restituiamo il tempo investito nei colloqui con un percorso di empowerment firmato\nUnobravo\n.\n\ud83c\udf31\u00a0Ready to start?\nNon \u00e8 solo una candidatura. \u00c8 un percorso che comincia ora. Inviaci il tuo CV: non vediamo l\u2019ora di conoscerti!\nBack\nApply\nShare this job:\nFacebook\nLinkedIn\nEmail",
        "application_url": "https://careers.jakala.com/en_US/careers/ApplicationMethods?jobId=2181",
        "": {},
        "metadata": {
            "Office": "Milano",
            "Country": "Italy",
            "Date Published": "10-Nov-2025",
            "Ref #": "2149",
            "Area": "Management Consulting",
            "Type of Presence": "Hybrid"
        },
        "link": "https://careers.jakala.com/en_US/careers/JobDetail/Intern-Client-Strategy-TMT-Energy/2181"
    },
    {
        "title": "Intern | Technology Consulting | Project Management Academy",
        "description_html": null,
        "description_text": "General information\nOffice\nRende, Roma\nCountry\nItaly\nDate Published\n05-Nov-2025\nRef #\n2144\nArea\nIT and Information Systems\nType of Presence\nHybrid\nDescription & Requirements\n\ud83d\udccd\nSede\n: Roma, Rende\nChi siamo\nJAKALA \u00e8 un'azienda che lavora su dati, intelligenza artificiale e sviluppo di esperienze per generare un impatto significativo e duraturo a livello globale.\nPresenti in oltre 30 citt\u00e0 in 21 paesi,\ni nostri team\nuniscono competenze su strategia, tecnologia, creativit\u00e0 e\noperations\nper offrire esperienze personalizzate e soluzioni trasformative ai nostri clienti, grazie al supporto di dati e intelligenza artificiale. I\nJakalers\nsono un gruppo eterogeneo di oltre 3.000 persone, animate da passione, ambizione e idee brillanti. Proprio questa combinazione unica di talenti \u00e8 il fattore distintivo che ha ispirato il nostro\npurpose\n:\nTogether\nto\nget\nthere\n.\nCreare un mondo migliore \u00e8 il nostro obiettivo ultimo: la nostra ambizione \u00e8 generare valore per tutti i nostri stakeholder in modo sostenibile, con particolare attenzione a etica, clima e qualit\u00e0. Nel 2021, abbiamo scelto di diventare una Societ\u00e0 Benefit, dimostrando il nostro impegno di lungo periodo e la volont\u00e0 di proteggere i principi e i valori che ogni giorno guidano le nostre azioni.\nCrediamo che la diversit\u00e0 sia la chiave del nostro successo e, per questo, siamo impegnati a creare un ambiente di lavoro inclusivo, dove ciascuno possa sentirsi valorizzato per la propria unicit\u00e0. Tutte le nostre opportunit\u00e0 di lavoro sono aperte ai candidati appartenenti alle categorie protette L.68/99.\nScopri\nil team\nTechnology Consulting\ne il progetto Academy\nHai passione per la tecnologia e desideri entrare nel cuore della trasformazione digitale? Nella Technology Consulting - Project Management Academy ti prepareremo a gestire progetti complessi con approcci\nWaterfall\ne Agile. Come Project Manager\nAnalyst\nin stage, lavorerai a fianco di professionisti esperti, portando il tuo contributo su iniziative strategiche che guidano l\u2019evoluzione digitale dei nostri clienti.\nAll\u2019inizio del percorso di stage\u00a0della\u00a0Project Management Academy,\u00a0sarai coinvolto\u00a0in un\nprogramma intensivo di\n3\nsettimane di formazione\nteorico-pratica su metodologie\nWaterfall\ne Agile\n, strumenti digitali di project management e soft skills trasversali.\nAl termine della formazione, potrai mettere in pratica le competenze acquisite, contribuendo alla gestione di progetti reali in ambito tecnologico, IT o consulenziale, insieme ai colleghi\ndel\nteam\ndi\nProject Management Office (PMO)\n.\n\ud83c\udfaf Ogni giorno sar\u00e0 diverso, ma eccoti un assaggio di quello che ti aspetta\nUn coinvolgimento nella pianificazione, monitoraggio e controllo di iniziative strategiche per grandi clienti, in collaborazione con professionisti esperti\nUn\u2019attivit\u00e0 focalizzata sull\u2019utilizzo di strumenti digitali di project management, sulla gestione di stakeholder e sulla comunicazione efficace, in un contesto dinamico e in continua evoluzione\nLa partecipazionea sessioni formative e workshop dedicati alle metodologie\nWaterfall\ne Agile, strumenti digitali e soft skills\n(\ncome\nleadership,\nteamwork\ne\nproblem\nsolving\n)\n, per consolidare le competenze acquisite durante l\na formazione\nUn percorso di mentoring con Project Manager Senior, per ricevere\nfeedback\ne crescere professionalmente in un ambiente inclusivo e orientato all\u2019innovazione\n\ud83d\udca1\nQueste caratteristiche sono un ottimo punto di partenza per crescere insieme\nLaurea triennale o magistrale in\nIngegneria, Informatica, Economia, Matematica, o discipline STEM\nInteresse per la gestione di progetti tecnologici e per la consulenza IT\nAttitudine all\u2019organizzazione, alla pianificazione e al\nproblem\nsolving\nBuone capacit\u00e0 di analisi e gestione delle priorit\u00e0\nTeam working, comunicazione efficace e orientamento al risultato\nCuriosit\u00e0 e desiderio di crescere in un contesto dinamico e collaborativo\nOttima conoscenza dell\u2019inglese scritto e parlato\n\ud83d\ude80Ci brillano gli occhi se hai anche\nCapacit\u00e0 di alternare un\nmindset\nanalitico a una forte attitudine alla comunicazione e alla gestione degli stakeholder\nAutonomia nella gestione di progetti e spirito di iniziativa\nEntusiasmo, curiosit\u00e0 e passione\n\ud83d\udc9c\nScopri in questo video le ragioni per cui scegliere JAKALA come prossimo step di carriera\nIn JAKALA crediamo che il tempo e il benessere delle persone vadano rispettati, sempre: incoraggiamo una presenza in ufficio di\n10\ngiorni al mese.\nIl nostro sistema di Total\nReward\ninclude convenzioni esclusive per viaggi, ristoranti, shopping, palestra e tempo libero, oltre a servizi gratuiti di telemedicina e supporto psicologico, pensati per te e per chi ami.\nInvestire nel nostro processo di selezione significa ricevere supporto autentico: un Recruiter dedicato ti accompagner\u00e0 con feedback personalizzati, consigli di carriera e insight sul tuo CV, a prescindere dall\u2019esito della candidatura. Niente AI, solo persone. E, grazie all\u2019iniziativa Your Time Back, ti restituiamo il tempo investito nei colloqui con un percorso di empowerment firmato\nUnobravo\n.\n\ud83c\udf31\u00a0Ready to start?\nNon \u00e8 solo una candidatura. \u00c8 un percorso che comincia ora. Inviaci il tuo CV: non vediamo l\u2019ora di conoscerti!\nBack\nApply\nShare this job:\nFacebook\nLinkedIn\nEmail",
        "application_url": "https://careers.jakala.com/en_US/careers/ApplicationMethods?jobId=2176",
        "": {},
        "metadata": {
            "Office": "Rende, Roma",
            "Country": "Italy",
            "Date Published": "05-Nov-2025",
            "Ref #": "2144",
            "Area": "IT and Information Systems",
            "Type of Presence": "Hybrid"
        },
        "link": "https://careers.jakala.com/en_US/careers/JobDetail/Intern-Technology-Consulting-Project-Management-Academy/2176"
    },
    {
        "title": "Agile Coach (all genders)",
        "description_html": null,
        "description_text": "General information\nOffice\nHamburg\nCountry\nGermany\nDate Published\n27-Oct-2025\nRef #\n2133\nArea\nIT and Information Systems\nType of Presence\nHybrid\nDescription & Requirements\nDu bist kein traditioneller Manager, sondern ein\nServant\nLeader, der Teams dabei unterst\u00fctzt, ihr volles Potenzial zu entfalten? Du bringst exzellente Moderations-, Kommunikations- und Coaching-Skills mit und hast ein tiefes Verst\u00e4ndnis f\u00fcr agile Prinzipien und Werte? Dann sollten wir uns kennenlernen.\nZum n\u00e4chstm\u00f6glichen Zeitpunkt suchen wir einen motivierten und engagierten Agile Coach (all\ngenders\n) in Hamburg oder hybrid.\nResponsibilities\nDu tr\u00e4gst die organisatorische und methodische Verantwortung f\u00fcr unsere interdisziplin\u00e4ren Teams.\nDu identifizierst Schwachstellen pr\u00e4zise und implementierst performancesteigernde Ma\u00dfnahmen.\nDu verantwortest Sprint-Events und stellst sicher, dass sie effektiv gestaltet und im Sinne der Teamziele genutzt werden.\nDu trittst sicher im Umgang mit dem Team und unseren Kunden auf und gestaltest die Zusammenarbeit partnerschaftlich mit.\nDu agierst als Coach deines Teams, st\u00e4rkst Eigenverantwortung und f\u00f6rderst eine offene Kommunikation innerhalb des Teams und \u00fcber Teamgrenzen hinweg.\nDu stellst einen klaren Informationsfluss sicher, l\u00f6st Konflikte fr\u00fchzeitig und baust Hindernisse ab, die den Fortschritt des Teams behindern.\nDu bist der kommunikative Br\u00fcckenbauer zwischen dem Team und externen Stakeholdern, schaffst Transparenz und managst Erwartungen.\nDu moderierst agile Zeremonien, schaffst eine Kultur von Offenheit und Respekt und tr\u00e4gst aktiv zur Zielerreichung und Motivation des Teams bei.\nOverview\nJAKALA ist ein weltweit t\u00e4tiges IT- und Consulting-Unternehmen im Bereich\nMartech\n, mit einem starken Fokus auf Daten und KI. Von den weltweit \u00fcber 3.300 Mitarbeitenden sind rund 230 in Hamburg und Berlin t\u00e4tig. Bei JAKALA Germany liegt der Schwerpunkt auf der Entwicklung von individuellen Software-L\u00f6sungen, haupts\u00e4chlich von sogenannten Digital Experience\nPlatforms\n(DXP), in denen Gesch\u00e4ftsprozesse entlang der Customer Journey digitalisiert werden. An der Schnittstelle von Strategie, Design und Technologie entwickelt JAKALA digitale Plattformen, Apps und andere Services, welche die digitalen Erlebnisse gro\u00dfer Marken ma\u00dfgeblich pr\u00e4gen. Zu den Kunden in Deutschland z\u00e4hlen beispielsweise TUI Cruises, Leica, die Hamburger Hochbahn oder das ZDF.\nQualifications\nDu hast mindestens 3 Jahre Erfahrung als\nScrum\nMaster oder Agile Coach und bist routiniert im Einsatz agiler Methoden.\nDu bringst fundiertes Wissen in agilen Prinzipien und Praktiken mit und hast idealerweise eine Agile Coach-Zertifizierung oder eine vergleichbare Qualifikation.\nDu kommunizierst klar und effektiv und erkennst sowie l\u00f6st Probleme fr\u00fchzeitig aus eigener Initiative.\nDu bist f\u00fcr dein Team pr\u00e4sent, erreichbar und baust durch deine Zuverl\u00e4ssigkeit Vertrauen auf.\nDeine Moderationsf\u00e4higkeiten f\u00f6rdern eine effektive Kommunikation und Zusammenarbeit im Team.\nDu organisierst dich selbst\u00e4ndig, priorisierst effektiv und beh\u00e4ltst auch in dynamischen Projektsituationen den \u00dcberblick\nEin grundlegendes Verst\u00e4ndnis von Softwareentwicklung sowie Agentur-Erfahrung sind von gro\u00dfem Vorteil, aber kein Muss\nDu beherrschst Deutsch perfekt in Wort und Schrift und kannst dich sicher auf Englisch verst\u00e4ndigen.\nOffer\nJob in Vollzeit oder Teilzeit - du entscheidest\nHybrides Arbeitsmodell (Remote und B\u00fcro) mit flexiblen Arbeitszeiten\nOffene und teamorientierte Unternehmenskultur\nWertsch\u00e4tzung deiner Ideen\nZuschuss f\u00fcr \u00d6PNV und\nBikeleasing\n-Option\nUrban Sports Club Membership\nW\u00f6chentliches gemeinsames Fr\u00fchst\u00fcck oder Mittagessen\nWenn du willst: Einstieg in unsere Hamburger Band (\nSchlagzeuger:in\ngesucht)\nWhat\nelse\n?\nWir wollen einen positiven Impact auf unsere Erde haben. Deshalb streben wir danach, auf nachhaltige Weise Wert f\u00fcr alle Interessengruppen zu schaffen und ber\u00fccksichtigen dabei Klima, Ethik und Qualit\u00e4t. 2021 haben wir uns entschieden, eine Benefit Corporation zu werden, um unser langfristiges Engagement f\u00fcr den Schutz der Prinzipien und Werte, die unser Handeln leiten, zu unterstreichen.\nBewirb dich noch heute. Wir freuen uns darauf, dich kennenzulernen.\nBack\nApply\nShare this job:\nFacebook\nLinkedIn\nEmail",
        "application_url": "https://careers.jakala.com/en_US/careers/ApplicationMethods?jobId=2165",
        "": {},
        "metadata": {
            "Office": "Hamburg",
            "Country": "Germany",
            "Date Published": "27-Oct-2025",
            "Ref #": "2133",
            "Area": "IT and Information Systems",
            "Type of Presence": "Hybrid"
        },
        "link": "https://careers.jakala.com/en_US/careers/JobDetail/Agile-Coach-all-genders/2165"
    },
    {
        "title": "Experienced Professional | Buying Office (Loyalty)",
        "description_html": null,
        "description_text": "General information\nOffice\nNichelino\nCountry\nItaly\nDate Published\n24-Oct-2025\nRef #\n2132\nArea\nPurchasing\nType of Presence\nHybrid\nDescription & Requirements\n\ud83d\udccd\nSede\n:\nNichelino (TO)\n\ud83d\udc40\nRank:\nAssociate Manager, Manager\nChi siamo\nJAKALA \u00e8 un'azienda che lavora su dati, intelligenza artificiale e sviluppo di esperienze per generare un impatto significativo e duraturo a livello globale.\nPresenti in oltre 30 citt\u00e0 in 21 paesi,\ni nostri team\nuniscono competenze su strategia, tecnologia, creativit\u00e0 e\noperations\nper offrire esperienze personalizzate e soluzioni trasformative ai nostri clienti, grazie al supporto di dati e intelligenza artificiale. I\nJakalers\nsono un gruppo eterogeneo di oltre 3.000 persone, animate da passione, ambizione e idee brillanti. Proprio questa combinazione unica di talenti \u00e8 il fattore distintivo che ha ispirato il nostro\npurpose\n:\nTogether\nto\nget\nthere\n.\nCreare un mondo migliore \u00e8 il nostro obiettivo ultimo: la nostra ambizione \u00e8 generare valore per tutti i nostri stakeholder in modo sostenibile, con particolare attenzione a etica, clima e qualit\u00e0. Nel 2021, abbiamo scelto di diventare una Societ\u00e0 Benefit, dimostrando il nostro impegno di lungo periodo e la volont\u00e0 di proteggere i principi e i valori che ogni giorno guidano le nostre azioni.\nCrediamo che la diversit\u00e0 sia la chiave del nostro successo e, per questo, siamo impegnati a creare un ambiente di lavoro inclusivo, dove ciascuno possa sentirsi valorizzato per la propria unicit\u00e0. Tutte le nostre opportunit\u00e0 di lavoro sono aperte ai candidati appartenenti alle categorie protette L.68/99.\nScopri\nil team\nBuying\nIl team\nBuying\nsi occupa della selezione e dell\u2019acquisto dei prodotti per le campagne loyalty, garantendo un\u2019offerta ampia, di qualit\u00e0 e coerente con le esigenze del cliente. Collabora con fornitori e\nteam interni\nper lo sviluppo prodotti e definisce le condizioni commerciali di acquisto.\n\ud83c\udfaf Le tue responsabilit\u00e0:\nGestione e interazione con fornitori italiani ed esteri e con diversi stakeholder interni\nAcquisto dei materiali e servizi relativi alla categoria merceologica\nHouseware\n, ottimizzando prezzo/qualit\u00e0 nel rispetto delle procedure aziendali\nRichiesta quotazioni, analisi e confronto offerte, negoziazione strategica\nCoordinamento con ufficio Marketing per prototipazione e sviluppo di nuove linee di prodotti\nCoordinamento con il team Supply Chain e Compliance per garantire il rispetto delle condizioni e delle tempistiche concordate con il fornitore, cos\u00ec come dei requisiti di compliance\n\ud83d\ude4c Se\nti riconosci\nin queste caratteristiche, potremmo essere il perfetto match:\nEsperienza pregressa di almeno\n5\nanni in ruoli analoghi\nLaurea, master e studi affini ad economia, marketing e comunicazione\nBuona conoscenza dei principali strumenti del pacchetto MS Office\nOttima conoscenza di MS Excel\nOttima conoscenza della lingua inglese\nDisponibilit\u00e0 a trasferte, in Italia e all\u2019estero\nSpiccate capacit\u00e0 comunicative e interpersonali, orientamento al lavoro di squadra\nForte motivazione e ambizione di crescita professionale\nCuriosit\u00e0, proattivit\u00e0 e capacit\u00e0 di generare valore tangibile\nAttenzione all\u2019analisi tecnica del prodotto e delle soluzioni produttive\nCapacit\u00e0 di\nproblem\nsolving\n\ud83d\udc9c\nScopri in questo video le ragioni per cui scegliere JAKALA come prossimo step di carriera\nIn JAKALA crediamo che il tempo e il benessere delle persone vadano rispettati, sempre: incoraggiamo una presenza in ufficio di\n10\ngiorni al mese, lasciando piena libert\u00e0 di lavorare da dove preferisci, sia in Italia che all\u2019interno della Comunit\u00e0 Europea.\nIl nostro sistema di Total\nReward\ninclude convenzioni esclusive per viaggi, ristoranti, shopping, palestra e tempo libero, oltre a servizi gratuiti di telemedicina e supporto psicologico, pensati per te e per chi ami.\nInvestire nel nostro processo di selezione significa ricevere supporto autentico: un Recruiter dedicato ti accompagner\u00e0 con feedback personalizzati, consigli di carriera e insight sul tuo CV, a prescindere dall\u2019esito della candidatura. Niente AI, solo persone. E, grazie all\u2019iniziativa Your Time Back, ti restituiamo il tempo investito nei colloqui con un percorso di empowerment firmato\nUnobravo\n.\n\ud83c\udf31 Ready to start?\nNon \u00e8 solo una candidatura. \u00c8 un percorso che comincia ora. Inviaci il tuo CV: non vediamo l\u2019ora di conoscerti!\nBack\nApply\nShare this job:\nFacebook\nLinkedIn\nEmail",
        "application_url": "https://careers.jakala.com/en_US/careers/ApplicationMethods?jobId=2164",
        "": {},
        "metadata": {
            "Office": "Nichelino",
            "Country": "Italy",
            "Date Published": "24-Oct-2025",
            "Ref #": "2132",
            "Area": "Purchasing",
            "Type of Presence": "Hybrid"
        },
        "link": "https://careers.jakala.com/en_US/careers/JobDetail/Experienced-Professional-Buying-Office-Loyalty/2164"
    },
    {
        "title": "Experienced Professional | Client Strategy Telco",
        "description_html": null,
        "description_text": "General information\nOffice\nMilano\nCountry\nItaly\nDate Published\n22-Oct-2025\nRef #\n2126\nArea\nManagement Consulting\nType of Presence\nHybrid\nDescription & Requirements\n\ud83d\udccd\nSede\n: Milano\n\ud83d\udc40\nRank\n: Manager\nChi siamo\nJAKALA \u00e8 un'azienda che lavora su dati, intelligenza artificiale e sviluppo di esperienze per generare un impatto significativo e duraturo a livello globale.\nPresenti in oltre 30 citt\u00e0 in 21 paesi,\ni nostri team\nuniscono competenze su strategia, tecnologia, creativit\u00e0 e\noperations\nper offrire esperienze personalizzate e soluzioni trasformative ai nostri clienti, grazie al supporto di dati e intelligenza artificiale. I\nJakalers\nsono un gruppo eterogeneo di oltre 3.000 persone, animate da passione, ambizione e idee brillanti. Proprio questa combinazione unica di talenti \u00e8 il fattore distintivo che ha ispirato il nostro\npurpose\n:\nTogether\nto\nget\nthere\n.\nCreare un mondo migliore \u00e8 il nostro obiettivo ultimo: la nostra ambizione \u00e8 generare valore per tutti i nostri stakeholder in modo sostenibile, con particolare attenzione a etica, clima e qualit\u00e0. Nel 2021, abbiamo scelto di diventare una Societ\u00e0 Benefit, dimostrando il nostro impegno di lungo periodo e la volont\u00e0 di proteggere i principi e i valori che ogni giorno guidano le nostre azioni.\nCrediamo che la diversit\u00e0 sia la chiave del nostro successo e, per questo, siamo impegnati a creare un ambiente di lavoro inclusivo, dove ciascuno possa sentirsi valorizzato per la propria unicit\u00e0. Tutte le nostre opportunit\u00e0 di lavoro sono aperte ai candidati appartenenti alle categorie protette L.68/99.\nScopri\nil team\nClient Strategy\nTi appassiona lavorare con dati e insight per contribuire alla definizione di strategie di crescita dei clienti del settore\nTelco\n? Entrerai a far parte di\nun team multidisciplinare e dinamico\n,\ndove avrai l\u2019opportunit\u00e0 di lavorare su iniziative strategiche ad alto impatto volte a valorizzare il patrimonio informativo dei\nb\nrand\n.\nI\nl team\nClient Strategy \u00e8 il motore consulenziale di JAKALA: guida la progettazione strategica, la gestione operativa e lo sviluppo di nuove opportunit\u00e0 di business, trasformando insight, tecnologia e creativit\u00e0 in soluzioni su misura. Approfondirai tematiche legate al mondo Strategy &\nConsulting\ncon un approccio proattivo e data-\nd\nriven\n,\nall\u2019interno di un ambiente in continua evoluzione.\n\ud83c\udfaf Le tue responsabilit\u00e0:\nSupportare l\u2019implementazione di strategie commerciali e di crescita per clienti del settore Telco, contribuendo alla traduzione degli insight di mercato e degli obiettivi di business in piani operativi concreti e sostenibili.\nPreparare e presentare proposte di valore e soluzioni consulenziali, includendo analisi di mercato di base, business case e indicatori di performance, a supporto delle decisioni dei clienti e delle iniziative di sviluppo.\nGestire le relazioni con i clienti, garantendo il coordinamento delle attivit\u00e0 e l\u2019allineamento con le priorit\u00e0 definite.\nAgire come punto di riferimento strategico per stakeholder interni ed esterni, favorendo la collaborazione tra\nteam\ne assicurando la coerenza tra analisi, proposte e risultati attesi\n.\nContribuire al miglioramento dei modelli commerciali e delle metodologie di go-to-market, portando suggerimenti pratici e competenze specifiche per rafforzare la crescita e la fidelizzazione dei clienti.\n\ud83d\ude4c\nSe\nti riconosci\nin queste caratteristiche, potremmo essere il perfetto match:\nLaurea in discipline economiche, ingegneristiche o affini, con preferenza per indirizzi gestionali; eventuali master o corsi di specializzazione in ambito business o management rappresentano un valore aggiunto.\n5\u20137 anni di esperienza in societ\u00e0 di consulenza o aziende Telco, con coinvolgimento in attivit\u00e0 di business\ndevelopment\n, go-to-market, customer management o analisi di mercato.\nEsperienza nella gestione di\nteam\ne progetti cross-funzionali, con capacit\u00e0 di coordinare attivit\u00e0 operative e contribuire al raggiungimento degli obiettivi commerciali.\nBuone capacit\u00e0 di\nproblem\nsolving e di analisi, con attitudine a combinare dati quantitativi e osservazioni qualitative per supportare decisioni operative.\nSolide competenze comunicative e relazionali, con abilit\u00e0 nel gestire relazioni a livello executive e nel posizionarsi come\ntrusted\nadvisor presso i clienti.\nOttima padronanza del pacchetto Microsoft Office, in particolare Excel e PowerPoint, utilizzati per la costruzione di business case, modelli economici e presentazioni strategiche di livello direzionale.\nFluente conoscenza dell\u2019inglese e dell\u2019italiano; la conoscenza dello spagnolo o del francese rappresenta un plus.\nForte interesse per l\u2019innovazione e le dinamiche strategiche del settore Telco, con orientamento costante alla crescita del valore per il cliente e per l\u2019organizzazione.\n\ud83d\udc9c\nScopri nel video le ragioni per cui scegliere JAKALA come prossimo step di carriera\n:\nIn JAKALA crediamo che il tempo e il benessere delle persone vadano rispettati, sempre: incoraggiamo una presenza in ufficio di\n10\ngiorni al mese, lasciando piena libert\u00e0 di lavorare da dove preferisci, sia in Italia che all\u2019interno della Comunit\u00e0 Europea.\nIl nostro sistema di Total\nReward\ninclude convenzioni esclusive per viaggi, ristoranti, shopping, palestra e tempo libero, oltre a servizi gratuiti di telemedicina e supporto psicologico, pensati per te e per chi ami.\nInvestire nel nostro processo di selezione significa ricevere supporto autentico: un Recruiter dedicato ti accompagner\u00e0 con feedback personalizzati, consigli di carriera e insight sul tuo CV, a prescindere dall\u2019esito della candidatura. Niente AI, solo persone. E, grazie all\u2019iniziativa Your Time Back, ti restituiamo il tempo investito nei colloqui con un percorso di empowerment firmato\nUnobravo\n.\n\ud83c\udf31 Ready to start?\nNon \u00e8 solo una candidatura. \u00c8 un percorso che comincia ora. Inviaci il tuo CV: non vediamo l\u2019ora di conoscerti!\nBack\nApply\nShare this job:\nFacebook\nLinkedIn\nEmail",
        "application_url": "https://careers.jakala.com/en_US/careers/ApplicationMethods?jobId=2158",
        "": {},
        "metadata": {
            "Office": "Milano",
            "Country": "Italy",
            "Date Published": "22-Oct-2025",
            "Ref #": "2126",
            "Area": "Management Consulting",
            "Type of Presence": "Hybrid"
        },
        "link": "https://careers.jakala.com/en_US/careers/JobDetail/Experienced-Professional-Client-Strategy-Telco/2158"
    },
    {
        "title": "Experienced Professional | Solution Architect Adobe Experience Manager",
        "description_html": null,
        "description_text": "General information\nOffice\nMilano, Napoli, Roma, Roncade\nCountry\nItaly\nDate Published\n15-Oct-2025\nRef #\n2117\nArea\nManagement Consulting\nType of Presence\nHybrid\nDescription & Requirements\n\ud83d\udccd\nSede\n: Milano, Roncade, Roma, Napoli, Rende\n\ud83d\udc40\nRank:\nExpert Lead\nChi siamo\nJAKALA \u00e8 un'azienda che lavora su dati, intelligenza artificiale e sviluppo di esperienze per generare un impatto significativo e duraturo a livello globale.\nPresenti in oltre 30 citt\u00e0 in 21 paesi, i nostri team uniscono competenze su strategia, tecnologia, creativit\u00e0 e operations per offrire esperienze personalizzate e soluzioni trasformative ai nostri clienti, grazie al supporto di dati e intelligenza artificiale. I Jakalers sono un gruppo eterogeneo di oltre 3.000 persone, animate da passione, ambizione e idee brillanti. Proprio questa combinazione unica di talenti \u00e8 il fattore distintivo che ha ispirato il nostro purpose: Together to get there.\nCreare un mondo migliore \u00e8 il nostro obiettivo ultimo: la nostra ambizione \u00e8 generare valore per tutti i nostri stakeholder in modo sostenibile, con particolare attenzione a etica, clima e qualit\u00e0. Nel 2021, abbiamo scelto di diventare una Societ\u00e0 Benefit, dimostrando il nostro impegno di lungo periodo e la volont\u00e0 di proteggere i principi e i valori che ogni giorno guidano le nostre azioni.\nCrediamo che la diversit\u00e0 sia la chiave del nostro successo e, per questo, siamo impegnati a creare un ambiente di lavoro inclusivo, dove ciascuno possa sentirsi valorizzato per la propria unicit\u00e0. Tutte le nostre opportunit\u00e0 di lavoro sono aperte ai candidati appartenenti alle categorie protette L.68/99.\nScopri il team Commerce & Enabling Solutions\nTi appassionano la progettazione di soluzioni digitali e le tecnologie Adobe? All\u2019interno della Service Line Commerce & Enabling Solutions di JAKALA lavoriamo per creare esperienze digitali innovative, integrando strategia, design e tecnologia per supportare la crescita dei nostri clienti.\nCome Solution Architect AEM, avrai un ruolo chiave nella progettazione e implementazione di soluzioni basate su Adobe Experience Manager, collaborando con team di sviluppo, business analyst e stakeholder per definire architetture solide, scalabili e in linea con le best practice di settore.\n\ud83c\udfaf\nLe tue responsabilit\u00e0:\nRivestirai il ruolo di AEM Architect all\u2019interno del team di progetto, supervisionando e validando tutte le implementazioni tecniche sulla piattaforma Adobe Experience Manager.\nCollaborerai con il Project Manager nella gestione della relazione con il cliente, traducendo i requisiti di business in architetture tecniche solide, coerenti e scalabili.\nCondurrai technical assessment indipendenti sulle soluzioni proposte dai fornitori, individuando rischi, inefficienze e opportunit\u00e0 di miglioramento, assicurando la conformit\u00e0 agli standard e alle best practice.\nGuiderai il team tecnico nella definizione di standard architetturali, linee guida di sviluppo e pattern di implementazione AEM, garantendo coerenza e qualit\u00e0 nei deliverable.\nPromuoverai il knowledge sharing e farai da mentor ai team pi\u00f9 junior, operando anche presso le sedi dei clienti per assicurare un allineamento costante sugli aspetti tecnici e strategici del progetto.\n\ud83d\udca1\nSe ti riconosci in queste caratteristiche, potremmo essere il perfetto match:\n8-10 anni di esperienza pregressa come Solution Architect/ PM su tecnologia AEM\nCertificazione Adobe\nCompetenza tecnica completa (Sites, Assets, integrazione, performance, security)\nSoft skills comunicative eccellenti\nCarisma e capacit\u00e0 di challenge costruttivo\nConoscenza fluente dell'inglese\nDisponibilit\u00e0 a trasferte\n\ud83d\udc9c\nScopri in questo video le ragioni per cui scegliere JAKALA come prossimo step di carriera\nIn JAKALA crediamo che il tempo e il benessere delle persone vadano rispettati, sempre: incoraggiamo una presenza in ufficio di\n10\ngiorni al mese, lasciando piena libert\u00e0 di lavorare da dove preferisci, sia in Italia che all\u2019interno della Comunit\u00e0 Europea.\nIl nostro sistema di Total\nReward i\nnclude convenzioni esclusive per viaggi, ristoranti, shopping, palestra e tempo libero, oltre a servizi gratuiti di telemedicina e supporto psicologico, pensati per te e per chi ami.\nInvestire nel nostro processo di selezione significa ricevere supporto autentico: un Recruiter dedicato ti accompagner\u00e0 con feedback personalizzati, consigli di carriera e insight sul tuo CV, a prescindere dall\u2019esito della candidatura. Niente AI, solo persone. E, grazie all\u2019iniziativa Your Time Back, ti restituiamo il tempo investito nei colloqui con un percorso di empowerment firmato\nUnobravo\n.\n\ud83c\udf31\nReady to start?\nIl ruolo \u00e8 solo il punto di partenza. Il resto lo metti tu. Inviaci il tuo CV, noi non vediamo l\u2019ora di conoscerti!\nBack\nApply\nShare this job:\nFacebook\nLinkedIn\nEmail",
        "application_url": "https://careers.jakala.com/en_US/careers/ApplicationMethods?jobId=2149",
        "": {},
        "metadata": {
            "Office": "Milano, Napoli, Roma, Roncade",
            "Country": "Italy",
            "Date Published": "15-Oct-2025",
            "Ref #": "2117",
            "Area": "Management Consulting",
            "Type of Presence": "Hybrid"
        },
        "link": "https://careers.jakala.com/en_US/careers/JobDetail/Experienced-Professional-Solution-Architect-Adobe-Experience-Manager/2149"
    },
    {
        "title": "Experienced Professional | Machine Learning Engineer (J-Science)",
        "description_html": null,
        "description_text": "General information\nOffice\nMilano, Roma\nCountry\nItaly\nDate Published\n09-Oct-2025\nRef #\n2108\nArea\nIT and Information Systems\nType of Presence\nHybrid\nDescription & Requirements\n\ud83d\udccd\nSede\n: Milano, Roma\n\ud83d\udc40\nRank: Senior Consultant\nChi siamo\nJAKALA \u00e8 un'azienda che lavora su dati, intelligenza artificiale e sviluppo di esperienze per generare un impatto significativo e duraturo a livello globale.\nPresenti in oltre 30 citt\u00e0 in 21 paesi, i nostri team uniscono competenze su strategia, tecnologia, creativit\u00e0 e operations per offrire esperienze personalizzate e soluzioni trasformative ai nostri clienti, grazie al supporto di dati e intelligenza artificiale. I Jakalers sono un gruppo eterogeneo di oltre 3.000 persone, animate da passione, ambizione e idee brillanti. Proprio questa combinazione unica di talenti \u00e8 il fattore distintivo che ha ispirato il nostro purpose: Together to get there.\nCreare un mondo migliore \u00e8 il nostro obiettivo ultimo: la nostra ambizione \u00e8 generare valore per tutti i nostri stakeholder in modo sostenibile, con particolare attenzione a etica, clima e qualit\u00e0. Nel 2021, abbiamo scelto di diventare una Societ\u00e0 Benefit, dimostrando il nostro impegno di lungo periodo e la volont\u00e0 di proteggere i principi e i valori che ogni giorno guidano le nostre azioni.\nCrediamo che la diversit\u00e0 sia la chiave del nostro successo e, per questo, siamo impegnati a creare un ambiente di lavoro inclusivo, dove ciascuno possa sentirsi valorizzato per la propria unicit\u00e0. Tutte le nostre opportunit\u00e0 di lavoro sono aperte ai candidati appartenenti alle categorie protette L.68/99.\nScopri il team J-Science\nTi appassionano i dati, l\u2019intelligenza artificiale e il linguaggio naturale? Nel team J-Science di JAKALA lavoriamo ogni giorno per trasformare queste tecnologie in soluzioni concrete e ad alto impatto per le aziende.\nSiamo un centro di eccellenza con sedi a Milano, Torino, Rende e Roma, e ci occupiamo di Data Science, Location Intelligence, Large Natural Language Models e sviluppo di piattaforme, progettando software avanzati con tecnologia all'avanguardia.\nDall\u2019AI applicata a testo e voce alla semantic search, passando per speech technology e predictive analytics: innoviamo per creare valore reale e accessibile, in contesti complessi e sfidanti. Per le nostre sedi di Milano e Roma siamo alla ricerca di una risorsa che si occuper\u00e0 dell\u2019industrializzazione di modelli di Machine Learning e soluzioni di Generative AI.\n\ud83c\udfaf\nLe tue responsabilit\u00e0:\nSupporto alla progettazione e implementazione di soluzioni cloud-based basate su modelli di Machine Learning e/o GenAI.\nCollaborare con data scientist e data engineer per integrare i modelli sviluppati e validati all\u2019interno delle Cloud Data Platform dei clienti.\nTrasformazione del codice sperimentale in soluzioni scalabili e production-ready secondo best practice di sviluppo software.\nDeployment in produzione dei modelli e gestione del loro ciclo di vita (monitoraggio, manutenzione, retraining).\nContributo alla definizione di pipeline MLOps e workflow di automazione.\n\ud83d\ude4c\nSe\nti riconosci in queste caratteristiche, potremmo essere il perfetto match:\nLaurea Triennale/Magistrale in Informatica, Ingegneria Informatica o discipline affini.\n1\u20134 anni di esperienza in ruoli simili.\nFamiliarit\u00e0 con metodologie di sviluppo software (e.g. version control, CI/CD...).\nOttima conoscenza di Python e programmazione a oggetti.\nEsperienza con sistemi di versionamento del codice (Git).\nEsperienza con librerie ML/AI (TensorFlow, PyTorch, scikit-learn).\nEsperienza di deployment in almeno uno dei principali cloud provider (AWS, GCP, Azure).\nConoscenza di tecnologie container-based (Docker, Kubernetes).\nConoscenza strumenti di Infrastructure as Code (e.g. Terraform, CloudFormation).\nConoscenza framework Python API (FastAPI, Flask, Django).\nEsperienza con database relazionali; gradita la conoscenza dei non-relazionali.\nConoscenza ed esperienza con Spark o altri framework di big data processing.\nFamiliarit\u00e0 con pratiche di MLOps avanzate (monitoraggio dei modelli, feature store, explainability).\nEsperienza in GenAI e LLM (e.g. LangChain, Hugging Face, RAG pattern).\n\ud83d\udc9c\nScopri in questo video le ragioni per cui scegliere JAKALA come prossimo step di carriera\nIn JAKALA crediamo che il tempo e il benessere delle persone vadano rispettati, sempre: incoraggiamo una presenza in ufficio di\n10\ngiorni al mese, lasciando piena libert\u00e0 di lavorare da dove preferisci, sia in Italia che all\u2019interno della Comunit\u00e0 Europea.\nIl nostro sistema di Total\nReward\ninclude convenzioni esclusive per viaggi, ristoranti, shopping, palestra e tempo libero, oltre a servizi gratuiti di telemedicina e supporto psicologico, pensati per te e per chi ami.\nInvestire nel nostro processo di selezione significa ricevere supporto autentico: un Recruiter dedicato ti accompagner\u00e0 con feedback personalizzati, consigli di carriera e insight sul tuo CV, a prescindere dall\u2019esito della candidatura. Niente AI, solo persone. E, grazie all\u2019iniziativa Your Time Back, ti restituiamo il tempo investito nei colloqui con un percorso di empowerment firmato\nUnobravo\n.\n\ud83c\udf31 Ready to start?\nNon \u00e8 solo una candidatura. \u00c8 un percorso che comincia ora. Inviaci il tuo CV: non vediamo l\u2019ora di conoscerti!\nBack\nApply\nShare this job:\nFacebook\nLinkedIn\nEmail",
        "application_url": "https://careers.jakala.com/en_US/careers/ApplicationMethods?jobId=2140",
        "": {},
        "metadata": {
            "Office": "Milano, Roma",
            "Country": "Italy",
            "Date Published": "09-Oct-2025",
            "Ref #": "2108",
            "Area": "IT and Information Systems",
            "Type of Presence": "Hybrid"
        },
        "link": "https://careers.jakala.com/en_US/careers/JobDetail/Experienced-Professional-Machine-Learning-Engineer-J-Science/2140"
    },
    {
        "title": "Experienced Professional | Financial Reporting",
        "description_html": null,
        "description_text": "General information\nOffice\nNichelino\nCountry\nItaly\nDate Published\n06-Oct-2025\nRef #\n2104\nArea\nFinance\nType of Presence\nHybrid\nDescription & Requirements\n\ud83d\udccd\nSede\n:\nNichelino (TO)\n\ud83d\udc40\nRank:\nAssociate Manager\nChi siamo\nJAKALA \u00e8 un'azienda che lavora su dati, intelligenza artificiale e sviluppo di esperienze per generare un impatto significativo e duraturo a livello globale.\nPresenti in oltre 30 citt\u00e0 in 21 paesi,\ni nostri team\nuniscono competenze su strategia, tecnologia, creativit\u00e0 e\noperations\nper offrire esperienze personalizzate e soluzioni trasformative ai nostri clienti, grazie al supporto di dati e intelligenza artificiale. I\nJakalers\nsono un gruppo eterogeneo di oltre 3.000 persone, animate da passione, ambizione e idee brillanti. Proprio questa combinazione unica di talenti \u00e8 il fattore distintivo che ha ispirato il nostro\npurpose\n:\nTogether\nto\nget\nthere\n.\nCreare un mondo migliore \u00e8 il nostro obiettivo ultimo: la nostra ambizione \u00e8 generare valore per tutti i nostri stakeholder in modo sostenibile, con particolare attenzione a etica, clima e qualit\u00e0. Nel 2021, abbiamo scelto di diventare una Societ\u00e0 Benefit, dimostrando il nostro impegno di lungo periodo e la volont\u00e0 di proteggere i principi e i valori che ogni giorno guidano le nostre azioni.\nCrediamo che la diversit\u00e0 sia la chiave del nostro successo e, per questo, siamo impegnati a creare un ambiente di lavoro inclusivo, dove ciascuno possa sentirsi valorizzato per la propria unicit\u00e0. Tutte le nostre opportunit\u00e0 di lavoro sono aperte ai candidati appartenenti alle categorie protette L.68/99.\nScopri\nil team\nFinancial Reporting\nIl team\nFinancial Reporting \u00e8 responsabile del processo di chiusura mensile, garantendo accuratezza e rispetto delle scadenze lungo tutto il processo. Collabora in modo trasversale con molte funzioni aziendali.\n\ud83c\udfaf Le tue responsabilit\u00e0:\nPredisposizione del consolidato mensile secondo i principi contabili IAS/IFRS, utilizzando il software di consolidamento TAGETIK e dove disponibili i dati dall\u2019ERP SAP (in alternativa dai reporting package delle filiali)\nRiconciliazione e analisi dei\nmonthly\nreport ricevuti dalle\nsubsidiaries\ne relazione team\nfinance\ninternazionali e\nprofessionisti locali\nesteri\nPredisposizione e analisi mensili del cash flow indiretto e dell\u2019andamento dell\u2019Operating Working Capital\nSupporto alla predisposizione dell\u2019Information\nundertakings\ne della reportistica mensile ai\nLenders\ndel Senior\nLoan\nPredisposizione del consolidato annuale civilistico secondo i principi contabili IAS/IFRS e supporto alla redazione delle note illustrative\n\ud83d\ude4c Se\nti riconosci\nin queste caratteristiche, potremmo essere il perfetto match:\nEsperienza pregressa di almeno\n5\nanni nel ruolo\nLaurea in Economia, o affini\nConoscenza approfondita dei principi contabili IAS/IFRS;\nExpertise in consolidati internazionali complessi (profit in stock, allocazione dei margini per country\ndestination\n)\nConoscenza del software TAGETIK e dell\u2019ERP SAP\nFluente conoscenza della lingua inglese\nDimestichezza nell\u2019utilizzo del pacchetto Office\nCapacit\u00e0 di analizzare le cause sottostanti alle performance del business\nUn approccio fortemente analitico e capacit\u00e0 di\nproblem\nsolving\nL\u2019esperienza pregressa in societ\u00e0 di consulenza sar\u00e0 considerata un plus\n\ud83d\udc9c\nScopri in questo video le ragioni per cui scegliere JAKALA per il tuo prossimo step di carriera\nIn JAKALA crediamo che il tempo e il benessere delle persone vadano rispettati, sempre: incoraggiamo una presenza in ufficio di\n10\ngiorni al mese, lasciando piena libert\u00e0 di lavorare da dove preferisci, sia in Italia che all\u2019interno della Comunit\u00e0 Europea.\nIl nostro sistema di Total\nReward\ninclude convenzioni esclusive per viaggi, ristoranti, shopping, palestra e tempo libero, oltre a servizi gratuiti di telemedicina e supporto psicologico, pensati per te e per chi ami.\nInvestire nel nostro processo di selezione significa ricevere supporto autentico: un Recruiter dedicato ti accompagner\u00e0 con feedback personalizzati, consigli di carriera e insight sul tuo CV, a prescindere dall\u2019esito della candidatura. Niente AI, solo persone. E, grazie all\u2019iniziativa Your Time Back, ti restituiamo il tempo investito nei colloqui con un percorso di empowerment firmato\nUnobravo\n.\n\ud83c\udf31 Ready to start?\nNon \u00e8 solo una candidatura. \u00c8 un percorso che comincia ora. Inviaci il tuo CV: non vediamo l\u2019ora di conoscerti!\nBack\nApply\nShare this job:\nFacebook\nLinkedIn\nEmail",
        "application_url": "https://careers.jakala.com/en_US/careers/ApplicationMethods?jobId=2136",
        "": {},
        "metadata": {
            "Office": "Nichelino",
            "Country": "Italy",
            "Date Published": "06-Oct-2025",
            "Ref #": "2104",
            "Area": "Finance",
            "Type of Presence": "Hybrid"
        },
        "link": "https://careers.jakala.com/en_US/careers/JobDetail/Experienced-Professional-Financial-Reporting/2136"
    },
    {
        "title": "Experienced Professional | Global Service Procurement Specialist",
        "description_html": null,
        "description_text": "General information\nOffice\nMilano\nCountry\nItaly\nDate Published\n03-Oct-2025\nRef #\n2103\nArea\nHuman Resources\nType of Presence\nHybrid\nDescription & Requirements\n\ud83d\udccd\nSede\n: Milano\n\ud83d\udc40\nRank:\nSenior Consultant\nChi siamo\nJAKALA \u00e8 un'azienda che lavora su dati, intelligenza artificiale e sviluppo di esperienze per generare un impatto significativo e duraturo a livello globale.\nPresenti in oltre 30 citt\u00e0 in 21 paesi, i nostri team uniscono competenze su strategia, tecnologia, creativit\u00e0 e operations per offrire esperienze personalizzate e soluzioni trasformative ai nostri clienti, grazie al supporto di dati e intelligenza artificiale. I Jakalers sono un gruppo eterogeneo di oltre 3.000 persone, animate da passione, ambizione e idee brillanti. Proprio questa combinazione unica di talenti \u00e8 il fattore distintivo che ha ispirato il nostro purpose: Together to get there.\nCreare un mondo migliore \u00e8 il nostro obiettivo ultimo: la nostra ambizione \u00e8 generare valore per tutti i nostri stakeholder in modo sostenibile, con particolare attenzione a etica, clima e qualit\u00e0. Nel 2021, abbiamo scelto di diventare una Societ\u00e0 Benefit, dimostrando il nostro impegno di lungo periodo e la volont\u00e0 di proteggere i principi e i valori che ogni giorno guidano le nostre azioni.\nCrediamo che la diversit\u00e0 sia la chiave del nostro successo e, per questo, siamo impegnati a creare un ambiente di lavoro inclusivo, dove ciascuno possa sentirsi valorizzato per la propria unicit\u00e0. Tutte le nostre opportunit\u00e0 di lavoro sono aperte ai candidati appartenenti alle categorie protette L.68/99.\nScopri il team Global Service Procurement\nSei una persona organizzata, precisa e ti interessa il mondo degli acquisti? Nel team Global Service Procurement di JAKALA gestiamo l\u2019intero ciclo di acquisto, dai fornitori alla rendicontazione, contribuendo all\u2019efficienza e all\u2019ottimizzazione dei processi interni. In qualit\u00e0 di Procurement Specialist ricoprirai un ruolo fondamentale nella gestione e nell\u2019ottimizzazione dei processi di acquisto di servizi, a livello nazionale e globale.\n\ud83c\udfaf\nLe tue responsabilit\u00e0:\nGestione Fornitori: selezionerai, gestirai e interagirai con fornitori nazionali e internazionali, monitorando le prestazioni e risolvendo eventuali problematiche;\nTrattative: condurrai trattative efficaci per ottenere le migliori condizioni contrattuali e commerciali, volte al raggiungimento degli obiettivi progettuali;\nInnovazione di processi e sistemi: contribuirai all\u2019implementazione di soluzioni digitali e innovative per migliorare l\u2019efficienza e l\u2019efficacia di processi di direct e indirect procurement,\nAttivit\u00e0 di Backoffice: gestirai le attivit\u00e0 amministrative legate ai processi di acquisto, garantendo l\u2019accuratezza e la puntualit\u00e0 dei documenti interni.\n\ud83d\udca1\nSe ti riconosci in queste caratteristiche, potremmo essere il perfetto match:\n2-3 anni di esperienza, preferibilmente maturata presso societ\u00e0 di consulenza o multinazionali;\nConoscenza dei processi di acquisto di servizi e familiarit\u00e0 con le metodologie di gestione degli acquisti digitali;\nPregressa esperienza nell\u2019utilizzo di SAP e/o di altri sistemi ERP;\nOttima conoscenza della lingua inglese (livello C1),\nBuone capacit\u00e0 comunicative e un forte orientamento al cliente per interagire con successo con stakeholder interni ed esterni.\nPregressa esperienza in attivit\u00e0 di Project Management, attitudine all\u2019innovazione e proposta di soluzioni migliorative;\nOttima conoscenza del pacchetto Microsoft Office;\nConoscenza di una seconda lingua (spagnolo, tedesco e/o francese),\nSpiccate capacit\u00e0 di analisi quantitativa, qualitativa e problem solving.\n\ud83d\udc9c\nScopri in questo video le ragioni per cui scegliere JAKALA come prossimo step di carriera\nIn JAKALA crediamo che il tempo e il benessere delle persone vadano rispettati, sempre: incoraggiamo una presenza in ufficio di10giorni al mese, lasciando piena libert\u00e0 di lavorare da dove preferisci, sia in Italia che all\u2019interno della Comunit\u00e0 Europea.\nIl nostro sistema di Total\u00a0Reward\u00a0include convenzioni esclusive per viaggi, ristoranti, shopping, palestra e tempo libero, oltre a servizi gratuiti di telemedicina e supporto psicologico, pensati per te e per chi ami.\nInvestire nel nostro processo di selezione significa ricevere supporto autentico: un Recruiter dedicato ti accompagner\u00e0 con feedback personalizzati, consigli di carriera e insight sul tuo CV, a prescindere dall\u2019esito della candidatura. Niente AI, solo persone. E, grazie all\u2019iniziativa Your Time Back, ti restituiamo il tempo investito nei colloqui con un percorso di empowerment firmato Unobravo.\n\ud83c\udf31\nReady to start?\nNon \u00e8 solo una candidatura. \u00c8 un percorso che comincia ora. Inviaci il tuo CV: non vediamo l\u2019ora di conoscerti!\nBack\nApply\nShare this job:\nFacebook\nLinkedIn\nEmail",
        "application_url": "https://careers.jakala.com/en_US/careers/ApplicationMethods?jobId=2135",
        "": {},
        "metadata": {
            "Office": "Milano",
            "Country": "Italy",
            "Date Published": "03-Oct-2025",
            "Ref #": "2103",
            "Area": "Human Resources",
            "Type of Presence": "Hybrid"
        },
        "link": "https://careers.jakala.com/en_US/careers/JobDetail/Experienced-Professional-Global-Service-Procurement-Specialist/2135"
    },
    {
        "title": "Intern | Solution Design",
        "description_html": null,
        "description_text": "General information\nOffice\nRoncade\nCountry\nItaly\nDate Published\n03-Oct-2025\nRef #\n2148\nArea\nIT and Information Systems\nType of Presence\nHybrid\nDescription & Requirements\n\ud83d\udccd\nSede\n: Roncade\nChi siamo\nJAKALA \u00e8 un'azienda che lavora su dati, intelligenza artificiale e sviluppo di esperienze per generare un impatto significativo e duraturo a livello globale.\nPresenti in oltre 30 citt\u00e0 in 21 paesi, i nostri team uniscono competenze su strategia, tecnologia, creativit\u00e0 e operations per offrire esperienze personalizzate e soluzioni trasformative ai nostri clienti, grazie al supporto di dati e intelligenza artificiale. I Jakalers sono un gruppo eterogeneo di oltre 3.000 persone, animate da passione, ambizione e idee brillanti. Proprio questa combinazione unica di talenti \u00e8 il fattore distintivo che ha ispirato il nostro purpose: Together to get there.\nCreare un mondo migliore \u00e8 il nostro obiettivo ultimo: la nostra ambizione \u00e8 generare valore per tutti i nostri stakeholder in modo sostenibile, con particolare attenzione a etica, clima e qualit\u00e0. Nel 2021, abbiamo scelto di diventare una Societ\u00e0 Benefit, dimostrando il nostro impegno di lungo periodo e la volont\u00e0 di proteggere i principi e i valori che ogni giorno guidano le nostre azioni.\nCrediamo che la diversit\u00e0 sia la chiave del nostro successo e, per questo, siamo impegnati a creare un ambiente di lavoro inclusivo, dove ciascuno possa sentirsi valorizzato per la propria unicit\u00e0. Tutte le nostre opportunit\u00e0 di lavoro sono aperte ai candidati appartenenti alle categorie protette L.68/99.\nScopri il team Solution Design\nSei pronto/a a mettere la tua passione per il tech al servizio di progetti innovativi? Questa \u00e8 l\u2019occasione perfetta per iniziare il tuo percorso professionale in un team strategico orientato alla progettazione di soluzioni digitali per aziende globali.\nNel team Solution Design trasformiamo i brief dei clienti in architetture tecnologiche avanzate, integrando piattaforme enterprise e collaborando con diverse funzioni. Lavoriamo su 7 industry e 22 mercati, progettando soluzioni su misura che generano valore reale e misurabile.\n\ud83c\udfaf\nOgni giorno sar\u00e0 diverso, ma eccoti un assaggio di quello che ti aspetta\nAnalisi di brief provenienti da clienti nazionali e internazionali per comprendere bisogni, requisiti e opportunit\u00e0 tecnologiche\nSupporto al disegno e alla progettazione di soluzioni digitali su misura in ambito CMS, eCommerce (con focus anche su Shopify), CRM, PIM, DAM e CDP\nAttivit\u00e0 di scouting e valutazione di tecnologie emergenti, sperimentando piattaforme e software leader di mercato\nSupporto alle attivit\u00e0 di presales, contribuendo alla definizione di soluzioni, stime e quotazioni economiche\nContributo alla preparazione di presentazioni e materiali progettuali ad alto impatto comunicativo\nCollaborazione con team multidisciplinari per la definizione di proposte innovative\nSupporto alle sessioni di presentazione delle soluzioni ai clienti\n\ud83d\udca1\nQueste caratteristiche sono un ottimo punto di partenza per crescere insieme\nLaurea o percorso di studi in Economia o materie STEM (preferibile)\nPassione per la tecnologia e desiderio di sperimentare con software e piattaforme digitali\nAttitudine all\u2019analisi e al problem solving con mindset strategico\nCapacit\u00e0 di comunicare in modo chiaro, sia nella produzione di presentazioni sia nella relazione con interlocutori interni\nConoscenza dell\u2019inglese e buona padronanza di Excel e PowerPoint\n\ud83d\ude80\nCi brillano gli occhi se hai anche\nInteresse verso strumenti AI driven e tecnologie eCommerce come Shopify\n\ud83d\udcac\nCosa dicono di noi?\nEcco i fattori chiave che spingono colleghe e colleghi a sceglierci ogni giorno:\nFlessibilit\u00e0 e smart working:\nin JAKALA crediamo nel work-life balance. Per questo, abbiamo deciso di incoraggiare la presenza in ufficio per 10 giorni al mese, da scegliere autonomamente in base alle tue esigenze.\nTotal Reward\ncreato per te (e per chi ami):\nin JAKALA offriamo un Total Reward personalizzato, ricco di iniziative pensate per migliorare la qualit\u00e0 della vita dentro e fuori dall\u2019ufficio, non solo per te ma anche per le persone che ti stanno a cuore.\u00a0Tra i benefit troverai accesso gratuito a servizi di telemedicina e supporto psicologico, perch\u00e9 prendersi cura di s\u00e9 \u00e8 fondamentale. E poi ancora sconti su viaggi, ristoranti, shopping, palestra e tante altre esperienze per vivere al meglio il tuo tempo libero.\nCrescita e formazione continua:\nlavorerai a fianco di team esperti che ti guideranno e ti aiuteranno a sviluppare nuove competenze e a crescere professionalmente. Ogni giorno avrai la possibilit\u00e0 di apprendere, ricevere feedback costruttivi e applicare le tue idee in un ambiente stimolante.\n\ud83d\udc9c\nIl nostro impegno verso di te inizia ora\nSe investi tempo nel nostro percorso di Recruiting, avrai tutto il nostro impegno. E oltre.\nLa tua candidatura verr\u00e0 presa in carico da un Recruiter del nostro Team Talent Acquisition, che esaminer\u00e0 il tuo CV e le informazioni fornite. Sar\u00e0 poi il tuo Recruiter di riferimento a ricontattarti per condividere il nostro feedback, indipendentemente dall\u2019esito. Riceverai sempre suggerimenti per ottimizzare il tuo CV, spunti per consolidare il tuo percorso di carriera e insight sull\u2019arena competitiva in cui operi.\nNiente AI\n: lo facciamo a mano, con il cuore, per te.\nOgni ora che investirai per conoscere\nJAKALA\n, te la restituiamo per conoscerti meglio: grazie all\u2019iniziativa\nYour Time Back\ne alla nostra partnership con\nUnobravo\n, hai diritto a un percorso di empowerment con sessioni equivalenti al numero di interviste sostenute. Potrai spenderle come meglio credi. Sappiamo che cercare lavoro pu\u00f2 essere sfidante, e siamo qui per supportarti, anche se ancora non ci conosciamo.\n\ud83c\udf31\nReady to start?\nIl ruolo \u00e8 solo il punto di partenza. Il resto lo metti tu. Inviaci il tuo CV, noi non vediamo l\u2019ora di conoscerti!\nBack\nApply\nShare this job:\nFacebook\nLinkedIn\nEmail",
        "application_url": "https://careers.jakala.com/en_US/careers/ApplicationMethods?jobId=2180",
        "": {},
        "metadata": {
            "Office": "Roncade",
            "Country": "Italy",
            "Date Published": "03-Oct-2025",
            "Ref #": "2148",
            "Area": "IT and Information Systems",
            "Type of Presence": "Hybrid"
        },
        "link": "https://careers.jakala.com/en_US/careers/JobDetail/Intern-Solution-Design/2180"
    },
    {
        "title": "Experienced Professional | Client Strategy Energy",
        "description_html": null,
        "description_text": "General information\nOffice\nMilano\nCountry\nItaly\nDate Published\n26-Sep-2025\nRef #\n2089\nArea\nManagement Consulting\nType of Presence\nHybrid\nDescription & Requirements\n\ud83d\udccd\nSede\n: Milano\n\ud83d\udc40 Rank: Senior Consultant\nChi siamo\nJAKALA \u00e8 un'azienda che lavora su dati, intelligenza artificiale e sviluppo di esperienze per generare un impatto significativo e duraturo a livello globale.\nPresenti in oltre 30 citt\u00e0 in 21 paesi, i nostri team uniscono competenze su strategia, tecnologia, creativit\u00e0 e operations per offrire esperienze personalizzate e soluzioni trasformative ai nostri clienti, grazie al supporto di dati e intelligenza artificiale. I Jakalers sono un gruppo eterogeneo di oltre 3.000 persone, animate da passione, ambizione e idee brillanti. Proprio questa combinazione unica di talenti \u00e8 il fattore distintivo che ha ispirato il nostro purpose: Together to get there.\nCreare un mondo migliore \u00e8 il nostro obiettivo ultimo: la nostra ambizione \u00e8 generare valore per tutti i nostri stakeholder in modo sostenibile, con particolare attenzione a etica, clima e qualit\u00e0. Nel 2021, abbiamo scelto di diventare una Societ\u00e0 Benefit, dimostrando il nostro impegno di lungo periodo e la volont\u00e0 di proteggere i principi e i valori che ogni giorno guidano le nostre azioni.\nCrediamo che la diversit\u00e0 sia la chiave del nostro successo e, per questo, siamo impegnati a creare un ambiente di lavoro inclusivo, dove ciascuno possa sentirsi valorizzato per la propria unicit\u00e0. Tutte le nostre opportunit\u00e0 di lavoro sono aperte ai candidati appartenenti alle categorie protette L.68/99.\nScopri il team Client Strategy Energy\nTi appassiona lavorare con dati e insight per contribuire alla definizione di strategie di crescita dei clienti del settore\nEnergy\n? Entrerai a far parte di un team multidisciplinare e dinamico, dove avrai l\u2019opportunit\u00e0 di lavorare su iniziative strategiche ad alto impatto volte a valorizzare il patrimonio informativo dei brand. Il team Client Strategy \u00e8 il motore consulenziale di JAKALA: guida la progettazione strategica, la gestione operativa e lo sviluppo di nuove opportunit\u00e0 di business, trasformando insight, tecnologia e creativit\u00e0 in soluzioni su misura. Approfondirai tematiche legate al mondo Strategy & Consulting con un approccio proattivo e data-driven, all\u2019interno di un ambiente in continua evoluzione.\n\ud83c\udfaf Le tue responsabilit\u00e0:\nGuidare la definizione e l\u2019implementazione di strategie di crescita per i clienti del settore Energy, integrando analisi di mercato, insight e obiettivi di business\nSviluppare e presentare deliverable consulenziali di alto livello (analisi di mercato, definizione di KPI, business case) a supporto delle decisioni del cliente\nInteragire in maniera proattiva con stakeholder interni ed esterni, garantendo allineamento tra insight analitici, proposte strategiche e obiettivi di business del cliente\nContribuire al miglioramento continuo di metodologie, framework e strumenti di analisi, apportando know-how specialistico al team\nGestire la relazione con i principali stakeholder, diventando punto di riferimento per il cliente e garantendo l\u2019allineamento tra obiettivi strategici e risultati operativi\n\ud83d\ude4c\nSe ti riconosci in queste caratteristiche, potremmo essere il perfetto match:\nLaurea preferibilmente in materie economiche o ingegneristiche\nDai 3 ai 7 anni di esperienza in societ\u00e0 di consulenza strategiche o in aziende del settore energy, preferibilmente su uno o pi\u00f9 dei seguenti ambiti: Customer Strategy & Go to Market; Customer Value Management, o Customer Analytics\nOttima conoscenza del pacchetto Microsoft Office (in particolare, Excel e PowerPoint)\nEsperienza nella gestione di team e/o progetti complessi, capacit\u00e0 di leadership e orientamento al risultato\nCapacit\u00e0 di problem solving e di coniugare analisi qualitative e business driven con analisi quantitative della customer base\nOttime capacit\u00e0 di comunicazione, presentazione e gestione della relazione con stakeholders di alto livello\nOttima conoscenza dell\u2019inglese e dell\u2019italiano. La conoscenza dello spagnolo o del francese sar\u00e0 considerato un plus\nInteresse per l\u2019innovazione e le sfide strategiche del mondo Energy, Marketing & Sales\n\ud83d\udc9c\nScopri nel video le ragioni per cui scegliere JAKALA come prossimo step di carriera\n:\nIn JAKALA crediamo che il tempo e il benessere delle persone vadano rispettati, sempre: incoraggiamo una presenza in ufficio di\n10\ngiorni al mese, lasciando piena libert\u00e0 di lavorare da dove preferisci, sia in Italia che all\u2019interno della Comunit\u00e0 Europea.\nIl nostro sistema di Total\nReward\ninclude convenzioni esclusive per viaggi, ristoranti, shopping, palestra e tempo libero, oltre a servizi gratuiti di telemedicina e supporto psicologico, pensati per te e per chi ami.\nInvestire nel nostro processo di selezione significa ricevere supporto autentico: un Recruiter dedicato ti accompagner\u00e0 con feedback personalizzati, consigli di carriera e insight sul tuo CV, a prescindere dall\u2019esito della candidatura. Niente AI, solo persone. E, grazie all\u2019iniziativa Your Time Back, ti restituiamo il tempo investito nei colloqui con un percorso di empowerment firmato\nUnobravo\n.\n\ud83c\udf31 Ready to start?\nNon \u00e8 solo una candidatura. \u00c8 un percorso che comincia ora. Inviaci il tuo CV: non vediamo l\u2019ora di conoscerti!\nBack\nApply\nShare this job:\nFacebook\nLinkedIn\nEmail",
        "application_url": "https://careers.jakala.com/en_US/careers/ApplicationMethods?jobId=2121",
        "": {},
        "metadata": {
            "Office": "Milano",
            "Country": "Italy",
            "Date Published": "26-Sep-2025",
            "Ref #": "2089",
            "Area": "Management Consulting",
            "Type of Presence": "Hybrid"
        },
        "link": "https://careers.jakala.com/en_US/careers/JobDetail/Experienced-Professional-Client-Strategy-Energy/2121"
    },
    {
        "title": "Experienced Professional | Customer Engagement & Partnerships",
        "description_html": null,
        "description_text": "General information\nOffice\nMilano\nCountry\nItaly\nDate Published\n25-Sep-2025\nRef #\n2088\nArea\nReward Marketing\nType of Presence\nHybrid\nDescription & Requirements\n\ud83d\udccd\nSede\n: Milano\n\ud83d\udc40\nRank: Senior Consultant\nChi siamo\nJAKALA \u00e8 un'azienda che lavora su dati, intelligenza artificiale e sviluppo di esperienze per generare un impatto significativo e duraturo a livello globale.\nPresenti in oltre 30 citt\u00e0 in 21 paesi,\u00a0i nostri team\u00a0uniscono competenze su strategia, tecnologia, creativit\u00e0 e\u00a0operations\u00a0per offrire esperienze personalizzate e soluzioni trasformative ai nostri clienti, grazie al supporto di dati e intelligenza artificiale. I\u00a0Jakalers\u00a0sono un gruppo eterogeneo di oltre 3.000 persone, animate da passione, ambizione e idee brillanti. Proprio questa combinazione unica di talenti \u00e8 il fattore distintivo che ha ispirato il nostro\u00a0purpose: Together to\u00a0get\u00a0there.\nCreare un mondo migliore \u00e8 il nostro obiettivo ultimo: la nostra ambizione \u00e8 generare valore per tutti i nostri stakeholder in modo sostenibile, con particolare attenzione a etica, clima e qualit\u00e0. Nel 2021, abbiamo scelto di diventare una Societ\u00e0 Benefit, dimostrando il nostro impegno di lungo periodo e la volont\u00e0 di proteggere i principi e i valori che ogni giorno guidano le nostre azioni.\nCrediamo che la diversit\u00e0 sia la chiave del nostro successo e, per questo, siamo impegnati a creare un ambiente di lavoro inclusivo, dove ciascuno possa sentirsi valorizzato per la propria unicit\u00e0. Tutte le nostre opportunit\u00e0 di lavoro sono aperte ai candidati appartenenti alle categorie protette L.68/99.\nScopri\u00a0il team\u00a0Customer\u00a0Engagament\u00a0& Partnerships\nHai una forte passione per il marketing e per lo sviluppo di partnership commerciali? Ti piace lavorare in un contesto dinamico, in crescita e in continua evoluzione? Dai un\u2019occhiata a questa opportunit\u00e0: potrebbe essere quella giusta per te. Entrando nel team Customer Engagement & Partnerships, avrai l\u2019occasione di contribuire in modo concreto all\u2019ideazione e realizzazione delle strategie di reward per i programmi di loyalty e per le attivit\u00e0 di engagement dei nostri clienti. Sarai coinvolto nella gestione operativa dei progetti, nel coordinamento con i partner commerciali e nel supporto alle aziende clienti per garantire la qualit\u00e0 e l\u2019efficacia delle iniziative.\n\ud83c\udfaf\nLe tue responsabilit\u00e0:\nGestire le relazioni con clienti, partner e stakeholder interni, assicurando una comunicazione chiara e strutturata\nSupportare la definizione e l\u2019implementazione delle offerte di co-marketing, curandone gli aspetti operativi, negoziali e contrattuali\nCoordinare le attivit\u00e0 di delivery dei materiali promozionali e supervisionare i processi di test,\u00a0quality\u00a0assurance\u00a0e pubblicazione\nContribuire alla definizione delle proposte di contenuto premiale e delle offerte economiche, garantendo coerenza strategica e sostenibilit\u00e0\nCollaborare al miglioramento continuo dei processi operativi e all\u2019identificazione di nuove opportunit\u00e0 di partnerships\n\ud83d\ude4c\nSe ti riconosci in queste caratteristiche, potremmo essere il perfetto match:\n2-4 anni di esperienza maturata in ambito consulenziale o in contesti affini (marketing,\u00a0reward, business/people strategy)\nLaurea in Marketing, International Management, Economia o discipline affini\nOttima padronanza della lingua italiana e inglese, scritta e parlata\nConoscenza avanzata di Excel e PowerPoint, a supporto di analisi, presentazioni e monitoraggio delle attivit\u00e0\nSpiccate capacit\u00e0 analitiche e di problem solving, unite a un approccio strutturato e orientato al risultato\n\ud83d\udc9c\nScopri in questo video le ragioni per cui scegliere JAKALA come prossimo step di carriera\nIn JAKALA crediamo che il tempo e il benessere delle persone vadano rispettati, sempre: incoraggiamo una presenza in ufficio di 10 giorni al mese, lasciando piena libert\u00e0 di lavorare da dove preferisci, sia in Italia che all\u2019interno della Comunit\u00e0 Europea.\nIl nostro sistema di Total Reward include convenzioni esclusive per viaggi, ristoranti, shopping, palestra e tempo libero, oltre a servizi gratuiti di telemedicina e supporto psicologico, pensati per te e per chi ami.\nInvestire nel nostro processo di selezione significa ricevere supporto autentico: un Recruiter dedicato ti accompagner\u00e0 con feedback personalizzati, consigli di carriera e insight sul tuo CV, a prescindere dall\u2019esito della candidatura. Niente AI, solo persone. E, grazie all\u2019iniziativa Your Time Back, ti restituiamo il tempo investito nei colloqui con un percorso di empowerment firmato Unobravo.\n\ud83c\udf31\nReady to start?\nNon \u00e8 solo una candidatura. \u00c8 un percorso che comincia ora. Inviaci il tuo CV: non vediamo l\u2019ora di conoscerti!\nBack\nApply\nShare this job:\nFacebook\nLinkedIn\nEmail",
        "application_url": "https://careers.jakala.com/en_US/careers/ApplicationMethods?jobId=2120",
        "": {},
        "metadata": {
            "Office": "Milano",
            "Country": "Italy",
            "Date Published": "25-Sep-2025",
            "Ref #": "2088",
            "Area": "Reward Marketing",
            "Type of Presence": "Hybrid"
        },
        "link": "https://careers.jakala.com/en_US/careers/JobDetail/Experienced-Professional-Customer-Engagement-Partnerships/2120"
    },
    {
        "title": "Experienced Professional | SEO Associate Manager",
        "description_html": null,
        "description_text": "General information\nOffice\nMilano\nCountry\nItaly\nDate Published\n18-Sep-2025\nRef #\n2084\nArea\nManagement Consulting\nType of Presence\nHybrid\nDescription & Requirements\n\ud83d\udccd\nSede\n: Milano\n\ud83d\udc40\nRank:\nAssociate Manager\nAbout us\nJAKALA is a data, AI, and experiences company that creates meaningful and lasting impact globally.\nAcross more than 30 cities in 21 countries, our people combine strategy, technology, creativity, and operations to deliver tailored experiences and transformative solutions with data and AI at the heart. Jakalers are a diverse and multifaceted group of more than 3,000 individuals with passion, ambition and bright ideas. This unique mix of talents has become the distinctive factor that inspired our purpose: Together to get there.\nAt JAKALA, creating a better world is our ultimate purpose; we aim at creating value for all stakeholders in a sustainable way with a focus on ethics, climate and quality. In 2021, we decided to become a Benefit Corporation, demonstrating our long-term commitment to protecting the principles and values that guide our actions.We believe that diversity is the key to our success and for this reason we are committed to create an inclusive workplace, where everyone can feel valued for their uniqueness.\nAll our job opportunities are open to candidates belonging to categorie protette L.68/99.\nDiscover the SEO team\nWe are looking for an experienced professional SEO Associate Manager to join our Milan office with strong strategic, technical and consulting skills, eager to take on complex and challenging projects in a fast-growing and cross-pollinating environment.\nYou will play an active role in defining, implementing and overseeing SEO strategies for our national and international clients, focusing on performance, innovation and interdisciplinary collaboration.\n\ud83c\udfaf\nYour responsibilities:\nBuild and maintain strong relationships with clients by deeply understanding their business, challenges, and spotting future opportunities\nLead the planning and\u00a0implementation\u00a0of innovative SEO\u00a0campaigns\u00a0aligned\u00a0with\u00a0KPIs\u00a0and\u00a0contractual\u00a0requirements\nConduct\u00a0SEO\u00a0analyses\u00a0on\u00a0industry, competitors, keywords, and trends to\u00a0inform\u00a0strategy and\u00a0optimization\u00a0proposals\nCoordinate teams of 2\u20133 SEO\u00a0Consultants,\u00a0supporting, training, and\u00a0upskilling\u00a0them\u00a0to drive\u00a0professional\u00a0growth\nMonitor site health,\u00a0identify\u00a0and\u00a0resolve\u00a0technical SEO\u00a0issues, and\u00a0manage\u00a0pre- and post-launch\u00a0phases\u00a0of new websites\nDevelop\u00a0link-building strategies,\u00a0local\u00a0SEO (including\u00a0GMB), and support SEO\u00a0approaches\u00a0for video and YouTube\nIntroduce innovative\u00a0methodologies, new tech partners, and best practices to\u00a0enhance\u00a0SEO services\nPlan, lead, and attend client meetings, QBRs, and annual reviews while consistently meeting deadlines and priorities in a fast-paced environment\n\ud83d\ude4c\nIf you see yourself in these characteristics, we could be the perfect match:\n4-7+ years of SEO experience with technical expertise on e-commerce and multi-country websites\nExcellent\u00a0command\u00a0of SEO tools (Google\u00a0Search\u00a0Console,\u00a0SEMrush,\u00a0Ahrefs,\u00a0Screaming\u00a0Frog, etc.) and\u00a0analytics\u00a0platforms\u00a0(Google Analytics, Adobe Analytics, etc.)\nAbility\u00a0to produce in-depth\u00a0technical and\u00a0editorial\u00a0SEO audits and\u00a0translate\u00a0business\u00a0requirements\u00a0and data\u00a0into\u00a0effective\u00a0solutions\nProficiency in\u00a0optimizing\u00a0copy, semantic tags, and metadata to\u00a0increase\u00a0relevance\u00a0and ranking\nExperience with Local SEO strategies, GMB management, and\u00a0content\u00a0development\nKnowledge of outreach strategies, backlink analysis, and building authoritative link profiles\nUp-to-date\u00a0understanding\u00a0of ranking\u00a0factors\u00a0and\u00a0search\u00a0engine\u00a0algorithms\nFamiliarity\u00a0with\u00a0various\u00a0CMS and,\u00a0as\u00a0a plus,\u00a0basic\u00a0knowledge of HTML/CSS\nHigh proficiency in MS Office and data\u00a0visualization\u00a0tools (Google Data Studio, Tableau or\u00a0similar)\nFull proficiency and\u00a0fluency\u00a0in English (C1/C2 or\u00a0equivalent), with confidence\u00a0presenting\u00a0to senior clients and\u00a0internal\u00a0teams\nStrong\u00a0organizational, project management, and\u00a0problem-solving skills, with the\u00a0ability\u00a0to\u00a0meet\u00a0deadlines in\u00a0dynamic\u00a0environments\nPassion for Digital Marketing, proactivity, and a strong attitude for training and developing team members\n\ud83d\udc9c\nDiscover in the video why choosing JAKALA could be your next career move.\nAt JAKALA, we believe that people\u2019s time and well-being must always be respected: we encourage an office presence of 10 days per month, giving you full freedom to work from wherever you prefer, whether in Italy or anywhere within the European Union.\nOur Total Reward system includes exclusive discounts for travel, restaurants, shopping, gyms, and leisure activities, as well as free telemedicine and psychological support services, designed for you and your loved ones.\nInvesting your time in our selection process means receiving genuine support: a dedicated Recruiter will guide you with personalized feedback, career advice, and insights on your CV\u2014regardless of the outcome of your application. No AI, just people. And thanks to the Your Time Back initiative, we give back the time you\u2019ve spent in interviews with an empowerment program by Unobravo.\n\ud83c\udf31 Ready to start?\nIt\u2019s not just an application \u2014 it\u2019s a journey that starts now\n.\nSend us your CV: we can\u2019t wait to meet you!\nBack\nApply\nShare this job:\nFacebook\nLinkedIn\nEmail",
        "application_url": "https://careers.jakala.com/en_US/careers/ApplicationMethods?jobId=2116",
        "": {},
        "metadata": {
            "Office": "Milano",
            "Country": "Italy",
            "Date Published": "18-Sep-2025",
            "Ref #": "2084",
            "Area": "Management Consulting",
            "Type of Presence": "Hybrid"
        },
        "link": "https://careers.jakala.com/en_US/careers/JobDetail/Experienced-Professional-SEO-Associate-Manager/2116"
    },
    {
        "title": "Senior Media Specialist",
        "description_html": null,
        "description_text": "General information\nOffice\nMiami\nCountry\nUnited States of America\nDate Published\n17-Sep-2025\nRef #\n2082\nArea\nManagement Consulting\nType of Presence\nHybrid\nDescription & Requirements\nWe are Jakala: an award-winning organization that offers world's leading brands support in the strategy, analytics, digital and technology fields.\nOur mission is to create competitive advantage for our clients, with a measurable impact on the top line, through the best combined use of media, data, advanced analytics, technologies, content and customer experience design.\nWe are 3,500+ people in 20 countries around world, growing at a fast-pace.\nFor our digital & media division, we are looking for brilliant candidates that are enthusiastic about digital marketing to join our media team in our Miami office as a Senior Media Specialist to be a part of this exciting growth phase.\nIf you are looking for an international company with people that share the same digital passion as you do, Jakala could be the place for you!\nThe Role\nAs a Senior Paid Media Specialist, you\u2019ll manage and optimize international campaigns across\nSearch, Social, and Display channels\nfor clients in diverse industries.\nYou\u2019ll work closely with Account Managers and the Account Director on onboarding new clients, building strategies, and driving measurable results.\nThis role is designed to give you the skills and exposure to progress into an Account Manager role.\nWhat You\u2019ll Do\nCampaign Strategy & Execution\nCollaborate with Account Managers and Directors to design campaign structures across\nGoogle Ads, Facebook Ads, and Display platforms\n.\nWrite and test ad copy, refine keyword strategies, and optimize placements to maximize ROI.\nPerformance Monitoring & Reporting\nTrack and analyze KPIs to uncover insights and guide optimizations.\nDeliver timely and accurate weekly, monthly, and ad hoc performance reports.\nClient & Stakeholder Communication\nShare clear updates on campaign results and project progress.\nAct as the key point of contact between clients and internal teams to ensure smooth execution.\nFinancial & Process Management\nMeet client and internal deadlines while ensuring financial accuracy and compliance.\nTroubleshoot and resolve issues during campaign delivery.\nIndustry Insights & Growth\nStay on top of the latest\nmedia, platform, and industry trends\nand share with clients and the team.\nContribute to new business efforts by preparing presentations and supporting pitches.\nThe Ideal Candidate\n2+ years\u2019 hands-on experience in\nPaid Search and Paid Social\n(travel, retail, or financial services a plus).\nExperience managing medium-to-large budgets and accounts.\nProficiency with:\nGoogle Ads\n(certification a plus)\nFacebook Ads\n(Blueprint a plus)\nExcel\n(VLOOKUP, IF statements, pivot tables) plus strong PowerPoint/Word skills\nBonus: basic HTML or SQL\nStrong analytical mindset and problem-solving skills.\nComfortable presenting to clients and collaborating across teams.\nA proactive, detail-oriented multitasker who thrives under pressure.\nFluent in English and legally authorized to work in the US.\nPlease Note: This position has a maximum salary of $115k USD\nAt Jakala, we are committed to providing equal employment opportunities for all individuals regardless of their race, color, religion, sex, national origin, age, disability, or any other legally protected status. We celebrate diversity and strive to create an inclusive workplace where all employees feel valued and respected. We also understand that accommodations may be necessary to ensure equal access to employment opportunities. If you require accommodations to apply for a position or participate in the hiring process, please contact us at jobhelp@jakala.com.\nBack\nApply\nShare this job:\nFacebook\nLinkedIn\nEmail",
        "application_url": "https://careers.jakala.com/en_US/careers/ApplicationMethods?jobId=2114",
        "": {},
        "metadata": {
            "Office": "Miami",
            "Country": "United States of America",
            "Date Published": "17-Sep-2025",
            "Ref #": "2082",
            "Area": "Management Consulting",
            "Type of Presence": "Hybrid"
        },
        "link": "https://careers.jakala.com/en_US/careers/JobDetail/Senior-Media-Specialist/2114"
    },
    {
        "title": "Media Manager",
        "description_html": null,
        "description_text": "General information\nOffice\nMiami\nCountry\nUnited States of America\nDate Published\n17-Sep-2025\nRef #\n2083\nArea\nManagement Consulting\nType of Presence\nHybrid\nDescription & Requirements\nWe are Jakala: an award-winning organization that offers world's leading brands support in the strategy, analytics, digital and technology fields.\nOur mission is to create competitive advantage for our clients, with a measurable impact on the top line, through the best combined use of media, data, advanced analytics, technologies, content and customer experience design.\nWe are 3,500+ people in 20 countries around world, growing at a fast-pace.\nFor our digital & media division, we are looking for brilliant candidates that are enthusiastic about digital marketing to join our media team in our Miami office as a Media Manager to be a part of this exciting growth phase.\nIf you are looking for an international company with people that share the same digital passion as you do, Jakala could be the place for you!\nThe Role\nAs a Media Manager, you\u2019ll take charge of\nmultinational media accounts\nacross industries, leading campaign strategy and execution while being the main client contact for performance and day-to-day queries.\nYou\u2019ll work across\nPaid Search, Paid Social, and Programmatic\n, analyzing results, optimizing campaigns, and collaborating closely with both clients and internal teams to deliver best-in-class digital performance.\nWhat You\u2019ll Do\nCampaign Strategy & Execution\nPlan, launch, and optimize campaigns across\nSearch (Google & Microsoft Ads), Social (Meta, LinkedIn, TikTok, etc.), and Programmatic platforms\n.\nMonitor campaign health daily, adjust bids, targeting, and creative for maximum impact.\nPerformance Monitoring & Insights\nAnalyze campaign data to surface insights, identify opportunities, and deliver actionable recommendations.\nProduce performance reports and translate results into strategic advice for clients.\nClient Communication & Relationship Management\nAct as the primary client contact for performance updates and queries.\nBuild trust through clear, proactive communication and consultative support.\nQuality Assurance & Compliance\nOversee daily/weekly QA checks to ensure accurate tracking, trafficking, and campaign setup.\nAdhere to financial processes and reporting standards with precision.\nCollaboration & Leadership\nPartner with the Media Director on high-level strategy while managing junior resources on accounts.\nContribute to cross-channel integrated plans with wider teams.\nInnovation & Growth\nKeep ahead of emerging trends, tools, and platforms, sharing knowledge with both clients and colleagues.\nSupport new business pitches and internal knowledge-sharing initiatives.\nThe Ideal Candidate\n5+ years of hands-on experience in\nPaid Media (PPC + Paid Social)\n; programmatic experience strongly preferred.\nProven track record in\nclient management\nand end-to-end campaign delivery (planning, execution, and strategy).\nStrong data analysis skills with the ability to turn numbers into strategy.\nAdvanced Excel (Pivot Tables, VLOOKUP, IF/SUMIF, CONCATENATE) and strong PowerPoint skills.\nExcellent communication and presentation abilities.\nDetail-oriented with strong problem-solving skills.\nAbility to manage multiple projects in a fast-paced environment.\nFluent in English and legally able to work in the US.\nPlease Note: The maximum salary for this position is $135K\nAt Jakala, we are committed to providing equal employment opportunities for all individuals regardless of their race, color, religion, sex, national origin, age, disability, or any other legally protected status. We celebrate diversity and strive to create an inclusive workplace where all employees feel valued and respected. We also understand that accommodations may be necessary to ensure equal access to employment opportunities. If you require accommodations to apply for a position or participate in the hiring process, please contact us at jobhelp@jakala.com.\nBack\nApply\nShare this job:\nFacebook\nLinkedIn\nEmail",
        "application_url": "https://careers.jakala.com/en_US/careers/ApplicationMethods?jobId=2115",
        "": {},
        "metadata": {
            "Office": "Miami",
            "Country": "United States of America",
            "Date Published": "17-Sep-2025",
            "Ref #": "2083",
            "Area": "Management Consulting",
            "Type of Presence": "Hybrid"
        },
        "link": "https://careers.jakala.com/en_US/careers/JobDetail/Media-Manager/2115"
    },
    {
        "title": "Intern | Client Strategy",
        "description_html": null,
        "description_text": "General information\nOffice\nMilano\nCountry\nItaly\nDate Published\n05-Sep-2025\nRef #\n2059\nArea\nManagement Consulting\nType of Presence\nHybrid\nDescription & Requirements\n\ud83d\udccd\nSede\n: Milano\nChi siamo\nJAKALA \u00e8 un'azienda che lavora su dati, intelligenza artificiale e sviluppo di esperienze per generare un impatto significativo e duraturo a livello globale.\nPresenti in oltre 30 citt\u00e0 in 21 paesi, i nostri team uniscono competenze su strategia, tecnologia, creativit\u00e0 e operations per offrire esperienze personalizzate e soluzioni trasformative ai nostri clienti, grazie al supporto di dati e intelligenza artificiale. I Jakalers sono un gruppo eterogeneo di oltre 3.000 persone, animate da passione, ambizione e idee brillanti. Proprio questa combinazione unica di talenti \u00e8 il fattore distintivo che ha ispirato il nostro purpose: Together to get there.\nCreare un mondo migliore \u00e8 il nostro obiettivo ultimo: la nostra ambizione \u00e8 generare valore per tutti i nostri stakeholder in modo sostenibile, con particolare attenzione a etica, clima e qualit\u00e0. Nel 2021, abbiamo scelto di diventare una Societ\u00e0 Benefit, dimostrando il nostro impegno di lungo periodo e la volont\u00e0 di proteggere i principi e i valori che ogni giorno guidano le nostre azioni.\nCrediamo che la diversit\u00e0 sia la chiave del nostro successo e, per questo, siamo impegnati a creare un ambiente di lavoro inclusivo, dove ciascuno possa sentirsi valorizzato per la propria unicit\u00e0. Tutte le nostre opportunit\u00e0 di lavoro sono aperte ai candidati appartenenti alle categorie protette L.68/99.\nScopri il team Client Strategy\nTi appassiona lavorare con dati e insight per contribuire alla definizione di strategie di crescita dei clienti? Entrerai a far parte di un team multidisciplinare e dinamico, e avrai l\u2019opportunit\u00e0 di lavorare su iniziative strategiche ad altro impatto volte a valorizzare il patrimonio informativo dei clienti. Approfondirai tematiche legate al mondo Strategy & Consulting con un approccio proattivo e data-driven all\u2019interno di un ambiente dinamico e in continua evoluzione. Se questo ruolo riflette le tue ambizioni, questa opportunit\u00e0 potrebbe essere l\u2019inizio del percorso che stavi cercando.\n\ud83c\udfaf Ogni giorno sar\u00e0 diverso, ma eccoti un assaggio di quello che ti aspetta\nSupportare il team nell\u2019analisi dei dati relativi al cliente per sviluppare insight utili alla definizione di strategie di crescita personalizzate\nContribuire alla preparazione di presentazioni strategiche per i clienti attraverso analisi di mercato, definizione di KPI e business case\nCollaborare con stakeholders interni ed esterni per garantire coerenza tra insight, proposta strategica e obiettivi business del cliente\n\ud83d\udca1\nQueste caratteristiche sono un ottimo punto di partenza per crescere insieme\nLaurea Magistrale in Economia e Management, Marketing o discipline affini\nOttima padronanza di Office365, in particolare Excel e PowerPoint\nBuone capacit\u00e0 analitiche e di sintesi, precisione e attenzione al dettaglio\nSolida conoscenza della lingua italiana e inglese\n\ud83d\ude80Ci brillano gli occhi se hai anche\nInteresse per la consulenza strategica e i progetti ad alto impatto\nOrientamento al raggiungimento degli obiettivi e risultati concreti\nAttitudine al lavoro di squadra in contesti dinamici e collaborativi\nBuone capacit\u00e0 relazionali e comunicative\n\ud83d\udc9c\nScopri in questo video le ragioni per cui scegliere JAKALA come prossimo step di carriera\nIn JAKALA crediamo che il tempo e il benessere delle persone vadano rispettati, sempre: incoraggiamo una presenza in ufficio di 10 giorni al mese.\nIl nostro sistema di Total Reward include convenzioni esclusive per viaggi, ristoranti, shopping, palestra e tempo libero, oltre a servizi gratuiti di telemedicina e supporto psicologico, pensati per te e per chi ami.\nInvestire nel nostro processo di selezione significa ricevere supporto autentico: un Recruiter dedicato ti accompagner\u00e0 con feedback personalizzati, consigli di carriera e insight sul tuo CV, a prescindere dall\u2019esito della candidatura. Niente AI, solo persone. E, grazie all\u2019iniziativa Your Time Back, ti restituiamo il tempo investito nei colloqui con un percorso di empowerment firmato Unobravo.\n\ud83c\udf31 Ready to start?\nNon \u00e8 solo una candidatura. \u00c8 un percorso che comincia ora. Inviaci il tuo CV: non vediamo l\u2019ora di conoscerti!\nBack\nApply\nShare this job:\nFacebook\nLinkedIn\nEmail",
        "application_url": "https://careers.jakala.com/en_US/careers/ApplicationMethods?jobId=2091",
        "": {},
        "metadata": {
            "Office": "Milano",
            "Country": "Italy",
            "Date Published": "05-Sep-2025",
            "Ref #": "2059",
            "Area": "Management Consulting",
            "Type of Presence": "Hybrid"
        },
        "link": "https://careers.jakala.com/en_US/careers/JobDetail/Intern-Client-Strategy/2091"
    },
    {
        "title": "Conversion Rate Optimizacion (CRO) Senior Consultant",
        "description_html": null,
        "description_text": "General information\nOffice\nMadrid\nCountry\nSpain\nDate Published\n30-May-2025\nRef #\n1920\nArea\nMarketing\nType of Presence\nHybrid\nDescription & Requirements\nEn JAKALA buscamos incorporar, en nuestra oficina de\nMadrid\n, un/a\nCRO Senior\nConsultant (Conversion Rate Optimization)\nque participar\u00e1 en proyectos\nmartech\npara impulsar las conversiones y la experiencia de usuarios mediante estrategias basadas en datos,\ntesting\ny personalizaci\u00f3n.\nFunciones:\nOptimizaci\u00f3n de experiencias digitales (CRO): Liderar la ideaci\u00f3n, implementaci\u00f3n y an\u00e1lisis de experimentos y personalizaciones en activos digitales, con el objetivo de maximizar la conversi\u00f3n y mejorar la experiencia de usuario.\nIdentificar puntos fuertes y a mejorar en activos digitales (web y\napp\n), utilizando herramientas de medici\u00f3n desde el punto de vista cuantitativo y cualitativo.\nTrabajar en estrategias para la optimizaci\u00f3n de web/\napp\nseg\u00fan resultados y alineados con la estrategia de la compa\u00f1\u00eda.\nEstrategias de orquestaci\u00f3n: Colaborar en la definici\u00f3n e implementaci\u00f3n de flujos y campa\u00f1as personalizadas que garanticen una experiencia\nomnicanal\ncoherente y efectiva.\nAn\u00e1lisis y visualizaci\u00f3n de datos: Identificar oportunidades de mejora basadas en datos, evaluando la efectividad de iniciativas y generando\nin\nsights\na\nccionables.\nGesti\u00f3n de herramientas digitales: Administrar y optimizar herramientas relacionadas con CRO y orquestaci\u00f3n (herramientas de experimentaci\u00f3n, personalizaci\u00f3n,\nCD\nPs\n,\netc.).\nColaboraci\u00f3n interdepartamental: Trabajar con equipos de desarrollo, dise\u00f1o, marketing y datos para garantizar la alineaci\u00f3n estrat\u00e9gica en la implementaci\u00f3n de proyectos y campa\u00f1as.\nRequisitos\n:\nPerfil experimentado con conocimiento profundo de la metodolog\u00eda CRO (\nC\nonversion\nR\nate\nO\nptimization\n)\ny experiencia demostrable\nliderando\nproyectos con clientes de sectores diferentes.\nAmplio conocimiento en herramientas de anal\u00edtica web y\ntesting\ncomo:\nAdobe\nAnalytics\n(imprescindible para este puesto)\n, Google\nAnalytics\n,\nOptimizely\n,\nF\nirebase\n,\nGoogle\nO\nptimize\n,\netc.\nExperiencia con herramientas de an\u00e1lisis cuantitativo y cualitativo (\nContentSquare\n,\nHotjar\n,\nMouseflow\n, etc.\n)\nExperiencia con suites de experimentaci\u00f3n como Adobe Target (imprescindible para este puesto), Dynamic\nYield\n, AB\nTasty\n,\nConvert\n, VWO ...\nBuen nivel de ingl\u00e9s hablado y escrito, capaz de trabajar en proyectos en donde este sea el \u00fanico idioma de comunicaci\u00f3n.\nCapacidad de establecer una excelente interlocuci\u00f3n con clientes de diferentes perfiles y necesidades.\nCapacidades de\nproblem\nsolving\ny an\u00e1lisis.\nValorable:\nFormaci\u00f3n/conocimiento profundo en\nBehavioral\nEconomics\n\u00bfQu\u00e9 ofrecemos?\nModelo h\u00edbrido de asistencia a la oficina (2 d\u00edas/semana presencial).\nTres semanas al a\u00f1o de full remote.\nSeguro m\u00e9dico.\nWellhub\npara cuidar tu salud f\u00edsica y mental.\nRetribuci\u00f3n flexible.\n28 d\u00edas de vacaciones al a\u00f1o.\nPath\nde carrera adaptado a tus inquietudes profesionales.\nAcceso a certificaciones (somos\npartners\nde Google y Salesforce).\nJxpert\n:\nprogramas de capacitaci\u00f3n tecnol\u00f3gica de las distintas disciplinas de\nJ\nakala\n.\nJlab\n:\nnuestro laboratorio de pruebas de soluciones tecnol\u00f3gicas.\nFormaci\u00f3n en idiomas.\nDeporte en la oficina.\nOficina de Madrid: Servicio de lanzadera\nDescripci\u00f3n de la empresa:\nJAKALA es una multinacional especializada en datos, Inteligencia Artificial y experiencias digitales que crea un impacto significativo y duradero a nivel global.\nEn m\u00e1s de 30 ciudades de 21 pa\u00edses, nuestro equipo combina estrategia, tecnolog\u00eda, creatividad y operaciones para ofrecer experiencias personalizadas y soluciones transformadoras, con datos e Inteligencia Artificial en el centro. Los\nJakalers\nson un grupo diverso de m\u00e1s de 3.000 personas con pasi\u00f3n, ambici\u00f3n e ideas brillantes. Esta combinaci\u00f3n \u00fanica de talentos se ha convertido en el factor distintivo que ha inspirado nuestro objetivo:\nTogeth\ne\nr\nt\no\ng\ne\nt\nthe\nre\n.\nEn JAKALA, crear un mundo mejor es nuestro objetivo final; aspiramos a crear valor para todas las partes interesadas de manera sostenible, con un enfoque en la \u00e9tica, el clima y la calidad.\nEn 2021, decidimos convertirnos en una Empresa Ben\u00e9fica, demostrando nuestro compromiso a largo plazo con la protecci\u00f3n de los principios y valores que gu\u00edan nuestras acciones.\nBack\nApply\nShare this job:\nFacebook\nLinkedIn\nEmail",
        "application_url": "https://careers.jakala.com/en_US/careers/ApplicationMethods?jobId=1950",
        "": {},
        "metadata": {
            "Office": "Madrid",
            "Country": "Spain",
            "Date Published": "30-May-2025",
            "Ref #": "1920",
            "Area": "Marketing",
            "Type of Presence": "Hybrid"
        },
        "link": "https://careers.jakala.com/en_US/careers/JobDetail/Conversion-Rate-Optimizacion-CRO-Senior-Consultant/1950"
    },
    {
        "title": "Intern | Client Strategy FSI",
        "description_html": null,
        "description_text": "General information\nOffice\nMilano\nCountry\nItaly\nDate Published\n29-May-2025\nRef #\n1944\nArea\nManagement Consulting\nType of Presence\nHybrid\nDescription & Requirements\n\ud83d\udccd\nSede\n: Milano\nChi siamo\nJAKALA \u00e8 un'azienda che lavora su dati, intelligenza artificiale e sviluppo di esperienze per generare un impatto significativo e duraturo a livello globale.\nPresenti in oltre 30 citt\u00e0 in 21 paesi,\ni nostri team\nuniscono competenze su strategia, tecnologia, creativit\u00e0 e\noperations\nper offrire esperienze personalizzate e soluzioni trasformative ai nostri clienti, grazie al supporto di dati e intelligenza artificiale. I\nJakalers\nsono un gruppo eterogeneo di oltre 3.000 persone, animate da passione, ambizione e idee brillanti. Proprio questa combinazione unica di talenti \u00e8 il fattore distintivo che ha ispirato il nostro\npurpose\n:\nTogether\nto\nget\nthere\n.\nCreare un mondo migliore \u00e8 il nostro obiettivo ultimo: la nostra ambizione \u00e8 generare valore per tutti i nostri stakeholder in modo sostenibile, con particolare attenzione a etica, clima e qualit\u00e0. Nel 2021, abbiamo scelto di diventare una Societ\u00e0 Benefit, dimostrando il nostro impegno di lungo periodo e la volont\u00e0 di proteggere i principi e i valori che ogni giorno guidano le nostre azioni.\nCrediamo che la diversit\u00e0 sia la chiave del nostro successo e, per questo, siamo impegnati a creare un ambiente di lavoro inclusivo, dove ciascuno possa sentirsi valorizzato per la propria unicit\u00e0. Tutte le nostre opportunit\u00e0 di lavoro sono aperte ai candidati appartenenti alle categorie protette L.68/99.\nScopri\nil team\nClient Strategy FSI\nHai passione per il mondo dei dati, della consulenza e dell\u2019innovazione digitale? In JAKALA,\nil team\nClient Strategy FSI lavora su progetti sfidanti per clienti leader di mercato, coniugando insight analitici, creativit\u00e0 e tecnologia in un contesto dinamico e stimolante.\n\ud83c\udfaf Ogni giorno sar\u00e0 diverso, ma eccoti un assaggio di quello che ti aspetta\nUn\u2019esperienza concreta all\u2019interno di un gruppo di lavoro multidisciplinare, dove potrai contribuire alla valorizzazione del patrimonio informativo dei clienti, approfondendo tematiche di Strategy & Consulting\nUn coinvolgimento nello sviluppo e nella realizzazione di progetti innovativi per grandi clienti in ambito\nBanking, Payments e Insurance\nUn\u2019attivit\u00e0 focalizzata su Data Analytics, Intelligenza Artificiale e trasformazione digitale, con l\u2019obiettivo di analizzare dati e sviluppare soluzioni innovative in un contesto in continua evoluzione\n\ud83d\udca1 Queste caratteristiche sono un ottimo punto di partenza per crescere insieme\nLaurea Magistrale, preferibilmente in Economia e Management, Marketing o discipline STEM\nOttime capacit\u00e0 analitiche, di sintesi e cura al dettaglio\nForte passione per il mondo della Consulenza in ambito Financial Services\nOttima conoscenza del pacchetto Office\nFluenza nella lingua italiana e inglese\n\ud83d\ude80Ci brillano gli occhi se hai anche\nForte orientamento al risultato\nVolont\u00e0 di implicarsi e incidere in un ambiente dinamico\nProblem\nsolving e orientamento al lavoro per obiettivi\nAttitudine al project management\nTeam working\nSpiccate capacit\u00e0 relazionali\n\ud83d\udc9c\nScopri in questo video le ragioni per cui scegliere JAKALA come prossimo step di carriera\nIn JAKALA crediamo che il tempo e il benessere delle persone vadano rispettati, sempre: incoraggiamo una presenza in ufficio di 10 giorni al mese.\nIl nostro sistema di Total Reward include convenzioni esclusive per viaggi, ristoranti, shopping, palestra e tempo libero, oltre a servizi gratuiti di telemedicina e supporto psicologico, pensati per te e per chi ami.\nInvestire nel nostro processo di selezione significa ricevere supporto autentico: un Recruiter dedicato ti accompagner\u00e0 con feedback personalizzati, consigli di carriera e insight sul tuo CV, a prescindere dall\u2019esito della candidatura. Niente AI, solo persone. E, grazie all\u2019iniziativa Your Time Back, ti restituiamo il tempo investito nei colloqui con un percorso di empowerment firmato\nUnobravo\n.\n\ud83c\udf31\u00a0Ready to start?\nNon \u00e8 solo una candidatura. \u00c8 un percorso che comincia ora. Inviaci il tuo CV: non vediamo l\u2019ora di conoscerti!\nBack\nApply\nShare this job:\nFacebook\nLinkedIn\nEmail",
        "application_url": "https://careers.jakala.com/en_US/careers/ApplicationMethods?jobId=1974",
        "": {},
        "metadata": {
            "Office": "Milano",
            "Country": "Italy",
            "Date Published": "29-May-2025",
            "Ref #": "1944",
            "Area": "Management Consulting",
            "Type of Presence": "Hybrid"
        },
        "link": "https://careers.jakala.com/en_US/careers/JobDetail/Intern-Client-Strategy-FSI/1974"
    },
    {
        "title": "Digital Product Strategist (all genders)",
        "description_html": null,
        "description_text": "General information\nOffice\nFull Remote, Berlin, Hamburg, Vienna\nCountry\nGermany\nDate Published\n22-Apr-2025\nRef #\n1879\nArea\nDesign\nType of Presence\nHybrid\nDescription & Requirements\nAls Digital Product Strategist (all genders) bringst du deine Erfahrungen in Service Design, Design Thinking und agiler Produktentwicklung variabel ein, um aus groben Strategien greifbare, digitale L\u00f6sungsans\u00e4tze zu machen. Durch dein kundenzentriertes Mindset hilfst du Kolleg:innen und Kunden dabei, technische L\u00f6sungen ganzheitlich zu betrachten und tr\u00e4gst somit ma\u00dfgeblich zur Gestaltung einer nahtlosen CX bei.\nResponsibilities\nDu arbeitest hand-in-hand mit unseren Kunden, um sie durch das Fuzzy Frontend der Produktentwicklung zu navigieren (von Recherche bis hin zu User Stories)\nDie Vorbereitung, Durchf\u00fchrung und Moderation von Workshops setzt du gezielt ein, um die interdisziplin\u00e4re Kollaboration und kreative L\u00f6sungsans\u00e4tze zu erm\u00f6glichen\nMit g\u00e4ngigen Tools wie Miro, Confluence, Jira und Figma vermittelst du deine Ergebnisse nachvollziehbar und Zielgruppengerecht\nDu \u00fcbernimmst das Service- und Produkt-Verst\u00e4ndnis in der Zusammenarbeit mit unseren Kunden, und bettest dies in den jeweiligen Projekt-Kontext ein\nDurch dein existierendes Wissen, gepaart mit einer unerm\u00fcdbaren Neugier schaffst du es eine unverzichtbare Schnittstelle zwischen dem Business, der Technik und den UX/UI Designern zu sein\nWas dich auszeichnet, ist deine Design-Thinking-Mentalit\u00e4t: Du schaffst es, die Neugier auf das Problem ebenso zu wecken wie den Gestaltungswillen f\u00fcr die L\u00f6sung\nBei der Definition von Anforderungen samt anschlie\u00dfender Priorisierung leistest du ma\u00dfgebliche Unterst\u00fctzung und hilfst unseren Kunden dabei MVPs und sp\u00e4tere Iterationen zu identifizieren\nQualifications\nDu verf\u00fcgst \u00fcber einen vielseitigen und wandelbaren Methodenkoffer, aus dem du f\u00fcr jede Herausforderung den passenden Ansatz gezielt einsetzen kannst\nDu hast drei bis f\u00fcnf Jahre Erfahrungen in der strategischen Entwicklung von digitalen Produkten und Services\nDu startest mit Empathie und verstehst es mit verschiedenen Ans\u00e4tzen die Probleme und Bed\u00fcrfnisse der Nutzenden richtig aufzudecken\nDu hast idealerweise Erfahrungen in der agilen Produktentwicklung sammeln k\u00f6nnen und verstehst die g\u00e4ngigen Prozesse und Methoden\nDu bewegst dich sicher in der Schnittmenge von Business-Modellen, Kundenbed\u00fcrfnissen und Technologie und wei\u00dft wie man den Sweetspot f\u00fcr neue Services entdeckt\nAnalytisches und strategisches Denken, aber auch eine kreative Passion beim L\u00f6sungsansatz, zeichnen dich aus\nDu verstehst es, mit einem Fokus auf das \"Big Picture\", das eigentliche Business-Problem nicht aus den Augen zu verlieren\nDu pr\u00e4sentierst gerne deine Ideen und Herangehensweisen und erweckst so Begeisterung und Vertrauen bei deinem Publikum\nAnpassungsf\u00e4higkeit: Du magst es, wenn sich Themen abwechseln und es gef\u00e4llt dir, dich in unterschiedliche Branchen, Themen und Kunden hineinzudenken\nDu verf\u00fcgst \u00fcber sehr gute Deutsch- und Englischkenntnisse in Wort und Schrift\nOffer\nDas bieten wir dir:\nJob in Vollzeit oder Teilzeit - du entscheidest\nHybrides Arbeitsmodell (Remote und B\u00fcro) mit flexiblen Arbeitszeiten\nOffene und teamorientierte Unternehmenskultur\nWertsch\u00e4tzung deiner Ideen\nZuschuss f\u00fcr \u00d6PNV und Bikeleasing-Option\nUrban Sports Club Membership\nW\u00f6chentliches gemeinsames Fr\u00fchst\u00fcck oder Mittagessen\nWenn du willst: Einstieg in unsere Hamburger Band (Schlagzeuger:in gesucht)\nWhat else?\nWir wollen einen positiven Impact auf unsere Erde haben. Deshalb streben wir danach, auf nachhaltige Weise Wert f\u00fcr alle Interessengruppen zu schaffen und ber\u00fccksichtigen dabei Klima, Ethik und Qualit\u00e4t. 2021 haben wir uns entschieden, eine Benefit Corporation zu werden, um unser langfristiges Engagement f\u00fcr den Schutz der Prinzipien und Werte, die unser Handeln leiten, zu unterstreichen.\nBewirb dich noch heute. Wir freuen uns darauf, dich kennenzulernen.\nBack\nApply\nShare this job:\nFacebook\nLinkedIn\nEmail",
        "application_url": "https://careers.jakala.com/en_US/careers/ApplicationMethods?jobId=1908",
        "": {},
        "metadata": {
            "Office": "Full Remote, Berlin, Hamburg, Vienna",
            "Country": "Germany",
            "Date Published": "22-Apr-2025",
            "Ref #": "1879",
            "Area": "Design",
            "Type of Presence": "Hybrid"
        },
        "link": "https://careers.jakala.com/en_US/careers/JobDetail/Digital-Product-Strategist-all-genders/1908"
    },
    {
        "title": "Experienced Professional | Senior Program Manager",
        "description_html": null,
        "description_text": "General information\nOffice\nMilano, Napoli, Roma\nCountry\nItaly\nDate Published\n10-Apr-2025\nRef #\n1864\nArea\nIT and Information Systems\nType of Presence\nHybrid\nDescription & Requirements\n\ud83d\udccd\nSede\n: Milano, Roma\n\ud83d\udc40\nRank:\nSenior Manager\nChi siamo\nJAKALA \u00e8 un'azienda che lavora su dati, intelligenza artificiale e sviluppo di esperienze per generare un impatto significativo e duraturo a livello globale.\nPresenti in oltre 30 citt\u00e0 in 21 paesi, i nostri team uniscono competenze su strategia, tecnologia, creativit\u00e0 e operations per offrire esperienze personalizzate e soluzioni trasformative ai nostri clienti, grazie al supporto di dati e intelligenza artificiale. I Jakalers sono un gruppo eterogeneo di oltre 3.000 persone, animate da passione, ambizione e idee brillanti. Proprio questa combinazione unica di talenti \u00e8 il fattore distintivo che ha ispirato il nostro purpose: Together to get there.\nCreare un mondo migliore \u00e8 il nostro obiettivo ultimo: la nostra ambizione \u00e8 generare valore per tutti i nostri stakeholder in modo sostenibile, con particolare attenzione a etica, clima e qualit\u00e0. Nel 2021, abbiamo scelto di diventare una Societ\u00e0 Benefit, dimostrando il nostro impegno di lungo periodo e la volont\u00e0 di proteggere i principi e i valori che ogni giorno guidano le nostre azioni.\nCrediamo che la diversit\u00e0 sia la chiave del nostro successo e, per questo, siamo impegnati a creare un ambiente di lavoro inclusivo, dove ciascuno possa sentirsi valorizzato per la propria unicit\u00e0. Tutte le nostre opportunit\u00e0 di lavoro sono aperte ai candidati appartenenti alle categorie protette L.68/99.\nScopri il team Project Management\nAll\u2019interno dell\u2019area Project Management di JAKALA, avrai l\u2019opportunit\u00e0 di supportare progetti complessi in ambito Digital, CRM, Data e Marketing Automation, contribuendo alla loro pianificazione, esecuzione e monitoraggio. Entrerai in un team strutturato e collaborativo, dove potrai coordinarti con stakeholder nazionali e internazionali, utilizzare strumenti avanzati di project management e contribuire al miglioramento continuo dei processi operativi.\nPer il potenziamento dell\u2019area, siamo alla ricerca di un Program Manager con una solida esperienza nella gestione di progetti complessi, nella leadership di team e nella collaborazione con stakeholder internazionali.\n\ud83c\udfaf\nLe tue responsabilit\u00e0:\nSupportare la gestione e il coordinamento di programmi digitali complessi, contribuendo all\u2019allineamento tra strategia, pianificazione e delivery operativa.\nMonitorare avanzamento, milestone, dipendenze e rischi, garantendo visibilit\u00e0 sui principali momenti di delivery.\nFacilitare la comunicazione e il coordinamento tra stakeholder interni, team internazionali e vendor.\nContribuire al monitoraggio di KPI, budget e risultati di business, in collaborazione con i team di riferimento.\nPromuovere modelli di governance e pratiche di delivery efficaci, orientate a qualit\u00e0 e miglioramento continuo.\n\ud83d\ude4c\nSe ti riconosci in queste caratteristiche, potremmo essere il perfetto match:\nEsperienza di 10+ anni nella gestione di programmi IT complessi.\nBackground in contesti di trasformazione digitale strutturati.\nConoscenza di metodologie Agile, SAFe o framework equivalenti.\nOttima padronanza di strumenti come Jira, Confluence, Power BI, Miro o simili.\nCapacit\u00e0 di pianificazione integrata e gestione di dipendenze complesse.\nAttitudine all\u2019anticipazione dei rischi e alla gestione del cambiamento.\nApproccio analitico e pragmatico alla gestione di roadmap, KPI e budget.\nEsperienza in ambienti multiculturali e multi-stakeholder.\nAttitudine al coaching e al supporto di leader e team.\nCapacit\u00e0 di lavorare sotto pressione mantenendo focus su risultati e qualit\u00e0.\n\ud83d\udc9c\nScopri nel video le ragioni per cui scegliere JAKALA come prossimo step di carriera\nIn JAKALA crediamo che il tempo e il benessere delle persone vadano rispettati, sempre: incoraggiamo una presenza in ufficio di10giorni al mese.\nIl nostro sistema di Total Reward include convenzioni esclusive per viaggi, ristoranti, shopping, palestra e tempo libero, oltre a servizi gratuiti di telemedicina e supporto psicologico, pensati per te e per chi ami.\nInvestire nel nostro processo di selezione significa ricevere supporto autentico: un Recruiter dedicato ti accompagner\u00e0 con feedback personalizzati, consigli di carriera e insight sul tuo CV, a prescindere dall\u2019esito della candidatura. Niente AI, solo persone. E, grazie all\u2019iniziativa Your Time Back, ti restituiamo il tempo investito nei colloqui con un percorso di empowerment firmato\u00a0Unobravo.\n\ud83c\udf31\nReady to start?\nNon \u00e8 solo una candidatura. \u00c8 un percorso che comincia ora. Inviaci il tuo CV: non vediamo l\u2019ora di conoscerti!\nBack\nApply\nShare this job:\nFacebook\nLinkedIn\nEmail",
        "application_url": "https://careers.jakala.com/en_US/careers/ApplicationMethods?jobId=1893",
        "": {},
        "metadata": {
            "Office": "Milano, Napoli, Roma",
            "Country": "Italy",
            "Date Published": "10-Apr-2025",
            "Ref #": "1864",
            "Area": "IT and Information Systems",
            "Type of Presence": "Hybrid"
        },
        "link": "https://careers.jakala.com/en_US/careers/JobDetail/Experienced-Professional-Senior-Program-Manager/1893"
    },
    {
        "title": "Experienced Professional | Cyber Security",
        "description_html": null,
        "description_text": "General information\nOffice\nMilano\nCountry\nItaly\nDate Published\n05-Mar-2025\nRef #\n1774\nArea\nCyber Security\nType of Presence\nHybrid\nDescription & Requirements\n\ud83d\udccd\nSede\n: Milano\n\ud83d\udc40\nRank: Specialist/Senior Specialist\nChi siamo\nJAKALA \u00e8 un'azienda che lavora su dati, intelligenza artificiale e sviluppo di esperienze per generare un impatto significativo e duraturo a livello globale.\nPresenti in oltre 30 citt\u00e0 in 21 paesi, i nostri team uniscono competenze su strategia, tecnologia, creativit\u00e0 e operations per offrire esperienze personalizzate e soluzioni trasformative ai nostri clienti, grazie al supporto di dati e intelligenza artificiale. I Jakalers sono un gruppo eterogeneo di oltre 3.000 persone, animate da passione, ambizione e idee brillanti. Proprio questa combinazione unica di talenti \u00e8 il fattore distintivo che ha ispirato il nostro purpose: Together to get there.\nCreare un mondo migliore \u00e8 il nostro obiettivo ultimo: la nostra ambizione \u00e8 generare valore per tutti i nostri stakeholder in modo sostenibile, con particolare attenzione a etica, clima e qualit\u00e0. Nel 2021, abbiamo scelto di diventare una Societ\u00e0 Benefit, dimostrando il nostro impegno di lungo periodo e la volont\u00e0 di proteggere i principi e i valori che ogni giorno guidano le nostre azioni.\nCrediamo che la diversit\u00e0 sia la chiave del nostro successo e, per questo, siamo impegnati a creare un ambiente di lavoro inclusivo, dove ciascuno possa sentirsi valorizzato per la propria unicit\u00e0. Tutte le nostre opportunit\u00e0 di lavoro sono aperte ai candidati appartenenti alle categorie protette L.68/99.\nScopri il team Cyber Security\nIl nostro team di Cyber Security si impegna ogni giorno nella protezione delle infrastrutture ICT aziendali, sia on-premises che in ambienti cloud.\nLavoriamo con un forte orientamento all\u2019innovazione, adottando architetture avanzate come Zero Trust e Defense in Depth, e ponendo grande attenzione alla gestione delle identit\u00e0 e alla sicurezza delle infrastrutture.\nCompetenze in Infrastructure Security, Networking e Cloud Security, in particolare su ambienti Windows, Microsoft Azure e GCP,\ntrovano spazio per crescere e fare la differenza in contesti complessi e sfidanti. Se cerchi un ambiente dove il valore della sicurezza \u00e8 condiviso e dove l\u2019esperienza si arricchisce ogni giorno a contatto con professionisti di alto livello, potresti essere nel posto giusto.\n\ud83c\udfaf\nLe tue responsabilit\u00e0:\nProgettare, configurare e gestire in modo sicuro le infrastrutture aziendali, garantendo la protezione e l\u2019evoluzione dei componenti critici basati su tecnologie Microsoft per la gestione delle identit\u00e0 e dei servizi. Implementare soluzioni avanzate di sicurezza per ambienti virtualizzati (VMware ESXi, vSphere, vCenter) e integrare politiche di protezione moderne per assicurare resilienza e un\u2019evoluzione continua dell\u2019infrastruttura\nGestire e proteggere le risorse nel cloud, con focus su ambienti Azure e GCP, configurando e ottimizzando la sicurezza di soluzioni Microsoft per il Cloud, quali i servizi Azure (Storage, Virtual Machines, Networking, etc.), e implementando soluzioni di sicurezza in GCP (IAM, Network Security, Security Command Center). Garantire la protezione dei workload cloud attraverso l'adozione di strategie avanzate di\nWorkload Security\n, includendo il monitoraggio delle risorse, la gestione delle vulnerabilit\u00e0 e l\u2019applicazione di controlli di sicurezza per workload ibridi e multi-cloud\nProteggere reti e applicazioni aziendali da minacce esterne e interne come\nDDoS\n,\nspoofing\ne\nman-in-the-middle\n. Implementare e ottimizzare soluzioni di sicurezza, incluse appliance\nNGFW\n(Next-Generation Firewall) e\nWAF\n(Web Application Firewall), per proteggere la rete e le applicazioni web da attacchi sofisticati\nCurare l\u2019adozione di soluzioni\nEntra\nper la gestione delle identit\u00e0, con consolidamento delle politiche di federazione, centralizzazione degli account nel cloud basate su principi di scalabilit\u00e0 e gestione semplificata degli accessi in ottica Zero Trust\nGestire soluzioni avanzate come Microsoft Defender for Endpoint, Microsoft Intune e Defender for Office 365, assicurando un controllo centralizzato sulla sicurezza degli endpoint e la protezione dei dispositivi aziendali. Applicare politiche di MDM per rafforzare la sicurezza e mitigare il rischio di attacchi mirati sui dispostivi\nGestire la risposta agli incidenti di sicurezza attraverso attivit\u00e0 integrate di monitoraggio, auditing e analisi forense, supportando il\nSecurity Operations Center (SOC)\ne l'ottimizzazione di sistemi\nSIEM\n(Security Information and Event Management) e\nSOAR\n(Security Orchestration, Automation, and Response) per migliorare la visibilit\u00e0 e ridurre i tempi di risposta agli incidenti\nAutomatizzare le operazioni di sicurezza e gestione dei sistemi utilizzando strumenti di scripting come\nPowerShell\n,\nBash\n,\nPython\ne\nKQL\n(Kusto Query Language)\nApplicare le migliori pratiche di sicurezza, inclusa la gestione delle vulnerabilit\u00e0,\npatch management\n, configurazione sicura e allineamento alle normative di sicurezza (\nISO 27001\n,\nNIST\n,\nGDPR\n)\nAggiornamento continuo su evoluzioni dell\u2019ecosistema digitale (motori di ricerca, AI, user behavior\u2026)\n\ud83d\ude4c\nSe ti riconosci in queste caratteristiche, potremmo essere il perfetto match:\nLaurea in Informatica, Ingegneria Informatica, Cyber Security o discipline affini. Certificazioni avanzate in ambito Microsoft, come Microsoft Certified: Azure Security Engineer Associate e Microsoft Certified: Security, Compliance, and Identity Fundamentals saranno considerate un ulteriore plus\nAlmeno 5 anni nella gestione della sicurezza IT, con expertise in Microsoft Windows Security, VMware, Cloud Security (Azure e GCP), gestione delle identit\u00e0 e architetture di sicurezza come Zero Trust e Defense in Depth\nEsperienza avanzata con Microsoft Security, VMware (vSphere, vCenter, ESXi), soluzioni di Identity and Access Management (IAM) e la gestione della sicurezza in ambienti cloud (Azure, GCP)\nCapacit\u00e0 di analizzare e risolvere problemi complessi di sicurezza, implementando soluzioni di mitigazione dei rischi e ottimizzando la protezione delle risorse aziendali\nOttima conoscenza dell'inglese sia scritto che parlato, per interagire con team internazionali\nEccellenti capacit\u00e0 comunicative, abilit\u00e0 nel lavorare in team, problem-solving e gestione delle priorit\u00e0 in ambienti complessi\n\ud83d\udc9c\nScopri in questo video le ragioni per cui scegliere JAKALA come prossimo step di carriera\nIn JAKALA crediamo che il tempo e il benessere delle persone vadano rispettati, sempre: incoraggiamo una presenza in ufficio di10giorni al mese, lasciando piena libert\u00e0 di lavorare da dove preferisci, sia in Italia che all\u2019interno della Comunit\u00e0 Europea.\nIl nostro sistema di Total\u00a0Reward\u00a0include convenzioni esclusive per viaggi, ristoranti, shopping, palestra e tempo libero, oltre a servizi gratuiti di telemedicina e supporto psicologico, pensati per te e per chi ami.\nInvestire nel nostro processo di selezione significa ricevere supporto autentico: un Recruiter dedicato ti accompagner\u00e0 con feedback personalizzati, consigli di carriera e insight sul tuo CV, a prescindere dall\u2019esito della candidatura. Niente AI, solo persone. E, grazie all\u2019iniziativa Your Time Back, ti restituiamo il tempo investito nei colloqui con un percorso di empowerment firmato Unobravo.\n\ud83c\udf31\nReady to start?\nNon \u00e8 solo una candidatura. \u00c8 un percorso che comincia ora. Inviaci il tuo CV: non vediamo l\u2019ora di conoscerti!\nBack\nApply\nShare this job:\nFacebook\nLinkedIn\nEmail",
        "application_url": "https://careers.jakala.com/en_US/careers/ApplicationMethods?jobId=1803",
        "": {},
        "metadata": {
            "Office": "Milano",
            "Country": "Italy",
            "Date Published": "05-Mar-2025",
            "Ref #": "1774",
            "Area": "Cyber Security",
            "Type of Presence": "Hybrid"
        },
        "link": "https://careers.jakala.com/en_US/careers/JobDetail/Experienced-Professional-Cyber-Security/1803"
    },
    {
        "title": "(Senior) Project Manager (all genders)",
        "description_html": null,
        "description_text": "General information\nOffice\nHamburg\nCountry\nGermany\nDate Published\n03-Mar-2025\nRef #\n1772\nArea\nProject Management\nType of Presence\nHybrid\nDescription & Requirements\nOb als (Senior) Project-Manager, Berater:in, Account-Executive, TPM oder Product Owner \u2013 wenn du ein erfahrener Profi bist, der komplexe Projekte mit strategischem Weitblick und operativer Exzellenz steuert, bist du bei uns genau richtig. Du zeichnest dich durch klare Kommunikation und effektives Team- und Kundenmanagement aus? Dann m\u00f6chten wir dich in unserem Team willkommen hei\u00dfen!\nF\u00fcr eines unserer gr\u00f6\u00dften Studios suchen wir zum n\u00e4chstm\u00f6glichen Zeitpunkt einen motivierten und engagierten (Senior) Project Manager (all genders) in Hamburg.\nResponsibilities\nProjektsteuerung: Du leitest komplexe Multiscreen-Projekte effizient und strukturiert, immer mit \u00dcberblick \u00fcber alle Tasks.\nPersonalplanung: Du planst das Projektpersonal und sorgst durch cleveres Controlling und Reporting f\u00fcr transparente Kommunikation mit Kunden und internen Stakeholdern.\nKundenberatung: Du stehst im engen Austausch mit Kunden, agierst souver\u00e4n als Consultant und teilst deine fundierte Meinung.\nInterne Zusammenarbeit: Du triffst Entscheidungen gemeinsam mit Kolleg:innen aus UI/UX, User Research, Informationsarchitektur, Softwareentwicklung, DevOps und QA.\nOverview\nJAKALA ist ein weltweit t\u00e4tiges IT- und Consulting-Unternehmen im Bereich Martech, mit einem starken Fokus auf Daten und KI. Von den weltweit \u00fcber 3.300 Mitarbeitenden sind rund 230 in Hamburg und Berlin t\u00e4tig. Bei JAKALA Germany liegt der Schwerpunkt auf der Entwicklung von individuellen Software-L\u00f6sungen, haupts\u00e4chlich von sogenannten Digital Experience Platforms (DXP), in denen Gesch\u00e4ftsprozesse entlang der Customer Journey digitalisiert werden. An der Schnittstelle von Strategie, Design und Technologie entwickelt JAKALA digitale Plattformen, Apps und andere Services, welche die digitalen Erlebnisse gro\u00dfer Marken ma\u00dfgeblich pr\u00e4gen. Zu den Kunden in Deutschland z\u00e4hlen beispielsweise TUI Cruises, Leica, die Hamburger Hochbahn oder das ZDF.\nQualifications\nDu verf\u00fcgst \u00fcber mehrere Jahre Erfahrung in einer Digitalagentur, einem Startup oder einem digitalen Innovationsumfeld.\nDu hast ein tiefes Verst\u00e4ndnis f\u00fcr digitale Produktentwicklung und hast idealerweise Erfahrung in der Leitung von Softwareentwicklungsprojekten gesammelt.\nScrum oder Kanban sind f\u00fcr dich keine Fremdw\u00f6rter und du f\u00fchlst dich mit Tools wie Jira und Confluence wohl.\nVerantwortung zu \u00fcbernehmen und Prozesse mit Leidenschaft neu zu gestalten ist f\u00fcr dich selbstverst\u00e4ndlich.\nDu kannst zeigen, dass du Projekte erfolgreich, p\u00fcnktlich und im Budgetrahmen abschlie\u00dfen kannst.\nDu liebst es, in interdisziplin\u00e4ren Teams zu arbeiten und sch\u00e4tzt den Austausch mit Kolleg:innen aus verschiedenen Bereichen.\nDu beherrschst Deutsch perfekt in Wort und Schrift und f\u00fchlst dich auch in der englischen Kommunikation sicher.\nOffer\nDas bieten wir dir:\nJob in Vollzeit oder Teilzeit - du entscheidest\nHybrides Arbeitsmodell (Remote und B\u00fcro) mit flexiblen Arbeitszeiten\nOffene und teamorientierte Unternehmenskultur\nWertsch\u00e4tzung deiner Ideen\nZuschuss f\u00fcr \u00d6PNV und Bikeleasing-Option\nUrban Sport Club Membership\nW\u00f6chentliches gemeinsames Fr\u00fchst\u00fcck oder Mittagessen\nWenn du willst: Einstieg in unsere Hamburger Band (Schlagzeuger:in gesucht)\nWhat else?\nWir wollen einen positiven Impact auf unsere Erde haben. Deshalb streben wir danach, auf nachhaltige Weise Wert f\u00fcr alle Interessengruppen zu schaffen und ber\u00fccksichtigen dabei Klima, Ethik und Qualit\u00e4t. 2021 haben wir uns entschieden, eine Benefit Corporation zu werden, um unser langfristiges Engagement f\u00fcr den Schutz der Prinzipien und Werte, die unser Handeln leiten, zu unterstreichen.\nBewirb dich noch heute. Wir freuen uns darauf, dich kennenzulernen.\nBack\nApply\nShare this job:\nFacebook\nLinkedIn\nEmail",
        "application_url": "https://careers.jakala.com/en_US/careers/ApplicationMethods?jobId=1801",
        "": {},
        "metadata": {
            "Office": "Hamburg",
            "Country": "Germany",
            "Date Published": "03-Mar-2025",
            "Ref #": "1772",
            "Area": "Project Management",
            "Type of Presence": "Hybrid"
        },
        "link": "https://careers.jakala.com/en_US/careers/JobDetail/Senior-Project-Manager-all-genders/1801"
    },
    {
        "title": "Experienced Professional | Technical Project Manager",
        "description_html": null,
        "description_text": "General information\nOffice\nMilano\nCountry\nItaly\nDate Published\n28-Feb-2025\nRef #\n1765\nArea\nProject Management\nType of Presence\nHybrid\nDescription & Requirements\n\ud83d\udccd\nSede\n: Milano, Napoli\n\ud83d\udc40\nRank:\nAssociate Manager\nChi siamo\nJAKALA \u00e8 un'azienda che lavora su dati, intelligenza artificiale e sviluppo di esperienze per generare un impatto significativo e duraturo a livello globale.\nPresenti in oltre 30 citt\u00e0 in 21 paesi,\u00a0i nostri team\u00a0uniscono competenze su strategia, tecnologia, creativit\u00e0 e\u00a0operations\u00a0per offrire esperienze personalizzate e soluzioni trasformative ai nostri clienti, grazie al supporto di dati e intelligenza artificiale. I\u00a0Jakalers\u00a0sono un gruppo eterogeneo di oltre 3.000 persone, animate da passione, ambizione e idee brillanti. Proprio questa combinazione unica di talenti \u00e8 il fattore distintivo che ha ispirato il nostro\u00a0purpose:\u00a0Together\u00a0to\u00a0get\u00a0there.\nCreare un mondo migliore \u00e8 il nostro obiettivo ultimo: la nostra ambizione \u00e8 generare valore per tutti i nostri stakeholder in modo sostenibile, con particolare attenzione a etica, clima e qualit\u00e0. Nel 2021, abbiamo scelto di diventare una Societ\u00e0 Benefit, dimostrando il nostro impegno di lungo periodo e la volont\u00e0 di proteggere i principi e i valori che ogni giorno guidano le nostre azioni.\nCrediamo che la diversit\u00e0 sia la chiave del nostro successo e, per questo, siamo impegnati a creare un ambiente di lavoro inclusivo, dove ciascuno possa sentirsi valorizzato per la propria unicit\u00e0. Tutte le nostre opportunit\u00e0 di lavoro sono aperte ai candidati appartenenti alle categorie protette L.68/99.\nScopri il team Project Management\nAll\u2019interno dell\u2019area Project Management di JAKALA, avrai l\u2019opportunit\u00e0 di supportare progetti complessi in ambito Digital, CRM, Data e Marketing Automation, contribuendo alla loro pianificazione, esecuzione e monitoraggio. Entrerai in un team strutturato e collaborativo, dove potrai coordinarti con stakeholder nazionali e internazionali, utilizzare strumenti avanzati di project management e contribuire al miglioramento continuo dei processi operativi.\n\ud83c\udfaf\nLe tue responsabilit\u00e0:\nCreazione e gestione di piani di progetto dettagliati (incluso Gantt) per monitorare tempi e milestone;\nIdentificazione e mitigazione dei rischi di progetto, garantendo il raggiungimento degli obiettivi;\nControllo del budget di progetto, assicurando l\u2019allocazione efficiente delle risorse;\nCoordinamento dei team di sviluppo, analisi e business, favorendo una comunicazione chiara tra stakeholder tecnici e non;\nSupervisione dell'integrazione e migrazione di sistemi IT (Adobe, Salesforce, Dynamics);\nComunicazione fluente in inglese con team internazionali e stakeholder;\nUtilizzo di metodologie Agile e Waterfall, a seconda delle esigenze del progetto;\nReporting dello stato di avanzamento, KPI e metriche di progetto.\n\ud83d\ude4c\nSe ti riconosci in queste caratteristiche, potremmo essere il perfetto match:\nEsperienza di almeno 5 anni come Project Manager in ambito tecnologico.\nConoscenza avanzata degli strumenti di gestione progetti (MS Project, JIRA, Trello, Asana, Monday.com);\nEsperienza pratica nella creazione di Gantt, gestione di rischi e controllo del budget;\nBackground tecnico con esperienza in progetti su Adobe, Salesforce, Microsoft Dynamics;\nFamiliarit\u00e0 con processi di migrazione e integrazione di sistemi IT;\nOttima capacit\u00e0 di problem solving, leadership e gestione delle priorit\u00e0;\nOttima conoscenza dell\u2019inglese scritto e parlato.\nCertificazioni PMP, PRINCE2, Agile/Scrum\nEsperienza in settori come e-commerce, CRM, ERP, Martech\nConoscenza di strumenti di Business Intelligence e Data Analytics.\n\ud83d\udc9c\nScopri in questo video le ragioni per cui scegliere JAKALA come prossimo step di carriera\nIn JAKALA crediamo che il tempo e il benessere delle persone vadano rispettati, sempre: incoraggiamo una presenza in ufficio di\n10\ngiorni al mese, lasciando piena libert\u00e0 di lavorare da dove preferisci, sia in Italia che all\u2019interno della Comunit\u00e0 Europea.\nIl nostro sistema di Total\nReward\ninclude convenzioni esclusive per viaggi, ristoranti, shopping, palestra e tempo libero, oltre a servizi gratuiti di telemedicina e supporto psicologico, pensati per te e per chi ami.\nInvestire nel nostro processo di selezione significa ricevere supporto autentico: un Recruiter dedicato ti accompagner\u00e0 con feedback personalizzati, consigli di carriera e insight sul tuo CV, a prescindere dall\u2019esito della candidatura. Niente AI, solo persone. E, grazie all\u2019iniziativa Your Time Back, ti restituiamo il tempo investito nei colloqui con un percorso di empowerment firmato\nUnobravo\n.\n\ud83c\udf31 Ready to start?\nNon \u00e8 solo una candidatura. \u00c8 un percorso che comincia ora. Inviaci il tuo CV: non vediamo l\u2019ora di conoscerti!\nBack\nApply\nShare this job:\nFacebook\nLinkedIn\nEmail",
        "application_url": "https://careers.jakala.com/en_US/careers/ApplicationMethods?jobId=1794",
        "": {},
        "metadata": {
            "Office": "Milano",
            "Country": "Italy",
            "Date Published": "28-Feb-2025",
            "Ref #": "1765",
            "Area": "Project Management",
            "Type of Presence": "Hybrid"
        },
        "link": "https://careers.jakala.com/en_US/careers/JobDetail/Experienced-Professional-Technical-Project-Manager/1794"
    },
    {
        "title": "Solution Architect (all genders) - PreSales & Consulting \u2013 Digitale Services & Applikationen",
        "description_html": null,
        "description_text": "General information\nOffice\nBerlin, Hamburg, Vienna\nCountry\nGermany\nDate Published\n14-Feb-2025\nRef #\n1731\nArea\nIT and Information Systems\nType of Presence\nHybrid\nDescription & Requirements\nDu bist ein enthusiastischer Techniker/Entwickler mit einem breiten Verst\u00e4ndnis des Aufbaus von digitalen Applikationen und liebst es, die Infrastruktur und Komponenten dieser l\u00f6sungsorientiert und nachhaltig zu entwerfen? Du verstehst es, komplexe IT-Konzepte klar und verst\u00e4ndlich zu pr\u00e4sentieren und Kunden von der Wertsch\u00f6pfung deiner Visionen zu \u00fcberzeugen? Du bist offen f\u00fcr neue Technologien? Dann bist du genau richtig bei uns!\nWir suchen zum n\u00e4chstm\u00f6glichen Zeitpunkt einen erfahrenen Solution\nArchitect\n(all\ngenders\n) f\u00fcr unser Team in Hamburg, Berlin oder Wien. Diese Rolle umfasst die Unterst\u00fctzung der Vertriebsteams im\nPre\n-Sales-Prozess durch technisches\nKnow-How\n,\nsowie die technische Beratung\nund Begleitung\neinzelner\nKundenprojekte\n.\nDie Rolle\nsteht auch im engen Austausch mit dem internen Innovation-Hub, damit Anfragen des Kunden sowie neue Impulse aus dem Hub in beide Richtungen transportiert werden.\nResponsibilities\nDu analysierst die Anforderungen der\nKund:innen\n, entwickelst ma\u00dfgeschneiderte L\u00f6sungen und ber\u00e4tst sie in technischen Fragen hinsichtlich der besten Technologien und Best Practices. Dabei hilfst du sowohl bestehenden als auch neuen\nKund:innen\n, die passenden L\u00f6sungen zu evaluieren und auszuw\u00e4hlen.\nGemeinsam mit unseren\nKund:innen\nentwickelst du digitale Strategien, die auf ihre Gesch\u00e4ftsziele abgestimmt sind. Du verschaffst dir einen \u00dcberblick \u00fcber ihre gesch\u00e4ftliche und technische Landschaft, identifizierst Chancen, minimierst Risiken und w\u00e4hlst die optimalen Technologien aus.\nBasierend auf den Anforderungen der\nKund:innen\nentwirfst du eine durchdachte und effektive L\u00f6sung. Du arbeitest eng mit den Teams aus Experience, Vertrieb und Service\nDelivery\nzusammen, um eine ganzheitliche Umsetzung sicherzustellen.\nDu bereitest die L\u00f6sungsdokumentation vor und \u00fcbergibst sie an das Projektteam f\u00fcr die Umsetzung.\nW\u00e4hrend laufender Projekte unterst\u00fctzt du das\nDelivery\n-Team, ber\u00e4tst das Account-Management zu\nKund:innenpotenzialen\nund Risiken. Gleichzeitig identifizierst du Chancen f\u00fcr neue Dienstleistungen und M\u00f6glichkeiten f\u00fcr eine engere und effizientere Zusammenarbeit mit dem Kunden.\nOverview\nJAKALA ist ein weltweit t\u00e4tiges IT- und Consulting-Unternehmen im Bereich\nMartech\n, mit einem starken Fokus auf Daten und KI. Von den weltweit \u00fcber 3.300 Mitarbeitenden sind rund 230 in Hamburg und Berlin t\u00e4tig. Bei JAKALA Germany liegt der Schwerpunkt auf der Entwicklung von individuellen Software-L\u00f6sungen, haupts\u00e4chlich von sogenannten Digital Experience\nPlatforms\n(DXP), in denen Gesch\u00e4ftsprozesse entlang der Customer Journey digitalisiert werden. An der Schnittstelle von Strategie, Design und Technologie entwickelt JAKALA digitale Plattformen, Apps und andere Services, welche die digitalen Erlebnisse gro\u00dfer Marken ma\u00dfgeblich pr\u00e4gen. Zu den Kunden in Deutschland z\u00e4hlen beispielsweise TUI Cruises, Leica, die Hamburger Hochbahn oder das ZDF.\nQualifications\nAbgeschlossenes Bachelor-Studium in Informatik, Ingenieurwesen oder einem verwandten Bereich sowie relevante Berufserfahrung\nMindestens 5 Jahre Erfahrung in der Entwicklung und Umsetzung ma\u00dfgeschneiderter IT-L\u00f6sungen\nFundierte Kenntnisse in den Konzepten der IT-Architektur sowie Softwareentwicklung und Systemintegration\nKenntnisse im Aufbau von modernen Web- und nativen mobilen Applikationen\nF\u00e4higkeit, komplexe technische Themen klar und verst\u00e4ndlich zu vermitteln \u2013 sowohl m\u00fcndlich als auch in Pr\u00e4sentationen\nProaktive Zusammenarbeit mit Teammitgliedern,\nKolleg:innen\nund\nNetzwerkpartner:innen\n, um Ideen und\nInsights\nzu gewinnen\nSt\u00e4ndiges Interesse an technologischen Entwicklungen sowie die F\u00e4higkeit, fundierte Empfehlungen f\u00fcr neue L\u00f6sungen abzuleiten\nBereitschaft, sich tief in neue Themen einzuarbeiten, um\nKund:innen\noptimal zu unterst\u00fctzen\nKenntnisse in Netzwerkkonzepten, -protokollen sowie bew\u00e4hrten Sicherheitspraktiken und Tools\nVerhandlungssichere Deutsch- und Englischkenntnisse\nOffer\nDas bieten wir dir:\nJob in Vollzeit oder Teilzeit - du entscheidest\nHybrides Arbeitsmodell (Remote und/oder B\u00fcro) mit flexiblen Arbeitszeiten\nOffene und teamorientierte Unternehmenskultur\nWertsch\u00e4tzung deiner Ideen\nZuschuss f\u00fcr \u00d6PNV, Mobilit\u00e4tsbudget,\nBikeleasing\n-Option\nUrban Sports Club Membership\nW\u00f6chentliches gemeinsames Fr\u00fchst\u00fcck oder Mittagessen\nWenn du willst: Einstieg in unsere Hamburger Band (\nS\u00e4nger:in\ngesucht)\nWhat\nelse\n?\nWir wollen einen positiven Impact auf unsere Erde haben. Deshalb streben wir danach, auf nachhaltige Weise Wert f\u00fcr alle Interessengruppen zu schaffen und ber\u00fccksichtigen dabei Klima, Ethik und Qualit\u00e4t. 2021 haben wir uns entschieden, eine Benefit Corporation zu werden, um unser langfristiges Engagement f\u00fcr den Schutz der Prinzipien und Werte, die unser Handeln leiten, zu unterstreichen.\nBewirb dich noch heute. Wir freuen uns darauf, dich kennenzulernen.\nBack\nApply\nShare this job:\nFacebook\nLinkedIn\nEmail",
        "application_url": "https://careers.jakala.com/en_US/careers/ApplicationMethods?jobId=1760",
        "": {},
        "metadata": {
            "Office": "Berlin, Hamburg, Vienna",
            "Country": "Germany",
            "Date Published": "14-Feb-2025",
            "Ref #": "1731",
            "Area": "IT and Information Systems",
            "Type of Presence": "Hybrid"
        },
        "link": "https://careers.jakala.com/en_US/careers/JobDetail/Solution-Architect-all-genders-PreSales-Consulting-Digitale-Services-Applikationen/1760"
    },
    {
        "title": "Paid Media Manager",
        "description_html": null,
        "description_text": "General information\nOffice\nLondon\nCountry\nUnited Kingdom\nDate Published\n31-Jan-2025\nRef #\n1708\nArea\nMarketing\nType of Presence\nHybrid\nDescription & Requirements\nJob\u00a0description\nWe are Jakala: an award winning organisation that offers world's leading brands support in the strategy, analytics, digital and technology fields. Our mission is to create competitive advantage for our clients, with a measurable impact on the top line, through the best combined use of Data, Advanced and Location Analytics, technologies, content and customer experience design. We are 3,000 people in 20 countries around world, growing at a fast-pace. For our digital & media division, we are looking for brilliant candidates that are enthusiastic about digital marketing to join our media team in our London office as a Paid Media Manager to be a part of this exciting growth phase. If you are looking for an international company with people that share the same digital passion as you do, Jakala could be the place for you!\nThe\u00a0Role\n\u2022\u00a0The\u00a0Paid\u00a0Media\u00a0Manager\u00a0will\u00a0be\u00a0working\u00a0on\u00a0a\u00a0variety\u00a0of\u00a0international\u00a0media\u00a0accounts\u00a0from\u00a0different\u00a0verticals\n\u2022\u00a0You\u00a0will\u00a0manage\u00a0client\u00a0updates\u00a0on\u00a0performance,\u00a0and\u00a0be\u00a0the\u00a0main\u00a0point\u00a0of\u00a0contact\u00a0for\u00a0day\u00a0to\u00a0day\u00a0queries\nThe\u00a0Responsibilities\n\u2022\u00a0Lead\u00a0the\u00a0planning,\u00a0implementation\u00a0and\u00a0execution\u00a0of\u00a0Paid\u00a0Search,\u00a0Social\u00a0and\u00a0Programmatic\u00a0campaigns,\u00a0depending\u00a0on\u00a0the\u00a0clients\u2019\u00a0needs\u00a0and\u00a0objectives.\n\u2022\u00a0Being\u00a0on\u00a0top\u00a0of\u00a0the\u00a0campaign\u00a0performance,\u00a0analysing\u00a0and\u00a0optimising\u00a0the\u00a0campaigns\u00a0on\u00a0a\u00a0regular\u00a0basis,\u00a0providing\u00a0recommendations\u00a0to\u00a0the\u00a0clients\u00a0based\u00a0on\u00a0a\u00a0deep\u00a0analysis\u00a0of\u00a0market\u00a0conditions\u00a0and\u00a0campaign\u00a0results\u00a0\u2013hence\u00a0strong\u00a0analytical\u00a0skills\u00a0are\u00a0essential.\n\u2022\u00a0Effectively\u00a0manage\u00a0any\u00a0external/internal\u00a0queries/issues\u00a0on\u00a0Account.\n\u2022\u00a0Support\u00a0the\u00a0Account\u00a0Director\u00a0in\u00a0overseeing\u00a0and\u00a0resolve\u00a0weekly\u00a0and/or\u00a0daily\u00a0campaign\u00a0QA\u00a0reports\u00a0to\u00a0ensure\u00a0accurate\u00a0campaign\u00a0results\u00a0and\u00a0trafficking\u00a0routines.\n\u2022\u00a0Developing\u00a0strong\u00a0client\u00a0relationships,\u00a0assisting\u00a0with\u00a0providing\u00a0technical\u00a0expertise\u00a0to\u00a0the\u00a0client\u00a0and\u00a0be\u00a0able\u00a0to\u00a0explain\u00a0campaign\u00a0progress.\n\u2022\u00a0Contributing\u00a0in\u00a0strategic\u00a0creative\u00a0planning\u00a0meetings,\u00a0to\u00a0support\u00a0the\u00a0other\u00a0team\u00a0members\u00a0when\u00a0needed.\n\u2022\u00a0Assessment\u00a0of\u00a0data\u00a0to\u00a0make\u00a0performance-based\u00a0decisions\u00a0on\u00a0media\u00a0and\u00a0campaign\u00a0optimisation.\n\u2022\u00a0Ensuring\u00a0that\u00a0all\u00a0company\u00a0financial\u00a0processes\u00a0and\u00a0deadlines\u00a0put\u00a0in\u00a0place\u00a0are\u00a0adhered\u00a0to,\u00a0and\u00a0that\u00a0all\u00a0work\u00a0is\u00a0produced\u00a0to\u00a0a\u00a0high\u00a0degree\u00a0of\u00a0accuracy.\n\u2022\u00a0Working\u00a0closely\u00a0with\u00a0both\u00a0agency\u00a0stakeholders,\u00a0and\u00a0clients\u00a0to\u00a0ensure\u00a0that\u00a0all\u00a0account/campaign\u00a0strategies\u00a0are\u00a0delivered.\n\u2022\u00a0Working\u00a0as\u00a0part\u00a0of\u00a0a\u00a0team\u00a0to\u00a0ensure\u00a0a\u00a0high\u00a0level\u00a0of\u00a0service\u00a0across\u00a0digital\u00a0platforms.\n\u2022\u00a0Keeping\u00a0up\u00a0to\u00a0date\u00a0with\u00a0industry\u00a0developments\u00a0and\u00a0responsible\u00a0for\u00a0sharing\u00a0news\u00a0and\u00a0information\u00a0with\u00a0the\u00a0rest\u00a0of\u00a0the\u00a0team,\u00a0as\u00a0well\u00a0as\u00a0with\u00a0clients.\nThe\u00a0Ideal\u00a0Candidate\n\u2022\u00a0Minimum\u00a03\u00a0years\u00a0Paid\u00a0Media\u00a0(ideally\u00a0both\u00a0PPC\u00a0and\u00a0Paid\u00a0Social)\u00a0experience.\n\u2022 Has a previous track record with client management, paid media management (both hands-on management, implementation and strategy) and managing / coordinating junior media resources\n\u2022 Is a results-driven and analytical person that has demonstrated great results in campaign management and has strong data analysis and interpretation skills which would be put to use as an input for the media campaign strategy\n\u2022\u00a0Excellent\u00a0communication\u00a0and\u00a0presentation\u00a0skills\n\u2022\u00a0Innovative\u00a0and\u00a0creative\u00a0thinker\u00a0with\u00a0the\u00a0ability\u00a0to\u00a0educate\u00a0clients\u00a0on\u00a0new\u00a0revenue\u00a0and\u00a0performance\u00a0models\n\u2022\u00a0Strong\u00a0attention\u00a0to\u00a0detail\u00a0with\u00a0the\u00a0ability\u00a0to\u00a0work\u00a0under\u00a0pressure\n\u2022\u00a0Has\u00a0great\u00a0time\u00a0management\u00a0and\u00a0organisational\u00a0skills\u00a0as\u00a0well\u00a0as\u00a0the\u00a0ability\u00a0to\u00a0multitask\n\u2022\u00a0Able\u00a0to\u00a0meet\u00a0deadlines\u00a0in\u00a0a\u00a0fast-paced\u00a0dynamic\u00a0industry\n\u2022\u00a0Must\u00a0demonstrate\u00a0strong\u00a0troubleshooting\u00a0and\u00a0problem-solving\u00a0skills.\n\u2022\u00a0Strong\u00a0understanding\u00a0of\u00a0Excel\u00a0e.g.\u00a0Pivot\u00a0Tables,\u00a0IF\u00a0/\u00a0SUMIF\u00a0/\u00a0Concatenate\u00a0/\u00a0VLOOKUP\u00a0etc.\u00a0formulas\n\u2022\u00a0Fluency\u00a0in\u00a0English\u00a0and\u00a0French\n\u2022\u00a0Has\u00a0a\u00a0valid\u00a0permit\u00a0to\u00a0live\u00a0and\u00a0work\u00a0in\u00a0the\u00a0UK\nBenefits\n\u2022\u00a0Pension\u00a0matching\u00a0up\u00a0to\u00a06%\n\u2022\u00a0Private\u00a0Medical\u00a0Insurance\u00a0and\u00a0Private\u00a0Dental\u00a0Insurance\n\u2022\u00a0Income\u00a0Protection\n\u2022\u00a0Life\u00a0Assurance\n\u2022\u00a0Gym\u00a0Membership\n\u2022\u00a0Cycle\u00a0to\u00a0Work\u00a0Scheme\n\u2022\u00a0Team\u00a0socials\u00a0throughout\u00a0the\u00a0year\n\u2022\u00a0Charity\u00a0volunteer\u00a0days\u00a0\u2013\u00a04\u00a0days\u00a0a\u00a0year\u00a0to\u00a0work\u00a0for\u00a0a\u00a0charity\u00a0of\u00a0your\u00a0choice\n\u2022\u00a0Workplace\u00a0Nursery\u00a0Scheme\u00a0\u2013\u00a0to\u00a0help\u00a0cover\u00a0childcare\u00a0costs\u00a0through\u00a0salary\u00a0sacrifice\n\u2022\u00a0Extra\u00a0office\u00a0perks\n\u2022 Enhanced Maternity & Paternity leave\nBack\nApply\nShare this job:\nFacebook\nLinkedIn\nEmail",
        "application_url": "https://careers.jakala.com/en_US/careers/ApplicationMethods?jobId=1737",
        "": {},
        "metadata": {
            "Office": "London",
            "Country": "United Kingdom",
            "Date Published": "31-Jan-2025",
            "Ref #": "1708",
            "Area": "Marketing",
            "Type of Presence": "Hybrid"
        },
        "link": "https://careers.jakala.com/en_US/careers/JobDetail/Paid-Media-Manager/1737"
    },
    {
        "title": "Senior Media Executive",
        "description_html": null,
        "description_text": "General information\nOffice\nLondon\nCountry\nUnited Kingdom\nDate Published\n30-Jan-2025\nRef #\n1706\nArea\nMarketing\nDescription & Requirements\nJob description\nJAKALA is a data, AI, and experiences company that creates meaningful and lasting impact globally.\nAcross more than 30 cities in 21 countries, our people combine strategy, technology, creativity, and operations to deliver tailored experiences and transformative solutions with data and AI at the heart. Jakalers are a diverse and multifaceted group of more than 3,000 individuals with passion, ambition and bright ideas. This unique mix of talents has become the distinctive factor that inspired our purpose: Together to get there.\nAt JAKALA, creating a better world is our ultimate purpose; we aim at creating value for all stakeholders in a sustainable way with a focus on ethics, climate and quality. In 2021, we decided to become a Benefit Corporation, demonstrating our long-term commitment to protecting the principles and values that guide our actions.\nFor our digital & media division, we are looking for brilliant candidates that are enthusiastic about digital marketing to join our media team in our London office as a Paid Media Executive to be a part of this exciting growth phase.\nIf you are looking for an international company with people that share the same digital passion as you do, Jakala could be the place for you!\nThe Role\nThe Media Account Executive will be working on a variety of international media accounts from different verticals\nYou will be working with the account managers and account director overseeing these accounts to successfully on-board the client by contributing to the setup of the campaign structure and strategy as well as proactively working on driving continuously improved performance of the campaigns\nThis position is designed to prepare a junior level candidate for an senior media executive role so you will be introduced to advanced setup, bidding & optimisation, and planning of media campaigns, as well as client management techniques\nThe Responsibilities\nManagement of campaign creation, ad copy and creative strategy & optimisation.\nManagement of creative tag creation and upload\nManagement of keyword and placement selection, implementation and optimisation strategy.\nMonitor delivery of client campaigns and the media budget spend.\nShow a clear understanding of the dynamics between key KPI\u2019s & comment on weekly performance fluctuations\nWorking closely with the Account Director and Account Managers to ensure that all account/campaign strategies are delivered, while adhering to the deadlines given by Client and Account Manager.\nEffectively manage any external/internal queries/issues on Account\nThe Ideal Candidate\nThe PPC Account Executive will need to have at least 2 year experience working within Paid Search and/or Paid Social Marketing, ideally delivering performance based results.\nGoogle Adwords Professional qualification is desirable (or at least strong working knowledge of Google Adwords)\nProficient in MS Office, including Excel (with VLookups, If statements, pivot tables, using filters and etc.), Word and PowerPoint.\nStrong numerical and analytical skills\nExperience of working on small to medium PPC accounts\nComfortable with using presentation tools (e.g. PowerPoint, Keynote etc.) and confident in presenting in front of people\nPassionate about digital media and committed to building a career in digital marketing\nA self-starter and a team-player\nHas great time management and organisational skills as well as the ability to multitask\nHas a great attention to detail and a problem-solving attitude\nFluency in English is a must and a second European language (French, German, Italian or Spanish) is highly desirable.\nBenefits\nPension matching up to 6%\nPrivate Medical Insurance and Private Dental Insurance\nIncome Protection\nLife Assurance\nGym Membership\nCycle to Work Scheme\nTeam socials throughout the year\nCharity volunteer days \u2013 4 days a year to work for a charity of your choice\nWorkplace Nursery Scheme \u2013 to help cover childcare costs through salary sacrifice\nExtra office perks\nEnhanced Maternity & Paternity leave\nBack\nApply\nShare this job:\nFacebook\nLinkedIn\nEmail",
        "application_url": "https://careers.jakala.com/en_US/careers/ApplicationMethods?jobId=1735",
        "": {},
        "metadata": {
            "Office": "London",
            "Country": "United Kingdom",
            "Date Published": "30-Jan-2025",
            "Ref #": "1706",
            "Area": "Marketing"
        },
        "link": "https://careers.jakala.com/en_US/careers/JobDetail/Senior-Media-Executive/1735"
    },
    {
        "title": "Data Visualization Specialist",
        "description_html": null,
        "description_text": "General information\nOffice\nRiga\nCountry\nLatvia\nDate Published\n21-Jan-2025\nRef #\n1684\nArea\nIT and Information Systems\nType of Presence\nRemote\nDescription & Requirements\nAbout Us\nWe are Jakala: an award-winning organization that offers world's leading brands support in the strategy, analytics, digital and technology fields. Our mission is to create competitive advantage for our clients, with a measurable impact on the top line, through the best combined use of Data, Advanced and Location Analytics, technologies, content and customer experience design. We are 3,500 people in 20 countries around world, growing at a fast-pace.\nAs we expand, we are looking for a\nJunior Data Visualization Specialist\nto join our team in Riga. This role will focus on\nSalesforce Datorama\n, helping transform marketing and business data into actionable insights.\nIf you are looking for an international company with people that share the same digital passion as you do, Jakala could be the place for you!\nKey Responsibilities\nBuild and maintain\ninteractive dashboards and reports\nin\nSalesforce Datorama\nto support internal and client teams.\nGather, clean, and analyze marketing and business data from multiple sources.\nEnsure data accuracy, consistency, and visualization best practices.\nCollaborate with digital marketing, analytics, and client teams to understand reporting needs and deliver insights.\nOptimize data pipelines and dashboard performance for better efficiency.\nProvide ad hoc reports and insights to stakeholders as required.\nRequired Qualifications & Skills\n1+ years of experience\nin\ndata analysis or data visualization\n(preferably in marketing, digital media, or business intelligence).\nHands-on experience with\nSalesforce Datorama\nor a strong willingness to learn it.\nProficiency in\ndata visualization tools\n(such as Tableau, Power BI, Google Data Studio, or similar).\nStrong\nExcel/Google Sheets\nskills (pivot tables, formulas, data manipulation).\nBasic knowledge of\nSQL\nand/or\nJavaScript\nfor dashboard customization is a plus.\nAnalytical mindset with attention to detail and data accuracy.\nHas great time management and organisational skills as well as the ability to multitask\nStrong communication and problem-solving skills.\nAbility to work in a fast-paced environment and manage multiple projects.\nFluency in English is a must, as the role will be collaborating with teams across Europe and Americas\nWhat We Offer\nOpportunity to work with global clients and cutting-edge marketing technologies.\nA collaborative and dynamic work environment.\nProfessional development and training opportunities.\nCompetitive salary and benefits.\nIf you're passionate about\ndata-driven storytelling\nand eager to grow in the world of marketing analytics, we'd love to hear from you!\nBack\nApply\nShare this job:\nFacebook\nLinkedIn\nEmail",
        "application_url": "https://careers.jakala.com/en_US/careers/ApplicationMethods?jobId=1713",
        "": {},
        "metadata": {
            "Office": "Riga",
            "Country": "Latvia",
            "Date Published": "21-Jan-2025",
            "Ref #": "1684",
            "Area": "IT and Information Systems",
            "Type of Presence": "Remote"
        },
        "link": "https://careers.jakala.com/en_US/careers/JobDetail/Data-Visualization-Specialist/1713"
    },
    {
        "title": "Senior Paid Media Executive",
        "description_html": null,
        "description_text": "General information\nOffice\nRiga\nCountry\nLatvia\nDate Published\n16-Jan-2025\nRef #\n1678\nArea\nMarketing\nType of Presence\nHybrid\nDescription & Requirements\nJAKALA is a data, AI, and experiences company that creates meaningful and lasting impact globally.\nAcross more than 30 cities in 21 countries, our people combine strategy, technology, creativity, and operations to deliver tailored experiences and transformative solutions with data and AI at the heart. Jakalers are a diverse and multifaceted group of more than 3,000 individuals with passion, ambition and bright ideas. This unique mix of talents has become the distinctive factor that inspired our purpose: Together to get there.\nAt JAKALA, creating a better world is our ultimate purpose; we aim at creating value for all stakeholders in a sustainable way with a focus on ethics, climate and quality. In 2021, we decided to become a Benefit Corporation, demonstrating our long-term commitment to protecting the principles and values that guide our actions.\nFor our digital & media division, we are looking for brilliant candidates that are enthusiastic about digital marketing to join our media team in our Riga office as a Senior Paid Media Executive to be a part of this exciting growth phase.\nIf you are looking for an international company with people that share the same digital passion as you do, JAKALA could be the place for you!\nThe Role\nThe Senior Media Account Executive will be working on a variety of international media accounts from different verticals\nYou will be working with the account managers and account director overseeing these accounts to successfully on-board the client by contributing to the setup of the campaign structure and strategy as well as proactively working on driving continuously improved performance of the campaigns\nThis position is designed to prepare a junior level candidate for an senior media executive role so you will be introduced to advanced setup, bidding & optimization, and planning of media campaigns, as well as client management techniques\nThe Responsibilities\nManagement of campaign creation, ad copy and creative strategy & optimisation.\nManagement of creative tag creation and upload\nManagement of keyword and placement selection, implementation and optimisation strategy.\nMonitor delivery of client campaigns and the media budget spend.\nShow a clear understanding of the dynamics between key KPI\u2019s & comment on weekly performance fluctuations.\nWorking closely with the Account Director and Account Managers to ensure that all account/campaign strategies are delivered, while adhering to the deadlines given by Client and Account Manager.\nEffectively manage any external/internal queries/issues on Account.\nThe Ideal Candidate\nThe PPC Account Executive will need to have at least 18+ months' experience working within Paid Search and/or Paid Social Marketing, ideally delivering performance based results.\nGoogle Adwords Professional qualification is desirable (or at least strong working knowledge of Google Adwords)\nProficient in MS Office, including Excel (\nwith\u00a0VLookups, If statements, pivot tables, using filters and etc.\n), Word and PowerPoint.\nStrong numerical and analytical skills\nExperience of working on small to medium PPC accounts\nComfortable with using presentation tools (\ne.g. PowerPoint, Keynote etc.\n) and confident in presenting in front of people\nPassionate about digital media and committed to building a career in digital marketing\nA self-starter and a team-player\nHas great time management and organisational skills as well as the ability to multitask\nHas a great attention to detail and a problem-solving attitude\nFluency in English is a must and a second European language (French, German, Italian or Spanish) is highly desirable.\nBack\nApply\nShare this job:\nFacebook\nLinkedIn\nEmail",
        "application_url": "https://careers.jakala.com/en_US/careers/ApplicationMethods?jobId=1707",
        "": {},
        "metadata": {
            "Office": "Riga",
            "Country": "Latvia",
            "Date Published": "16-Jan-2025",
            "Ref #": "1678",
            "Area": "Marketing",
            "Type of Presence": "Hybrid"
        },
        "link": "https://careers.jakala.com/en_US/careers/JobDetail/Senior-Paid-Media-Executive/1707"
    },
    {
        "title": "Senior Programmatic Account Executive",
        "description_html": null,
        "description_text": "General information\nOffice\nLondon\nCountry\nUnited Kingdom\nDate Published\n16-Jan-2025\nRef #\n1679\nArea\nMarketing\nType of Presence\nHybrid\nDescription & Requirements\nJAKALA\u00a0is\u00a0a\u00a0data,\u00a0AI,\u00a0and\u00a0experiences\u00a0company\u00a0that\u00a0creates\u00a0meaningful\u00a0and\u00a0lasting\u00a0impact\u00a0globally.\u00a0Across\u00a0more\u00a0than\u00a030\u00a0cities\u00a0in\u00a021\u00a0countries,\u00a0our\u00a0people\u00a0combine\u00a0strategy,\u00a0technology,\u00a0creativity,\u00a0and\u00a0operations\u00a0to\u00a0deliver\u00a0tailored\u00a0experiences\u00a0and\u00a0transformative\u00a0solutions\u00a0with\u00a0data\u00a0and\u00a0AI\u00a0at\u00a0the\u00a0heart.\nJakalers\u00a0are\u00a0a\u00a0diverse\u00a0and\u00a0multifaceted\u00a0group\u00a0of\u00a0more\u00a0than\u00a03,000\u00a0individuals\u00a0with\u00a0passion,\u00a0ambition\u00a0and\u00a0bright\u00a0ideas.\u00a0This\u00a0unique\u00a0mix\u00a0of\u00a0talents\u00a0has\u00a0become\u00a0the\u00a0distinctive\u00a0factor\u00a0that\u00a0inspired\u00a0our\u00a0purpose:\u00a0Together\u00a0to\u00a0get\u00a0there.\nAt\u00a0JAKALA,\u00a0creating\u00a0a\u00a0better\u00a0world\u00a0is\u00a0our\u00a0ultimate\u00a0purpose;\u00a0we\u00a0aim\u00a0at\u00a0creating\u00a0value\u00a0for\u00a0all\u00a0stakeholders\u00a0in\u00a0a\u00a0sustainable\u00a0way\u00a0with\u00a0a\u00a0focus\u00a0on\u00a0ethics,\u00a0climate\u00a0and\u00a0quality.\u00a0In\u00a02021,\u00a0we\u00a0decided\u00a0to\u00a0become\u00a0a\u00a0Benefit\u00a0Corporation,\u00a0demonstrating\u00a0our\u00a0long-term\u00a0commitment\u00a0to\u00a0protecting\u00a0the\u00a0principles\u00a0and\u00a0values\u00a0that\u00a0guide\u00a0our\u00a0actions.\nFor\u00a0our\u00a0digital\u00a0&\u00a0media\u00a0division,\u00a0we\u00a0are\u00a0looking\u00a0for\u00a0brilliant\u00a0candidates\u00a0that\u00a0are\u00a0enthusiastic\u00a0about\u00a0digital\u00a0marketing\u00a0to\u00a0join\u00a0our\u00a0media\u00a0team\u00a0in\u00a0our\u00a0London\u00a0office\u00a0as\u00a0a\u00a0Senior\u00a0Programmatic\u00a0Manager\u00a0to\u00a0be\u00a0a\u00a0part\u00a0of\u00a0this\u00a0exciting\u00a0growth\u00a0phase.\u00a0If\u00a0you\u00a0are\u00a0looking\u00a0for\u00a0an\u00a0international\u00a0company\u00a0with\u00a0people\u00a0that\u00a0share\u00a0the\u00a0same\u00a0digital\u00a0passion\u00a0as\u00a0you\u00a0do,\u00a0Jakala\u00a0could\u00a0be\u00a0the\u00a0place\u00a0for\u00a0you!\nWhat you'll do;\nLeading\u00a0on\u00a0the\u00a0planning\u00a0and\u00a0implementation\u00a0of\u00a0biddable\u00a0media\u00a0campaigns\u00a0on\u00a0DSPs\u00a0(including\u00a0DoubleClick\u00a0Bid\u00a0Manager,\u00a0Adform,\u00a0Turn\u00a0and\u00a0etc.)\u00a0and\u00a0Ad\u00a0Servers\u00a0(including\u00a0DoubleClick\u00a0Campaign\u00a0Manager\u00a0and\u00a0Adform),\u00a0depending\u00a0on\u00a0the\u00a0clients\u2019\u00a0needs\u00a0and\u00a0objectives\nBeing\u00a0on\u00a0top\u00a0of\u00a0the\u00a0campaign\u00a0performance,\u00a0analysing\u00a0and\u00a0optimizing\u00a0the\u00a0campaigns\u00a0on\u00a0a\u00a0regular\u00a0basis,\u00a0providing\u00a0recommendations\u00a0to\u00a0the\u00a0clients\u00a0based\u00a0on\u00a0a\u00a0deep\u00a0analysis\u00a0of\u00a0market\u00a0conditions\u00a0and\u00a0campaign\u00a0results\u00a0\u2013hence\u00a0strong\u00a0analytical\u00a0skills\u00a0are\u00a0essential\nEffectively\u00a0manage\u00a0any\u00a0external/internal\u00a0queries/issues\u00a0on\u00a0Account\u00a0Management\u00a0of\u00a0tag\u00a0creation,\u00a0campaign\u00a0setup,\u00a0trafficking\u00a0and\u00a0optimization\nExecute\u00a0and\u00a0manage\u00a0online\u00a0media\u00a0campaigns\u00a0for\u00a0agency\u00a0clients\u00a0(e.g.\u00a0auction\u00a0/\u00a0exchange\u00a0based\u00a0performance\u00a0media,\u00a0audience-based\u00a0buying,\u00a0remarketing\u00a0campaigns\u00a0etc.)\nHandle\u00a0daily\u00a0campaign\u00a0maintenance,\u00a0including\u00a0questions\u00a0regarding\u00a0tracking\u00a0and\u00a0status\u00a0of\u00a0various\u00a0campaigns\nResponsible\u00a0for\u00a0the\u00a0management\u00a0of\u00a0the\u00a0relationship\u00a0with\u00a0the\u00a0publishers\u00a0when\u00a0building\u00a0private\u00a0marketplaces\u00a0or\u00a0handling\u00a0direct\u00a0buys\nSupport\u00a0the\u00a0Account\u00a0Director\u00a0in\u00a0overseeing\u00a0and\u00a0resolve\u00a0weekly\u00a0and/or\u00a0daily\u00a0campaign\u00a0QA\u00a0reports\u00a0to\u00a0ensure\u00a0accurate\u00a0campaign\u00a0results\u00a0and\u00a0trafficking\u00a0routines\nDeveloping\u00a0strong\u00a0client\u00a0relationships\u00a0where\u00a0the\u00a0account\u00a0manager\u00a0leads\u00a0the\u00a0weekly\u00a0calls\u00a0with\u00a0clients\u00a0and\u00a0providing\u00a0strategies\u00a0and\u00a0plan\u00a0for\u00a0the\u00a0upcoming\u00a0months\u2019\u00a0KPIs\u00a0during\u00a0the\u00a0face-to-face\u00a0meetings\nEnsuring\u00a0that\u00a0all\u00a0weekly,\u00a0monthly\u00a0&\u00a0ad\u00a0hoc\u00a0client\u00a0reports\u00a0are\u00a0produced\u00a0in\u00a0a\u00a0timely\u00a0and\u00a0accurate\u00a0manner\nContributing\u00a0in\u00a0strategic\u00a0creative\u00a0planning\u00a0meetings,\u00a0to\u00a0support\u00a0the\u00a0other\u00a0team\u00a0members\u00a0when\u00a0needed\nEnsuring\u00a0that\u00a0all\u00a0company\u00a0financial\u00a0processes\u00a0and\u00a0deadlines\u00a0put\u00a0in\u00a0place\u00a0are\u00a0adhered\u00a0to,\u00a0and\u00a0that\u00a0all\u00a0work\u00a0is\u00a0produced\u00a0to\u00a0a\u00a0high\u00a0degree\u00a0of\u00a0accuracy\nShowing\u00a0a\u00a0clear\u00a0understanding\u00a0of\u00a0the\u00a0dynamics\u00a0between\u00a0key\u00a0KPI\u2019s\u00a0&\u00a0comment\u00a0on\u00a0weekly\u00a0performance\u00a0fluctuations\nWorking\u00a0closely\u00a0with\u00a0both\u00a0agency\u00a0stakeholders,\u00a0and\u00a0clients\u00a0to\u00a0ensure\u00a0that\u00a0all\u00a0account/campaign\u00a0strategies\u00a0are\u00a0delivered\nAs\u00a0a\u00a0Senior\u00a0Programmatic\u00a0Account\u00a0Executive,\u00a0you\u00a0will\u00a0play\u00a0a\u00a0key\u00a0role\u00a0in\u00a0the\u00a0execution,\u00a0delivery,\u00a0and\u00a0coordination\u00a0of\u00a0programmatic\u00a0campaigns\u00a0for\u00a0the\u00a0clients\nWhat you'll need;\nAble\u00a0to\u00a0demonstrate\u00a0knowledge\u00a0and\u00a0experience\u00a0in\u00a0Programmatic\u00a0and\u00a0Ad\u00a0Server\u00a0implementations\u00a0(DBM,\u00a0DoubleClick\u00a0Campaign\u00a0Manager\u00a0and\u00a0Adform\u00a0are\u00a0a\u00a0must,\u00a0additional\u00a0experience\u00a0desirable)\u00a0in\u00a0an\u00a0independent\u00a0manner\nIs\u00a0a\u00a0results-driven\u00a0and\u00a0analytical\u00a0person\u00a0that\u00a0has\u00a0demonstrated\u00a0great\u00a0results\u00a0in\u00a0campaign\u00a0management\u00a0and\u00a0has\u00a0strong\u00a0data\u00a0analysis\u00a0and\u00a0interpretation\u00a0skills\u00a0which\u00a0would\u00a0be\u00a0put\u00a0to\u00a0use\u00a0as\u00a0an\u00a0input\u00a0for\u00a0the\u00a0media\u00a0campaign\u00a0strategy\nDeveloped\u00a0a\u00a0functional\u00a0knowledge\u00a0and\u00a0is\u00a0a\u00a0competent\u00a0user\u00a0of\u00a0Excel\nComfortable\u00a0with\u00a0using\u00a0presentation\u00a0tools\u00a0(e.g.\u00a0PowerPoint,\u00a0Keynote\u00a0etc.)\u00a0and\u00a0confident\u00a0in\u00a0presenting\u00a0in\u00a0front\u00a0of\u00a0the\u00a0clients\nPassionate\u00a0about\u00a0digital\u00a0media\u00a0and\u00a0committed\u00a0to\u00a0building\u00a0a\u00a0career\u00a0in\u00a0digital\u00a0marketing\nAble\u00a0to\u00a0assist\u00a0in\u00a0new\u00a0business\u00a0opportunities\u00a0when\u00a0required,\u00a0preparing\u00a0presentations\u00a0or\u00a0helping\u00a0with\u00a0pitches\nA\u00a0self-starter\u00a0and\u00a0a\u00a0team-player\nA\u00a0proactive\u00a0attitude\u00a0in\u00a0coming\u00a0up\u00a0with\u00a0solutions\u00a0rather\u00a0than\u00a0simply\u00a0presenting\u00a0problems\nHas\u00a0a\u00a0great\u00a0attention\u00a0to\u00a0detail\nAble\u00a0to\u00a0meet\u00a0deadlines\u00a0in\u00a0a\u00a0fast-paced\u00a0dynamic\u00a0industry\nHas\u00a0a\u00a0positive\u00a0attitude,\u00a0is\u00a0self-confident,\u00a0and\u00a0welcomes\u00a0new\u00a0challenges\nFluent\u00a0in\u00a0English\u00a0and\u00a0a\u00a0second\u00a0European\u00a0language\u00a0(Dutch,\u00a0German,\u00a0French,\u00a0Italian,\u00a0Spanish\u00a0or\u00a0Russian)\u00a0is\u00a0highly\u00a0desirable\nHas\u00a0a\u00a0valid\u00a0permit\u00a0to\u00a0live\u00a0and\u00a0work\u00a0in\u00a0the\u00a0UK\nDesirable\u00a0but\u00a0not\u00a0mandatory;\nExperience\u00a0with\u00a0third\u00a0party\u00a0tracking\u00a0tools\nFamiliarity\u00a0with\u00a0Facebook\u00a0Power\u00a0Editor\u00a0and\u00a0Facebook\u00a0Marketing\u00a0Partners\u00a0tools\nExperience\u00a0with\u00a0Google\u00a0Analytics\u00a0and\u00a0the\u00a0basics\u00a0of\u00a0the\u00a0tracking\u00a0and\u00a0GTM\nWhy work for us!\nPension\u00a0matching\u00a0up\u00a0to\u00a06%\nPrivate\u00a0Medical\u00a0Insurance\u00a0and\u00a0Private\u00a0Dental\u00a0Insurance\nIncome\u00a0Protection\nLife\u00a0Assurance\nGym\u00a0Membership\nCycle\u00a0to\u00a0Work\u00a0Scheme\nTeam\u00a0socials\u00a0throughout\u00a0the\u00a0year\nCharity\u00a0volunteer\u00a0days\u00a0\u2013\u00a04\u00a0days\u00a0a\u00a0year\u00a0to\u00a0work\u00a0for\u00a0a\u00a0charity\u00a0of\u00a0your\u00a0choice\nWorkplace\u00a0Nursery\u00a0Scheme\u00a0\u2013\u00a0to\u00a0help\u00a0cover\u00a0childcare\u00a0costs\u00a0through\u00a0salary\u00a0sacrifice\nExtra\u00a0office\u00a0perks\nEnhanced Maternity & Paternity leave\nBack\nApply\nShare this job:\nFacebook\nLinkedIn\nEmail",
        "application_url": "https://careers.jakala.com/en_US/careers/ApplicationMethods?jobId=1708",
        "": {},
        "metadata": {
            "Office": "London",
            "Country": "United Kingdom",
            "Date Published": "16-Jan-2025",
            "Ref #": "1679",
            "Area": "Marketing",
            "Type of Presence": "Hybrid"
        },
        "link": "https://careers.jakala.com/en_US/careers/JobDetail/Senior-Programmatic-Account-Executive/1708"
    },
    {
        "title": "Senior Frontend Developer (all genders) - React",
        "description_html": null,
        "description_text": "General information\nOffice\nBerlin, Hamburg, Vienna\nCountry\nGermany\nDate Published\n20-Dec-2024\nRef #\n1510\nArea\nIT and Information Systems\nType of Presence\nRemote\nDescription & Requirements\nDu bist erfahrener Frontend Developer (all genders) mit einer Leidenschaft f\u00fcr innovative L\u00f6sungen? Du bringst tiefgehende Erfahrung in der Entwicklung von Webanwendungen mit und liebst es, im Team anspruchsvolle Projekte mit React im Frontend zu realisieren? Dann suchen wir genau dich.\nZum n\u00e4chstm\u00f6glichen Zeitpunkt suchen wir einen motivierten und engagierten Senior Frontend Developer (all genders) in Hamburg, Berlin, Wien, hybrid oder remote.\nResponsibilities\nDu entwickelst die Plattform eines unserer Kunden innovativ und nach neuesten Standards weiter\nDu arbeitest eng mit UX/UI-Design und Backend-Entwicklung zusammen um zur herausragende Benutzererlebnissen innerhalb der Produktteams zu schaffen\nDu bindest die AWS Cloud Services an das Frontend an\nDu integrierst Inhalte aus dem Headless CMS\nDu entwickelst die Personalisierung und Messbarkeit der Nutzererfahrung weiter\nDu gew\u00e4hrleistest hohe Code-Qualit\u00e4t und setzt Clean Code-Prinzipien konsequent um, um wartbare und erweiterbare Anwendungen zu schaffen\nOverview\nJAKALA ist ein weltweit t\u00e4tiges IT- und Consulting-Unternehmen im Bereich Martech, mit einem starken Fokus auf Daten und KI. Von den weltweit rund 3.200 Mitarbeitenden sind knapp 240 in Hamburg und Berlin t\u00e4tig. Bei JAKALA Germany liegt der Schwerpunkt auf der Entwicklung von individuellen Software-L\u00f6sungen, haupts\u00e4chlich von sogenannten Digital Experience Platforms (DXP). An der Schnittstelle von Strategie, Design und Technologie entwickeln wir digitale Plattformen, Apps und andere Services, welche die digitalen Erlebnisse gro\u00dfer Marken ma\u00dfgeblich pr\u00e4gen. Zu den Kunden in Deutschland z\u00e4hlen beispielsweise TUI Cruises, Leica, die Hamburger Hochbahn oder das ZDF.\nQualifications\nDu besitzt tiefe Kenntnisse in Javascript/Typescript, React und Next.js und hast mit diesen Technologien bereits erfolgreich in Projekten gearbeitet\nDu hast einen technologischen Weitblick und breite Erfahrungswerte \u00fcber das Kernarbeitsgebiet hinaus (Personalisierung, Daten, SEO, Analytics, Contentful CMS, AWS, Designsystem)\nDu bist vertraut mit agilen Entwicklungsmethoden und f\u00fchlst dich in integrierten Teams wohl\nDu verf\u00fcgst \u00fcber eine schnelle Auffassungsgabe\nDu hast ein wirtschaftliches Bewusstsein f\u00fcr ein angemessenes Ma\u00df zwischen Effizienz und h\u00f6chster Qualit\u00e4t\nDu bist ein:e starke:r Kommunikator:in, der oder die sich sowohl in der Zusammenarbeit mit interdisziplin\u00e4ren Teams als auch im Austausch mit Kunden souver\u00e4n bewegt, mindestens auf deutsch und besser noch zus\u00e4tzlich auf englisch\nOffer\nDas bieten wir dir:\nJob in Vollzeit oder Teilzeit - du entscheidest\nHybrides Arbeitsmodell (Remote und B\u00fcro) mit flexiblen Arbeitszeiten\nOffene und teamorientierte Unternehmenskultur\nWertsch\u00e4tzung deiner Ideen\nZuschuss f\u00fcr \u00d6PNV, Mobilit\u00e4tsbudget, Bikeleasing-Option\nUrban Sports Club Membership\nW\u00f6chentliches gemeinsames Fr\u00fchst\u00fcck oder Mittagessen\nWenn du willst: Einstieg in unsere Hamburger Band (S\u00e4nger:in gesucht)\nWhat else?\nWir wollen einen positiven Impact auf unsere Erde haben. Deshalb streben wir danach, auf nachhaltige Weise Wert f\u00fcr alle Interessengruppen zu schaffen und ber\u00fccksichtigen dabei Klima, Ethik und Qualit\u00e4t. 2021 haben wir uns entschieden, eine Benefit Corporation zu werden, um unser langfristiges Engagement f\u00fcr den Schutz der Prinzipien und Werte, die unser Handeln leiten, zu unterstreichen.\nBewirb dich noch heute. Wir freuen uns darauf, dich kennenzulernen.\nBack\nApply\nShare this job:\nFacebook\nLinkedIn\nEmail",
        "application_url": "https://careers.jakala.com/en_US/careers/ApplicationMethods?jobId=1539",
        "": {},
        "metadata": {
            "Office": "Berlin, Hamburg, Vienna",
            "Country": "Germany",
            "Date Published": "20-Dec-2024",
            "Ref #": "1510",
            "Area": "IT and Information Systems",
            "Type of Presence": "Remote"
        },
        "link": "https://careers.jakala.com/en_US/careers/JobDetail/Senior-Frontend-Developer-all-genders-React/1539"
    },
    {
        "title": "DevOps Engineer (all genders)",
        "description_html": null,
        "description_text": "General information\nOffice\nFull Remote, Berlin, Hamburg, Vienna\nCountry\nGermany\nDate Published\n20-Dec-2024\nRef #\n1514\nArea\nIT and Information Systems\nType of Presence\nHybrid\nDescription & Requirements\nDu\u00a0bist\u00a0(Senior)\u00a0DevOps\u00a0Engineer\u00a0(all\u00a0genders)\u00a0mit\u00a0einer\u00a0Leidenschaft\u00a0f\u00fcr\u00a0effiziente\u00a0Entwicklungsprozesse\u00a0und\u00a0stabile\u00a0Infrastrukturen?\u00a0Du\u00a0hast\u00a0Lust,\u00a0CI/CD-Pipelines\u00a0zu\u00a0optimieren\u00a0und\u00a0tr\u00e4gst\u00a0gerne\u00a0dazu\u00a0bei,\u00a0Entwicklung\u00a0und\u00a0Betrieb\u00a0nahtlos\u00a0zu\u00a0integrieren?\u00a0Dann\u00a0bist\u00a0du\u00a0bei\u00a0uns\u00a0genau\u00a0richtig.\nZum n\u00e4chstm\u00f6glichen Zeitpunkt suchen wir einen motivierten und engagierten (Senior) DevOps Engineer (all genders) in Hamburg, Berlin, Wien, hybrid oder remote.\nResponsibilities\nDu\u00a0setzt\u00a0h\u00f6chste\u00a0Standards\u00a0bei\u00a0Frontends,\u00a0Systemarchitektur,\u00a0Codequalit\u00e4t\u00a0und\u00a0Testabdeckung\u00a0und\u00a0realisierst\u00a0unsere\u00a0Backends\u00a0testgetrieben\u00a0mit\u00a0einem\u00a0Fokus\u00a0auf\u00a0hoch\u00a0skalierbare\u00a0Architekturen\u00a0und\u00a0RESTful\u00a0Microservices\nDu\u00a0baust\u00a0cloudnative\u00a0Architekturen\u00a0auf,\u00a0um\u00a0Microservices-Stacks\u00a0effizient\u00a0auf\u00a0Basis\u00a0von\u00a0Kubernetes\u00a0in\u00a0Cloud-Umgebungen\u00a0zu\u00a0betreiben\nDu\u00a0bist\u00a0verantwortlich\u00a0f\u00fcr\u00a0das\u00a0Design,\u00a0den\u00a0Aufbau\u00a0und\u00a0den\u00a0Betrieb\u00a0verteilter,\u00a0hochverf\u00fcgbarer\u00a0cloudnativer\u00a0Anwendungsstacks\u00a0und\u00a0der\u00a0dahinter\u00a0liegenden\u00a0Infrastrukturen\nDu\u00a0gestaltest\u00a0CI/CD-Strategien\u00a0entsprechend\u00a0den\u00a0spezifischen\u00a0Anforderungen\u00a0und\u00a0implementierst\u00a0zugeh\u00f6rige\u00a0Pipelines,\u00a0die\u00a0auf\u00a0Gitlab\u00a0CI\u00a0und\u00a0Argo\u00a0CD\u00a0basieren\nDu\u00a0arbeitest\u00a0in\u00a0agilen\u00a0Teams\u00a0und\u00a0Prozessen,\u00a0wobei\u00a0du\u00a0Continuous\u00a0Integration\u00a0und\u00a0Continuous\u00a0Delivery\u00a0praktizierst,\u00a0um\u00a0eine\u00a0effiziente\u00a0und\u00a0effektive\u00a0Entwicklungsumgebung\u00a0zu\u00a0gew\u00e4hrleisten\nOverview\nJAKALA ist ein weltweit t\u00e4tiges IT- und Consulting-Unternehmen im Bereich Martech, mit einem starken Fokus auf Daten und KI. Von den weltweit rund 3.200 Mitarbeitenden sind knapp 240 in Hamburg und Berlin t\u00e4tig. Bei JAKALA Germany liegt der Schwerpunkt auf der Entwicklung von individuellen Software-L\u00f6sungen, haupts\u00e4chlich von sogenannten Digital Experience Platforms (DXP). An der Schnittstelle von Strategie, Design und Technologie entwickeln wir digitale Plattformen, Apps und andere Services, welche die digitalen Erlebnisse gro\u00dfer Marken ma\u00dfgeblich pr\u00e4gen. Zu den Kunden in Deutschland z\u00e4hlen beispielsweise TUI Cruises, Leica, die Hamburger Hochbahn oder das ZDF.\nQualifications\nDu\u00a0hast\u00a0fundierte\u00a0Kenntnisse\u00a0und\u00a0praktische\u00a0Erfahrung\u00a0im\u00a0Design\u00a0und\u00a0Aufbau\u00a0von\u00a0cloudnativen\u00a0Stacks,\u00a0insbesondere\u00a0mit\u00a0Kubernetes\nTiefgehendes\u00a0Infrastrukturwissen\u00a0in\u00a0mindestens\u00a0einem\u00a0Hyper\u00a0Scaler\u00a0(GCP\u00a0und/oder\u00a0AWS)\u00a0zeichnet\u00a0dich\u00a0aus\nDu\u00a0verf\u00fcgst\u00a0\u00fcber\u00a0Erfahrung\u00a0in\u00a0der\u00a0Definition\u00a0und\u00a0Implementierung\u00a0von\u00a0Monitoring\u00a0und\u00a0Alerting\u00a0f\u00fcr\u00a0komplexe\u00a0IT-L\u00f6sungen,\u00a0unter\u00a0anderem\u00a0mit\u00a0Tools\u00a0wie\u00a0Prometheus,\u00a0Grafana\u00a0und\u00a0Alertmanager\nKenntnisse\u00a0in\u00a0der\u00a0Definition\u00a0von\u00a0Infrastruktur\u00a0als\u00a0Code,\u00a0vor\u00a0allem\u00a0mit\u00a0Terraform\u00a0und\u00a0Terragrunt,\u00a0bringst\u00a0du\u00a0mit\nErfahrung\u00a0im\u00a0Umgang\u00a0mit\u00a0Tools\u00a0und\u00a0L\u00f6sungen\u00a0aus\u00a0dem\u00a0CNCF-\u00d6kosystem,\u00a0wie\u00a0ArgoCD,\u00a0Istio\u00a0und\u00a0Helm,\u00a0ist\u00a0f\u00fcr\u00a0dich\u00a0selbstverst\u00e4ndlich\nDeine\u00a0Begeisterung\u00a0f\u00fcr\u00a0Technologie\u00a0treibt\u00a0dich\u00a0an,\u00a0dich\u00a0in\u00a0diesem\u00a0Bereich\u00a0kontinuierlich\u00a0weiterzubilden\nDu\u00a0kannst\u00a0dich\u00a0sowohl\u00a0auf\u00a0Deutsch\u00a0als\u00a0auch\u00a0auf\u00a0Englisch\u00a0gut\u00a0verst\u00e4ndigen\nOffer\nDas\u00a0bieten\u00a0wir\u00a0dir:\nJob\u00a0in\u00a0Vollzeit\u00a0oder\u00a0Teilzeit\u00a0-\u00a0du\u00a0entscheidest\nHybrides\u00a0Arbeitsmodell\u00a0(Remote\u00a0und/oder\u00a0B\u00fcro)\u00a0mit\u00a0flexiblen\u00a0Arbeitszeiten\nOffene\u00a0und\u00a0teamorientierte\u00a0Unternehmenskultur\nWertsch\u00e4tzung\u00a0deiner\u00a0Ideen\nZuschuss\u00a0f\u00fcr\u00a0\u00d6PNV,\u00a0Mobilit\u00e4tsbudget,\u00a0Bikeleasing-Option\nUrban\u00a0Sports\u00a0Club\u00a0Membership\nW\u00f6chentliches\u00a0gemeinsames\u00a0Fr\u00fchst\u00fcck\u00a0oder\u00a0Mittagessen\nWenn\u00a0du\u00a0willst:\u00a0Einstieg\u00a0in\u00a0unsere\u00a0Hamburger\u00a0Band\u00a0(S\u00e4nger:in\u00a0gesucht)\nWhat\u00a0else?\nWir\u00a0wollen\u00a0einen\u00a0positiven\u00a0Impact\u00a0auf\u00a0unsere\u00a0Erde\u00a0haben.\u00a0Deshalb\u00a0streben\u00a0wir\u00a0danach,\u00a0auf\u00a0nachhaltige\u00a0Weise\u00a0Wert\u00a0f\u00fcr\u00a0alle\u00a0Interessengruppen\u00a0zu\u00a0schaffen\u00a0und\u00a0ber\u00fccksichtigen\u00a0dabei\u00a0Klima,\u00a0Ethik\u00a0und\u00a0Qualit\u00e4t.\u00a02021\u00a0haben\u00a0wir\u00a0uns\u00a0entschieden,\u00a0eine\u00a0Benefit\u00a0Corporation\u00a0zu\u00a0werden,\u00a0um\u00a0unser\u00a0langfristiges\u00a0Engagement\u00a0f\u00fcr\u00a0den\u00a0Schutz\u00a0der\u00a0Prinzipien\u00a0und\u00a0Werte,\u00a0die\u00a0unser\u00a0Handeln\u00a0leiten,\u00a0zu\u00a0unterstreichen.\nBewirb dich noch heute. Wir freuen uns darauf, dich kennenzulernen\nBack\nApply\nShare this job:\nFacebook\nLinkedIn\nEmail",
        "application_url": "https://careers.jakala.com/en_US/careers/ApplicationMethods?jobId=1543",
        "": {},
        "metadata": {
            "Office": "Full Remote, Berlin, Hamburg, Vienna",
            "Country": "Germany",
            "Date Published": "20-Dec-2024",
            "Ref #": "1514",
            "Area": "IT and Information Systems",
            "Type of Presence": "Hybrid"
        },
        "link": "https://careers.jakala.com/en_US/careers/JobDetail/DevOps-Engineer-all-genders/1543"
    },
    {
        "title": "Senior Android Developer (all genders)",
        "description_html": null,
        "description_text": "General information\nOffice\nFull Remote, Berlin, Hamburg, Vienna\nCountry\nGermany\nDate Published\n19-Dec-2024\nRef #\n1503\nArea\nIT and Information Systems\nType of Presence\nRemote\nDescription & Requirements\nDu bist Senior Android Developer und bringst eine Leidenschaft f\u00fcr herausragende Apps und User Experiences mit? Du hast Freude daran, gemeinsam im Team individuelle Software-L\u00f6sungen f\u00fcr unsere Kunden zu realisieren? Dann sollten wir uns kennenlernen.\nZum n\u00e4chstm\u00f6glichen Zeitpunkt suchen wir einen motivierten und engagierten Senior Android Developer (all genders) in Hamburg, Berlin, Wien, hybrid oder remote.\nResponsibilities\nDu arbeitest in cross-funktionalen und agilen Entwicklungsteams mit, um gemeinsam innovative L\u00f6sungen zu schaffen\nDu konzipierst und realisierst anspruchsvolle mobile L\u00f6sungen unter Verwendung relevanter Technologien wie Jetpack Compose, Coroutines, Dagger Hilt und KMP\nDu setzt Produktanforderungen und Designs entsprechend der Zielplattform mit hochwertigem Code um\nDu passt dich verschiedenen Technologien und Plattformen flexibel an und setzt deinen Projekte erfolgreich um\nGemeinsam mit unseren interdisziplin\u00e4ren Teams arbeitest du daran, neue Funktionen zu definieren, zu gestalten und zu entwickeln\nOverview\nJAKALA ist ein weltweit t\u00e4tiges IT- und Consulting-Unternehmen im Bereich Martech, mit einem starken Fokus auf Daten und KI. Von den weltweit rund 3.200 Mitarbeitenden sind knapp 240 in Hamburg und Berlin t\u00e4tig. Bei JAKALA Germany liegt der Schwerpunkt auf der Entwicklung von individuellen Software-L\u00f6sungen, haupts\u00e4chlich von sogenannten Digital Experience Platforms (DXP). An der Schnittstelle von Strategie, Design und Technologie entwickeln wir digitale Plattformen, Apps und andere Services, welche die digitalen Erlebnisse gro\u00dfer Marken ma\u00dfgeblich pr\u00e4gen. Zu den Kunden in Deutschland z\u00e4hlen beispielsweise TUI Cruises, Leica, die Hamburger Hochbahn oder das ZDF.\nQualifications\nDu verf\u00fcgst \u00fcber umfangreiche und langj\u00e4hrige Expertise in der Entwicklung nativer Android-Apps\nDein Entwicklungs-Stack umfasst Kotlin und du bist sicher in der Verwendung g\u00e4ngiger Tools und Frameworks\nDu hast ein Gesp\u00fcr f\u00fcr eine gelungene User Experience und interessierst dich f\u00fcr neue Technologien wie Jetpack Compose und KMP\nDu sprichst flie\u00dfend Deutsch und kommunizierst auch auf Englisch sicher\nOffer\nDas bieten wir dir:\nJob in Vollzeit oder Teilzeit - du entscheidest\nHybrides Arbeitsmodell (Remote und B\u00fcro) mit flexiblen Arbeitszeiten\nOffene und teamorientierte Unternehmenskultur\nWertsch\u00e4tzung deiner Ideen\nZuschuss f\u00fcr \u00d6PNV und Bikeleasing-Option\nUrban Sports Club Membership\nW\u00f6chentliches gemeinsames Fr\u00fchst\u00fcck / Lunch\nWenn du willst: Einstieg in unsere Hamburger Band (Schlagzeuger:in gesucht)\nWhat else?\nWir wollen einen positiven Impact auf unsere Erde haben. Deshalb streben wir danach, auf nachhaltige Weise Wert f\u00fcr alle Interessengruppen zu schaffen und ber\u00fccksichtigen dabei Klima, Ethik und Qualit\u00e4t. 2021 haben wir uns entschieden, eine Benefit Corporation zu werden, um unser langfristiges Engagement f\u00fcr den Schutz der Prinzipien und Werte, die unser Handeln leiten, zu unterstreichen.\nBewirb dich noch heute. Wir freuen uns darauf, dich kennenzulernen.\nBack\nApply\nShare this job:\nFacebook\nLinkedIn\nEmail",
        "application_url": "https://careers.jakala.com/en_US/careers/ApplicationMethods?jobId=1532",
        "": {},
        "metadata": {
            "Office": "Full Remote, Berlin, Hamburg, Vienna",
            "Country": "Germany",
            "Date Published": "19-Dec-2024",
            "Ref #": "1503",
            "Area": "IT and Information Systems",
            "Type of Presence": "Remote"
        },
        "link": "https://careers.jakala.com/en_US/careers/JobDetail/Senior-Android-Developer-all-genders/1532"
    },
    {
        "title": "Experienced Professional | Data Analyst (Data Lab)",
        "description_html": null,
        "description_text": "General information\nOffice\nMilano\nCountry\nItaly\nDate Published\n03-Dec-2024\nRef #\n1458\nArea\nManagement Consulting\nType of Presence\nHybrid\nDescription & Requirements\n\ud83d\udccd\nSede\n: Milano\n\ud83d\udc40\nRank: Consultant\nChi siamo\nJAKALA \u00e8 un'azienda che lavora su dati, intelligenza artificiale e sviluppo di esperienze per generare un impatto significativo e duraturo a livello globale.\nPresenti in oltre 30 citt\u00e0 in 21 paesi, i nostri team uniscono competenze su strategia, tecnologia, creativit\u00e0 e operations per offrire esperienze personalizzate e soluzioni trasformative ai nostri clienti, grazie al supporto di dati e intelligenza artificiale. I Jakalers sono un gruppo eterogeneo di oltre 3.000 persone, animate da passione, ambizione e idee brillanti. Proprio questa combinazione unica di talenti \u00e8 il fattore distintivo che ha ispirato il nostro purpose: Together to get there.\nCreare un mondo migliore \u00e8 il nostro obiettivo ultimo: la nostra ambizione \u00e8 generare valore per tutti i nostri stakeholder in modo sostenibile, con particolare attenzione a etica, clima e qualit\u00e0. Nel 2021, abbiamo scelto di diventare una Societ\u00e0 Benefit, dimostrando il nostro impegno di lungo periodo e la volont\u00e0 di proteggere i principi e i valori che ogni giorno guidano le nostre azioni.\nCrediamo che la diversit\u00e0 sia la chiave del nostro successo e, per questo, siamo impegnati a creare un ambiente di lavoro inclusivo, dove ciascuno possa sentirsi valorizzato per la propria unicit\u00e0. Tutte le nostre opportunit\u00e0 di lavoro sono aperte ai candidati appartenenti alle categorie protette L.68/99.\nScopri il team J-Science\nTi appassionano i dati, l\u2019intelligenza artificiale e il linguaggio naturale? Nel team J-Science di JAKALA lavoriamo ogni giorno per trasformare queste tecnologie in soluzioni concrete e ad alto impatto per le aziende.\nSiamo un centro di eccellenza con sedi a Milano, Torino, Rende e Roma, e ci occupiamo di Data Science, Location Intelligence, Large Natural Language Models e sviluppo di piattaforme, progettando software avanzati con tecnologia all'avanguardia.\nDall\u2019AI applicata a testo e voce alla semantic search, passando per speech technology e predictive analytics: innoviamo per creare valore reale e accessibile, in contesti complessi e sfidanti.\nPer il potenziamento dell\u2019area Data Lab stiamo cercando Data Analyst che vogliano entrare a far parte di un team di specialisti dedicato allo sviluppo di prodotti e soluzioni innovative basate su banche dati microterritoriali proprietarie uniche in Italia, che permettono alle aziende di incrementare le vendite e ridurre il Cost to Serve grazie a una migliore conoscenza di Territorio, Reti di vendita, Clienti e Prospect.\n\ud83c\udfaf\nLe tue responsabilit\u00e0:\nLe risorse saranno inserite in un contesto fortemente dinamico e \u201cdata-intensive\u201d dove potranno mettere a frutto, con un elevato grado di autonomia, le proprie conoscenze di analisi statistiche e/o geografiche contribuendo allo sviluppo dell\u2019offerta dati aziendale e supportando l\u2019attivit\u00e0 delle aree di Business Client Strategy, Location Intelligence e Data & AI\nSviluppo e realizzazione di soluzioni enterprise in ambito Advanced Analytics e Geo-Intelligence con particolare riferimento alla integrazione di componenti e\\o servizi di intelligenza artificiale\nPartecipazione a team di progetti composti da un mix di talenti con esperienza in data science, machine learning e AI.\n\ud83d\ude4c\nSe ti riconosci in queste caratteristiche, potremmo essere il perfetto match:\nLaurea preferibilmente in materie scientifiche (Data Science, Ingegneria, Statistica, Big\nData Analytics, Matematica o affini)\nForte attitudine quantitativa e passione per il mondo dei\u00a0dati\nPrecisione e cura del dettaglio\nCapacit\u00e0 di relazionarsi con altre funzioni aziendali per comprendere il problema di business da analizzare e trasformare le analisi in insight azionabili\nLaurea\u00a0in\u00a0Scienze Statistiche\u00a0o titoli di studio affini\u00a0con eccellenti risultati accademici\nSolide basi statistiche e conoscenza di principali metodi di estrazione (es. SQL) e\u00a0pre-processing /\u00a0cleansing\u00a0dei dati\nConoscenza di linguaggi o tool di Data Science (es. SAS, Python,\u00a0R, ecc.)\nOttima capacit\u00e0 di\u00a0problem\u00a0setting e\u00a0problem\u00a0solving\nFamiliarit\u00e0 con i principali tool di BI (PowerBI, Tableau,\u00a0QlikView)\nFamiliarit\u00e0 con tematiche di Business Intelligence, DWH, ecc.\nConoscenza di Data Platform quali GCP, AWS e Azure\nInteresse\u00a0nei\u00a0confronti\u00a0delle\u00a0principali\u00a0tematiche\u00a0in area Business analysis, Performance optimization, Customer Experience management, CRM, Network development, Loyalty & Engagement design\nOttima capacit\u00e0 di sintetizzare e rappresentare un problema, oltre che di svilupparne la risoluzione attraverso slide e metodi di \u201cData Storytelling\u201d\n\ud83d\udc9c\nScopri\u00a0nel\u00a0video le ragioni per cui scegliere JAKALA come prossimo step di carriera\nIn JAKALA crediamo che il tempo e il benessere delle persone vadano rispettati, sempre: incoraggiamo una presenza in ufficio di\n10\ngiorni al mese.\nIl nostro sistema di Total\nReward\ninclude convenzioni esclusive per viaggi, ristoranti, shopping, palestra e tempo libero, oltre a servizi gratuiti di telemedicina e supporto psicologico, pensati per te e per chi ami.\nInvestire nel nostro processo di selezione significa ricevere supporto autentico: un Recruiter dedicato ti accompagner\u00e0 con feedback personalizzati, consigli di carriera e insight sul tuo CV, a prescindere dall\u2019esito della candidatura. Niente AI, solo persone. E, grazie all\u2019iniziativa Your Time Back, ti restituiamo il tempo investito nei colloqui con un percorso di empowerment firmato\nUnobravo\n.\n\ud83c\udf31 Ready to start?\nNon \u00e8 solo una candidatura. \u00c8 un percorso che comincia ora. Inviaci il tuo CV: non vediamo l\u2019ora di conoscerti!\nBack\nApply\nShare this job:\nFacebook\nLinkedIn\nEmail",
        "application_url": "https://careers.jakala.com/en_US/careers/ApplicationMethods?jobId=1487",
        "": {},
        "metadata": {
            "Office": "Milano",
            "Country": "Italy",
            "Date Published": "03-Dec-2024",
            "Ref #": "1458",
            "Area": "Management Consulting",
            "Type of Presence": "Hybrid"
        },
        "link": "https://careers.jakala.com/en_US/careers/JobDetail/Experienced-Professional-Data-Analyst-Data-Lab/1487"
    },
    {
        "title": "Experienced Professional | Data Analyst (Advanced Analytics)",
        "description_html": null,
        "description_text": "General information\nOffice\nRoma\nCountry\nItaly\nDate Published\n03-Dec-2024\nRef #\n2136\nArea\nManagement Consulting\nType of Presence\nHybrid\nDescription & Requirements\n\ud83d\udccd\nSede\n: Roma\n\ud83d\udc40\nRank: Consultant\nChi siamo\nJAKALA \u00e8 un'azienda che lavora su dati, intelligenza artificiale e sviluppo di esperienze per generare un impatto significativo e duraturo a livello globale.\nPresenti in oltre 30 citt\u00e0 in 21 paesi, i nostri team uniscono competenze su strategia, tecnologia, creativit\u00e0 e operations per offrire esperienze personalizzate e soluzioni trasformative ai nostri clienti, grazie al supporto di dati e intelligenza artificiale. I Jakalers sono un gruppo eterogeneo di oltre 3.000 persone, animate da passione, ambizione e idee brillanti. Proprio questa combinazione unica di talenti \u00e8 il fattore distintivo che ha ispirato il nostro purpose: Together to get there.\nCreare un mondo migliore \u00e8 il nostro obiettivo ultimo: la nostra ambizione \u00e8 generare valore per tutti i nostri stakeholder in modo sostenibile, con particolare attenzione a etica, clima e qualit\u00e0. Nel 2021, abbiamo scelto di diventare una Societ\u00e0 Benefit, dimostrando il nostro impegno di lungo periodo e la volont\u00e0 di proteggere i principi e i valori che ogni giorno guidano le nostre azioni.\nCrediamo che la diversit\u00e0 sia la chiave del nostro successo e, per questo, siamo impegnati a creare un ambiente di lavoro inclusivo, dove ciascuno possa sentirsi valorizzato per la propria unicit\u00e0. Tutte le nostre opportunit\u00e0 di lavoro sono aperte ai candidati appartenenti alle categorie protette L.68/99.\nScopri il team J-Science\nTi appassionano i dati, l\u2019intelligenza artificiale e il linguaggio naturale? Nel team J-Science di JAKALA lavoriamo ogni giorno per trasformare queste tecnologie in soluzioni concrete e ad alto impatto per le aziende.\nSiamo un centro di eccellenza con sedi a Milano, Torino, Rende e Roma, e ci occupiamo di Data Science, Location Intelligence, Large Natural Language Models e sviluppo di piattaforme, progettando software avanzati con tecnologia all'avanguardia.\nDall\u2019AI applicata a testo e voce alla semantic search, passando per speech technology e predictive analytics: innoviamo per creare valore reale e accessibile, in contesti complessi e sfidanti.\nPer il potenziamento dell\u2019area Data Lab stiamo cercando Data Scientist che vogliano entrare a far parte di un team di specialisti dedicato allo sviluppo di prodotti e soluzioni innovative basate su banche dati microterritoriali proprietarie uniche in Italia, che permettono alle aziende di incrementare le vendite e ridurre il Cost to Serve grazie a una migliore conoscenza di Territorio, Reti di vendita, Clienti e Prospect.\n\ud83c\udfaf\nLe tue responsabilit\u00e0:\nLe risorse saranno inserite in un contesto fortemente dinamico e \u201cdata-intensive\u201d dove potranno mettere a frutto, con un elevato grado di autonomia, le proprie conoscenze di analisi statistiche e/o geografiche contribuendo allo sviluppo dell\u2019offerta dati aziendale e supportando l\u2019attivit\u00e0 delle aree di Business Client Strategy, Location Intelligence e Data & AI\nSviluppo e realizzazione di soluzioni enterprise in ambito Advanced Analytics e Geo-Intelligence con particolare riferimento alla integrazione di componenti e\\o servizi di intelligenza artificiale\nPartecipazione a team di progetti composti da un mix di talenti con esperienza in data science, machine learning e AI.\n\ud83d\ude4c\nSe ti riconosci in queste caratteristiche, potremmo essere il perfetto match:\nLaurea preferibilmente in materie scientifiche (Data Science, Ingegneria, Statistica, Big\nData Analytics, Matematica o affini)\nForte attitudine quantitativa e passione per il mondo dei\u00a0dati\nPrecisione e cura del dettaglio\nCapacit\u00e0 di relazionarsi con altre funzioni aziendali per comprendere il problema di business da analizzare e trasformare le analisi in insight azionabili\nLaurea\u00a0in\u00a0Scienze Statistiche\u00a0o titoli di studio affini\u00a0con eccellenti risultati accademici\nSolide basi statistiche e conoscenza di principali metodi di estrazione (es. SQL) e\u00a0pre-processing /\u00a0cleansing\u00a0dei dati\nConoscenza di linguaggi o tool di Data Science (es. SAS, Python,\u00a0R, ecc.)\nOttima capacit\u00e0 di\u00a0problem\u00a0setting e\u00a0problem\u00a0solving\nFamiliarit\u00e0 con i principali tool di BI (PowerBI, Tableau,\u00a0QlikView)\nFamiliarit\u00e0 con tematiche di Business Intelligence, DWH, ecc.\nConoscenza di Data Platform quali GCP, AWS e Azure\nInteresse\u00a0nei\u00a0confronti\u00a0delle\u00a0principali\u00a0tematiche\u00a0in area Business analysis, Performance optimization, Customer Experience management, CRM, Network development, Loyalty & Engagement design\nOttima capacit\u00e0 di sintetizzare e rappresentare un problema, oltre che di svilupparne la risoluzione attraverso slide e metodi di \u201cData Storytelling\"\n\ud83d\udc9c\nScopri\u00a0nel\u00a0video le ragioni per cui scegliere JAKALA come prossimo step di carriera\nIn JAKALA crediamo che il tempo e il benessere delle persone vadano rispettati, sempre: incoraggiamo una presenza in ufficio di\n10\ngiorni al mese.\nIl nostro sistema di Total\nReward\ninclude convenzioni esclusive per viaggi, ristoranti, shopping, palestra e tempo libero, oltre a servizi gratuiti di telemedicina e supporto psicologico, pensati per te e per chi ami.\nInvestire nel nostro processo di selezione significa ricevere supporto autentico: un Recruiter dedicato ti accompagner\u00e0 con feedback personalizzati, consigli di carriera e insight sul tuo CV, a prescindere dall\u2019esito della candidatura. Niente AI, solo persone. E, grazie all\u2019iniziativa Your Time Back, ti restituiamo il tempo investito nei colloqui con un percorso di empowerment firmato\nUnobravo\n.\n\ud83c\udf31 Ready to start?\nNon \u00e8 solo una candidatura. \u00c8 un percorso che comincia ora. Inviaci il tuo CV: non vediamo l\u2019ora di conoscerti!\nBack\nApply\nShare this job:\nFacebook\nLinkedIn\nEmail",
        "application_url": "https://careers.jakala.com/en_US/careers/ApplicationMethods?jobId=2168",
        "": {},
        "metadata": {
            "Office": "Roma",
            "Country": "Italy",
            "Date Published": "03-Dec-2024",
            "Ref #": "2136",
            "Area": "Management Consulting",
            "Type of Presence": "Hybrid"
        },
        "link": "https://careers.jakala.com/en_US/careers/JobDetail/Experienced-Professional-Data-Analyst-Advanced-Analytics/2168"
    },
    {
        "title": "Intern | Junior Procurement Specialist (Ufficio acquisti internazionali)",
        "description_html": null,
        "description_text": "General information\nOffice\nMilano\nCountry\nItaly\nDate Published\n08-Oct-2024\nRef #\n1908\nArea\nHuman Resources\nType of Presence\nHybrid\nDescription & Requirements\n\ud83d\udccd\nSede:\nMilano\nChi siamo\nJAKALA \u00e8 un'azienda che lavora su dati, intelligenza artificiale e sviluppo di esperienze per generare un impatto significativo e duraturo a livello globale.\nPresenti in oltre 30 citt\u00e0 in 21 paesi, i nostri team uniscono competenze su strategia, tecnologia, creativit\u00e0 e operations per offrire esperienze personalizzate e soluzioni trasformative ai nostri clienti, grazie al supporto di dati e intelligenza artificiale. I Jakalers sono un gruppo eterogeneo di oltre 3.000 persone, animate da passione, ambizione e idee brillanti. Proprio questa combinazione unica di talenti \u00e8 il fattore distintivo che ha ispirato il nostro purpose: Together to get there.\nCreare un mondo migliore \u00e8 il nostro obiettivo ultimo: la nostra ambizione \u00e8 generare valore per tutti i nostri stakeholder in modo sostenibile, con particolare attenzione a etica, clima e qualit\u00e0. Nel 2021, abbiamo scelto di diventare una Societ\u00e0 Benefit, dimostrando il nostro impegno di lungo periodo e la volont\u00e0 di proteggere i principi e i valori che ogni giorno guidano le nostre azioni.\nCrediamo che la diversit\u00e0 sia la chiave del nostro successo e, per questo, siamo impegnati a creare un ambiente di lavoro inclusivo, dove ciascuno possa sentirsi valorizzato per la propria unicit\u00e0. Tutte le nostre opportunit\u00e0 di lavoro sono aperte ai candidati appartenenti alle categorie protette L.68/99.\nScopri\nil team\nGlobal Service Procurement\nSei una persona organizzata, precisa e ti interessa il mondo degli acquisti? Vuoi imparare come funziona la gestione degli approvvigionamenti in una realt\u00e0 complessa e in continua evoluzione?\nNel team Global Service Procurement\ndi JAKALA gestiamo l\u2019intero ciclo di acquisto, dai fornitori alla rendicontazione, contribuendo all\u2019efficienza e all\u2019ottimizzazione dei processi interni.\nPer il\ndell\u2019area\nstiamo cercando una figura da inserire in un percorso di stage retribuito nella nostra sede di Milano,\nche supporter\u00e0\nil team\nnella gestione del ciclo di acquisto, dal rapporto con i fornitori al controllo delle fatture.\n\ud83c\udfaf Ogni giorno sar\u00e0 diverso, ma eccoti un assaggio di quello che ti aspetta:\nSupporto attivo\nal team Global Service Procurement\nnella gestione dell'intero ciclo di acquisto, dall'individuazione del fornitore alla rendicontazione finale.\nControllo e gestione delle fatture, garantendo la correttezza dei pagamenti e l'ottimizzazione dei costi.\nInterfaccia diretta con fornitori e stakeholder interni, assicurando un flusso di informazioni efficiente e trasparente.\nPartecipazione attiva ai progetti di innovazione e miglioramento dei processi di acquisto, con l'utilizzo di strumenti all'avanguardia come SAP.\n\ud83d\udca1 Queste caratteristiche sono un ottimo punto di partenza per crescere insieme:\nDiploma in ragioneria e simili o Laurea triennale o magistrale in discipline economiche o ingegneristiche.\nOttima conoscenza di Excel e forte propensione all'utilizzo di strumenti digitali.\nBuona conoscenza della lingua inglese.\nPrecisione, affidabilit\u00e0 e capacit\u00e0 di lavorare in\nteam\n.\nProattivit\u00e0 e voglia di imparare.\n\ud83d\udc9c\nScopri nel video le ragioni per cui scegliere JAKALA come prossimo step di carriera:\nIn JAKALA crediamo che il tempo e il benessere delle persone vadano rispettati, sempre: incoraggiamo una presenza in ufficio di 10 giorni al mese.\nIl nostro sistema di Total Reward include convenzioni esclusive per viaggi, ristoranti, shopping, palestra e tempo libero, oltre a servizi gratuiti di telemedicina e supporto psicologico, pensati per te e per chi ami.\nInvestire nel nostro processo di selezione significa ricevere supporto autentico: un Recruiter dedicato ti accompagner\u00e0 con feedback personalizzati, consigli di carriera e insight sul tuo CV, a prescindere dall\u2019esito della candidatura. Niente AI, solo persone. E, grazie all\u2019iniziativa Your Time Back, ti restituiamo il tempo investito nei colloqui con un percorso di empowerment firmato Unobravo.\n\ud83c\udf31\nReady to start?\nNon \u00e8 solo una candidatura. \u00c8 un percorso che comincia ora. Inviaci il tuo CV: non vediamo l\u2019ora di conoscerti!\nBack\nApply\nShare this job:\nFacebook\nLinkedIn\nEmail",
        "application_url": "https://careers.jakala.com/en_US/careers/ApplicationMethods?jobId=1938",
        "": {},
        "metadata": {
            "Office": "Milano",
            "Country": "Italy",
            "Date Published": "08-Oct-2024",
            "Ref #": "1908",
            "Area": "Human Resources",
            "Type of Presence": "Hybrid"
        },
        "link": "https://careers.jakala.com/en_US/careers/JobDetail/Intern-Junior-Procurement-Specialist-Ufficio-acquisti-internazionali/1938"
    },
    {
        "title": "Experienced Professional | Web Analytics",
        "description_html": null,
        "description_text": "General information\nOffice\nMilano\nCountry\nItaly\nDate Published\n05-Apr-2024\nRef #\n1161\nArea\nManagement Consulting\nType of Presence\nHybrid\nDescription & Requirements\n\ud83d\udccd\nSede\n: Roncade\n\ud83d\udc40\nRank: Senior Associate\nChi siamo\nJAKALA \u00e8 un'azienda che lavora su dati, intelligenza artificiale e sviluppo di esperienze per generare un impatto significativo e duraturo a livello globale.\nPresenti in oltre 30 citt\u00e0 in 21 paesi, i nostri team uniscono competenze su strategia, tecnologia, creativit\u00e0 e\noperations\nper offrire esperienze personalizzate e soluzioni trasformative ai nostri clienti, grazie al supporto di dati e intelligenza artificiale. I\nJakalers\nsono un gruppo eterogeneo di oltre 3.000 persone, animate da passione, ambizione e idee brillanti. Proprio questa combinazione unica di talenti \u00e8 il fattore distintivo che ha ispirato il nostro\npurpose\n:\nTogether\nto\nget\nthere\n.\nCreare un mondo migliore \u00e8 il nostro obiettivo ultimo: la nostra ambizione \u00e8 generare valore per tutti i nostri stakeholder in modo sostenibile, con particolare attenzione a etica, clima e qualit\u00e0. Nel 2021, abbiamo scelto di diventare una Societ\u00e0 Benefit, dimostrando il nostro impegno di lungo periodo e la volont\u00e0 di proteggere i principi e i valori che ogni giorno guidano le nostre azioni.\nCrediamo che la diversit\u00e0 sia la chiave del nostro successo e, per questo, siamo impegnati a creare un ambiente di lavoro inclusivo, dove ciascuno possa sentirsi valorizzato per la propria unicit\u00e0. Tutte le nostre opportunit\u00e0 di lavoro sono aperte ai candidati appartenenti alle categorie protette L.68/99.\nScopri il team\nAll\u2019interno della Service Line Web Analytics di JAKALA, lavoriamo ogni giorno per contribuire in maniera concreta allo sviluppo e alla realizzazione di progetti innovativi da portare sul mercato su grandi clienti, che vogliano crescere rapidamente ed essere pronti a raccogliere le sfide giornaliere in maniera flessibile e con un approccio \u201copen minded\u201d.\nI nostri nuovi colleghi verranno coinvolti nello sviluppo di progetti di implementazione su piattaforme di tag management e Web Analytics e tool di Dashboarding.\n\ud83c\udfaf Le tue responsabilit\u00e0:\nAttivit\u00e0 di audit di tracciamento e analitica, web e app\nRealizzazione documenti di tracking strategy\nImplementazione tracking, in particolare mediante Google Tag Manager e Adobe e relativi debug\nAnalisi del dato raccolto, mediante creazione di reportistica o dashboard ad hoc\n\ud83d\ude4c Se ti riconosci in queste caratteristiche, potremmo essere il perfetto match:\nLaurea specialistica in ambito tecnico informatico/statistico/marketing o affini\nConoscenza approfondita di tool di Web Analytics, Google e Adobe\nAlmeno tre anni di esperienza su web analytics e data analysis\nConoscenza di Javascript e Html per la gestione dei Tag\nDoti relazionali per instaurare proficui e duraturi rapporti con i team di Jakala e del cliente\nForte orientamento al risultato e passione per l\u2019analisi di dati e per le performance marketing data driven\nConoscenza aggiuntiva dello stack Adobe\nUtilizzo di SDK mobile, come Firebase o Adobe Mobile SDK\nCapacit\u00e0 organizzative e attenzione ai dettagli\nOttima conoscenza della lingua inglese\n\ud83d\udc9c\nScopri in questo video le ragioni per cui scegliere JAKALA come prossimo step di carriera\nIn JAKALA crediamo che il tempo e il benessere delle persone vadano rispettati, sempre: incoraggiamo una presenza in ufficio di 10 giorni al mese, lasciando piena libert\u00e0 di lavorare da dove preferisci, sia in Italia che all\u2019interno della Comunit\u00e0 Europea.\nIl nostro sistema di Total Reward include convenzioni esclusive per viaggi, ristoranti, shopping, palestra e tempo libero, oltre a servizi gratuiti di telemedicina e supporto psicologico, pensati per te e per chi ami.\nInvestire nel nostro processo di selezione significa ricevere supporto autentico: un Recruiter dedicato ti accompagner\u00e0 con feedback personalizzati, consigli di carriera e insight sul tuo CV, a prescindere dall\u2019esito della candidatura. Niente AI, solo persone. E, grazie all\u2019iniziativa Your Time Back, ti restituiamo il tempo investito nei colloqui con un percorso di empowerment firmato Unobravo.\n\ud83c\udf31 Ready to start?\nNon \u00e8 solo una candidatura. \u00c8 un percorso che comincia ora. Inviaci il tuo CV: non vediamo l\u2019ora di conoscerti!\nBack\nApply\nShare this job:\nFacebook\nLinkedIn\nEmail",
        "application_url": "https://careers.jakala.com/en_US/careers/ApplicationMethods?jobId=1189",
        "": {},
        "metadata": {
            "Office": "Milano",
            "Country": "Italy",
            "Date Published": "05-Apr-2024",
            "Ref #": "1161",
            "Area": "Management Consulting",
            "Type of Presence": "Hybrid"
        },
        "link": "https://careers.jakala.com/en_US/careers/JobDetail/Experienced-Professional-Web-Analytics/1189"
    },
    {
        "title": "Experienced Professional | Generative AI Developer (J-Science)",
        "description_html": null,
        "description_text": "General information\nOffice\nMilano, Roma, Torino\nCountry\nItaly\nDate Published\n08-Mar-2024\nRef #\n1109\nArea\nIT and Information Systems\nType of Presence\nHybrid\nDescription & Requirements\n\ud83d\udccd\nSede\n: Torino, Milano\n\ud83d\udc40\nRank: Consultant\nChi siamo\nJAKALA \u00e8 un'azienda che lavora su dati, intelligenza artificiale e sviluppo di esperienze per generare un impatto significativo e duraturo a livello globale.\nPresenti in oltre 30 citt\u00e0 in 21 paesi, i nostri team uniscono competenze su strategia, tecnologia, creativit\u00e0 e operations per offrire esperienze personalizzate e soluzioni trasformative ai nostri clienti, grazie al supporto di dati e intelligenza artificiale. I Jakalers sono un gruppo eterogeneo di oltre 3.000 persone, animate da passione, ambizione e idee brillanti. Proprio questa combinazione unica di talenti \u00e8 il fattore distintivo che ha ispirato il nostro purpose: Together to get there.\nCreare un mondo migliore \u00e8 il nostro obiettivo ultimo: la nostra ambizione \u00e8 generare valore per tutti i nostri stakeholder in modo sostenibile, con particolare attenzione a etica, clima e qualit\u00e0. Nel 2021, abbiamo scelto di diventare una Societ\u00e0 Benefit, dimostrando il nostro impegno di lungo periodo e la volont\u00e0 di proteggere i principi e i valori che ogni giorno guidano le nostre azioni.\nCrediamo che la diversit\u00e0 sia la chiave del nostro successo e, per questo, siamo impegnati a creare un ambiente di lavoro inclusivo, dove ciascuno possa sentirsi valorizzato per la propria unicit\u00e0. Tutte le nostre opportunit\u00e0 di lavoro sono aperte ai candidati appartenenti alle categorie protette L.68/99.\nScopri il team J-Science\nTi appassiona l\u2019intelligenza artificiale? Nel team J-Science di JAKALA lavoriamo ogni giorno per trasformare queste tecnologie in soluzioni concrete e ad alto impatto per le aziende. \u00a0Siamo un centro di eccellenza con sedi a Milano, Torino, Rende e Roma, e ci occupiamo di Data Science, Generative AI, Sviluppo di Piattaforme e Location Intelligence, progettando software avanzati con tecnologia allo stato dell\u2019arte.\nDai Large Language Models applicati a testo, immagini e voce, alla semantic search, passando per speech technology e predictive analytics: innoviamo per creare valore reale e accessibile, in contesti complessi e sfidanti.\nCerchiamo le migliori soluzioni a problemi reali dei nostri clienti, integrando la ricerca applicata in ambito AI ad una solida competenza architetturale. Utilizziamo i pi\u00f9 avanzati LLM sul mercato, sia SaaS, sia OnPremises, per sviluppare progetti e prodotti modulari ed innovativi, siano essi proof of concept o piattaforme core. Contribuirai allo sviluppo di prodotti che fanno uso di pipeline analitiche, modelli predittivi e soluzioni basate su dati strutturati (es:territoriali, transazionali...) e non strutturati (es: documenti, registrazioni audio\u2026) con team multidisciplinari in un contesto dinamico e tecnologicamente avanzato.\n\ud83c\udfaf\nLe tue responsabilit\u00e0:\nAnalisi dei requisiti dei clienti e identificazione delle opportunit\u00e0 di applicazione della Generative AI\nDisegno, progettazione e sviluppo di soluzioni basate su servizi di Generative AI, utilizzando modelli/librerie open source o proprietarie\nSelezione, utilizzo e fine-tuning di modelli di AI generativa\nRealizzazione di prototipi rapidi (fast prototyping) per la validazione delle soluzioni\nIntegrazione delle soluzioni AI sviluppate con i sistemi aziendali esistenti (es. siti web, CRM, knowledge base, ecc.)\nIngegnerizzazione delle soluzioni per renderle scalabili e pronte per il mercato\nCollaborazione con il team per garantire coerenza tecnica e visione strategica del prodotto\nContributo al miglioramento continuo delle pratiche di sviluppo e delle architetture Gen AI adottate\n\ud83d\ude4c\nSe ti riconosci in queste caratteristiche, potremmo essere il perfetto match:\nLaurea preferibilmente in materie scientifiche (Data Science, Ingegneria, Statistica, Big Data Analytics, Matematica o affini)\nPregressa esperienza di 1-2 anni nel ruolo\nConsolidata conoscenza di Python e/o Java\nEsperienza consolidata nell\u2019uso di LLM ed in particolare dei modelli transformers (es. Bert, Gpt\u2026)\nEsperienza nella sperimentazione di framework agentici (Langchain, Autogen\u2026)\nEsperienza nel fine tuning di modelli LLM e addestramento di sistemi transformer con approcci supervised\nBuona conoscenza del framework Spring o di framework Python equivalenti\nBuona conoscenza di tematiche di integrazione, in particolare REST API\nConoscenza architetture a microservizi\nConoscenza di Design Patterns e principi di testing e software design\nConoscenza dei linguaggi Bash scripting\nConoscenza di SQL\nConoscenza dei sistemi Kubernetes e Docker\nConoscenza dei motori di ricerca (Solr, Elastic Search, Lucene, etc.)\nMessage queueing system (es. Apache kafka, rabbit Mq)\n\ud83d\udc9c\nScopri in questo video le ragioni per cui scegliere JAKALA come prossimo step di carriera\nIn JAKALA crediamo che il tempo e il benessere delle persone vadano rispettati, sempre: incoraggiamo una presenza in ufficio di10giorni al mese, lasciando piena libert\u00e0 di lavorare da dove preferisci, sia in Italia che all\u2019interno della Comunit\u00e0 Europea.\nIl nostro sistema di TotalRewardinclude convenzioni esclusive per viaggi, ristoranti, shopping, palestra e tempo libero, oltre a servizi gratuiti di telemedicina e supporto psicologico, pensati per te e per chi ami.\nInvestire nel nostro processo di selezione significa ricevere supporto autentico: un Recruiter dedicato ti accompagner\u00e0 con feedback personalizzati, consigli di carriera e insight sul tuo CV, a prescindere dall\u2019esito della candidatura. Niente AI, solo persone. E, grazie all\u2019iniziativa Your Time Back, ti restituiamo il tempo investito nei colloqui con un percorso di empowerment firmato\u00a0Unobravo.\n\ud83c\udf31\nReady to start?\nIl ruolo \u00e8 solo il punto di partenza. Il resto lo metti tu. Inviaci il tuo CV, noi non vediamo l\u2019ora di conoscerti!\nBack\nApply\nShare this job:\nFacebook\nLinkedIn\nEmail",
        "application_url": "https://careers.jakala.com/en_US/careers/ApplicationMethods?jobId=1137",
        "": {},
        "metadata": {
            "Office": "Milano, Roma, Torino",
            "Country": "Italy",
            "Date Published": "08-Mar-2024",
            "Ref #": "1109",
            "Area": "IT and Information Systems",
            "Type of Presence": "Hybrid"
        },
        "link": "https://careers.jakala.com/en_US/careers/JobDetail/Experienced-Professional-Generative-AI-Developer-J-Science/1137"
    }
]